Workbook

Sheet Instrucciones
A1: Planilla de salario y liquidación Nicaragua 2026
A3: 1 | B3: Las celdas amarillas son para tus datos. Las verdes se calculan solas, con las fórmulas de la ley. A la derecha de cada hoja está el paso a paso de la cuenta.
A4: 2 | B4: «Salario neto»: ponés tu salario bruto y te dice el INSS, el IR que te retienen y tu salario neto.
A5: 3 | B5: «Aguinaldo»: calcula el aguinaldo de diciembre, completo o proporcional si dejaste el trabajo.
A6: 4 | B6: «Liquidación»: ponés tus fechas, tu salario y cómo terminó el contrato, y te dice la indemnización por antigüedad, el aguinaldo y las vacaciones.
A7: 5 | B7: «Tablas oficiales» tiene cada valor oficial que usan las fórmulas, con el enlace a su fuente y la fecha en que lo verificamos. Los valores son los vigentes al 13/10/2026.
A8: 6 | B8: Cuando cambia un valor oficial, actualizamos la planilla y el mismo enlace de descarga te baja la versión nueva.
A10: Da los mismos números que las calculadoras gratuitas de calcularya.com. Antes de publicar cada versión, una verificación automática recalcula este archivo y lo compara con ellas.
A11: Es una referencia de cálculo con sus fuentes, no asesoramiento legal. Tu contrato o tu empresa pueden darte más que el mínimo de ley.
A12: Las fechas van como dd/mm/aaaa. Si tu Excel está en inglés y las lee al revés, escribilas como aaaa-mm-dd.

Sheet Salario neto
A1: Salario neto: INSS e IR
E3: Paso a paso
A4: TUS DATOS | E4: Tasa del INSS | F4: =INDEX('Tablas oficiales'!$C$4:$C$5,MATCH(B6,'Tablas oficiales'!$B$4:$B$5,0))
A5: Salario bruto mensual | B5: 20000 | E5: INSS | F5: =ROUND(B5*F4/100,2)
A6: Régimen del INSS | B6: Régimen integral (con enfermedad y maternidad) | E6: Salario menos INSS | F6: =ROUND(B5-F5,2)
E7: Renta neta del año | F7: =ROUND(F6*12,2)
A8: TU SALARIO NETO | E8: IR del año | F8: =ROUND(IF(F7<=0,0,INDEX('Tablas oficiales'!$E$8:$E$12,IFERROR(MATCH(F7,'Tablas oficiales'!$B$8:$B$12,1),1))+(F7-INDEX('Tablas oficiales'!$B$8:$B$12,IFERROR(MATCH(F7,'Tablas oficiales'!$B$8:$B$12,1),1)))*INDEX('Tablas oficiales'!$D$8:$D$12,IFERROR(MATCH(F7,'Tablas oficiales'!$B$8:$B$12,1),1))/100),2)
A9: Tasa del INSS | B9: =F4 | E9: IR del mes | F9: =ROUND(F8/12,2)
A10: INSS | B10: =F5
A11: IR | B11: =F9
A12: Salario neto | B12: =ROUND(B5-F5-F9,2)
A14: DETALLE DEL IR
A15: INSS del mes | B15: =F5
A16: Renta neta del año | B16: =F7
A17: IR del año | B17: =F8
A18: IR del mes | B18: =F9
A19: Tasa del último tramo | B19: =IF(COUNTIF('Tablas oficiales'!$B$8:$B$12,"<"&F7)=0,0,INDEX('Tablas oficiales'!$D$8:$D$12,COUNTIF('Tablas oficiales'!$B$8:$B$12,"<"&F7)))
A20: Tasa efectiva sobre el salario | B20: =IF(B5>0,ROUND(F9/B5*100,2),0)
A22: El IR se retiene cada mes sobre el salario de todo el año. No incluye otros descuentos, como préstamos, cuota sindical o pensión de alimentos.

Sheet Aguinaldo
A1: Aguinaldo (décimo tercer mes)
E3: Paso a paso
A4: TUS DATOS | E4: Cierre del período | F4: =IF(B7="La parte que te toca porque dejaste el trabajo",B8,DATE(YEAR(B9),11,30))
A5: Salario mensual | B5: 15000 | C5: El último salario ordinario. Si ganás por comisión o a destajo, el más alto de los últimos seis meses. | E5: Días del período del aguinaldo | F5: =MIN(365,F4-MAX(B6,DATE(IF(MONTH(F4)=12,YEAR(F4),YEAR(F4)-1),12,1))+1)
A6: Fecha en que empezaste a trabajar | B6: 45352
A7: Qué querés calcular | B7: El aguinaldo de diciembre
A8: Último día de trabajo (opcional) | C8: Solo si dejaste el trabajo.
A9: Fecha de hoy | B9: =TODAY() | C9: Se llena sola. Define de qué año es el aguinaldo.
A11: TU AGUINALDO
A12: =IF(AND(B7="La parte que te toca porque dejaste el trabajo",NOT(ISNUMBER(B8))),"Poné tu último día de trabajo.",IF(B6>F4,"La fecha de ingreso no puede ser posterior al cierre del período.",""))
A13: Días que cuentan | B13: =F5
A14: Aguinaldo | B14: =ROUND(B5*'Tablas oficiales'!$C$14*F5/365,2)
A16: Va del 1 de diciembre al 30 de noviembre y se paga en los primeros diez días de diciembre. No paga INSS ni IR.

Sheet Liquidación
A1: Liquidación: indemnización por antigüedad, aguinaldo y vacaciones
E3: Paso a paso
A4: TUS DATOS | E4: Años cumplidos | F4: =IF(AND((YEAR(B6)-YEAR(B5))>0,DATE(YEAR(B5)+(YEAR(B6)-YEAR(B5)),MONTH(B5),MIN(DAY(B5),DAY(EOMONTH(DATE(YEAR(B5)+(YEAR(B6)-YEAR(B5)),MONTH(B5),1),0))))>B6),(YEAR(B6)-YEAR(B5))-1,(YEAR(B6)-YEAR(B5)))
A5: Fecha en que empezaste a trabajar | B5: 44348 | E5: Días del año en curso | F5: =MIN(365,B6-DATE(YEAR(B5)+F4,MONTH(B5),MIN(DAY(B5),DAY(EOMONTH(DATE(YEAR(B5)+F4,MONTH(B5),1),0))))+1)
A6: Último día de trabajo | B6: 46308 | E6: Antigüedad en años | F6: =IF(F5=365,F4+1,F4+F5/365)
A7: Cómo terminó el contrato | B7: Te despidieron sin causa justificada | E7: Meses de indemnización | F7: =IF(B7="Te despidieron por una causa del artículo 48",0,MIN('Tablas oficiales'!$C$17,IF(B7="Te despidieron sin causa justificada",MAX('Tablas oficiales'!$C$18,(MIN(F6,3)*'Tablas oficiales'!$C$15+MAX(0,F6-3)*'Tablas oficiales'!$C$16/30)),(MIN(F6,3)*'Tablas oficiales'!$C$15+MAX(0,F6-3)*'Tablas oficiales'!$C$16/30))))
A8: Salario mensual | B8: 15000 | C8: El último salario ordinario. Si varía, el promedio de los últimos seis meses. | E8: Indemnización por antigüedad | F8: =ROUND(B8*F7,2)
A9: Días de vacaciones que no gozaste (opcional) | C9: Si lo dejás vacío, se calculan los del último año, desde tu último aniversario. | E9: Días del período del aguinaldo | F9: =MIN(365,B6-MAX(B5,DATE(IF(MONTH(B6)=12,YEAR(B6),YEAR(B6)-1),12,1))+1)
E10: Aguinaldo proporcional | F10: =ROUND(B8*'Tablas oficiales'!$C$14*F9/365,2)
A11: TU LIQUIDACIÓN | E11: Días de vacaciones | F11: =ROUND(IF(ISNUMBER(B9),B9,'Tablas oficiales'!$C$19*2*F5/365),2)
A12: =IF(B5>B6,"La fecha de ingreso no puede ser posterior a la de salida.","") | E12: Vacaciones | F12: =ROUND(B8/30*F11,2)
A13: Antigüedad en años | B13: =ROUND(F6,2)
A14: Meses de salario de indemnización | B14: =ROUND(F7,2)
A15: Indemnización por antigüedad | B15: =F8
A16: Días del aguinaldo | B16: =F9
A17: Aguinaldo proporcional | B17: =F10
A18: Días de vacaciones | B18: =F11
A19: Vacaciones | B19: =F12
A20: Total | B20: =ROUND(F8+F10+F12,2)
A22: Al renunciar conservás lo ganado por antigüedad (art. 43), sin el mínimo de un mes. Con despido justificado no hay indemnización. Las vacaciones se pagan con el salario mensual entre 30.
A24: SOLO LA INDEMNIZACIÓN POR ANTIGÜEDAD
A25: Antigüedad en años | B25: =ROUND(F6,2)
A26: Meses de salario | B26: =ROUND(F7,2)
A27: Indemnización por antigüedad | B27: =F8
A29: Un mes de salario por cada uno de los tres primeros años y 20 días por año desde el cuarto, con un mínimo de un mes y un máximo de cinco. No paga IR.

Sheet Tablas oficiales
A1: Tablas oficiales de Nicaragua
A2: Son los valores que usan las fórmulas de esta planilla, vigentes al 13/10/2026. Cada uno trae el enlace a la norma o al organismo que lo publica y la fecha en que lo verificamos.
A3: Dato | B3: Detalle | C3: Valor | D3: Unidad | E3: Vigente desde | F3: Fuente oficial | G3: Verificado el
A4: Cotización del trabajador al INSS | B4: Régimen integral (con enfermedad y maternidad) | C4: 7 | D4: % | E4: 1/2/2019 | F4: https://digesto.asamblea.gob.ni/consultas/normas/shownorms.php?idnorm=MjQxNDk= | G4: 7/10/2026
A5: Cotización del trabajador al INSS | B5: Régimen de invalidez, vejez, muerte y riesgos profesionales | C5: 5 | D5: % | E5: 1/2/2019 | F5: https://digesto.asamblea.gob.ni/consultas/normas/shownorms.php?idnorm=MjQxNDk= | G5: 7/10/2026
A6: Tarifa progresiva anual del IR de rentas del trabajo | D6: NIO | E6: 1/1/2013 | F6: https://digesto.asamblea.gob.ni/consultas/normas/shownorms.php?idnorm=Mzc5 | G6: 7/10/2026
B7: Desde | C7: Hasta | D7: Tasa % | E7: Cuota fija
B8: 0 | C8: 100000 | D8: 0 | E8: 0
B9: 100000 | C9: 200000 | D9: 15 | E9: 0
B10: 200000 | C10: 350000 | D10: 20 | E10: 15000
B11: 350000 | C11: 500000 | D11: 25 | E11: 45000
B12: 500000 | C12: 1e+15 | D12: 30 | E12: 82500
A14: Décimo tercer mes: salarios por año trabajado | C14: 1 | D14: meses | E14: 29/12/1996 | F14: https://digesto.asamblea.gob.ni/consultas/normas/shownorms.php?idnorm=MTMzMDY= | G14: 7/10/2026
A15: Indemnización por antigüedad: meses de salario por cada uno de los tres primeros años | C15: 1 | D15: meses | E15: 29/12/1996 | F15: https://digesto.asamblea.gob.ni/consultas/normas/shownorms.php?idnorm=MTMzMDY= | G15: 7/10/2026
A16: Indemnización por antigüedad: días de salario por año desde el cuarto | C16: 20 | D16: días | E16: 29/12/1996 | F16: https://digesto.asamblea.gob.ni/consultas/normas/shownorms.php?idnorm=MTMzMDY= | G16: 7/10/2026
A17: Indemnización por antigüedad: máximo en meses de salario | C17: 5 | D17: meses | E17: 29/12/1996 | F17: https://digesto.asamblea.gob.ni/consultas/normas/shownorms.php?idnorm=MTMzMDY= | G17: 7/10/2026
A18: Indemnización por antigüedad: mínimo en meses de salario | C18: 1 | D18: meses | E18: 29/12/1996 | F18: https://digesto.asamblea.gob.ni/consultas/normas/shownorms.php?idnorm=MTMzMDY= | G18: 7/10/2026
A19: Días de vacaciones por cada seis meses de trabajo | C19: 15 | D19: días | E19: 29/12/1996 | F19: https://digesto.asamblea.gob.ni/consultas/normas/shownorms.php?idnorm=MTMzMDY= | G19: 7/10/2026
