Workbook

Sheet Instrucciones
A1: Planilla de sueldo y liquidación Ecuador 2026
A3: 1 | B3: Las celdas amarillas son para tus datos. Las verdes se calculan solas, con las fórmulas de la ley. A la derecha de cada hoja está el paso a paso de la cuenta.
A4: 2 | B4: «Sueldo neto»: pones tu sueldo y te dice el aporte al IESS, la retención del impuesto a la renta, los décimos mensualizados y lo que recibes.
A5: 3 | B5: «Décimos»: calcula el décimo tercero (hasta el 24 de diciembre) y el décimo cuarto de tu región, completos o proporcionales.
A6: 4 | B6: «Liquidación»: pones tus fechas, tu remuneración y cómo terminó la relación, y te dice el desahucio, la indemnización, los décimos pendientes y las vacaciones.
A7: 5 | B7: «Tablas oficiales» tiene cada valor oficial que usan las fórmulas, con el enlace a su fuente y la fecha en que lo verificamos. Los valores son los vigentes al 20/10/2026.
A8: 6 | B8: Cuando cambia un valor oficial, actualizamos la planilla y el mismo enlace de descarga te baja la versión nueva.
A10: Da los mismos números que las calculadoras gratuitas de calcularya.com. Antes de publicar cada versión, una verificación automática recalcula este archivo y lo compara con ellas.
A11: Es una referencia de cálculo con sus fuentes, no asesoría legal. Tu contrato o tu empresa pueden darte más que el mínimo de ley.
A12: Las fechas van como dd/mm/aaaa. Si tu Excel está en inglés y las lee al revés, escríbelas como aaaa-mm-dd.

Sheet Sueldo neto
A1: Sueldo neto: IESS, impuesto a la renta y décimos | Z1: Sin cargas familiares
Z2: 1 carga familiar
E3: Paso a paso | Z3: 2 cargas familiares
A4: TUS DATOS | Z4: 3 cargas familiares
A5: Sueldo mensual | B5: 1500 | C5: Tu remuneración del mes: sueldo, horas extra y comisiones. | E5: Aporte e impuesto a la renta | Z5: 4 cargas familiares
A6: Cobras los décimos cada mes | B6: Sí | E6: Aporte personal al IESS | F6: =ROUND(B5*'Tablas oficiales'!$C$10/100,2) | Z6: 5 o más cargas familiares
A7: Gastos personales proyectados para el año | B7: 0 | C7: Los que pusiste en tu proyección de gastos personales. Si no la presentaste, deja 0. | E7: Base imponible del año | F7: =ROUND((B5-F6)*12,2)
A8: Cargas familiares | B8: Sin cargas familiares | E8: Impuesto causado del año | F8: =ROUND(IF(F7<=0,0,INDEX('Tablas oficiales'!$E$13:$E$22,IFERROR(MATCH(F7,'Tablas oficiales'!$B$13:$B$22,1),1))+(F7-INDEX('Tablas oficiales'!$B$13:$B$22,IFERROR(MATCH(F7,'Tablas oficiales'!$B$13:$B$22,1),1)))*INDEX('Tablas oficiales'!$D$13:$D$22,IFERROR(MATCH(F7,'Tablas oficiales'!$B$13:$B$22,1),1))/100),2)
A9: Tú o una carga tienen discapacidad o una enfermedad catastrófica | B9: No | C9: También vale para enfermedades raras o huérfanas. | E9: Canastas que topan los gastos | F9: =IF(B9="Sí",'Tablas oficiales'!$C$24,INDEX('Tablas oficiales'!$C$4:$C$9,MATCH(B8,'Tablas oficiales'!$B$4:$B$9,0)))
E10: Tope de gastos personales | F10: =ROUND('Tablas oficiales'!$C$25*F9,2)
A11: TU ROL DE PAGOS | E11: Rebaja por gastos personales | F11: =MIN(ROUND(MIN(B7,F10)*'Tablas oficiales'!$C$26/100,2),F8)
A12: Sueldo | B12: =B5 | E12: Impuesto a la renta del año | F12: =ROUND(F8-F11,2)
A13: Aporte personal al IESS | B13: =F6 | E13: Retención mensual (de febrero a diciembre) | F13: =ROUND(F12/11,2)
A14: Retención del impuesto a la renta | B14: =F13 | E14: Décimo tercero mensual | F14: =IF(B6="Sí",ROUND(B5/12,2),0)
A15: Impuesto a la renta del año | B15: =F12 | E15: Décimo cuarto mensual | F15: =IF(B6="Sí",ROUND('Tablas oficiales'!$C$27/12,2),0)
A16: Décimo tercero mensual | B16: =F14
A17: Décimo cuarto mensual | B17: =F15
A18: Sueldo neto | B18: =ROUND(B5-F6-F13+F14+F15,2)
A20: En enero no te retienen impuesto a la renta, así que ese mes recibes un poco más. Si llevas más de un año con tu empleador, también te corresponde el fondo de reserva.

Sheet Décimos
A1: Décimo tercero y décimo cuarto | Z1: Costa y Galápagos
Z2: Sierra y Amazonía
E3: Paso a paso
A4: DÉCIMO TERCERO | E4: Total ganado en el período | F4: =B5*B6+B7
A5: Sueldo mensual | B5: 1000 | C5: Sin contar los décimos, las utilidades ni el fondo de reserva.
A6: Meses trabajados del 1 de diciembre al 30 de noviembre | B6: 12 | C6: Si trabajaste el período completo, deja 12. Puedes usar decimales. | E6: Décimo cuarto
A7: Horas extra, comisiones y bonos del período | B7: 0 | C7: La suma de todo el período. Si no tuviste, deja 0. | E7: Mes en que empieza el período | F7: =INDEX('Tablas oficiales'!$C$28:$C$29,MATCH(B15,'Tablas oficiales'!$B$28:$B$29,0))
A8: Total ganado en el período | B8: =ROUND(F4,2) | E8: Fecha de corte | F8: =IF(NOT(ISNUMBER(B17)),B18,B17)
A9: Décimo tercero mensual | B9: =ROUND(B5/12,2) | E9: Período que contiene el corte | F9: =DATE(IF(MONTH(F8)>=F7,YEAR(F8),YEAR(F8)-1),F7,1)
A10: Décimo tercero acumulado | B10: =ROUND(F4/12,2) | E10: Inicio del período que se paga | F10: =IF(AND(NOT(ISNUMBER(B17)),B18<=DATE(YEAR(F9),F7,15)),EDATE(F9,-12),F9)
E11: Fin del período que se paga | F11: =EDATE(F10,12)-1
A12: Si lo cobras cada mes en tu rol de pagos, ya lo recibiste. Este cálculo es para quien lo cobra acumulado. | E12: Último día que cuenta | F12: =IF(NOT(ISNUMBER(B17)),F11,F8)
E13: Período: años completos | F13: =IF(EDATE(MAX(B16,F10),12*(YEAR((F12+1))-YEAR(MAX(B16,F10))))>(F12+1),(YEAR((F12+1))-YEAR(MAX(B16,F10)))-1,(YEAR((F12+1))-YEAR(MAX(B16,F10))))
A14: DÉCIMO CUARTO | E14: Período: último aniversario | F14: =EDATE(MAX(B16,F10),12*F13)
A15: Región donde trabajas | B15: Sierra y Amazonía | E15: Período: meses | F15: =MIN(12,IF(EDATE(F14,((YEAR((F12+1))-YEAR(F14))*12+MONTH((F12+1))-MONTH(F14)))>(F12+1),((YEAR((F12+1))-YEAR(F14))*12+MONTH((F12+1))-MONTH(F14))-1,((YEAR((F12+1))-YEAR(F14))*12+MONTH((F12+1))-MONTH(F14))))
A16: Fecha en que empezaste a trabajar | B16: 45672 | E16: Período: días | F16: =(F12+1)-EDATE(F14,F15)
A17: Fecha de salida (opcional) | C17: Déjala vacía si sigues trabajando: se calcula el próximo pago. | E17: Período: meses trabajados | F17: =MIN(12,F13*12+F15+F16/30)
A18: Fecha de hoy | B18: =TODAY() | C18: Se llena sola. Cámbiala si quieres calcular a otra fecha.
A19: =IF(B16>F11,"Empezaste a trabajar después de este período.",IF(B16>F8,"La fecha en que empezaste no puede ser posterior al corte.",""))
A20: Período | B20: ="Del "&DAY(F10)&"/"&MONTH(F10)&"/"&YEAR(F10)&" al "&DAY(F11)&"/"&MONTH(F11)&"/"&YEAR(F11)
A21: Meses trabajados en el período | B21: =ROUND(F17,2)
A22: Décimo cuarto mensual | B22: =ROUND('Tablas oficiales'!$C$27/12,2)
A23: Décimo cuarto | B23: =ROUND('Tablas oficiales'!$C$27*F17/12,2)
A25: Es un salario básico por año. En la Sierra y la Amazonía se paga hasta el 15 de agosto; en la Costa y Galápagos, hasta el 15 de marzo.

Sheet Liquidación
A1: Liquidación: desahucio, despido, décimos y vacaciones | Z1: Costa y Galápagos
Z2: Sierra y Amazonía
E3: Paso a paso
A4: TUS DATOS | E4: Tiempo de servicio: años completos | F4: =IF(EDATE(B5,12*(YEAR((B6+1))-YEAR(B5)))>(B6+1),(YEAR((B6+1))-YEAR(B5))-1,(YEAR((B6+1))-YEAR(B5)))
A5: Fecha en que empezaste a trabajar | B5: 44621 | E5: Tiempo de servicio: último aniversario | F5: =EDATE(B5,12*F4)
A6: Último día de trabajo | B6: 46315 | E6: Tiempo de servicio: meses | F6: =MIN(12,IF(EDATE(F5,((YEAR((B6+1))-YEAR(F5))*12+MONTH((B6+1))-MONTH(F5)))>(B6+1),((YEAR((B6+1))-YEAR(F5))*12+MONTH((B6+1))-MONTH(F5))-1,((YEAR((B6+1))-YEAR(F5))*12+MONTH((B6+1))-MONTH(F5))))
A7: Última remuneración mensual | B7: 900 | C7: Sueldo más horas extra y comisiones habituales. Sin décimos, utilidades ni fondo de reserva. | E7: Tiempo de servicio: días | F7: =(B6+1)-EDATE(F5,F6)
A8: Cómo terminó la relación laboral | B8: Despido intempestivo (sin causa)
A9: Región donde trabajabas | B9: Sierra y Amazonía | E9: Desahucio e indemnización
A10: Cobrabas los décimos cada mes | B10: Sí | E10: Bonificación por desahucio | F10: =IF(B8<>"Visto bueno pedido por el empleador",ROUND(B7*'Tablas oficiales'!$C$30/100*F4,2),0)
A11: Días de vacaciones de años anteriores sin tomar | B11: 0 | E11: Meses de indemnización | F11: =IF(B8="Despido intempestivo (sin causa)",IF(OR(F4<'Tablas oficiales'!$C$31,AND(F4='Tablas oficiales'!$C$31,NOT(OR(F6>0,F7>0)))),'Tablas oficiales'!$C$32,MIN(F4+IF(OR(F6>0,F7>0),1,0),'Tablas oficiales'!$C$33)),0)
E12: Indemnización por despido | F12: =ROUND(B7*F11,2)
A13: TU LIQUIDACIÓN
A14: =IF(B6<B5,"El último día tiene que ser posterior a la fecha en que empezaste.","") | E14: Décimos pendientes
A15: Tiempo de servicio | B15: =F4&" años, "&F6&" meses y "&F7&" días" | E15: Décimo tercero: años completos | F15: =IF(EDATE(MAX(B5,DATE(IF(MONTH(B6)>=12,YEAR(B6),YEAR(B6)-1),12,1)),12*(YEAR((B6+1))-YEAR(MAX(B5,DATE(IF(MONTH(B6)>=12,YEAR(B6),YEAR(B6)-1),12,1)))))>(B6+1),(YEAR((B6+1))-YEAR(MAX(B5,DATE(IF(MONTH(B6)>=12,YEAR(B6),YEAR(B6)-1),12,1))))-1,(YEAR((B6+1))-YEAR(MAX(B5,DATE(IF(MONTH(B6)>=12,YEAR(B6),YEAR(B6)-1),12,1)))))
A16: Bonificación por desahucio | B16: =F10 | E16: Décimo tercero: último aniversario | F16: =EDATE(MAX(B5,DATE(IF(MONTH(B6)>=12,YEAR(B6),YEAR(B6)-1),12,1)),12*F15)
A17: Meses de indemnización por despido | B17: =F11 | E17: Décimo tercero: meses | F17: =MIN(12,IF(EDATE(F16,((YEAR((B6+1))-YEAR(F16))*12+MONTH((B6+1))-MONTH(F16)))>(B6+1),((YEAR((B6+1))-YEAR(F16))*12+MONTH((B6+1))-MONTH(F16))-1,((YEAR((B6+1))-YEAR(F16))*12+MONTH((B6+1))-MONTH(F16))))
A18: Indemnización por despido intempestivo | B18: =F12 | E18: Décimo tercero: días | F18: =(B6+1)-EDATE(F16,F17)
A19: Décimo tercero proporcional | B19: =F25 | E19: Décimo tercero: meses trabajados | F19: =MIN(12,F15*12+F17+F18/30)
A20: Décimo cuarto proporcional | B20: =F26 | E20: Décimo cuarto: años completos | F20: =IF(EDATE(MAX(B5,DATE(IF(MONTH(B6)>=INDEX('Tablas oficiales'!$C$28:$C$29,MATCH(B9,'Tablas oficiales'!$B$28:$B$29,0)),YEAR(B6),YEAR(B6)-1),INDEX('Tablas oficiales'!$C$28:$C$29,MATCH(B9,'Tablas oficiales'!$B$28:$B$29,0)),1)),12*(YEAR((B6+1))-YEAR(MAX(B5,DATE(IF(MONTH(B6)>=INDEX('Tablas oficiales'!$C$28:$C$29,MATCH(B9,'Tablas oficiales'!$B$28:$B$29,0)),YEAR(B6),YEAR(B6)-1),INDEX('Tablas oficiales'!$C$28:$C$29,MATCH(B9,'Tablas oficiales'!$B$28:$B$29,0)),1)))))>(B6+1),(YEAR((B6+1))-YEAR(MAX(B5,DATE(IF(MONTH(B6)>=INDEX('Tablas oficiales'!$C$28:$C$29,MATCH(B9,'Tablas oficiales'!$B$28:$B$29,0)),YEAR(B6),YEAR(B6)-1),INDEX('Tablas oficiales'!$C$28:$C$29,MATCH(B9,'Tablas oficiales'!$B$28:$B$29,0)),1))))-1,(YEAR((B6+1))-YEAR(MAX(B5,DATE(IF(MONTH(B6)>=INDEX('Tablas oficiales'!$C$28:$C$29,MATCH(B9,'Tablas oficiales'!$B$28:$B$29,0)),YEAR(B6),YEAR(B6)-1),INDEX('Tablas oficiales'!$C$28:$C$29,MATCH(B9,'Tablas oficiales'!$B$28:$B$29,0)),1)))))
A21: Vacaciones proporcionales y pendientes | B21: =F31 | E21: Décimo cuarto: último aniversario | F21: =EDATE(MAX(B5,DATE(IF(MONTH(B6)>=INDEX('Tablas oficiales'!$C$28:$C$29,MATCH(B9,'Tablas oficiales'!$B$28:$B$29,0)),YEAR(B6),YEAR(B6)-1),INDEX('Tablas oficiales'!$C$28:$C$29,MATCH(B9,'Tablas oficiales'!$B$28:$B$29,0)),1)),12*F20)
A22: Total de la liquidación | B22: =ROUND(F10+F12+F25+F26+F31,2) | E22: Décimo cuarto: meses | F22: =MIN(12,IF(EDATE(F21,((YEAR((B6+1))-YEAR(F21))*12+MONTH((B6+1))-MONTH(F21)))>(B6+1),((YEAR((B6+1))-YEAR(F21))*12+MONTH((B6+1))-MONTH(F21))-1,((YEAR((B6+1))-YEAR(F21))*12+MONTH((B6+1))-MONTH(F21))))
E23: Décimo cuarto: días | F23: =(B6+1)-EDATE(F21,F22)
A24: El fondo de reserva no entra: si lo cobrabas cada mes ya lo recibiste, y si estaba en el IESS lo retiras allí. Para el despido se usa la última remuneración. | E24: Décimo cuarto: meses trabajados | F24: =MIN(12,F20*12+F22+F23/30)
E25: Décimo tercero proporcional | F25: =IF(B10="Sí",0,ROUND(B7*F19/12,2))
E26: Décimo cuarto proporcional | F26: =IF(B10="Sí",0,ROUND('Tablas oficiales'!$C$27*F24/12,2))
E28: Vacaciones
E29: Días de vacaciones del año en curso | F29: ='Tablas oficiales'!$C$34+MIN(MAX(F4+1-'Tablas oficiales'!$C$35,0),'Tablas oficiales'!$C$36)
E30: Días proporcionales | F30: =F29*((F6+F7/30)/12)
E31: Vacaciones | F31: =ROUND(F30*B7/30+B11*B7/30,2)

Sheet Tablas oficiales
A1: Tablas oficiales de Ecuador
A2: Son los valores que usan las fórmulas de esta planilla, vigentes al 20/10/2026. Cada uno trae el enlace a la norma o al organismo que lo publica y la fecha en que lo verificamos.
A3: Dato | B3: Detalle | C3: Valor | D3: Unidad | E3: Vigente desde | F3: Fuente oficial | G3: Verificado el
A4: Canastas básicas que topan los gastos personales, según las cargas familiares | B4: Sin cargas familiares | C4: 7 | E4: 20/6/2023 | F4: https://www.sri.gob.ec/o/sri-portlet-biblioteca-alfresco-internet/descargar/de132165-dc5e-4267-a8a8-b9368be697f9/Ley_Organica_Fortalecimiento_Econ_Familiar_20_jun_2023.pdf | G4: 7/10/2026
A5: Canastas básicas que topan los gastos personales, según las cargas familiares | B5: 1 carga familiar | C5: 9 | E5: 20/6/2023 | F5: https://www.sri.gob.ec/o/sri-portlet-biblioteca-alfresco-internet/descargar/de132165-dc5e-4267-a8a8-b9368be697f9/Ley_Organica_Fortalecimiento_Econ_Familiar_20_jun_2023.pdf | G5: 7/10/2026
A6: Canastas básicas que topan los gastos personales, según las cargas familiares | B6: 2 cargas familiares | C6: 11 | E6: 20/6/2023 | F6: https://www.sri.gob.ec/o/sri-portlet-biblioteca-alfresco-internet/descargar/de132165-dc5e-4267-a8a8-b9368be697f9/Ley_Organica_Fortalecimiento_Econ_Familiar_20_jun_2023.pdf | G6: 7/10/2026
A7: Canastas básicas que topan los gastos personales, según las cargas familiares | B7: 3 cargas familiares | C7: 14 | E7: 20/6/2023 | F7: https://www.sri.gob.ec/o/sri-portlet-biblioteca-alfresco-internet/descargar/de132165-dc5e-4267-a8a8-b9368be697f9/Ley_Organica_Fortalecimiento_Econ_Familiar_20_jun_2023.pdf | G7: 7/10/2026
A8: Canastas básicas que topan los gastos personales, según las cargas familiares | B8: 4 cargas familiares | C8: 17 | E8: 20/6/2023 | F8: https://www.sri.gob.ec/o/sri-portlet-biblioteca-alfresco-internet/descargar/de132165-dc5e-4267-a8a8-b9368be697f9/Ley_Organica_Fortalecimiento_Econ_Familiar_20_jun_2023.pdf | G8: 7/10/2026
A9: Canastas básicas que topan los gastos personales, según las cargas familiares | B9: 5 o más cargas familiares | C9: 20 | E9: 20/6/2023 | F9: https://www.sri.gob.ec/o/sri-portlet-biblioteca-alfresco-internet/descargar/de132165-dc5e-4267-a8a8-b9368be697f9/Ley_Organica_Fortalecimiento_Econ_Familiar_20_jun_2023.pdf | G9: 7/10/2026
A10: Aporte personal al IESS (sector privado, relación de dependencia) | C10: 9.45 | D10: % | E10: 1/1/2026 | F10: https://www.iess.gob.ec/documents/13718/54965/Tasasdeaportacion.pdf | G10: 7/10/2026
A11: Tabla del impuesto a la renta de personas naturales (anual) | D11: USD | E11: 1/1/2026 | F11: https://www.sri.gob.ec/o/sri-portlet-biblioteca-alfresco-internet/descargar/58a7f4f6-ab51-48b6-b9ff-a8e97e1a28ef/Tablas%20de%20c%c3%a1lculo%20de%20Impuesto%20a%20la%20Renta.pdf | G11: 7/10/2026
B12: Desde | C12: Hasta | D12: Tasa % | E12: Cuota fija
B13: 0 | C13: 12208 | D13: 0 | E13: 0
B14: 12208 | C14: 15549 | D14: 5 | E14: 0
B15: 15549 | C15: 20188 | D15: 10 | E15: 167
B16: 20188 | C16: 26700 | D16: 12 | E16: 631
B17: 26700 | C17: 35136 | D17: 15 | E17: 1412
B18: 35136 | C18: 46575 | D18: 20 | E18: 2678
B19: 46575 | C19: 62005 | D19: 25 | E19: 4965
B20: 62005 | C20: 82679 | D20: 30 | E20: 8823
B21: 82679 | C21: 109956 | D21: 35 | E21: 15025
B22: 109956 | C22: 1e+15 | D22: 37 | E22: 24572
A24: Canastas básicas que topan los gastos personales con discapacidad o enfermedad catastrófica, rara o huérfana | C24: 100 | E24: 20/12/2023 | F24: https://www.sri.gob.ec/o/sri-portlet-biblioteca-alfresco-internet/descargar/67a341b5-cb7d-4de3-bd9b-b1f0a25b603d/Ley%20de%20R%c3%a9gimen%20Tributario%20Interno.pdf | G24: 7/10/2026
A25: Canasta familiar básica de enero (para la rebaja por gastos personales) | C25: 821.8 | D25: USD | E25: 1/1/2026 | F25: https://www.ecuadorencifras.gob.ec/documentos/web-inec/Inflacion/2026/enero/BOLETIN_TECNICO_IPC_2026_01.pdf | G25: 7/10/2026
A26: Rebaja del impuesto a la renta por gastos personales | C26: 18 | D26: % | E26: 20/6/2023 | F26: https://www.sri.gob.ec/o/sri-portlet-biblioteca-alfresco-internet/descargar/67a341b5-cb7d-4de3-bd9b-b1f0a25b603d/Ley%20de%20R%c3%a9gimen%20Tributario%20Interno.pdf | G26: 7/10/2026
A27: Salario básico unificado (SBU) | C27: 482 | D27: USD | E27: 1/1/2026 | F27: https://www.iess.gob.ec/aplicaciones/AfiliacionIESS/ | G27: 7/10/2026
A28: Mes en que empieza el período del décimo cuarto (y en cuyo día 15 vence el pago) | B28: Costa y Galápagos | C28: 3 | E28: 6/5/2015 | F28: https://www.goberguayas.gob.ec/pdf/LOTAIP/Leyes/7-Acuerdo-MDT.pdf | G28: 7/10/2026
A29: Mes en que empieza el período del décimo cuarto (y en cuyo día 15 vence el pago) | B29: Sierra y Amazonía | C29: 8 | E29: 6/5/2015 | F29: https://www.goberguayas.gob.ec/pdf/LOTAIP/Leyes/7-Acuerdo-MDT.pdf | G29: 7/10/2026
A30: Bonificación por desahucio, por cada año de servicio | C30: 25 | D30: % | E30: 20/4/2015 | F30: https://portal.compraspublicas.gob.ec/sercop/wp-content/uploads/2026/08/CODIGO-DEL-TRABAJO.pdf | G30: 7/10/2026
A31: Años de servicio que cubre la indemnización mínima por despido intempestivo | C31: 3 | D31: años | E31: 16/12/2005 | F31: https://portal.compraspublicas.gob.ec/sercop/wp-content/uploads/2026/08/CODIGO-DEL-TRABAJO.pdf | G31: 7/10/2026
A32: Meses de remuneración por despido intempestivo con hasta tres años de servicio | C32: 3 | D32: meses | E32: 16/12/2005 | F32: https://portal.compraspublicas.gob.ec/sercop/wp-content/uploads/2026/08/CODIGO-DEL-TRABAJO.pdf | G32: 7/10/2026
A33: Tope de la indemnización por despido intempestivo | C33: 25 | D33: meses | E33: 16/12/2005 | F33: https://portal.compraspublicas.gob.ec/sercop/wp-content/uploads/2026/08/CODIGO-DEL-TRABAJO.pdf | G33: 7/10/2026
A34: Días de vacaciones por año | C34: 15 | D34: días | E34: 16/12/2005 | F34: https://portal.compraspublicas.gob.ec/sercop/wp-content/uploads/2026/08/CODIGO-DEL-TRABAJO.pdf | G34: 7/10/2026
A35: Años de servicio después de los cuales se suma un día de vacaciones por año | C35: 5 | D35: años | E35: 16/12/2005 | F35: https://portal.compraspublicas.gob.ec/sercop/wp-content/uploads/2026/08/CODIGO-DEL-TRABAJO.pdf | G35: 7/10/2026
A36: Máximo de días adicionales de vacaciones por antigüedad | C36: 15 | D36: días | E36: 16/12/2005 | F36: https://portal.compraspublicas.gob.ec/sercop/wp-content/uploads/2026/08/CODIGO-DEL-TRABAJO.pdf | G36: 7/10/2026
