Workbook

Sheet Instrucciones
A1: Planilla de sueldo y liquidación Perú 2026
A3: 1 | B3: Las celdas amarillas son para tus datos. Las verdes se calculan solas, con las fórmulas de la ley. A la derecha de cada hoja está el paso a paso de la cuenta.
A4: 2 | B4: «Sueldo neto»: pones tu sueldo y te dice el descuento de pensión (AFP u ONP), la retención de quinta categoría y tu sueldo neto.
A5: 3 | B5: «Gratificación y CTS»: calcula la gratificación con su bonificación extraordinaria y el depósito de CTS de mayo o noviembre.
A6: 4 | B6: «Liquidación»: pones tus fechas y tu sueldo, y te dice la CTS trunca, la gratificación trunca, las vacaciones y, si te despidieron sin causa, la indemnización.
A7: 5 | B7: «Tablas oficiales» tiene cada valor oficial que usan las fórmulas, con el enlace a su fuente y la fecha en que lo verificamos. Los valores son los vigentes al 8/10/2026.
A8: 6 | B8: Cuando cambia un valor oficial, actualizamos la planilla y el mismo enlace de descarga te baja la versión nueva.
A10: Da los mismos números que las calculadoras gratuitas de calcularya.com. Antes de publicar cada versión, una verificación automática recalcula este archivo y lo compara con ellas.
A11: Es una referencia de cálculo con sus fuentes, no asesoría legal. Tu contrato o tu empresa pueden darte más que el mínimo de ley.
A12: Las fechas van como dd/mm/aaaa. Si tu Excel está en inglés y las lee al revés, escríbelas como aaaa-mm-dd.

Sheet Sueldo neto
A1: Sueldo neto: AFP u ONP y renta de quinta
E3: Paso a paso
A4: TUS DATOS
A5: Sueldo mensual bruto | B5: 3000 | E5: Pensión
A6: Cobras asignación familiar | B6: No | E6: Asignación familiar | F6: =IF(B6="Sí",ROUND('Tablas oficiales'!$C$11*'Tablas oficiales'!$C$12/100,2),0)
A7: Sistema de pensiones | B7: AFP (sistema privado) | E7: Sueldo bruto | F7: =ROUND(B5+F6,2)
A8: Tu AFP | B8: AFP Habitat | E8: Aporte a la ONP | F8: =IF(B7="AFP (sistema privado)",0,ROUND(F7*'Tablas oficiales'!$C$13/100,2))
A9: Tipo de comisión de tu AFP | B9: Sobre el saldo (mixta) | C9: Si entraste a la AFP desde 2013 o no elegiste nada, tienes comisión sobre el saldo. | E9: Aporte al fondo AFP | F9: =IF(B7="AFP (sistema privado)",ROUND(F7*'Tablas oficiales'!$C$14/100,2),0)
A10: Gratificaciones de julio y diciembre | B10: Sí: un sueldo cada una | C10: Medio sueldo es lo que paga la pequeña empresa del régimen especial. | E10: Prima de seguro AFP | F10: =IF(B7="AFP (sistema privado)",ROUND(MIN(F7,'Tablas oficiales'!$C$15)*'Tablas oficiales'!$C$16/100,2),0)
A11: Tu seguro de salud | B11: EsSalud | E11: Comisión sobre el sueldo (%) | F11: =IF(B9="Sobre el sueldo (flujo)",INDEX('Tablas oficiales'!$C$4:$C$7,MATCH(B8,'Tablas oficiales'!$B$4:$B$7,0)),'Tablas oficiales'!$C$17)
E12: Comisión de la AFP | F12: =IF(B7="AFP (sistema privado)",ROUND(F7*F11/100,2),0)
A13: TU SUELDO NETO | E13: Total de pensión | F13: =ROUND(F8+F9+F10+F12,2)
A14: Sueldo bruto | B14: =F7
A15: Aporte a la ONP | B15: =F8 | E15: Renta de quinta categoría
A16: Aporte a tu fondo AFP | B16: =F9 | E16: Gratificaciones del año | F16: =ROUND(F7*IF(B10="Sí: un sueldo cada una",2,IF(B10="Sí: medio sueldo cada una",1,0)),2)
A17: Prima de seguro AFP | B17: =F10 | E17: Bonificación extraordinaria del año | F17: =ROUND(F16*INDEX('Tablas oficiales'!$C$8:$C$9,MATCH(B11,'Tablas oficiales'!$B$8:$B$9,0))/100,2)
A18: Comisión de la AFP | B18: =F12 | E18: Ingreso del año | F18: =ROUND(F7*12+F16+F17,2)
A19: Total de descuento de pensión | B19: =F13 | E19: Renta neta (menos 7 UIT) | F19: =MAX(0,ROUND(F18-'Tablas oficiales'!$C$18*'Tablas oficiales'!$C$10,2))
A20: Retención de quinta categoría | B20: =F26 | E20: Impuesto anual: tramo 1 | F20: =MAX(0,MIN(F19,'Tablas oficiales'!$C$21*'Tablas oficiales'!$C$10)-'Tablas oficiales'!$B$21*'Tablas oficiales'!$C$10)*'Tablas oficiales'!$D$21/100
A21: Sueldo neto | B21: =ROUND(F7-F13-F26,2) | E21: Impuesto anual: tramo 2 | F21: =MAX(0,MIN(F19,'Tablas oficiales'!$C$22*'Tablas oficiales'!$C$10)-'Tablas oficiales'!$B$22*'Tablas oficiales'!$C$10)*'Tablas oficiales'!$D$22/100
E22: Impuesto anual: tramo 3 | F22: =MAX(0,MIN(F19,'Tablas oficiales'!$C$23*'Tablas oficiales'!$C$10)-'Tablas oficiales'!$B$23*'Tablas oficiales'!$C$10)*'Tablas oficiales'!$D$23/100
A23: La retención de quinta es un promedio mensual: la empresa la ajusta en el año si cambian tus ingresos. Con comisión sobre el saldo, la AFP no te descuenta comisión del sueldo. | E23: Impuesto anual: tramo 4 | F23: =MAX(0,MIN(F19,'Tablas oficiales'!$C$24*'Tablas oficiales'!$C$10)-'Tablas oficiales'!$B$24*'Tablas oficiales'!$C$10)*'Tablas oficiales'!$D$24/100
E24: Impuesto anual: tramo 5 | F24: =MAX(0,MIN(F19,'Tablas oficiales'!$C$25*'Tablas oficiales'!$C$10)-'Tablas oficiales'!$B$25*'Tablas oficiales'!$C$10)*'Tablas oficiales'!$D$25/100
E25: Impuesto anual: total | F25: =SUM(F20,F21,F22,F23,F24)
E26: Retención de quinta del mes | F26: =ROUND(ROUND(F25,2)/12,2)

Sheet Gratificación y CTS
A1: Gratificación de julio y diciembre, y depósito de CTS
E3: Paso a paso
A4: TUS DATOS | E4: Asignación familiar | F4: =IF(B6="Sí",ROUND('Tablas oficiales'!$C$11*'Tablas oficiales'!$C$12/100,2),0)
A5: Sueldo mensual | B5: 3000 | C5: Tu remuneración básica, sin descuentos.
A6: Cobras asignación familiar | B6: No | E6: Gratificación
A7: Promedio mensual de pagos variables (opcional) | C7: Comisiones, horas extras u otros pagos que recibiste al menos 3 meses del semestre. Déjalo vacío si no tienes. | E7: Remuneración computable de la gratificación | F7: =ROUND(B5+F4+IF(ISNUMBER(B7),B7,0),2)
A8: Régimen laboral de tu empleador | B8: Régimen general | E8: Gratificación | F8: =IF(B8="Microempresa (REMYPE)",0,ROUND(F7*IF(B8="Régimen general",'Tablas oficiales'!$C$27,IF(B8="Pequeña empresa (REMYPE)",'Tablas oficiales'!$C$28,0))*B11/6,2))
E9: Bonificación extraordinaria | F9: =IF(B8="Microempresa (REMYPE)",0,ROUND(F8*INDEX('Tablas oficiales'!$C$8:$C$9,MATCH(B12,'Tablas oficiales'!$B$8:$B$9,0))/100,2))
A10: GRATIFICACIÓN
A11: Meses completos trabajados en el semestre | B11: 6 | E11: CTS
A12: Tu seguro de salud | B12: EsSalud | E12: Sexto de la gratificación | F12: =ROUND(IF(ISNUMBER(B22),B22,0)/6,2)
A13: Remuneración que se usa para el cálculo | B13: =F7 | E13: Remuneración computable de la CTS | F13: =ROUND(B5+F4+IF(ISNUMBER(B7),B7,0)+F12,2)
A14: Asignación familiar incluida | B14: =F4 | E14: CTS por los meses | F14: =IF(B8="Microempresa (REMYPE)",0,ROUND(F13*IF(B8="Régimen general",'Tablas oficiales'!$C$29,IF(B8="Pequeña empresa (REMYPE)",'Tablas oficiales'!$C$30,0))/12*B23,2))
A15: Gratificación | B15: =F8 | E15: CTS por los días | F15: =IF(B8="Microempresa (REMYPE)",0,ROUND(F13*IF(B8="Régimen general",'Tablas oficiales'!$C$29,IF(B8="Pequeña empresa (REMYPE)",'Tablas oficiales'!$C$30,0))/360*B24,2))
A16: Bonificación extraordinaria | B16: =F9
A17: Total a cobrar | B17: =ROUND(F8+F9,2)
A19: Se paga en la primera quincena de julio y de diciembre. En la microempresa del régimen especial no se paga gratificación.
A21: CTS
A22: Gratificación que cobraste en el semestre (opcional) | C22: La de diciembre para el depósito de mayo y la de julio para el de noviembre, sin la bonificación. Se suma un sexto.
A23: Meses completos trabajados en el semestre de la CTS | B23: 6
A24: Días sueltos, además de los meses | B24: 0
A25: Remuneración computable | B25: =F13
A26: Sexto de la gratificación incluido | B26: =F12
A27: Por los meses completos | B27: =F14
A28: Por los días sueltos | B28: =F15
A29: Depósito de CTS | B29: =ROUND(F14+F15,2)
A31: Se deposita en la cuenta CTS en los primeros 15 días de mayo y de noviembre. En la microempresa del régimen especial no hay CTS.

Sheet Liquidación
A1: Liquidación de beneficios sociales e indemnización
E3: Paso a paso
A4: TUS DATOS | E4: Asignación familiar | F4: =IF(B8="Sí",ROUND('Tablas oficiales'!$C$11*'Tablas oficiales'!$C$12/100,2),0)
A5: Fecha de ingreso | B5: 44986 | E5: Remuneración computable | F5: =ROUND(B7+F4+IF(ISNUMBER(B9),B9,0),2)
A6: Último día de trabajo | B6: 46303
A7: Último sueldo mensual | B7: 3000 | E7: Tiempo de servicio
A8: Cobras asignación familiar | B8: No | E8: Servicio: meses de servicio | F8: =IF(B6<B5,0,(YEAR((B6+1))-YEAR(B5))*12+MONTH((B6+1))-MONTH(B5)-IF(DAY((B6+1))<DAY(B5),1,0))
A9: Promedio mensual de pagos variables (opcional) | C9: Comisiones, horas extras u otros pagos regulares. Déjalo vacío si no tienes. | E9: Servicio: años | F9: =INT(F8/12)
A10: Régimen laboral de tu empleador | B10: Régimen general | E10: Servicio: meses | F10: =MOD(F8,12)
A11: Última gratificación que cobraste (opcional) | C11: Sin la bonificación extraordinaria. Un sexto se suma a la CTS trunca. | E11: Servicio: días | F11: =IF(B6<B5,0,MIN((B6+1)-DATE(YEAR(DATE(YEAR(B5),MONTH(B5)+F8,1)),MONTH(DATE(YEAR(B5),MONTH(B5)+F8,1)),MIN(DAY(B5),DAY(EOMONTH(DATE(YEAR(B5),MONTH(B5)+F8,1),0)))),29))
A12: Días de vacaciones ganadas que no tomaste | B12: 0
A13: Tu seguro de salud | B13: EsSalud | E13: CTS trunca
E14: CTS: días sueltos de las puntas | F14: =IF(DAY(MAX(B5,IF(MONTH(B6)>=11,DATE(YEAR(B6),11,1),IF(MONTH(B6)>=5,DATE(YEAR(B6),5,1),DATE(YEAR(B6)-1,11,1)))))=1,0,DAY(EOMONTH(MAX(B5,IF(MONTH(B6)>=11,DATE(YEAR(B6),11,1),IF(MONTH(B6)>=5,DATE(YEAR(B6),5,1),DATE(YEAR(B6)-1,11,1)))),0))-DAY(MAX(B5,IF(MONTH(B6)>=11,DATE(YEAR(B6),11,1),IF(MONTH(B6)>=5,DATE(YEAR(B6),5,1),DATE(YEAR(B6)-1,11,1)))))+1)+IF(DAY(B6)=DAY(EOMONTH(B6,0)),0,DAY(B6))
A15: TU LIQUIDACIÓN | E15: CTS: meses | F15: =IF(B6<MAX(B5,IF(MONTH(B6)>=11,DATE(YEAR(B6),11,1),IF(MONTH(B6)>=5,DATE(YEAR(B6),5,1),DATE(YEAR(B6)-1,11,1)))),0,IF(AND(YEAR(MAX(B5,IF(MONTH(B6)>=11,DATE(YEAR(B6),11,1),IF(MONTH(B6)>=5,DATE(YEAR(B6),5,1),DATE(YEAR(B6)-1,11,1)))))=YEAR(B6),MONTH(MAX(B5,IF(MONTH(B6)>=11,DATE(YEAR(B6),11,1),IF(MONTH(B6)>=5,DATE(YEAR(B6),5,1),DATE(YEAR(B6)-1,11,1)))))=MONTH(B6)),IF(AND(DAY(MAX(B5,IF(MONTH(B6)>=11,DATE(YEAR(B6),11,1),IF(MONTH(B6)>=5,DATE(YEAR(B6),5,1),DATE(YEAR(B6)-1,11,1)))))=1,DAY(B6)=DAY(EOMONTH(B6,0))),1,0),IF(DAY(MAX(B5,IF(MONTH(B6)>=11,DATE(YEAR(B6),11,1),IF(MONTH(B6)>=5,DATE(YEAR(B6),5,1),DATE(YEAR(B6)-1,11,1)))))=1,1,0)+IF(DAY(B6)=DAY(EOMONTH(B6,0)),1,0)+MAX(0,(YEAR(B6)*12+MONTH(B6))-(YEAR(MAX(B5,IF(MONTH(B6)>=11,DATE(YEAR(B6),11,1),IF(MONTH(B6)>=5,DATE(YEAR(B6),5,1),DATE(YEAR(B6)-1,11,1)))))*12+MONTH(MAX(B5,IF(MONTH(B6)>=11,DATE(YEAR(B6),11,1),IF(MONTH(B6)>=5,DATE(YEAR(B6),5,1),DATE(YEAR(B6)-1,11,1))))))-1)+INT(F14/30)))
A16: =IF(B6<B5,"El último día de trabajo tiene que ser posterior a la fecha de ingreso.","") | E16: CTS: días | F16: =IF(B6<MAX(B5,IF(MONTH(B6)>=11,DATE(YEAR(B6),11,1),IF(MONTH(B6)>=5,DATE(YEAR(B6),5,1),DATE(YEAR(B6)-1,11,1)))),0,IF(AND(YEAR(MAX(B5,IF(MONTH(B6)>=11,DATE(YEAR(B6),11,1),IF(MONTH(B6)>=5,DATE(YEAR(B6),5,1),DATE(YEAR(B6)-1,11,1)))))=YEAR(B6),MONTH(MAX(B5,IF(MONTH(B6)>=11,DATE(YEAR(B6),11,1),IF(MONTH(B6)>=5,DATE(YEAR(B6),5,1),DATE(YEAR(B6)-1,11,1)))))=MONTH(B6)),IF(AND(DAY(MAX(B5,IF(MONTH(B6)>=11,DATE(YEAR(B6),11,1),IF(MONTH(B6)>=5,DATE(YEAR(B6),5,1),DATE(YEAR(B6)-1,11,1)))))=1,DAY(B6)=DAY(EOMONTH(B6,0))),0,DAY(B6)-DAY(MAX(B5,IF(MONTH(B6)>=11,DATE(YEAR(B6),11,1),IF(MONTH(B6)>=5,DATE(YEAR(B6),5,1),DATE(YEAR(B6)-1,11,1)))))+1),MOD(F14,30)))
A17: Remuneración computable | B17: =F5 | E17: Remuneración de la CTS (con un sexto de la gratificación) | F17: =F5+ROUND(IF(ISNUMBER(B11),B11,0)/6,2)
A18: CTS trunca | B18: =F18 | E18: CTS trunca | F18: =IF(AND(NOT(B10="Microempresa (REMYPE)"),OR(F9>0,F10>0)),ROUND(F17*IF(B10="Régimen general",'Tablas oficiales'!$C$29,IF(B10="Pequeña empresa (REMYPE)",'Tablas oficiales'!$C$30,0))/12*F15+F17*IF(B10="Régimen general",'Tablas oficiales'!$C$29,IF(B10="Pequeña empresa (REMYPE)",'Tablas oficiales'!$C$30,0))/360*F16,2),0)
A19: Gratificación trunca | B19: =F22
A20: Bonificación extraordinaria | B20: =F23 | E20: Gratificación trunca
A21: Vacaciones truncas | B21: =F27 | E21: Meses completos del semestre | F21: =IF(B6<MAX(B5,DATE(YEAR(B6),IF(MONTH(B6)<=6,1,7),1)),0,MAX(0,IF(DAY(B6)=DAY(EOMONTH(B6,0)),(YEAR(B6)*12+MONTH(B6)),(YEAR(B6)*12+MONTH(B6))-1)-IF(DAY(MAX(B5,DATE(YEAR(B6),IF(MONTH(B6)<=6,1,7),1)))=1,(YEAR(MAX(B5,DATE(YEAR(B6),IF(MONTH(B6)<=6,1,7),1)))*12+MONTH(MAX(B5,DATE(YEAR(B6),IF(MONTH(B6)<=6,1,7),1)))),(YEAR(MAX(B5,DATE(YEAR(B6),IF(MONTH(B6)<=6,1,7),1)))*12+MONTH(MAX(B5,DATE(YEAR(B6),IF(MONTH(B6)<=6,1,7),1))))+1)+1))
A22: Vacaciones ganadas no tomadas | B22: =F28 | E22: Gratificación trunca | F22: =IF(B10="Microempresa (REMYPE)",0,ROUND(F5*IF(B10="Régimen general",'Tablas oficiales'!$C$27,IF(B10="Pequeña empresa (REMYPE)",'Tablas oficiales'!$C$28,0))*F21/6,2))
A23: Total de la liquidación | B23: =ROUND(F18+F22+F23+F27+F28,2) | E23: Bonificación extraordinaria | F23: =IF(B10="Microempresa (REMYPE)",0,ROUND(F22*INDEX('Tablas oficiales'!$C$8:$C$9,MATCH(B13,'Tablas oficiales'!$B$8:$B$9,0))/100,2))
A24: Meses que cuenta la CTS trunca | B24: =F15
A25: Días sueltos de la CTS trunca | B25: =F16 | E25: Vacaciones
A26: Meses que cuenta la gratificación trunca | B26: =F21 | E26: Remuneración vacacional | F26: =F5*IF(B10="Régimen general",'Tablas oficiales'!$C$31,IF(B10="Pequeña empresa (REMYPE)",'Tablas oficiales'!$C$32,'Tablas oficiales'!$C$33))/30
E27: Vacaciones truncas | F27: =IF(OR(F9>0,F10>0),ROUND(F26/12*F10+F26/360*F11,2),0)
A28: Si ya te pagaron la gratificación de este semestre, réstala: no se cobra dos veces. En la microempresa del régimen especial solo se pagan las vacaciones. | E28: Vacaciones ganadas no tomadas | F28: =ROUND(F5/30*B12,2)
A30: SI TE DESPIDIERON SIN CAUSA | E30: Indemnización por despido arbitrario
A31: Tipo de contrato | B31: A plazo indeterminado | E31: Remuneraciones diarias antes del tope | F31: =IF(B31="A plazo fijo (con fecha de fin)",IF(B10="Régimen general",'Tablas oficiales'!$C$34,IF(B10="Pequeña empresa (REMYPE)",'Tablas oficiales'!$C$35,'Tablas oficiales'!$C$36))*B32+IF(B10="Régimen general",'Tablas oficiales'!$C$34,IF(B10="Pequeña empresa (REMYPE)",'Tablas oficiales'!$C$35,'Tablas oficiales'!$C$36))/30*B33,IF(B10="Régimen general",IF(B10="Régimen general",'Tablas oficiales'!$C$34,IF(B10="Pequeña empresa (REMYPE)",'Tablas oficiales'!$C$35,'Tablas oficiales'!$C$36))*(F9+F10/12+F11/360),IF(B10="Régimen general",'Tablas oficiales'!$C$34,IF(B10="Pequeña empresa (REMYPE)",'Tablas oficiales'!$C$35,'Tablas oficiales'!$C$36))*(F9+F10/12)))
A32: Meses que faltaban para terminar el contrato | B32: 0 | C32: Solo si tu contrato era a plazo fijo. | E32: Remuneraciones diarias | F32: =IF(AND(F9=0,F10<3),0,MIN(F31,IF(B10="Régimen general",'Tablas oficiales'!$C$37,IF(B10="Pequeña empresa (REMYPE)",'Tablas oficiales'!$C$38,'Tablas oficiales'!$C$39))))
A33: Días sueltos que faltaban | B33: 0 | C33: Solo si tu contrato era a plazo fijo.
A34: =IF(AND(B31="A plazo fijo (con fecha de fin)",NOT(B10="Régimen general")),"Para contratos a plazo fijo en la micro o pequeña empresa no tenemos una regla confirmada en la norma.",IF(AND(F9=0,F10<3),"Si te despiden durante los tres primeros meses (periodo de prueba) no corresponde indemnización.",""))
A35: Remuneración mensual que se usa | B35: =F5
A36: Años completos trabajados | B36: =F9
A37: Meses adicionales | B37: =F10
A38: Días adicionales | B38: =F11
A39: Remuneraciones diarias que te corresponden | B39: =ROUND(F32,2)
A40: Indemnización por despido arbitrario | B40: =ROUND(F32*F5/30,2)
A42: Régimen general: una remuneración y media por año, con tope de 12 remuneraciones (DS 003-97-TR, art. 38). No incluye la indemnización por vacaciones vencidas.

Sheet Tablas oficiales
A1: Tablas oficiales de Perú
A2: Son los valores que usan las fórmulas de esta planilla, vigentes al 8/10/2026. Cada uno trae el enlace a la norma o al organismo que lo publica y la fecha en que lo verificamos.
A3: Dato | B3: Detalle | C3: Valor | D3: Unidad | E3: Vigente desde | F3: Fuente oficial | G3: Verificado el
A4: Comisión sobre la remuneración (flujo) de cada AFP | B4: AFP Habitat | C4: 1.47 | D4: % | E4: 1/10/2026 | F4: https://www.sbs.gob.pe/app/spp/empleadores/comisiones_spp/Paginas/comision_prima.aspx | G4: 7/10/2026
A5: Comisión sobre la remuneración (flujo) de cada AFP | B5: AFP Integra | C5: 1.55 | D5: % | E5: 1/10/2026 | F5: https://www.sbs.gob.pe/app/spp/empleadores/comisiones_spp/Paginas/comision_prima.aspx | G5: 7/10/2026
A6: Comisión sobre la remuneración (flujo) de cada AFP | B6: Prima AFP | C6: 1.6 | D6: % | E6: 1/10/2026 | F6: https://www.sbs.gob.pe/app/spp/empleadores/comisiones_spp/Paginas/comision_prima.aspx | G6: 7/10/2026
A7: Comisión sobre la remuneración (flujo) de cada AFP | B7: Profuturo AFP | C7: 1.69 | D7: % | E7: 1/10/2026 | F7: https://www.sbs.gob.pe/app/spp/empleadores/comisiones_spp/Paginas/comision_prima.aspx | G7: 7/10/2026
A8: Bonificación extraordinaria sobre la gratificación | B8: EsSalud | C8: 9 | D8: % | E8: 25/6/2015 | F8: https://cdn.www.gob.pe/uploads/document/file/3321103/guia_gratificaciones.pdf | G8: 7/10/2026
A9: Bonificación extraordinaria sobre la gratificación | B9: EPS (entidad prestadora de salud) | C9: 6.75 | D9: % | E9: 25/6/2015 | F9: https://cdn.www.gob.pe/uploads/document/file/3321103/guia_gratificaciones.pdf | G9: 7/10/2026
A10: Unidad impositiva tributaria | C10: 5500 | D10: PEN | E10: 1/1/2026 | F10: https://busquedas.elperuano.pe/dispositivo/NL/2469116-1 | G10: 7/10/2026
A11: Remuneración mínima vital | C11: 1230 | D11: PEN | E11: 1/10/2026 | F11: https://busquedas.elperuano.pe/dispositivo/EX/2559163-1 | G11: 7/10/2026
A12: Asignación familiar | C12: 10 | D12: % | E12: 7/12/1989 | F12: https://www2.congreso.gob.pe/sicr/cendocbib/con4_uibd.nsf/e39398877e100a4a05257e37005c2e26/$file/compendio_normas_laborales_mintra_2013.pdf | G12: 7/10/2026
A13: Aporte al Sistema Nacional de Pensiones (ONP) | C13: 13 | D13: % | E13: 1/1/2026 | F13: https://www.gob.pe/7944-aportes-a-la-onp-recaudados-por-sunat | G13: 7/10/2026
A14: Aporte obligatorio al fondo de la AFP | C14: 10 | D14: % | E14: 1/10/2026 | F14: https://www.sbs.gob.pe/app/spp/empleadores/comisiones_spp/Paginas/comision_prima.aspx | G14: 7/10/2026
A15: Remuneración máxima asegurable (tope de la prima de seguro AFP) | C15: 12732.7 | D15: PEN | E15: 1/10/2026 | F15: https://www.sbs.gob.pe/app/spp/empleadores/comisiones_spp/Paginas/comision_prima.aspx | G15: 7/10/2026
A16: Prima de seguro de invalidez, sobrevivencia y gastos de sepelio (AFP) | C16: 1.37 | D16: % | E16: 1/10/2026 | F16: https://www.sbs.gob.pe/app/spp/empleadores/comisiones_spp/Paginas/comision_prima.aspx | G16: 7/10/2026
A17: Componente sobre el sueldo de la comisión mixta (AFP) | C17: 0 | D17: % | E17: 1/2/2023 | F17: https://www.sbs.gob.pe/app/spp/empleadores/comisiones_spp/Paginas/comision_prima.aspx | G17: 7/10/2026
A18: Deducción fija de las rentas de cuarta y quinta categoría | C18: 7 | D18: UIT | E18: 1/1/2017 | F18: https://www.sunat.gob.pe/legislacion/renta/ley/capvi.pdf | G18: 7/10/2026
A19: Escala del impuesto a la renta de trabajo | D19: UIT | E19: 1/1/2015 | F19: https://www.sunat.gob.pe/legislacion/renta/ley/capvii.pdf | G19: 7/10/2026
B20: Desde | C20: Hasta | D20: Tasa % | E20: Cuota fija
B21: 0 | C21: 5 | D21: 8 | E21: 0
B22: 5 | C22: 20 | D22: 14 | E22: 0
B23: 20 | C23: 35 | D23: 17 | E23: 0
B24: 35 | C24: 45 | D24: 20 | E24: 0
B25: 45 | C25: 1e+15 | D25: 30 | E25: 0
A27: Gratificación por régimen laboral (remuneraciones por semestre) | B27: Régimen general | C27: 1 | D27: veces | E27: 1/10/2008 | F27: https://www2.congreso.gob.pe/sicr/cendocbib/con4_uibd.nsf/e39398877e100a4a05257e37005c2e26/$file/compendio_normas_laborales_mintra_2013.pdf | G27: 7/10/2026
A28: Gratificación por régimen laboral (remuneraciones por semestre) | B28: Pequeña empresa | C28: 0.5 | D28: veces | E28: 1/10/2008 | F28: https://www2.congreso.gob.pe/sicr/cendocbib/con4_uibd.nsf/e39398877e100a4a05257e37005c2e26/$file/compendio_normas_laborales_mintra_2013.pdf | G28: 7/10/2026
A29: CTS por régimen laboral (remuneraciones por año) | B29: Régimen general | C29: 1 | D29: veces | E29: 1/10/2008 | F29: https://www2.congreso.gob.pe/sicr/cendocbib/con4_uibd.nsf/e39398877e100a4a05257e37005c2e26/$file/compendio_normas_laborales_mintra_2013.pdf | G29: 7/10/2026
A30: CTS por régimen laboral (remuneraciones por año) | B30: Pequeña empresa | C30: 0.5 | D30: veces | E30: 1/10/2008 | F30: https://www2.congreso.gob.pe/sicr/cendocbib/con4_uibd.nsf/e39398877e100a4a05257e37005c2e26/$file/compendio_normas_laborales_mintra_2013.pdf | G30: 7/10/2026
A31: Días de vacaciones por año completo | B31: Régimen general | C31: 30 | D31: días | E31: 1/10/2008 | F31: https://www2.congreso.gob.pe/sicr/cendocbib/con4_uibd.nsf/e39398877e100a4a05257e37005c2e26/$file/compendio_normas_laborales_mintra_2013.pdf | G31: 7/10/2026
A32: Días de vacaciones por año completo | B32: Pequeña empresa | C32: 15 | D32: días | E32: 1/10/2008 | F32: https://www2.congreso.gob.pe/sicr/cendocbib/con4_uibd.nsf/e39398877e100a4a05257e37005c2e26/$file/compendio_normas_laborales_mintra_2013.pdf | G32: 7/10/2026
A33: Días de vacaciones por año completo | B33: Microempresa | C33: 15 | D33: días | E33: 1/10/2008 | F33: https://www2.congreso.gob.pe/sicr/cendocbib/con4_uibd.nsf/e39398877e100a4a05257e37005c2e26/$file/compendio_normas_laborales_mintra_2013.pdf | G33: 7/10/2026
A34: Indemnización por despido arbitrario por año completo | B34: Régimen general | C34: 45 | D34: días | E34: 1/10/2008 | F34: https://www2.congreso.gob.pe/sicr/cendocbib/con4_uibd.nsf/e39398877e100a4a05257e37005c2e26/$file/compendio_normas_laborales_mintra_2013.pdf | G34: 7/10/2026
A35: Indemnización por despido arbitrario por año completo | B35: Pequeña empresa | C35: 20 | D35: días | E35: 1/10/2008 | F35: https://www2.congreso.gob.pe/sicr/cendocbib/con4_uibd.nsf/e39398877e100a4a05257e37005c2e26/$file/compendio_normas_laborales_mintra_2013.pdf | G35: 7/10/2026
A36: Indemnización por despido arbitrario por año completo | B36: Microempresa | C36: 10 | D36: días | E36: 1/10/2008 | F36: https://www2.congreso.gob.pe/sicr/cendocbib/con4_uibd.nsf/e39398877e100a4a05257e37005c2e26/$file/compendio_normas_laborales_mintra_2013.pdf | G36: 7/10/2026
A37: Tope de la indemnización por despido arbitrario | B37: Régimen general | C37: 360 | D37: días | E37: 1/10/2008 | F37: https://www2.congreso.gob.pe/sicr/cendocbib/con4_uibd.nsf/e39398877e100a4a05257e37005c2e26/$file/compendio_normas_laborales_mintra_2013.pdf | G37: 7/10/2026
A38: Tope de la indemnización por despido arbitrario | B38: Pequeña empresa | C38: 120 | D38: días | E38: 1/10/2008 | F38: https://www2.congreso.gob.pe/sicr/cendocbib/con4_uibd.nsf/e39398877e100a4a05257e37005c2e26/$file/compendio_normas_laborales_mintra_2013.pdf | G38: 7/10/2026
A39: Tope de la indemnización por despido arbitrario | B39: Microempresa | C39: 90 | D39: días | E39: 1/10/2008 | F39: https://www2.congreso.gob.pe/sicr/cendocbib/con4_uibd.nsf/e39398877e100a4a05257e37005c2e26/$file/compendio_normas_laborales_mintra_2013.pdf | G39: 7/10/2026
