Workbook

Sheet Instrucciones
A1: Planilla de salario y prestaciones El Salvador 2026
A3: 1 | B3: Las celdas amarillas son para sus datos. Las verdes se calculan solas, con las fórmulas de la ley. A la derecha de cada hoja está el paso a paso de la cuenta.
A4: 2 | B4: «Retención de renta»: pone su salario y el descuento del ISSS, y le dice la AFP, la renta que le retienen y su salario líquido.
A5: 3 | B5: «Aguinaldo y Quincena 25»: calcula el aguinaldo de diciembre y la Quincena 25 de enero, completos o proporcionales.
A6: 4 | B6: «Indemnización y renuncia»: pone sus fechas y su salario, y le dice la indemnización por despido sin causa o la prestación por renuncia voluntaria.
A7: 5 | B7: «Tablas oficiales» tiene cada valor oficial que usan las fórmulas, con el enlace a su fuente y la fecha en que lo verificamos. Los valores son los vigentes al 12/10/2026.
A8: 6 | B8: Cuando cambia un valor oficial, actualizamos la planilla y el mismo enlace de descarga le baja la versión nueva.
A10: Da los mismos números que las calculadoras gratuitas de calcularya.com. Antes de publicar cada versión, una verificación automática recalcula este archivo y lo compara con ellas.
A11: Es una referencia de cálculo con sus fuentes, no asesoría legal. Su contrato o su empresa pueden darle más que el mínimo de ley.
A12: Las fechas van como dd/mm/aaaa. Si su Excel está en inglés y las lee al revés, escríbalas como aaaa-mm-dd.

Sheet Retención de renta
A1: Retención de renta, AFP e ISSS
E3: Paso a paso
A4: SUS DATOS | E4: AFP | F4: =ROUND(B6*'Tablas oficiales'!$C$4/100,2)
A5: Cada cuánto le pagan | B5: Cada mes | E5: Salario gravado | F5: =ROUND(MAX(0,B6-F4-B7),2)
A6: Salario del período | B6: 900 | C6: Lo que gana en el mes o en la quincena, antes de descuentos. | E6: Tabla mensual: tramo | F6: =MIN(4,COUNTIF('Tablas oficiales'!$C$7:$C$10,"<"&F5)+1)
A7: Descuento del ISSS del período | B7: 27 | C7: Aparece en su boleta de pago. Si no cotiza al ISSS, ponga 0. | E7: Tabla quincenal: tramo | F7: =MIN(4,COUNTIF('Tablas oficiales'!$C$14:$C$17,"<"&F5)+1)
E8: Renta retenida | F8: =ROUND(IF(B5="Cada mes",IF(F5<=0,0,IF(INDEX('Tablas oficiales'!$D$7:$D$10,F6)=0,0,INDEX('Tablas oficiales'!$E$7:$E$10,F6)+(F5-IF(F6=1,INDEX('Tablas oficiales'!$B$7:$B$10,1)-0.01,INDEX('Tablas oficiales'!$C$7:$C$10,F6-1)))*INDEX('Tablas oficiales'!$D$7:$D$10,F6)/100)),IF(F5<=0,0,IF(INDEX('Tablas oficiales'!$D$14:$D$17,F7)=0,0,INDEX('Tablas oficiales'!$E$14:$E$17,F7)+(F5-IF(F7=1,INDEX('Tablas oficiales'!$B$14:$B$17,1)-0.01,INDEX('Tablas oficiales'!$C$14:$C$17,F7-1)))*INDEX('Tablas oficiales'!$D$14:$D$17,F7)/100))),2)
A9: SU SALARIO LÍQUIDO
A10: =IF(B7>B6,"El descuento del ISSS no puede ser mayor que el salario.","")
A11: AFP | B11: =F4
A12: ISSS | B12: =ROUND(B7,2)
A13: Salario gravado | B13: =F5
A14: Renta retenida | B14: =F8
A15: Salario líquido | B15: =ROUND(B6-F4-B7-F8,2)
A17: En junio y diciembre el patrono recalcula la renta con todo lo ganado en el año, así que ese mes la retención puede cambiar. El ISSS se copia de su boleta.

Sheet Aguinaldo y Quincena 25
A1: Aguinaldo y Quincena 25
E3: Paso a paso
A4: SUS DATOS | E4: Salario diario (entre 30) | F4: =B5/30
A5: Salario mensual | B5: 600 | C5: Su salario básico, sin horas extra. | E5: Días de aguinaldo por año | F5: =IF(OR(B9="Menos de 1 año",B9="De 1 a menos de 3 años"),'Tablas oficiales'!$C$19,IF(B9="De 3 a menos de 10 años",'Tablas oficiales'!$C$20,'Tablas oficiales'!$C$21))
A6: Días trabajados (solo si tiene menos de 1 año) | C6: Cuente desde su primer día de trabajo. | E6: Días de aguinaldo | F6: =IF(B9="Menos de 1 año",F5*IF(ISNUMBER(B6),B6,0)/365,F5)
E7: Quincena 25 completa | F7: =IF(B5>'Tablas oficiales'!$C$22,0,ROUND(B5*'Tablas oficiales'!$C$23/100,2))
A8: AGUINALDO
A9: Tiempo trabajando con el mismo patrono | B9: De 1 a menos de 3 años
A10: =IF(AND(B9="Menos de 1 año",NOT(ISNUMBER(B6))),"Indique cuántos días lleva trabajando.","")
A11: Salario diario | B11: =ROUND(F4,2)
A12: Días de aguinaldo | B12: =ROUND(F6,2)
A13: Aguinaldo | B13: =ROUND(F4*F6,2)
A15: Se paga entre el 12 y el 20 de diciembre. Con menos de un año cobra la parte proporcional de 15 días.
A17: QUINCENA 25
A18: Tiene un año o más con el mismo patrono | B18: Sí
A19: =IF(AND(B18="No",NOT(ISNUMBER(B6))),"Indique cuántos días lleva trabajando.","")
A20: Quincena 25 completa | B20: =F7
A21: Quincena 25 que le toca | B21: =IF(B18="Sí",F7,ROUND(F7*IF(ISNUMBER(B6),B6,0)/365,2))
A23: Es para salarios de hasta el máximo de la ley (ver tablas). Se paga entre el 15 y el 25 de enero, sin descuentos de renta, ISSS ni AFP.

Sheet Indemnización y renuncia
A1: Indemnización por despido y prestación por renuncia
E3: Paso a paso
A4: SUS DATOS | E4: Años de servicio | F4: =IF(EDATE(B6,12*(YEAR((B7+1))-YEAR(B6)))>(B7+1),(YEAR((B7+1))-YEAR(B6))-1,(YEAR((B7+1))-YEAR(B6)))
A5: Salario mensual | B5: 600 | C5: Su salario básico, sin horas extra. | E5: Días después del último aniversario | F5: =(B7+1)-EDATE(B6,12*F4)
A6: Fecha en que empezó a trabajar | B6: 44228 | E6: Salario diario (entre 30) | F6: =B5/30
A7: Último día trabajado | B7: 46307 | E7: Salario mínimo diario del sector | F7: =INDEX('Tablas oficiales'!$C$24:$C$30,MATCH(B8,'Tablas oficiales'!$B$24:$B$30,0))
A8: Sector de la empresa | B8: Comercio y servicios
E9: Indemnización
A10: INDEMNIZACIÓN POR DESPIDO SIN CAUSA | E10: Salario diario para la indemnización (con tope) | F10: =MIN(F6,'Tablas oficiales'!$C$31*F7)
A11: =IF(B7<B6,"El último día tiene que ser posterior a la fecha de inicio.","") | E11: Días de indemnización | F11: =MAX('Tablas oficiales'!$C$32*F4+'Tablas oficiales'!$C$32*F5/365,'Tablas oficiales'!$C$33)
A12: Tiempo de servicio | B12: =F4&" años y "&F5&" días"
A13: Salario diario que se usa | B13: =ROUND(F10,2) | E13: Prestación por renuncia
A14: Días de indemnización | B14: =ROUND(F11,2) | E14: Salario diario para la prestación (con tope) | F14: =MIN(F6,'Tablas oficiales'!$C$34*F7)
A15: Indemnización | B15: =ROUND(F10*F11,2) | E15: Días de prestación | F15: =IF(F4>='Tablas oficiales'!$C$35,'Tablas oficiales'!$C$36*F4,0)
A17: Un mes de salario por año, y la fracción en proporción, con un mínimo de 15 días y un tope de cuatro salarios mínimos diarios. Aparte le deben las vacaciones y el aguinaldo proporcionales.
A19: PRESTACIÓN POR RENUNCIA VOLUNTARIA
A20: Salario diario que se usa | B20: =ROUND(F14,2)
A21: Días de prestación | B21: =F15
A22: Prestación por renuncia | B22: =ROUND(F14*F15,2)
A24: Se gana con al menos 2 años de servicio y paga 15 días por año completo, con un tope de dos salarios mínimos diarios. Hay que avisar por escrito con 15 días de anticipación (30 en jefaturas).

Sheet Tablas oficiales
A1: Tablas oficiales de El Salvador
A2: Son los valores que usan las fórmulas de esta planilla, vigentes al 12/10/2026. Cada uno trae el enlace a la norma o al organismo que lo publica y la fecha en que lo verificamos.
A3: Dato | B3: Detalle | C3: Valor | D3: Unidad | E3: Vigente desde | F3: Fuente oficial | G3: Verificado el
A4: Cotización a la AFP a cargo del trabajador | C4: 7.25 | D4: % | E4: 29/12/2022 | F4: https://www.asamblea.gob.sv/sites/default/files/documents/decretos/F94AF319-257C-4A85-97B7-4D03A6C65A48.pdf | G4: 7/10/2026
A5: Tabla de retención de renta para salarios mensuales | D5: USD | E5: 1/5/2025 | F5: https://www.jurisprudencia.gob.sv/DocumentosBoveda/D/2/2020-2029/2025/04/10A052.PDF | G5: 7/10/2026
B6: Desde | C6: Hasta | D6: Tasa % | E6: Cuota fija
B7: 0.01 | C7: 550 | D7: 0 | E7: 0
B8: 550.01 | C8: 895.24 | D8: 10 | E8: 17.67
B9: 895.25 | C9: 2038.1 | D9: 20 | E9: 60
B10: 2038.11 | C10: 1e+15 | D10: 30 | E10: 288.57
A12: Tabla de retención de renta para salarios quincenales | D12: USD | E12: 1/5/2025 | F12: https://www.jurisprudencia.gob.sv/DocumentosBoveda/D/2/2020-2029/2025/04/10A052.PDF | G12: 7/10/2026
B13: Desde | C13: Hasta | D13: Tasa % | E13: Cuota fija
B14: 0.01 | C14: 275 | D14: 0 | E14: 0
B15: 275.01 | C15: 447.62 | D15: 10 | E15: 8.83
B16: 447.63 | C16: 1019.05 | D16: 20 | E16: 30
B17: 1019.06 | C17: 1e+15 | D17: 30 | E17: 144.28
A19: Días de salario de aguinaldo según la antigüedad | B19: De 1 a menos de 3 años | C19: 15 | D19: días | E19: 1/1/2026 | F19: https://www.jurisprudencia.gob.sv/DocumentosBoveda/D/2/1970-1979/1972/07/886E0.PDF | G19: 7/10/2026
A20: Días de salario de aguinaldo según la antigüedad | B20: De 3 a menos de 10 años | C20: 19 | D20: días | E20: 1/1/2026 | F20: https://www.jurisprudencia.gob.sv/DocumentosBoveda/D/2/1970-1979/1972/07/886E0.PDF | G20: 7/10/2026
A21: Días de salario de aguinaldo según la antigüedad | B21: 10 años o más | C21: 21 | D21: días | E21: 1/1/2026 | F21: https://www.jurisprudencia.gob.sv/DocumentosBoveda/D/2/1970-1979/1972/07/886E0.PDF | G21: 7/10/2026
A22: Quincena 25: salario mensual máximo para tenerla | C22: 1500 | D22: USD | E22: 14/1/2026 | F22: https://www.asamblea.gob.sv/sites/default/files/documents/decretos/D72EB960-89D5-443E-AE2D-196F677CB0F2.pdf | G22: 7/10/2026
A23: Quincena 25: porcentaje del salario mensual | C23: 50 | D23: % | E23: 14/1/2026 | F23: https://www.asamblea.gob.sv/sites/default/files/documents/decretos/D72EB960-89D5-443E-AE2D-196F677CB0F2.pdf | G23: 7/10/2026
A24: Salario mínimo diario por sector | B24: Comercio y servicios | C24: 13.44 | D24: USD | E24: 1/6/2025 | F24: https://www.jurisprudencia.gob.sv/DocumentosBoveda/D/2/2020-2029/2025/05/10A4DA.PDF | G24: 7/10/2026
A25: Salario mínimo diario por sector | B25: Industria (incluye ingenios azucareros y agroindustria) | C25: 13.44 | D25: USD | E25: 1/6/2025 | F25: https://www.jurisprudencia.gob.sv/DocumentosBoveda/D/2/2020-2029/2025/05/10A4DA.PDF | G25: 7/10/2026
A26: Salario mínimo diario por sector | B26: Maquila textil y confección | C26: 13.227 | D26: USD | E26: 1/6/2025 | F26: https://www.jurisprudencia.gob.sv/DocumentosBoveda/D/2/2020-2029/2025/05/10A4DA.PDF | G26: 7/10/2026
A27: Salario mínimo diario por sector | B27: Beneficios de café | C27: 10.035 | D27: USD | E27: 1/6/2025 | F27: https://www.jurisprudencia.gob.sv/DocumentosBoveda/D/2/2020-2029/2025/05/10A4DA.PDF | G27: 7/10/2026
A28: Salario mínimo diario por sector | B28: Recolección de caña de azúcar | C28: 10.035 | D28: USD | E28: 1/6/2025 | F28: https://www.jurisprudencia.gob.sv/DocumentosBoveda/D/2/2020-2029/2025/05/10A4DA.PDF | G28: 7/10/2026
A29: Salario mínimo diario por sector | B29: Agropecuario, pesca y otras actividades agrícolas | C29: 8.96 | D29: USD | E29: 1/6/2025 | F29: https://www.jurisprudencia.gob.sv/DocumentosBoveda/D/2/2020-2029/2025/05/10A4DA.PDF | G29: 7/10/2026
A30: Salario mínimo diario por sector | B30: Recolección de café | C30: 8.96 | D30: USD | E30: 1/6/2025 | F30: https://www.jurisprudencia.gob.sv/DocumentosBoveda/D/2/2020-2029/2025/05/10A4DA.PDF | G30: 7/10/2026
A31: Tope del salario diario para la indemnización (veces el salario mínimo diario) | C31: 4 | D31: veces | E31: 1/1/2026 | F31: https://www.jurisprudencia.gob.sv/DocumentosBoveda/D/2/1970-1979/1972/07/886E0.PDF | G31: 7/10/2026
A32: Días de salario de indemnización por año de servicio | C32: 30 | D32: días | E32: 1/1/2026 | F32: https://www.jurisprudencia.gob.sv/DocumentosBoveda/D/2/1970-1979/1972/07/886E0.PDF | G32: 7/10/2026
A33: Indemnización mínima en días de salario | C33: 15 | D33: días | E33: 1/1/2026 | F33: https://www.jurisprudencia.gob.sv/DocumentosBoveda/D/2/1970-1979/1972/07/886E0.PDF | G33: 7/10/2026
A34: Tope del salario diario para la prestación por renuncia (veces el salario mínimo diario del sector) | C34: 2 | D34: veces | E34: 1/1/2015 | F34: https://www.asamblea.gob.sv/sites/default/files/documents/decretos/64753625-5A99-425D-B845-BF2719C6A710.pdf | G34: 7/10/2026
A35: Años de servicio continuo para tener la prestación por renuncia | C35: 2 | D35: años | E35: 1/1/2015 | F35: https://www.asamblea.gob.sv/sites/default/files/documents/decretos/64753625-5A99-425D-B845-BF2719C6A710.pdf | G35: 7/10/2026
A36: Días de salario de la prestación por renuncia, por año de servicio | C36: 15 | D36: días | E36: 1/1/2015 | F36: https://www.asamblea.gob.sv/sites/default/files/documents/decretos/64753625-5A99-425D-B845-BF2719C6A710.pdf | G36: 7/10/2026
