Workbook

Sheet Instrucciones
A1: Planilla de salario y liquidación Panamá 2026
A3: 1 | B3: Las celdas amarillas son para tus datos. Las verdes se calculan solas, con las fórmulas de la ley. A la derecha de cada hoja está el paso a paso de la cuenta.
A4: 2 | B4: «Salario neto»: pones tu salario bruto y te dice la cuota del Seguro Social, el seguro educativo, el ISR estimado y lo que recibes por quincena.
A5: 3 | B5: «Décimo tercer mes»: calcula cada partida del décimo tercer mes (abril, agosto y diciembre) y su descuento del Seguro Social.
A6: 4 | B6: «Liquidación»: pones tus fechas, tu salario y cómo terminó la relación, y te dice la prima de antigüedad, la indemnización, las vacaciones y el décimo proporcional.
A7: 5 | B7: «Tablas oficiales» tiene cada valor oficial que usan las fórmulas, con el enlace a su fuente y la fecha en que lo verificamos. Los valores son los vigentes al 19/10/2026.
A8: 6 | B8: Cuando cambia un valor oficial, actualizamos la planilla y el mismo enlace de descarga te baja la versión nueva.
A10: Da los mismos números que las calculadoras gratuitas de calcularya.com. Antes de publicar cada versión, una verificación automática recalcula este archivo y lo compara con ellas.
A11: Es una referencia de cálculo con sus fuentes, no asesoría legal. Tu contrato o tu empresa pueden darte más que el mínimo de ley.
A12: Las fechas van como dd/mm/aaaa. Si tu Excel está en inglés y las lee al revés, escríbelas como aaaa-mm-dd.

Sheet Salario neto
A1: Salario neto: Seguro Social, seguro educativo e ISR
E3: Paso a paso
A4: TUS DATOS | E4: Caja de Seguro Social | F4: =ROUND(B5*'Tablas oficiales'!$C$4/100,2)
A5: Salario bruto mensual | B5: 1500 | E5: Seguro educativo | F5: =ROUND(B5*'Tablas oficiales'!$C$5/100,2)
E6: ISR del mes (impuesto de 13 pagos entre 13) | F6: =ROUND(IF(B5*13<=0,0,INDEX('Tablas oficiales'!$E$8:$E$10,IFERROR(MATCH(B5*13,'Tablas oficiales'!$B$8:$B$10,1),1))+(B5*13-INDEX('Tablas oficiales'!$B$8:$B$10,IFERROR(MATCH(B5*13,'Tablas oficiales'!$B$8:$B$10,1),1)))*INDEX('Tablas oficiales'!$D$8:$D$10,IFERROR(MATCH(B5*13,'Tablas oficiales'!$B$8:$B$10,1),1))/100)/13,2)
A7: TU SALARIO NETO | E7: Salario neto | F7: =ROUND(B5-F4-F5-F6,2)
A8: Caja de Seguro Social | B8: =F4
A9: Seguro educativo | B9: =F5
A10: Impuesto sobre la renta estimado | B10: =F6
A11: Salario neto del mes | B11: =F7
A12: Lo que recibes por quincena | B12: =ROUND(F7/2,2)
A14: El ISR es una estimación sin deducciones: el año son 13 pagos (12 salarios y el décimo). Si tienes gastos deducibles, la retención real puede ser menor.

Sheet Décimo tercer mes
A1: Décimo tercer mes
E3: Paso a paso
A4: TUS DATOS | E4: Partida bruta | F4: =ROUND(B6/'Tablas oficiales'!$C$12,2)
A5: Qué partida quieres calcular | B5: Tercera partida (15 de diciembre) | E5: Seguro Social del décimo | F5: =ROUND(F4*'Tablas oficiales'!$C$13/100,2)
A6: Total ganado en esos cuatro meses | B6: 6000 | C6: Salario, horas extra, comisiones y vacaciones del período. Con salario fijo y el período completo, son cuatro salarios.
A8: TU DÉCIMO
A9: Partida bruta | B9: =F4
A10: Seguro Social | B10: =F5
A11: Partida neta | B11: =ROUND(F4-F5,2)
A13: Los períodos van del 16 de diciembre al 15 de abril, del 16 de abril al 15 de agosto y del 16 de agosto al 15 de diciembre. No lleva seguro educativo.

Sheet Liquidación
A1: Liquidación: prima de antigüedad, indemnización, vacaciones y décimo
E3: Paso a paso
A4: TUS DATOS | E4: Tiempo trabajado: años completos | F4: =IF(EDATE(B6,12*(YEAR((B7+1))-YEAR(B6)))>(B7+1),(YEAR((B7+1))-YEAR(B6))-1,(YEAR((B7+1))-YEAR(B6)))
A5: Salario mensual | B5: 1200 | C5: Tu salario de los últimos meses, con horas extra y comisiones. | E5: Tiempo trabajado: último aniversario | F5: =EDATE(B6,12*F4)
A6: Fecha de ingreso | B6: 43862 | E6: Tiempo trabajado: meses | F6: =MIN(12,IF(EDATE(F5,((YEAR((B7+1))-YEAR(F5))*12+MONTH((B7+1))-MONTH(F5)))>(B7+1),((YEAR((B7+1))-YEAR(F5))*12+MONTH((B7+1))-MONTH(F5))-1,((YEAR((B7+1))-YEAR(F5))*12+MONTH((B7+1))-MONTH(F5))))
A7: Último día de trabajo | B7: 46314 | E7: Tiempo trabajado: días | F7: =(B7+1)-EDATE(F5,F6)
A8: Cómo terminó la relación de trabajo | B8: Despido injustificado | E8: Años con fracción | F8: =(F4*12+F6+F7/30)/12
A9: Tu contrato era por tiempo indefinido | B9: Sí | C9: Si era por obra o por un plazo fijo, marca que no. | E9: Salario semanal (12 meses entre 52 semanas) | F9: =B5*12/52
A10: Meses trabajados desde tus últimas vacaciones | B10: 0 | C10: Si no tomaste vacaciones en un período completo, súmalo también.
E11: Prima e indemnización
A12: TU LIQUIDACIÓN | E12: Prima de antigüedad | F12: =IF(B9="Sí",ROUND(F9*F8*'Tablas oficiales'!$C$14,2),0)
A13: =IF(B7<B6,"La fecha de salida tiene que ser igual o posterior a la de ingreso.",IF(AND(AND(B9="Sí",B8="Despido injustificado"),B6<DATE(1995,8,14)),"Si empezaste antes del 14 de agosto de 1995, la indemnización usa otras escalas del artículo 225 que esta planilla no cubre.","")) | E13: Semanas de indemnización | F13: =IF(AND(B9="Sí",B8="Despido injustificado"),MIN(F8,10)*'Tablas oficiales'!$C$15+MAX(F8-10,0)*'Tablas oficiales'!$C$16,0)
A14: Tiempo trabajado | B14: =F4&" años, "&F6&" meses y "&F7&" días" | E14: Indemnización | F14: =ROUND(F9*F13,2)
A15: Prima de antigüedad | B15: =F12
A16: Indemnización por despido injustificado | B16: =F14 | E16: Vacaciones y décimo
A17: Vacaciones | B17: =F17 | E17: Vacaciones | F17: =ROUND(B5*B10/'Tablas oficiales'!$C$17,2)
A18: Décimo tercer mes proporcional | B18: =F23 | E18: Período del décimo: años completos | F18: =IF(EDATE(MAX(B6,IF(AND((MONTH(B7)*100+DAY(B7))>=416,(MONTH(B7)*100+DAY(B7))<=815),DATE(YEAR(B7),4,16),IF(AND((MONTH(B7)*100+DAY(B7))>=816,(MONTH(B7)*100+DAY(B7))<=1215),DATE(YEAR(B7),8,16),IF((MONTH(B7)*100+DAY(B7))>=1216,DATE(YEAR(B7),12,16),DATE(YEAR(B7)-1,12,16))))),12*(YEAR((B7+1))-YEAR(MAX(B6,IF(AND((MONTH(B7)*100+DAY(B7))>=416,(MONTH(B7)*100+DAY(B7))<=815),DATE(YEAR(B7),4,16),IF(AND((MONTH(B7)*100+DAY(B7))>=816,(MONTH(B7)*100+DAY(B7))<=1215),DATE(YEAR(B7),8,16),IF((MONTH(B7)*100+DAY(B7))>=1216,DATE(YEAR(B7),12,16),DATE(YEAR(B7)-1,12,16))))))))>(B7+1),(YEAR((B7+1))-YEAR(MAX(B6,IF(AND((MONTH(B7)*100+DAY(B7))>=416,(MONTH(B7)*100+DAY(B7))<=815),DATE(YEAR(B7),4,16),IF(AND((MONTH(B7)*100+DAY(B7))>=816,(MONTH(B7)*100+DAY(B7))<=1215),DATE(YEAR(B7),8,16),IF((MONTH(B7)*100+DAY(B7))>=1216,DATE(YEAR(B7),12,16),DATE(YEAR(B7)-1,12,16)))))))-1,(YEAR((B7+1))-YEAR(MAX(B6,IF(AND((MONTH(B7)*100+DAY(B7))>=416,(MONTH(B7)*100+DAY(B7))<=815),DATE(YEAR(B7),4,16),IF(AND((MONTH(B7)*100+DAY(B7))>=816,(MONTH(B7)*100+DAY(B7))<=1215),DATE(YEAR(B7),8,16),IF((MONTH(B7)*100+DAY(B7))>=1216,DATE(YEAR(B7),12,16),DATE(YEAR(B7)-1,12,16))))))))
A19: Total | B19: =ROUND(F12+F14+F17+F23,2) | E19: Período del décimo: último aniversario | F19: =EDATE(MAX(B6,IF(AND((MONTH(B7)*100+DAY(B7))>=416,(MONTH(B7)*100+DAY(B7))<=815),DATE(YEAR(B7),4,16),IF(AND((MONTH(B7)*100+DAY(B7))>=816,(MONTH(B7)*100+DAY(B7))<=1215),DATE(YEAR(B7),8,16),IF((MONTH(B7)*100+DAY(B7))>=1216,DATE(YEAR(B7),12,16),DATE(YEAR(B7)-1,12,16))))),12*F18)
E20: Período del décimo: meses | F20: =MIN(12,IF(EDATE(F19,((YEAR((B7+1))-YEAR(F19))*12+MONTH((B7+1))-MONTH(F19)))>(B7+1),((YEAR((B7+1))-YEAR(F19))*12+MONTH((B7+1))-MONTH(F19))-1,((YEAR((B7+1))-YEAR(F19))*12+MONTH((B7+1))-MONTH(F19))))
A21: En un contrato por obra o plazo fijo no hay prima de antigüedad. La indemnización es de 3,4 semanas por año los primeros diez años y una semana por año después. Las vacaciones y el décimo llevan descuentos del Seguro Social. | E21: Período del décimo: días | F21: =(B7+1)-EDATE(F19,F20)
E22: Meses del período del décimo | F22: =MIN(4,F18*12+F20+F21/30)
E23: Décimo proporcional (con las vacaciones) | F23: =ROUND((B5*F22+F17)/'Tablas oficiales'!$C$12,2)

Sheet Tablas oficiales
A1: Tablas oficiales de Panamá
A2: Son los valores que usan las fórmulas de esta planilla, vigentes al 19/10/2026. Cada uno trae el enlace a la norma o al organismo que lo publica y la fecha en que lo verificamos.
A3: Dato | B3: Detalle | C3: Valor | D3: Unidad | E3: Vigente desde | F3: Fuente oficial | G3: Verificado el
A4: Cuota del empleado a la Caja de Seguro Social | C4: 9.75 | D4: % | E4: 18/3/2025 | F4: https://s3-legispan.asamblea.gob.pa/legispan/GACETAS/2020/2025/30238_2025.pdf | G4: 7/10/2026
A5: Seguro educativo a cargo del empleado | C5: 1.25 | D5: % | E5: 5/8/1987 | F5: https://s3-legispan.asamblea.gob.pa/legispan/GACETAS/1980/1987/20858_1987.pdf | G5: 7/10/2026
A6: Tarifa anual del impuesto sobre la renta de personas naturales | D6: USD | E6: 15/3/2010 | F6: https://www.organojudicial.gob.pa/uploads/wp_repo/blogs.dir/cendoj/novedades_normativas/ley_8_2010.pdf | G6: 7/10/2026
B7: Desde | C7: Hasta | D7: Tasa % | E7: Cuota fija
B8: 0 | C8: 11000 | D8: 0 | E8: 0
B9: 11000 | C9: 50000 | D9: 15 | E9: 0
B10: 50000 | C10: 1e+15 | D10: 25 | E10: 5850
A12: Divisor del décimo tercer mes (total ganado en el período entre este número) | C12: 12 | E12: 20/9/1973 | F12: https://mitradel.gob.pa/wp-content/uploads/2019/12/Bolet%C3%ADn.pdf | G12: 7/10/2026
A13: Contribución especial del empleado sobre cada partida del décimo tercer mes | C13: 7.25 | D13: % | E13: 18/3/2025 | F13: https://s3-legispan.asamblea.gob.pa/legispan/GACETAS/2020/2025/30238_2025.pdf | G13: 7/10/2026
A14: Semanas de salario de prima de antigüedad por año laborado | C14: 1 | E14: 14/8/1995 | F14: https://www.defensoria.gob.pa/wp-content/uploads/Ley-No.-44-de1995-12-agosto.pdf | G14: 7/10/2026
A15: Semanas de salario de indemnización por año (relaciones iniciadas desde la Ley 44 de 1995) | B15: Por cada uno de los diez primeros años | C15: 3.4 | E15: 14/8/1995 | F15: https://www.defensoria.gob.pa/wp-content/uploads/Ley-No.-44-de1995-12-agosto.pdf | G15: 7/10/2026
A16: Semanas de salario de indemnización por año (relaciones iniciadas desde la Ley 44 de 1995) | B16: Por cada año posterior a los diez | C16: 1 | E16: 14/8/1995 | F16: https://www.defensoria.gob.pa/wp-content/uploads/Ley-No.-44-de1995-12-agosto.pdf | G16: 7/10/2026
A17: Meses continuos de trabajo que dan derecho a las vacaciones | C17: 11 | D17: meses | E17: 2/4/1972 | F17: https://www.organojudicial.gob.pa/uploads/wp_repo/uploads/2016/11/c%C3%B3digo-detrabajo.pdf | G17: 7/10/2026
