Workbook

Sheet Instrucciones
A1: Planilla de sueldo y finiquito Chile 2026
A3: 1 | B3: Las celdas amarillas son para tus datos. Las verdes se calculan solas, con las fórmulas de la ley. A la derecha de cada hoja está el paso a paso de la cuenta.
A4: 2 | B4: «Sueldo líquido»: pones tu sueldo imponible y te dice los descuentos de AFP, salud, seguro de cesantía e impuesto único, y tu sueldo líquido.
A5: 3 | B5: «Gratificación»: calcula la gratificación mensual con el 25 % de tu remuneración y su tope legal.
A6: 4 | B6: «Finiquito»: pones tus fechas, tu remuneración y el motivo del término, y te dice las indemnizaciones y las vacaciones pendientes y proporcionales.
A7: 5 | B7: «Tablas oficiales» tiene cada valor oficial que usan las fórmulas, con el enlace a su fuente y la fecha en que lo verificamos. Los valores son los vigentes al 8/10/2026.
A8: 6 | B8: Cuando cambia un valor oficial, actualizamos la planilla y el mismo enlace de descarga te baja la versión nueva.
A10: Da los mismos números que las calculadoras gratuitas de calcularya.com. Antes de publicar cada versión, una verificación automática recalcula este archivo y lo compara con ellas.
A11: Es una referencia de cálculo con sus fuentes, no asesoría legal. Tu contrato o tu empresa pueden darte más que el mínimo de ley.
A12: Las fechas van como dd/mm/aaaa. Si tu Excel está en inglés y las lee al revés, escríbelas como aaaa-mm-dd.

Sheet Sueldo líquido
A1: Sueldo líquido: AFP, salud, seguro de cesantía e impuesto único
E3: Paso a paso
A4: TUS DATOS
A5: Sueldo bruto imponible | B5: 1200000 | C5: Sueldo base más gratificación, horas extra, bonos y comisiones del mes. | E5: Cotizaciones
A6: Colación y movilización | B6: 0 | C6: Lo que no paga cotizaciones ni impuesto. Si no tienes, deja 0. | E6: Tope imponible del mes | F6: =ROUND('Tablas oficiales'!$C$13*'Tablas oficiales'!$C$11,0)
A7: Tu AFP | B7: AFP Habitat | E7: Tope imponible del seguro de cesantía | F7: =ROUND('Tablas oficiales'!$C$14*'Tablas oficiales'!$C$11,0)
A8: Sistema de salud | B8: Fonasa | E8: Base de AFP y salud | F8: =MIN(B5,F6)
A9: Valor de tu plan de Isapre en UF | B9: 0 | C9: Solo si tu sistema de salud es Isapre. Si tu plan cuesta menos que la cotización legal, se descuenta igual la cotización legal. | E9: AFP: cotización más comisión (%) | F9: ='Tablas oficiales'!$C$15+INDEX('Tablas oficiales'!$C$4:$C$10,MATCH(B7,'Tablas oficiales'!$B$4:$B$10,0))
A10: Tipo de contrato | B10: Indefinido | E10: AFP | F10: =ROUND(F8*F9/100,0)
E11: Cotización legal de salud | F11: =ROUND(F8*'Tablas oficiales'!$C$16/100,0)
A12: TU LIQUIDACIÓN DE SUELDO | E12: Plan de Isapre en pesos | F12: =IF(B8="Isapre",ROUND(B9*'Tablas oficiales'!$C$11,0),0)
A13: Sueldo bruto imponible | B13: =B5 | E13: Salud que te descuentan | F13: =MAX(F11,F12)
A14: AFP (cotización y comisión) | B14: =F10 | E14: Seguro de cesantía | F14: =IF(B10="Indefinido",ROUND(MIN(B5,F7)*'Tablas oficiales'!$C$17/100,0),0)
A15: Salud | B15: =F13
A16: Seguro de cesantía | B16: =F14 | E16: Impuesto único
A17: Base para el impuesto | B17: =F17 | E17: Base para el impuesto | F17: =MAX(0,B5-F10-F11-F14)
A18: Impuesto único | B18: =F19 | E18: Base en UTM | F18: =F17/'Tablas oficiales'!$C$12
A19: Total de descuentos | B19: =F20 | E19: Impuesto único | F19: =ROUND(IF(F18<=0,0,INDEX('Tablas oficiales'!$E$20:$E$27,IFERROR(MATCH(F18,'Tablas oficiales'!$B$20:$B$27,1),1))+(F18-INDEX('Tablas oficiales'!$B$20:$B$27,IFERROR(MATCH(F18,'Tablas oficiales'!$B$20:$B$27,1),1)))*INDEX('Tablas oficiales'!$D$20:$D$27,IFERROR(MATCH(F18,'Tablas oficiales'!$B$20:$B$27,1),1))/100)*'Tablas oficiales'!$C$12,0)
A20: Colación y movilización | B20: =B6 | E20: Total de descuentos | F20: =F10+F13+F14+F19
A21: Sueldo líquido | B21: =B5-F20+B6
A22: Tope imponible del mes | B22: =F6
A24: La UF y la UTM están en la hoja de tablas con su fecha. Lo que tu plan de Isapre cobra por sobre la cotización legal se descuenta del sueldo, pero no rebaja el impuesto.

Sheet Gratificación
A1: Gratificación legal del artículo 50
E3: Paso a paso
A4: TUS DATOS | E4: Porcentaje legal de la remuneración | F4: =B5*'Tablas oficiales'!$C$30/100
A5: Remuneración mensual | B5: 900000 | C5: Sueldo más lo variable del mes (comisiones, horas extra). Sin colación ni movilización. | E5: Tope mensual (4,75 ingresos mínimos al año) | F5: ='Tablas oficiales'!$C$31*'Tablas oficiales'!$C$29/12
A6: Meses trabajados en el año | B6: 12 | E6: Gratificación mensual exacta | F6: =MIN(F4,F5)
A8: TU GRATIFICACIÓN
A9: Porcentaje legal de tu remuneración | B9: =ROUND(F4,0)
A10: Tope mensual | B10: =ROUND(F5,0)
A11: Gratificación mensual | B11: =ROUND(F6,0)
A12: Gratificación del año | B12: =ROUND(F6*B6,0)
A13: Ingreso mínimo usado para el tope | B13: ='Tablas oficiales'!$C$29
A15: Es la modalidad del artículo 50 del Código del Trabajo, la que usan casi todas las empresas. Si la tuya reparte el 30 % de las utilidades (artículo 47), el monto puede ser otro.

Sheet Finiquito
A1: Finiquito: indemnizaciones y vacaciones
E3: Paso a paso
A4: TUS DATOS
A5: Fecha en que empezaste a trabajar | B5: 44635 | E5: Antigüedad
A6: Último día de trabajo | B6: 46303 | E6: Años completos | F6: =IF(EDATE(B5,12*(YEAR(B6)-YEAR(B5)))>B6,(YEAR(B6)-YEAR(B5))-1,(YEAR(B6)-YEAR(B5)))
A7: Última remuneración mensual | B7: 1200000 | C7: Sueldo más lo fijo que recibes cada mes (colación, movilización, cotizaciones). Sin horas extra ni gratificación anual. | E7: Última anualidad | F7: =EDATE(B5,12*F6)
A8: Motivo del término | B8: Necesidades de la empresa (despido art. 161) | E8: Meses desde la última anualidad | F8: =MIN(12,IF(EDATE(F7,((YEAR(B6)-YEAR(F7))*12+MONTH(B6)-MONTH(F7)))>B6,((YEAR(B6)-YEAR(F7))*12+MONTH(B6)-MONTH(F7))-1,((YEAR(B6)-YEAR(F7))*12+MONTH(B6)-MONTH(F7))))
A9: Te avisaron con 30 días o más de anticipación | B9: No | E9: Días sueltos | F9: =B6-EDATE(F7,F8)
A10: Días hábiles de vacaciones de años anteriores sin tomar | B10: 0
A11: Trabajas en Magallanes, Aysén o Palena | B11: No | E11: Indemnizaciones
E12: Tope de la remuneración (90 UF) | F12: =ROUND('Tablas oficiales'!$C$32*'Tablas oficiales'!$C$11,0)
A13: TU FINIQUITO | E13: Base para las indemnizaciones | F13: =MIN(B7,F12)
A14: =IF(B6<B5,"El último día tiene que ser posterior a la fecha en que empezaste.","") | E14: Años que se indemnizan (más de 6 meses suman uno) | F14: =F6+IF(OR(F8>6,AND(F8=6,F9>0)),1,0)
A15: Antigüedad | B15: =F6&" años, "&F8&" meses y "&F9&" días" | E15: Días de indemnización | F15: =IF(AND(B8="Necesidades de la empresa (despido art. 161)",F6>=1),IF(B5<DATE(1981,8,14),F14*'Tablas oficiales'!$C$33,MIN(F14*'Tablas oficiales'!$C$33,'Tablas oficiales'!$C$34)),0)
A16: Base para las indemnizaciones | B16: =F13 | E16: Indemnización por años de servicio | F16: =ROUND(F13*F15/30,0)
A17: Años que se indemnizan | B17: =IF(B8="Necesidades de la empresa (despido art. 161)",F14,0) | E17: Indemnización sustitutiva del aviso previo | F17: =IF(AND(B8="Necesidades de la empresa (despido art. 161)",B9="No"),F13,0)
A18: Indemnización por años de servicio | B18: =F16
A19: Indemnización sustitutiva del aviso previo | B19: =F17 | E19: Vacaciones (feriado)
A20: Días de vacaciones a pagar (corridos) | B20: =F24 | E20: Días hábiles de feriado por año | F20: =IF(B11="Sí",'Tablas oficiales'!$C$35,'Tablas oficiales'!$C$36)
A21: Vacaciones pendientes y proporcionales | B21: =F25 | E21: Días hábiles a pagar | F21: =F20/12*F8+F20/12/30*F9+B10
A22: Total del finiquito | B22: =F16+F17+F25 | E22: Días hábiles que se recorren | F22: =MAX(0,ROUNDUP(F21-0.000000001,0))
E23: Sábados y domingos que se suman | F23: =WORKDAY(B6,F22)-B6-F22
A24: Las vacaciones se cuentan desde el día siguiente a tu salida, sumando sábados y domingos. Si en ese período cae un festivo en día hábil, se suma un día más por cada uno. La indemnización por años tiene tope de 11 años, salvo contratos anteriores al 14 de agosto de 1981. | E24: Días corridos a pagar | F24: =F21+F23
E25: Vacaciones a pagar | F25: =ROUND(B7/30*F24,0)

Sheet Tablas oficiales
A1: Tablas oficiales de Chile
A2: Son los valores que usan las fórmulas de esta planilla, vigentes al 8/10/2026. Cada uno trae el enlace a la norma o al organismo que lo publica y la fecha en que lo verificamos.
A3: Dato | B3: Detalle | C3: Valor | D3: Unidad | E3: Vigente desde | F3: Fuente oficial | G3: Verificado el
A4: Comisión mensual de cada AFP | B4: AFP Capital | C4: 1.44 | D4: % | E4: 1/10/2026 | F4: https://www.spensiones.cl/infoydec | G4: 7/10/2026
A5: Comisión mensual de cada AFP | B5: AFP Cuprum | C5: 1.44 | D5: % | E5: 1/10/2026 | F5: https://www.spensiones.cl/infoydec | G5: 7/10/2026
A6: Comisión mensual de cada AFP | B6: AFP Habitat | C6: 1.27 | D6: % | E6: 1/10/2026 | F6: https://www.spensiones.cl/infoydec | G6: 7/10/2026
A7: Comisión mensual de cada AFP | B7: AFP Modelo | C7: 0.58 | D7: % | E7: 1/10/2026 | F7: https://www.spensiones.cl/infoydec | G7: 7/10/2026
A8: Comisión mensual de cada AFP | B8: AFP PlanVital | C8: 1.16 | D8: % | E8: 1/10/2026 | F8: https://www.spensiones.cl/infoydec | G8: 7/10/2026
A9: Comisión mensual de cada AFP | B9: AFP ProVida | C9: 1.45 | D9: % | E9: 1/10/2026 | F9: https://www.spensiones.cl/infoydec | G9: 7/10/2026
A10: Comisión mensual de cada AFP | B10: AFP Uno | C10: 0.46 | D10: % | E10: 1/10/2026 | F10: https://www.spensiones.cl/infoydec | G10: 7/10/2026
A11: Unidad de Fomento (UF) | B11: Valor al 8/10/2026 | C11: 41122.74 | D11: CLP | E11: 8/10/2026 | F11: https://www.sii.cl/valores_y_fechas/uf/uf2026.htm | G11: 7/10/2026
A12: Unidad Tributaria Mensual (UTM) | B12: Valor al 1/10/2026 | C12: 72151 | D12: CLP | E12: 1/10/2026 | F12: https://www.sii.cl/valores_y_fechas/utm/utm2026.htm | G12: 7/10/2026
A13: Tope imponible mensual para AFP, salud y accidentes del trabajo | C13: 90 | D13: UF | E13: 1/2/2026 | F13: https://www.spensiones.cl/portal/institucional/594/w3-article-16921.html | G13: 7/10/2026
A14: Tope imponible mensual del seguro de cesantía | C14: 135.2 | D14: UF | E14: 1/2/2026 | F14: https://www.spensiones.cl/portal/institucional/594/w3-article-16921.html | G14: 7/10/2026
A15: Cotización obligatoria de pensiones (AFP) | C15: 10 | D15: % | E15: 1/1/2026 | F15: https://www.spensiones.cl/portal/institucional/594/w3-propertyvalue-9897.html | G15: 7/10/2026
A16: Cotización legal de salud | C16: 7 | D16: % | E16: 1/1/2026 | F16: https://www.superdesalud.gob.cl/preguntas-frecuentes/cual-es-la-cotizacion-legal-para-salud-y-en-que-plazo-deben-ser-declaradas-y-pagadas/ | G16: 7/10/2026
A17: Seguro de cesantía a cargo de quien trabaja (contrato indefinido) | C17: 0.6 | D17: % | E17: 1/1/2026 | F17: https://www.spensiones.cl/portal/institucional/594/w3-propertyvalue-9902.html | G17: 7/10/2026
A18: Impuesto Único de Segunda Categoría, tabla mensual | D18: UTM | E18: 1/1/2026 | F18: https://www.sii.cl/valores_y_fechas/impuesto_2da_categoria/impuesto2026.htm | G18: 7/10/2026
B19: Desde | C19: Hasta | D19: Tasa % | E19: Cuota fija
B20: 0 | C20: 13.5 | D20: 0 | E20: 0
B21: 13.5 | C21: 30 | D21: 4 | E21: 0
B22: 30 | C22: 50 | D22: 8 | E22: 0.66
B23: 50 | C23: 70 | D23: 13.5 | E23: 2.26
B24: 70 | C24: 90 | D24: 23 | E24: 4.96
B25: 90 | C25: 120 | D25: 30.4 | E25: 9.56
B26: 120 | C26: 310 | D26: 35 | E26: 18.68
B27: 310 | C27: 1e+15 | D27: 40 | E27: 85.18
A29: Ingreso mínimo mensual (18 a 65 años) | C29: 553553 | D29: CLP | E29: 1/5/2026 | F29: https://www.diariooficial.interior.gob.cl/publicaciones/2026/06/22/44481-B/01/2829298.pdf | G29: 7/10/2026
A30: Gratificación legal del artículo 50 (porcentaje de lo devengado) | C30: 25 | D30: % | E30: 1/1/2026 | F30: https://www.bcn.cl/leychile/navegar?idNorma=207436 | G30: 7/10/2026
A31: Tope anual de la gratificación del artículo 50 | C31: 4.75 | D31: IMM | E31: 1/1/2026 | F31: https://www.bcn.cl/leychile/navegar?idNorma=207436 | G31: 7/10/2026
A32: Tope de la remuneración para indemnizaciones | C32: 90 | D32: UF | E32: 1/1/2026 | F32: https://www.bcn.cl/leychile/navegar?idNorma=207436 | G32: 7/10/2026
A33: Indemnización por años de servicio: días por año | C33: 30 | D33: días | E33: 1/1/2026 | F33: https://www.bcn.cl/leychile/navegar?idNorma=207436 | G33: 7/10/2026
A34: Indemnización por años de servicio: tope de días | C34: 330 | D34: días | E34: 1/1/2026 | F34: https://www.bcn.cl/leychile/navegar?idNorma=207436 | G34: 7/10/2026
A35: Feriado anual en Magallanes, Aysén y Palena | C35: 20 | D35: días | E35: 1/1/2026 | F35: https://www.bcn.cl/leychile/navegar?idNorma=207436 | G35: 7/10/2026
A36: Feriado anual (vacaciones legales) | C36: 15 | D36: días | E36: 1/1/2026 | F36: https://www.bcn.cl/leychile/navegar?idNorma=207436 | G36: 7/10/2026
