Workbook

Sheet Instrucciones
A1: Planilla de salario y prestaciones Guatemala 2026
A3: 1 | B3: Las celdas amarillas son para sus datos. Las verdes se calculan solas, con las fórmulas de la ley. A la derecha de cada hoja está el paso a paso de la cuenta.
A4: 2 | B4: «ISR de su salario»: pone su salario, bonificaciones e IGSS, y le dice el ISR del año y la retención de cada mes.
A5: 3 | B5: «Aguinaldo y Bono 14»: calcula el aguinaldo de diciembre y enero y el Bono 14 de julio, completos o proporcionales si dejó de trabajar.
A6: 4 | B6: «Indemnización»: pone sus fechas, su salario promedio y cómo terminó la relación, y le dice la indemnización, el aguinaldo, el Bono 14 y las vacaciones.
A7: 5 | B7: «Tablas oficiales» tiene cada valor oficial que usan las fórmulas, con el enlace a su fuente y la fecha en que lo verificamos. Los valores son los vigentes al 8/10/2026.
A8: 6 | B8: Cuando cambia un valor oficial, actualizamos la planilla y el mismo enlace de descarga le baja la versión nueva.
A10: Da los mismos números que las calculadoras gratuitas de calcularya.com. Antes de publicar cada versión, una verificación automática recalcula este archivo y lo compara con ellas.
A11: Es una referencia de cálculo con sus fuentes, no asesoría legal. Su contrato o su empresa pueden darle más que el mínimo de ley.
A12: Las fechas van como dd/mm/aaaa. Si su Excel está en inglés y las lee al revés, escríbalas como aaaa-mm-dd.

Sheet ISR de su salario
A1: ISR de rentas del trabajo
E3: Paso a paso
A4: SUS DATOS | E4: Renta del año | F4: =(B5+B6)*B8
A5: Salario mensual | B5: 12000 | C5: Su salario ordinario más horas extra, comisiones y otros pagos fijos del mes. | E5: Deducciones del año | F5: ='Tablas oficiales'!$C$4+'Tablas oficiales'!$C$5+B7*B8+MIN(B9,'Tablas oficiales'!$C$6)
A6: Bonificaciones mensuales | B6: 250 | C6: La bonificación incentivo y otras bonificaciones. Pagan ISR aunque no paguen IGSS. | E6: Renta imponible | F6: =ROUND(MAX(0,F4-F5),2)
A7: Descuento mensual del IGSS | B7: 580 | C7: Cópielo de su recibo de pago o boleta. | E7: ISR del año | F7: =ROUND(IF(F6<=0,0,INDEX('Tablas oficiales'!$E$9:$E$10,IFERROR(MATCH(F6,'Tablas oficiales'!$B$9:$B$10,1),1))+(F6-INDEX('Tablas oficiales'!$B$9:$B$10,IFERROR(MATCH(F6,'Tablas oficiales'!$B$9:$B$10,1),1)))*INDEX('Tablas oficiales'!$D$9:$D$10,IFERROR(MATCH(F6,'Tablas oficiales'!$B$9:$B$10,1),1))/100),2)
A8: Meses que va a trabajar este año | B8: 12
A9: IVA de sus facturas del año (planilla del IVA) | B9: 0 | C9: El IVA de sus compras personales con factura a su NIT. Déjelo en cero si no presenta la planilla.
A11: SU ISR
A12: =IF(B7>B5,"El descuento del IGSS no puede ser mayor que el salario.","")
A13: Renta del año | B13: =ROUND(F4,2)
A14: Deducciones del año | B14: =ROUND(F5,2)
A15: Renta imponible | B15: =F6
A16: ISR del año | B16: =F7
A17: Retención de cada mes | B17: =ROUND(F7/B8,2)
A19: El aguinaldo y el Bono 14 no pagan ISR (hasta un salario cada uno), por eso no se suman. La planilla del IVA tiene un tope.

Sheet Aguinaldo y Bono 14
A1: Aguinaldo y Bono 14
E3: Paso a paso
A4: SUS DATOS | E4: Aguinaldo: cierre del período | F4: =IF(B11="Lo que le toca porque dejó de trabajar",B7,DATE(IF(MONTH(B8)=1,YEAR(B8)-1,YEAR(B8)),11,30))
A5: Salario ordinario mensual | B5: 4500 | C5: Sin la bonificación incentivo ni horas extra. | E5: Aguinaldo: días del período | F5: =MIN(365,F4-MAX(B6,DATE(IF(MONTH(F4)>=12,YEAR(F4),YEAR(F4)-1),12,1))+1)
A6: Fecha en que empezó a trabajar | B6: 45352 | E6: Aguinaldo | F6: =ROUND(B5*'Tablas oficiales'!$C$12/100*F5/365,2)
A7: Último día de trabajo (opcional) | C7: Solo si dejó de trabajar. | E7: Aguinaldo en diciembre | F7: =IF(B11="Lo que le toca porque dejó de trabajar","",ROUND(F6*'Tablas oficiales'!$C$13/100,2))
A8: Fecha de hoy | B8: =TODAY() | C8: Se llena sola. Sirve para saber qué período se paga. | E8: Bono 14: cierre del período | F8: =IF(B21="Lo que le toca porque dejó de trabajar",B7,DATE(IF(MONTH(B8)<=7,YEAR(B8),YEAR(B8)+1),6,30))
E9: Bono 14: días del período | F9: =MIN(365,F8-MAX(B6,DATE(IF(MONTH(F8)>=7,YEAR(F8),YEAR(F8)-1),7,1))+1)
A10: AGUINALDO
A11: Qué quiere calcular | B11: El aguinaldo de diciembre y enero
A12: =IF(AND(B11="Lo que le toca porque dejó de trabajar",NOT(ISNUMBER(B7))),"Indique su último día de trabajo.",IF(B6>F4,"La fecha de ingreso no puede ser posterior al cierre del período.",""))
A13: Días que cuentan | B13: =F5
A14: Aguinaldo | B14: =F6
A15: Se paga en diciembre | B15: =F7
A16: Se paga en enero | B16: =IF(B11="Lo que le toca porque dejó de trabajar","",ROUND(F6-F7,2))
A18: El aguinaldo es un salario por año, del 1 de diciembre al 30 de noviembre. La mitad se paga en la primera quincena de diciembre y el resto en la segunda de enero.
A20: BONO 14
A21: Qué quiere calcular | B21: El Bono 14 que se paga en julio
A22: =IF(AND(B21="Lo que le toca porque dejó de trabajar",NOT(ISNUMBER(B7))),"Indique su último día de trabajo.",IF(B6>F8,"La fecha de ingreso no puede ser posterior al cierre del período.",""))
A23: Días que cuentan | B23: =F9
A24: Bono 14 | B24: =ROUND(B5*'Tablas oficiales'!$C$14/100*F9/365,2)
A26: El Bono 14 es un salario por año, del 1 de julio al 30 de junio, y se paga en la primera quincena de julio.

Sheet Indemnización
A1: Indemnización y prestaciones al terminar
E3: Paso a paso
A4: SUS DATOS
A5: Fecha en que empezó a trabajar | B5: 44317 | E5: Indemnización
A6: Último día de trabajo | B6: 46303 | E6: Días de servicio | F6: =B6-B5+1
A7: Cómo terminó la relación laboral | B7: Lo despidieron sin causa justa | E7: Salario indemnizable (con un sexto de aguinaldo y Bono 14) | F7: =ROUND(B8+B8*'Tablas oficiales'!$C$12/100/12+B8*'Tablas oficiales'!$C$14/100/12,2)
A8: Promedio de su salario de los últimos seis meses | B8: 5000 | C8: Con horas extra y sin la bonificación incentivo. Sume los seis meses y divida entre seis. | E8: Indemnización | F8: =IF(OR(B7="Lo despidieron sin causa justa",B7="Renunció por una falta grave del patrono"),ROUND(F7*'Tablas oficiales'!$C$15*F6/365,2),0)
A9: Días de vacaciones de años anteriores que no gozó | B9: 0
E10: Prestaciones proporcionales
A11: SU LIQUIDACIÓN | E11: Aguinaldo: días del período | F11: =MIN(365,B6-MAX(B5,DATE(IF(MONTH(B6)>=12,YEAR(B6),YEAR(B6)-1),12,1))+1)
A12: =IF(B5>B6,"La fecha de ingreso no puede ser posterior a la de salida.","") | E12: Bono 14: días del período | F12: =MIN(365,B6-MAX(B5,DATE(IF(MONTH(B6)>=7,YEAR(B6),YEAR(B6)-1),7,1))+1)
A13: Días de servicio | B13: =F6 | E13: Aguinaldo proporcional | F13: =ROUND(B8*'Tablas oficiales'!$C$12/100*F11/365,2)
A14: Salario indemnizable | B14: =F7 | E14: Bono 14 proporcional | F14: =ROUND(B8*'Tablas oficiales'!$C$14/100*F12/365,2)
A15: Indemnización por tiempo servido | B15: =F8 | E15: Años cumplidos | F15: =IF(AND((YEAR(B6)-YEAR(B5))>0,DATE(YEAR(B5)+(YEAR(B6)-YEAR(B5)),MONTH(B5),MIN(DAY(B5),DAY(EOMONTH(DATE(YEAR(B5)+(YEAR(B6)-YEAR(B5)),MONTH(B5),1),0))))>B6),(YEAR(B6)-YEAR(B5))-1,(YEAR(B6)-YEAR(B5)))
A16: Aguinaldo proporcional | B16: =F13 | E16: Días desde el último aniversario | F16: =MIN(365,B6-DATE(YEAR(B5)+F15,MONTH(B5),MIN(DAY(B5),DAY(EOMONTH(DATE(YEAR(B5)+F15,MONTH(B5),1),0))))+1)
A17: Bono 14 proporcional | B17: =F14 | E17: Días de vacaciones | F17: =ROUND('Tablas oficiales'!$C$16*F16/365+B9,2)
A18: Días de vacaciones a pagar | B18: =F17 | E18: Vacaciones | F18: =ROUND(B8/30*F17,2)
A19: Vacaciones | B19: =F18
A20: Total | B20: =ROUND(F8+F13+F14+F18,2)
A22: La indemnización se calcula con su promedio más la sexta parte del aguinaldo y del Bono 14, como se aplica en la práctica. Si renunció o lo despidieron con causa justa, no hay indemnización, pero sí las prestaciones.

Sheet Tablas oficiales
A1: Tablas oficiales de Guatemala
A2: Son los valores que usan las fórmulas de esta planilla, vigentes al 8/10/2026. Cada uno trae el enlace a la norma o al organismo que lo publica y la fecha en que lo verificamos.
A3: Dato | B3: Detalle | C3: Valor | D3: Unidad | E3: Vigente desde | F3: Fuente oficial | G3: Verificado el
A4: Deducción anual por gastos personales sin comprobar | C4: 48000 | D4: GTQ | E4: 1/1/2013 | F4: https://www.congreso.gob.gt/assets/uploads/info_legislativo/decretos/2012/010-2012.pdf | G4: 7/10/2026
A5: Deducción extraordinaria del ISR de 2026 | C5: 3024 | D5: GTQ | E5: 23/5/2026 | F5: https://www.congreso.gob.gt/assets/uploads/info_legislativo/decretos/3bcf4-13-2026.pdf | G5: 7/10/2026
A6: Crédito máximo por la planilla del IVA | C6: 12000 | D6: GTQ | E6: 1/1/2013 | F6: https://www.congreso.gob.gt/assets/uploads/info_legislativo/decretos/2012/010-2012.pdf | G6: 7/10/2026
A7: ISR de rentas del trabajo: escala anual | D7: GTQ | E7: 1/1/2013 | F7: https://www.congreso.gob.gt/assets/uploads/info_legislativo/decretos/2012/010-2012.pdf | G7: 7/10/2026
B8: Desde | C8: Hasta | D8: Tasa % | E8: Cuota fija
B9: 0 | C9: 300000 | D9: 5 | E9: 0
B10: 300000 | C10: 1e+15 | D10: 7 | E10: 15000
A12: Aguinaldo por año de servicios | C12: 100 | D12: % | E12: 30/11/1978 | F12: https://mintrabajo.gob.gt/wp-content/uploads/2026/06/Ley-Reguladora-del-Aguinaldo-Decreto-76-78.pdf | G12: 7/10/2026
A13: Parte del aguinaldo que se paga en diciembre | C13: 50 | D13: % | E13: 30/11/1978 | F13: https://mintrabajo.gob.gt/wp-content/uploads/2026/06/Ley-Reguladora-del-Aguinaldo-Decreto-76-78.pdf | G13: 7/10/2026
A14: Bono 14 por año de servicios | C14: 100 | D14: % | E14: 2/7/1992 | F14: https://mintrabajo.gob.gt/wp-content/uploads/2026/06/Ley-de-Bonificacion-Anual-para-Trabajadores-del-Sector-Privado-y-Publico-Decreto-42-92.pdf | G14: 7/10/2026
A15: Indemnización por tiempo servido, meses de salario por año | C15: 1 | D15: meses | E15: 1/10/2024 | F15: https://mintrabajo.gob.gt/wp-content/uploads/2026/06/Codigo-de-Trabajo.pdf | G15: 7/10/2026
A16: Vacaciones mínimas por año de trabajo | C16: 15 | D16: días | E16: 1/10/2024 | F16: https://mintrabajo.gob.gt/wp-content/uploads/2026/06/Codigo-de-Trabajo.pdf | G16: 7/10/2026
