Workbook

Sheet Instrucciones
A1: Planilla de salario y liquidación Costa Rica 2026
A3: 1 | B3: Las celdas amarillas son para sus datos. Las verdes se calculan solas, con las fórmulas de la ley. A la derecha de cada hoja está el paso a paso de la cuenta.
A4: 2 | B4: «Salario neto»: pone su salario bruto y le dice las cuotas de la Caja, el aporte al Banco Popular, el impuesto al salario y su salario neto.
A5: 3 | B5: «Aguinaldo»: calcula el aguinaldo de diciembre, completo o proporcional.
A6: 4 | B6: «Liquidación»: pone sus fechas, su salario y cómo terminó la relación, y le dice el preaviso, la cesantía, las vacaciones y el aguinaldo proporcional.
A7: 5 | B7: «Tablas oficiales» tiene cada valor oficial que usan las fórmulas, con el enlace a su fuente y la fecha en que lo verificamos. Los valores son los vigentes al 8/10/2026.
A8: 6 | B8: Cuando cambia un valor oficial, actualizamos la planilla y el mismo enlace de descarga le baja la versión nueva.
A10: Da los mismos números que las calculadoras gratuitas de calcularya.com. Antes de publicar cada versión, una verificación automática recalcula este archivo y lo compara con ellas.
A11: Es una referencia de cálculo con sus fuentes, no asesoría legal. Su contrato o su empresa pueden darle más que el mínimo de ley.
A12: Las fechas van como dd/mm/aaaa. Si su Excel está en inglés y las lee al revés, escríbalas como aaaa-mm-dd.

Sheet Salario neto
A1: Salario neto: cargas sociales e impuesto al salario
E3: Paso a paso
A4: SUS DATOS
A5: Salario bruto mensual | B5: 1200000 | C5: Lo que dice el contrato, antes de rebajos. | E5: Cargas sociales
A6: Hijos que declara para el crédito fiscal | B6: 0 | E6: Seguro de Salud (SEM) | F6: =ROUND(B5*'Tablas oficiales'!$C$4/100,2)
A7: Declara el crédito por cónyuge | B7: No | E7: Invalidez, Vejez y Muerte (IVM) | F7: =ROUND(B5*'Tablas oficiales'!$C$5/100,2)
E8: Banco Popular | F8: =ROUND(B5*'Tablas oficiales'!$C$6/100,2)
A9: SU SALARIO NETO | E9: Total de cargas sociales | F9: =ROUND(F6+F7+F8,2)
A10: Seguro de Salud (SEM) | B10: =F6
A11: Invalidez, Vejez y Muerte (IVM) | B11: =F7 | E11: Impuesto al salario
A12: Banco Popular | B12: =F8 | E12: Impuesto por tramos: tramo 1 | F12: =MAX(0,MIN(B5,'Tablas oficiales'!$C$9)-'Tablas oficiales'!$B$9)*'Tablas oficiales'!$D$9/100
A13: Total de cargas sociales | B13: =F9 | E13: Impuesto por tramos: tramo 2 | F13: =MAX(0,MIN(B5,'Tablas oficiales'!$C$10)-'Tablas oficiales'!$B$10)*'Tablas oficiales'!$D$10/100
A14: Impuesto al salario | B14: =F19 | E14: Impuesto por tramos: tramo 3 | F14: =MAX(0,MIN(B5,'Tablas oficiales'!$C$11)-'Tablas oficiales'!$B$11)*'Tablas oficiales'!$D$11/100
A15: Salario neto | B15: =ROUND(B5-F9-F19,2) | E15: Impuesto por tramos: tramo 4 | F15: =MAX(0,MIN(B5,'Tablas oficiales'!$C$12)-'Tablas oficiales'!$B$12)*'Tablas oficiales'!$D$12/100
E16: Impuesto por tramos: tramo 5 | F16: =MAX(0,MIN(B5,'Tablas oficiales'!$C$13)-'Tablas oficiales'!$B$13)*'Tablas oficiales'!$D$13/100
A17: El impuesto se calcula sobre el salario bruto: las cuotas de la Caja no se restan antes. | E17: Impuesto por tramos: total | F17: =SUM(F12,F13,F14,F15,F16)
E18: Créditos fiscales | F18: =B6*'Tablas oficiales'!$C$15+IF(B7="Sí",'Tablas oficiales'!$C$16,0)
E19: Impuesto al salario | F19: =MAX(0,ROUND(F17-F18,2))

Sheet Aguinaldo
A1: Aguinaldo
E3: Paso a paso
A4: SUS DATOS | E4: Total devengado en el período | F4: =ROUND(B5*B6+IF(ISNUMBER(B7),B7,0),2)
A5: Salario bruto mensual | B5: 600000 | C5: Sin rebajos. Si su salario cambió durante el año, use el promedio.
A6: Meses trabajados entre el 1 de diciembre y el 30 de noviembre | B6: 12 | C6: Puede usar decimales: medio mes es 0,5.
A7: Horas extra, comisiones y bonos del mismo período (opcional) | C7: Si no tuvo, déjelo vacío.
A9: SU AGUINALDO
A10: Total devengado en el período | B10: =F4
A11: Aguinaldo | B11: =IF(B6>=1,ROUND(F4/12,2),0)
A13: Se paga en los primeros 20 días de diciembre. No paga impuesto sobre la renta ni cuotas de la Caja, así que se recibe completo. Con menos de un mes trabajado no hay aguinaldo.

Sheet Liquidación
A1: Liquidación: preaviso, cesantía, vacaciones y aguinaldo
E3: Paso a paso
A4: SUS DATOS | E4: Tiempo trabajado: años completos | F4: =IF(EDATE(B6,12*(YEAR((B7+1))-YEAR(B6)))>(B7+1),(YEAR((B7+1))-YEAR(B6))-1,(YEAR((B7+1))-YEAR(B6)))
A5: Salario promedio mensual de los últimos seis meses | B5: 600000 | C5: Bruto, con horas extra y comisiones incluidas. | E5: Tiempo trabajado: último aniversario | F5: =EDATE(B6,12*F4)
A6: Fecha de ingreso | B6: 44621 | E6: Tiempo trabajado: meses | F6: =MIN(12,IF(EDATE(F5,((YEAR((B7+1))-YEAR(F5))*12+MONTH((B7+1))-MONTH(F5)))>(B7+1),((YEAR((B7+1))-YEAR(F5))*12+MONTH((B7+1))-MONTH(F5))-1,((YEAR((B7+1))-YEAR(F5))*12+MONTH((B7+1))-MONTH(F5))))
A7: Último día de trabajo | B7: 46303 | E7: Tiempo trabajado: días | F7: =(B7+1)-EDATE(F5,F6)
A8: Cómo terminó la relación laboral | B8: Despido sin justa causa (con responsabilidad patronal)
A9: El patrono le avisó del despido con la anticipación de ley | B9: No | C9: Si lo despidieron de un día para otro, marque que no. | E9: Preaviso y cesantía
A10: Días de vacaciones que no disfrutó | B10: 0 | C10: Si no lo sabe, cuente un día por cada mes trabajado desde sus últimas vacaciones. | E10: Días de preaviso | F10: =IF(AND(B8="Despido sin justa causa (con responsabilidad patronal)",B9="No"),IF(F4=0,IF(F6<3,0,IF(OR(F6>6,AND(F6=6,F7>0)),'Tablas oficiales'!$C$18,'Tablas oficiales'!$C$17)),IF(AND(F4=1,F6=0,F7=0),'Tablas oficiales'!$C$18,'Tablas oficiales'!$C$19)),0)
A11: Salarios ganados desde el 1 de diciembre (opcional) | C11: Si lo deja vacío, se estima con su salario promedio. | E11: Años computables (más de seis meses suman uno) | F11: =F4+IF(OR(F6>6,AND(F6=6,F7>0)),1,0)
E12: Días de cesantía | F12: =IF(B8="Despido sin justa causa (con responsabilidad patronal)",IF(F4=0,IF(F6<3,0,IF(OR(F6>6,AND(F6=6,F7>0)),'Tablas oficiales'!$C$21,'Tablas oficiales'!$C$20)),CHOOSE(MIN(F11,13),'Tablas oficiales'!$C$22,'Tablas oficiales'!$C$23,'Tablas oficiales'!$C$24,'Tablas oficiales'!$C$25,'Tablas oficiales'!$C$26,'Tablas oficiales'!$C$27,'Tablas oficiales'!$C$28,'Tablas oficiales'!$C$29,'Tablas oficiales'!$C$30,'Tablas oficiales'!$C$31,'Tablas oficiales'!$C$32,'Tablas oficiales'!$C$33,'Tablas oficiales'!$C$34)*MIN(F11,'Tablas oficiales'!$C$35)),0)
A13: SU LIQUIDACIÓN | E13: Salario diario | F13: =B5/'Tablas oficiales'!$C$36
A14: =IF(B7<B6,"La fecha de salida tiene que ser igual o posterior a la de ingreso.","")
A15: Tiempo trabajado | B15: =F4&" años, "&F6&" meses y "&F7&" días" | E15: Aguinaldo proporcional
A16: Salario diario | B16: =ROUND(F13,2) | E16: Período del aguinaldo: años completos | F16: =IF(EDATE(MAX(B6,IF(MONTH(B7)=12,DATE(YEAR(B7),12,1),DATE(YEAR(B7)-1,12,1))),12*(YEAR((B7+1))-YEAR(MAX(B6,IF(MONTH(B7)=12,DATE(YEAR(B7),12,1),DATE(YEAR(B7)-1,12,1))))))>(B7+1),(YEAR((B7+1))-YEAR(MAX(B6,IF(MONTH(B7)=12,DATE(YEAR(B7),12,1),DATE(YEAR(B7)-1,12,1)))))-1,(YEAR((B7+1))-YEAR(MAX(B6,IF(MONTH(B7)=12,DATE(YEAR(B7),12,1),DATE(YEAR(B7)-1,12,1))))))
A17: Días de preaviso | B17: =F10 | E17: Período del aguinaldo: último aniversario | F17: =EDATE(MAX(B6,IF(MONTH(B7)=12,DATE(YEAR(B7),12,1),DATE(YEAR(B7)-1,12,1))),12*F16)
A18: Preaviso | B18: =F22 | E18: Período del aguinaldo: meses | F18: =MIN(12,IF(EDATE(F17,((YEAR((B7+1))-YEAR(F17))*12+MONTH((B7+1))-MONTH(F17)))>(B7+1),((YEAR((B7+1))-YEAR(F17))*12+MONTH((B7+1))-MONTH(F17))-1,((YEAR((B7+1))-YEAR(F17))*12+MONTH((B7+1))-MONTH(F17))))
A19: Días de cesantía | B19: =F12 | E19: Período del aguinaldo: días | F19: =(B7+1)-EDATE(F17,F18)
A20: Cesantía | B20: =F23 | E20: Meses en el período del aguinaldo | F20: =MIN(12,F16*12+F18+F19/30)
A21: Vacaciones no disfrutadas | B21: =F24 | E21: Salarios del período | F21: =IF(ISNUMBER(B11),B11,B5*F20)
A22: Aguinaldo proporcional | B22: =F25 | E22: Preaviso | F22: =ROUND(F13*F10,2)
A23: Total de la liquidación | B23: =ROUND(F22+F23+F24+F25,2) | E23: Cesantía | F23: =ROUND(F13*F12,2)
E24: Vacaciones | F24: =ROUND(F13*B10,2)
A25: La cesantía se paga por 8 años como máximo. Si renunció sin dar el preaviso, el patrono puede rebajarlo de la liquidación. Las vacaciones se calculan con el salario promedio entre 30: la ley usa el promedio de las últimas 50 semanas. | E25: Aguinaldo | F25: =IF(F4*12+F6>=1,ROUND(F21/12,2),0)

Sheet Tablas oficiales
A1: Tablas oficiales de Costa Rica
A2: Son los valores que usan las fórmulas de esta planilla, vigentes al 8/10/2026. Cada uno trae el enlace a la norma o al organismo que lo publica y la fecha en que lo verificamos.
A3: Dato | B3: Detalle | C3: Valor | D3: Unidad | E3: Vigente desde | F3: Fuente oficial | G3: Verificado el
A4: Cuota del trabajador al Seguro de Salud (SEM) | C4: 5.5 | D4: % | E4: 1/1/2026 | F4: https://sinalevi.go.cr/ResultadosNormativa/Informacion?param1=43463&param2=146812&param3=1 | G4: 7/10/2026
A5: Cuota del trabajador al Seguro de Invalidez, Vejez y Muerte (IVM) | C5: 4.33 | D5: % | E5: 1/1/2026 | F5: https://www.imprentanacional.go.cr/pub/2019/08/28/ALCA191_28_08_2019.pdf | G5: 7/10/2026
A6: Aporte del trabajador al Banco Popular | C6: 1 | D6: % | E6: 1/1/2026 | F6: https://sinalevi.go.cr/ResultadosNormativa/Informacion?param1=35582&param2=130484&param3=1 | G6: 7/10/2026
A7: Impuesto al salario, tramos mensuales | D7: CRC | E7: 1/1/2026 | F7: https://sinalevi.go.cr/ResultadosNormativa/Informacion?param1=105834&param2=148657&param3=1 | G7: 7/10/2026
B8: Desde | C8: Hasta | D8: Tasa % | E8: Cuota fija
B9: 0 | C9: 918000 | D9: 0 | E9: 0
B10: 918000 | C10: 1347000 | D10: 10 | E10: 0
B11: 1347000 | C11: 2364000 | D11: 15 | E11: 0
B12: 2364000 | C12: 4727000 | D12: 20 | E12: 0
B13: 4727000 | C13: 1e+15 | D13: 25 | E13: 0
A15: Crédito fiscal mensual por cada hijo | C15: 1710 | D15: CRC | E15: 1/1/2026 | F15: https://sinalevi.go.cr/ResultadosNormativa/Informacion?param1=105834&param2=148657&param3=1 | G15: 7/10/2026
A16: Crédito fiscal mensual por el cónyuge | C16: 2590 | D16: CRC | E16: 1/1/2026 | F16: https://sinalevi.go.cr/ResultadosNormativa/Informacion?param1=105834&param2=148657&param3=1 | G16: 7/10/2026
A17: Días de preaviso según el tiempo trabajado | B17: De 3 a 6 meses | C17: 7 | D17: días | E17: 1/1/2026 | F17: https://sinalevi.go.cr/ResultadosNormativa/Informacion?param1=8045&param2=151754&param3=1 | G17: 7/10/2026
A18: Días de preaviso según el tiempo trabajado | B18: Más de 6 meses y hasta un año | C18: 15 | D18: días | E18: 1/1/2026 | F18: https://sinalevi.go.cr/ResultadosNormativa/Informacion?param1=8045&param2=151754&param3=1 | G18: 7/10/2026
A19: Días de preaviso según el tiempo trabajado | B19: Más de un año | C19: 30 | D19: días | E19: 1/1/2026 | F19: https://sinalevi.go.cr/ResultadosNormativa/Informacion?param1=8045&param2=151754&param3=1 | G19: 7/10/2026
A20: Días de cesantía con menos de un año trabajado | B20: 3-a-6-meses | C20: 7 | D20: días | E20: 1/1/2026 | F20: https://sinalevi.go.cr/ResultadosNormativa/Informacion?param1=8045&param2=151754&param3=1 | G20: 7/10/2026
A21: Días de cesantía con menos de un año trabajado | B21: 6-a-12-meses | C21: 14 | D21: días | E21: 1/1/2026 | F21: https://sinalevi.go.cr/ResultadosNormativa/Informacion?param1=8045&param2=151754&param3=1 | G21: 7/10/2026
A22: Días de cesantía por año laborado según la antigüedad | B22: 1 | C22: 19.5 | D22: días | E22: 1/1/2026 | F22: https://sinalevi.go.cr/ResultadosNormativa/Informacion?param1=8045&param2=151754&param3=1 | G22: 7/10/2026
A23: Días de cesantía por año laborado según la antigüedad | B23: 2 | C23: 20 | D23: días | E23: 1/1/2026 | F23: https://sinalevi.go.cr/ResultadosNormativa/Informacion?param1=8045&param2=151754&param3=1 | G23: 7/10/2026
A24: Días de cesantía por año laborado según la antigüedad | B24: 3 | C24: 20.5 | D24: días | E24: 1/1/2026 | F24: https://sinalevi.go.cr/ResultadosNormativa/Informacion?param1=8045&param2=151754&param3=1 | G24: 7/10/2026
A25: Días de cesantía por año laborado según la antigüedad | B25: 4 | C25: 21 | D25: días | E25: 1/1/2026 | F25: https://sinalevi.go.cr/ResultadosNormativa/Informacion?param1=8045&param2=151754&param3=1 | G25: 7/10/2026
A26: Días de cesantía por año laborado según la antigüedad | B26: 5 | C26: 21.24 | D26: días | E26: 1/1/2026 | F26: https://sinalevi.go.cr/ResultadosNormativa/Informacion?param1=8045&param2=151754&param3=1 | G26: 7/10/2026
A27: Días de cesantía por año laborado según la antigüedad | B27: 6 | C27: 21.5 | D27: días | E27: 1/1/2026 | F27: https://sinalevi.go.cr/ResultadosNormativa/Informacion?param1=8045&param2=151754&param3=1 | G27: 7/10/2026
A28: Días de cesantía por año laborado según la antigüedad | B28: 7 | C28: 22 | D28: días | E28: 1/1/2026 | F28: https://sinalevi.go.cr/ResultadosNormativa/Informacion?param1=8045&param2=151754&param3=1 | G28: 7/10/2026
... A34: Días de cesantía por año laborado según la antigüedad | B34: 13 | C34: 20 | D34: días | E34: 1/1/2026 | F34: https://sinalevi.go.cr/ResultadosNormativa/Informacion?param1=8045&param2=151754&param3=1 | G34: 7/10/2026
A35: Años máximos que se indemnizan por cesantía | C35: 8 | D35: años | E35: 1/1/2026 | F35: https://sinalevi.go.cr/ResultadosNormativa/Informacion?param1=8045&param2=151754&param3=1 | G35: 7/10/2026
A36: Días que paga un salario mensual | C36: 30 | D36: días | E36: 1/1/2026 | F36: https://sinalevi.go.cr/ResultadosNormativa/Informacion?param1=105838&param2=148681&param3=1 | G36: 7/10/2026
