Workbook

Sheet Instrucciones
A1: Planilla de sueldo y finiquito Bolivia 2026
A3: 1 | B3: Las celdas amarillas son para sus datos. Las verdes se calculan solas, con las fórmulas de la ley. A la derecha de cada hoja está el paso a paso de la cuenta.
A4: 2 | B4: «Sueldo líquido»: pone su total ganado y le dice los aportes laborales, el Aporte Nacional Solidario, el RC-IVA y su líquido pagable.
A5: 3 | B5: «Aguinaldo»: calcula el aguinaldo de la gestión, completo o en duodécimas si entró o salió este año.
A6: 4 | B6: «Finiquito»: pone sus fechas, su promedio y cómo terminó el trabajo, y le dice la indemnización, el desahucio, el aguinaldo y las vacaciones.
A7: 5 | B7: «Tablas oficiales» tiene cada valor oficial que usan las fórmulas, con el enlace a su fuente y la fecha en que lo verificamos. Los valores son los vigentes al 13/10/2026.
A8: 6 | B8: Cuando cambia un valor oficial, actualizamos la planilla y el mismo enlace de descarga le baja la versión nueva.
A10: Da los mismos números que las calculadoras gratuitas de calcularya.com. Antes de publicar cada versión, una verificación automática recalcula este archivo y lo compara con ellas.
A11: Es una referencia de cálculo con sus fuentes, no asesoría legal. Su contrato o su empresa pueden darle más que el mínimo de ley.
A12: Las fechas van como dd/mm/aaaa. Si su Excel está en inglés y las lee al revés, escríbalas como aaaa-mm-dd.

Sheet Sueldo líquido
A1: Sueldo líquido: aportes a la Gestora y RC-IVA
E3: Paso a paso
A4: SUS DATOS
A5: Total ganado del mes | B5: 9000 | C5: Haber básico más bono de antigüedad, horas extras, comisiones y otros pagos del mes. | E5: Aportes laborales
A6: Facturas que presenta en el Formulario 110 (opcional) | C6: La suma de sus facturas del mes. Solo cuenta si paga RC-IVA. | E6: Cotización mensual | F6: =ROUND(B5*'Tablas oficiales'!$C$4/100,2)
E7: Prima de riesgo común | F7: =ROUND(B5*'Tablas oficiales'!$C$5/100,2)
A8: SU LÍQUIDO PAGABLE | E8: Comisión de la Gestora | F8: =ROUND(B5*'Tablas oficiales'!$C$6/100,2)
A9: Cotización mensual (10 %) | B9: =F6 | E9: Aporte solidario | F9: =ROUND(B5*'Tablas oficiales'!$C$7/100,2)
A10: Prima de riesgo común | B10: =F7 | E10: Total a la Gestora | F10: =ROUND(F6+F7+F8+F9,2)
A11: Comisión de la Gestora | B11: =F8 | E11: Aporte Nacional Solidario | F11: =ROUND(ROUND(MAX(0,B5-'Tablas oficiales'!$C$11)*'Tablas oficiales'!$C$8/100,2)+ROUND(MAX(0,B5-'Tablas oficiales'!$C$12)*'Tablas oficiales'!$C$9/100,2)+ROUND(MAX(0,B5-'Tablas oficiales'!$C$13)*'Tablas oficiales'!$C$10/100,2),2)
A12: Aporte solidario | B12: =F9 | E12: Sueldo neto (menos aportes) | F12: =ROUND(B5-ROUND(F10+F11,2),2)
A13: Total a la Gestora | B13: =F10
A14: Aporte Nacional Solidario | B14: =F11 | E14: RC-IVA
A15: RC-IVA | B15: =F19 | E15: Base imponible (menos dos salarios mínimos) | F15: =ROUND(MAX(0,F12-ROUND('Tablas oficiales'!$C$14*'Tablas oficiales'!$C$16,2)),2)
A16: Líquido pagable | B16: =ROUND(F12-F19,2) | E16: Impuesto (13 %) | F16: =ROUND(F15*'Tablas oficiales'!$C$15/100,2)
A17: Saldo a favor para el mes siguiente | B17: =ROUND(MAX(0,F18-F17),2) | E17: Impuesto menos el 13 % de un salario mínimo | F17: =ROUND(MAX(0,F16-ROUND('Tablas oficiales'!$C$14*'Tablas oficiales'!$C$17*'Tablas oficiales'!$C$15/100,2)),2)
E18: Crédito por facturas | F18: =ROUND(IF(ISNUMBER(B6),B6,0)*'Tablas oficiales'!$C$15/100,2)
A19: Si le descuentan otros conceptos (anticipos, cuota sindical), réstelos aparte. Con más facturas en el Formulario 110 la retención de RC-IVA baja. | E19: RC-IVA retenido | F19: =ROUND(MAX(0,F17-F18),2)

Sheet Aguinaldo
A1: Aguinaldo de Navidad
E3: Paso a paso
A4: SUS DATOS | E4: Fin del cálculo | F4: =IF(ISNUMBER(B8),B8,DATE(YEAR(B9),12,31))
A5: Usted es | B5: Empleada o empleado | E5: Gestión: meses cumplidos | F5: =IF(EDATE(MAX(B7,DATE(YEAR(F4),1,1)),((YEAR((F4+1))-YEAR(MAX(B7,DATE(YEAR(F4),1,1))))*12+MONTH((F4+1))-MONTH(MAX(B7,DATE(YEAR(F4),1,1)))))>(F4+1),((YEAR((F4+1))-YEAR(MAX(B7,DATE(YEAR(F4),1,1))))*12+MONTH((F4+1))-MONTH(MAX(B7,DATE(YEAR(F4),1,1))))-1,((YEAR((F4+1))-YEAR(MAX(B7,DATE(YEAR(F4),1,1))))*12+MONTH((F4+1))-MONTH(MAX(B7,DATE(YEAR(F4),1,1)))))
A6: Promedio del total ganado de los últimos 3 meses | B6: 6000 | C6: Si es obrero, ponga lo del último mes. | E6: Gestión: años | F6: =INT(F5/12)
A7: Fecha de ingreso | B7: 45762 | E7: Gestión: meses | F7: =MOD(F5,12)
A8: Fecha de retiro, si dejó el trabajo este año (opcional) | C8: Si sigue trabajando, déjela vacía: se calcula la gestión completa. | E8: Gestión: días | F8: =(F4+1)-EDATE(MAX(B7,DATE(YEAR(F4),1,1)),F5)
A9: Fecha de hoy | B9: =TODAY() | C9: Se llena sola. Define la gestión. | E9: Meses mínimos | F9: =IF(B5="Obrera u obrero",'Tablas oficiales'!$C$19,'Tablas oficiales'!$C$18)
A11: SU AGUINALDO
A12: =IF(F4<B7,"Revise las fechas: el ingreso tiene que ser anterior al retiro o al fin de la gestión.","")
A13: Tiempo en la gestión | B13: =F5&" meses y "&F8&" días"
A14: Aguinaldo | B14: =IF(F5>=F9,ROUND(ROUND(B6*0,2)+ROUND(B6/12*F5,2)+ROUND(B6/360*F8,2),2),0)
A16: Se paga entero, sin aportes ni RC-IVA. Para cobrarlo hay que trabajar al menos 3 meses seguidos en la gestión (1 mes si es obrero).

Sheet Finiquito
A1: Finiquito: indemnización, desahucio, aguinaldo y vacaciones
E3: Paso a paso
A4: SUS DATOS | E4: Antigüedad: meses cumplidos | F4: =IF(EDATE(B7,((YEAR(B8)-YEAR(B7))*12+MONTH(B8)-MONTH(B7)))>B8,((YEAR(B8)-YEAR(B7))*12+MONTH(B8)-MONTH(B7))-1,((YEAR(B8)-YEAR(B7))*12+MONTH(B8)-MONTH(B7)))
A5: Cómo terminó el trabajo | B5: Me despidieron sin causa justificada | C5: El artículo 16 es el de la Ley General del Trabajo. | E5: Antigüedad: años | F5: =INT(F4/12)
A6: Promedio del total ganado de los últimos 3 meses | B6: 6000 | C6: Es el salario promedio indemnizable. | E6: Antigüedad: meses | F6: =MOD(F4,12)
A7: Fecha de ingreso | B7: 44398 | E7: Antigüedad: días | F7: =B8-EDATE(B7,F4)
A8: Fecha de retiro | B8: 46308
A9: Días de vacación de gestiones anteriores que no tomó | B9: 0 | E9: Indemnización y desahucio
A10: Quinquenios que ya cobró | B10: 0 | C10: Cada quinquenio cobrado ya pagó la indemnización de 5 años, que se descuentan. | E10: Indemnización | F10: =IF(AND((B8-B7+1)>'Tablas oficiales'!$C$21,B5<>"Me despidieron por una causa del artículo 16"),ROUND(ROUND(B6*(F5-B10*'Tablas oficiales'!$C$20),2)+ROUND(B6/12*F6,2)+ROUND(B6/360*F7,2),2),0)
E11: Desahucio | F11: =IF(AND((B8-B7+1)>'Tablas oficiales'!$C$21,B5="Me despidieron sin causa justificada"),ROUND(B6*'Tablas oficiales'!$C$22,2),0)
A12: SU FINIQUITO
A13: =IF(B8<B7,"La fecha de retiro tiene que ser posterior a la de ingreso.",IF(B10*'Tablas oficiales'!$C$20>F5,"Cobró más quinquenios que los años que trabajó. Revise el dato.","")) | E13: Aguinaldo y vacaciones
A14: Antigüedad | B14: =F5&" años, "&F6&" meses y "&F7&" días" | E14: Gestión: meses cumplidos | F14: =IF(EDATE(MAX(B7,DATE(YEAR(B8),1,1)),((YEAR((B8+1))-YEAR(MAX(B7,DATE(YEAR(B8),1,1))))*12+MONTH((B8+1))-MONTH(MAX(B7,DATE(YEAR(B8),1,1)))))>(B8+1),((YEAR((B8+1))-YEAR(MAX(B7,DATE(YEAR(B8),1,1))))*12+MONTH((B8+1))-MONTH(MAX(B7,DATE(YEAR(B8),1,1))))-1,((YEAR((B8+1))-YEAR(MAX(B7,DATE(YEAR(B8),1,1))))*12+MONTH((B8+1))-MONTH(MAX(B7,DATE(YEAR(B8),1,1)))))
A15: Indemnización por tiempo de servicios | B15: =F10 | E15: Gestión: años | F15: =INT(F14/12)
A16: Desahucio | B16: =F11 | E16: Gestión: meses | F16: =MOD(F14,12)
A17: Aguinaldo en duodécimas | B17: =F18 | E17: Gestión: días | F17: =(B8+1)-EDATE(MAX(B7,DATE(YEAR(B8),1,1)),F14)
A18: Vacaciones de gestiones anteriores | B18: =F20 | E18: Aguinaldo en duodécimas | F18: =IF(F14>='Tablas oficiales'!$C$18,ROUND(ROUND(B6*0,2)+ROUND(B6/12*F14,2)+ROUND(B6/360*F17,2),2),0)
A19: Días de vacación por fracción | B19: =ROUND(F19,2) | E19: Días de vacación por fracción | F19: =IF(F5>=1,IF((F5+1)<=5,'Tablas oficiales'!$C$23,IF((F5+1)<=10,'Tablas oficiales'!$C$24,'Tablas oficiales'!$C$25))/12*F6+IF((F5+1)<=5,'Tablas oficiales'!$C$23,IF((F5+1)<=10,'Tablas oficiales'!$C$24,'Tablas oficiales'!$C$25))/360*F7,0)
A20: Vacación por fracción | B20: =F21 | E20: Vacaciones de gestiones anteriores | F20: =ROUND(B6/30*B9,2)
A21: Total del finiquito | B21: =ROUND(F10+F11+F18+F20+F21,2) | E21: Vacación por fracción | F21: =ROUND(B6/30*F19,2)
A23: Son montos brutos. El empleador tiene 15 días calendario para pagar; si se atrasa, paga un 30 % más. Con 90 días o menos de trabajo no hay indemnización ni desahucio, y el desahucio solo se paga en un despido sin causa.

Sheet Tablas oficiales
A1: Tablas oficiales de Bolivia
A2: Son los valores que usan las fórmulas de esta planilla, vigentes al 13/10/2026. Cada uno trae el enlace a la norma o al organismo que lo publica y la fecha en que lo verificamos.
A3: Dato | B3: Detalle | C3: Valor | D3: Unidad | E3: Vigente desde | F3: Fuente oficial | G3: Verificado el
A4: Aportes del trabajador dependiente al Sistema Integral de Pensiones | B4: Cotización mensual (vejez) | C4: 10 | D4: % | E4: 1/1/2025 | F4: https://media.economiayfinanzas.gob.bo/sites/default/files/2025-10/Bolet%C3%ADn%20SIP_diciembre%202024.pdf | G4: 7/10/2026
A5: Aportes del trabajador dependiente al Sistema Integral de Pensiones | B5: Prima por riesgo común | C5: 1.71 | D5: % | E5: 1/1/2025 | F5: https://media.economiayfinanzas.gob.bo/sites/default/files/2025-10/Bolet%C3%ADn%20SIP_diciembre%202024.pdf | G5: 7/10/2026
A6: Aportes del trabajador dependiente al Sistema Integral de Pensiones | B6: Comisión de la Gestora | C6: 0.5 | D6: % | E6: 1/1/2025 | F6: https://media.economiayfinanzas.gob.bo/sites/default/files/2025-10/Bolet%C3%ADn%20SIP_diciembre%202024.pdf | G6: 7/10/2026
A7: Aportes del trabajador dependiente al Sistema Integral de Pensiones | B7: Aporte solidario del asegurado | C7: 0.5 | D7: % | E7: 1/1/2025 | F7: https://media.economiayfinanzas.gob.bo/sites/default/files/2025-10/Bolet%C3%ADn%20SIP_diciembre%202024.pdf | G7: 7/10/2026
A8: Aporte Nacional Solidario: porcentaje sobre cada excedente | B8: Sobre lo que pasa de Bs 13.000 | C8: 1.15 | D8: % | E8: 1/10/2024 | F8: https://www.economiayfinanzas.gob.bo/sites/default/files/2024-10/L15821807NCPP.pdf | G8: 7/10/2026
A9: Aporte Nacional Solidario: porcentaje sobre cada excedente | B9: Sobre lo que pasa de Bs 25.000 | C9: 5.74 | D9: % | E9: 1/10/2024 | F9: https://www.economiayfinanzas.gob.bo/sites/default/files/2024-10/L15821807NCPP.pdf | G9: 7/10/2026
A10: Aporte Nacional Solidario: porcentaje sobre cada excedente | B10: Sobre lo que pasa de Bs 35.000 | C10: 11.48 | D10: % | E10: 1/10/2024 | F10: https://www.economiayfinanzas.gob.bo/sites/default/files/2024-10/L15821807NCPP.pdf | G10: 7/10/2026
A11: Aporte Nacional Solidario: montos desde los que se aporta | B11: Primer monto | C11: 13000 | D11: BOB | E11: 1/10/2024 | F11: https://www.economiayfinanzas.gob.bo/sites/default/files/2024-10/L15821807NCPP.pdf | G11: 7/10/2026
A12: Aporte Nacional Solidario: montos desde los que se aporta | B12: Segundo monto | C12: 25000 | D12: BOB | E12: 1/10/2024 | F12: https://www.economiayfinanzas.gob.bo/sites/default/files/2024-10/L15821807NCPP.pdf | G12: 7/10/2026
A13: Aporte Nacional Solidario: montos desde los que se aporta | B13: Tercer monto | C13: 35000 | D13: BOB | E13: 1/10/2024 | F13: https://www.economiayfinanzas.gob.bo/sites/default/files/2024-10/L15821807NCPP.pdf | G13: 7/10/2026
A14: Salario Mínimo Nacional | C14: 3300 | D14: BOB | E14: 1/1/2026 | F14: https://www.impuestos.gob.bo/wp-content/uploads/2026/02/DS-5516.pdf | G14: 7/10/2026
A15: Alícuota del RC-IVA | C15: 13 | D15: % | E15: 1/1/2025 | F15: https://www.impuestos.gob.bo/wp-content/uploads/2026/09/1.-LEY-N%C2%B0-843-08-26.pdf | G15: 7/10/2026
A16: Mínimo no imponible del RC-IVA (en salarios mínimos) | C16: 2 | E16: 1/1/2025 | F16: https://www.impuestos.gob.bo/wp-content/uploads/2026/09/1.-LEY-N%C2%B0-843-08-26.pdf | G16: 7/10/2026
A17: Cómputo del 13 % sobre salarios mínimos que se descuenta del RC-IVA | C17: 1 | E17: 1/5/2025 | F17: https://www.impuestos.gob.bo/wp-content/uploads/2026/09/1.-LEY-N%C2%B0-843-08-26.pdf | G17: 7/10/2026
A18: Meses seguidos de trabajo en la gestión para cobrar aguinaldo | B18: Empleadas y empleados | C18: 3 | D18: meses | E18: 1/1/2025 | F18: https://mintrabajo.gob.bo/wp-content/uploads/2025/12/INSTRUCTIVO-DGTHSO-No0119-2025.pdf | G18: 7/10/2026
A19: Meses seguidos de trabajo en la gestión para cobrar aguinaldo | B19: Obreras y obreros | C19: 1 | D19: meses | E19: 1/1/2025 | F19: https://mintrabajo.gob.bo/wp-content/uploads/2025/12/INSTRUCTIVO-DGTHSO-No0119-2025.pdf | G19: 7/10/2026
A20: Años de trabajo continuo que consolida un quinquenio | C20: 5 | D20: años | E20: 1/1/2025 | F20: https://www.mintrabajo.gob.bo/wp-content/uploads/2025/10/Libro-No-73-Guia-de-derechos-laborales-MTEPS-2024.pdf | G20: 7/10/2026
A21: Días de trabajo continuo para tener indemnización | C21: 90 | D21: días | E21: 1/1/2025 | F21: https://www.mintrabajo.gob.bo/wp-content/uploads/2025/10/Libro-No-73-Guia-de-derechos-laborales-MTEPS-2024.pdf | G21: 7/10/2026
A22: Desahucio por despido injustificado (en sueldos) | C22: 3 | E22: 1/1/2025 | F22: https://www.mintrabajo.gob.bo/wp-content/uploads/2025/10/Libro-No-73-Guia-de-derechos-laborales-MTEPS-2024.pdf | G22: 7/10/2026
A23: Días hábiles de vacación por año según antigüedad | B23: De 1 a 5 años de trabajo | C23: 15 | D23: días | E23: 1/1/2025 | F23: https://www.mintrabajo.gob.bo/wp-content/uploads/2025/10/Libro-No-73-Guia-de-derechos-laborales-MTEPS-2024.pdf | G23: 7/10/2026
A24: Días hábiles de vacación por año según antigüedad | B24: De 5 a 10 años de trabajo | C24: 20 | D24: días | E24: 1/1/2025 | F24: https://www.mintrabajo.gob.bo/wp-content/uploads/2025/10/Libro-No-73-Guia-de-derechos-laborales-MTEPS-2024.pdf | G24: 7/10/2026
A25: Días hábiles de vacación por año según antigüedad | B25: De 10 años en adelante | C25: 30 | D25: días | E25: 1/1/2025 | F25: https://www.mintrabajo.gob.bo/wp-content/uploads/2025/10/Libro-No-73-Guia-de-derechos-laborales-MTEPS-2024.pdf | G25: 7/10/2026
