Workbook

Sheet Cómo usarla
A1: Cómo usar la planilla de plazos fijos
A3: 1 | B3: En «Mis plazos fijos» reemplazá las filas de ejemplo con tus plazos fijos: banco, fecha en que lo armaste, capital, TNA y días. Entran 24, de todos los bancos que uses.
A4: 2 | B4: Cada fila te dice cuándo vence, cuánto cobrás, la TEA y si le ganó a la inflación. Cuando el INDEC ya publicó los meses del plazo, usa el IPC oficial; si no, la inflación que estimás en la celda B5.
A5: 3 | B5: «Calendario» ordena los vigentes por fecha y te dice cuánto se acredita cada mes de los próximos doce.
A6: 4 | B6: «Renovación», «Tradicional vs UVA» y «Escalera» son simuladores: probá renovar todo un año, comparar con un UVA al mismo plazo o partir el capital en escalones.
A7: 5 | B7: «Resumen del año» junta lo del año: intereses, ganancia real y la inflación oficial. «IPC» y «Fuentes» muestran de dónde sale cada dato.
A9: COLORES
B10: Amarillo: lo completás vos.
B11: Verde: lo calcula la planilla. Están protegidas para que no se pisen sin querer (Revisar > Desproteger hoja, si alguna vez lo necesitás).
A13: LO QUE CONVIENE SABER
B14: • El interés de un plazo fijo tradicional es simple, sobre un año de 365 días: capital × TNA × días ÷ 365. La TEA es lo que rendiría en un año renovando capital + intereses en cada vencimiento.
B15: • La tasa real es la que importa para tu bolsillo: lo que cobrás descontada la inflación del período. Una TNA alta puede tener tasa real negativa si la inflación fue mayor.
B16: • TNA de referencia: el promedio que pagan los bancos por depósitos a 30 días, publicado por el BCRA (22,66% al 16/10/2026). Tu banco puede pagar más o menos: cargá siempre la tuya.
B17: • Plazo fijo UVA (Com. «A» 8246 del BCRA): mínimo 90 días, precancelable desde el día 30 sin el ajuste por inflación.
B18: • Garantía de los depósitos: hasta $ 50.000.000 por persona desde el 1/4/2026 (Com. «A» 8407 del BCRA). La columna «Garantía» de «Mis plazos fijos» te avisa si en un banco te pasás del tope.
A20: CÓMO SE MANTIENE AL DÍA
B21: • El enlace de descarga que te llegó por mail no vence y siempre baja la última versión, con el IPC y la TNA de referencia al día. Para pasar tus plazos fijos: copiá las celdas amarillas de «Mis plazos fijos» y pegalas en el mismo lugar del archivo nuevo.
B22: • ¿Preferís no cambiar de archivo? Cuando salga un IPC nuevo, cargá el % del mes en la columna amarilla de la hoja «IPC»: las filas que estaban estimadas pasan solas al dato oficial.
A24: Es una herramienta de cálculo y control: no es asesoramiento financiero ni recomienda bancos ni productos. Da los mismos números que la calculadora gratuita de calcular.ar/plazo-fijo; si alguna vez no coinciden, escribinos y lo corregimos.

Sheet Mis plazos fijos
A1: Mis plazos fijos
A2: Las dos primeras filas son un ejemplo: reemplazalas con tus plazos fijos. Completás las celdas amarillas (banco, fecha, capital, TNA y días); las verdes se calculan solas.
A4: SUPUESTO PARA LO QUE TODAVÍA NO PUBLICÓ EL INDEC
A5: Inflación mensual estimada (%) | B5: 1.7 | C5: Último dato oficial: 1,7% en agosto 2026 (INDEC). Se usa sólo para los plazos fijos que vencen después del último IPC publicado: cuando salga el dato, la fila pasa sola al IPC del INDEC.
A6: Hoy | B6: =TODAY()
A8: RESUMEN
A9: Capital en plazos fijos vigentes | B9: =SUM($AA$15:$AA$38)
A10: Intereses por cobrar de los vigentes | B10: =SUM($AB$15:$AB$38)
A11: Próximo vencimiento | B11: =IFERROR(INT(SMALL($V$15:$V$38,1)),"") | C11: =IF(ISNUMBER(B11),INDEX($A$1:$A$38,ROUND(MOD(SMALL($V$15:$V$38,1),1)*100000,0))&"","No hay plazos fijos vigentes cargados")
A12: Se acredita en los próximos 30 días | B12: =SUMIFS($X$15:$X$38,$F$15:$F$38,"<="&(B6+30))
A13: TUS PLAZOS FIJOS
A14: Banco | B14: Constituido el | C14: Capital | D14: TNA (%) | E14: Días | F14: Vence el | G14: Interés | H14: Cobrás al vencimiento | I14: TEA | J14: Inflación del período | K14: Inflación según | L14: Tasa real | M14: ¿Le ganó a la inflación? | N14: Estado | O14: Garantía de los depósitos
A15: Banco A (ejemplo) | B15: 46208 | C15: 1000000 | D15: 22.66 | E15: 30 | F15: =IF(P15=1,B15+E15,"") | G15: =IF(P15=1,C15*D15/100*E15/365,"") | H15: =IF(P15=1,C15+G15,"") | I15: =IF(P15=1,(1+D15/100*E15/365)^(365/E15)-1,"") | J15: =IF(P15=1,IF(S15=1,U15/T15-1,(1+B5/100)^(E15/30)-1),"") | K15: =IF(P15=1,IF(S15=1,"IPC del INDEC","Estimada"),"") | L15: =IF(P15=1,H15/(1+J15)/C15-1,"") | M15: =IF(P15=0,IF(OR(A15<>"",ISNUMBER(B15),ISNUMBER(C15),ISNUMBER(D15),ISNUMBER(E15)),"Faltan datos: fecha, capital, TNA y días (mínimo 30)",""),IF(S15=1,IF(L15>=0,"Le ganó a la inflación","Perdió contra la inflación"),IF(L15>=0,"Le gana, si la inflación es la estimada","Pierde, si la inflación es la estimada"))) | N15: =IF(P15=0,"",IF(F15<$B$6,"Vencido",IF(F15=$B$6,"Vence hoy","Faltan "&(F15-$B$6)&IF(F15-$B$6=1," día"," días")))) | O15: =IF(OR(P15=0,F15<$B$6),"",IF(A15="","Cargá el banco para controlarla",IF(SUMIFS($X$15:$X$38,$A$15:$A$38,A15)>50000000,"Supera el tope en este banco","Dentro del tope"))) | P15: =IF(AND(ISNUMBER(B15),ISNUMBER(C15),C15>0,ISNUMBER(D15),D15>=0,ISNUMBER(E15),E15>=30),1,0) | Q15: =IF(P15=1,YEAR(B15)*12+MONTH(B15)-1,"") | R15: =IF(P15=1,YEAR(F15)*12+MONTH(F15)-1,"") | S15: =IF(P15=1,IF(AND(Q15-1>=IPC!$J$2,R15<=IPC!$J$3),1,0),0) | T15: =IF(S15=1,INDEX(IPC!$D$5:$D$173,(Q15-1)-IPC!$J$2+1)*(INDEX(IPC!$D$5:$D$173,(Q15)-IPC!$J$2+1)/INDEX(IPC!$D$5:$D$173,(Q15-1)-IPC!$J$2+1))^(DAY(B15)/DAY(EOMONTH(B15,0))),"") | U15: =IF(S15=1,INDEX(IPC!$D$5:$D$173,(R15-1)-IPC!$J$2+1)*(INDEX(IPC!$D$5:$D$173,(R15)-IPC!$J$2+1)/INDEX(IPC!$D$5:$D$173,(R15-1)-IPC!$J$2+1))^(DAY(F15)/DAY(EOMONTH(F15,0))),"") | V15: =IF(AND(P15=1,F15>=$B$6),F15+ROW()/100000,"") | W15: =IF(P15=1,H15/(1+J15)-C15,"") | X15: =IF(AND(P15=1,F15>=$B$6),H15,"") | Y15: =IF(P15=1,YEAR(F15),"") | Z15: =IF(AND(P15=1,F15<=$B$6),G15,"") | AA15: =IF(AND(P15=1,F15>=$B$6),C15,"") | AB15: =IF(AND(P15=1,F15>=$B$6),G15,"")
A16: Banco B (ejemplo) | B16: 46314 | C16: 2500000 | D16: 22.66 | E16: 60 | F16: =IF(P16=1,B16+E16,"") | G16: =IF(P16=1,C16*D16/100*E16/365,"") | H16: =IF(P16=1,C16+G16,"") | I16: =IF(P16=1,(1+D16/100*E16/365)^(365/E16)-1,"") | J16: =IF(P16=1,IF(S16=1,U16/T16-1,(1+B5/100)^(E16/30)-1),"") | K16: =IF(P16=1,IF(S16=1,"IPC del INDEC","Estimada"),"") | L16: =IF(P16=1,H16/(1+J16)/C16-1,"") | M16: =IF(P16=0,IF(OR(A16<>"",ISNUMBER(B16),ISNUMBER(C16),ISNUMBER(D16),ISNUMBER(E16)),"Faltan datos: fecha, capital, TNA y días (mínimo 30)",""),IF(S16=1,IF(L16>=0,"Le ganó a la inflación","Perdió contra la inflación"),IF(L16>=0,"Le gana, si la inflación es la estimada","Pierde, si la inflación es la estimada"))) | N16: =IF(P16=0,"",IF(F16<$B$6,"Vencido",IF(F16=$B$6,"Vence hoy","Faltan "&(F16-$B$6)&IF(F16-$B$6=1," día"," días")))) | O16: =IF(OR(P16=0,F16<$B$6),"",IF(A16="","Cargá el banco para controlarla",IF(SUMIFS($X$15:$X$38,$A$15:$A$38,A16)>50000000,"Supera el tope en este banco","Dentro del tope"))) | P16: =IF(AND(ISNUMBER(B16),ISNUMBER(C16),C16>0,ISNUMBER(D16),D16>=0,ISNUMBER(E16),E16>=30),1,0) | Q16: =IF(P16=1,YEAR(B16)*12+MONTH(B16)-1,"") | R16: =IF(P16=1,YEAR(F16)*12+MONTH(F16)-1,"") | S16: =IF(P16=1,IF(AND(Q16-1>=IPC!$J$2,R16<=IPC!$J$3),1,0),0) | T16: =IF(S16=1,INDEX(IPC!$D$5:$D$173,(Q16-1)-IPC!$J$2+1)*(INDEX(IPC!$D$5:$D$173,(Q16)-IPC!$J$2+1)/INDEX(IPC!$D$5:$D$173,(Q16-1)-IPC!$J$2+1))^(DAY(B16)/DAY(EOMONTH(B16,0))),"") | U16: =IF(S16=1,INDEX(IPC!$D$5:$D$173,(R16-1)-IPC!$J$2+1)*(INDEX(IPC!$D$5:$D$173,(R16)-IPC!$J$2+1)/INDEX(IPC!$D$5:$D$173,(R16-1)-IPC!$J$2+1))^(DAY(F16)/DAY(EOMONTH(F16,0))),"") | V16: =IF(AND(P16=1,F16>=$B$6),F16+ROW()/100000,"") | W16: =IF(P16=1,H16/(1+J16)-C16,"") | X16: =IF(AND(P16=1,F16>=$B$6),H16,"") | Y16: =IF(P16=1,YEAR(F16),"") | Z16: =IF(AND(P16=1,F16<=$B$6),G16,"") | AA16: =IF(AND(P16=1,F16>=$B$6),C16,"") | AB16: =IF(AND(P16=1,F16>=$B$6),G16,"")
F17: =IF(P17=1,B17+E17,"") | G17: =IF(P17=1,C17*D17/100*E17/365,"") | H17: =IF(P17=1,C17+G17,"") | I17: =IF(P17=1,(1+D17/100*E17/365)^(365/E17)-1,"") | J17: =IF(P17=1,IF(S17=1,U17/T17-1,(1+B5/100)^(E17/30)-1),"") | K17: =IF(P17=1,IF(S17=1,"IPC del INDEC","Estimada"),"") | L17: =IF(P17=1,H17/(1+J17)/C17-1,"") | M17: =IF(P17=0,IF(OR(A17<>"",ISNUMBER(B17),ISNUMBER(C17),ISNUMBER(D17),ISNUMBER(E17)),"Faltan datos: fecha, capital, TNA y días (mínimo 30)",""),IF(S17=1,IF(L17>=0,"Le ganó a la inflación","Perdió contra la inflación"),IF(L17>=0,"Le gana, si la inflación es la estimada","Pierde, si la inflación es la estimada"))) | N17: =IF(P17=0,"",IF(F17<$B$6,"Vencido",IF(F17=$B$6,"Vence hoy","Faltan "&(F17-$B$6)&IF(F17-$B$6=1," día"," días")))) | O17: =IF(OR(P17=0,F17<$B$6),"",IF(A17="","Cargá el banco para controlarla",IF(SUMIFS($X$15:$X$38,$A$15:$A$38,A17)>50000000,"Supera el tope en este banco","Dentro del tope"))) | P17: =IF(AND(ISNUMBER(B17),ISNUMBER(C17),C17>0,ISNUMBER(D17),D17>=0,ISNUMBER(E17),E17>=30),1,0) | Q17: =IF(P17=1,YEAR(B17)*12+MONTH(B17)-1,"") | R17: =IF(P17=1,YEAR(F17)*12+MONTH(F17)-1,"") | S17: =IF(P17=1,IF(AND(Q17-1>=IPC!$J$2,R17<=IPC!$J$3),1,0),0) | T17: =IF(S17=1,INDEX(IPC!$D$5:$D$173,(Q17-1)-IPC!$J$2+1)*(INDEX(IPC!$D$5:$D$173,(Q17)-IPC!$J$2+1)/INDEX(IPC!$D$5:$D$173,(Q17-1)-IPC!$J$2+1))^(DAY(B17)/DAY(EOMONTH(B17,0))),"") | U17: =IF(S17=1,INDEX(IPC!$D$5:$D$173,(R17-1)-IPC!$J$2+1)*(INDEX(IPC!$D$5:$D$173,(R17)-IPC!$J$2+1)/INDEX(IPC!$D$5:$D$173,(R17-1)-IPC!$J$2+1))^(DAY(F17)/DAY(EOMONTH(F17,0))),"") | V17: =IF(AND(P17=1,F17>=$B$6),F17+ROW()/100000,"") | W17: =IF(P17=1,H17/(1+J17)-C17,"") | X17: =IF(AND(P17=1,F17>=$B$6),H17,"") | Y17: =IF(P17=1,YEAR(F17),"") | Z17: =IF(AND(P17=1,F17<=$B$6),G17,"") | AA17: =IF(AND(P17=1,F17>=$B$6),C17,"") | AB17: =IF(AND(P17=1,F17>=$B$6),G17,"")
F18: =IF(P18=1,B18+E18,"") | G18: =IF(P18=1,C18*D18/100*E18/365,"") | H18: =IF(P18=1,C18+G18,"") | I18: =IF(P18=1,(1+D18/100*E18/365)^(365/E18)-1,"") | J18: =IF(P18=1,IF(S18=1,U18/T18-1,(1+B5/100)^(E18/30)-1),"") | K18: =IF(P18=1,IF(S18=1,"IPC del INDEC","Estimada"),"") | L18: =IF(P18=1,H18/(1+J18)/C18-1,"") | M18: =IF(P18=0,IF(OR(A18<>"",ISNUMBER(B18),ISNUMBER(C18),ISNUMBER(D18),ISNUMBER(E18)),"Faltan datos: fecha, capital, TNA y días (mínimo 30)",""),IF(S18=1,IF(L18>=0,"Le ganó a la inflación","Perdió contra la inflación"),IF(L18>=0,"Le gana, si la inflación es la estimada","Pierde, si la inflación es la estimada"))) | N18: =IF(P18=0,"",IF(F18<$B$6,"Vencido",IF(F18=$B$6,"Vence hoy","Faltan "&(F18-$B$6)&IF(F18-$B$6=1," día"," días")))) | O18: =IF(OR(P18=0,F18<$B$6),"",IF(A18="","Cargá el banco para controlarla",IF(SUMIFS($X$15:$X$38,$A$15:$A$38,A18)>50000000,"Supera el tope en este banco","Dentro del tope"))) | P18: =IF(AND(ISNUMBER(B18),ISNUMBER(C18),C18>0,ISNUMBER(D18),D18>=0,ISNUMBER(E18),E18>=30),1,0) | Q18: =IF(P18=1,YEAR(B18)*12+MONTH(B18)-1,"") | R18: =IF(P18=1,YEAR(F18)*12+MONTH(F18)-1,"") | S18: =IF(P18=1,IF(AND(Q18-1>=IPC!$J$2,R18<=IPC!$J$3),1,0),0) | T18: =IF(S18=1,INDEX(IPC!$D$5:$D$173,(Q18-1)-IPC!$J$2+1)*(INDEX(IPC!$D$5:$D$173,(Q18)-IPC!$J$2+1)/INDEX(IPC!$D$5:$D$173,(Q18-1)-IPC!$J$2+1))^(DAY(B18)/DAY(EOMONTH(B18,0))),"") | U18: =IF(S18=1,INDEX(IPC!$D$5:$D$173,(R18-1)-IPC!$J$2+1)*(INDEX(IPC!$D$5:$D$173,(R18)-IPC!$J$2+1)/INDEX(IPC!$D$5:$D$173,(R18-1)-IPC!$J$2+1))^(DAY(F18)/DAY(EOMONTH(F18,0))),"") | V18: =IF(AND(P18=1,F18>=$B$6),F18+ROW()/100000,"") | W18: =IF(P18=1,H18/(1+J18)-C18,"") | X18: =IF(AND(P18=1,F18>=$B$6),H18,"") | Y18: =IF(P18=1,YEAR(F18),"") | Z18: =IF(AND(P18=1,F18<=$B$6),G18,"") | AA18: =IF(AND(P18=1,F18>=$B$6),C18,"") | AB18: =IF(AND(P18=1,F18>=$B$6),G18,"")
F19: =IF(P19=1,B19+E19,"") | G19: =IF(P19=1,C19*D19/100*E19/365,"") | H19: =IF(P19=1,C19+G19,"") | I19: =IF(P19=1,(1+D19/100*E19/365)^(365/E19)-1,"") | J19: =IF(P19=1,IF(S19=1,U19/T19-1,(1+B5/100)^(E19/30)-1),"") | K19: =IF(P19=1,IF(S19=1,"IPC del INDEC","Estimada"),"") | L19: =IF(P19=1,H19/(1+J19)/C19-1,"") | M19: =IF(P19=0,IF(OR(A19<>"",ISNUMBER(B19),ISNUMBER(C19),ISNUMBER(D19),ISNUMBER(E19)),"Faltan datos: fecha, capital, TNA y días (mínimo 30)",""),IF(S19=1,IF(L19>=0,"Le ganó a la inflación","Perdió contra la inflación"),IF(L19>=0,"Le gana, si la inflación es la estimada","Pierde, si la inflación es la estimada"))) | N19: =IF(P19=0,"",IF(F19<$B$6,"Vencido",IF(F19=$B$6,"Vence hoy","Faltan "&(F19-$B$6)&IF(F19-$B$6=1," día"," días")))) | O19: =IF(OR(P19=0,F19<$B$6),"",IF(A19="","Cargá el banco para controlarla",IF(SUMIFS($X$15:$X$38,$A$15:$A$38,A19)>50000000,"Supera el tope en este banco","Dentro del tope"))) | P19: =IF(AND(ISNUMBER(B19),ISNUMBER(C19),C19>0,ISNUMBER(D19),D19>=0,ISNUMBER(E19),E19>=30),1,0) | Q19: =IF(P19=1,YEAR(B19)*12+MONTH(B19)-1,"") | R19: =IF(P19=1,YEAR(F19)*12+MONTH(F19)-1,"") | S19: =IF(P19=1,IF(AND(Q19-1>=IPC!$J$2,R19<=IPC!$J$3),1,0),0) | T19: =IF(S19=1,INDEX(IPC!$D$5:$D$173,(Q19-1)-IPC!$J$2+1)*(INDEX(IPC!$D$5:$D$173,(Q19)-IPC!$J$2+1)/INDEX(IPC!$D$5:$D$173,(Q19-1)-IPC!$J$2+1))^(DAY(B19)/DAY(EOMONTH(B19,0))),"") | U19: =IF(S19=1,INDEX(IPC!$D$5:$D$173,(R19-1)-IPC!$J$2+1)*(INDEX(IPC!$D$5:$D$173,(R19)-IPC!$J$2+1)/INDEX(IPC!$D$5:$D$173,(R19-1)-IPC!$J$2+1))^(DAY(F19)/DAY(EOMONTH(F19,0))),"") | V19: =IF(AND(P19=1,F19>=$B$6),F19+ROW()/100000,"") | W19: =IF(P19=1,H19/(1+J19)-C19,"") | X19: =IF(AND(P19=1,F19>=$B$6),H19,"") | Y19: =IF(P19=1,YEAR(F19),"") | Z19: =IF(AND(P19=1,F19<=$B$6),G19,"") | AA19: =IF(AND(P19=1,F19>=$B$6),C19,"") | AB19: =IF(AND(P19=1,F19>=$B$6),G19,"")
F20: =IF(P20=1,B20+E20,"") | G20: =IF(P20=1,C20*D20/100*E20/365,"") | H20: =IF(P20=1,C20+G20,"") | I20: =IF(P20=1,(1+D20/100*E20/365)^(365/E20)-1,"") | J20: =IF(P20=1,IF(S20=1,U20/T20-1,(1+B5/100)^(E20/30)-1),"") | K20: =IF(P20=1,IF(S20=1,"IPC del INDEC","Estimada"),"") | L20: =IF(P20=1,H20/(1+J20)/C20-1,"") | M20: =IF(P20=0,IF(OR(A20<>"",ISNUMBER(B20),ISNUMBER(C20),ISNUMBER(D20),ISNUMBER(E20)),"Faltan datos: fecha, capital, TNA y días (mínimo 30)",""),IF(S20=1,IF(L20>=0,"Le ganó a la inflación","Perdió contra la inflación"),IF(L20>=0,"Le gana, si la inflación es la estimada","Pierde, si la inflación es la estimada"))) | N20: =IF(P20=0,"",IF(F20<$B$6,"Vencido",IF(F20=$B$6,"Vence hoy","Faltan "&(F20-$B$6)&IF(F20-$B$6=1," día"," días")))) | O20: =IF(OR(P20=0,F20<$B$6),"",IF(A20="","Cargá el banco para controlarla",IF(SUMIFS($X$15:$X$38,$A$15:$A$38,A20)>50000000,"Supera el tope en este banco","Dentro del tope"))) | P20: =IF(AND(ISNUMBER(B20),ISNUMBER(C20),C20>0,ISNUMBER(D20),D20>=0,ISNUMBER(E20),E20>=30),1,0) | Q20: =IF(P20=1,YEAR(B20)*12+MONTH(B20)-1,"") | R20: =IF(P20=1,YEAR(F20)*12+MONTH(F20)-1,"") | S20: =IF(P20=1,IF(AND(Q20-1>=IPC!$J$2,R20<=IPC!$J$3),1,0),0) | T20: =IF(S20=1,INDEX(IPC!$D$5:$D$173,(Q20-1)-IPC!$J$2+1)*(INDEX(IPC!$D$5:$D$173,(Q20)-IPC!$J$2+1)/INDEX(IPC!$D$5:$D$173,(Q20-1)-IPC!$J$2+1))^(DAY(B20)/DAY(EOMONTH(B20,0))),"") | U20: =IF(S20=1,INDEX(IPC!$D$5:$D$173,(R20-1)-IPC!$J$2+1)*(INDEX(IPC!$D$5:$D$173,(R20)-IPC!$J$2+1)/INDEX(IPC!$D$5:$D$173,(R20-1)-IPC!$J$2+1))^(DAY(F20)/DAY(EOMONTH(F20,0))),"") | V20: =IF(AND(P20=1,F20>=$B$6),F20+ROW()/100000,"") | W20: =IF(P20=1,H20/(1+J20)-C20,"") | X20: =IF(AND(P20=1,F20>=$B$6),H20,"") | Y20: =IF(P20=1,YEAR(F20),"") | Z20: =IF(AND(P20=1,F20<=$B$6),G20,"") | AA20: =IF(AND(P20=1,F20>=$B$6),C20,"") | AB20: =IF(AND(P20=1,F20>=$B$6),G20,"")
F21: =IF(P21=1,B21+E21,"") | G21: =IF(P21=1,C21*D21/100*E21/365,"") | H21: =IF(P21=1,C21+G21,"") | I21: =IF(P21=1,(1+D21/100*E21/365)^(365/E21)-1,"") | J21: =IF(P21=1,IF(S21=1,U21/T21-1,(1+B5/100)^(E21/30)-1),"") | K21: =IF(P21=1,IF(S21=1,"IPC del INDEC","Estimada"),"") | L21: =IF(P21=1,H21/(1+J21)/C21-1,"") | M21: =IF(P21=0,IF(OR(A21<>"",ISNUMBER(B21),ISNUMBER(C21),ISNUMBER(D21),ISNUMBER(E21)),"Faltan datos: fecha, capital, TNA y días (mínimo 30)",""),IF(S21=1,IF(L21>=0,"Le ganó a la inflación","Perdió contra la inflación"),IF(L21>=0,"Le gana, si la inflación es la estimada","Pierde, si la inflación es la estimada"))) | N21: =IF(P21=0,"",IF(F21<$B$6,"Vencido",IF(F21=$B$6,"Vence hoy","Faltan "&(F21-$B$6)&IF(F21-$B$6=1," día"," días")))) | O21: =IF(OR(P21=0,F21<$B$6),"",IF(A21="","Cargá el banco para controlarla",IF(SUMIFS($X$15:$X$38,$A$15:$A$38,A21)>50000000,"Supera el tope en este banco","Dentro del tope"))) | P21: =IF(AND(ISNUMBER(B21),ISNUMBER(C21),C21>0,ISNUMBER(D21),D21>=0,ISNUMBER(E21),E21>=30),1,0) | Q21: =IF(P21=1,YEAR(B21)*12+MONTH(B21)-1,"") | R21: =IF(P21=1,YEAR(F21)*12+MONTH(F21)-1,"") | S21: =IF(P21=1,IF(AND(Q21-1>=IPC!$J$2,R21<=IPC!$J$3),1,0),0) | T21: =IF(S21=1,INDEX(IPC!$D$5:$D$173,(Q21-1)-IPC!$J$2+1)*(INDEX(IPC!$D$5:$D$173,(Q21)-IPC!$J$2+1)/INDEX(IPC!$D$5:$D$173,(Q21-1)-IPC!$J$2+1))^(DAY(B21)/DAY(EOMONTH(B21,0))),"") | U21: =IF(S21=1,INDEX(IPC!$D$5:$D$173,(R21-1)-IPC!$J$2+1)*(INDEX(IPC!$D$5:$D$173,(R21)-IPC!$J$2+1)/INDEX(IPC!$D$5:$D$173,(R21-1)-IPC!$J$2+1))^(DAY(F21)/DAY(EOMONTH(F21,0))),"") | V21: =IF(AND(P21=1,F21>=$B$6),F21+ROW()/100000,"") | W21: =IF(P21=1,H21/(1+J21)-C21,"") | X21: =IF(AND(P21=1,F21>=$B$6),H21,"") | Y21: =IF(P21=1,YEAR(F21),"") | Z21: =IF(AND(P21=1,F21<=$B$6),G21,"") | AA21: =IF(AND(P21=1,F21>=$B$6),C21,"") | AB21: =IF(AND(P21=1,F21>=$B$6),G21,"")
F22: =IF(P22=1,B22+E22,"") | G22: =IF(P22=1,C22*D22/100*E22/365,"") | H22: =IF(P22=1,C22+G22,"") | I22: =IF(P22=1,(1+D22/100*E22/365)^(365/E22)-1,"") | J22: =IF(P22=1,IF(S22=1,U22/T22-1,(1+B5/100)^(E22/30)-1),"") | K22: =IF(P22=1,IF(S22=1,"IPC del INDEC","Estimada"),"") | L22: =IF(P22=1,H22/(1+J22)/C22-1,"") | M22: =IF(P22=0,IF(OR(A22<>"",ISNUMBER(B22),ISNUMBER(C22),ISNUMBER(D22),ISNUMBER(E22)),"Faltan datos: fecha, capital, TNA y días (mínimo 30)",""),IF(S22=1,IF(L22>=0,"Le ganó a la inflación","Perdió contra la inflación"),IF(L22>=0,"Le gana, si la inflación es la estimada","Pierde, si la inflación es la estimada"))) | N22: =IF(P22=0,"",IF(F22<$B$6,"Vencido",IF(F22=$B$6,"Vence hoy","Faltan "&(F22-$B$6)&IF(F22-$B$6=1," día"," días")))) | O22: =IF(OR(P22=0,F22<$B$6),"",IF(A22="","Cargá el banco para controlarla",IF(SUMIFS($X$15:$X$38,$A$15:$A$38,A22)>50000000,"Supera el tope en este banco","Dentro del tope"))) | P22: =IF(AND(ISNUMBER(B22),ISNUMBER(C22),C22>0,ISNUMBER(D22),D22>=0,ISNUMBER(E22),E22>=30),1,0) | Q22: =IF(P22=1,YEAR(B22)*12+MONTH(B22)-1,"") | R22: =IF(P22=1,YEAR(F22)*12+MONTH(F22)-1,"") | S22: =IF(P22=1,IF(AND(Q22-1>=IPC!$J$2,R22<=IPC!$J$3),1,0),0) | T22: =IF(S22=1,INDEX(IPC!$D$5:$D$173,(Q22-1)-IPC!$J$2+1)*(INDEX(IPC!$D$5:$D$173,(Q22)-IPC!$J$2+1)/INDEX(IPC!$D$5:$D$173,(Q22-1)-IPC!$J$2+1))^(DAY(B22)/DAY(EOMONTH(B22,0))),"") | U22: =IF(S22=1,INDEX(IPC!$D$5:$D$173,(R22-1)-IPC!$J$2+1)*(INDEX(IPC!$D$5:$D$173,(R22)-IPC!$J$2+1)/INDEX(IPC!$D$5:$D$173,(R22-1)-IPC!$J$2+1))^(DAY(F22)/DAY(EOMONTH(F22,0))),"") | V22: =IF(AND(P22=1,F22>=$B$6),F22+ROW()/100000,"") | W22: =IF(P22=1,H22/(1+J22)-C22,"") | X22: =IF(AND(P22=1,F22>=$B$6),H22,"") | Y22: =IF(P22=1,YEAR(F22),"") | Z22: =IF(AND(P22=1,F22<=$B$6),G22,"") | AA22: =IF(AND(P22=1,F22>=$B$6),C22,"") | AB22: =IF(AND(P22=1,F22>=$B$6),G22,"")
F23: =IF(P23=1,B23+E23,"") | G23: =IF(P23=1,C23*D23/100*E23/365,"") | H23: =IF(P23=1,C23+G23,"") | I23: =IF(P23=1,(1+D23/100*E23/365)^(365/E23)-1,"") | J23: =IF(P23=1,IF(S23=1,U23/T23-1,(1+B5/100)^(E23/30)-1),"") | K23: =IF(P23=1,IF(S23=1,"IPC del INDEC","Estimada"),"") | L23: =IF(P23=1,H23/(1+J23)/C23-1,"") | M23: =IF(P23=0,IF(OR(A23<>"",ISNUMBER(B23),ISNUMBER(C23),ISNUMBER(D23),ISNUMBER(E23)),"Faltan datos: fecha, capital, TNA y días (mínimo 30)",""),IF(S23=1,IF(L23>=0,"Le ganó a la inflación","Perdió contra la inflación"),IF(L23>=0,"Le gana, si la inflación es la estimada","Pierde, si la inflación es la estimada"))) | N23: =IF(P23=0,"",IF(F23<$B$6,"Vencido",IF(F23=$B$6,"Vence hoy","Faltan "&(F23-$B$6)&IF(F23-$B$6=1," día"," días")))) | O23: =IF(OR(P23=0,F23<$B$6),"",IF(A23="","Cargá el banco para controlarla",IF(SUMIFS($X$15:$X$38,$A$15:$A$38,A23)>50000000,"Supera el tope en este banco","Dentro del tope"))) | P23: =IF(AND(ISNUMBER(B23),ISNUMBER(C23),C23>0,ISNUMBER(D23),D23>=0,ISNUMBER(E23),E23>=30),1,0) | Q23: =IF(P23=1,YEAR(B23)*12+MONTH(B23)-1,"") | R23: =IF(P23=1,YEAR(F23)*12+MONTH(F23)-1,"") | S23: =IF(P23=1,IF(AND(Q23-1>=IPC!$J$2,R23<=IPC!$J$3),1,0),0) | T23: =IF(S23=1,INDEX(IPC!$D$5:$D$173,(Q23-1)-IPC!$J$2+1)*(INDEX(IPC!$D$5:$D$173,(Q23)-IPC!$J$2+1)/INDEX(IPC!$D$5:$D$173,(Q23-1)-IPC!$J$2+1))^(DAY(B23)/DAY(EOMONTH(B23,0))),"") | U23: =IF(S23=1,INDEX(IPC!$D$5:$D$173,(R23-1)-IPC!$J$2+1)*(INDEX(IPC!$D$5:$D$173,(R23)-IPC!$J$2+1)/INDEX(IPC!$D$5:$D$173,(R23-1)-IPC!$J$2+1))^(DAY(F23)/DAY(EOMONTH(F23,0))),"") | V23: =IF(AND(P23=1,F23>=$B$6),F23+ROW()/100000,"") | W23: =IF(P23=1,H23/(1+J23)-C23,"") | X23: =IF(AND(P23=1,F23>=$B$6),H23,"") | Y23: =IF(P23=1,YEAR(F23),"") | Z23: =IF(AND(P23=1,F23<=$B$6),G23,"") | AA23: =IF(AND(P23=1,F23>=$B$6),C23,"") | AB23: =IF(AND(P23=1,F23>=$B$6),G23,"")
F24: =IF(P24=1,B24+E24,"") | G24: =IF(P24=1,C24*D24/100*E24/365,"") | H24: =IF(P24=1,C24+G24,"") | I24: =IF(P24=1,(1+D24/100*E24/365)^(365/E24)-1,"") | J24: =IF(P24=1,IF(S24=1,U24/T24-1,(1+B5/100)^(E24/30)-1),"") | K24: =IF(P24=1,IF(S24=1,"IPC del INDEC","Estimada"),"") | L24: =IF(P24=1,H24/(1+J24)/C24-1,"") | M24: =IF(P24=0,IF(OR(A24<>"",ISNUMBER(B24),ISNUMBER(C24),ISNUMBER(D24),ISNUMBER(E24)),"Faltan datos: fecha, capital, TNA y días (mínimo 30)",""),IF(S24=1,IF(L24>=0,"Le ganó a la inflación","Perdió contra la inflación"),IF(L24>=0,"Le gana, si la inflación es la estimada","Pierde, si la inflación es la estimada"))) | N24: =IF(P24=0,"",IF(F24<$B$6,"Vencido",IF(F24=$B$6,"Vence hoy","Faltan "&(F24-$B$6)&IF(F24-$B$6=1," día"," días")))) | O24: =IF(OR(P24=0,F24<$B$6),"",IF(A24="","Cargá el banco para controlarla",IF(SUMIFS($X$15:$X$38,$A$15:$A$38,A24)>50000000,"Supera el tope en este banco","Dentro del tope"))) | P24: =IF(AND(ISNUMBER(B24),ISNUMBER(C24),C24>0,ISNUMBER(D24),D24>=0,ISNUMBER(E24),E24>=30),1,0) | Q24: =IF(P24=1,YEAR(B24)*12+MONTH(B24)-1,"") | R24: =IF(P24=1,YEAR(F24)*12+MONTH(F24)-1,"") | S24: =IF(P24=1,IF(AND(Q24-1>=IPC!$J$2,R24<=IPC!$J$3),1,0),0) | T24: =IF(S24=1,INDEX(IPC!$D$5:$D$173,(Q24-1)-IPC!$J$2+1)*(INDEX(IPC!$D$5:$D$173,(Q24)-IPC!$J$2+1)/INDEX(IPC!$D$5:$D$173,(Q24-1)-IPC!$J$2+1))^(DAY(B24)/DAY(EOMONTH(B24,0))),"") | U24: =IF(S24=1,INDEX(IPC!$D$5:$D$173,(R24-1)-IPC!$J$2+1)*(INDEX(IPC!$D$5:$D$173,(R24)-IPC!$J$2+1)/INDEX(IPC!$D$5:$D$173,(R24-1)-IPC!$J$2+1))^(DAY(F24)/DAY(EOMONTH(F24,0))),"") | V24: =IF(AND(P24=1,F24>=$B$6),F24+ROW()/100000,"") | W24: =IF(P24=1,H24/(1+J24)-C24,"") | X24: =IF(AND(P24=1,F24>=$B$6),H24,"") | Y24: =IF(P24=1,YEAR(F24),"") | Z24: =IF(AND(P24=1,F24<=$B$6),G24,"") | AA24: =IF(AND(P24=1,F24>=$B$6),C24,"") | AB24: =IF(AND(P24=1,F24>=$B$6),G24,"")
F25: =IF(P25=1,B25+E25,"") | G25: =IF(P25=1,C25*D25/100*E25/365,"") | H25: =IF(P25=1,C25+G25,"") | I25: =IF(P25=1,(1+D25/100*E25/365)^(365/E25)-1,"") | J25: =IF(P25=1,IF(S25=1,U25/T25-1,(1+B5/100)^(E25/30)-1),"") | K25: =IF(P25=1,IF(S25=1,"IPC del INDEC","Estimada"),"") | L25: =IF(P25=1,H25/(1+J25)/C25-1,"") | M25: =IF(P25=0,IF(OR(A25<>"",ISNUMBER(B25),ISNUMBER(C25),ISNUMBER(D25),ISNUMBER(E25)),"Faltan datos: fecha, capital, TNA y días (mínimo 30)",""),IF(S25=1,IF(L25>=0,"Le ganó a la inflación","Perdió contra la inflación"),IF(L25>=0,"Le gana, si la inflación es la estimada","Pierde, si la inflación es la estimada"))) | N25: =IF(P25=0,"",IF(F25<$B$6,"Vencido",IF(F25=$B$6,"Vence hoy","Faltan "&(F25-$B$6)&IF(F25-$B$6=1," día"," días")))) | O25: =IF(OR(P25=0,F25<$B$6),"",IF(A25="","Cargá el banco para controlarla",IF(SUMIFS($X$15:$X$38,$A$15:$A$38,A25)>50000000,"Supera el tope en este banco","Dentro del tope"))) | P25: =IF(AND(ISNUMBER(B25),ISNUMBER(C25),C25>0,ISNUMBER(D25),D25>=0,ISNUMBER(E25),E25>=30),1,0) | Q25: =IF(P25=1,YEAR(B25)*12+MONTH(B25)-1,"") | R25: =IF(P25=1,YEAR(F25)*12+MONTH(F25)-1,"") | S25: =IF(P25=1,IF(AND(Q25-1>=IPC!$J$2,R25<=IPC!$J$3),1,0),0) | T25: =IF(S25=1,INDEX(IPC!$D$5:$D$173,(Q25-1)-IPC!$J$2+1)*(INDEX(IPC!$D$5:$D$173,(Q25)-IPC!$J$2+1)/INDEX(IPC!$D$5:$D$173,(Q25-1)-IPC!$J$2+1))^(DAY(B25)/DAY(EOMONTH(B25,0))),"") | U25: =IF(S25=1,INDEX(IPC!$D$5:$D$173,(R25-1)-IPC!$J$2+1)*(INDEX(IPC!$D$5:$D$173,(R25)-IPC!$J$2+1)/INDEX(IPC!$D$5:$D$173,(R25-1)-IPC!$J$2+1))^(DAY(F25)/DAY(EOMONTH(F25,0))),"") | V25: =IF(AND(P25=1,F25>=$B$6),F25+ROW()/100000,"") | W25: =IF(P25=1,H25/(1+J25)-C25,"") | X25: =IF(AND(P25=1,F25>=$B$6),H25,"") | Y25: =IF(P25=1,YEAR(F25),"") | Z25: =IF(AND(P25=1,F25<=$B$6),G25,"") | AA25: =IF(AND(P25=1,F25>=$B$6),C25,"") | AB25: =IF(AND(P25=1,F25>=$B$6),G25,"")
F26: =IF(P26=1,B26+E26,"") | G26: =IF(P26=1,C26*D26/100*E26/365,"") | H26: =IF(P26=1,C26+G26,"") | I26: =IF(P26=1,(1+D26/100*E26/365)^(365/E26)-1,"") | J26: =IF(P26=1,IF(S26=1,U26/T26-1,(1+B5/100)^(E26/30)-1),"") | K26: =IF(P26=1,IF(S26=1,"IPC del INDEC","Estimada"),"") | L26: =IF(P26=1,H26/(1+J26)/C26-1,"") | M26: =IF(P26=0,IF(OR(A26<>"",ISNUMBER(B26),ISNUMBER(C26),ISNUMBER(D26),ISNUMBER(E26)),"Faltan datos: fecha, capital, TNA y días (mínimo 30)",""),IF(S26=1,IF(L26>=0,"Le ganó a la inflación","Perdió contra la inflación"),IF(L26>=0,"Le gana, si la inflación es la estimada","Pierde, si la inflación es la estimada"))) | N26: =IF(P26=0,"",IF(F26<$B$6,"Vencido",IF(F26=$B$6,"Vence hoy","Faltan "&(F26-$B$6)&IF(F26-$B$6=1," día"," días")))) | O26: =IF(OR(P26=0,F26<$B$6),"",IF(A26="","Cargá el banco para controlarla",IF(SUMIFS($X$15:$X$38,$A$15:$A$38,A26)>50000000,"Supera el tope en este banco","Dentro del tope"))) | P26: =IF(AND(ISNUMBER(B26),ISNUMBER(C26),C26>0,ISNUMBER(D26),D26>=0,ISNUMBER(E26),E26>=30),1,0) | Q26: =IF(P26=1,YEAR(B26)*12+MONTH(B26)-1,"") | R26: =IF(P26=1,YEAR(F26)*12+MONTH(F26)-1,"") | S26: =IF(P26=1,IF(AND(Q26-1>=IPC!$J$2,R26<=IPC!$J$3),1,0),0) | T26: =IF(S26=1,INDEX(IPC!$D$5:$D$173,(Q26-1)-IPC!$J$2+1)*(INDEX(IPC!$D$5:$D$173,(Q26)-IPC!$J$2+1)/INDEX(IPC!$D$5:$D$173,(Q26-1)-IPC!$J$2+1))^(DAY(B26)/DAY(EOMONTH(B26,0))),"") | U26: =IF(S26=1,INDEX(IPC!$D$5:$D$173,(R26-1)-IPC!$J$2+1)*(INDEX(IPC!$D$5:$D$173,(R26)-IPC!$J$2+1)/INDEX(IPC!$D$5:$D$173,(R26-1)-IPC!$J$2+1))^(DAY(F26)/DAY(EOMONTH(F26,0))),"") | V26: =IF(AND(P26=1,F26>=$B$6),F26+ROW()/100000,"") | W26: =IF(P26=1,H26/(1+J26)-C26,"") | X26: =IF(AND(P26=1,F26>=$B$6),H26,"") | Y26: =IF(P26=1,YEAR(F26),"") | Z26: =IF(AND(P26=1,F26<=$B$6),G26,"") | AA26: =IF(AND(P26=1,F26>=$B$6),C26,"") | AB26: =IF(AND(P26=1,F26>=$B$6),G26,"")
F27: =IF(P27=1,B27+E27,"") | G27: =IF(P27=1,C27*D27/100*E27/365,"") | H27: =IF(P27=1,C27+G27,"") | I27: =IF(P27=1,(1+D27/100*E27/365)^(365/E27)-1,"") | J27: =IF(P27=1,IF(S27=1,U27/T27-1,(1+B5/100)^(E27/30)-1),"") | K27: =IF(P27=1,IF(S27=1,"IPC del INDEC","Estimada"),"") | L27: =IF(P27=1,H27/(1+J27)/C27-1,"") | M27: =IF(P27=0,IF(OR(A27<>"",ISNUMBER(B27),ISNUMBER(C27),ISNUMBER(D27),ISNUMBER(E27)),"Faltan datos: fecha, capital, TNA y días (mínimo 30)",""),IF(S27=1,IF(L27>=0,"Le ganó a la inflación","Perdió contra la inflación"),IF(L27>=0,"Le gana, si la inflación es la estimada","Pierde, si la inflación es la estimada"))) | N27: =IF(P27=0,"",IF(F27<$B$6,"Vencido",IF(F27=$B$6,"Vence hoy","Faltan "&(F27-$B$6)&IF(F27-$B$6=1," día"," días")))) | O27: =IF(OR(P27=0,F27<$B$6),"",IF(A27="","Cargá el banco para controlarla",IF(SUMIFS($X$15:$X$38,$A$15:$A$38,A27)>50000000,"Supera el tope en este banco","Dentro del tope"))) | P27: =IF(AND(ISNUMBER(B27),ISNUMBER(C27),C27>0,ISNUMBER(D27),D27>=0,ISNUMBER(E27),E27>=30),1,0) | Q27: =IF(P27=1,YEAR(B27)*12+MONTH(B27)-1,"") | R27: =IF(P27=1,YEAR(F27)*12+MONTH(F27)-1,"") | S27: =IF(P27=1,IF(AND(Q27-1>=IPC!$J$2,R27<=IPC!$J$3),1,0),0) | T27: =IF(S27=1,INDEX(IPC!$D$5:$D$173,(Q27-1)-IPC!$J$2+1)*(INDEX(IPC!$D$5:$D$173,(Q27)-IPC!$J$2+1)/INDEX(IPC!$D$5:$D$173,(Q27-1)-IPC!$J$2+1))^(DAY(B27)/DAY(EOMONTH(B27,0))),"") | U27: =IF(S27=1,INDEX(IPC!$D$5:$D$173,(R27-1)-IPC!$J$2+1)*(INDEX(IPC!$D$5:$D$173,(R27)-IPC!$J$2+1)/INDEX(IPC!$D$5:$D$173,(R27-1)-IPC!$J$2+1))^(DAY(F27)/DAY(EOMONTH(F27,0))),"") | V27: =IF(AND(P27=1,F27>=$B$6),F27+ROW()/100000,"") | W27: =IF(P27=1,H27/(1+J27)-C27,"") | X27: =IF(AND(P27=1,F27>=$B$6),H27,"") | Y27: =IF(P27=1,YEAR(F27),"") | Z27: =IF(AND(P27=1,F27<=$B$6),G27,"") | AA27: =IF(AND(P27=1,F27>=$B$6),C27,"") | AB27: =IF(AND(P27=1,F27>=$B$6),G27,"")
F28: =IF(P28=1,B28+E28,"") | G28: =IF(P28=1,C28*D28/100*E28/365,"") | H28: =IF(P28=1,C28+G28,"") | I28: =IF(P28=1,(1+D28/100*E28/365)^(365/E28)-1,"") | J28: =IF(P28=1,IF(S28=1,U28/T28-1,(1+B5/100)^(E28/30)-1),"") | K28: =IF(P28=1,IF(S28=1,"IPC del INDEC","Estimada"),"") | L28: =IF(P28=1,H28/(1+J28)/C28-1,"") | M28: =IF(P28=0,IF(OR(A28<>"",ISNUMBER(B28),ISNUMBER(C28),ISNUMBER(D28),ISNUMBER(E28)),"Faltan datos: fecha, capital, TNA y días (mínimo 30)",""),IF(S28=1,IF(L28>=0,"Le ganó a la inflación","Perdió contra la inflación"),IF(L28>=0,"Le gana, si la inflación es la estimada","Pierde, si la inflación es la estimada"))) | N28: =IF(P28=0,"",IF(F28<$B$6,"Vencido",IF(F28=$B$6,"Vence hoy","Faltan "&(F28-$B$6)&IF(F28-$B$6=1," día"," días")))) | O28: =IF(OR(P28=0,F28<$B$6),"",IF(A28="","Cargá el banco para controlarla",IF(SUMIFS($X$15:$X$38,$A$15:$A$38,A28)>50000000,"Supera el tope en este banco","Dentro del tope"))) | P28: =IF(AND(ISNUMBER(B28),ISNUMBER(C28),C28>0,ISNUMBER(D28),D28>=0,ISNUMBER(E28),E28>=30),1,0) | Q28: =IF(P28=1,YEAR(B28)*12+MONTH(B28)-1,"") | R28: =IF(P28=1,YEAR(F28)*12+MONTH(F28)-1,"") | S28: =IF(P28=1,IF(AND(Q28-1>=IPC!$J$2,R28<=IPC!$J$3),1,0),0) | T28: =IF(S28=1,INDEX(IPC!$D$5:$D$173,(Q28-1)-IPC!$J$2+1)*(INDEX(IPC!$D$5:$D$173,(Q28)-IPC!$J$2+1)/INDEX(IPC!$D$5:$D$173,(Q28-1)-IPC!$J$2+1))^(DAY(B28)/DAY(EOMONTH(B28,0))),"") | U28: =IF(S28=1,INDEX(IPC!$D$5:$D$173,(R28-1)-IPC!$J$2+1)*(INDEX(IPC!$D$5:$D$173,(R28)-IPC!$J$2+1)/INDEX(IPC!$D$5:$D$173,(R28-1)-IPC!$J$2+1))^(DAY(F28)/DAY(EOMONTH(F28,0))),"") | V28: =IF(AND(P28=1,F28>=$B$6),F28+ROW()/100000,"") | W28: =IF(P28=1,H28/(1+J28)-C28,"") | X28: =IF(AND(P28=1,F28>=$B$6),H28,"") | Y28: =IF(P28=1,YEAR(F28),"") | Z28: =IF(AND(P28=1,F28<=$B$6),G28,"") | AA28: =IF(AND(P28=1,F28>=$B$6),C28,"") | AB28: =IF(AND(P28=1,F28>=$B$6),G28,"")
F29: =IF(P29=1,B29+E29,"") | G29: =IF(P29=1,C29*D29/100*E29/365,"") | H29: =IF(P29=1,C29+G29,"") | I29: =IF(P29=1,(1+D29/100*E29/365)^(365/E29)-1,"") | J29: =IF(P29=1,IF(S29=1,U29/T29-1,(1+B5/100)^(E29/30)-1),"") | K29: =IF(P29=1,IF(S29=1,"IPC del INDEC","Estimada"),"") | L29: =IF(P29=1,H29/(1+J29)/C29-1,"") | M29: =IF(P29=0,IF(OR(A29<>"",ISNUMBER(B29),ISNUMBER(C29),ISNUMBER(D29),ISNUMBER(E29)),"Faltan datos: fecha, capital, TNA y días (mínimo 30)",""),IF(S29=1,IF(L29>=0,"Le ganó a la inflación","Perdió contra la inflación"),IF(L29>=0,"Le gana, si la inflación es la estimada","Pierde, si la inflación es la estimada"))) | N29: =IF(P29=0,"",IF(F29<$B$6,"Vencido",IF(F29=$B$6,"Vence hoy","Faltan "&(F29-$B$6)&IF(F29-$B$6=1," día"," días")))) | O29: =IF(OR(P29=0,F29<$B$6),"",IF(A29="","Cargá el banco para controlarla",IF(SUMIFS($X$15:$X$38,$A$15:$A$38,A29)>50000000,"Supera el tope en este banco","Dentro del tope"))) | P29: =IF(AND(ISNUMBER(B29),ISNUMBER(C29),C29>0,ISNUMBER(D29),D29>=0,ISNUMBER(E29),E29>=30),1,0) | Q29: =IF(P29=1,YEAR(B29)*12+MONTH(B29)-1,"") | R29: =IF(P29=1,YEAR(F29)*12+MONTH(F29)-1,"") | S29: =IF(P29=1,IF(AND(Q29-1>=IPC!$J$2,R29<=IPC!$J$3),1,0),0) | T29: =IF(S29=1,INDEX(IPC!$D$5:$D$173,(Q29-1)-IPC!$J$2+1)*(INDEX(IPC!$D$5:$D$173,(Q29)-IPC!$J$2+1)/INDEX(IPC!$D$5:$D$173,(Q29-1)-IPC!$J$2+1))^(DAY(B29)/DAY(EOMONTH(B29,0))),"") | U29: =IF(S29=1,INDEX(IPC!$D$5:$D$173,(R29-1)-IPC!$J$2+1)*(INDEX(IPC!$D$5:$D$173,(R29)-IPC!$J$2+1)/INDEX(IPC!$D$5:$D$173,(R29-1)-IPC!$J$2+1))^(DAY(F29)/DAY(EOMONTH(F29,0))),"") | V29: =IF(AND(P29=1,F29>=$B$6),F29+ROW()/100000,"") | W29: =IF(P29=1,H29/(1+J29)-C29,"") | X29: =IF(AND(P29=1,F29>=$B$6),H29,"") | Y29: =IF(P29=1,YEAR(F29),"") | Z29: =IF(AND(P29=1,F29<=$B$6),G29,"") | AA29: =IF(AND(P29=1,F29>=$B$6),C29,"") | AB29: =IF(AND(P29=1,F29>=$B$6),G29,"")
F30: =IF(P30=1,B30+E30,"") | G30: =IF(P30=1,C30*D30/100*E30/365,"") | H30: =IF(P30=1,C30+G30,"") | I30: =IF(P30=1,(1+D30/100*E30/365)^(365/E30)-1,"") | J30: =IF(P30=1,IF(S30=1,U30/T30-1,(1+B5/100)^(E30/30)-1),"") | K30: =IF(P30=1,IF(S30=1,"IPC del INDEC","Estimada"),"") | L30: =IF(P30=1,H30/(1+J30)/C30-1,"") | M30: =IF(P30=0,IF(OR(A30<>"",ISNUMBER(B30),ISNUMBER(C30),ISNUMBER(D30),ISNUMBER(E30)),"Faltan datos: fecha, capital, TNA y días (mínimo 30)",""),IF(S30=1,IF(L30>=0,"Le ganó a la inflación","Perdió contra la inflación"),IF(L30>=0,"Le gana, si la inflación es la estimada","Pierde, si la inflación es la estimada"))) | N30: =IF(P30=0,"",IF(F30<$B$6,"Vencido",IF(F30=$B$6,"Vence hoy","Faltan "&(F30-$B$6)&IF(F30-$B$6=1," día"," días")))) | O30: =IF(OR(P30=0,F30<$B$6),"",IF(A30="","Cargá el banco para controlarla",IF(SUMIFS($X$15:$X$38,$A$15:$A$38,A30)>50000000,"Supera el tope en este banco","Dentro del tope"))) | P30: =IF(AND(ISNUMBER(B30),ISNUMBER(C30),C30>0,ISNUMBER(D30),D30>=0,ISNUMBER(E30),E30>=30),1,0) | Q30: =IF(P30=1,YEAR(B30)*12+MONTH(B30)-1,"") | R30: =IF(P30=1,YEAR(F30)*12+MONTH(F30)-1,"") | S30: =IF(P30=1,IF(AND(Q30-1>=IPC!$J$2,R30<=IPC!$J$3),1,0),0) | T30: =IF(S30=1,INDEX(IPC!$D$5:$D$173,(Q30-1)-IPC!$J$2+1)*(INDEX(IPC!$D$5:$D$173,(Q30)-IPC!$J$2+1)/INDEX(IPC!$D$5:$D$173,(Q30-1)-IPC!$J$2+1))^(DAY(B30)/DAY(EOMONTH(B30,0))),"") | U30: =IF(S30=1,INDEX(IPC!$D$5:$D$173,(R30-1)-IPC!$J$2+1)*(INDEX(IPC!$D$5:$D$173,(R30)-IPC!$J$2+1)/INDEX(IPC!$D$5:$D$173,(R30-1)-IPC!$J$2+1))^(DAY(F30)/DAY(EOMONTH(F30,0))),"") | V30: =IF(AND(P30=1,F30>=$B$6),F30+ROW()/100000,"") | W30: =IF(P30=1,H30/(1+J30)-C30,"") | X30: =IF(AND(P30=1,F30>=$B$6),H30,"") | Y30: =IF(P30=1,YEAR(F30),"") | Z30: =IF(AND(P30=1,F30<=$B$6),G30,"") | AA30: =IF(AND(P30=1,F30>=$B$6),C30,"") | AB30: =IF(AND(P30=1,F30>=$B$6),G30,"")
F31: =IF(P31=1,B31+E31,"") | G31: =IF(P31=1,C31*D31/100*E31/365,"") | H31: =IF(P31=1,C31+G31,"") | I31: =IF(P31=1,(1+D31/100*E31/365)^(365/E31)-1,"") | J31: =IF(P31=1,IF(S31=1,U31/T31-1,(1+B5/100)^(E31/30)-1),"") | K31: =IF(P31=1,IF(S31=1,"IPC del INDEC","Estimada"),"") | L31: =IF(P31=1,H31/(1+J31)/C31-1,"") | M31: =IF(P31=0,IF(OR(A31<>"",ISNUMBER(B31),ISNUMBER(C31),ISNUMBER(D31),ISNUMBER(E31)),"Faltan datos: fecha, capital, TNA y días (mínimo 30)",""),IF(S31=1,IF(L31>=0,"Le ganó a la inflación","Perdió contra la inflación"),IF(L31>=0,"Le gana, si la inflación es la estimada","Pierde, si la inflación es la estimada"))) | N31: =IF(P31=0,"",IF(F31<$B$6,"Vencido",IF(F31=$B$6,"Vence hoy","Faltan "&(F31-$B$6)&IF(F31-$B$6=1," día"," días")))) | O31: =IF(OR(P31=0,F31<$B$6),"",IF(A31="","Cargá el banco para controlarla",IF(SUMIFS($X$15:$X$38,$A$15:$A$38,A31)>50000000,"Supera el tope en este banco","Dentro del tope"))) | P31: =IF(AND(ISNUMBER(B31),ISNUMBER(C31),C31>0,ISNUMBER(D31),D31>=0,ISNUMBER(E31),E31>=30),1,0) | Q31: =IF(P31=1,YEAR(B31)*12+MONTH(B31)-1,"") | R31: =IF(P31=1,YEAR(F31)*12+MONTH(F31)-1,"") | S31: =IF(P31=1,IF(AND(Q31-1>=IPC!$J$2,R31<=IPC!$J$3),1,0),0) | T31: =IF(S31=1,INDEX(IPC!$D$5:$D$173,(Q31-1)-IPC!$J$2+1)*(INDEX(IPC!$D$5:$D$173,(Q31)-IPC!$J$2+1)/INDEX(IPC!$D$5:$D$173,(Q31-1)-IPC!$J$2+1))^(DAY(B31)/DAY(EOMONTH(B31,0))),"") | U31: =IF(S31=1,INDEX(IPC!$D$5:$D$173,(R31-1)-IPC!$J$2+1)*(INDEX(IPC!$D$5:$D$173,(R31)-IPC!$J$2+1)/INDEX(IPC!$D$5:$D$173,(R31-1)-IPC!$J$2+1))^(DAY(F31)/DAY(EOMONTH(F31,0))),"") | V31: =IF(AND(P31=1,F31>=$B$6),F31+ROW()/100000,"") | W31: =IF(P31=1,H31/(1+J31)-C31,"") | X31: =IF(AND(P31=1,F31>=$B$6),H31,"") | Y31: =IF(P31=1,YEAR(F31),"") | Z31: =IF(AND(P31=1,F31<=$B$6),G31,"") | AA31: =IF(AND(P31=1,F31>=$B$6),C31,"") | AB31: =IF(AND(P31=1,F31>=$B$6),G31,"")
F32: =IF(P32=1,B32+E32,"") | G32: =IF(P32=1,C32*D32/100*E32/365,"") | H32: =IF(P32=1,C32+G32,"") | I32: =IF(P32=1,(1+D32/100*E32/365)^(365/E32)-1,"") | J32: =IF(P32=1,IF(S32=1,U32/T32-1,(1+B5/100)^(E32/30)-1),"") | K32: =IF(P32=1,IF(S32=1,"IPC del INDEC","Estimada"),"") | L32: =IF(P32=1,H32/(1+J32)/C32-1,"") | M32: =IF(P32=0,IF(OR(A32<>"",ISNUMBER(B32),ISNUMBER(C32),ISNUMBER(D32),ISNUMBER(E32)),"Faltan datos: fecha, capital, TNA y días (mínimo 30)",""),IF(S32=1,IF(L32>=0,"Le ganó a la inflación","Perdió contra la inflación"),IF(L32>=0,"Le gana, si la inflación es la estimada","Pierde, si la inflación es la estimada"))) | N32: =IF(P32=0,"",IF(F32<$B$6,"Vencido",IF(F32=$B$6,"Vence hoy","Faltan "&(F32-$B$6)&IF(F32-$B$6=1," día"," días")))) | O32: =IF(OR(P32=0,F32<$B$6),"",IF(A32="","Cargá el banco para controlarla",IF(SUMIFS($X$15:$X$38,$A$15:$A$38,A32)>50000000,"Supera el tope en este banco","Dentro del tope"))) | P32: =IF(AND(ISNUMBER(B32),ISNUMBER(C32),C32>0,ISNUMBER(D32),D32>=0,ISNUMBER(E32),E32>=30),1,0) | Q32: =IF(P32=1,YEAR(B32)*12+MONTH(B32)-1,"") | R32: =IF(P32=1,YEAR(F32)*12+MONTH(F32)-1,"") | S32: =IF(P32=1,IF(AND(Q32-1>=IPC!$J$2,R32<=IPC!$J$3),1,0),0) | T32: =IF(S32=1,INDEX(IPC!$D$5:$D$173,(Q32-1)-IPC!$J$2+1)*(INDEX(IPC!$D$5:$D$173,(Q32)-IPC!$J$2+1)/INDEX(IPC!$D$5:$D$173,(Q32-1)-IPC!$J$2+1))^(DAY(B32)/DAY(EOMONTH(B32,0))),"") | U32: =IF(S32=1,INDEX(IPC!$D$5:$D$173,(R32-1)-IPC!$J$2+1)*(INDEX(IPC!$D$5:$D$173,(R32)-IPC!$J$2+1)/INDEX(IPC!$D$5:$D$173,(R32-1)-IPC!$J$2+1))^(DAY(F32)/DAY(EOMONTH(F32,0))),"") | V32: =IF(AND(P32=1,F32>=$B$6),F32+ROW()/100000,"") | W32: =IF(P32=1,H32/(1+J32)-C32,"") | X32: =IF(AND(P32=1,F32>=$B$6),H32,"") | Y32: =IF(P32=1,YEAR(F32),"") | Z32: =IF(AND(P32=1,F32<=$B$6),G32,"") | AA32: =IF(AND(P32=1,F32>=$B$6),C32,"") | AB32: =IF(AND(P32=1,F32>=$B$6),G32,"")
F33: =IF(P33=1,B33+E33,"") | G33: =IF(P33=1,C33*D33/100*E33/365,"") | H33: =IF(P33=1,C33+G33,"") | I33: =IF(P33=1,(1+D33/100*E33/365)^(365/E33)-1,"") | J33: =IF(P33=1,IF(S33=1,U33/T33-1,(1+B5/100)^(E33/30)-1),"") | K33: =IF(P33=1,IF(S33=1,"IPC del INDEC","Estimada"),"") | L33: =IF(P33=1,H33/(1+J33)/C33-1,"") | M33: =IF(P33=0,IF(OR(A33<>"",ISNUMBER(B33),ISNUMBER(C33),ISNUMBER(D33),ISNUMBER(E33)),"Faltan datos: fecha, capital, TNA y días (mínimo 30)",""),IF(S33=1,IF(L33>=0,"Le ganó a la inflación","Perdió contra la inflación"),IF(L33>=0,"Le gana, si la inflación es la estimada","Pierde, si la inflación es la estimada"))) | N33: =IF(P33=0,"",IF(F33<$B$6,"Vencido",IF(F33=$B$6,"Vence hoy","Faltan "&(F33-$B$6)&IF(F33-$B$6=1," día"," días")))) | O33: =IF(OR(P33=0,F33<$B$6),"",IF(A33="","Cargá el banco para controlarla",IF(SUMIFS($X$15:$X$38,$A$15:$A$38,A33)>50000000,"Supera el tope en este banco","Dentro del tope"))) | P33: =IF(AND(ISNUMBER(B33),ISNUMBER(C33),C33>0,ISNUMBER(D33),D33>=0,ISNUMBER(E33),E33>=30),1,0) | Q33: =IF(P33=1,YEAR(B33)*12+MONTH(B33)-1,"") | R33: =IF(P33=1,YEAR(F33)*12+MONTH(F33)-1,"") | S33: =IF(P33=1,IF(AND(Q33-1>=IPC!$J$2,R33<=IPC!$J$3),1,0),0) | T33: =IF(S33=1,INDEX(IPC!$D$5:$D$173,(Q33-1)-IPC!$J$2+1)*(INDEX(IPC!$D$5:$D$173,(Q33)-IPC!$J$2+1)/INDEX(IPC!$D$5:$D$173,(Q33-1)-IPC!$J$2+1))^(DAY(B33)/DAY(EOMONTH(B33,0))),"") | U33: =IF(S33=1,INDEX(IPC!$D$5:$D$173,(R33-1)-IPC!$J$2+1)*(INDEX(IPC!$D$5:$D$173,(R33)-IPC!$J$2+1)/INDEX(IPC!$D$5:$D$173,(R33-1)-IPC!$J$2+1))^(DAY(F33)/DAY(EOMONTH(F33,0))),"") | V33: =IF(AND(P33=1,F33>=$B$6),F33+ROW()/100000,"") | W33: =IF(P33=1,H33/(1+J33)-C33,"") | X33: =IF(AND(P33=1,F33>=$B$6),H33,"") | Y33: =IF(P33=1,YEAR(F33),"") | Z33: =IF(AND(P33=1,F33<=$B$6),G33,"") | AA33: =IF(AND(P33=1,F33>=$B$6),C33,"") | AB33: =IF(AND(P33=1,F33>=$B$6),G33,"")
F34: =IF(P34=1,B34+E34,"") | G34: =IF(P34=1,C34*D34/100*E34/365,"") | H34: =IF(P34=1,C34+G34,"") | I34: =IF(P34=1,(1+D34/100*E34/365)^(365/E34)-1,"") | J34: =IF(P34=1,IF(S34=1,U34/T34-1,(1+B5/100)^(E34/30)-1),"") | K34: =IF(P34=1,IF(S34=1,"IPC del INDEC","Estimada"),"") | L34: =IF(P34=1,H34/(1+J34)/C34-1,"") | M34: =IF(P34=0,IF(OR(A34<>"",ISNUMBER(B34),ISNUMBER(C34),ISNUMBER(D34),ISNUMBER(E34)),"Faltan datos: fecha, capital, TNA y días (mínimo 30)",""),IF(S34=1,IF(L34>=0,"Le ganó a la inflación","Perdió contra la inflación"),IF(L34>=0,"Le gana, si la inflación es la estimada","Pierde, si la inflación es la estimada"))) | N34: =IF(P34=0,"",IF(F34<$B$6,"Vencido",IF(F34=$B$6,"Vence hoy","Faltan "&(F34-$B$6)&IF(F34-$B$6=1," día"," días")))) | O34: =IF(OR(P34=0,F34<$B$6),"",IF(A34="","Cargá el banco para controlarla",IF(SUMIFS($X$15:$X$38,$A$15:$A$38,A34)>50000000,"Supera el tope en este banco","Dentro del tope"))) | P34: =IF(AND(ISNUMBER(B34),ISNUMBER(C34),C34>0,ISNUMBER(D34),D34>=0,ISNUMBER(E34),E34>=30),1,0) | Q34: =IF(P34=1,YEAR(B34)*12+MONTH(B34)-1,"") | R34: =IF(P34=1,YEAR(F34)*12+MONTH(F34)-1,"") | S34: =IF(P34=1,IF(AND(Q34-1>=IPC!$J$2,R34<=IPC!$J$3),1,0),0) | T34: =IF(S34=1,INDEX(IPC!$D$5:$D$173,(Q34-1)-IPC!$J$2+1)*(INDEX(IPC!$D$5:$D$173,(Q34)-IPC!$J$2+1)/INDEX(IPC!$D$5:$D$173,(Q34-1)-IPC!$J$2+1))^(DAY(B34)/DAY(EOMONTH(B34,0))),"") | U34: =IF(S34=1,INDEX(IPC!$D$5:$D$173,(R34-1)-IPC!$J$2+1)*(INDEX(IPC!$D$5:$D$173,(R34)-IPC!$J$2+1)/INDEX(IPC!$D$5:$D$173,(R34-1)-IPC!$J$2+1))^(DAY(F34)/DAY(EOMONTH(F34,0))),"") | V34: =IF(AND(P34=1,F34>=$B$6),F34+ROW()/100000,"") | W34: =IF(P34=1,H34/(1+J34)-C34,"") | X34: =IF(AND(P34=1,F34>=$B$6),H34,"") | Y34: =IF(P34=1,YEAR(F34),"") | Z34: =IF(AND(P34=1,F34<=$B$6),G34,"") | AA34: =IF(AND(P34=1,F34>=$B$6),C34,"") | AB34: =IF(AND(P34=1,F34>=$B$6),G34,"")
F35: =IF(P35=1,B35+E35,"") | G35: =IF(P35=1,C35*D35/100*E35/365,"") | H35: =IF(P35=1,C35+G35,"") | I35: =IF(P35=1,(1+D35/100*E35/365)^(365/E35)-1,"") | J35: =IF(P35=1,IF(S35=1,U35/T35-1,(1+B5/100)^(E35/30)-1),"") | K35: =IF(P35=1,IF(S35=1,"IPC del INDEC","Estimada"),"") | L35: =IF(P35=1,H35/(1+J35)/C35-1,"") | M35: =IF(P35=0,IF(OR(A35<>"",ISNUMBER(B35),ISNUMBER(C35),ISNUMBER(D35),ISNUMBER(E35)),"Faltan datos: fecha, capital, TNA y días (mínimo 30)",""),IF(S35=1,IF(L35>=0,"Le ganó a la inflación","Perdió contra la inflación"),IF(L35>=0,"Le gana, si la inflación es la estimada","Pierde, si la inflación es la estimada"))) | N35: =IF(P35=0,"",IF(F35<$B$6,"Vencido",IF(F35=$B$6,"Vence hoy","Faltan "&(F35-$B$6)&IF(F35-$B$6=1," día"," días")))) | O35: =IF(OR(P35=0,F35<$B$6),"",IF(A35="","Cargá el banco para controlarla",IF(SUMIFS($X$15:$X$38,$A$15:$A$38,A35)>50000000,"Supera el tope en este banco","Dentro del tope"))) | P35: =IF(AND(ISNUMBER(B35),ISNUMBER(C35),C35>0,ISNUMBER(D35),D35>=0,ISNUMBER(E35),E35>=30),1,0) | Q35: =IF(P35=1,YEAR(B35)*12+MONTH(B35)-1,"") | R35: =IF(P35=1,YEAR(F35)*12+MONTH(F35)-1,"") | S35: =IF(P35=1,IF(AND(Q35-1>=IPC!$J$2,R35<=IPC!$J$3),1,0),0) | T35: =IF(S35=1,INDEX(IPC!$D$5:$D$173,(Q35-1)-IPC!$J$2+1)*(INDEX(IPC!$D$5:$D$173,(Q35)-IPC!$J$2+1)/INDEX(IPC!$D$5:$D$173,(Q35-1)-IPC!$J$2+1))^(DAY(B35)/DAY(EOMONTH(B35,0))),"") | U35: =IF(S35=1,INDEX(IPC!$D$5:$D$173,(R35-1)-IPC!$J$2+1)*(INDEX(IPC!$D$5:$D$173,(R35)-IPC!$J$2+1)/INDEX(IPC!$D$5:$D$173,(R35-1)-IPC!$J$2+1))^(DAY(F35)/DAY(EOMONTH(F35,0))),"") | V35: =IF(AND(P35=1,F35>=$B$6),F35+ROW()/100000,"") | W35: =IF(P35=1,H35/(1+J35)-C35,"") | X35: =IF(AND(P35=1,F35>=$B$6),H35,"") | Y35: =IF(P35=1,YEAR(F35),"") | Z35: =IF(AND(P35=1,F35<=$B$6),G35,"") | AA35: =IF(AND(P35=1,F35>=$B$6),C35,"") | AB35: =IF(AND(P35=1,F35>=$B$6),G35,"")
F36: =IF(P36=1,B36+E36,"") | G36: =IF(P36=1,C36*D36/100*E36/365,"") | H36: =IF(P36=1,C36+G36,"") | I36: =IF(P36=1,(1+D36/100*E36/365)^(365/E36)-1,"") | J36: =IF(P36=1,IF(S36=1,U36/T36-1,(1+B5/100)^(E36/30)-1),"") | K36: =IF(P36=1,IF(S36=1,"IPC del INDEC","Estimada"),"") | L36: =IF(P36=1,H36/(1+J36)/C36-1,"") | M36: =IF(P36=0,IF(OR(A36<>"",ISNUMBER(B36),ISNUMBER(C36),ISNUMBER(D36),ISNUMBER(E36)),"Faltan datos: fecha, capital, TNA y días (mínimo 30)",""),IF(S36=1,IF(L36>=0,"Le ganó a la inflación","Perdió contra la inflación"),IF(L36>=0,"Le gana, si la inflación es la estimada","Pierde, si la inflación es la estimada"))) | N36: =IF(P36=0,"",IF(F36<$B$6,"Vencido",IF(F36=$B$6,"Vence hoy","Faltan "&(F36-$B$6)&IF(F36-$B$6=1," día"," días")))) | O36: =IF(OR(P36=0,F36<$B$6),"",IF(A36="","Cargá el banco para controlarla",IF(SUMIFS($X$15:$X$38,$A$15:$A$38,A36)>50000000,"Supera el tope en este banco","Dentro del tope"))) | P36: =IF(AND(ISNUMBER(B36),ISNUMBER(C36),C36>0,ISNUMBER(D36),D36>=0,ISNUMBER(E36),E36>=30),1,0) | Q36: =IF(P36=1,YEAR(B36)*12+MONTH(B36)-1,"") | R36: =IF(P36=1,YEAR(F36)*12+MONTH(F36)-1,"") | S36: =IF(P36=1,IF(AND(Q36-1>=IPC!$J$2,R36<=IPC!$J$3),1,0),0) | T36: =IF(S36=1,INDEX(IPC!$D$5:$D$173,(Q36-1)-IPC!$J$2+1)*(INDEX(IPC!$D$5:$D$173,(Q36)-IPC!$J$2+1)/INDEX(IPC!$D$5:$D$173,(Q36-1)-IPC!$J$2+1))^(DAY(B36)/DAY(EOMONTH(B36,0))),"") | U36: =IF(S36=1,INDEX(IPC!$D$5:$D$173,(R36-1)-IPC!$J$2+1)*(INDEX(IPC!$D$5:$D$173,(R36)-IPC!$J$2+1)/INDEX(IPC!$D$5:$D$173,(R36-1)-IPC!$J$2+1))^(DAY(F36)/DAY(EOMONTH(F36,0))),"") | V36: =IF(AND(P36=1,F36>=$B$6),F36+ROW()/100000,"") | W36: =IF(P36=1,H36/(1+J36)-C36,"") | X36: =IF(AND(P36=1,F36>=$B$6),H36,"") | Y36: =IF(P36=1,YEAR(F36),"") | Z36: =IF(AND(P36=1,F36<=$B$6),G36,"") | AA36: =IF(AND(P36=1,F36>=$B$6),C36,"") | AB36: =IF(AND(P36=1,F36>=$B$6),G36,"")
F37: =IF(P37=1,B37+E37,"") | G37: =IF(P37=1,C37*D37/100*E37/365,"") | H37: =IF(P37=1,C37+G37,"") | I37: =IF(P37=1,(1+D37/100*E37/365)^(365/E37)-1,"") | J37: =IF(P37=1,IF(S37=1,U37/T37-1,(1+B5/100)^(E37/30)-1),"") | K37: =IF(P37=1,IF(S37=1,"IPC del INDEC","Estimada"),"") | L37: =IF(P37=1,H37/(1+J37)/C37-1,"") | M37: =IF(P37=0,IF(OR(A37<>"",ISNUMBER(B37),ISNUMBER(C37),ISNUMBER(D37),ISNUMBER(E37)),"Faltan datos: fecha, capital, TNA y días (mínimo 30)",""),IF(S37=1,IF(L37>=0,"Le ganó a la inflación","Perdió contra la inflación"),IF(L37>=0,"Le gana, si la inflación es la estimada","Pierde, si la inflación es la estimada"))) | N37: =IF(P37=0,"",IF(F37<$B$6,"Vencido",IF(F37=$B$6,"Vence hoy","Faltan "&(F37-$B$6)&IF(F37-$B$6=1," día"," días")))) | O37: =IF(OR(P37=0,F37<$B$6),"",IF(A37="","Cargá el banco para controlarla",IF(SUMIFS($X$15:$X$38,$A$15:$A$38,A37)>50000000,"Supera el tope en este banco","Dentro del tope"))) | P37: =IF(AND(ISNUMBER(B37),ISNUMBER(C37),C37>0,ISNUMBER(D37),D37>=0,ISNUMBER(E37),E37>=30),1,0) | Q37: =IF(P37=1,YEAR(B37)*12+MONTH(B37)-1,"") | R37: =IF(P37=1,YEAR(F37)*12+MONTH(F37)-1,"") | S37: =IF(P37=1,IF(AND(Q37-1>=IPC!$J$2,R37<=IPC!$J$3),1,0),0) | T37: =IF(S37=1,INDEX(IPC!$D$5:$D$173,(Q37-1)-IPC!$J$2+1)*(INDEX(IPC!$D$5:$D$173,(Q37)-IPC!$J$2+1)/INDEX(IPC!$D$5:$D$173,(Q37-1)-IPC!$J$2+1))^(DAY(B37)/DAY(EOMONTH(B37,0))),"") | U37: =IF(S37=1,INDEX(IPC!$D$5:$D$173,(R37-1)-IPC!$J$2+1)*(INDEX(IPC!$D$5:$D$173,(R37)-IPC!$J$2+1)/INDEX(IPC!$D$5:$D$173,(R37-1)-IPC!$J$2+1))^(DAY(F37)/DAY(EOMONTH(F37,0))),"") | V37: =IF(AND(P37=1,F37>=$B$6),F37+ROW()/100000,"") | W37: =IF(P37=1,H37/(1+J37)-C37,"") | X37: =IF(AND(P37=1,F37>=$B$6),H37,"") | Y37: =IF(P37=1,YEAR(F37),"") | Z37: =IF(AND(P37=1,F37<=$B$6),G37,"") | AA37: =IF(AND(P37=1,F37>=$B$6),C37,"") | AB37: =IF(AND(P37=1,F37>=$B$6),G37,"")
F38: =IF(P38=1,B38+E38,"") | G38: =IF(P38=1,C38*D38/100*E38/365,"") | H38: =IF(P38=1,C38+G38,"") | I38: =IF(P38=1,(1+D38/100*E38/365)^(365/E38)-1,"") | J38: =IF(P38=1,IF(S38=1,U38/T38-1,(1+B5/100)^(E38/30)-1),"") | K38: =IF(P38=1,IF(S38=1,"IPC del INDEC","Estimada"),"") | L38: =IF(P38=1,H38/(1+J38)/C38-1,"") | M38: =IF(P38=0,IF(OR(A38<>"",ISNUMBER(B38),ISNUMBER(C38),ISNUMBER(D38),ISNUMBER(E38)),"Faltan datos: fecha, capital, TNA y días (mínimo 30)",""),IF(S38=1,IF(L38>=0,"Le ganó a la inflación","Perdió contra la inflación"),IF(L38>=0,"Le gana, si la inflación es la estimada","Pierde, si la inflación es la estimada"))) | N38: =IF(P38=0,"",IF(F38<$B$6,"Vencido",IF(F38=$B$6,"Vence hoy","Faltan "&(F38-$B$6)&IF(F38-$B$6=1," día"," días")))) | O38: =IF(OR(P38=0,F38<$B$6),"",IF(A38="","Cargá el banco para controlarla",IF(SUMIFS($X$15:$X$38,$A$15:$A$38,A38)>50000000,"Supera el tope en este banco","Dentro del tope"))) | P38: =IF(AND(ISNUMBER(B38),ISNUMBER(C38),C38>0,ISNUMBER(D38),D38>=0,ISNUMBER(E38),E38>=30),1,0) | Q38: =IF(P38=1,YEAR(B38)*12+MONTH(B38)-1,"") | R38: =IF(P38=1,YEAR(F38)*12+MONTH(F38)-1,"") | S38: =IF(P38=1,IF(AND(Q38-1>=IPC!$J$2,R38<=IPC!$J$3),1,0),0) | T38: =IF(S38=1,INDEX(IPC!$D$5:$D$173,(Q38-1)-IPC!$J$2+1)*(INDEX(IPC!$D$5:$D$173,(Q38)-IPC!$J$2+1)/INDEX(IPC!$D$5:$D$173,(Q38-1)-IPC!$J$2+1))^(DAY(B38)/DAY(EOMONTH(B38,0))),"") | U38: =IF(S38=1,INDEX(IPC!$D$5:$D$173,(R38-1)-IPC!$J$2+1)*(INDEX(IPC!$D$5:$D$173,(R38)-IPC!$J$2+1)/INDEX(IPC!$D$5:$D$173,(R38-1)-IPC!$J$2+1))^(DAY(F38)/DAY(EOMONTH(F38,0))),"") | V38: =IF(AND(P38=1,F38>=$B$6),F38+ROW()/100000,"") | W38: =IF(P38=1,H38/(1+J38)-C38,"") | X38: =IF(AND(P38=1,F38>=$B$6),H38,"") | Y38: =IF(P38=1,YEAR(F38),"") | Z38: =IF(AND(P38=1,F38<=$B$6),G38,"") | AA38: =IF(AND(P38=1,F38>=$B$6),C38,"") | AB38: =IF(AND(P38=1,F38>=$B$6),G38,"")
A40: Interés = capital × TNA × días ÷ 365, la convención de los bancos argentinos. Tasa real = lo que cobrás descontada la inflación del período: si es positiva, tu plata compra más que el día que la pusiste. «IPC del INDEC»: el INDEC ya publicó todos los meses del plazo fijo (el índice se reparte día por día dentro de cada mes). «Estimada»: falta algún mes y se usa la inflación de la celda B5, igual que la calculadora de calcular.ar.
A41: Garantía de los depósitos: hasta $ 50.000.000 por persona, sumando capital e intereses de sus depósitos, desde el 1/4/2026 (Com. «A» 8407 del BCRA). No cubre los plazos fijos pactados a una tasa mayor a la de referencia del BCRA. Si el vencimiento cae en un día no hábil, el banco lo paga el día hábil siguiente.

Sheet Calendario
A1: Calendario de vencimientos
A2: =IF(COUNT('Mis plazos fijos'!$V$15:$V$38)=0,"No hay plazos fijos vigentes: cargalos en la hoja «Mis plazos fijos» y acá aparecen ordenados por fecha.","Tus plazos fijos vigentes, del que vence primero al último. Esta hoja no se completa: sale sola de «Mis plazos fijos».")
A4: Vence el | B4: Banco | C4: Capital | D4: Interés | E4: Se acredita | F4: Faltan (días) | G4: Tasa real
A5: =IFERROR(INT(SMALL('Mis plazos fijos'!$V$15:$V$38,1)),"") | B5: =IF($J5="","",INDEX('Mis plazos fijos'!$A$1:$A$38,$J5)&"") | C5: =IF($J5="","",INDEX('Mis plazos fijos'!$C$1:$C$38,$J5)) | D5: =IF($J5="","",INDEX('Mis plazos fijos'!$G$1:$G$38,$J5)) | E5: =IF($J5="","",INDEX('Mis plazos fijos'!$H$1:$H$38,$J5)) | F5: =IF(A5="","",A5-'Mis plazos fijos'!$B$6) | G5: =IF($J5="","",INDEX('Mis plazos fijos'!$L$1:$L$38,$J5)) | J5: =IFERROR(ROUND(MOD(SMALL('Mis plazos fijos'!$V$15:$V$38,1),1)*100000,0),"")
A6: =IFERROR(INT(SMALL('Mis plazos fijos'!$V$15:$V$38,2)),"") | B6: =IF($J6="","",INDEX('Mis plazos fijos'!$A$1:$A$38,$J6)&"") | C6: =IF($J6="","",INDEX('Mis plazos fijos'!$C$1:$C$38,$J6)) | D6: =IF($J6="","",INDEX('Mis plazos fijos'!$G$1:$G$38,$J6)) | E6: =IF($J6="","",INDEX('Mis plazos fijos'!$H$1:$H$38,$J6)) | F6: =IF(A6="","",A6-'Mis plazos fijos'!$B$6) | G6: =IF($J6="","",INDEX('Mis plazos fijos'!$L$1:$L$38,$J6)) | J6: =IFERROR(ROUND(MOD(SMALL('Mis plazos fijos'!$V$15:$V$38,2),1)*100000,0),"")
A7: =IFERROR(INT(SMALL('Mis plazos fijos'!$V$15:$V$38,3)),"") | B7: =IF($J7="","",INDEX('Mis plazos fijos'!$A$1:$A$38,$J7)&"") | C7: =IF($J7="","",INDEX('Mis plazos fijos'!$C$1:$C$38,$J7)) | D7: =IF($J7="","",INDEX('Mis plazos fijos'!$G$1:$G$38,$J7)) | E7: =IF($J7="","",INDEX('Mis plazos fijos'!$H$1:$H$38,$J7)) | F7: =IF(A7="","",A7-'Mis plazos fijos'!$B$6) | G7: =IF($J7="","",INDEX('Mis plazos fijos'!$L$1:$L$38,$J7)) | J7: =IFERROR(ROUND(MOD(SMALL('Mis plazos fijos'!$V$15:$V$38,3),1)*100000,0),"")
A8: =IFERROR(INT(SMALL('Mis plazos fijos'!$V$15:$V$38,4)),"") | B8: =IF($J8="","",INDEX('Mis plazos fijos'!$A$1:$A$38,$J8)&"") | C8: =IF($J8="","",INDEX('Mis plazos fijos'!$C$1:$C$38,$J8)) | D8: =IF($J8="","",INDEX('Mis plazos fijos'!$G$1:$G$38,$J8)) | E8: =IF($J8="","",INDEX('Mis plazos fijos'!$H$1:$H$38,$J8)) | F8: =IF(A8="","",A8-'Mis plazos fijos'!$B$6) | G8: =IF($J8="","",INDEX('Mis plazos fijos'!$L$1:$L$38,$J8)) | J8: =IFERROR(ROUND(MOD(SMALL('Mis plazos fijos'!$V$15:$V$38,4),1)*100000,0),"")
A9: =IFERROR(INT(SMALL('Mis plazos fijos'!$V$15:$V$38,5)),"") | B9: =IF($J9="","",INDEX('Mis plazos fijos'!$A$1:$A$38,$J9)&"") | C9: =IF($J9="","",INDEX('Mis plazos fijos'!$C$1:$C$38,$J9)) | D9: =IF($J9="","",INDEX('Mis plazos fijos'!$G$1:$G$38,$J9)) | E9: =IF($J9="","",INDEX('Mis plazos fijos'!$H$1:$H$38,$J9)) | F9: =IF(A9="","",A9-'Mis plazos fijos'!$B$6) | G9: =IF($J9="","",INDEX('Mis plazos fijos'!$L$1:$L$38,$J9)) | J9: =IFERROR(ROUND(MOD(SMALL('Mis plazos fijos'!$V$15:$V$38,5),1)*100000,0),"")
A10: =IFERROR(INT(SMALL('Mis plazos fijos'!$V$15:$V$38,6)),"") | B10: =IF($J10="","",INDEX('Mis plazos fijos'!$A$1:$A$38,$J10)&"") | C10: =IF($J10="","",INDEX('Mis plazos fijos'!$C$1:$C$38,$J10)) | D10: =IF($J10="","",INDEX('Mis plazos fijos'!$G$1:$G$38,$J10)) | E10: =IF($J10="","",INDEX('Mis plazos fijos'!$H$1:$H$38,$J10)) | F10: =IF(A10="","",A10-'Mis plazos fijos'!$B$6) | G10: =IF($J10="","",INDEX('Mis plazos fijos'!$L$1:$L$38,$J10)) | J10: =IFERROR(ROUND(MOD(SMALL('Mis plazos fijos'!$V$15:$V$38,6),1)*100000,0),"")
A11: =IFERROR(INT(SMALL('Mis plazos fijos'!$V$15:$V$38,7)),"") | B11: =IF($J11="","",INDEX('Mis plazos fijos'!$A$1:$A$38,$J11)&"") | C11: =IF($J11="","",INDEX('Mis plazos fijos'!$C$1:$C$38,$J11)) | D11: =IF($J11="","",INDEX('Mis plazos fijos'!$G$1:$G$38,$J11)) | E11: =IF($J11="","",INDEX('Mis plazos fijos'!$H$1:$H$38,$J11)) | F11: =IF(A11="","",A11-'Mis plazos fijos'!$B$6) | G11: =IF($J11="","",INDEX('Mis plazos fijos'!$L$1:$L$38,$J11)) | J11: =IFERROR(ROUND(MOD(SMALL('Mis plazos fijos'!$V$15:$V$38,7),1)*100000,0),"")
A12: =IFERROR(INT(SMALL('Mis plazos fijos'!$V$15:$V$38,8)),"") | B12: =IF($J12="","",INDEX('Mis plazos fijos'!$A$1:$A$38,$J12)&"") | C12: =IF($J12="","",INDEX('Mis plazos fijos'!$C$1:$C$38,$J12)) | D12: =IF($J12="","",INDEX('Mis plazos fijos'!$G$1:$G$38,$J12)) | E12: =IF($J12="","",INDEX('Mis plazos fijos'!$H$1:$H$38,$J12)) | F12: =IF(A12="","",A12-'Mis plazos fijos'!$B$6) | G12: =IF($J12="","",INDEX('Mis plazos fijos'!$L$1:$L$38,$J12)) | J12: =IFERROR(ROUND(MOD(SMALL('Mis plazos fijos'!$V$15:$V$38,8),1)*100000,0),"")
A13: =IFERROR(INT(SMALL('Mis plazos fijos'!$V$15:$V$38,9)),"") | B13: =IF($J13="","",INDEX('Mis plazos fijos'!$A$1:$A$38,$J13)&"") | C13: =IF($J13="","",INDEX('Mis plazos fijos'!$C$1:$C$38,$J13)) | D13: =IF($J13="","",INDEX('Mis plazos fijos'!$G$1:$G$38,$J13)) | E13: =IF($J13="","",INDEX('Mis plazos fijos'!$H$1:$H$38,$J13)) | F13: =IF(A13="","",A13-'Mis plazos fijos'!$B$6) | G13: =IF($J13="","",INDEX('Mis plazos fijos'!$L$1:$L$38,$J13)) | J13: =IFERROR(ROUND(MOD(SMALL('Mis plazos fijos'!$V$15:$V$38,9),1)*100000,0),"")
A14: =IFERROR(INT(SMALL('Mis plazos fijos'!$V$15:$V$38,10)),"") | B14: =IF($J14="","",INDEX('Mis plazos fijos'!$A$1:$A$38,$J14)&"") | C14: =IF($J14="","",INDEX('Mis plazos fijos'!$C$1:$C$38,$J14)) | D14: =IF($J14="","",INDEX('Mis plazos fijos'!$G$1:$G$38,$J14)) | E14: =IF($J14="","",INDEX('Mis plazos fijos'!$H$1:$H$38,$J14)) | F14: =IF(A14="","",A14-'Mis plazos fijos'!$B$6) | G14: =IF($J14="","",INDEX('Mis plazos fijos'!$L$1:$L$38,$J14)) | J14: =IFERROR(ROUND(MOD(SMALL('Mis plazos fijos'!$V$15:$V$38,10),1)*100000,0),"")
A15: =IFERROR(INT(SMALL('Mis plazos fijos'!$V$15:$V$38,11)),"") | B15: =IF($J15="","",INDEX('Mis plazos fijos'!$A$1:$A$38,$J15)&"") | C15: =IF($J15="","",INDEX('Mis plazos fijos'!$C$1:$C$38,$J15)) | D15: =IF($J15="","",INDEX('Mis plazos fijos'!$G$1:$G$38,$J15)) | E15: =IF($J15="","",INDEX('Mis plazos fijos'!$H$1:$H$38,$J15)) | F15: =IF(A15="","",A15-'Mis plazos fijos'!$B$6) | G15: =IF($J15="","",INDEX('Mis plazos fijos'!$L$1:$L$38,$J15)) | J15: =IFERROR(ROUND(MOD(SMALL('Mis plazos fijos'!$V$15:$V$38,11),1)*100000,0),"")
A16: =IFERROR(INT(SMALL('Mis plazos fijos'!$V$15:$V$38,12)),"") | B16: =IF($J16="","",INDEX('Mis plazos fijos'!$A$1:$A$38,$J16)&"") | C16: =IF($J16="","",INDEX('Mis plazos fijos'!$C$1:$C$38,$J16)) | D16: =IF($J16="","",INDEX('Mis plazos fijos'!$G$1:$G$38,$J16)) | E16: =IF($J16="","",INDEX('Mis plazos fijos'!$H$1:$H$38,$J16)) | F16: =IF(A16="","",A16-'Mis plazos fijos'!$B$6) | G16: =IF($J16="","",INDEX('Mis plazos fijos'!$L$1:$L$38,$J16)) | J16: =IFERROR(ROUND(MOD(SMALL('Mis plazos fijos'!$V$15:$V$38,12),1)*100000,0),"")
A17: =IFERROR(INT(SMALL('Mis plazos fijos'!$V$15:$V$38,13)),"") | B17: =IF($J17="","",INDEX('Mis plazos fijos'!$A$1:$A$38,$J17)&"") | C17: =IF($J17="","",INDEX('Mis plazos fijos'!$C$1:$C$38,$J17)) | D17: =IF($J17="","",INDEX('Mis plazos fijos'!$G$1:$G$38,$J17)) | E17: =IF($J17="","",INDEX('Mis plazos fijos'!$H$1:$H$38,$J17)) | F17: =IF(A17="","",A17-'Mis plazos fijos'!$B$6) | G17: =IF($J17="","",INDEX('Mis plazos fijos'!$L$1:$L$38,$J17)) | J17: =IFERROR(ROUND(MOD(SMALL('Mis plazos fijos'!$V$15:$V$38,13),1)*100000,0),"")
A18: =IFERROR(INT(SMALL('Mis plazos fijos'!$V$15:$V$38,14)),"") | B18: =IF($J18="","",INDEX('Mis plazos fijos'!$A$1:$A$38,$J18)&"") | C18: =IF($J18="","",INDEX('Mis plazos fijos'!$C$1:$C$38,$J18)) | D18: =IF($J18="","",INDEX('Mis plazos fijos'!$G$1:$G$38,$J18)) | E18: =IF($J18="","",INDEX('Mis plazos fijos'!$H$1:$H$38,$J18)) | F18: =IF(A18="","",A18-'Mis plazos fijos'!$B$6) | G18: =IF($J18="","",INDEX('Mis plazos fijos'!$L$1:$L$38,$J18)) | J18: =IFERROR(ROUND(MOD(SMALL('Mis plazos fijos'!$V$15:$V$38,14),1)*100000,0),"")
A19: =IFERROR(INT(SMALL('Mis plazos fijos'!$V$15:$V$38,15)),"") | B19: =IF($J19="","",INDEX('Mis plazos fijos'!$A$1:$A$38,$J19)&"") | C19: =IF($J19="","",INDEX('Mis plazos fijos'!$C$1:$C$38,$J19)) | D19: =IF($J19="","",INDEX('Mis plazos fijos'!$G$1:$G$38,$J19)) | E19: =IF($J19="","",INDEX('Mis plazos fijos'!$H$1:$H$38,$J19)) | F19: =IF(A19="","",A19-'Mis plazos fijos'!$B$6) | G19: =IF($J19="","",INDEX('Mis plazos fijos'!$L$1:$L$38,$J19)) | J19: =IFERROR(ROUND(MOD(SMALL('Mis plazos fijos'!$V$15:$V$38,15),1)*100000,0),"")
A20: =IFERROR(INT(SMALL('Mis plazos fijos'!$V$15:$V$38,16)),"") | B20: =IF($J20="","",INDEX('Mis plazos fijos'!$A$1:$A$38,$J20)&"") | C20: =IF($J20="","",INDEX('Mis plazos fijos'!$C$1:$C$38,$J20)) | D20: =IF($J20="","",INDEX('Mis plazos fijos'!$G$1:$G$38,$J20)) | E20: =IF($J20="","",INDEX('Mis plazos fijos'!$H$1:$H$38,$J20)) | F20: =IF(A20="","",A20-'Mis plazos fijos'!$B$6) | G20: =IF($J20="","",INDEX('Mis plazos fijos'!$L$1:$L$38,$J20)) | J20: =IFERROR(ROUND(MOD(SMALL('Mis plazos fijos'!$V$15:$V$38,16),1)*100000,0),"")
A21: =IFERROR(INT(SMALL('Mis plazos fijos'!$V$15:$V$38,17)),"") | B21: =IF($J21="","",INDEX('Mis plazos fijos'!$A$1:$A$38,$J21)&"") | C21: =IF($J21="","",INDEX('Mis plazos fijos'!$C$1:$C$38,$J21)) | D21: =IF($J21="","",INDEX('Mis plazos fijos'!$G$1:$G$38,$J21)) | E21: =IF($J21="","",INDEX('Mis plazos fijos'!$H$1:$H$38,$J21)) | F21: =IF(A21="","",A21-'Mis plazos fijos'!$B$6) | G21: =IF($J21="","",INDEX('Mis plazos fijos'!$L$1:$L$38,$J21)) | J21: =IFERROR(ROUND(MOD(SMALL('Mis plazos fijos'!$V$15:$V$38,17),1)*100000,0),"")
A22: =IFERROR(INT(SMALL('Mis plazos fijos'!$V$15:$V$38,18)),"") | B22: =IF($J22="","",INDEX('Mis plazos fijos'!$A$1:$A$38,$J22)&"") | C22: =IF($J22="","",INDEX('Mis plazos fijos'!$C$1:$C$38,$J22)) | D22: =IF($J22="","",INDEX('Mis plazos fijos'!$G$1:$G$38,$J22)) | E22: =IF($J22="","",INDEX('Mis plazos fijos'!$H$1:$H$38,$J22)) | F22: =IF(A22="","",A22-'Mis plazos fijos'!$B$6) | G22: =IF($J22="","",INDEX('Mis plazos fijos'!$L$1:$L$38,$J22)) | J22: =IFERROR(ROUND(MOD(SMALL('Mis plazos fijos'!$V$15:$V$38,18),1)*100000,0),"")
A23: =IFERROR(INT(SMALL('Mis plazos fijos'!$V$15:$V$38,19)),"") | B23: =IF($J23="","",INDEX('Mis plazos fijos'!$A$1:$A$38,$J23)&"") | C23: =IF($J23="","",INDEX('Mis plazos fijos'!$C$1:$C$38,$J23)) | D23: =IF($J23="","",INDEX('Mis plazos fijos'!$G$1:$G$38,$J23)) | E23: =IF($J23="","",INDEX('Mis plazos fijos'!$H$1:$H$38,$J23)) | F23: =IF(A23="","",A23-'Mis plazos fijos'!$B$6) | G23: =IF($J23="","",INDEX('Mis plazos fijos'!$L$1:$L$38,$J23)) | J23: =IFERROR(ROUND(MOD(SMALL('Mis plazos fijos'!$V$15:$V$38,19),1)*100000,0),"")
A24: =IFERROR(INT(SMALL('Mis plazos fijos'!$V$15:$V$38,20)),"") | B24: =IF($J24="","",INDEX('Mis plazos fijos'!$A$1:$A$38,$J24)&"") | C24: =IF($J24="","",INDEX('Mis plazos fijos'!$C$1:$C$38,$J24)) | D24: =IF($J24="","",INDEX('Mis plazos fijos'!$G$1:$G$38,$J24)) | E24: =IF($J24="","",INDEX('Mis plazos fijos'!$H$1:$H$38,$J24)) | F24: =IF(A24="","",A24-'Mis plazos fijos'!$B$6) | G24: =IF($J24="","",INDEX('Mis plazos fijos'!$L$1:$L$38,$J24)) | J24: =IFERROR(ROUND(MOD(SMALL('Mis plazos fijos'!$V$15:$V$38,20),1)*100000,0),"")
A25: =IFERROR(INT(SMALL('Mis plazos fijos'!$V$15:$V$38,21)),"") | B25: =IF($J25="","",INDEX('Mis plazos fijos'!$A$1:$A$38,$J25)&"") | C25: =IF($J25="","",INDEX('Mis plazos fijos'!$C$1:$C$38,$J25)) | D25: =IF($J25="","",INDEX('Mis plazos fijos'!$G$1:$G$38,$J25)) | E25: =IF($J25="","",INDEX('Mis plazos fijos'!$H$1:$H$38,$J25)) | F25: =IF(A25="","",A25-'Mis plazos fijos'!$B$6) | G25: =IF($J25="","",INDEX('Mis plazos fijos'!$L$1:$L$38,$J25)) | J25: =IFERROR(ROUND(MOD(SMALL('Mis plazos fijos'!$V$15:$V$38,21),1)*100000,0),"")
A26: =IFERROR(INT(SMALL('Mis plazos fijos'!$V$15:$V$38,22)),"") | B26: =IF($J26="","",INDEX('Mis plazos fijos'!$A$1:$A$38,$J26)&"") | C26: =IF($J26="","",INDEX('Mis plazos fijos'!$C$1:$C$38,$J26)) | D26: =IF($J26="","",INDEX('Mis plazos fijos'!$G$1:$G$38,$J26)) | E26: =IF($J26="","",INDEX('Mis plazos fijos'!$H$1:$H$38,$J26)) | F26: =IF(A26="","",A26-'Mis plazos fijos'!$B$6) | G26: =IF($J26="","",INDEX('Mis plazos fijos'!$L$1:$L$38,$J26)) | J26: =IFERROR(ROUND(MOD(SMALL('Mis plazos fijos'!$V$15:$V$38,22),1)*100000,0),"")
A27: =IFERROR(INT(SMALL('Mis plazos fijos'!$V$15:$V$38,23)),"") | B27: =IF($J27="","",INDEX('Mis plazos fijos'!$A$1:$A$38,$J27)&"") | C27: =IF($J27="","",INDEX('Mis plazos fijos'!$C$1:$C$38,$J27)) | D27: =IF($J27="","",INDEX('Mis plazos fijos'!$G$1:$G$38,$J27)) | E27: =IF($J27="","",INDEX('Mis plazos fijos'!$H$1:$H$38,$J27)) | F27: =IF(A27="","",A27-'Mis plazos fijos'!$B$6) | G27: =IF($J27="","",INDEX('Mis plazos fijos'!$L$1:$L$38,$J27)) | J27: =IFERROR(ROUND(MOD(SMALL('Mis plazos fijos'!$V$15:$V$38,23),1)*100000,0),"")
A28: =IFERROR(INT(SMALL('Mis plazos fijos'!$V$15:$V$38,24)),"") | B28: =IF($J28="","",INDEX('Mis plazos fijos'!$A$1:$A$38,$J28)&"") | C28: =IF($J28="","",INDEX('Mis plazos fijos'!$C$1:$C$38,$J28)) | D28: =IF($J28="","",INDEX('Mis plazos fijos'!$G$1:$G$38,$J28)) | E28: =IF($J28="","",INDEX('Mis plazos fijos'!$H$1:$H$38,$J28)) | F28: =IF(A28="","",A28-'Mis plazos fijos'!$B$6) | G28: =IF($J28="","",INDEX('Mis plazos fijos'!$L$1:$L$38,$J28)) | J28: =IFERROR(ROUND(MOD(SMALL('Mis plazos fijos'!$V$15:$V$38,24),1)*100000,0),"")
A30: MES POR MES · LOS PRÓXIMOS 12 MESES
A31: Mes | B31: Plazos fijos que vencen | C31: Se acredita
A32: =INDEX(IPC!$J$5:$J$16,MOD((YEAR('Mis plazos fijos'!$B$6)*12+MONTH('Mis plazos fijos'!$B$6)-1+0),12)+1)&" de "&INT(((YEAR('Mis plazos fijos'!$B$6)*12+MONTH('Mis plazos fijos'!$B$6)-1+0))/12) | B32: =COUNTIFS('Mis plazos fijos'!$R$15:$R$38,(YEAR('Mis plazos fijos'!$B$6)*12+MONTH('Mis plazos fijos'!$B$6)-1+0),'Mis plazos fijos'!$V$15:$V$38,">0") | C32: =SUMIFS('Mis plazos fijos'!$X$15:$X$38,'Mis plazos fijos'!$R$15:$R$38,(YEAR('Mis plazos fijos'!$B$6)*12+MONTH('Mis plazos fijos'!$B$6)-1+0))
A33: =INDEX(IPC!$J$5:$J$16,MOD((YEAR('Mis plazos fijos'!$B$6)*12+MONTH('Mis plazos fijos'!$B$6)-1+1),12)+1)&" de "&INT(((YEAR('Mis plazos fijos'!$B$6)*12+MONTH('Mis plazos fijos'!$B$6)-1+1))/12) | B33: =COUNTIFS('Mis plazos fijos'!$R$15:$R$38,(YEAR('Mis plazos fijos'!$B$6)*12+MONTH('Mis plazos fijos'!$B$6)-1+1),'Mis plazos fijos'!$V$15:$V$38,">0") | C33: =SUMIFS('Mis plazos fijos'!$X$15:$X$38,'Mis plazos fijos'!$R$15:$R$38,(YEAR('Mis plazos fijos'!$B$6)*12+MONTH('Mis plazos fijos'!$B$6)-1+1))
A34: =INDEX(IPC!$J$5:$J$16,MOD((YEAR('Mis plazos fijos'!$B$6)*12+MONTH('Mis plazos fijos'!$B$6)-1+2),12)+1)&" de "&INT(((YEAR('Mis plazos fijos'!$B$6)*12+MONTH('Mis plazos fijos'!$B$6)-1+2))/12) | B34: =COUNTIFS('Mis plazos fijos'!$R$15:$R$38,(YEAR('Mis plazos fijos'!$B$6)*12+MONTH('Mis plazos fijos'!$B$6)-1+2),'Mis plazos fijos'!$V$15:$V$38,">0") | C34: =SUMIFS('Mis plazos fijos'!$X$15:$X$38,'Mis plazos fijos'!$R$15:$R$38,(YEAR('Mis plazos fijos'!$B$6)*12+MONTH('Mis plazos fijos'!$B$6)-1+2))
A35: =INDEX(IPC!$J$5:$J$16,MOD((YEAR('Mis plazos fijos'!$B$6)*12+MONTH('Mis plazos fijos'!$B$6)-1+3),12)+1)&" de "&INT(((YEAR('Mis plazos fijos'!$B$6)*12+MONTH('Mis plazos fijos'!$B$6)-1+3))/12) | B35: =COUNTIFS('Mis plazos fijos'!$R$15:$R$38,(YEAR('Mis plazos fijos'!$B$6)*12+MONTH('Mis plazos fijos'!$B$6)-1+3),'Mis plazos fijos'!$V$15:$V$38,">0") | C35: =SUMIFS('Mis plazos fijos'!$X$15:$X$38,'Mis plazos fijos'!$R$15:$R$38,(YEAR('Mis plazos fijos'!$B$6)*12+MONTH('Mis plazos fijos'!$B$6)-1+3))
A36: =INDEX(IPC!$J$5:$J$16,MOD((YEAR('Mis plazos fijos'!$B$6)*12+MONTH('Mis plazos fijos'!$B$6)-1+4),12)+1)&" de "&INT(((YEAR('Mis plazos fijos'!$B$6)*12+MONTH('Mis plazos fijos'!$B$6)-1+4))/12) | B36: =COUNTIFS('Mis plazos fijos'!$R$15:$R$38,(YEAR('Mis plazos fijos'!$B$6)*12+MONTH('Mis plazos fijos'!$B$6)-1+4),'Mis plazos fijos'!$V$15:$V$38,">0") | C36: =SUMIFS('Mis plazos fijos'!$X$15:$X$38,'Mis plazos fijos'!$R$15:$R$38,(YEAR('Mis plazos fijos'!$B$6)*12+MONTH('Mis plazos fijos'!$B$6)-1+4))
A37: =INDEX(IPC!$J$5:$J$16,MOD((YEAR('Mis plazos fijos'!$B$6)*12+MONTH('Mis plazos fijos'!$B$6)-1+5),12)+1)&" de "&INT(((YEAR('Mis plazos fijos'!$B$6)*12+MONTH('Mis plazos fijos'!$B$6)-1+5))/12) | B37: =COUNTIFS('Mis plazos fijos'!$R$15:$R$38,(YEAR('Mis plazos fijos'!$B$6)*12+MONTH('Mis plazos fijos'!$B$6)-1+5),'Mis plazos fijos'!$V$15:$V$38,">0") | C37: =SUMIFS('Mis plazos fijos'!$X$15:$X$38,'Mis plazos fijos'!$R$15:$R$38,(YEAR('Mis plazos fijos'!$B$6)*12+MONTH('Mis plazos fijos'!$B$6)-1+5))
A38: =INDEX(IPC!$J$5:$J$16,MOD((YEAR('Mis plazos fijos'!$B$6)*12+MONTH('Mis plazos fijos'!$B$6)-1+6),12)+1)&" de "&INT(((YEAR('Mis plazos fijos'!$B$6)*12+MONTH('Mis plazos fijos'!$B$6)-1+6))/12) | B38: =COUNTIFS('Mis plazos fijos'!$R$15:$R$38,(YEAR('Mis plazos fijos'!$B$6)*12+MONTH('Mis plazos fijos'!$B$6)-1+6),'Mis plazos fijos'!$V$15:$V$38,">0") | C38: =SUMIFS('Mis plazos fijos'!$X$15:$X$38,'Mis plazos fijos'!$R$15:$R$38,(YEAR('Mis plazos fijos'!$B$6)*12+MONTH('Mis plazos fijos'!$B$6)-1+6))
A39: =INDEX(IPC!$J$5:$J$16,MOD((YEAR('Mis plazos fijos'!$B$6)*12+MONTH('Mis plazos fijos'!$B$6)-1+7),12)+1)&" de "&INT(((YEAR('Mis plazos fijos'!$B$6)*12+MONTH('Mis plazos fijos'!$B$6)-1+7))/12) | B39: =COUNTIFS('Mis plazos fijos'!$R$15:$R$38,(YEAR('Mis plazos fijos'!$B$6)*12+MONTH('Mis plazos fijos'!$B$6)-1+7),'Mis plazos fijos'!$V$15:$V$38,">0") | C39: =SUMIFS('Mis plazos fijos'!$X$15:$X$38,'Mis plazos fijos'!$R$15:$R$38,(YEAR('Mis plazos fijos'!$B$6)*12+MONTH('Mis plazos fijos'!$B$6)-1+7))
A40: =INDEX(IPC!$J$5:$J$16,MOD((YEAR('Mis plazos fijos'!$B$6)*12+MONTH('Mis plazos fijos'!$B$6)-1+8),12)+1)&" de "&INT(((YEAR('Mis plazos fijos'!$B$6)*12+MONTH('Mis plazos fijos'!$B$6)-1+8))/12) | B40: =COUNTIFS('Mis plazos fijos'!$R$15:$R$38,(YEAR('Mis plazos fijos'!$B$6)*12+MONTH('Mis plazos fijos'!$B$6)-1+8),'Mis plazos fijos'!$V$15:$V$38,">0") | C40: =SUMIFS('Mis plazos fijos'!$X$15:$X$38,'Mis plazos fijos'!$R$15:$R$38,(YEAR('Mis plazos fijos'!$B$6)*12+MONTH('Mis plazos fijos'!$B$6)-1+8))
A41: =INDEX(IPC!$J$5:$J$16,MOD((YEAR('Mis plazos fijos'!$B$6)*12+MONTH('Mis plazos fijos'!$B$6)-1+9),12)+1)&" de "&INT(((YEAR('Mis plazos fijos'!$B$6)*12+MONTH('Mis plazos fijos'!$B$6)-1+9))/12) | B41: =COUNTIFS('Mis plazos fijos'!$R$15:$R$38,(YEAR('Mis plazos fijos'!$B$6)*12+MONTH('Mis plazos fijos'!$B$6)-1+9),'Mis plazos fijos'!$V$15:$V$38,">0") | C41: =SUMIFS('Mis plazos fijos'!$X$15:$X$38,'Mis plazos fijos'!$R$15:$R$38,(YEAR('Mis plazos fijos'!$B$6)*12+MONTH('Mis plazos fijos'!$B$6)-1+9))
A42: =INDEX(IPC!$J$5:$J$16,MOD((YEAR('Mis plazos fijos'!$B$6)*12+MONTH('Mis plazos fijos'!$B$6)-1+10),12)+1)&" de "&INT(((YEAR('Mis plazos fijos'!$B$6)*12+MONTH('Mis plazos fijos'!$B$6)-1+10))/12) | B42: =COUNTIFS('Mis plazos fijos'!$R$15:$R$38,(YEAR('Mis plazos fijos'!$B$6)*12+MONTH('Mis plazos fijos'!$B$6)-1+10),'Mis plazos fijos'!$V$15:$V$38,">0") | C42: =SUMIFS('Mis plazos fijos'!$X$15:$X$38,'Mis plazos fijos'!$R$15:$R$38,(YEAR('Mis plazos fijos'!$B$6)*12+MONTH('Mis plazos fijos'!$B$6)-1+10))
A43: =INDEX(IPC!$J$5:$J$16,MOD((YEAR('Mis plazos fijos'!$B$6)*12+MONTH('Mis plazos fijos'!$B$6)-1+11),12)+1)&" de "&INT(((YEAR('Mis plazos fijos'!$B$6)*12+MONTH('Mis plazos fijos'!$B$6)-1+11))/12) | B43: =COUNTIFS('Mis plazos fijos'!$R$15:$R$38,(YEAR('Mis plazos fijos'!$B$6)*12+MONTH('Mis plazos fijos'!$B$6)-1+11),'Mis plazos fijos'!$V$15:$V$38,">0") | C43: =SUMIFS('Mis plazos fijos'!$X$15:$X$38,'Mis plazos fijos'!$R$15:$R$38,(YEAR('Mis plazos fijos'!$B$6)*12+MONTH('Mis plazos fijos'!$B$6)-1+11))

Sheet Renovación
A1: Simulador de renovación: capital + intereses
A2: Qué pasa si al vencer volvés a poner todo (capital + intereses) con la misma TNA. Viene armado para cubrir un año.
A4: DATOS
A5: Capital | B5: 1000000 | N5: =IF(AND(ISNUMBER(B5),B5>0,ISNUMBER(B6),B6>=0,ISNUMBER(B7),B7>=30,ISNUMBER(B8),B8>=0,B8<=24,ISNUMBER(B9)),1,0)
A6: TNA (%) | B6: 22.66 | C6: TNA promedio de los bancos al 16/10/2026 (BCRA): 22,66%. Poné la de tu banco. | N6: =IF(N5=1,INT(B8),0)
A7: Días de cada plazo | B7: 30
A8: Renovaciones (veces) | B8: 11 | C8: 30 días renovado 11 veces = 12 plazos, casi un año.
A9: Inflación mensual estimada (%) | B9: 1.7
A11: EL PRIMER PLAZO
A12: Interés del primer plazo | B12: =IF($N$5=1,B5*B6/100*B7/365,"")
A13: Total al vencimiento | B13: =IF($N$5=1,B5+B12,"")
A14: Tasa del período | B14: =IF($N$5=1,B6/100*B7/365,"")
A15: Tasa efectiva mensual (TEM) | B15: =IF($N$5=1,B6/100*30/365,"")
A16: Tasa efectiva anual (TEA) | B16: =IF($N$5=1,(1+B14)^(365/B7)-1,"")
A18: RENOVANDO CAPITAL + INTERESES
A19: Días en total | B19: =IF($N$5=1,B7*($N$6+1),"")
A20: Terminás con | B20: =IF($N$5=1,INDEX(D31:D55,$N$6+1),"")
A21: Interés total | B21: =IF($N$5=1,B20-B5,"")
A22: Rendimiento total | B22: =IF($N$5=1,B20/B5-1,"")
A23: Inflación estimada del período | B23: =IF($N$5=1,(1+B9/100)^(B19/30)-1,"")
A24: En plata de hoy | B24: =IF($N$5=1,B20/(1+B23),"")
A25: Resultado real | B25: =IF($N$5=1,B24/B5-1,"")
A26: Qué dice la cuenta | B26: =IF($N$5=0,"Completá las celdas amarillas de arriba.",IF(B25>=0,"Con la inflación que estimaste, renovando le ganás a la inflación: al final tu plata compra más que hoy.","Con la inflación que estimaste, la inflación le gana: al final tu plata compra menos que hoy."))
A29: RENOVACIÓN POR RENOVACIÓN
A30: Plazo | B30: Vence el día | C30: Interés del período | D30: Acumulado | E30: En plata de hoy
A31: =IF(AND($N$5=1,1<=$N$6+1),"#1","") | B31: =IF(AND($N$5=1,1<=$N$6+1),1*$B$7,"") | C31: =IF(AND($N$5=1,1<=$N$6+1),$B$5*$B$6/100*$B$7/365,"") | D31: =IF(AND($N$5=1,1<=$N$6+1),$B$5+C31,"") | E31: =IF(AND($N$5=1,1<=$N$6+1),D31/(1+$B$9/100)^(B31/30),"")
A32: =IF(AND($N$5=1,2<=$N$6+1),"#2","") | B32: =IF(AND($N$5=1,2<=$N$6+1),2*$B$7,"") | C32: =IF(AND($N$5=1,2<=$N$6+1),D31*$B$6/100*$B$7/365,"") | D32: =IF(AND($N$5=1,2<=$N$6+1),D31+C32,"") | E32: =IF(AND($N$5=1,2<=$N$6+1),D32/(1+$B$9/100)^(B32/30),"")
A33: =IF(AND($N$5=1,3<=$N$6+1),"#3","") | B33: =IF(AND($N$5=1,3<=$N$6+1),3*$B$7,"") | C33: =IF(AND($N$5=1,3<=$N$6+1),D32*$B$6/100*$B$7/365,"") | D33: =IF(AND($N$5=1,3<=$N$6+1),D32+C33,"") | E33: =IF(AND($N$5=1,3<=$N$6+1),D33/(1+$B$9/100)^(B33/30),"")
A34: =IF(AND($N$5=1,4<=$N$6+1),"#4","") | B34: =IF(AND($N$5=1,4<=$N$6+1),4*$B$7,"") | C34: =IF(AND($N$5=1,4<=$N$6+1),D33*$B$6/100*$B$7/365,"") | D34: =IF(AND($N$5=1,4<=$N$6+1),D33+C34,"") | E34: =IF(AND($N$5=1,4<=$N$6+1),D34/(1+$B$9/100)^(B34/30),"")
A35: =IF(AND($N$5=1,5<=$N$6+1),"#5","") | B35: =IF(AND($N$5=1,5<=$N$6+1),5*$B$7,"") | C35: =IF(AND($N$5=1,5<=$N$6+1),D34*$B$6/100*$B$7/365,"") | D35: =IF(AND($N$5=1,5<=$N$6+1),D34+C35,"") | E35: =IF(AND($N$5=1,5<=$N$6+1),D35/(1+$B$9/100)^(B35/30),"")
A36: =IF(AND($N$5=1,6<=$N$6+1),"#6","") | B36: =IF(AND($N$5=1,6<=$N$6+1),6*$B$7,"") | C36: =IF(AND($N$5=1,6<=$N$6+1),D35*$B$6/100*$B$7/365,"") | D36: =IF(AND($N$5=1,6<=$N$6+1),D35+C36,"") | E36: =IF(AND($N$5=1,6<=$N$6+1),D36/(1+$B$9/100)^(B36/30),"")
A37: =IF(AND($N$5=1,7<=$N$6+1),"#7","") | B37: =IF(AND($N$5=1,7<=$N$6+1),7*$B$7,"") | C37: =IF(AND($N$5=1,7<=$N$6+1),D36*$B$6/100*$B$7/365,"") | D37: =IF(AND($N$5=1,7<=$N$6+1),D36+C37,"") | E37: =IF(AND($N$5=1,7<=$N$6+1),D37/(1+$B$9/100)^(B37/30),"")
A38: =IF(AND($N$5=1,8<=$N$6+1),"#8","") | B38: =IF(AND($N$5=1,8<=$N$6+1),8*$B$7,"") | C38: =IF(AND($N$5=1,8<=$N$6+1),D37*$B$6/100*$B$7/365,"") | D38: =IF(AND($N$5=1,8<=$N$6+1),D37+C38,"") | E38: =IF(AND($N$5=1,8<=$N$6+1),D38/(1+$B$9/100)^(B38/30),"")
A39: =IF(AND($N$5=1,9<=$N$6+1),"#9","") | B39: =IF(AND($N$5=1,9<=$N$6+1),9*$B$7,"") | C39: =IF(AND($N$5=1,9<=$N$6+1),D38*$B$6/100*$B$7/365,"") | D39: =IF(AND($N$5=1,9<=$N$6+1),D38+C39,"") | E39: =IF(AND($N$5=1,9<=$N$6+1),D39/(1+$B$9/100)^(B39/30),"")
A40: =IF(AND($N$5=1,10<=$N$6+1),"#10","") | B40: =IF(AND($N$5=1,10<=$N$6+1),10*$B$7,"") | C40: =IF(AND($N$5=1,10<=$N$6+1),D39*$B$6/100*$B$7/365,"") | D40: =IF(AND($N$5=1,10<=$N$6+1),D39+C40,"") | E40: =IF(AND($N$5=1,10<=$N$6+1),D40/(1+$B$9/100)^(B40/30),"")
A41: =IF(AND($N$5=1,11<=$N$6+1),"#11","") | B41: =IF(AND($N$5=1,11<=$N$6+1),11*$B$7,"") | C41: =IF(AND($N$5=1,11<=$N$6+1),D40*$B$6/100*$B$7/365,"") | D41: =IF(AND($N$5=1,11<=$N$6+1),D40+C41,"") | E41: =IF(AND($N$5=1,11<=$N$6+1),D41/(1+$B$9/100)^(B41/30),"")
A42: =IF(AND($N$5=1,12<=$N$6+1),"#12","") | B42: =IF(AND($N$5=1,12<=$N$6+1),12*$B$7,"") | C42: =IF(AND($N$5=1,12<=$N$6+1),D41*$B$6/100*$B$7/365,"") | D42: =IF(AND($N$5=1,12<=$N$6+1),D41+C42,"") | E42: =IF(AND($N$5=1,12<=$N$6+1),D42/(1+$B$9/100)^(B42/30),"")
A43: =IF(AND($N$5=1,13<=$N$6+1),"#13","") | B43: =IF(AND($N$5=1,13<=$N$6+1),13*$B$7,"") | C43: =IF(AND($N$5=1,13<=$N$6+1),D42*$B$6/100*$B$7/365,"") | D43: =IF(AND($N$5=1,13<=$N$6+1),D42+C43,"") | E43: =IF(AND($N$5=1,13<=$N$6+1),D43/(1+$B$9/100)^(B43/30),"")
A44: =IF(AND($N$5=1,14<=$N$6+1),"#14","") | B44: =IF(AND($N$5=1,14<=$N$6+1),14*$B$7,"") | C44: =IF(AND($N$5=1,14<=$N$6+1),D43*$B$6/100*$B$7/365,"") | D44: =IF(AND($N$5=1,14<=$N$6+1),D43+C44,"") | E44: =IF(AND($N$5=1,14<=$N$6+1),D44/(1+$B$9/100)^(B44/30),"")
A45: =IF(AND($N$5=1,15<=$N$6+1),"#15","") | B45: =IF(AND($N$5=1,15<=$N$6+1),15*$B$7,"") | C45: =IF(AND($N$5=1,15<=$N$6+1),D44*$B$6/100*$B$7/365,"") | D45: =IF(AND($N$5=1,15<=$N$6+1),D44+C45,"") | E45: =IF(AND($N$5=1,15<=$N$6+1),D45/(1+$B$9/100)^(B45/30),"")
A46: =IF(AND($N$5=1,16<=$N$6+1),"#16","") | B46: =IF(AND($N$5=1,16<=$N$6+1),16*$B$7,"") | C46: =IF(AND($N$5=1,16<=$N$6+1),D45*$B$6/100*$B$7/365,"") | D46: =IF(AND($N$5=1,16<=$N$6+1),D45+C46,"") | E46: =IF(AND($N$5=1,16<=$N$6+1),D46/(1+$B$9/100)^(B46/30),"")
A47: =IF(AND($N$5=1,17<=$N$6+1),"#17","") | B47: =IF(AND($N$5=1,17<=$N$6+1),17*$B$7,"") | C47: =IF(AND($N$5=1,17<=$N$6+1),D46*$B$6/100*$B$7/365,"") | D47: =IF(AND($N$5=1,17<=$N$6+1),D46+C47,"") | E47: =IF(AND($N$5=1,17<=$N$6+1),D47/(1+$B$9/100)^(B47/30),"")
A48: =IF(AND($N$5=1,18<=$N$6+1),"#18","") | B48: =IF(AND($N$5=1,18<=$N$6+1),18*$B$7,"") | C48: =IF(AND($N$5=1,18<=$N$6+1),D47*$B$6/100*$B$7/365,"") | D48: =IF(AND($N$5=1,18<=$N$6+1),D47+C48,"") | E48: =IF(AND($N$5=1,18<=$N$6+1),D48/(1+$B$9/100)^(B48/30),"")
A49: =IF(AND($N$5=1,19<=$N$6+1),"#19","") | B49: =IF(AND($N$5=1,19<=$N$6+1),19*$B$7,"") | C49: =IF(AND($N$5=1,19<=$N$6+1),D48*$B$6/100*$B$7/365,"") | D49: =IF(AND($N$5=1,19<=$N$6+1),D48+C49,"") | E49: =IF(AND($N$5=1,19<=$N$6+1),D49/(1+$B$9/100)^(B49/30),"")
A50: =IF(AND($N$5=1,20<=$N$6+1),"#20","") | B50: =IF(AND($N$5=1,20<=$N$6+1),20*$B$7,"") | C50: =IF(AND($N$5=1,20<=$N$6+1),D49*$B$6/100*$B$7/365,"") | D50: =IF(AND($N$5=1,20<=$N$6+1),D49+C50,"") | E50: =IF(AND($N$5=1,20<=$N$6+1),D50/(1+$B$9/100)^(B50/30),"")
A51: =IF(AND($N$5=1,21<=$N$6+1),"#21","") | B51: =IF(AND($N$5=1,21<=$N$6+1),21*$B$7,"") | C51: =IF(AND($N$5=1,21<=$N$6+1),D50*$B$6/100*$B$7/365,"") | D51: =IF(AND($N$5=1,21<=$N$6+1),D50+C51,"") | E51: =IF(AND($N$5=1,21<=$N$6+1),D51/(1+$B$9/100)^(B51/30),"")
A52: =IF(AND($N$5=1,22<=$N$6+1),"#22","") | B52: =IF(AND($N$5=1,22<=$N$6+1),22*$B$7,"") | C52: =IF(AND($N$5=1,22<=$N$6+1),D51*$B$6/100*$B$7/365,"") | D52: =IF(AND($N$5=1,22<=$N$6+1),D51+C52,"") | E52: =IF(AND($N$5=1,22<=$N$6+1),D52/(1+$B$9/100)^(B52/30),"")
A53: =IF(AND($N$5=1,23<=$N$6+1),"#23","") | B53: =IF(AND($N$5=1,23<=$N$6+1),23*$B$7,"") | C53: =IF(AND($N$5=1,23<=$N$6+1),D52*$B$6/100*$B$7/365,"") | D53: =IF(AND($N$5=1,23<=$N$6+1),D52+C53,"") | E53: =IF(AND($N$5=1,23<=$N$6+1),D53/(1+$B$9/100)^(B53/30),"")
A54: =IF(AND($N$5=1,24<=$N$6+1),"#24","") | B54: =IF(AND($N$5=1,24<=$N$6+1),24*$B$7,"") | C54: =IF(AND($N$5=1,24<=$N$6+1),D53*$B$6/100*$B$7/365,"") | D54: =IF(AND($N$5=1,24<=$N$6+1),D53+C54,"") | E54: =IF(AND($N$5=1,24<=$N$6+1),D54/(1+$B$9/100)^(B54/30),"")
A55: =IF(AND($N$5=1,25<=$N$6+1),"#25","") | B55: =IF(AND($N$5=1,25<=$N$6+1),25*$B$7,"") | C55: =IF(AND($N$5=1,25<=$N$6+1),D54*$B$6/100*$B$7/365,"") | D55: =IF(AND($N$5=1,25<=$N$6+1),D54+C55,"") | E55: =IF(AND($N$5=1,25<=$N$6+1),D55/(1+$B$9/100)^(B55/30),"")
A57: Supone que la TNA se mantiene en cada renovación, algo que nadie puede asegurar: cambiala y mirá cómo cambia el resultado. Es la misma cuenta que la calculadora de calcular.ar/plazo-fijo.

Sheet Tradicional vs UVA
A1: Plazo fijo tradicional vs UVA, al mismo plazo
A2: El UVA ajusta el capital por inflación y suma una tasa chica; el tradicional paga una TNA fija. Esta hoja te muestra con cuánto terminás en cada uno y qué inflación los empata. No elige por vos.
A4: DATOS
A5: Capital | B5: 1000000 | N5: =IF(AND(ISNUMBER(B5),B5>0,ISNUMBER(B6),B6>=30,ISNUMBER(B7),B7>=0,B7<=24,ISNUMBER(B8),B8>=0,ISNUMBER(B9),ISNUMBER(B10),B10>=0),1,0)
A6: Días de cada plazo tradicional | B6: 30 | N6: =IF(N5=1,INT(B7),0)
A7: Renovaciones del tradicional (veces) | B7: 11 | C7: El UVA se compara contra el tradicional renovado hasta el mismo plazo total.
A8: TNA del tradicional (%) | B8: 22.66
A9: Inflación mensual estimada (%) | B9: 1.7
A10: Tasa adicional del UVA (TNA %) | B10: 4.5 | C10: La fija cada banco: fijate la del tuyo el día que lo armes.
A12: AL MISMO PLAZO
A13: Plazo que se compara (días) | B13: =IF($N$5=1,B6*($N$6+1),"")
A14: Inflación estimada del período | B14: =IF($N$5=1,(1+B9/100)^(B13/30)-1,"")
A15: Tradicional renovado: terminás con | B15: =IF($N$5=1,B5*(1+B8/100*B6/365)^($N$6+1),"")
A16: UVA: terminás con | B16: =IF(AND($N$5=1,B13>=90),B5*(1+B14)*(1+B10/100*B13/365),"")
A17: Diferencia (UVA − tradicional) | B17: =IF(AND($N$5=1,B13>=90),B16-B15,"")
A18: Inflación mensual que los empata | B18: =IF(AND($N$5=1,B13>=90),(B15/B5/(1+B10/100*B13/365))^(30/B13)-1,"")
A19: Cómo se lee | B19: =IF($N$5=0,"Completá las celdas amarillas de arriba.",IF(B13<90,"El plazo fijo UVA exige 90 días como mínimo (Com. «A» 8246 del BCRA): subí los días o las renovaciones para compararlo.","Si la inflación mensual promedio de esos "&B13&" días es mayor a la de empate, el UVA termina con más; si es menor, termina con más el tradicional. La inflación futura nadie la sabe: probá con distintas."))
A21: Regla del BCRA (Com. «A» 8246, vigente desde el 2/6/2025): el plazo fijo UVA de personas humanas es de 90 días como mínimo y se puede precancelar desde el día 30, a una tasa fija y sin el ajuste por inflación. Acá el UVA se calcula con la inflación que estimaste; en la realidad ajusta por UVA (CER), que sigue al IPC con unas semanas de atraso.

Sheet Escalera
A1: Escalera de plazos fijos
A2: Partís el capital en varios plazos fijos que vencen uno detrás de otro: así tenés plata disponible seguido sin cortar ninguno antes de tiempo.
A4: DATOS
A5: Capital total | B5: 1000000 | N5: =IF(AND(ISNUMBER(B5),B5>0,ISNUMBER(B6),B6>=1,B6<=12,ISNUMBER(B7),B7>=30,ISNUMBER(B8),ISNUMBER(B9),B9>=0),1,0)
A6: Cantidad de escalones | B6: 4 | N6: =IF(N5=1,INT(B6),0)
A7: Vence uno cada (días) | B7: 30
A8: Fecha en que los armás | B8: 46314
A9: TNA (%) | B9: 22.66 | C9: Si tu banco paga otra TNA a plazos más largos, cargala escalón por escalón en la columna amarilla de abajo.
A11: Cada escalón | B11: =IF($N$5=1,B5/$N$6,"")
A12: Interés de la primera vuelta | B12: =IF($N$5=1,SUM(G15:G26),"")
A13: Cómo sigue | B13: =IF($N$5=0,"Completá las celdas amarillas de arriba.",IF($N$6=1,"Con un solo escalón es un plazo fijo común: subí la cantidad para escalonarlo.","Vas a tener un vencimiento cada "&B7&" días. Si cada parte que vence la volvés a poner a "&($N$6*B7)&" días, la escalera se mantiene sola."))
A14: Escalón | B14: Capital | C14: Plazo (días) | D14: TNA de este plazo (opcional) | E14: TNA que se usa | F14: Vence el | G14: Interés | H14: Cobrás | I14: Al vencer, renovalo a (días)
A15: =IF(AND($N$5=1,1<=$N$6),"Escalón 1","") | B15: =IF(AND($N$5=1,1<=$N$6),$B$5/$N$6,"") | C15: =IF(AND($N$5=1,1<=$N$6),1*$B$7,"") | E15: =IF(AND($N$5=1,1<=$N$6),IF(ISNUMBER(D15),D15,$B$9),"") | F15: =IF(AND($N$5=1,1<=$N$6),$B$8+C15,"") | G15: =IF(AND($N$5=1,1<=$N$6),B15*E15/100*C15/365,"") | H15: =IF(AND($N$5=1,1<=$N$6),B15+G15,"") | I15: =IF(AND($N$5=1,1<=$N$6),$N$6*$B$7,"")
A16: =IF(AND($N$5=1,2<=$N$6),"Escalón 2","") | B16: =IF(AND($N$5=1,2<=$N$6),$B$5/$N$6,"") | C16: =IF(AND($N$5=1,2<=$N$6),2*$B$7,"") | E16: =IF(AND($N$5=1,2<=$N$6),IF(ISNUMBER(D16),D16,$B$9),"") | F16: =IF(AND($N$5=1,2<=$N$6),$B$8+C16,"") | G16: =IF(AND($N$5=1,2<=$N$6),B16*E16/100*C16/365,"") | H16: =IF(AND($N$5=1,2<=$N$6),B16+G16,"") | I16: =IF(AND($N$5=1,2<=$N$6),$N$6*$B$7,"")
A17: =IF(AND($N$5=1,3<=$N$6),"Escalón 3","") | B17: =IF(AND($N$5=1,3<=$N$6),$B$5/$N$6,"") | C17: =IF(AND($N$5=1,3<=$N$6),3*$B$7,"") | E17: =IF(AND($N$5=1,3<=$N$6),IF(ISNUMBER(D17),D17,$B$9),"") | F17: =IF(AND($N$5=1,3<=$N$6),$B$8+C17,"") | G17: =IF(AND($N$5=1,3<=$N$6),B17*E17/100*C17/365,"") | H17: =IF(AND($N$5=1,3<=$N$6),B17+G17,"") | I17: =IF(AND($N$5=1,3<=$N$6),$N$6*$B$7,"")
A18: =IF(AND($N$5=1,4<=$N$6),"Escalón 4","") | B18: =IF(AND($N$5=1,4<=$N$6),$B$5/$N$6,"") | C18: =IF(AND($N$5=1,4<=$N$6),4*$B$7,"") | E18: =IF(AND($N$5=1,4<=$N$6),IF(ISNUMBER(D18),D18,$B$9),"") | F18: =IF(AND($N$5=1,4<=$N$6),$B$8+C18,"") | G18: =IF(AND($N$5=1,4<=$N$6),B18*E18/100*C18/365,"") | H18: =IF(AND($N$5=1,4<=$N$6),B18+G18,"") | I18: =IF(AND($N$5=1,4<=$N$6),$N$6*$B$7,"")
A19: =IF(AND($N$5=1,5<=$N$6),"Escalón 5","") | B19: =IF(AND($N$5=1,5<=$N$6),$B$5/$N$6,"") | C19: =IF(AND($N$5=1,5<=$N$6),5*$B$7,"") | E19: =IF(AND($N$5=1,5<=$N$6),IF(ISNUMBER(D19),D19,$B$9),"") | F19: =IF(AND($N$5=1,5<=$N$6),$B$8+C19,"") | G19: =IF(AND($N$5=1,5<=$N$6),B19*E19/100*C19/365,"") | H19: =IF(AND($N$5=1,5<=$N$6),B19+G19,"") | I19: =IF(AND($N$5=1,5<=$N$6),$N$6*$B$7,"")
A20: =IF(AND($N$5=1,6<=$N$6),"Escalón 6","") | B20: =IF(AND($N$5=1,6<=$N$6),$B$5/$N$6,"") | C20: =IF(AND($N$5=1,6<=$N$6),6*$B$7,"") | E20: =IF(AND($N$5=1,6<=$N$6),IF(ISNUMBER(D20),D20,$B$9),"") | F20: =IF(AND($N$5=1,6<=$N$6),$B$8+C20,"") | G20: =IF(AND($N$5=1,6<=$N$6),B20*E20/100*C20/365,"") | H20: =IF(AND($N$5=1,6<=$N$6),B20+G20,"") | I20: =IF(AND($N$5=1,6<=$N$6),$N$6*$B$7,"")
A21: =IF(AND($N$5=1,7<=$N$6),"Escalón 7","") | B21: =IF(AND($N$5=1,7<=$N$6),$B$5/$N$6,"") | C21: =IF(AND($N$5=1,7<=$N$6),7*$B$7,"") | E21: =IF(AND($N$5=1,7<=$N$6),IF(ISNUMBER(D21),D21,$B$9),"") | F21: =IF(AND($N$5=1,7<=$N$6),$B$8+C21,"") | G21: =IF(AND($N$5=1,7<=$N$6),B21*E21/100*C21/365,"") | H21: =IF(AND($N$5=1,7<=$N$6),B21+G21,"") | I21: =IF(AND($N$5=1,7<=$N$6),$N$6*$B$7,"")
A22: =IF(AND($N$5=1,8<=$N$6),"Escalón 8","") | B22: =IF(AND($N$5=1,8<=$N$6),$B$5/$N$6,"") | C22: =IF(AND($N$5=1,8<=$N$6),8*$B$7,"") | E22: =IF(AND($N$5=1,8<=$N$6),IF(ISNUMBER(D22),D22,$B$9),"") | F22: =IF(AND($N$5=1,8<=$N$6),$B$8+C22,"") | G22: =IF(AND($N$5=1,8<=$N$6),B22*E22/100*C22/365,"") | H22: =IF(AND($N$5=1,8<=$N$6),B22+G22,"") | I22: =IF(AND($N$5=1,8<=$N$6),$N$6*$B$7,"")
A23: =IF(AND($N$5=1,9<=$N$6),"Escalón 9","") | B23: =IF(AND($N$5=1,9<=$N$6),$B$5/$N$6,"") | C23: =IF(AND($N$5=1,9<=$N$6),9*$B$7,"") | E23: =IF(AND($N$5=1,9<=$N$6),IF(ISNUMBER(D23),D23,$B$9),"") | F23: =IF(AND($N$5=1,9<=$N$6),$B$8+C23,"") | G23: =IF(AND($N$5=1,9<=$N$6),B23*E23/100*C23/365,"") | H23: =IF(AND($N$5=1,9<=$N$6),B23+G23,"") | I23: =IF(AND($N$5=1,9<=$N$6),$N$6*$B$7,"")
A24: =IF(AND($N$5=1,10<=$N$6),"Escalón 10","") | B24: =IF(AND($N$5=1,10<=$N$6),$B$5/$N$6,"") | C24: =IF(AND($N$5=1,10<=$N$6),10*$B$7,"") | E24: =IF(AND($N$5=1,10<=$N$6),IF(ISNUMBER(D24),D24,$B$9),"") | F24: =IF(AND($N$5=1,10<=$N$6),$B$8+C24,"") | G24: =IF(AND($N$5=1,10<=$N$6),B24*E24/100*C24/365,"") | H24: =IF(AND($N$5=1,10<=$N$6),B24+G24,"") | I24: =IF(AND($N$5=1,10<=$N$6),$N$6*$B$7,"")
A25: =IF(AND($N$5=1,11<=$N$6),"Escalón 11","") | B25: =IF(AND($N$5=1,11<=$N$6),$B$5/$N$6,"") | C25: =IF(AND($N$5=1,11<=$N$6),11*$B$7,"") | E25: =IF(AND($N$5=1,11<=$N$6),IF(ISNUMBER(D25),D25,$B$9),"") | F25: =IF(AND($N$5=1,11<=$N$6),$B$8+C25,"") | G25: =IF(AND($N$5=1,11<=$N$6),B25*E25/100*C25/365,"") | H25: =IF(AND($N$5=1,11<=$N$6),B25+G25,"") | I25: =IF(AND($N$5=1,11<=$N$6),$N$6*$B$7,"")
A26: =IF(AND($N$5=1,12<=$N$6),"Escalón 12","") | B26: =IF(AND($N$5=1,12<=$N$6),$B$5/$N$6,"") | C26: =IF(AND($N$5=1,12<=$N$6),12*$B$7,"") | E26: =IF(AND($N$5=1,12<=$N$6),IF(ISNUMBER(D26),D26,$B$9),"") | F26: =IF(AND($N$5=1,12<=$N$6),$B$8+C26,"") | G26: =IF(AND($N$5=1,12<=$N$6),B26*E26/100*C26/365,"") | H26: =IF(AND($N$5=1,12<=$N$6),B26+G26,"") | I26: =IF(AND($N$5=1,12<=$N$6),$N$6*$B$7,"")
A28: Cuando armes cada plazo fijo de la escalera, cargalo también en «Mis plazos fijos»: así entra al calendario y al resumen del año.

Sheet Resumen del año
A1: Resumen del año
A2: Junta los plazos fijos de «Mis plazos fijos» que vencen en el año que elijas.
A5: Año | B5: 2026
A7: TUS PLAZOS FIJOS QUE VENCEN EN EL AÑO
A8: Cantidad | B8: =COUNTIFS('Mis plazos fijos'!$Y$15:$Y$38,$B$5)
A9: Capital que pusiste | B9: =SUMIFS('Mis plazos fijos'!$C$15:$C$38,'Mis plazos fijos'!$Y$15:$Y$38,$B$5)
A10: Intereses (cobrados y por cobrar) | B10: =SUMIFS('Mis plazos fijos'!$G$15:$G$38,'Mis plazos fijos'!$Y$15:$Y$38,$B$5)
A11: Intereses ya cobrados al día de hoy | B11: =SUMIFS('Mis plazos fijos'!$Z$15:$Z$38,'Mis plazos fijos'!$Y$15:$Y$38,$B$5)
A12: Ganancia real, en pesos del día en que los armaste | B12: =SUMIFS('Mis plazos fijos'!$W$15:$W$38,'Mis plazos fijos'!$Y$15:$Y$38,$B$5) | C12: Lo que cobrás descontada la inflación de cada plazo. Si da negativo, la inflación se comió más que los intereses.
A14: LA INFLACIÓN DEL AÑO (IPC DEL INDEC)
A15: Inflación acumulada del año | B15: =IF(AND($B$5*12-1>=IPC!$J$2,MIN($B$5*12+11,IPC!$J$3)>=$B$5*12),INDEX(IPC!$D$5:$D$173,(MIN($B$5*12+11,IPC!$J$3))-IPC!$J$2+1)/INDEX(IPC!$D$5:$D$173,($B$5*12-1)-IPC!$J$2+1)-1,"")
A16: Con datos hasta | B16: =IF(AND($B$5*12-1>=IPC!$J$2,MIN($B$5*12+11,IPC!$J$3)>=$B$5*12),INDEX(IPC!$J$5:$J$16,MOD(MIN($B$5*12+11,IPC!$J$3),12)+1)&" de "&INT((MIN($B$5*12+11,IPC!$J$3))/12),"Todavía no hay IPC publicado de ese año")
A18: IMPUESTOS · LO QUE DICE LA LEY (DATO, NO CONSEJO)
A19: Ganancias: los intereses de plazos fijos de personas humanas están exentos (Ley de Impuesto a las Ganancias, t.o. 2019, art. 26 inc. h; texto según la Ley 27.802, B.O. 6/3/2026).
A20: Bienes Personales: los depósitos a plazo fijo están exentos (Ley 23.966, art. 21 inc. h). Si tenés dudas sobre tu situación, consultalo con tu contador.

Sheet IPC
A1: IPC Nacional del INDEC — nivel general (base diciembre 2016 = 100)
A2: Serie oficial descargada el 15/10/2026 de la API de series de tiempo del Estado (datos.gob.ar). Último dato: agosto de 2026. Si ya salió un mes que acá no está, cargá su % en la columna amarilla. | J2: 24203
J3: =J2+COUNT(D5:D173)-1
A4: Período | D4: Índice | E4: Variación del mes | F4: ¿Salió y no está? Cargá el % del mes | G4: Origen | J4: =INDEX(IPC!$J$5:$J$16,MOD(J3,12)+1)&" de "&INT((J3)/12)
A5: diciembre de 2016 | D5: 100 | G5: INDEC | J5: enero
A6: enero de 2017 | D6: 101.5859 | E6: =D6/D5-1 | G6: INDEC | J6: febrero
A7: febrero de 2017 | D7: 103.6859 | E7: =D7/D6-1 | G7: INDEC | J7: marzo
A8: marzo de 2017 | D8: 106.1476 | E8: =D8/D7-1 | G8: INDEC | J8: abril
A9: abril de 2017 | D9: 108.9667 | E9: =D9/D8-1 | G9: INDEC | J9: mayo
A10: mayo de 2017 | D10: 110.5301 | E10: =D10/D9-1 | G10: INDEC | J10: junio
A11: junio de 2017 | D11: 111.8477 | E11: =D11/D10-1 | G11: INDEC | J11: julio
A12: julio de 2017 | D12: 113.7852 | E12: =D12/D11-1 | G12: INDEC | J12: agosto
A13: agosto de 2017 | D13: 115.3819 | E13: =D13/D12-1 | G13: INDEC | J13: septiembre
A14: septiembre de 2017 | D14: 117.5719 | E14: =D14/D13-1 | G14: INDEC | J14: octubre
A15: octubre de 2017 | D15: 119.3528 | E15: =D15/D14-1 | G15: INDEC | J15: noviembre
A16: noviembre de 2017 | D16: 120.994 | E16: =D16/D15-1 | G16: INDEC | J16: diciembre
A17: diciembre de 2017 | D17: 124.7956 | E17: =D17/D16-1 | G17: INDEC
A18: enero de 2018 | D18: 126.9887 | E18: =D18/D17-1 | G18: INDEC
A19: febrero de 2018 | D19: 130.0606 | E19: =D19/D18-1 | G19: INDEC
A20: marzo de 2018 | D20: 133.1054 | E20: =D20/D19-1 | G20: INDEC
A21: abril de 2018 | D21: 136.7512 | E21: =D21/D20-1 | G21: INDEC
A22: mayo de 2018 | D22: 139.5893 | E22: =D22/D21-1 | G22: INDEC
A23: junio de 2018 | D23: 144.8053 | E23: =D23/D22-1 | G23: INDEC
A24: julio de 2018 | D24: 149.2966 | E24: =D24/D23-1 | G24: INDEC
A25: agosto de 2018 | D25: 155.1034 | E25: =D25/D24-1 | G25: INDEC
A26: septiembre de 2018 | D26: 165.2383 | E26: =D26/D25-1 | G26: INDEC
A27: octubre de 2018 | D27: 174.1473 | E27: =D27/D26-1 | G27: INDEC
A28: noviembre de 2018 | D28: 179.6388 | E28: =D28/D27-1 | G28: INDEC
... A121: agosto de 2026 | D121: 12276.766 | E121: =D121/D120-1 | G121: INDEC
A122: septiembre de 2026 | D122: =IF(OR(F122="",D121=""),"",D121*(1+F122/100)) | E122: =IF(D122="","",D122/D121-1) | G122: =IF(F122="","","Cargado por vos")
A123: octubre de 2026 | D123: =IF(OR(F123="",D122=""),"",D122*(1+F123/100)) | E123: =IF(D123="","",D123/D122-1) | G123: =IF(F123="","","Cargado por vos")
A124: noviembre de 2026 | D124: =IF(OR(F124="",D123=""),"",D123*(1+F124/100)) | E124: =IF(D124="","",D124/D123-1) | G124: =IF(F124="","","Cargado por vos")
A125: diciembre de 2026 | D125: =IF(OR(F125="",D124=""),"",D124*(1+F125/100)) | E125: =IF(D125="","",D125/D124-1) | G125: =IF(F125="","","Cargado por vos")
A126: enero de 2027 | D126: =IF(OR(F126="",D125=""),"",D125*(1+F126/100)) | E126: =IF(D126="","",D126/D125-1) | G126: =IF(F126="","","Cargado por vos")
A127: febrero de 2027 | D127: =IF(OR(F127="",D126=""),"",D126*(1+F127/100)) | E127: =IF(D127="","",D127/D126-1) | G127: =IF(F127="","","Cargado por vos")
A128: marzo de 2027 | D128: =IF(OR(F128="",D127=""),"",D127*(1+F128/100)) | E128: =IF(D128="","",D128/D127-1) | G128: =IF(F128="","","Cargado por vos")
A129: abril de 2027 | D129: =IF(OR(F129="",D128=""),"",D128*(1+F129/100)) | E129: =IF(D129="","",D129/D128-1) | G129: =IF(F129="","","Cargado por vos")
A130: mayo de 2027 | D130: =IF(OR(F130="",D129=""),"",D129*(1+F130/100)) | E130: =IF(D130="","",D130/D129-1) | G130: =IF(F130="","","Cargado por vos")
A131: junio de 2027 | D131: =IF(OR(F131="",D130=""),"",D130*(1+F131/100)) | E131: =IF(D131="","",D131/D130-1) | G131: =IF(F131="","","Cargado por vos")
A132: julio de 2027 | D132: =IF(OR(F132="",D131=""),"",D131*(1+F132/100)) | E132: =IF(D132="","",D132/D131-1) | G132: =IF(F132="","","Cargado por vos")
A133: agosto de 2027 | D133: =IF(OR(F133="",D132=""),"",D132*(1+F133/100)) | E133: =IF(D133="","",D133/D132-1) | G133: =IF(F133="","","Cargado por vos")
... A173: diciembre de 2030 | D173: =IF(OR(F173="",D172=""),"",D172*(1+F173/100)) | E173: =IF(D173="","",D173/D172-1) | G173: =IF(F173="","","Cargado por vos")

Sheet Fuentes
A1: Fuentes oficiales
A2: Todos los datos de esta planilla se verificaron el 30 de julio de 2026 contra los documentos oficiales de abajo. Ningún blog, ningún resumen de terceros.
A4: Documento | B4: Link
A5: BCRA: Estadísticas monetarias, tasa de depósitos a 30 días (serie 12) | B5: https://api.bcra.gob.ar/estadisticas/v4.0/monetarias/12
A6: BCRA: Comunicación «A» 8246/2025 (plazo fijo UVA: mínimo 90 días) | B6: https://www.bcra.gob.ar/Pdfs/comytexord/A8246.pdf
A7: BCRA: Comunicación «A» 8407 (garantía de los depósitos: $50.000.000) | B7: https://www.bcra.gob.ar/archivos/Pdfs/comytexord/A8407.pdf
A8: INDEC: IPC Nacional, nivel general (API oficial de series de tiempo) | B8: https://datos.gob.ar/series/api/series/?ids=148.3_INIVELNAL_DICI_M_26&format=json
A9: Ley de Impuesto a las Ganancias t.o. 2019, art. 26 inc. h (Infoleg) | B9: https://servicios.infoleg.gob.ar/infolegInternet/anexos/330000-334999/332890/texact.htm
A11: Planilla de calcular.ar. Serie del IPC descargada el 15/10/2026; TNA de referencia del BCRA al 16/10/2026. Cada vez que el INDEC publica un IPC nuevo regeneramos el archivo: el mismo enlace de descarga te baja la versión al día, sin costo.
