Workbook

Sheet Instrucciones
A1: Cómo usar esta planilla
A3: 1 | B3: Andá a la hoja «Liquidador». Completá solo las celdas amarillas: mes, categoría, modalidad, horas por semana, zona, horas extras y la condición de la persona que trabaja en tu casa.
A4: 2 | B4: Las celdas verdes se calculan solas: el sueldo del mes, el aguinaldo que va generando y lo que tenés que pagarle a ARCA. No escribas encima de ellas.
A5: 3 | B5: En «Pagos del año» anotá lo que pagaste cada mes. Te calcula el aguinaldo de junio y de diciembre con la regla de la ley (50% del mejor sueldo del semestre) y los días de vacaciones.
A6: 4 | B6: La hoja «Recibo» se completa sola con el mes que liquidaste. Cargá los nombres una vez, imprimila por duplicado y que cada parte se quede con una copia firmada.
A7: 5 | B7: «Escala 2026» y «Aportes ARCA» son las tablas oficiales de donde salen los números. «Fuentes» tiene el link a cada documento y la fecha en que se verificó.
A9: LO QUE TENÉS QUE SABER DE ESTE RÉGIMEN
B10: • Hay DOS pisos que conviven: un valor por hora y un mínimo mensual. Si trabaja la jornada completa (48 horas semanales), no puede cobrar menos que el mínimo mensual de su categoría. Con menos horas, se paga por hora. La planilla aplica el que corresponde.
B11: • Las horas extras se pagan con 50% de recargo en días comunes y 100% los sábados después de las 13, los domingos y los feriados (Ley 26.844, art. 25).
B12: • Zona desfavorable: 31% sobre el mínimo de cada categoría desde el 1 de abril de 2026, en La Pampa, Río Negro, Chubut, Neuquén, Santa Cruz, Tierra del Fuego, Antártida e Islas del Atlántico Sur y el partido de Patagones.
B13: • Aguinaldo: 50% de la mayor remuneración mensual del semestre (Ley 26.844, art. 26). Se paga en junio y en diciembre.
B14: • Vacaciones según antigüedad al 31 de diciembre: 14 días (más de 6 meses y hasta 5 años); 21 días (más de 5 y hasta 10 años); 28 días (más de 10 y hasta 20 años); 35 días (más de 20 años). Con menos de 6 meses, un día de descanso cada 20 días trabajados.
B15: • Los pagos de los aportes son siempre a mes vencido: cada mes se paga por lo trabajado en el mes anterior. La excepción es la ART, que se paga a mes en curso.
B16: • Con menos de 16 horas semanales pagás en regla, pero la trabajadora puede quedar sin obra social y sin cómputo jubilatorio: la planilla te muestra cuánto falta para llegar al piso. Si las contribuciones abonadas por la parte empleadora no alcanzaran esa suma, el trabajador podrá pagar la diferencia.
B17: • Los importes de la escala son el MÍNIMO legal, no un tope: podés pagar más. Si pactaron un sueldo mayor, usá ese.
B18: • Si la relación termina (renuncia o despido), la liquidación final tiene reglas propias: usá la calculadora gratis de calcular.ar/despido-empleada-domestica.
A20: Esta planilla da exactamente los mismos números que las calculadoras gratuitas de calcular.ar/empleada-domestica y calcular.ar/aportes-empleada-domestica: misma escala oficial, misma fórmula. Antes de publicar cada versión, una verificación automática recalcula el archivo y lo compara contra esas calculadoras. Si alguna vez difieren, escribinos y lo corregimos.

Sheet Liquidador
A1: Sueldo del mes — Personal de Casas Particulares
A2: Ley 26.844 · Resolución CNTCP 6/2026 · Verificado el 2026-09-15
A4: DATOS DEL MES
A5: Mes a liquidar | B5: septiembre de 2026 | D5: =MATCH(B5,'Escala 2026'!$E$2:$I$2,0)
A6: Categoría | B6: Personal para tareas generales | D6: =CONCATENATE("H|",B6,"|",B7)
A7: Modalidad | B7: Con retiro | D7: =IFERROR(INDEX('Escala 2026'!$E$3:$I$22,MATCH(D6,'Escala 2026'!$A$3:$A$22,0),D5),0)
A8: Horas que trabaja por semana (en tu casa) | B8: 20 | D8: =CONCATENATE("M|",B6,"|",B7)
A9: ¿Zona desfavorable (Patagonia)? | B9: No | D9: =IFERROR(INDEX('Escala 2026'!$E$3:$I$22,MATCH(D8,'Escala 2026'!$A$3:$A$22,0),D5),0)
A10: Horas extras del mes en días comunes | B10: 0 | D10: =IF(B9="Sí",1.31,1)
A11: Horas extras sábado desde las 13, domingo o feriado | B11: 0 | D11: =MIN(MAX(B8,0),48)
A12: Condición de la trabajadora (para ARCA) | B12: Mayor de 18 años | D12: =IF(MAX(B8,0)>=16,"16 horas semanales o más",IF(MAX(B8,0)>=12,"Desde 12 a menos de 16 horas semanales","Menos de 12 horas semanales"))
A13: Chequeo | B13: =IF(D7=0,"Esa combinación no existe en la escala oficial: los caseros son siempre sin retiro.","OK") | D13: =CONCATENATE(B12,"|",D12)
A14: SUELDO DEL MES | D14: =CONCATENATE(B12,"|","16 horas semanales o más")
A15: Valor de la hora | B15: =IF(D7=0,0,ROUND(D7*D10,2))
A16: Mínimo mensual (jornada completa de 48 h) | B16: =ROUND(D9*D10,2)
A17: Horas trabajadas en el mes | B17: =ROUND(D11*52/12,2)
A18: Sueldo por las horas trabajadas | B18: =ROUND(B15*B17,2)
A19: Básico del mes | B19: =IF(D11>=48,MAX(B18,B16),B18)
A20: Horas extras comunes (+50%) | B20: =ROUND(MAX(B10,0)*B15*1.5,2)
A21: Horas extras fin de semana y feriados (+100%) | B21: =ROUND(MAX(B11,0)*B15*2,2)
A22: TOTAL A PAGARLE ESTE MES | B22: =ROUND(B19+B20+B21,2)
A23: Aguinaldo que va generando (50%) | B23: =ROUND(B22/2,2)
A25: LO QUE LE PAGÁS A ARCA (aportes, contribuciones y ART)
A26: Rango de horas para ARCA | B26: =D12
A27: Pago mensual a ARCA por esta trabajadora | B27: =IFERROR(INDEX('Aportes ARCA'!$D$3:$D$11,MATCH(D13,'Aportes ARCA'!$A$3:$A$11,0)),0)
A28: · de eso, cuota de la ART | B28: =IFERROR(INDEX('Aportes ARCA'!$G$3:$G$11,MATCH(D13,'Aportes ARCA'!$A$3:$A$11,0)),0)
A29: Falta para que tenga obra social | B29: =MAX(0,ROUND(IFERROR(INDEX('Aportes ARCA'!$E$3:$E$11,MATCH(D14,'Aportes ARCA'!$A$3:$A$11,0)),0)-IFERROR(INDEX('Aportes ARCA'!$E$3:$E$11,MATCH(D13,'Aportes ARCA'!$A$3:$A$11,0)),0),2))
A30: Falta para que le compute la jubilación | B30: =MAX(0,ROUND(IFERROR(INDEX('Aportes ARCA'!$F$3:$F$11,MATCH(D14,'Aportes ARCA'!$A$3:$A$11,0)),0)-IFERROR(INDEX('Aportes ARCA'!$F$3:$F$11,MATCH(D13,'Aportes ARCA'!$A$3:$A$11,0)),0),2))
A31: COSTO TOTAL DEL MES (sueldo + ARCA) | B31: =ROUND(B22+B27,2)
A33: * Importes mínimos legales. Si pactaron un sueldo mayor, se paga el pactado.
A34: * Los pagos de los aportes son siempre a mes vencido: cada mes se paga por lo trabajado en el mes anterior. La excepción es la ART, que se paga a mes en curso.
A35: * «Falta para…» aparece con menos de 16 horas semanales: pagás en regla, pero sin completar esa diferencia la trabajadora no accede a la obra social y ese mes no le computa para jubilarse. La diferencia la puede pagar ella o la pueden acordar.

Sheet Pagos del año
A1: Pagos del año 2026 — aguinaldo y vacaciones
A3: Mes | B3: Sueldo pagado | C3: Pagado a ARCA | D3: Notas
A4: Enero 2026
A5: Febrero 2026
A6: Marzo 2026
A7: Abril 2026
A8: Mayo 2026
A9: Junio 2026
A10: Julio 2026
A11: Agosto 2026
A12: Septiembre 2026
A13: Octubre 2026
A14: Noviembre 2026
A15: Diciembre 2026
A16: AGUINALDO (Ley 26.844, art. 26)
A17: Aguinaldo de junio (1er semestre) | B17: =ROUND(MAX(B4:B9)/2,2)
A18: Aguinaldo de diciembre (2do semestre) | B18: =ROUND(MAX(B10:B15)/2,2)
A19: Total pagado en sueldos en el año | B19: =SUM(B4:B15)
A20: Total pagado a ARCA en el año | B20: =SUM(C4:C15)
A22: VACACIONES (Ley 26.844, art. 29)
A23: Antigüedad al 31 de diciembre (años) | B23: 1
A24: Días de vacaciones que le corresponden | B24: =IF(B23<=5,14,IF(B23<=10,21,IF(B23<=20,28,35)))
A26: * El aguinaldo es el 50% del MEJOR sueldo del semestre, no el promedio. Si trabajó solo una parte del semestre, corresponde en proporción al tiempo trabajado: para ese caso usá calcular.ar/aguinaldo.
A27: * Con menos de 6 meses de antigüedad no hay licencia completa: corresponde un día de descanso cada 20 días trabajados (Ley 26.844, art. 30).

Sheet Recibo
A1: Recibo de sueldo — Personal de Casas Particulares
A2: Modelo para imprimir por duplicado: una copia firmada queda para cada parte. Las celdas amarillas se completan una sola vez.
A4: Empleador/a (nombre y apellido)
A5: CUIL/CUIT del empleador/a
A6: Trabajador/a (nombre y apellido)
A7: CUIL del trabajador/a
A8: Período | B8: ='Liquidador'!B5
A9: Categoría | B9: ='Liquidador'!B6
A10: Modalidad | B10: ='Liquidador'!B7
A11: Horas semanales | B11: ='Liquidador'!B8
A12: Básico | B12: ='Liquidador'!B19
A13: Horas extras comunes (+50%) | B13: ='Liquidador'!B20
A14: Horas extras fin de semana y feriados (+100%) | B14: ='Liquidador'!B21
A15: TOTAL | B15: ='Liquidador'!B22
A16: Fecha de pago
A19: Recibí conforme el importe total indicado.
A22: Firma del trabajador/a | B22: Firma del empleador/a

Sheet Escala 2026
A1: Escala oficial — Personal de Casas Particulares 2026 (Resolución CNTCP 6/2026)
A2: Clave | B2: Categoría | C2: Modalidad | D2: Valor | E2: agosto de 2026 | F2: septiembre de 2026 | G2: octubre de 2026 | H2: noviembre de 2026 | I2: diciembre de 2026
A3: H|Supervisor/a|Con retiro | B3: Supervisor/a | C3: Con retiro | D3: por hora | E3: 4523.11 | F3: 4645.33 | G3: 4805.82 | H3: 4928.28 | I3: 5007.14
A4: M|Supervisor/a|Con retiro | B4: Supervisor/a | C4: Con retiro | D4: por mes | E4: 564246.7 | F4: 579493.14 | G4: 599514.52 | H4: 614791.27 | I4: 624627.93
A5: H|Supervisor/a|Sin retiro | B5: Supervisor/a | C5: Sin retiro | D5: por hora | E5: 4920.89 | F5: 5049.58 | G5: 5215.59 | H5: 5344.33 | I5: 5429.84
A6: M|Supervisor/a|Sin retiro | B6: Supervisor/a | C6: Sin retiro | D6: por mes | E6: 624313.9 | F6: 640641.55 | G6: 661702.46 | H6: 678036.4 | I6: 688884.98
A7: H|Personal para tareas específicas|Con retiro | B7: Personal para tareas específicas | C7: Con retiro | D7: por hora | E7: 4303.5 | F7: 4422.54 | G7: 4580.8 | H7: 4700.21 | I7: 4775.41
A8: M|Personal para tareas específicas|Con retiro | B8: Personal para tareas específicas | C8: Con retiro | D8: por mes | E8: 526829.56 | F8: 541402.49 | G8: 560776.33 | H8: 575394.53 | I8: 584600.84
A9: H|Personal para tareas específicas|Sin retiro | B9: Personal para tareas específicas | C9: Sin retiro | D9: por hora | E9: 4684.53 | F9: 4809.8 | G9: 4973.38 | H9: 5098.84 | I9: 5180.42
A10: M|Personal para tareas específicas|Sin retiro | B10: Personal para tareas específicas | C10: Sin retiro | D10: por mes | E10: 582283.26 | F10: 597854.36 | G10: 618187.89 | H10: 633782.08 | I10: 643922.59
A11: H|Caseros|Con retiro | B11: Caseros | C11: Con retiro | D11: por hora
A12: M|Caseros|Con retiro | B12: Caseros | C12: Con retiro | D12: por mes
A13: H|Caseros|Sin retiro | B13: Caseros | C13: Sin retiro | D13: por hora | E13: 4072.38 | F13: 4185.94 | G13: 4337.53 | H13: 4451.49 | I13: 4522.71
A14: M|Caseros|Sin retiro | B14: Caseros | C14: Sin retiro | D14: por mes | E14: 514903.51 | F14: 529261.78 | G14: 548429.23 | H14: 562837.52 | I14: 571842.92
A15: H|Asistencia y cuidado de personas|Con retiro | B15: Asistencia y cuidado de personas | C15: Con retiro | D15: por hora | E15: 4072.38 | F15: 4185.94 | G15: 4337.53 | H15: 4451.49 | I15: 4522.71
A16: M|Asistencia y cuidado de personas|Con retiro | B16: Asistencia y cuidado de personas | C16: Con retiro | D16: por mes | E16: 514903.51 | F16: 529261.78 | G16: 548429.23 | H16: 562837.52 | I16: 571842.92
A17: H|Asistencia y cuidado de personas|Sin retiro | B17: Asistencia y cuidado de personas | C17: Sin retiro | D17: por hora | E17: 4520.15 | F17: 4641.9 | G17: 4801.52 | H17: 4923.5 | I17: 5002.28
A18: M|Asistencia y cuidado de personas|Sin retiro | B18: Asistencia y cuidado de personas | C18: Sin retiro | D18: por mes | E18: 569593.41 | F18: 584936.09 | G18: 605050 | H18: 620420.85 | I18: 630347.58
A19: H|Personal para tareas generales|Con retiro | B19: Personal para tareas generales | C19: Con retiro | D19: por hora | E19: 3804.66 | F19: 3914.64 | G19: 4064.08 | H19: 4174.62 | I19: 4241.42
A20: M|Personal para tareas generales|Con retiro | B20: Personal para tareas generales | C20: Con retiro | D20: por mes | E20: 466756.24 | F20: 480247.85 | G20: 498582.06 | H20: 512142.96 | I20: 520337.24
A21: H|Personal para tareas generales|Sin retiro | B21: Personal para tareas generales | C21: Sin retiro | D21: por hora | E21: 4072.38 | F21: 4185.94 | G21: 4337.53 | H21: 4451.49 | I21: 4522.71
A22: M|Personal para tareas generales|Sin retiro | B22: Personal para tareas generales | C22: Sin retiro | D22: por mes | E22: 514903.51 | F22: 529261.78 | G22: 548429.23 | H22: 562837.52 | I22: 571842.92
A24: Valores sin zona desfavorable. El adicional del 31% lo aplica el Liquidador. Los caseros solo existen en la modalidad sin retiro (el anexo trae un guion en «con retiro»).
A25: Importes transcriptos de los Anexos 1 a 5 de la Resolución CNTCP 6/2026 (B.O. 3/9/2026), verificados el 2026-09-15. La columna «Clave» la usa el Liquidador: no la borres.

Sheet Aportes ARCA
A1: Aportes, contribuciones y ART — valores de agosto de 2026 (se pagan en septiembre de 2026)
A2: Clave | B2: Condición | C2: Horas semanales | D2: Total a pagar | E2: Obra social | F2: Jubilación (SIPA) | G2: ART
A3: Mayor de 18 años|Menos de 12 horas semanales | B3: Trabajador/a activo, mayor de 18 años | C3: Menos de 12 horas semanales | D3: 10352.01 | E3: 2084.85 | F3: 729.9 | G3: 7537.26
A4: Mayor de 18 años|Desde 12 a menos de 16 horas semanales | B4: Trabajador/a activo, mayor de 18 años | C4: Desde 12 a menos de 16 horas semanales | D4: 16279.36 | E4: 3863.3 | F4: 1459.48 | G4: 10956.58
A5: Mayor de 18 años|16 horas semanales o más | B5: Trabajador/a activo, mayor de 18 años | C5: 16 horas semanales o más | D5: 43733 | E5: 25694.55 | F5: 2128.79 | G5: 15909.66
A6: De 16 o 17 años|Menos de 12 horas semanales | B6: Trabajador/a de 16 o 17 años | C6: Menos de 12 horas semanales | D6: 9622.11 | E6: 2084.85 | G6: 7537.26
A7: De 16 o 17 años|Desde 12 a menos de 16 horas semanales | B7: Trabajador/a de 16 o 17 años | C7: Desde 12 a menos de 16 horas semanales | D7: 14819.88 | E7: 3863.3 | G7: 10956.58
A8: De 16 o 17 años|16 horas semanales o más | B8: Trabajador/a de 16 o 17 años | C8: 16 horas semanales o más | D8: 41604.21 | E8: 25694.55 | G8: 15909.66
A9: Jubilado/a|Menos de 12 horas semanales | B9: Trabajador/a jubilado | C9: Menos de 12 horas semanales | D9: 8267.16 | F9: 729.9 | G9: 7537.26
A10: Jubilado/a|Desde 12 a menos de 16 horas semanales | B10: Trabajador/a jubilado | C10: Desde 12 a menos de 16 horas semanales | D10: 12416.06 | F10: 1459.48 | G10: 10956.58
A11: Jubilado/a|16 horas semanales o más | B11: Trabajador/a jubilado | C11: 16 horas semanales o más | D11: 18038.45 | F11: 2128.79 | G11: 15909.66
A13: Montos fijos por trabajador, de la tabla oficial de ARCA (Casas-particulares-aportes-y-contribuciones-08-26.pdf). Celda vacía = ese concepto no se paga en esa condición.
A14: Los pagos de los aportes son siempre a mes vencido: cada mes se paga por lo trabajado en el mes anterior. La excepción es la ART, que se paga a mes en curso.
A15: Para tener acceso a las prestaciones, los aportes de obra social tienen que ser iguales o superiores a la cuota establecida para la categoría de 16 o más horas trabajadas semanalmente.

Sheet Fuentes
A1: Fuentes oficiales
A2: Todos los datos de esta planilla se verificaron el 2026-09-15 contra los documentos oficiales de abajo. Ningún blog, ningún resumen de terceros.
A4: Documento | B4: Link
A5: Resolución CNTCP 6/2026 (texto completo) | B5: https://www.boletinoficial.gob.ar/detalleAviso/primera/346855/20260903
A6: Resolución CNTCP 6/2026 — Anexos 1 a 5 (las escalas) | B6: https://www.boletinoficial.gob.ar/detalleAviso/primera/346855/20260903
A7: Resolución CNTCP 4/2026 — la escala anterior (abril a julio de 2026) | B7: https://www.argentina.gob.ar/normativa/426540_res4-4_pdf/archivo
A8: Ley 26.844 — Régimen Especial para el Personal de Casas Particulares | B8: https://servicios.infoleg.gob.ar/infolegInternet/anexos/210000-214999/210489/texact.htm
A9: ARCA — Aportes, contribuciones y ART de casas particulares (tabla oficial) | B9: https://www.arca.gob.ar/casasparticulares/aportes-contribuciones-ART/documentos/2026/Casas-particulares-aportes-y-contribuciones-08-26.pdf
A10: ARCA — Conceptos y valores del pago mensual | B10: https://www.arca.gob.ar/casasparticulares/aportes-contribuciones-ART/conceptos.asp
A11: ARCA — Obra social del personal de casas particulares | B11: https://www.arca.gob.ar/casasparticulares/ayuda/empleador/obra-social.asp
A12: ARCA — Jubilación del personal de casas particulares | B12: https://www.arca.gob.ar/casasparticulares/ayuda/empleador/jubilacion.asp
A13: Ley 26.844 — Régimen Especial para el Personal de Casas Particulares | B13: https://servicios.infoleg.gob.ar/infolegInternet/anexos/210000-214999/210489/texact.htm
A15: Planilla de calcular.ar. Las actualizaciones del año están incluidas en el precio: cuando la Comisión Nacional de Trabajo en Casas Particulares fija una escala nueva, o ARCA publica la tabla de aportes del mes, regeneramos la planilla y el mismo enlace de descarga te baja la versión al día.
