Workbook

Sheet Instrucciones
A1: Planilla de sueldos Camioneros 2026 — cómo usarla
A3: 1 | B3: En «Liquidador» elegí categoría, mes, años de antigüedad y zona. Si el chofer viajó, cargá los kilómetros, las comidas, los viáticos especiales y las pernoctadas del mes.
A4: 2 | B4: Solo se completan las celdas amarillas. Las verdes se calculan solas: básico, horas extra por km, antigüedad, aportes, neto y lo que cobra en total.
A5: 3 | B5: «Nómina» liquida a toda la flota en una sola hoja: un trabajador por fila, con el mismo mes del Liquidador. Abajo tenés los totales del mes.
A6: 4 | B6: «Recibo» toma lo del Liquidador y queda listo para imprimir en A4. Los datos de la empresa y del trabajador se escriben acá y no salen de tu computadora.
A7: 5 | B7: «SAC (Aguinaldo)» calcula el medio aguinaldo con el mejor mes del semestre, proporcional si trabajó menos tiempo.
A8: 6 | B8: «Escala 2026» tiene los básicos firmados mes por mes y «Fuentes» el PDF oficial de cada uno. Si alguien te discute un número, ahí está el documento.
A10: LO QUE TENÉS QUE SABER DEL CCT 40/89
B11: • Escala nacional única: el básico es el mismo en todo el país. Los básicos de esta planilla son los de las planillas firmadas que publica FADEEAC, de marzo 2026 a febrero 2027 (Disposiciones DNRyRT 455/2026 y 1277/2026, y revisión de julio).
B12: • Antigüedad (ítem 6.1.5): 1% por año sobre los conceptos remunerativos. Sin kilómetros ni adicionales, es el 1% del básico por año.
B13: • Kilómetros: el ítem 4.2.3 (horas extraordinarias por kilometraje) es remunerativo y lleva aportes; el ítem 4.2.4 (viático por km) no. Los dos valen lo mismo por km. El viático 4.2.4 no puede ser menor a 350 km por día de viaje, y el 4.2.3 se paga al 100% más los sábados después de las 13, domingos y feriados: esos km cargalos dobles.
B14: • Comida (4.1.12), viático especial (4.1.13), pernoctada (4.1.14) y viático por km (4.2.4) no son remunerativos (ítem 4.2.11 del convenio y art. 106 de la LCT): no llevan aportes ni entran en el aguinaldo.
B15: • Zona: quien reside al sur del Río Colorado cobra los viáticos y el 4.2.3 con coeficiente 1,2, y al sur del Río Santa Cruz con 1,4. El básico no cambia.
B16: • Los valores de viáticos son los de la planilla de octubre 2026. Si liquidás otro mes, reemplazalos en el Liquidador por los de esa planilla (son celdas amarillas).
B17: • Aportes del trabajador: 11% jubilación, 3% PAMI (Ley 19.032) y 3% obra social, sobre lo remunerativo.
B18: • La escala llega hasta febrero 2027, la última planilla firmada publicada por FADEEAC. Cuando salga la siguiente, la cargamos y la versión nueva te llega al mismo enlace de descarga: no vence.
A20: Es una referencia de cálculo con las fuentes a la vista, no un recibo oficial. No incluye contribuciones patronales, ART, cuota sindical ni aportes solidarios del convenio, Ganancias ni embargos. Los adicionales por rama (combustibles, sustancias peligrosas, larga distancia y otros) se cargan en «Otros adicionales».
A22: Con kilómetros y viáticos en cero, esta planilla da exactamente los mismos números que la calculadora gratis de calcular.ar/convenios/camioneros: misma escala, misma cuenta. Si alguna vez difieren, escribinos y lo corregimos.

Sheet Liquidador
A1: Liquidación de sueldo — Camioneros (CCT 40/89)
A2: Básicos de las planillas firmadas FADEEAC · verificados el 10/10/2026 · calcular.ar
A4: DATOS DEL TRABAJADOR
A5: Categoría | B5: Chofer de Primera | D5: =MATCH(B6,'Escala 2026'!$B$2:$M$2,0)
A6: Mes a liquidar | B6: Febrero 2027 | D6: =INDEX('Escala 2026'!$B$3:$M$11,MATCH(B5,'Escala 2026'!$A$3:$A$11,0),D5)
A7: Años de antigüedad | B7: 0 | C7: Ítem 6.1.5: 1% por año sobre lo remunerativo | D7: =IF(B8="Sur del Río Santa Cruz",1.4,IF(B8="Sur del Río Colorado",1.2,1))
A8: Zona de residencia | B8: General | C8: Coeficiente 1,20 / 1,40 sobre viáticos y 4.2.3
A10: VIAJES Y ADICIONALES DEL MES (en cero si no viajó)
A11: Km recorridos — horas extra por km | B11: 0 | C11: Ítem 4.2.3 · remunerativo
A12: Km recorridos — viático por km | B12: 0 | C12: Ítem 4.2.4 · no remunerativo · mínimo 350 km por día de viaje
A13: Comidas | B13: 0 | C13: Ítem 4.1.12 · no remunerativo
A14: Viáticos especiales | B14: 0 | C14: Ítem 4.1.13 · no remunerativo
A15: Pernoctadas | B15: 0 | C15: Ítem 4.1.14 · no remunerativo
A16: Otros adicionales remunerativos ($) | B16: 0 | C16: Adicionales por rama, horas extra, etc.
A17: Otros no remunerativos ($) | B17: 0 | C17: Permanencia (4.2.5), cruce de frontera (4.2.17), etc.
A18: LIQUIDACIÓN DEL MES
A19: Sueldo básico | B19: =D6
A20: Horas extra por km (4.2.3) | B20: =B11*B32*D7
A21: Otros adicionales remunerativos | B21: =B16
A22: Antigüedad | B22: =(B19+B20+B21)*0.01*B7
A23: TOTAL REMUNERATIVO (bruto) | B23: =B19+B20+B21+B22 | C23: Base de aportes y del aguinaldo
A24: Jubilación (11%) | B24: =-B23*0.11
A25: PAMI — Ley 19.032 (3%) | B25: =-B23*0.03
A26: Obra social (3%) | B26: =-B23*0.03
A27: NETO DE HABERES | B27: =B23+B24+B25+B26
A28: Viáticos no remunerativos | B28: =(B12*B32+B13*B33+B14*B34+B15*B35)*D7+B17 | C28: No llevan aportes (ítem 4.2.11 y art. 106 LCT)
A29: TOTAL A COBRAR | B29: =B27+B28
A31: VALORES DE VIÁTICOS (planilla octubre 2026)
A32: Valor por km (4.2.3 y 4.2.4) | B32: 90.09389 | C32: =IF(B6="Octubre 2026","Valores de la planilla firmada de octubre 2026","Ojo: son los valores de octubre 2026. Reemplazalos por los de la planilla de "&B6)
A33: Comida (4.1.12) | B33: 17231.89
A34: Viático especial (4.1.13) | B34: 8646.93
A35: Pernoctada (4.1.14) | B35: 20070.36
A37: * El sueldo del convenio es un piso: si pagan más, cargá la diferencia en «Otros adicionales remunerativos».
A38: * El neto no descuenta cuota sindical, aportes solidarios, Ganancias ni embargos. No incluye contribuciones patronales ni ART.
A39: * Las celdas amarillas se completan; las verdes las calcula la planilla. La columna D está oculta a propósito: no la borres.

Sheet Nómina
A1: Nómina del mes — toda la flota en una hoja
A2: Mes liquidado | B2: ='Liquidador'!B6 | C2: El mes y los valores de viáticos salen del Liquidador. Un trabajador por fila; las filas sin categoría no suman.
A3: Amarillo: lo cargás vos. Verde: lo calcula la planilla. Con km y viáticos en cero, cada fila da lo mismo que la calculadora gratis.
A5: Trabajador | B5: Categoría | C5: Años | D5: Zona | E5: Km 4.2.3 | F5: Km 4.2.4 | G5: Comidas | H5: Viát. esp. | I5: Pernoct. | J5: Otros rem. $ | K5: Otros no rem. $ | L5: Básico | M5: Horas extra km | N5: Antigüedad | O5: Total remunerativo | P5: Aportes 17% | Q5: Neto de haberes | R5: No remunerativo | S5: A cobrar | T5: coef
A6: Trabajador 1 | B6: Chofer de Primera | C6: 0 | D6: General | L6: =IF(B6="","",INDEX('Escala 2026'!$B$3:$M$11,MATCH(B6,'Escala 2026'!$A$3:$A$11,0),'Liquidador'!$D$5)) | M6: =IF(B6="","",E6*'Liquidador'!$B$32*T6) | N6: =IF(B6="","",(L6+M6+J6)*0.01*C6) | O6: =IF(B6="","",L6+M6+J6+N6) | P6: =IF(B6="","",O6*(0.11+0.03+0.03)) | Q6: =IF(B6="","",O6-P6) | R6: =IF(B6="","",(F6*'Liquidador'!$B$32+G6*'Liquidador'!$B$33+H6*'Liquidador'!$B$34+I6*'Liquidador'!$B$35)*T6+K6) | S6: =IF(B6="","",Q6+R6) | T6: =IF(D6="Sur del Río Santa Cruz",1.4,IF(D6="Sur del Río Colorado",1.2,1))
L7: =IF(B7="","",INDEX('Escala 2026'!$B$3:$M$11,MATCH(B7,'Escala 2026'!$A$3:$A$11,0),'Liquidador'!$D$5)) | M7: =IF(B7="","",E7*'Liquidador'!$B$32*T7) | N7: =IF(B7="","",(L7+M7+J7)*0.01*C7) | O7: =IF(B7="","",L7+M7+J7+N7) | P7: =IF(B7="","",O7*(0.11+0.03+0.03)) | Q7: =IF(B7="","",O7-P7) | R7: =IF(B7="","",(F7*'Liquidador'!$B$32+G7*'Liquidador'!$B$33+H7*'Liquidador'!$B$34+I7*'Liquidador'!$B$35)*T7+K7) | S7: =IF(B7="","",Q7+R7) | T7: =IF(D7="Sur del Río Santa Cruz",1.4,IF(D7="Sur del Río Colorado",1.2,1))
L8: =IF(B8="","",INDEX('Escala 2026'!$B$3:$M$11,MATCH(B8,'Escala 2026'!$A$3:$A$11,0),'Liquidador'!$D$5)) | M8: =IF(B8="","",E8*'Liquidador'!$B$32*T8) | N8: =IF(B8="","",(L8+M8+J8)*0.01*C8) | O8: =IF(B8="","",L8+M8+J8+N8) | P8: =IF(B8="","",O8*(0.11+0.03+0.03)) | Q8: =IF(B8="","",O8-P8) | R8: =IF(B8="","",(F8*'Liquidador'!$B$32+G8*'Liquidador'!$B$33+H8*'Liquidador'!$B$34+I8*'Liquidador'!$B$35)*T8+K8) | S8: =IF(B8="","",Q8+R8) | T8: =IF(D8="Sur del Río Santa Cruz",1.4,IF(D8="Sur del Río Colorado",1.2,1))
L9: =IF(B9="","",INDEX('Escala 2026'!$B$3:$M$11,MATCH(B9,'Escala 2026'!$A$3:$A$11,0),'Liquidador'!$D$5)) | M9: =IF(B9="","",E9*'Liquidador'!$B$32*T9) | N9: =IF(B9="","",(L9+M9+J9)*0.01*C9) | O9: =IF(B9="","",L9+M9+J9+N9) | P9: =IF(B9="","",O9*(0.11+0.03+0.03)) | Q9: =IF(B9="","",O9-P9) | R9: =IF(B9="","",(F9*'Liquidador'!$B$32+G9*'Liquidador'!$B$33+H9*'Liquidador'!$B$34+I9*'Liquidador'!$B$35)*T9+K9) | S9: =IF(B9="","",Q9+R9) | T9: =IF(D9="Sur del Río Santa Cruz",1.4,IF(D9="Sur del Río Colorado",1.2,1))
L10: =IF(B10="","",INDEX('Escala 2026'!$B$3:$M$11,MATCH(B10,'Escala 2026'!$A$3:$A$11,0),'Liquidador'!$D$5)) | M10: =IF(B10="","",E10*'Liquidador'!$B$32*T10) | N10: =IF(B10="","",(L10+M10+J10)*0.01*C10) | O10: =IF(B10="","",L10+M10+J10+N10) | P10: =IF(B10="","",O10*(0.11+0.03+0.03)) | Q10: =IF(B10="","",O10-P10) | R10: =IF(B10="","",(F10*'Liquidador'!$B$32+G10*'Liquidador'!$B$33+H10*'Liquidador'!$B$34+I10*'Liquidador'!$B$35)*T10+K10) | S10: =IF(B10="","",Q10+R10) | T10: =IF(D10="Sur del Río Santa Cruz",1.4,IF(D10="Sur del Río Colorado",1.2,1))
L11: =IF(B11="","",INDEX('Escala 2026'!$B$3:$M$11,MATCH(B11,'Escala 2026'!$A$3:$A$11,0),'Liquidador'!$D$5)) | M11: =IF(B11="","",E11*'Liquidador'!$B$32*T11) | N11: =IF(B11="","",(L11+M11+J11)*0.01*C11) | O11: =IF(B11="","",L11+M11+J11+N11) | P11: =IF(B11="","",O11*(0.11+0.03+0.03)) | Q11: =IF(B11="","",O11-P11) | R11: =IF(B11="","",(F11*'Liquidador'!$B$32+G11*'Liquidador'!$B$33+H11*'Liquidador'!$B$34+I11*'Liquidador'!$B$35)*T11+K11) | S11: =IF(B11="","",Q11+R11) | T11: =IF(D11="Sur del Río Santa Cruz",1.4,IF(D11="Sur del Río Colorado",1.2,1))
L12: =IF(B12="","",INDEX('Escala 2026'!$B$3:$M$11,MATCH(B12,'Escala 2026'!$A$3:$A$11,0),'Liquidador'!$D$5)) | M12: =IF(B12="","",E12*'Liquidador'!$B$32*T12) | N12: =IF(B12="","",(L12+M12+J12)*0.01*C12) | O12: =IF(B12="","",L12+M12+J12+N12) | P12: =IF(B12="","",O12*(0.11+0.03+0.03)) | Q12: =IF(B12="","",O12-P12) | R12: =IF(B12="","",(F12*'Liquidador'!$B$32+G12*'Liquidador'!$B$33+H12*'Liquidador'!$B$34+I12*'Liquidador'!$B$35)*T12+K12) | S12: =IF(B12="","",Q12+R12) | T12: =IF(D12="Sur del Río Santa Cruz",1.4,IF(D12="Sur del Río Colorado",1.2,1))
L13: =IF(B13="","",INDEX('Escala 2026'!$B$3:$M$11,MATCH(B13,'Escala 2026'!$A$3:$A$11,0),'Liquidador'!$D$5)) | M13: =IF(B13="","",E13*'Liquidador'!$B$32*T13) | N13: =IF(B13="","",(L13+M13+J13)*0.01*C13) | O13: =IF(B13="","",L13+M13+J13+N13) | P13: =IF(B13="","",O13*(0.11+0.03+0.03)) | Q13: =IF(B13="","",O13-P13) | R13: =IF(B13="","",(F13*'Liquidador'!$B$32+G13*'Liquidador'!$B$33+H13*'Liquidador'!$B$34+I13*'Liquidador'!$B$35)*T13+K13) | S13: =IF(B13="","",Q13+R13) | T13: =IF(D13="Sur del Río Santa Cruz",1.4,IF(D13="Sur del Río Colorado",1.2,1))
L14: =IF(B14="","",INDEX('Escala 2026'!$B$3:$M$11,MATCH(B14,'Escala 2026'!$A$3:$A$11,0),'Liquidador'!$D$5)) | M14: =IF(B14="","",E14*'Liquidador'!$B$32*T14) | N14: =IF(B14="","",(L14+M14+J14)*0.01*C14) | O14: =IF(B14="","",L14+M14+J14+N14) | P14: =IF(B14="","",O14*(0.11+0.03+0.03)) | Q14: =IF(B14="","",O14-P14) | R14: =IF(B14="","",(F14*'Liquidador'!$B$32+G14*'Liquidador'!$B$33+H14*'Liquidador'!$B$34+I14*'Liquidador'!$B$35)*T14+K14) | S14: =IF(B14="","",Q14+R14) | T14: =IF(D14="Sur del Río Santa Cruz",1.4,IF(D14="Sur del Río Colorado",1.2,1))
L15: =IF(B15="","",INDEX('Escala 2026'!$B$3:$M$11,MATCH(B15,'Escala 2026'!$A$3:$A$11,0),'Liquidador'!$D$5)) | M15: =IF(B15="","",E15*'Liquidador'!$B$32*T15) | N15: =IF(B15="","",(L15+M15+J15)*0.01*C15) | O15: =IF(B15="","",L15+M15+J15+N15) | P15: =IF(B15="","",O15*(0.11+0.03+0.03)) | Q15: =IF(B15="","",O15-P15) | R15: =IF(B15="","",(F15*'Liquidador'!$B$32+G15*'Liquidador'!$B$33+H15*'Liquidador'!$B$34+I15*'Liquidador'!$B$35)*T15+K15) | S15: =IF(B15="","",Q15+R15) | T15: =IF(D15="Sur del Río Santa Cruz",1.4,IF(D15="Sur del Río Colorado",1.2,1))
L16: =IF(B16="","",INDEX('Escala 2026'!$B$3:$M$11,MATCH(B16,'Escala 2026'!$A$3:$A$11,0),'Liquidador'!$D$5)) | M16: =IF(B16="","",E16*'Liquidador'!$B$32*T16) | N16: =IF(B16="","",(L16+M16+J16)*0.01*C16) | O16: =IF(B16="","",L16+M16+J16+N16) | P16: =IF(B16="","",O16*(0.11+0.03+0.03)) | Q16: =IF(B16="","",O16-P16) | R16: =IF(B16="","",(F16*'Liquidador'!$B$32+G16*'Liquidador'!$B$33+H16*'Liquidador'!$B$34+I16*'Liquidador'!$B$35)*T16+K16) | S16: =IF(B16="","",Q16+R16) | T16: =IF(D16="Sur del Río Santa Cruz",1.4,IF(D16="Sur del Río Colorado",1.2,1))
L17: =IF(B17="","",INDEX('Escala 2026'!$B$3:$M$11,MATCH(B17,'Escala 2026'!$A$3:$A$11,0),'Liquidador'!$D$5)) | M17: =IF(B17="","",E17*'Liquidador'!$B$32*T17) | N17: =IF(B17="","",(L17+M17+J17)*0.01*C17) | O17: =IF(B17="","",L17+M17+J17+N17) | P17: =IF(B17="","",O17*(0.11+0.03+0.03)) | Q17: =IF(B17="","",O17-P17) | R17: =IF(B17="","",(F17*'Liquidador'!$B$32+G17*'Liquidador'!$B$33+H17*'Liquidador'!$B$34+I17*'Liquidador'!$B$35)*T17+K17) | S17: =IF(B17="","",Q17+R17) | T17: =IF(D17="Sur del Río Santa Cruz",1.4,IF(D17="Sur del Río Colorado",1.2,1))
L18: =IF(B18="","",INDEX('Escala 2026'!$B$3:$M$11,MATCH(B18,'Escala 2026'!$A$3:$A$11,0),'Liquidador'!$D$5)) | M18: =IF(B18="","",E18*'Liquidador'!$B$32*T18) | N18: =IF(B18="","",(L18+M18+J18)*0.01*C18) | O18: =IF(B18="","",L18+M18+J18+N18) | P18: =IF(B18="","",O18*(0.11+0.03+0.03)) | Q18: =IF(B18="","",O18-P18) | R18: =IF(B18="","",(F18*'Liquidador'!$B$32+G18*'Liquidador'!$B$33+H18*'Liquidador'!$B$34+I18*'Liquidador'!$B$35)*T18+K18) | S18: =IF(B18="","",Q18+R18) | T18: =IF(D18="Sur del Río Santa Cruz",1.4,IF(D18="Sur del Río Colorado",1.2,1))
... L35: =IF(B35="","",INDEX('Escala 2026'!$B$3:$M$11,MATCH(B35,'Escala 2026'!$A$3:$A$11,0),'Liquidador'!$D$5)) | M35: =IF(B35="","",E35*'Liquidador'!$B$32*T35) | N35: =IF(B35="","",(L35+M35+J35)*0.01*C35) | O35: =IF(B35="","",L35+M35+J35+N35) | P35: =IF(B35="","",O35*(0.11+0.03+0.03)) | Q35: =IF(B35="","",O35-P35) | R35: =IF(B35="","",(F35*'Liquidador'!$B$32+G35*'Liquidador'!$B$33+H35*'Liquidador'!$B$34+I35*'Liquidador'!$B$35)*T35+K35) | S35: =IF(B35="","",Q35+R35) | T35: =IF(D35="Sur del Río Santa Cruz",1.4,IF(D35="Sur del Río Colorado",1.2,1))
A36: TOTALES DEL MES | L36: =SUM(L6:L35) | M36: =SUM(M6:M35) | N36: =SUM(N6:N35) | O36: =SUM(O6:O35) | P36: =SUM(P6:P35) | Q36: =SUM(Q6:Q35) | R36: =SUM(R6:R35) | S36: =SUM(S6:S35)

Sheet Recibo
A1: Recibo de haberes — CCT 40/89 Camioneros
A2: Se completa solo con el Liquidador. Los datos de la empresa y del trabajador se escriben una vez acá: no salen de tu computadora.
A4: Empleador (razón social)
A5: CUIT del empleador
A6: Trabajador (apellido y nombre)
A7: CUIL del trabajador
A8: Fecha de ingreso
A9: Período | B9: ='Liquidador'!B6
A10: Categoría | B10: ='Liquidador'!B5
A11: Años de antigüedad | B11: ='Liquidador'!B7
A13: Concepto | B13: Cantidad | C13: Haberes rem. | D13: No remunerativo | E13: Descuentos
A14: Sueldo básico | C14: ='Liquidador'!B19
A15: Horas extra por km (4.2.3) | B15: ='Liquidador'!B11 | C15: ='Liquidador'!B20
A16: Otros adicionales remunerativos | C16: ='Liquidador'!B21
A17: Antigüedad (6.1.5) | B17: ='Liquidador'!B7 | C17: ='Liquidador'!B22
A18: Viáticos, comidas y pernoctadas (no rem.) | D18: ='Liquidador'!B28
A19: Jubilación 11% | E19: =-'Liquidador'!B24
A20: PAMI Ley 19.032 3% | E20: =-'Liquidador'!B25
A21: Obra social 3% | E21: =-'Liquidador'!B26
A22: Totales | C22: =SUM(C14:C21) | D22: =SUM(D14:D21) | E22: =SUM(E14:E21)
A23: NETO A COBRAR | E23: =C22+D22-E22
A25: Lugar y fecha de pago
A26: Los aportes del trabajador se depositaron en el período anterior. Recibí el importe neto de este recibo y un duplicado firmado.
A30: Firma del trabajador | C30: Firma y sello del empleador

Sheet SAC (Aguinaldo)
A1: Aguinaldo (SAC) — Ley 23.041 y arts. 121 a 123 LCT
A3: DATOS DEL SEMESTRE
A4: Semestre | B4: 2do semestre 2026
A5: =IF(B4="1er semestre 2026","Enero","Julio")&" — total remunerativo" | B5: ='Liquidador'!B23 | C5: Vienen con el bruto del Liquidador: escribí encima lo que pagaste cada mes
A6: =IF(B4="1er semestre 2026","Febrero","Agosto")&" — total remunerativo" | B6: ='Liquidador'!B23
A7: =IF(B4="1er semestre 2026","Marzo","Septiembre")&" — total remunerativo" | B7: ='Liquidador'!B23
A8: =IF(B4="1er semestre 2026","Abril","Octubre")&" — total remunerativo" | B8: ='Liquidador'!B23
A9: =IF(B4="1er semestre 2026","Mayo","Noviembre")&" — total remunerativo" | B9: ='Liquidador'!B23
A10: =IF(B4="1er semestre 2026","Junio","Diciembre")&" — total remunerativo" | B10: ='Liquidador'!B23
A11: Días trabajados en el semestre | C11: Dejala vacía si trabajó el semestre completo
A13: AGUINALDO
A14: Mejor remuneración del semestre | B14: =MAX(B5:B10)
A15: Días del semestre | B15: =IF(B4="1er semestre 2026",181,184)
A16: Días computados | B16: =IF(ISBLANK(B11),B15,MIN(B11,B15))
A17: SAC bruto | B17: =B14/2*B16/B15
A18: Jubilación (11%) | B18: =-B17*0.11
A19: PAMI (3%) | B19: =-B17*0.03
A20: Obra social (3%) | B20: =-B17*0.03
A21: SAC NETO ESTIMADO | B21: =SUM(B17:B20)
A23: * El aguinaldo es el 50% de la MEJOR remuneración mensual del semestre, no el promedio. Si trabajó una parte, es proporcional a los días.
A24: * Vencimientos: 30 de junio de 2026 y 18 de diciembre de 2026 (art. 122 LCT). Los viáticos no remunerativos (4.1.12, 4.1.13, 4.1.14, 4.2.4) no entran en la base.

Sheet Escala 2026
A1: Básicos mensuales oficiales — CCT 40/89 (planillas firmadas FADEEAC)
A2: Categoría | B2: Marzo 2026 | C2: Abril 2026 | D2: Mayo 2026 | E2: Junio 2026 | F2: Julio 2026 | G2: Agosto 2026 | H2: Septiembre 2026 | I2: Octubre 2026 | J2: Noviembre 2026 | K2: Diciembre 2026 | L2: Enero 2027 | M2: Febrero 2027
A3: Chofer de Primera | B3: 917462.42 | C3: 984338.23 | D3: 1001072 | E3: 1017089.1 | F3: 1060010.3 | G3: 1075910.4 | H3: 1095276.8 | I3: 1126149.4 | J3: 1145293.9 | K3: 1163618.6 | L3: 1182236.5 | M3: 1199970.1
A4: Chofer de Segunda | B4: 901112.88 | C4: 966796.94 | D4: 983232.49 | E4: 998964.21 | F4: 1041120.5 | G4: 1056737.3 | H4: 1075758.6 | I4: 1106081 | J4: 1124884.4 | K4: 1142882.5 | L4: 1161168.6 | M4: 1178586.2
A5: Chofer de Tercera | B5: 884746.81 | C5: 949237.91 | D5: 965374.95 | E5: 980820.95 | F5: 1022211.6 | G5: 1037544.8 | H5: 1056220.6 | I5: 1085992.3 | J5: 1104454.1 | K5: 1122125.4 | L5: 1140079.4 | M5: 1157180.6
A6: Encargado | B6: 862285.2 | C6: 925139.02 | D6: 940866.38 | E6: 955920.24 | F6: 996260.07 | G6: 1011204 | H6: 1029405.6 | I6: 1058421.5 | J6: 1076414.7 | K6: 1093637.3 | L6: 1111135.5 | M6: 1127802.5
A7: Peón | B7: 837929.46 | C7: 899007.94 | D7: 914291.07 | E7: 928919.73 | F7: 968120.14 | G7: 982641.94 | H7: 1000329.5 | I7: 1028525.8 | J7: 1046010.7 | K7: 1062746.9 | L7: 1079750.8 | M7: 1095947.1
A8: Ayudante mayor de 18 años | B8: 821870.69 | C8: 881778.61 | D8: 896768.85 | E8: 911117.15 | F8: 949566.29 | G8: 963809.78 | H8: 981158.36 | I8: 1008814.3 | J8: 1025964.1 | K8: 1042379.5 | L8: 1059057.6 | M8: 1074943.5
A9: Oficial de Primera (taller) | B9: 1021805.2 | C9: 1096286.8 | D9: 1114923.7 | E9: 1132762.5 | F9: 1180565.1 | G9: 1198273.5 | H9: 1219842.5 | I9: 1254226.2 | J9: 1275548 | K9: 1295956.8 | L9: 1316692.1 | M9: 1336442.5
A10: Oficial (taller) | B10: 921140.39 | C10: 988284.3 | D10: 1005085.1 | E10: 1021166.5 | F10: 1064259.7 | G10: 1080223.6 | H10: 1099667.6 | I10: 1130664 | J10: 1149885.3 | K10: 1168283.4 | L10: 1186976 | M10: 1204780.6
A11: Medio Oficial (taller) | B11: 870164.95 | C11: 933593.15 | D11: 949464.23 | E11: 964655.66 | F11: 1005364.1 | G11: 1020444.6 | H11: 1038812.6 | I11: 1068093.6 | J11: 1086251.2 | K11: 1103631.2 | L11: 1121289.3 | M11: 1138108.6
A13: Marzo 2026: Primer tramo del acuerdo del 13/3/2026. Además, suma no remunerativa de $53.000 por única vez con los haberes de marzo (cláusula PRIMERA).
A14: Abril 2026: Se incorporan al básico $49.471 de la suma no remunerativa de marzo (al Chofer de Primera, y en proporción al resto). Además, corre el tramo de abril.
A15: Mayo 2026: Tramo de mayo: +1,7% sobre el básico de abril.
A16: Junio 2026: Tramo de junio: +1,6% sobre el básico de mayo.
A17: Julio 2026: +4,22% sobre junio: acá entra la REVISIÓN de la cláusula TERCERA (no es el +1,5% del tramo original). La escala de julio se republicó firmada en agosto.
A18: Agosto 2026: Último tramo del acuerdo: +1,5% sobre el básico de julio (ya revisado). Desde septiembre rige el acuerdo del 18/9/2026.
A19: Septiembre 2026: Primer tramo del acuerdo del 18/9/2026: +1,8% sobre el básico de agosto. Además, suma no remunerativa de $18.000 por única vez con los haberes de septiembre (cláusula PRIMERA).
A20: Octubre 2026: Tramo de octubre: +1,7% sobre septiembre, y se incorporan al básico $12.252,86 de la suma no remunerativa de septiembre (al Chofer de Primera, y en proporción al resto). En total, +2,82%.
A21: Noviembre 2026: Tramo de noviembre: +1,7% sobre el básico de octubre.
A22: Diciembre 2026: Tramo de diciembre: +1,6% sobre el básico de noviembre. El acuerdo prevé una revisión en la primera quincena de diciembre contra la inflación de septiembre a noviembre.
A23: Enero 2027: Tramo de enero: +1,6% sobre el básico de diciembre. Además, empieza la asignación extraordinaria no remunerativa: 4 cuotas de $300.000 (enero a abril de 2027).
A24: Febrero 2027: Último tramo del acuerdo del 18/9/2026: +1,5% sobre el básico de enero. Hay una revisión pactada para la primera quincena de marzo de 2027.
... A27: El Liquidador y la Nómina buscan el básico por el nombre de la categoría y del mes: no los edites.

Sheet Fuentes
A1: Fuentes oficiales
A2: Todos los datos de esta planilla se verificaron el 10/10/2026 contra los documentos oficiales de abajo. Ningún blog, ningún resumen de terceros.
A4: Documento | B4: Link
A5: FADEEAC — planilla salarial firmada de marzo 2026 (CCT 40/89) | B5: https://www.fadeeac.org.ar/wp-content/uploads/2026/03/Planilla-MARZO-26.pdf
A6: FADEEAC — planilla salarial firmada de abril 2026 (CCT 40/89) | B6: https://www.fadeeac.org.ar/wp-content/uploads/2026/03/Planilla-ABRIL-26.pdf
A7: FADEEAC — planilla salarial firmada de mayo 2026 (CCT 40/89) | B7: https://www.fadeeac.org.ar/wp-content/uploads/2026/03/Planilla-MAYO-26.pdf
A8: FADEEAC — planilla salarial firmada de junio 2026 (CCT 40/89) | B8: https://www.fadeeac.org.ar/wp-content/uploads/2026/03/Planilla-JUNIO-26.pdf
A9: FADEEAC — planilla salarial firmada de julio 2026 (CCT 40/89) | B9: https://www.fadeeac.org.ar/wp-content/uploads/2026/08/Planilla-de-escalas-salariales-julio-2026-OK.pdf
A10: FADEEAC — planilla salarial firmada de agosto 2026 (CCT 40/89) | B10: https://www.fadeeac.org.ar/wp-content/uploads/2026/08/Planillas-de-escalas-salariales-agosto-2026-OK.pdf
A11: FADEEAC — planilla salarial firmada de septiembre 2026 (CCT 40/89) | B11: https://www.fadeeac.org.ar/wp-content/uploads/2026/10/3-Planillas-salariales-acuerdo-SEPT-2026-a-FEB-2027.pdf
A12: FADEEAC — planilla salarial firmada de octubre 2026 (CCT 40/89) | B12: https://www.fadeeac.org.ar/wp-content/uploads/2026/10/3-Planillas-salariales-acuerdo-SEPT-2026-a-FEB-2027.pdf
A13: FADEEAC — planilla salarial firmada de noviembre 2026 (CCT 40/89) | B13: https://www.fadeeac.org.ar/wp-content/uploads/2026/10/3-Planillas-salariales-acuerdo-SEPT-2026-a-FEB-2027.pdf
A14: FADEEAC — planilla salarial firmada de diciembre 2026 (CCT 40/89) | B14: https://www.fadeeac.org.ar/wp-content/uploads/2026/10/3-Planillas-salariales-acuerdo-SEPT-2026-a-FEB-2027.pdf
A15: FADEEAC — planilla salarial firmada de enero 2027 (CCT 40/89) | B15: https://www.fadeeac.org.ar/wp-content/uploads/2026/10/3-Planillas-salariales-acuerdo-SEPT-2026-a-FEB-2027.pdf
... A25: Ley de Contrato de Trabajo 20.744, arts. 121-123 (texto actualizado) | B25: https://servicios.infoleg.gob.ar/infolegInternet/anexos/25000-29999/25552/texact.htm
A27: Homologaciones
A28: Disposición DNRyRT 455/2026
A29: Disposición DNRyRT 1277/2026
A31: Planilla de calcular.ar. Las actualizaciones del año están incluidas en el precio: cuando FADEEAC publica la planilla firmada de un mes nuevo, la cargamos y el mismo enlace de descarga te baja la versión al día.
