Workbook

Sheet Instrucciones
A1: Vacaciones 2026 de tu equipo — cómo usar esta planilla
A3: 1 | B3: En «Equipo» cargá a cada persona: nombre, fecha de ingreso y sueldo bruto mensual (hasta 40). Te dice cuántos días le corresponden y cuánto le tenés que pagar. Las celdas amarillas son las tuyas; las verdes se calculan solas.
A4: 2 | B4: Elegí la fecha de inicio de cada uno. La columna «Estado» te avisa si no cae en lunes, si se pasa del 30 de abril, si el tramo es muy corto o si se te está por vencer el aviso. Probá fechas hasta que todas digan «En regla».
A5: 3 | B5: En «Notificación» elegí el número de empleado: la nota sale lista, con días, fechas y regreso, por duplicado. Imprimila, firmala y que la persona firme la copia que te quedás. Después marcá «Sí» en la columna «¿Notificado?».
A6: 4 | B6: «Liquidación» muestra el detalle del pago de una persona; «Temporada» te dice cuánto vas a pagar en vacaciones mes por mes, para que no te agarre la caja en enero.
A7: 5 | B7: Si alguien se va, en «Egresos» ponés su número y la fecha de egreso: te calcula las vacaciones no gozadas para la liquidación final.
A9: LO QUE DICE LA LEY (Ley de Contrato de Trabajo, con la reforma de la Ley 27.802)
B10: • Días según la antigüedad al 31 de diciembre de 2026: hasta 5 años, 14 días corridos; más de 5 y hasta 10 años, 21 días corridos; más de 10 y hasta 20 años, 28 días corridos; más de 20 años, 35 días corridos (art. 150). Son corridos: cuentan sábados, domingos y feriados.
B11: • Quien no trabajó al menos la mitad de los días hábiles del año tiene 1 día de descanso cada 20 días trabajados (arts. 151 y 153). La planilla lo detecta sola por la fecha de ingreso.
B12: • Se otorgan entre el 1 de octubre y el 30 de abril. Fuera de ese período, sólo de común acuerdo (art. 154). La fecha de inicio se avisa por escrito con al menos 30 días de anticipación; si tu convenio fija otra anticipación, cambiala en la celda de arriba de «Equipo».
B13: • Empiezan un lunes, o el día hábil siguiente si ese lunes es feriado (art. 151). Para quien trabaja en días inhábiles la regla es otra: empiezan el día siguiente a su franco.
B14: • Se pueden partir en tramos, si los dos están de acuerdo, siempre que ningún tramo tenga menos de 7 días (art. 154). Cargá los días del tramo en la columna «Días de este tramo» y el saldo te queda a la vista.
B15: • Si no las tomás todos juntos, organizalas para que cada persona tenga vacaciones en verano al menos una vez cada tres años (art. 154).
B16: • Cada día se paga el sueldo mensual dividido 25, y se paga al empezar las vacaciones (art. 155). Es bruto: lleva los mismos descuentos que el sueldo. Con sueldo variable (comisiones, destajo), cargá el promedio del año o, si la persona lo prefiere, el de los últimos seis meses. Si cobra por día o por hora, cada día de vacaciones vale lo que habría cobrado en la jornada anterior al inicio (art. 155 inc. b): para que la cuenta dé eso, cargá en «Sueldo» ese jornal multiplicado por 25.
B17: • Si no avisaste a tiempo, la persona puede tomárselas avisándote de forma fehaciente, para que terminen antes del 31 de mayo (art. 157). No se pueden pagar en plata en lugar de tomarlas, salvo al terminar la relación (arts. 156 y 162).
B18: • Si se enferma durante las vacaciones y te avisa a tiempo, vuelve en la fecha prevista y el saldo de días se reprograma (art. 154).
A20: Esta planilla da los mismos números que la calculadora gratuita de calcular.ar/vacaciones: misma ley, misma fórmula. Antes de publicar cada versión, una verificación automática recalcula el archivo y lo compara contra la calculadora. Es una referencia de cálculo con sus fuentes, no asesoramiento legal: tu convenio colectivo puede tener reglas propias.
A21: Las fechas se escriben como dd/mm/aaaa. Si tu Excel está configurado en inglés y lee las fechas al revés, escribilas como aaaa-mm-dd.

Sheet Equipo
A1: Vacaciones 2026 del equipo — días, fechas, aviso y pago
A2: LCT arts. 150 a 157 · art. 154 según Ley 27.802 · Verificado el 11 de junio de 2026
A3: Año | B3: 2026 | C3: Días de aviso previo | E3: 30 | F3: Fecha de hoy | H3: =TODAY()
A5: Nº | B5: Nombre y apellido | C5: Fecha de ingreso | D5: Sueldo bruto mensual | E5: Días de este tramo (vacío = todos) | F5: Fecha de inicio | G5: ¿Notificado? | H5: Antigüedad al 31/12 | I5: Días que le tocan | J5: Régimen | K5: Días del tramo | L5: Saldo | M5: Último día | N5: Vuelve a trabajar | O5: Notificar hasta el | P5: Valor del día (÷ 25) | Q5: A pagar al inicio | R5: Plus vacacional | S5: Estado
A6: 1 | B6: Ana (ejemplo) | C6: 43535 | D6: 1450000 | F6: 46370 | G6: No | H6: =IF(U6=1,INT((($B$3-YEAR(C6))*12+12-MONTH(C6))/12)&IF(INT((($B$3-YEAR(C6))*12+12-MONTH(C6))/12)=1," año"," años")&" y "&MOD((($B$3-YEAR(C6))*12+12-MONTH(C6)),12)&IF(MOD((($B$3-YEAR(C6))*12+12-MONTH(C6)),12)=1," mes"," meses"),"") | I6: =IF(U6=1,IF(X6=1,INT(W6/20),V6),"") | J6: =IF(U6=1,IF(X6=1,"Proporcional (art. 153)","Escala (art. 150)"),"") | K6: =IF(U6=1,IF(E6="",I6,MIN(MAX(E6,0),I6)),"") | L6: =IF(U6=1,I6-K6,"") | M6: =IF(AND(U6=1,F6<>""),IF(K6>0,F6+K6-1,""),"") | N6: =IF(M6="","",M6+1) | O6: =IF(AND(U6=1,F6<>""),F6-$E$3,"") | P6: =IF(U6=1,D6/25,"") | Q6: =IF(U6=1,P6*K6,"") | R6: =IF(U6=1,(D6/25-D6/30)*K6,"") | S6: =IF(OR(C6="",D6=""),"",IF(C6>DATE($B$3,12,31),"Ingresa después del 31/12: no entra en este período",IF(I6=0,"Todavía no generó días de vacaciones (art. 153)",IF(F6="","Falta la fecha de inicio",IF(F6<>WORKDAY(F6-WEEKDAY(F6,2),1,'Feriados'!$A$5:$A$35),"Tiene que empezar un lunes (o el hábil siguiente si es feriado)",IF(AND(K6<I6,OR(K6<7,L6<7)),"Cada tramo tiene que ser de 7 días o más",IF(OR(F6<DATE($B$3,10,1),M6>DATE($B$3+1,4,30)),"Fuera del 1/10 al 30/4: sólo con acuerdo por escrito",IF(G6="Sí","Notificado",IF($H$3>O6,"Aviso fuera de plazo: notificá hoy o acordá otra fecha",IF(O6-$H$3<=7,"Notificá ya: el plazo vence el "&DAY(O6)&"/"&MONTH(O6)&"/"&YEAR(O6),"En regla: notificar hasta el "&DAY(O6)&"/"&MONTH(O6)&"/"&YEAR(O6))))))))))) | T6: =IF(OR(S6="Notificado",LEFT(S6,8)="En regla"),1,0) | U6: =IF(OR(C6="",D6=""),0,IF(C6>DATE($B$3,12,31),0,1)) | V6: =IF(U6=1,IF(C6>=DATE($B$3-5,12,31),14,IF(C6>=DATE($B$3-10,12,31),21,IF(C6>=DATE($B$3-20,12,31),28,35))),"") | W6: =IF(U6=1,IF(C6>DATE($B$3,1,1),NETWORKDAYS(C6,DATE($B$3,12,31)),""),"") | X6: =IF(U6=1,IF(W6="",0,IF(W6<NETWORKDAYS(DATE($B$3,1,1),DATE($B$3,12,31))/2,1,0)),"")
A7: 2 | B7: Bruno (ejemplo) | C7: 41792 | D7: 1900000 | E7: 14 | F7: 46391 | G7: No | H7: =IF(U7=1,INT((($B$3-YEAR(C7))*12+12-MONTH(C7))/12)&IF(INT((($B$3-YEAR(C7))*12+12-MONTH(C7))/12)=1," año"," años")&" y "&MOD((($B$3-YEAR(C7))*12+12-MONTH(C7)),12)&IF(MOD((($B$3-YEAR(C7))*12+12-MONTH(C7)),12)=1," mes"," meses"),"") | I7: =IF(U7=1,IF(X7=1,INT(W7/20),V7),"") | J7: =IF(U7=1,IF(X7=1,"Proporcional (art. 153)","Escala (art. 150)"),"") | K7: =IF(U7=1,IF(E7="",I7,MIN(MAX(E7,0),I7)),"") | L7: =IF(U7=1,I7-K7,"") | M7: =IF(AND(U7=1,F7<>""),IF(K7>0,F7+K7-1,""),"") | N7: =IF(M7="","",M7+1) | O7: =IF(AND(U7=1,F7<>""),F7-$E$3,"") | P7: =IF(U7=1,D7/25,"") | Q7: =IF(U7=1,P7*K7,"") | R7: =IF(U7=1,(D7/25-D7/30)*K7,"") | S7: =IF(OR(C7="",D7=""),"",IF(C7>DATE($B$3,12,31),"Ingresa después del 31/12: no entra en este período",IF(I7=0,"Todavía no generó días de vacaciones (art. 153)",IF(F7="","Falta la fecha de inicio",IF(F7<>WORKDAY(F7-WEEKDAY(F7,2),1,'Feriados'!$A$5:$A$35),"Tiene que empezar un lunes (o el hábil siguiente si es feriado)",IF(AND(K7<I7,OR(K7<7,L7<7)),"Cada tramo tiene que ser de 7 días o más",IF(OR(F7<DATE($B$3,10,1),M7>DATE($B$3+1,4,30)),"Fuera del 1/10 al 30/4: sólo con acuerdo por escrito",IF(G7="Sí","Notificado",IF($H$3>O7,"Aviso fuera de plazo: notificá hoy o acordá otra fecha",IF(O7-$H$3<=7,"Notificá ya: el plazo vence el "&DAY(O7)&"/"&MONTH(O7)&"/"&YEAR(O7),"En regla: notificar hasta el "&DAY(O7)&"/"&MONTH(O7)&"/"&YEAR(O7))))))))))) | T7: =IF(OR(S7="Notificado",LEFT(S7,8)="En regla"),1,0) | U7: =IF(OR(C7="",D7=""),0,IF(C7>DATE($B$3,12,31),0,1)) | V7: =IF(U7=1,IF(C7>=DATE($B$3-5,12,31),14,IF(C7>=DATE($B$3-10,12,31),21,IF(C7>=DATE($B$3-20,12,31),28,35))),"") | W7: =IF(U7=1,IF(C7>DATE($B$3,1,1),NETWORKDAYS(C7,DATE($B$3,12,31)),""),"") | X7: =IF(U7=1,IF(W7="",0,IF(W7<NETWORKDAYS(DATE($B$3,1,1),DATE($B$3,12,31))/2,1,0)),"")
A8: 3 | B8: Carla (ejemplo) | C8: 46237 | D8: 1200000 | F8: 46428 | G8: No | H8: =IF(U8=1,INT((($B$3-YEAR(C8))*12+12-MONTH(C8))/12)&IF(INT((($B$3-YEAR(C8))*12+12-MONTH(C8))/12)=1," año"," años")&" y "&MOD((($B$3-YEAR(C8))*12+12-MONTH(C8)),12)&IF(MOD((($B$3-YEAR(C8))*12+12-MONTH(C8)),12)=1," mes"," meses"),"") | I8: =IF(U8=1,IF(X8=1,INT(W8/20),V8),"") | J8: =IF(U8=1,IF(X8=1,"Proporcional (art. 153)","Escala (art. 150)"),"") | K8: =IF(U8=1,IF(E8="",I8,MIN(MAX(E8,0),I8)),"") | L8: =IF(U8=1,I8-K8,"") | M8: =IF(AND(U8=1,F8<>""),IF(K8>0,F8+K8-1,""),"") | N8: =IF(M8="","",M8+1) | O8: =IF(AND(U8=1,F8<>""),F8-$E$3,"") | P8: =IF(U8=1,D8/25,"") | Q8: =IF(U8=1,P8*K8,"") | R8: =IF(U8=1,(D8/25-D8/30)*K8,"") | S8: =IF(OR(C8="",D8=""),"",IF(C8>DATE($B$3,12,31),"Ingresa después del 31/12: no entra en este período",IF(I8=0,"Todavía no generó días de vacaciones (art. 153)",IF(F8="","Falta la fecha de inicio",IF(F8<>WORKDAY(F8-WEEKDAY(F8,2),1,'Feriados'!$A$5:$A$35),"Tiene que empezar un lunes (o el hábil siguiente si es feriado)",IF(AND(K8<I8,OR(K8<7,L8<7)),"Cada tramo tiene que ser de 7 días o más",IF(OR(F8<DATE($B$3,10,1),M8>DATE($B$3+1,4,30)),"Fuera del 1/10 al 30/4: sólo con acuerdo por escrito",IF(G8="Sí","Notificado",IF($H$3>O8,"Aviso fuera de plazo: notificá hoy o acordá otra fecha",IF(O8-$H$3<=7,"Notificá ya: el plazo vence el "&DAY(O8)&"/"&MONTH(O8)&"/"&YEAR(O8),"En regla: notificar hasta el "&DAY(O8)&"/"&MONTH(O8)&"/"&YEAR(O8))))))))))) | T8: =IF(OR(S8="Notificado",LEFT(S8,8)="En regla"),1,0) | U8: =IF(OR(C8="",D8=""),0,IF(C8>DATE($B$3,12,31),0,1)) | V8: =IF(U8=1,IF(C8>=DATE($B$3-5,12,31),14,IF(C8>=DATE($B$3-10,12,31),21,IF(C8>=DATE($B$3-20,12,31),28,35))),"") | W8: =IF(U8=1,IF(C8>DATE($B$3,1,1),NETWORKDAYS(C8,DATE($B$3,12,31)),""),"") | X8: =IF(U8=1,IF(W8="",0,IF(W8<NETWORKDAYS(DATE($B$3,1,1),DATE($B$3,12,31))/2,1,0)),"")
A9: 4 | G9: No | H9: =IF(U9=1,INT((($B$3-YEAR(C9))*12+12-MONTH(C9))/12)&IF(INT((($B$3-YEAR(C9))*12+12-MONTH(C9))/12)=1," año"," años")&" y "&MOD((($B$3-YEAR(C9))*12+12-MONTH(C9)),12)&IF(MOD((($B$3-YEAR(C9))*12+12-MONTH(C9)),12)=1," mes"," meses"),"") | I9: =IF(U9=1,IF(X9=1,INT(W9/20),V9),"") | J9: =IF(U9=1,IF(X9=1,"Proporcional (art. 153)","Escala (art. 150)"),"") | K9: =IF(U9=1,IF(E9="",I9,MIN(MAX(E9,0),I9)),"") | L9: =IF(U9=1,I9-K9,"") | M9: =IF(AND(U9=1,F9<>""),IF(K9>0,F9+K9-1,""),"") | N9: =IF(M9="","",M9+1) | O9: =IF(AND(U9=1,F9<>""),F9-$E$3,"") | P9: =IF(U9=1,D9/25,"") | Q9: =IF(U9=1,P9*K9,"") | R9: =IF(U9=1,(D9/25-D9/30)*K9,"") | S9: =IF(OR(C9="",D9=""),"",IF(C9>DATE($B$3,12,31),"Ingresa después del 31/12: no entra en este período",IF(I9=0,"Todavía no generó días de vacaciones (art. 153)",IF(F9="","Falta la fecha de inicio",IF(F9<>WORKDAY(F9-WEEKDAY(F9,2),1,'Feriados'!$A$5:$A$35),"Tiene que empezar un lunes (o el hábil siguiente si es feriado)",IF(AND(K9<I9,OR(K9<7,L9<7)),"Cada tramo tiene que ser de 7 días o más",IF(OR(F9<DATE($B$3,10,1),M9>DATE($B$3+1,4,30)),"Fuera del 1/10 al 30/4: sólo con acuerdo por escrito",IF(G9="Sí","Notificado",IF($H$3>O9,"Aviso fuera de plazo: notificá hoy o acordá otra fecha",IF(O9-$H$3<=7,"Notificá ya: el plazo vence el "&DAY(O9)&"/"&MONTH(O9)&"/"&YEAR(O9),"En regla: notificar hasta el "&DAY(O9)&"/"&MONTH(O9)&"/"&YEAR(O9))))))))))) | T9: =IF(OR(S9="Notificado",LEFT(S9,8)="En regla"),1,0) | U9: =IF(OR(C9="",D9=""),0,IF(C9>DATE($B$3,12,31),0,1)) | V9: =IF(U9=1,IF(C9>=DATE($B$3-5,12,31),14,IF(C9>=DATE($B$3-10,12,31),21,IF(C9>=DATE($B$3-20,12,31),28,35))),"") | W9: =IF(U9=1,IF(C9>DATE($B$3,1,1),NETWORKDAYS(C9,DATE($B$3,12,31)),""),"") | X9: =IF(U9=1,IF(W9="",0,IF(W9<NETWORKDAYS(DATE($B$3,1,1),DATE($B$3,12,31))/2,1,0)),"")
A10: 5 | G10: No | H10: =IF(U10=1,INT((($B$3-YEAR(C10))*12+12-MONTH(C10))/12)&IF(INT((($B$3-YEAR(C10))*12+12-MONTH(C10))/12)=1," año"," años")&" y "&MOD((($B$3-YEAR(C10))*12+12-MONTH(C10)),12)&IF(MOD((($B$3-YEAR(C10))*12+12-MONTH(C10)),12)=1," mes"," meses"),"") | I10: =IF(U10=1,IF(X10=1,INT(W10/20),V10),"") | J10: =IF(U10=1,IF(X10=1,"Proporcional (art. 153)","Escala (art. 150)"),"") | K10: =IF(U10=1,IF(E10="",I10,MIN(MAX(E10,0),I10)),"") | L10: =IF(U10=1,I10-K10,"") | M10: =IF(AND(U10=1,F10<>""),IF(K10>0,F10+K10-1,""),"") | N10: =IF(M10="","",M10+1) | O10: =IF(AND(U10=1,F10<>""),F10-$E$3,"") | P10: =IF(U10=1,D10/25,"") | Q10: =IF(U10=1,P10*K10,"") | R10: =IF(U10=1,(D10/25-D10/30)*K10,"") | S10: =IF(OR(C10="",D10=""),"",IF(C10>DATE($B$3,12,31),"Ingresa después del 31/12: no entra en este período",IF(I10=0,"Todavía no generó días de vacaciones (art. 153)",IF(F10="","Falta la fecha de inicio",IF(F10<>WORKDAY(F10-WEEKDAY(F10,2),1,'Feriados'!$A$5:$A$35),"Tiene que empezar un lunes (o el hábil siguiente si es feriado)",IF(AND(K10<I10,OR(K10<7,L10<7)),"Cada tramo tiene que ser de 7 días o más",IF(OR(F10<DATE($B$3,10,1),M10>DATE($B$3+1,4,30)),"Fuera del 1/10 al 30/4: sólo con acuerdo por escrito",IF(G10="Sí","Notificado",IF($H$3>O10,"Aviso fuera de plazo: notificá hoy o acordá otra fecha",IF(O10-$H$3<=7,"Notificá ya: el plazo vence el "&DAY(O10)&"/"&MONTH(O10)&"/"&YEAR(O10),"En regla: notificar hasta el "&DAY(O10)&"/"&MONTH(O10)&"/"&YEAR(O10))))))))))) | T10: =IF(OR(S10="Notificado",LEFT(S10,8)="En regla"),1,0) | U10: =IF(OR(C10="",D10=""),0,IF(C10>DATE($B$3,12,31),0,1)) | V10: =IF(U10=1,IF(C10>=DATE($B$3-5,12,31),14,IF(C10>=DATE($B$3-10,12,31),21,IF(C10>=DATE($B$3-20,12,31),28,35))),"") | W10: =IF(U10=1,IF(C10>DATE($B$3,1,1),NETWORKDAYS(C10,DATE($B$3,12,31)),""),"") | X10: =IF(U10=1,IF(W10="",0,IF(W10<NETWORKDAYS(DATE($B$3,1,1),DATE($B$3,12,31))/2,1,0)),"")
A11: 6 | G11: No | H11: =IF(U11=1,INT((($B$3-YEAR(C11))*12+12-MONTH(C11))/12)&IF(INT((($B$3-YEAR(C11))*12+12-MONTH(C11))/12)=1," año"," años")&" y "&MOD((($B$3-YEAR(C11))*12+12-MONTH(C11)),12)&IF(MOD((($B$3-YEAR(C11))*12+12-MONTH(C11)),12)=1," mes"," meses"),"") | I11: =IF(U11=1,IF(X11=1,INT(W11/20),V11),"") | J11: =IF(U11=1,IF(X11=1,"Proporcional (art. 153)","Escala (art. 150)"),"") | K11: =IF(U11=1,IF(E11="",I11,MIN(MAX(E11,0),I11)),"") | L11: =IF(U11=1,I11-K11,"") | M11: =IF(AND(U11=1,F11<>""),IF(K11>0,F11+K11-1,""),"") | N11: =IF(M11="","",M11+1) | O11: =IF(AND(U11=1,F11<>""),F11-$E$3,"") | P11: =IF(U11=1,D11/25,"") | Q11: =IF(U11=1,P11*K11,"") | R11: =IF(U11=1,(D11/25-D11/30)*K11,"") | S11: =IF(OR(C11="",D11=""),"",IF(C11>DATE($B$3,12,31),"Ingresa después del 31/12: no entra en este período",IF(I11=0,"Todavía no generó días de vacaciones (art. 153)",IF(F11="","Falta la fecha de inicio",IF(F11<>WORKDAY(F11-WEEKDAY(F11,2),1,'Feriados'!$A$5:$A$35),"Tiene que empezar un lunes (o el hábil siguiente si es feriado)",IF(AND(K11<I11,OR(K11<7,L11<7)),"Cada tramo tiene que ser de 7 días o más",IF(OR(F11<DATE($B$3,10,1),M11>DATE($B$3+1,4,30)),"Fuera del 1/10 al 30/4: sólo con acuerdo por escrito",IF(G11="Sí","Notificado",IF($H$3>O11,"Aviso fuera de plazo: notificá hoy o acordá otra fecha",IF(O11-$H$3<=7,"Notificá ya: el plazo vence el "&DAY(O11)&"/"&MONTH(O11)&"/"&YEAR(O11),"En regla: notificar hasta el "&DAY(O11)&"/"&MONTH(O11)&"/"&YEAR(O11))))))))))) | T11: =IF(OR(S11="Notificado",LEFT(S11,8)="En regla"),1,0) | U11: =IF(OR(C11="",D11=""),0,IF(C11>DATE($B$3,12,31),0,1)) | V11: =IF(U11=1,IF(C11>=DATE($B$3-5,12,31),14,IF(C11>=DATE($B$3-10,12,31),21,IF(C11>=DATE($B$3-20,12,31),28,35))),"") | W11: =IF(U11=1,IF(C11>DATE($B$3,1,1),NETWORKDAYS(C11,DATE($B$3,12,31)),""),"") | X11: =IF(U11=1,IF(W11="",0,IF(W11<NETWORKDAYS(DATE($B$3,1,1),DATE($B$3,12,31))/2,1,0)),"")
A12: 7 | G12: No | H12: =IF(U12=1,INT((($B$3-YEAR(C12))*12+12-MONTH(C12))/12)&IF(INT((($B$3-YEAR(C12))*12+12-MONTH(C12))/12)=1," año"," años")&" y "&MOD((($B$3-YEAR(C12))*12+12-MONTH(C12)),12)&IF(MOD((($B$3-YEAR(C12))*12+12-MONTH(C12)),12)=1," mes"," meses"),"") | I12: =IF(U12=1,IF(X12=1,INT(W12/20),V12),"") | J12: =IF(U12=1,IF(X12=1,"Proporcional (art. 153)","Escala (art. 150)"),"") | K12: =IF(U12=1,IF(E12="",I12,MIN(MAX(E12,0),I12)),"") | L12: =IF(U12=1,I12-K12,"") | M12: =IF(AND(U12=1,F12<>""),IF(K12>0,F12+K12-1,""),"") | N12: =IF(M12="","",M12+1) | O12: =IF(AND(U12=1,F12<>""),F12-$E$3,"") | P12: =IF(U12=1,D12/25,"") | Q12: =IF(U12=1,P12*K12,"") | R12: =IF(U12=1,(D12/25-D12/30)*K12,"") | S12: =IF(OR(C12="",D12=""),"",IF(C12>DATE($B$3,12,31),"Ingresa después del 31/12: no entra en este período",IF(I12=0,"Todavía no generó días de vacaciones (art. 153)",IF(F12="","Falta la fecha de inicio",IF(F12<>WORKDAY(F12-WEEKDAY(F12,2),1,'Feriados'!$A$5:$A$35),"Tiene que empezar un lunes (o el hábil siguiente si es feriado)",IF(AND(K12<I12,OR(K12<7,L12<7)),"Cada tramo tiene que ser de 7 días o más",IF(OR(F12<DATE($B$3,10,1),M12>DATE($B$3+1,4,30)),"Fuera del 1/10 al 30/4: sólo con acuerdo por escrito",IF(G12="Sí","Notificado",IF($H$3>O12,"Aviso fuera de plazo: notificá hoy o acordá otra fecha",IF(O12-$H$3<=7,"Notificá ya: el plazo vence el "&DAY(O12)&"/"&MONTH(O12)&"/"&YEAR(O12),"En regla: notificar hasta el "&DAY(O12)&"/"&MONTH(O12)&"/"&YEAR(O12))))))))))) | T12: =IF(OR(S12="Notificado",LEFT(S12,8)="En regla"),1,0) | U12: =IF(OR(C12="",D12=""),0,IF(C12>DATE($B$3,12,31),0,1)) | V12: =IF(U12=1,IF(C12>=DATE($B$3-5,12,31),14,IF(C12>=DATE($B$3-10,12,31),21,IF(C12>=DATE($B$3-20,12,31),28,35))),"") | W12: =IF(U12=1,IF(C12>DATE($B$3,1,1),NETWORKDAYS(C12,DATE($B$3,12,31)),""),"") | X12: =IF(U12=1,IF(W12="",0,IF(W12<NETWORKDAYS(DATE($B$3,1,1),DATE($B$3,12,31))/2,1,0)),"")
A13: 8 | G13: No | H13: =IF(U13=1,INT((($B$3-YEAR(C13))*12+12-MONTH(C13))/12)&IF(INT((($B$3-YEAR(C13))*12+12-MONTH(C13))/12)=1," año"," años")&" y "&MOD((($B$3-YEAR(C13))*12+12-MONTH(C13)),12)&IF(MOD((($B$3-YEAR(C13))*12+12-MONTH(C13)),12)=1," mes"," meses"),"") | I13: =IF(U13=1,IF(X13=1,INT(W13/20),V13),"") | J13: =IF(U13=1,IF(X13=1,"Proporcional (art. 153)","Escala (art. 150)"),"") | K13: =IF(U13=1,IF(E13="",I13,MIN(MAX(E13,0),I13)),"") | L13: =IF(U13=1,I13-K13,"") | M13: =IF(AND(U13=1,F13<>""),IF(K13>0,F13+K13-1,""),"") | N13: =IF(M13="","",M13+1) | O13: =IF(AND(U13=1,F13<>""),F13-$E$3,"") | P13: =IF(U13=1,D13/25,"") | Q13: =IF(U13=1,P13*K13,"") | R13: =IF(U13=1,(D13/25-D13/30)*K13,"") | S13: =IF(OR(C13="",D13=""),"",IF(C13>DATE($B$3,12,31),"Ingresa después del 31/12: no entra en este período",IF(I13=0,"Todavía no generó días de vacaciones (art. 153)",IF(F13="","Falta la fecha de inicio",IF(F13<>WORKDAY(F13-WEEKDAY(F13,2),1,'Feriados'!$A$5:$A$35),"Tiene que empezar un lunes (o el hábil siguiente si es feriado)",IF(AND(K13<I13,OR(K13<7,L13<7)),"Cada tramo tiene que ser de 7 días o más",IF(OR(F13<DATE($B$3,10,1),M13>DATE($B$3+1,4,30)),"Fuera del 1/10 al 30/4: sólo con acuerdo por escrito",IF(G13="Sí","Notificado",IF($H$3>O13,"Aviso fuera de plazo: notificá hoy o acordá otra fecha",IF(O13-$H$3<=7,"Notificá ya: el plazo vence el "&DAY(O13)&"/"&MONTH(O13)&"/"&YEAR(O13),"En regla: notificar hasta el "&DAY(O13)&"/"&MONTH(O13)&"/"&YEAR(O13))))))))))) | T13: =IF(OR(S13="Notificado",LEFT(S13,8)="En regla"),1,0) | U13: =IF(OR(C13="",D13=""),0,IF(C13>DATE($B$3,12,31),0,1)) | V13: =IF(U13=1,IF(C13>=DATE($B$3-5,12,31),14,IF(C13>=DATE($B$3-10,12,31),21,IF(C13>=DATE($B$3-20,12,31),28,35))),"") | W13: =IF(U13=1,IF(C13>DATE($B$3,1,1),NETWORKDAYS(C13,DATE($B$3,12,31)),""),"") | X13: =IF(U13=1,IF(W13="",0,IF(W13<NETWORKDAYS(DATE($B$3,1,1),DATE($B$3,12,31))/2,1,0)),"")
A14: 9 | G14: No | H14: =IF(U14=1,INT((($B$3-YEAR(C14))*12+12-MONTH(C14))/12)&IF(INT((($B$3-YEAR(C14))*12+12-MONTH(C14))/12)=1," año"," años")&" y "&MOD((($B$3-YEAR(C14))*12+12-MONTH(C14)),12)&IF(MOD((($B$3-YEAR(C14))*12+12-MONTH(C14)),12)=1," mes"," meses"),"") | I14: =IF(U14=1,IF(X14=1,INT(W14/20),V14),"") | J14: =IF(U14=1,IF(X14=1,"Proporcional (art. 153)","Escala (art. 150)"),"") | K14: =IF(U14=1,IF(E14="",I14,MIN(MAX(E14,0),I14)),"") | L14: =IF(U14=1,I14-K14,"") | M14: =IF(AND(U14=1,F14<>""),IF(K14>0,F14+K14-1,""),"") | N14: =IF(M14="","",M14+1) | O14: =IF(AND(U14=1,F14<>""),F14-$E$3,"") | P14: =IF(U14=1,D14/25,"") | Q14: =IF(U14=1,P14*K14,"") | R14: =IF(U14=1,(D14/25-D14/30)*K14,"") | S14: =IF(OR(C14="",D14=""),"",IF(C14>DATE($B$3,12,31),"Ingresa después del 31/12: no entra en este período",IF(I14=0,"Todavía no generó días de vacaciones (art. 153)",IF(F14="","Falta la fecha de inicio",IF(F14<>WORKDAY(F14-WEEKDAY(F14,2),1,'Feriados'!$A$5:$A$35),"Tiene que empezar un lunes (o el hábil siguiente si es feriado)",IF(AND(K14<I14,OR(K14<7,L14<7)),"Cada tramo tiene que ser de 7 días o más",IF(OR(F14<DATE($B$3,10,1),M14>DATE($B$3+1,4,30)),"Fuera del 1/10 al 30/4: sólo con acuerdo por escrito",IF(G14="Sí","Notificado",IF($H$3>O14,"Aviso fuera de plazo: notificá hoy o acordá otra fecha",IF(O14-$H$3<=7,"Notificá ya: el plazo vence el "&DAY(O14)&"/"&MONTH(O14)&"/"&YEAR(O14),"En regla: notificar hasta el "&DAY(O14)&"/"&MONTH(O14)&"/"&YEAR(O14))))))))))) | T14: =IF(OR(S14="Notificado",LEFT(S14,8)="En regla"),1,0) | U14: =IF(OR(C14="",D14=""),0,IF(C14>DATE($B$3,12,31),0,1)) | V14: =IF(U14=1,IF(C14>=DATE($B$3-5,12,31),14,IF(C14>=DATE($B$3-10,12,31),21,IF(C14>=DATE($B$3-20,12,31),28,35))),"") | W14: =IF(U14=1,IF(C14>DATE($B$3,1,1),NETWORKDAYS(C14,DATE($B$3,12,31)),""),"") | X14: =IF(U14=1,IF(W14="",0,IF(W14<NETWORKDAYS(DATE($B$3,1,1),DATE($B$3,12,31))/2,1,0)),"")
A15: 10 | G15: No | H15: =IF(U15=1,INT((($B$3-YEAR(C15))*12+12-MONTH(C15))/12)&IF(INT((($B$3-YEAR(C15))*12+12-MONTH(C15))/12)=1," año"," años")&" y "&MOD((($B$3-YEAR(C15))*12+12-MONTH(C15)),12)&IF(MOD((($B$3-YEAR(C15))*12+12-MONTH(C15)),12)=1," mes"," meses"),"") | I15: =IF(U15=1,IF(X15=1,INT(W15/20),V15),"") | J15: =IF(U15=1,IF(X15=1,"Proporcional (art. 153)","Escala (art. 150)"),"") | K15: =IF(U15=1,IF(E15="",I15,MIN(MAX(E15,0),I15)),"") | L15: =IF(U15=1,I15-K15,"") | M15: =IF(AND(U15=1,F15<>""),IF(K15>0,F15+K15-1,""),"") | N15: =IF(M15="","",M15+1) | O15: =IF(AND(U15=1,F15<>""),F15-$E$3,"") | P15: =IF(U15=1,D15/25,"") | Q15: =IF(U15=1,P15*K15,"") | R15: =IF(U15=1,(D15/25-D15/30)*K15,"") | S15: =IF(OR(C15="",D15=""),"",IF(C15>DATE($B$3,12,31),"Ingresa después del 31/12: no entra en este período",IF(I15=0,"Todavía no generó días de vacaciones (art. 153)",IF(F15="","Falta la fecha de inicio",IF(F15<>WORKDAY(F15-WEEKDAY(F15,2),1,'Feriados'!$A$5:$A$35),"Tiene que empezar un lunes (o el hábil siguiente si es feriado)",IF(AND(K15<I15,OR(K15<7,L15<7)),"Cada tramo tiene que ser de 7 días o más",IF(OR(F15<DATE($B$3,10,1),M15>DATE($B$3+1,4,30)),"Fuera del 1/10 al 30/4: sólo con acuerdo por escrito",IF(G15="Sí","Notificado",IF($H$3>O15,"Aviso fuera de plazo: notificá hoy o acordá otra fecha",IF(O15-$H$3<=7,"Notificá ya: el plazo vence el "&DAY(O15)&"/"&MONTH(O15)&"/"&YEAR(O15),"En regla: notificar hasta el "&DAY(O15)&"/"&MONTH(O15)&"/"&YEAR(O15))))))))))) | T15: =IF(OR(S15="Notificado",LEFT(S15,8)="En regla"),1,0) | U15: =IF(OR(C15="",D15=""),0,IF(C15>DATE($B$3,12,31),0,1)) | V15: =IF(U15=1,IF(C15>=DATE($B$3-5,12,31),14,IF(C15>=DATE($B$3-10,12,31),21,IF(C15>=DATE($B$3-20,12,31),28,35))),"") | W15: =IF(U15=1,IF(C15>DATE($B$3,1,1),NETWORKDAYS(C15,DATE($B$3,12,31)),""),"") | X15: =IF(U15=1,IF(W15="",0,IF(W15<NETWORKDAYS(DATE($B$3,1,1),DATE($B$3,12,31))/2,1,0)),"")
A16: 11 | G16: No | H16: =IF(U16=1,INT((($B$3-YEAR(C16))*12+12-MONTH(C16))/12)&IF(INT((($B$3-YEAR(C16))*12+12-MONTH(C16))/12)=1," año"," años")&" y "&MOD((($B$3-YEAR(C16))*12+12-MONTH(C16)),12)&IF(MOD((($B$3-YEAR(C16))*12+12-MONTH(C16)),12)=1," mes"," meses"),"") | I16: =IF(U16=1,IF(X16=1,INT(W16/20),V16),"") | J16: =IF(U16=1,IF(X16=1,"Proporcional (art. 153)","Escala (art. 150)"),"") | K16: =IF(U16=1,IF(E16="",I16,MIN(MAX(E16,0),I16)),"") | L16: =IF(U16=1,I16-K16,"") | M16: =IF(AND(U16=1,F16<>""),IF(K16>0,F16+K16-1,""),"") | N16: =IF(M16="","",M16+1) | O16: =IF(AND(U16=1,F16<>""),F16-$E$3,"") | P16: =IF(U16=1,D16/25,"") | Q16: =IF(U16=1,P16*K16,"") | R16: =IF(U16=1,(D16/25-D16/30)*K16,"") | S16: =IF(OR(C16="",D16=""),"",IF(C16>DATE($B$3,12,31),"Ingresa después del 31/12: no entra en este período",IF(I16=0,"Todavía no generó días de vacaciones (art. 153)",IF(F16="","Falta la fecha de inicio",IF(F16<>WORKDAY(F16-WEEKDAY(F16,2),1,'Feriados'!$A$5:$A$35),"Tiene que empezar un lunes (o el hábil siguiente si es feriado)",IF(AND(K16<I16,OR(K16<7,L16<7)),"Cada tramo tiene que ser de 7 días o más",IF(OR(F16<DATE($B$3,10,1),M16>DATE($B$3+1,4,30)),"Fuera del 1/10 al 30/4: sólo con acuerdo por escrito",IF(G16="Sí","Notificado",IF($H$3>O16,"Aviso fuera de plazo: notificá hoy o acordá otra fecha",IF(O16-$H$3<=7,"Notificá ya: el plazo vence el "&DAY(O16)&"/"&MONTH(O16)&"/"&YEAR(O16),"En regla: notificar hasta el "&DAY(O16)&"/"&MONTH(O16)&"/"&YEAR(O16))))))))))) | T16: =IF(OR(S16="Notificado",LEFT(S16,8)="En regla"),1,0) | U16: =IF(OR(C16="",D16=""),0,IF(C16>DATE($B$3,12,31),0,1)) | V16: =IF(U16=1,IF(C16>=DATE($B$3-5,12,31),14,IF(C16>=DATE($B$3-10,12,31),21,IF(C16>=DATE($B$3-20,12,31),28,35))),"") | W16: =IF(U16=1,IF(C16>DATE($B$3,1,1),NETWORKDAYS(C16,DATE($B$3,12,31)),""),"") | X16: =IF(U16=1,IF(W16="",0,IF(W16<NETWORKDAYS(DATE($B$3,1,1),DATE($B$3,12,31))/2,1,0)),"")
A17: 12 | G17: No | H17: =IF(U17=1,INT((($B$3-YEAR(C17))*12+12-MONTH(C17))/12)&IF(INT((($B$3-YEAR(C17))*12+12-MONTH(C17))/12)=1," año"," años")&" y "&MOD((($B$3-YEAR(C17))*12+12-MONTH(C17)),12)&IF(MOD((($B$3-YEAR(C17))*12+12-MONTH(C17)),12)=1," mes"," meses"),"") | I17: =IF(U17=1,IF(X17=1,INT(W17/20),V17),"") | J17: =IF(U17=1,IF(X17=1,"Proporcional (art. 153)","Escala (art. 150)"),"") | K17: =IF(U17=1,IF(E17="",I17,MIN(MAX(E17,0),I17)),"") | L17: =IF(U17=1,I17-K17,"") | M17: =IF(AND(U17=1,F17<>""),IF(K17>0,F17+K17-1,""),"") | N17: =IF(M17="","",M17+1) | O17: =IF(AND(U17=1,F17<>""),F17-$E$3,"") | P17: =IF(U17=1,D17/25,"") | Q17: =IF(U17=1,P17*K17,"") | R17: =IF(U17=1,(D17/25-D17/30)*K17,"") | S17: =IF(OR(C17="",D17=""),"",IF(C17>DATE($B$3,12,31),"Ingresa después del 31/12: no entra en este período",IF(I17=0,"Todavía no generó días de vacaciones (art. 153)",IF(F17="","Falta la fecha de inicio",IF(F17<>WORKDAY(F17-WEEKDAY(F17,2),1,'Feriados'!$A$5:$A$35),"Tiene que empezar un lunes (o el hábil siguiente si es feriado)",IF(AND(K17<I17,OR(K17<7,L17<7)),"Cada tramo tiene que ser de 7 días o más",IF(OR(F17<DATE($B$3,10,1),M17>DATE($B$3+1,4,30)),"Fuera del 1/10 al 30/4: sólo con acuerdo por escrito",IF(G17="Sí","Notificado",IF($H$3>O17,"Aviso fuera de plazo: notificá hoy o acordá otra fecha",IF(O17-$H$3<=7,"Notificá ya: el plazo vence el "&DAY(O17)&"/"&MONTH(O17)&"/"&YEAR(O17),"En regla: notificar hasta el "&DAY(O17)&"/"&MONTH(O17)&"/"&YEAR(O17))))))))))) | T17: =IF(OR(S17="Notificado",LEFT(S17,8)="En regla"),1,0) | U17: =IF(OR(C17="",D17=""),0,IF(C17>DATE($B$3,12,31),0,1)) | V17: =IF(U17=1,IF(C17>=DATE($B$3-5,12,31),14,IF(C17>=DATE($B$3-10,12,31),21,IF(C17>=DATE($B$3-20,12,31),28,35))),"") | W17: =IF(U17=1,IF(C17>DATE($B$3,1,1),NETWORKDAYS(C17,DATE($B$3,12,31)),""),"") | X17: =IF(U17=1,IF(W17="",0,IF(W17<NETWORKDAYS(DATE($B$3,1,1),DATE($B$3,12,31))/2,1,0)),"")
A18: 13 | G18: No | H18: =IF(U18=1,INT((($B$3-YEAR(C18))*12+12-MONTH(C18))/12)&IF(INT((($B$3-YEAR(C18))*12+12-MONTH(C18))/12)=1," año"," años")&" y "&MOD((($B$3-YEAR(C18))*12+12-MONTH(C18)),12)&IF(MOD((($B$3-YEAR(C18))*12+12-MONTH(C18)),12)=1," mes"," meses"),"") | I18: =IF(U18=1,IF(X18=1,INT(W18/20),V18),"") | J18: =IF(U18=1,IF(X18=1,"Proporcional (art. 153)","Escala (art. 150)"),"") | K18: =IF(U18=1,IF(E18="",I18,MIN(MAX(E18,0),I18)),"") | L18: =IF(U18=1,I18-K18,"") | M18: =IF(AND(U18=1,F18<>""),IF(K18>0,F18+K18-1,""),"") | N18: =IF(M18="","",M18+1) | O18: =IF(AND(U18=1,F18<>""),F18-$E$3,"") | P18: =IF(U18=1,D18/25,"") | Q18: =IF(U18=1,P18*K18,"") | R18: =IF(U18=1,(D18/25-D18/30)*K18,"") | S18: =IF(OR(C18="",D18=""),"",IF(C18>DATE($B$3,12,31),"Ingresa después del 31/12: no entra en este período",IF(I18=0,"Todavía no generó días de vacaciones (art. 153)",IF(F18="","Falta la fecha de inicio",IF(F18<>WORKDAY(F18-WEEKDAY(F18,2),1,'Feriados'!$A$5:$A$35),"Tiene que empezar un lunes (o el hábil siguiente si es feriado)",IF(AND(K18<I18,OR(K18<7,L18<7)),"Cada tramo tiene que ser de 7 días o más",IF(OR(F18<DATE($B$3,10,1),M18>DATE($B$3+1,4,30)),"Fuera del 1/10 al 30/4: sólo con acuerdo por escrito",IF(G18="Sí","Notificado",IF($H$3>O18,"Aviso fuera de plazo: notificá hoy o acordá otra fecha",IF(O18-$H$3<=7,"Notificá ya: el plazo vence el "&DAY(O18)&"/"&MONTH(O18)&"/"&YEAR(O18),"En regla: notificar hasta el "&DAY(O18)&"/"&MONTH(O18)&"/"&YEAR(O18))))))))))) | T18: =IF(OR(S18="Notificado",LEFT(S18,8)="En regla"),1,0) | U18: =IF(OR(C18="",D18=""),0,IF(C18>DATE($B$3,12,31),0,1)) | V18: =IF(U18=1,IF(C18>=DATE($B$3-5,12,31),14,IF(C18>=DATE($B$3-10,12,31),21,IF(C18>=DATE($B$3-20,12,31),28,35))),"") | W18: =IF(U18=1,IF(C18>DATE($B$3,1,1),NETWORKDAYS(C18,DATE($B$3,12,31)),""),"") | X18: =IF(U18=1,IF(W18="",0,IF(W18<NETWORKDAYS(DATE($B$3,1,1),DATE($B$3,12,31))/2,1,0)),"")
A19: 14 | G19: No | H19: =IF(U19=1,INT((($B$3-YEAR(C19))*12+12-MONTH(C19))/12)&IF(INT((($B$3-YEAR(C19))*12+12-MONTH(C19))/12)=1," año"," años")&" y "&MOD((($B$3-YEAR(C19))*12+12-MONTH(C19)),12)&IF(MOD((($B$3-YEAR(C19))*12+12-MONTH(C19)),12)=1," mes"," meses"),"") | I19: =IF(U19=1,IF(X19=1,INT(W19/20),V19),"") | J19: =IF(U19=1,IF(X19=1,"Proporcional (art. 153)","Escala (art. 150)"),"") | K19: =IF(U19=1,IF(E19="",I19,MIN(MAX(E19,0),I19)),"") | L19: =IF(U19=1,I19-K19,"") | M19: =IF(AND(U19=1,F19<>""),IF(K19>0,F19+K19-1,""),"") | N19: =IF(M19="","",M19+1) | O19: =IF(AND(U19=1,F19<>""),F19-$E$3,"") | P19: =IF(U19=1,D19/25,"") | Q19: =IF(U19=1,P19*K19,"") | R19: =IF(U19=1,(D19/25-D19/30)*K19,"") | S19: =IF(OR(C19="",D19=""),"",IF(C19>DATE($B$3,12,31),"Ingresa después del 31/12: no entra en este período",IF(I19=0,"Todavía no generó días de vacaciones (art. 153)",IF(F19="","Falta la fecha de inicio",IF(F19<>WORKDAY(F19-WEEKDAY(F19,2),1,'Feriados'!$A$5:$A$35),"Tiene que empezar un lunes (o el hábil siguiente si es feriado)",IF(AND(K19<I19,OR(K19<7,L19<7)),"Cada tramo tiene que ser de 7 días o más",IF(OR(F19<DATE($B$3,10,1),M19>DATE($B$3+1,4,30)),"Fuera del 1/10 al 30/4: sólo con acuerdo por escrito",IF(G19="Sí","Notificado",IF($H$3>O19,"Aviso fuera de plazo: notificá hoy o acordá otra fecha",IF(O19-$H$3<=7,"Notificá ya: el plazo vence el "&DAY(O19)&"/"&MONTH(O19)&"/"&YEAR(O19),"En regla: notificar hasta el "&DAY(O19)&"/"&MONTH(O19)&"/"&YEAR(O19))))))))))) | T19: =IF(OR(S19="Notificado",LEFT(S19,8)="En regla"),1,0) | U19: =IF(OR(C19="",D19=""),0,IF(C19>DATE($B$3,12,31),0,1)) | V19: =IF(U19=1,IF(C19>=DATE($B$3-5,12,31),14,IF(C19>=DATE($B$3-10,12,31),21,IF(C19>=DATE($B$3-20,12,31),28,35))),"") | W19: =IF(U19=1,IF(C19>DATE($B$3,1,1),NETWORKDAYS(C19,DATE($B$3,12,31)),""),"") | X19: =IF(U19=1,IF(W19="",0,IF(W19<NETWORKDAYS(DATE($B$3,1,1),DATE($B$3,12,31))/2,1,0)),"")
A20: 15 | G20: No | H20: =IF(U20=1,INT((($B$3-YEAR(C20))*12+12-MONTH(C20))/12)&IF(INT((($B$3-YEAR(C20))*12+12-MONTH(C20))/12)=1," año"," años")&" y "&MOD((($B$3-YEAR(C20))*12+12-MONTH(C20)),12)&IF(MOD((($B$3-YEAR(C20))*12+12-MONTH(C20)),12)=1," mes"," meses"),"") | I20: =IF(U20=1,IF(X20=1,INT(W20/20),V20),"") | J20: =IF(U20=1,IF(X20=1,"Proporcional (art. 153)","Escala (art. 150)"),"") | K20: =IF(U20=1,IF(E20="",I20,MIN(MAX(E20,0),I20)),"") | L20: =IF(U20=1,I20-K20,"") | M20: =IF(AND(U20=1,F20<>""),IF(K20>0,F20+K20-1,""),"") | N20: =IF(M20="","",M20+1) | O20: =IF(AND(U20=1,F20<>""),F20-$E$3,"") | P20: =IF(U20=1,D20/25,"") | Q20: =IF(U20=1,P20*K20,"") | R20: =IF(U20=1,(D20/25-D20/30)*K20,"") | S20: =IF(OR(C20="",D20=""),"",IF(C20>DATE($B$3,12,31),"Ingresa después del 31/12: no entra en este período",IF(I20=0,"Todavía no generó días de vacaciones (art. 153)",IF(F20="","Falta la fecha de inicio",IF(F20<>WORKDAY(F20-WEEKDAY(F20,2),1,'Feriados'!$A$5:$A$35),"Tiene que empezar un lunes (o el hábil siguiente si es feriado)",IF(AND(K20<I20,OR(K20<7,L20<7)),"Cada tramo tiene que ser de 7 días o más",IF(OR(F20<DATE($B$3,10,1),M20>DATE($B$3+1,4,30)),"Fuera del 1/10 al 30/4: sólo con acuerdo por escrito",IF(G20="Sí","Notificado",IF($H$3>O20,"Aviso fuera de plazo: notificá hoy o acordá otra fecha",IF(O20-$H$3<=7,"Notificá ya: el plazo vence el "&DAY(O20)&"/"&MONTH(O20)&"/"&YEAR(O20),"En regla: notificar hasta el "&DAY(O20)&"/"&MONTH(O20)&"/"&YEAR(O20))))))))))) | T20: =IF(OR(S20="Notificado",LEFT(S20,8)="En regla"),1,0) | U20: =IF(OR(C20="",D20=""),0,IF(C20>DATE($B$3,12,31),0,1)) | V20: =IF(U20=1,IF(C20>=DATE($B$3-5,12,31),14,IF(C20>=DATE($B$3-10,12,31),21,IF(C20>=DATE($B$3-20,12,31),28,35))),"") | W20: =IF(U20=1,IF(C20>DATE($B$3,1,1),NETWORKDAYS(C20,DATE($B$3,12,31)),""),"") | X20: =IF(U20=1,IF(W20="",0,IF(W20<NETWORKDAYS(DATE($B$3,1,1),DATE($B$3,12,31))/2,1,0)),"")
... A45: 40 | G45: No | H45: =IF(U45=1,INT((($B$3-YEAR(C45))*12+12-MONTH(C45))/12)&IF(INT((($B$3-YEAR(C45))*12+12-MONTH(C45))/12)=1," año"," años")&" y "&MOD((($B$3-YEAR(C45))*12+12-MONTH(C45)),12)&IF(MOD((($B$3-YEAR(C45))*12+12-MONTH(C45)),12)=1," mes"," meses"),"") | I45: =IF(U45=1,IF(X45=1,INT(W45/20),V45),"") | J45: =IF(U45=1,IF(X45=1,"Proporcional (art. 153)","Escala (art. 150)"),"") | K45: =IF(U45=1,IF(E45="",I45,MIN(MAX(E45,0),I45)),"") | L45: =IF(U45=1,I45-K45,"") | M45: =IF(AND(U45=1,F45<>""),IF(K45>0,F45+K45-1,""),"") | N45: =IF(M45="","",M45+1) | O45: =IF(AND(U45=1,F45<>""),F45-$E$3,"") | P45: =IF(U45=1,D45/25,"") | Q45: =IF(U45=1,P45*K45,"") | R45: =IF(U45=1,(D45/25-D45/30)*K45,"") | S45: =IF(OR(C45="",D45=""),"",IF(C45>DATE($B$3,12,31),"Ingresa después del 31/12: no entra en este período",IF(I45=0,"Todavía no generó días de vacaciones (art. 153)",IF(F45="","Falta la fecha de inicio",IF(F45<>WORKDAY(F45-WEEKDAY(F45,2),1,'Feriados'!$A$5:$A$35),"Tiene que empezar un lunes (o el hábil siguiente si es feriado)",IF(AND(K45<I45,OR(K45<7,L45<7)),"Cada tramo tiene que ser de 7 días o más",IF(OR(F45<DATE($B$3,10,1),M45>DATE($B$3+1,4,30)),"Fuera del 1/10 al 30/4: sólo con acuerdo por escrito",IF(G45="Sí","Notificado",IF($H$3>O45,"Aviso fuera de plazo: notificá hoy o acordá otra fecha",IF(O45-$H$3<=7,"Notificá ya: el plazo vence el "&DAY(O45)&"/"&MONTH(O45)&"/"&YEAR(O45),"En regla: notificar hasta el "&DAY(O45)&"/"&MONTH(O45)&"/"&YEAR(O45))))))))))) | T45: =IF(OR(S45="Notificado",LEFT(S45,8)="En regla"),1,0) | U45: =IF(OR(C45="",D45=""),0,IF(C45>DATE($B$3,12,31),0,1)) | V45: =IF(U45=1,IF(C45>=DATE($B$3-5,12,31),14,IF(C45>=DATE($B$3-10,12,31),21,IF(C45>=DATE($B$3-20,12,31),28,35))),"") | W45: =IF(U45=1,IF(C45>DATE($B$3,1,1),NETWORKDAYS(C45,DATE($B$3,12,31)),""),"") | X45: =IF(U45=1,IF(W45="",0,IF(W45<NETWORKDAYS(DATE($B$3,1,1),DATE($B$3,12,31))/2,1,0)),"")
A46: TOTAL DE LA TEMPORADA | K46: =SUM(K6:K45) | Q46: =SUM(Q6:Q45) | R46: =SUM(R6:R45)
A48: * «Notificar hasta el»: último día para entregar el aviso por escrito con 30 días de anticipación (o los que pongas arriba si tu convenio fija otro plazo). «A pagar al inicio» es bruto: lleva los mismos descuentos que el sueldo.
A49: * Los feriados para la regla del lunes están en la hoja «Feriados». Los días no laborables (Jueves Santo, días turísticos) no cuentan: los decide cada empleador.

Sheet Liquidación
A1: Vacaciones de una persona — detalle del pago
A2: Elegí el número de empleado de la hoja «Equipo». Todo lo demás se completa solo.
A4: EMPLEADO
A5: Empleado Nº (de la hoja Equipo) | B5: 1
A6: Nombre y apellido | B6: =IFERROR(IF(INDEX('Equipo'!$B$6:$B$45,$B$5)="","Escribilo en la hoja Equipo",INDEX('Equipo'!$B$6:$B$45,$B$5)),"")
A7: Fecha de ingreso | B7: =IFERROR(IF(INDEX('Equipo'!$C$6:$C$45,$B$5)="","",INDEX('Equipo'!$C$6:$C$45,$B$5)),"")
A8: Sueldo bruto mensual | B8: =IFERROR(IF(INDEX('Equipo'!$D$6:$D$45,$B$5)="","",INDEX('Equipo'!$D$6:$D$45,$B$5)),"")
A9: Antigüedad al 31 de diciembre | B9: =IFERROR(IF(INDEX('Equipo'!$H$6:$H$45,$B$5)="","",INDEX('Equipo'!$H$6:$H$45,$B$5)),"")
A10: Régimen | B10: =IFERROR(IF(INDEX('Equipo'!$J$6:$J$45,$B$5)="","",INDEX('Equipo'!$J$6:$J$45,$B$5)),"")
A11: DÍAS Y FECHAS
A12: Días de vacaciones que le corresponden | B12: =IFERROR(IF(INDEX('Equipo'!$I$6:$I$45,$B$5)="","",INDEX('Equipo'!$I$6:$I$45,$B$5)),"")
A13: Días de este tramo | B13: =IFERROR(IF(INDEX('Equipo'!$K$6:$K$45,$B$5)="","",INDEX('Equipo'!$K$6:$K$45,$B$5)),"")
A14: Primer día de vacaciones | B14: =IFERROR(IF(INDEX('Equipo'!$F$6:$F$45,$B$5)="","",INDEX('Equipo'!$F$6:$F$45,$B$5)),"")
A15: Último día de vacaciones | B15: =IFERROR(IF(INDEX('Equipo'!$M$6:$M$45,$B$5)="","",INDEX('Equipo'!$M$6:$M$45,$B$5)),"")
A16: Vuelve a trabajar el | B16: =IFERROR(IF(INDEX('Equipo'!$N$6:$N$45,$B$5)="","",INDEX('Equipo'!$N$6:$N$45,$B$5)),"")
A17: Notificar por escrito hasta el | B17: =IFERROR(IF(INDEX('Equipo'!$O$6:$O$45,$B$5)="","",INDEX('Equipo'!$O$6:$O$45,$B$5)),"")
A18: PAGO (art. 155 LCT)
A19: Valor del día de vacaciones (sueldo ÷ 25) | B19: =IFERROR(IF(INDEX('Equipo'!$P$6:$P$45,$B$5)="","",INDEX('Equipo'!$P$6:$P$45,$B$5)),"")
A20: Valor del día trabajado (sueldo ÷ 30) | B20: =IF(B8="","",B8/30)
A21: A PAGAR AL INICIO DE LAS VACACIONES | B21: =IFERROR(IF(INDEX('Equipo'!$Q$6:$Q$45,$B$5)="","",INDEX('Equipo'!$Q$6:$Q$45,$B$5)),"")
A22: Plus vacacional incluido | B22: =IFERROR(IF(INDEX('Equipo'!$R$6:$R$45,$B$5)="","",INDEX('Equipo'!$R$6:$R$45,$B$5)),"")
A23: Estado | B23: =IFERROR(IF(INDEX('Equipo'!$S$6:$S$45,$B$5)="","",INDEX('Equipo'!$S$6:$S$45,$B$5)),"")
A25: * El plus vacacional no es un adicional aparte: sale de pagar cada día de vacaciones a sueldo ÷ 25 en lugar de ÷ 30. El importe es bruto: lleva los mismos aportes que el sueldo (jubilación, PAMI, obra social y, si corresponde, sindicato y Ganancias).

Sheet Notificación
A1: Notificación de vacaciones — lista para imprimir y firmar
A3: Empleado Nº (de la hoja Equipo) | B3: 1
A4: Empleador o razón social
A5: Lugar
A6: Fecha de la nota | B6: =TODAY()
A7: Antes de imprimir, revisá | B7: =IF(IFERROR(INDEX('Equipo'!$S$6:$S$45,$B$3),"")="","Elegí un número de empleado cargado en la hoja Equipo.",IFERROR(INDEX('Equipo'!$S$6:$S$45,$B$3),""))
A8: Se imprimen las dos copias en una hoja A4: una para la persona y otra, firmada por ella, para el legajo. Las celdas amarillas son las únicas que completás acá.
A11: NOTIFICACIÓN DE VACACIONES · ORIGINAL (para la persona)
A13: =IF($B$5="","",$B$5&", ")&IF($B$6="","",CHOOSE(WEEKDAY($B$6,2),"lunes","martes","miércoles","jueves","viernes","sábado","domingo")&" "&DAY($B$6)&" de "&CHOOSE(MONTH($B$6),"enero","febrero","marzo","abril","mayo","junio","julio","agosto","septiembre","octubre","noviembre","diciembre")&" de "&YEAR($B$6))
A15: ="Señor/a "&IF(IFERROR(INDEX('Equipo'!$B$6:$B$45,$B$3),"")="","______________________________",IFERROR(INDEX('Equipo'!$B$6:$B$45,$B$3),""))
A16: Presente
A18: =IF(AND(IFERROR(INDEX('Equipo'!$F$6:$F$45,$B$3),"")<>"",IFERROR(INDEX('Equipo'!$M$6:$M$45,$B$3),"")<>""),"Por medio de la presente le notificamos que, conforme al artículo 154 de la Ley de Contrato de Trabajo, usted gozará de "&IFERROR(INDEX('Equipo'!$K$6:$K$45,$B$3),"")&" días corridos de su licencia anual ordinaria correspondiente al año "&'Equipo'!$B$3&", desde el "&CHOOSE(WEEKDAY(IFERROR(INDEX('Equipo'!$F$6:$F$45,$B$3),""),2),"lunes","martes","miércoles","jueves","viernes","sábado","domingo")&" "&DAY(IFERROR(INDEX('Equipo'!$F$6:$F$45,$B$3),""))&" de "&CHOOSE(MONTH(IFERROR(INDEX('Equipo'!$F$6:$F$45,$B$3),"")),"enero","febrero","marzo","abril","mayo","junio","julio","agosto","septiembre","octubre","noviembre","diciembre")&" de "&YEAR(IFERROR(INDEX('Equipo'!$F$6:$F$45,$B$3),""))&" hasta el "&CHOOSE(WEEKDAY(IFERROR(INDEX('Equipo'!$M$6:$M$45,$B$3),""),2),"lunes","martes","miércoles","jueves","viernes","sábado","domingo")&" "&DAY(IFERROR(INDEX('Equipo'!$M$6:$M$45,$B$3),""))&" de "&CHOOSE(MONTH(IFERROR(INDEX('Equipo'!$M$6:$M$45,$B$3),"")),"enero","febrero","marzo","abril","mayo","junio","julio","agosto","septiembre","octubre","noviembre","diciembre")&" de "&YEAR(IFERROR(INDEX('Equipo'!$M$6:$M$45,$B$3),""))&" inclusive, y deberá reintegrarse a sus tareas el "&CHOOSE(WEEKDAY(IFERROR(INDEX('Equipo'!$N$6:$N$45,$B$3),""),2),"lunes","martes","miércoles","jueves","viernes","sábado","domingo")&" "&DAY(IFERROR(INDEX('Equipo'!$N$6:$N$45,$B$3),""))&" de "&CHOOSE(MONTH(IFERROR(INDEX('Equipo'!$N$6:$N$45,$B$3),"")),"enero","febrero","marzo","abril","mayo","junio","julio","agosto","septiembre","octubre","noviembre","diciembre")&" de "&YEAR(IFERROR(INDEX('Equipo'!$N$6:$N$45,$B$3),""))&"."&IF(IFERROR(INDEX('Equipo'!$L$6:$L$45,$B$3),"")>0," Los "&IFERROR(INDEX('Equipo'!$L$6:$L$45,$B$3),"")&" días restantes de este período los gozará en la fecha que acordemos.",""),"Para armar la nota, completá la fecha de inicio de esta persona en la hoja Equipo.")
A23: Importe bruto de sus vacaciones, que se abona al inicio de la licencia (art. 155): | D23: =IF(AND(IFERROR(INDEX('Equipo'!$F$6:$F$45,$B$3),"")<>"",IFERROR(INDEX('Equipo'!$M$6:$M$45,$B$3),"")<>""),IFERROR(INDEX('Equipo'!$Q$6:$Q$45,$B$3),""),"")
A25: Si durante las vacaciones se enfermara, avísenos en el momento: se reincorporará en la fecha prevista y los días que no haya podido gozar se reprogramarán (art. 154). Saludamos a usted atentamente.
A29: ="Firma y aclaración"&IF($B$4="",""," · "&$B$4) | C29: Recibí la notificación. Firma, aclaración y fecha
A31: NOTIFICACIÓN DE VACACIONES · DUPLICADO (firmado, para el legajo)
A33: =IF($B$5="","",$B$5&", ")&IF($B$6="","",CHOOSE(WEEKDAY($B$6,2),"lunes","martes","miércoles","jueves","viernes","sábado","domingo")&" "&DAY($B$6)&" de "&CHOOSE(MONTH($B$6),"enero","febrero","marzo","abril","mayo","junio","julio","agosto","septiembre","octubre","noviembre","diciembre")&" de "&YEAR($B$6))
A35: ="Señor/a "&IF(IFERROR(INDEX('Equipo'!$B$6:$B$45,$B$3),"")="","______________________________",IFERROR(INDEX('Equipo'!$B$6:$B$45,$B$3),""))
A36: Presente
A38: =IF(AND(IFERROR(INDEX('Equipo'!$F$6:$F$45,$B$3),"")<>"",IFERROR(INDEX('Equipo'!$M$6:$M$45,$B$3),"")<>""),"Por medio de la presente le notificamos que, conforme al artículo 154 de la Ley de Contrato de Trabajo, usted gozará de "&IFERROR(INDEX('Equipo'!$K$6:$K$45,$B$3),"")&" días corridos de su licencia anual ordinaria correspondiente al año "&'Equipo'!$B$3&", desde el "&CHOOSE(WEEKDAY(IFERROR(INDEX('Equipo'!$F$6:$F$45,$B$3),""),2),"lunes","martes","miércoles","jueves","viernes","sábado","domingo")&" "&DAY(IFERROR(INDEX('Equipo'!$F$6:$F$45,$B$3),""))&" de "&CHOOSE(MONTH(IFERROR(INDEX('Equipo'!$F$6:$F$45,$B$3),"")),"enero","febrero","marzo","abril","mayo","junio","julio","agosto","septiembre","octubre","noviembre","diciembre")&" de "&YEAR(IFERROR(INDEX('Equipo'!$F$6:$F$45,$B$3),""))&" hasta el "&CHOOSE(WEEKDAY(IFERROR(INDEX('Equipo'!$M$6:$M$45,$B$3),""),2),"lunes","martes","miércoles","jueves","viernes","sábado","domingo")&" "&DAY(IFERROR(INDEX('Equipo'!$M$6:$M$45,$B$3),""))&" de "&CHOOSE(MONTH(IFERROR(INDEX('Equipo'!$M$6:$M$45,$B$3),"")),"enero","febrero","marzo","abril","mayo","junio","julio","agosto","septiembre","octubre","noviembre","diciembre")&" de "&YEAR(IFERROR(INDEX('Equipo'!$M$6:$M$45,$B$3),""))&" inclusive, y deberá reintegrarse a sus tareas el "&CHOOSE(WEEKDAY(IFERROR(INDEX('Equipo'!$N$6:$N$45,$B$3),""),2),"lunes","martes","miércoles","jueves","viernes","sábado","domingo")&" "&DAY(IFERROR(INDEX('Equipo'!$N$6:$N$45,$B$3),""))&" de "&CHOOSE(MONTH(IFERROR(INDEX('Equipo'!$N$6:$N$45,$B$3),"")),"enero","febrero","marzo","abril","mayo","junio","julio","agosto","septiembre","octubre","noviembre","diciembre")&" de "&YEAR(IFERROR(INDEX('Equipo'!$N$6:$N$45,$B$3),""))&"."&IF(IFERROR(INDEX('Equipo'!$L$6:$L$45,$B$3),"")>0," Los "&IFERROR(INDEX('Equipo'!$L$6:$L$45,$B$3),"")&" días restantes de este período los gozará en la fecha que acordemos.",""),"Para armar la nota, completá la fecha de inicio de esta persona en la hoja Equipo.")
A43: Importe bruto de sus vacaciones, que se abona al inicio de la licencia (art. 155): | D43: =IF(AND(IFERROR(INDEX('Equipo'!$F$6:$F$45,$B$3),"")<>"",IFERROR(INDEX('Equipo'!$M$6:$M$45,$B$3),"")<>""),IFERROR(INDEX('Equipo'!$Q$6:$Q$45,$B$3),""),"")
A45: Si durante las vacaciones se enfermara, avísenos en el momento: se reincorporará en la fecha prevista y los días que no haya podido gozar se reprogramarán (art. 154). Saludamos a usted atentamente.
A49: ="Firma y aclaración"&IF($B$4="",""," · "&$B$4) | C49: Recibí la notificación. Firma, aclaración y fecha

Sheet Temporada
A1: La temporada en números — cuánto pagás y cuándo
A3: RESUMEN DEL EQUIPO
A4: Personas con vacaciones cargadas | B4: =SUM('Equipo'!$U$6:$U$45)
A5: Días de vacaciones de este tramo | B5: =SUM('Equipo'!$K$6:$K$45)
A6: TOTAL A PAGAR EN VACACIONES | B6: =SUM('Equipo'!$Q$6:$Q$45)
A7: Plus vacacional incluido | B7: =SUM('Equipo'!$R$6:$R$45)
A8: Personas con algo para revisar en «Estado» | B8: =B4-SUM('Equipo'!$T$6:$T$45)
A10: Mes en que empiezan | B10: Personas | C10: Días | D10: A pagar ese mes
A11: ="Octubre "&YEAR(DATE('Equipo'!$B$3,10,1)) | B11: =COUNTIFS('Equipo'!$U$6:$U$45,1,'Equipo'!$F$6:$F$45,">="&DATE('Equipo'!$B$3,10,1),'Equipo'!$F$6:$F$45,"<"&DATE('Equipo'!$B$3,11,1)) | C11: =SUMIFS('Equipo'!$K$6:$K$45,'Equipo'!$U$6:$U$45,1,'Equipo'!$F$6:$F$45,">="&DATE('Equipo'!$B$3,10,1),'Equipo'!$F$6:$F$45,"<"&DATE('Equipo'!$B$3,11,1)) | D11: =SUMIFS('Equipo'!$Q$6:$Q$45,'Equipo'!$U$6:$U$45,1,'Equipo'!$F$6:$F$45,">="&DATE('Equipo'!$B$3,10,1),'Equipo'!$F$6:$F$45,"<"&DATE('Equipo'!$B$3,11,1))
A12: ="Noviembre "&YEAR(DATE('Equipo'!$B$3,11,1)) | B12: =COUNTIFS('Equipo'!$U$6:$U$45,1,'Equipo'!$F$6:$F$45,">="&DATE('Equipo'!$B$3,11,1),'Equipo'!$F$6:$F$45,"<"&DATE('Equipo'!$B$3,12,1)) | C12: =SUMIFS('Equipo'!$K$6:$K$45,'Equipo'!$U$6:$U$45,1,'Equipo'!$F$6:$F$45,">="&DATE('Equipo'!$B$3,11,1),'Equipo'!$F$6:$F$45,"<"&DATE('Equipo'!$B$3,12,1)) | D12: =SUMIFS('Equipo'!$Q$6:$Q$45,'Equipo'!$U$6:$U$45,1,'Equipo'!$F$6:$F$45,">="&DATE('Equipo'!$B$3,11,1),'Equipo'!$F$6:$F$45,"<"&DATE('Equipo'!$B$3,12,1))
A13: ="Diciembre "&YEAR(DATE('Equipo'!$B$3,12,1)) | B13: =COUNTIFS('Equipo'!$U$6:$U$45,1,'Equipo'!$F$6:$F$45,">="&DATE('Equipo'!$B$3,12,1),'Equipo'!$F$6:$F$45,"<"&DATE('Equipo'!$B$3,13,1)) | C13: =SUMIFS('Equipo'!$K$6:$K$45,'Equipo'!$U$6:$U$45,1,'Equipo'!$F$6:$F$45,">="&DATE('Equipo'!$B$3,12,1),'Equipo'!$F$6:$F$45,"<"&DATE('Equipo'!$B$3,13,1)) | D13: =SUMIFS('Equipo'!$Q$6:$Q$45,'Equipo'!$U$6:$U$45,1,'Equipo'!$F$6:$F$45,">="&DATE('Equipo'!$B$3,12,1),'Equipo'!$F$6:$F$45,"<"&DATE('Equipo'!$B$3,13,1))
A14: ="Enero "&YEAR(DATE('Equipo'!$B$3,13,1)) | B14: =COUNTIFS('Equipo'!$U$6:$U$45,1,'Equipo'!$F$6:$F$45,">="&DATE('Equipo'!$B$3,13,1),'Equipo'!$F$6:$F$45,"<"&DATE('Equipo'!$B$3,14,1)) | C14: =SUMIFS('Equipo'!$K$6:$K$45,'Equipo'!$U$6:$U$45,1,'Equipo'!$F$6:$F$45,">="&DATE('Equipo'!$B$3,13,1),'Equipo'!$F$6:$F$45,"<"&DATE('Equipo'!$B$3,14,1)) | D14: =SUMIFS('Equipo'!$Q$6:$Q$45,'Equipo'!$U$6:$U$45,1,'Equipo'!$F$6:$F$45,">="&DATE('Equipo'!$B$3,13,1),'Equipo'!$F$6:$F$45,"<"&DATE('Equipo'!$B$3,14,1))
A15: ="Febrero "&YEAR(DATE('Equipo'!$B$3,14,1)) | B15: =COUNTIFS('Equipo'!$U$6:$U$45,1,'Equipo'!$F$6:$F$45,">="&DATE('Equipo'!$B$3,14,1),'Equipo'!$F$6:$F$45,"<"&DATE('Equipo'!$B$3,15,1)) | C15: =SUMIFS('Equipo'!$K$6:$K$45,'Equipo'!$U$6:$U$45,1,'Equipo'!$F$6:$F$45,">="&DATE('Equipo'!$B$3,14,1),'Equipo'!$F$6:$F$45,"<"&DATE('Equipo'!$B$3,15,1)) | D15: =SUMIFS('Equipo'!$Q$6:$Q$45,'Equipo'!$U$6:$U$45,1,'Equipo'!$F$6:$F$45,">="&DATE('Equipo'!$B$3,14,1),'Equipo'!$F$6:$F$45,"<"&DATE('Equipo'!$B$3,15,1))
A16: ="Marzo "&YEAR(DATE('Equipo'!$B$3,15,1)) | B16: =COUNTIFS('Equipo'!$U$6:$U$45,1,'Equipo'!$F$6:$F$45,">="&DATE('Equipo'!$B$3,15,1),'Equipo'!$F$6:$F$45,"<"&DATE('Equipo'!$B$3,16,1)) | C16: =SUMIFS('Equipo'!$K$6:$K$45,'Equipo'!$U$6:$U$45,1,'Equipo'!$F$6:$F$45,">="&DATE('Equipo'!$B$3,15,1),'Equipo'!$F$6:$F$45,"<"&DATE('Equipo'!$B$3,16,1)) | D16: =SUMIFS('Equipo'!$Q$6:$Q$45,'Equipo'!$U$6:$U$45,1,'Equipo'!$F$6:$F$45,">="&DATE('Equipo'!$B$3,15,1),'Equipo'!$F$6:$F$45,"<"&DATE('Equipo'!$B$3,16,1))
A17: ="Abril "&YEAR(DATE('Equipo'!$B$3,16,1)) | B17: =COUNTIFS('Equipo'!$U$6:$U$45,1,'Equipo'!$F$6:$F$45,">="&DATE('Equipo'!$B$3,16,1),'Equipo'!$F$6:$F$45,"<"&DATE('Equipo'!$B$3,17,1)) | C17: =SUMIFS('Equipo'!$K$6:$K$45,'Equipo'!$U$6:$U$45,1,'Equipo'!$F$6:$F$45,">="&DATE('Equipo'!$B$3,16,1),'Equipo'!$F$6:$F$45,"<"&DATE('Equipo'!$B$3,17,1)) | D17: =SUMIFS('Equipo'!$Q$6:$Q$45,'Equipo'!$U$6:$U$45,1,'Equipo'!$F$6:$F$45,">="&DATE('Equipo'!$B$3,16,1),'Equipo'!$F$6:$F$45,"<"&DATE('Equipo'!$B$3,17,1))
A18: Fuera de temporada (con acuerdo) | B18: =COUNTIFS('Equipo'!$U$6:$U$45,1,'Equipo'!$F$6:$F$45,">0")-SUM(B11:B17) | C18: =SUMIFS('Equipo'!$K$6:$K$45,'Equipo'!$U$6:$U$45,1,'Equipo'!$F$6:$F$45,">0")-SUM(C11:C17) | D18: =SUMIFS('Equipo'!$Q$6:$Q$45,'Equipo'!$U$6:$U$45,1,'Equipo'!$F$6:$F$45,">0")-SUM(D11:D17)
A19: Todavía sin fecha de inicio | B19: =B4-COUNTIFS('Equipo'!$U$6:$U$45,1,'Equipo'!$F$6:$F$45,">0") | C19: =B5-SUMIFS('Equipo'!$K$6:$K$45,'Equipo'!$U$6:$U$45,1,'Equipo'!$F$6:$F$45,">0") | D19: =B6-SUMIFS('Equipo'!$Q$6:$Q$45,'Equipo'!$U$6:$U$45,1,'Equipo'!$F$6:$F$45,">0")
A21: * Cada licencia se cuenta en el mes en que empieza, que es cuando se paga (art. 155). Los importes son brutos, antes de descuentos y sin las contribuciones patronales.

Sheet Egresos
A1: Si alguien se va — vacaciones no gozadas (art. 156 LCT)
A2: Corresponde por cualquier causa de egreso (renuncia, despido, acuerdo). Se paga en la liquidación final: días de la escala × días trabajados en el año ÷ 365, a sueldo ÷ 25, más el aguinaldo sobre ese importe.
A3: Si ya se tomó a cuenta vacaciones de este mismo año, o le quedó sin gozar un período anterior, ajustalo con quien liquida: esta hoja calcula el proporcional del año del egreso.
A5: Nº | B5: Nombre | C5: Ingreso | D5: Mejor sueldo mensual | E5: Fecha de egreso | F5: Días del año trabajados | G5: Días proporcionales | H5: Vacaciones no gozadas | I5: Aguinaldo sobre vacaciones | J5: TOTAL
A6: 3 | B6: =IF(A6="","",IFERROR(IF(INDEX('Equipo'!$B$6:$B$45,A6)="","",INDEX('Equipo'!$B$6:$B$45,A6)),"")) | C6: =IF(A6="","",IFERROR(IF(INDEX('Equipo'!$C$6:$C$45,A6)="","",INDEX('Equipo'!$C$6:$C$45,A6)),"")) | D6: =IF(A6="","",IFERROR(IF(INDEX('Equipo'!$D$6:$D$45,A6)="","",INDEX('Equipo'!$D$6:$D$45,A6)),"")) | E6: 46371 | F6: =IF(OR(A6="",E6="",C6="",D6=""),"",E6-MAX(C6,DATE(YEAR(E6),1,1))+1) | G6: =IF(F6="","",IF(C6>=DATE(YEAR(E6)-5,12,31),14,IF(C6>=DATE(YEAR(E6)-10,12,31),21,IF(C6>=DATE(YEAR(E6)-20,12,31),28,35)))*F6/365) | H6: =IF(F6="","",G6*D6/25) | I6: =IF(F6="","",H6/12) | J6: =IF(F6="","",H6+I6)
B7: =IF(A7="","",IFERROR(IF(INDEX('Equipo'!$B$6:$B$45,A7)="","",INDEX('Equipo'!$B$6:$B$45,A7)),"")) | C7: =IF(A7="","",IFERROR(IF(INDEX('Equipo'!$C$6:$C$45,A7)="","",INDEX('Equipo'!$C$6:$C$45,A7)),"")) | D7: =IF(A7="","",IFERROR(IF(INDEX('Equipo'!$D$6:$D$45,A7)="","",INDEX('Equipo'!$D$6:$D$45,A7)),"")) | F7: =IF(OR(A7="",E7="",C7="",D7=""),"",E7-MAX(C7,DATE(YEAR(E7),1,1))+1) | G7: =IF(F7="","",IF(C7>=DATE(YEAR(E7)-5,12,31),14,IF(C7>=DATE(YEAR(E7)-10,12,31),21,IF(C7>=DATE(YEAR(E7)-20,12,31),28,35)))*F7/365) | H7: =IF(F7="","",G7*D7/25) | I7: =IF(F7="","",H7/12) | J7: =IF(F7="","",H7+I7)
B8: =IF(A8="","",IFERROR(IF(INDEX('Equipo'!$B$6:$B$45,A8)="","",INDEX('Equipo'!$B$6:$B$45,A8)),"")) | C8: =IF(A8="","",IFERROR(IF(INDEX('Equipo'!$C$6:$C$45,A8)="","",INDEX('Equipo'!$C$6:$C$45,A8)),"")) | D8: =IF(A8="","",IFERROR(IF(INDEX('Equipo'!$D$6:$D$45,A8)="","",INDEX('Equipo'!$D$6:$D$45,A8)),"")) | F8: =IF(OR(A8="",E8="",C8="",D8=""),"",E8-MAX(C8,DATE(YEAR(E8),1,1))+1) | G8: =IF(F8="","",IF(C8>=DATE(YEAR(E8)-5,12,31),14,IF(C8>=DATE(YEAR(E8)-10,12,31),21,IF(C8>=DATE(YEAR(E8)-20,12,31),28,35)))*F8/365) | H8: =IF(F8="","",G8*D8/25) | I8: =IF(F8="","",H8/12) | J8: =IF(F8="","",H8+I8)
B9: =IF(A9="","",IFERROR(IF(INDEX('Equipo'!$B$6:$B$45,A9)="","",INDEX('Equipo'!$B$6:$B$45,A9)),"")) | C9: =IF(A9="","",IFERROR(IF(INDEX('Equipo'!$C$6:$C$45,A9)="","",INDEX('Equipo'!$C$6:$C$45,A9)),"")) | D9: =IF(A9="","",IFERROR(IF(INDEX('Equipo'!$D$6:$D$45,A9)="","",INDEX('Equipo'!$D$6:$D$45,A9)),"")) | F9: =IF(OR(A9="",E9="",C9="",D9=""),"",E9-MAX(C9,DATE(YEAR(E9),1,1))+1) | G9: =IF(F9="","",IF(C9>=DATE(YEAR(E9)-5,12,31),14,IF(C9>=DATE(YEAR(E9)-10,12,31),21,IF(C9>=DATE(YEAR(E9)-20,12,31),28,35)))*F9/365) | H9: =IF(F9="","",G9*D9/25) | I9: =IF(F9="","",H9/12) | J9: =IF(F9="","",H9+I9)
B10: =IF(A10="","",IFERROR(IF(INDEX('Equipo'!$B$6:$B$45,A10)="","",INDEX('Equipo'!$B$6:$B$45,A10)),"")) | C10: =IF(A10="","",IFERROR(IF(INDEX('Equipo'!$C$6:$C$45,A10)="","",INDEX('Equipo'!$C$6:$C$45,A10)),"")) | D10: =IF(A10="","",IFERROR(IF(INDEX('Equipo'!$D$6:$D$45,A10)="","",INDEX('Equipo'!$D$6:$D$45,A10)),"")) | F10: =IF(OR(A10="",E10="",C10="",D10=""),"",E10-MAX(C10,DATE(YEAR(E10),1,1))+1) | G10: =IF(F10="","",IF(C10>=DATE(YEAR(E10)-5,12,31),14,IF(C10>=DATE(YEAR(E10)-10,12,31),21,IF(C10>=DATE(YEAR(E10)-20,12,31),28,35)))*F10/365) | H10: =IF(F10="","",G10*D10/25) | I10: =IF(F10="","",H10/12) | J10: =IF(F10="","",H10+I10)
B11: =IF(A11="","",IFERROR(IF(INDEX('Equipo'!$B$6:$B$45,A11)="","",INDEX('Equipo'!$B$6:$B$45,A11)),"")) | C11: =IF(A11="","",IFERROR(IF(INDEX('Equipo'!$C$6:$C$45,A11)="","",INDEX('Equipo'!$C$6:$C$45,A11)),"")) | D11: =IF(A11="","",IFERROR(IF(INDEX('Equipo'!$D$6:$D$45,A11)="","",INDEX('Equipo'!$D$6:$D$45,A11)),"")) | F11: =IF(OR(A11="",E11="",C11="",D11=""),"",E11-MAX(C11,DATE(YEAR(E11),1,1))+1) | G11: =IF(F11="","",IF(C11>=DATE(YEAR(E11)-5,12,31),14,IF(C11>=DATE(YEAR(E11)-10,12,31),21,IF(C11>=DATE(YEAR(E11)-20,12,31),28,35)))*F11/365) | H11: =IF(F11="","",G11*D11/25) | I11: =IF(F11="","",H11/12) | J11: =IF(F11="","",H11+I11)
B12: =IF(A12="","",IFERROR(IF(INDEX('Equipo'!$B$6:$B$45,A12)="","",INDEX('Equipo'!$B$6:$B$45,A12)),"")) | C12: =IF(A12="","",IFERROR(IF(INDEX('Equipo'!$C$6:$C$45,A12)="","",INDEX('Equipo'!$C$6:$C$45,A12)),"")) | D12: =IF(A12="","",IFERROR(IF(INDEX('Equipo'!$D$6:$D$45,A12)="","",INDEX('Equipo'!$D$6:$D$45,A12)),"")) | F12: =IF(OR(A12="",E12="",C12="",D12=""),"",E12-MAX(C12,DATE(YEAR(E12),1,1))+1) | G12: =IF(F12="","",IF(C12>=DATE(YEAR(E12)-5,12,31),14,IF(C12>=DATE(YEAR(E12)-10,12,31),21,IF(C12>=DATE(YEAR(E12)-20,12,31),28,35)))*F12/365) | H12: =IF(F12="","",G12*D12/25) | I12: =IF(F12="","",H12/12) | J12: =IF(F12="","",H12+I12)
B13: =IF(A13="","",IFERROR(IF(INDEX('Equipo'!$B$6:$B$45,A13)="","",INDEX('Equipo'!$B$6:$B$45,A13)),"")) | C13: =IF(A13="","",IFERROR(IF(INDEX('Equipo'!$C$6:$C$45,A13)="","",INDEX('Equipo'!$C$6:$C$45,A13)),"")) | D13: =IF(A13="","",IFERROR(IF(INDEX('Equipo'!$D$6:$D$45,A13)="","",INDEX('Equipo'!$D$6:$D$45,A13)),"")) | F13: =IF(OR(A13="",E13="",C13="",D13=""),"",E13-MAX(C13,DATE(YEAR(E13),1,1))+1) | G13: =IF(F13="","",IF(C13>=DATE(YEAR(E13)-5,12,31),14,IF(C13>=DATE(YEAR(E13)-10,12,31),21,IF(C13>=DATE(YEAR(E13)-20,12,31),28,35)))*F13/365) | H13: =IF(F13="","",G13*D13/25) | I13: =IF(F13="","",H13/12) | J13: =IF(F13="","",H13+I13)
B14: =IF(A14="","",IFERROR(IF(INDEX('Equipo'!$B$6:$B$45,A14)="","",INDEX('Equipo'!$B$6:$B$45,A14)),"")) | C14: =IF(A14="","",IFERROR(IF(INDEX('Equipo'!$C$6:$C$45,A14)="","",INDEX('Equipo'!$C$6:$C$45,A14)),"")) | D14: =IF(A14="","",IFERROR(IF(INDEX('Equipo'!$D$6:$D$45,A14)="","",INDEX('Equipo'!$D$6:$D$45,A14)),"")) | F14: =IF(OR(A14="",E14="",C14="",D14=""),"",E14-MAX(C14,DATE(YEAR(E14),1,1))+1) | G14: =IF(F14="","",IF(C14>=DATE(YEAR(E14)-5,12,31),14,IF(C14>=DATE(YEAR(E14)-10,12,31),21,IF(C14>=DATE(YEAR(E14)-20,12,31),28,35)))*F14/365) | H14: =IF(F14="","",G14*D14/25) | I14: =IF(F14="","",H14/12) | J14: =IF(F14="","",H14+I14)
B15: =IF(A15="","",IFERROR(IF(INDEX('Equipo'!$B$6:$B$45,A15)="","",INDEX('Equipo'!$B$6:$B$45,A15)),"")) | C15: =IF(A15="","",IFERROR(IF(INDEX('Equipo'!$C$6:$C$45,A15)="","",INDEX('Equipo'!$C$6:$C$45,A15)),"")) | D15: =IF(A15="","",IFERROR(IF(INDEX('Equipo'!$D$6:$D$45,A15)="","",INDEX('Equipo'!$D$6:$D$45,A15)),"")) | F15: =IF(OR(A15="",E15="",C15="",D15=""),"",E15-MAX(C15,DATE(YEAR(E15),1,1))+1) | G15: =IF(F15="","",IF(C15>=DATE(YEAR(E15)-5,12,31),14,IF(C15>=DATE(YEAR(E15)-10,12,31),21,IF(C15>=DATE(YEAR(E15)-20,12,31),28,35)))*F15/365) | H15: =IF(F15="","",G15*D15/25) | I15: =IF(F15="","",H15/12) | J15: =IF(F15="","",H15+I15)

Sheet Feriados
A1: Feriados nacionales 2026 y 2027 (Ley 27.399)
A2: Los usa la regla del art. 151: si el lunes de inicio es feriado, las vacaciones empiezan el hábil siguiente. Están los inamovibles y los trasladables ya trasladados. Si tu provincia tiene un feriado propio, agregalo al final de la lista.
A4: Fecha | B4: Feriado
A5: 46023 | B5: Año Nuevo
A6: 46069 | B6: Lunes de Carnaval
A7: 46070 | B7: Martes de Carnaval
A8: 46105 | B8: Día Nacional de la Memoria por la Verdad y la Justicia
A9: 46114 | B9: Día del Veterano y de los Caídos en la Guerra de Malvinas
A10: 46115 | B10: Viernes Santo
A11: 46143 | B11: Día del Trabajo
A12: 46167 | B12: Día de la Revolución de Mayo
A13: 46188 | B13: Paso a la Inmortalidad del General Martín Miguel de Güemes
A14: 46193 | B14: Paso a la Inmortalidad del General Manuel Belgrano
A15: 46212 | B15: Día de la Independencia
A16: 46251 | B16: Paso a la Inmortalidad del General José de San Martín
... A35: 46746 | B35: Navidad

Sheet Fuentes
A1: Fuentes oficiales
A2: Todos los datos de esta planilla se verificaron el 6 de octubre de 2026 contra los documentos oficiales de abajo. Ningún blog, ningún resumen de terceros.
A4: Documento | B4: Link
A5: Ley de Contrato de Trabajo 20.744, arts. 150-164 (texto actualizado) | B5: https://servicios.infoleg.gob.ar/infolegInternet/anexos/25000-29999/25552/texact.htm
A6: Ley 27.802: nuevo art. 154 LCT (B.O. 6/3/2026) | B6: https://servicios.infoleg.gob.ar/infolegInternet/verNorma.do?id=423680
A7: Ley 27.399: Régimen de feriados nacionales y días no laborables | B7: https://servicios.infoleg.gob.ar/infolegInternet/anexos/280000-284999/281835/norma.htm
A8: Decreto 614/2025: traslado de los feriados que caen fin de semana | B8: https://www.boletinoficial.gob.ar/detalleAviso/primera/330457/20250828
A9: Resolución 164/2025: días no laborables con fines turísticos 2026 | B9: https://www.boletinoficial.gob.ar/detalleAviso/primera/336753/20251226
A10: Calendario oficial de feriados: Jefatura de Gabinete | B10: https://www.argentina.gob.ar/jefatura/feriados-nacionales-2026
A12: Planilla de calcular.ar. Las actualizaciones del año están incluidas en el precio: si cambia una norma de vacaciones o el calendario de feriados, regeneramos la planilla y el mismo enlace de descarga te baja la versión al día. Referencia de cálculo con fuentes; no reemplaza el asesoramiento de un profesional.
