Workbook

Sheet Cómo usarla
A1: Cómo usar la planilla de alquileres
A3: 1 | B3: Abrí la hoja «Contrato 1» y reemplazá el ejemplo con los datos de tu contrato: dirección, inquilino, mes y año de inicio, alquiler inicial, índice y cada cuántos meses se ajusta. Sólo se tocan las celdas amarillas.
A4: 2 | B4: Si alquilás más de una propiedad, usá «Contrato 2», «Contrato 3»… hasta 6. La hoja «Mis contratos» las junta todas: cuánto cobrás hoy, cuándo toca el próximo aumento y qué hacer.
A5: 3 | B5: Cuando se aplica un aumento, abrí «Aviso de aumento», elegí el contrato y copiá el mensaje: trae el monto nuevo, la cuenta y la fuente oficial.
A6: 4 | B6: Cada mes, en «Recibo» elegís el contrato y el mes: el importe sale solo. Imprimís la hoja y tenés dos copias, una para tu inquilino y otra para vos.
A7: 5 | B7: La hoja «IPC» tiene la serie oficial del INDEC y la hoja «Fuentes», de dónde sale cada dato.
A9: COLORES
B10: Amarillo: lo completás vos.
B11: Verde: lo calcula la planilla. Están protegidas para que no se pisen sin querer (Revisar > Desproteger hoja, si alguna vez lo necesitás).
A13: LO QUE CONVIENE SABER
B14: • Desde el DNU 70/2023 el índice y la periodicidad del ajuste se pactan libremente (art. 1199 del Código Civil y Comercial). Lo más común en los contratos nuevos es el IPC del INDEC cada 3 o 4 meses.
B15: • El ajuste multiplica el alquiler por la variación del IPC del período. Los porcentajes mensuales se componen, no se suman: tres meses de 2% dan 6,12%, no 6%.
B16: • El INDEC publica el IPC de cada mes entre el 10 y el 15 del mes siguiente. Por eso hay dos formas de tomar los meses: los completos antes del ajuste (la de esta planilla y la de calcular.ar, por defecto) o los últimos publicados, que corren un mes atrás. Elegí la que diga tu contrato en «Meses del IPC que toma».
B17: • Si tu contrato ajusta por ICL (BCRA), Casa Propia u otro índice, elegí «Otro índice» y cargá el % de cada ajuste en el cronograma. El resto (recibo, aviso, tablero) funciona igual.
B18: • Los contratos firmados entre julio de 2020 y diciembre de 2023, con la ley 27.551, en general siguen con su esquema original (ajuste anual por ICL) hasta que terminan.
A20: CÓMO SE MANTIENE AL DÍA
B21: • El enlace de descarga que te llegó por mail no vence y siempre baja la última versión, con el IPC al día. Para pasar tus contratos: copiá las celdas amarillas de cada «Contrato» y pegalas en el mismo lugar de la versión nueva.
B22: • ¿Preferís no cambiar de archivo? Cuando salga un IPC nuevo, cargá el % del mes en la columna amarilla de la hoja «IPC» y todo se recalcula.
A24: Esta planilla da los mismos números que la calculadora gratuita de calcular.ar/inflacion/alquiler: es la misma serie oficial y la misma cuenta. Si alguna vez no coinciden, escribinos y lo corregimos. No es asesoramiento legal: la letra de tu contrato manda.

Sheet Mis contratos
A1: Mis contratos de alquiler
A2: ="IPC oficial del INDEC cargado hasta "&IPC!$J$4&". Cuando salga el siguiente, bajá la versión nueva desde el mismo enlace o cargalo en la hoja IPC."
A4: Contrato | B4: Propiedad | C4: Inquilino/a | D4: Alquiler hoy | E4: Rige desde | F4: Próximo ajuste | G4: Próximo estimado | H4: Qué hacer
A5: Contrato 1 | B5: =IF('Contrato 1'!$B$5="","",'Contrato 1'!$B$5&"") | C5: =IF('Contrato 1'!$B$6="","",'Contrato 1'!$B$6&"") | D5: ='Contrato 1'!$B$17 | E5: ='Contrato 1'!$B$18&"" | F5: ='Contrato 1'!$B$21&"" | G5: ='Contrato 1'!$B$22 | H5: =IF('Contrato 1'!$N$5=1,'Contrato 1'!$B$24,"Sin cargar todavía: completá la hoja «Contrato 1».")
A6: Contrato 2 | B6: =IF('Contrato 2'!$B$5="","",'Contrato 2'!$B$5&"") | C6: =IF('Contrato 2'!$B$6="","",'Contrato 2'!$B$6&"") | D6: ='Contrato 2'!$B$17 | E6: ='Contrato 2'!$B$18&"" | F6: ='Contrato 2'!$B$21&"" | G6: ='Contrato 2'!$B$22 | H6: =IF('Contrato 2'!$N$5=1,'Contrato 2'!$B$24,"Sin cargar todavía: completá la hoja «Contrato 2».")
A7: Contrato 3 | B7: =IF('Contrato 3'!$B$5="","",'Contrato 3'!$B$5&"") | C7: =IF('Contrato 3'!$B$6="","",'Contrato 3'!$B$6&"") | D7: ='Contrato 3'!$B$17 | E7: ='Contrato 3'!$B$18&"" | F7: ='Contrato 3'!$B$21&"" | G7: ='Contrato 3'!$B$22 | H7: =IF('Contrato 3'!$N$5=1,'Contrato 3'!$B$24,"Sin cargar todavía: completá la hoja «Contrato 3».")
A8: Contrato 4 | B8: =IF('Contrato 4'!$B$5="","",'Contrato 4'!$B$5&"") | C8: =IF('Contrato 4'!$B$6="","",'Contrato 4'!$B$6&"") | D8: ='Contrato 4'!$B$17 | E8: ='Contrato 4'!$B$18&"" | F8: ='Contrato 4'!$B$21&"" | G8: ='Contrato 4'!$B$22 | H8: =IF('Contrato 4'!$N$5=1,'Contrato 4'!$B$24,"Sin cargar todavía: completá la hoja «Contrato 4».")
A9: Contrato 5 | B9: =IF('Contrato 5'!$B$5="","",'Contrato 5'!$B$5&"") | C9: =IF('Contrato 5'!$B$6="","",'Contrato 5'!$B$6&"") | D9: ='Contrato 5'!$B$17 | E9: ='Contrato 5'!$B$18&"" | F9: ='Contrato 5'!$B$21&"" | G9: ='Contrato 5'!$B$22 | H9: =IF('Contrato 5'!$N$5=1,'Contrato 5'!$B$24,"Sin cargar todavía: completá la hoja «Contrato 5».")
A10: Contrato 6 | B10: =IF('Contrato 6'!$B$5="","",'Contrato 6'!$B$5&"") | C10: =IF('Contrato 6'!$B$6="","",'Contrato 6'!$B$6&"") | D10: ='Contrato 6'!$B$17 | E10: ='Contrato 6'!$B$18&"" | F10: ='Contrato 6'!$B$21&"" | G10: ='Contrato 6'!$B$22 | H10: =IF('Contrato 6'!$N$5=1,'Contrato 6'!$B$24,"Sin cargar todavía: completá la hoja «Contrato 6».")
A12: Esta hoja no se completa: junta lo que cargaste en cada «Contrato». Para el recibo del mes andá a la hoja «Recibo»; para avisarle el aumento a tu inquilino, a «Aviso de aumento».

Sheet Contrato 1
A1: Contrato 1
A2: Este contrato viene cargado con un ejemplo: reemplazá las celdas amarillas con los datos del tuyo. Las verdes se calculan solas.
A4: DATOS DEL CONTRATO
A5: Propiedad (dirección) | B5: Av. Corrientes 1234, 3° B (ejemplo) | N5: =IF(AND(N6>0,ISNUMBER(B9),ISNUMBER(B11),B11>0,ISNUMBER(B13),B13>=1,ISNUMBER(B10),B10>=1),1,0)
A6: Inquilino/a | B6: Laura Gómez (ejemplo) | N6: =IFERROR(MATCH(B8,IPC!$J$5:$J$16,0),0)
A7: Tu nombre (para el recibo y el aviso) | N7: =IF(N5=1,B9*12+N6-1,0)
A8: Mes de inicio del contrato | B8: septiembre | C8: El primer mes en que se cobró el valor inicial. | N8: =IF(N5=1,INT(B13),1)
A9: Año de inicio | B9: 2025 | N9: =IF(B14="Los últimos publicados",1,0)
A10: Duración (meses) | B10: 24 | N10: =IF(B12="Otro índice (cargo el %)",0,1)
A11: Alquiler inicial (el del primer mes) | B11: 500000 | N11: =IF(N5=1,MIN(INT((B10-1)/N8),60),0)
A12: Índice de ajuste | B12: IPC (INDEC) | C12: Si tu contrato ajusta por ICL, Casa Propia u otro índice, elegí «Otro» y cargá el % de cada ajuste en el cronograma (columna F). | N12: =IPC!$J$3
A13: Se ajusta cada (meses) | B13: 3 | C13: Trimestral = 3, cuatrimestral = 4, semestral = 6, anual = 12. | N13: =IPC!$J$2
A14: Meses del IPC que toma | B14: Los completos antes del ajuste | C14: «Completos»: un ajuste de julio usa el IPC de abril a junio (como la calculadora de calcular.ar). «Últimos publicados»: usa el de marzo a mayo, porque el de junio sale a mitad de julio. Fijate qué dice tu contrato. | N14: =IF(N5=0,0,IF(N10=0,1,IF(AND(N7-1-N9>=N13,N7-1-N9<=N12),1,0)))
N15: =COUNT(G29:G88)
A16: CÓMO VIENE EL CONTRATO | N16: =IF(N5=1,INDEX(G28:G88,N15+1),"")
A17: Alquiler que se cobra hoy | B17: =N16 | N17: =N15+1
A18: Rige desde | B18: =IF(N5=1,INDEX(B28:B88,N15+1),"") | N18: =IF(AND(N5=1,N17<=N11),1,0)
A19: Ajustes aplicados | B19: =IF(N5=1,N15,"") | N19: =N7+N17*N8-1-N9
A20: Aumento desde el inicio | B20: =IF(N5=1,N16/B11-1,"") | N20: =N19-N12
A21: Próximo ajuste | B21: =IF(N18=1,INDEX(B28:B88,N17+1),IF(N5=1,"No quedan ajustes antes de que termine","")) | N21: =INDEX(IPC!$D$5:$D$173,(N12)-IPC!$J$2+1)/INDEX(IPC!$D$5:$D$173,(N12-1)-IPC!$J$2+1)-1
A22: Próximo alquiler estimado | B22: =N22 | N22: =IF(AND(N18=1,N10=1,N14=1,N20>0,N20<=12),N16*INDEX(IPC!$D$5:$D$173,(N12)-IPC!$J$2+1)*(1+N21)^N20/INDEX(IPC!$D$5:$D$173,(N19-N8)-IPC!$J$2+1),"")
A23: Último mes del contrato | B23: =IF(N5=1,INDEX(IPC!$J$5:$J$16,MOD(N7+B10-1,12)+1)&" de "&INT((N7+B10-1)/12),"") | N23: =IF(ISNUMBER(N22),ROUND(N22,0),"")
A24: Qué hacer ahora | B24: =IF(N5=0,"Completá las celdas amarillas de arriba y acá aparece el cronograma de aumentos.",IF(N14=0,"Todavía no está publicado el IPC de "&INDEX(IPC!$J$5:$J$16,MOD(N7-1-N9,12)+1)&" de "&INT((N7-1-N9)/12)&", que es la base de este contrato. Mientras tanto se cobra el valor inicial.",IF(N18=0,"No quedan ajustes: el contrato termina en "&INDEX(IPC!$J$5:$J$16,MOD(N7+B10-1,12)+1)&" de "&INT((N7+B10-1)/12)&".",IF(N10=1,"El próximo ajuste rige desde "&B21&". Se calcula cuando el INDEC publique el IPC de "&INDEX(IPC!$J$5:$J$16,MOD(N19,12)+1)&" de "&INT((N19)/12)&" (sale entre el 10 y el 15 del mes siguiente)"&IF(ISNUMBER(N22),". Si la inflación siguiera como el último mes, el alquiler quedaría en unos $ "&N24&".","."),"El próximo ajuste rige desde "&B21&": cuando lo tengas, cargá el % del índice pactado en la columna F del cronograma.")))) | N24: =IF(ISNUMBER(N23),IF(N23>=1000000000,INT(N23/1000000000)&"."&RIGHT("00"&INT(MOD(N23,1000000000)/1000000),3)&"."&RIGHT("00"&INT(MOD(N23,1000000)/1000),3)&"."&RIGHT("00"&INT(MOD(N23,1000)/1),3),IF(N23>=1000000,INT(N23/1000000)&"."&RIGHT("00"&INT(MOD(N23,1000000)/1000),3)&"."&RIGHT("00"&INT(MOD(N23,1000)/1),3),IF(N23>=1000,INT(N23/1000)&"."&RIGHT("00"&INT(MOD(N23,1000)/1),3),""&N23))),"")
A26: CRONOGRAMA DE AJUSTES
A27: Ajuste | B27: Rige desde | C27: Mes del IPC base | D27: Mes del IPC final | E27: Variación | F27: % a mano (otro índice) | G27: Alquiler | H27: Estado
A28: =IF($N$5=1,"Valor inicial","") | B28: =IF($N$5=1,INDEX(IPC!$J$5:$J$16,MOD(J28,12)+1)&" de "&INT((J28)/12),"") | G28: =IF($N$5=1,B11,"") | H28: =IF($N$5=1,"Valor inicial del contrato","") | J28: =IF($N$5=1,$N$7+0*$N$8,"") | K28: =IF($N$5=1,J28-1-$N$9,"") | L28: =IF($N$5=1,K28-$N$8,"")
A29: =IF(AND($N$5=1,1<=$N$11),"1° ajuste","") | B29: =IF(AND($N$5=1,1<=$N$11),INDEX(IPC!$J$5:$J$16,MOD(J29,12)+1)&" de "&INT((J29)/12),"") | C29: =IF(AND(AND($N$5=1,1<=$N$11),$N$10=1),INDEX(IPC!$J$5:$J$16,MOD(L29,12)+1)&" de "&INT((L29)/12),"") | D29: =IF(AND(AND($N$5=1,1<=$N$11),$N$10=1),INDEX(IPC!$J$5:$J$16,MOD(K29,12)+1)&" de "&INT((K29)/12),"") | E29: =IF(NOT(AND($N$5=1,1<=$N$11)),"",IF($N$10=1,IF(AND($N$14=1,K29<=$N$12),INDEX(IPC!$D$5:$D$173,(K29)-IPC!$J$2+1)/INDEX(IPC!$D$5:$D$173,(L29)-IPC!$J$2+1)-1,""),IF(ISNUMBER(F29),F29/100,""))) | G29: =IF(AND(AND($N$5=1,1<=$N$11),ISNUMBER(G28),ISNUMBER(E29)),G28*(1+E29),"") | H29: =IF(NOT(AND($N$5=1,1<=$N$11)),"",IF(ISNUMBER(G29),"Aplicado",IF(ISNUMBER(G28),IF($N$10=1,"Falta el IPC de "&INDEX(IPC!$J$5:$J$16,MOD($N$12+1,12)+1)&" de "&INT(($N$12+1)/12),"Cargá el % de este ajuste en la columna F"),""))) | J29: =IF($N$5=1,$N$7+1*$N$8,"") | K29: =IF($N$5=1,J29-1-$N$9,"") | L29: =IF($N$5=1,K29-$N$8,"")
A30: =IF(AND($N$5=1,2<=$N$11),"2° ajuste","") | B30: =IF(AND($N$5=1,2<=$N$11),INDEX(IPC!$J$5:$J$16,MOD(J30,12)+1)&" de "&INT((J30)/12),"") | C30: =IF(AND(AND($N$5=1,2<=$N$11),$N$10=1),INDEX(IPC!$J$5:$J$16,MOD(L30,12)+1)&" de "&INT((L30)/12),"") | D30: =IF(AND(AND($N$5=1,2<=$N$11),$N$10=1),INDEX(IPC!$J$5:$J$16,MOD(K30,12)+1)&" de "&INT((K30)/12),"") | E30: =IF(NOT(AND($N$5=1,2<=$N$11)),"",IF($N$10=1,IF(AND($N$14=1,K30<=$N$12),INDEX(IPC!$D$5:$D$173,(K30)-IPC!$J$2+1)/INDEX(IPC!$D$5:$D$173,(L30)-IPC!$J$2+1)-1,""),IF(ISNUMBER(F30),F30/100,""))) | G30: =IF(AND(AND($N$5=1,2<=$N$11),ISNUMBER(G29),ISNUMBER(E30)),G29*(1+E30),"") | H30: =IF(NOT(AND($N$5=1,2<=$N$11)),"",IF(ISNUMBER(G30),"Aplicado",IF(ISNUMBER(G29),IF($N$10=1,"Falta el IPC de "&INDEX(IPC!$J$5:$J$16,MOD($N$12+1,12)+1)&" de "&INT(($N$12+1)/12),"Cargá el % de este ajuste en la columna F"),""))) | J30: =IF($N$5=1,$N$7+2*$N$8,"") | K30: =IF($N$5=1,J30-1-$N$9,"") | L30: =IF($N$5=1,K30-$N$8,"")
A31: =IF(AND($N$5=1,3<=$N$11),"3° ajuste","") | B31: =IF(AND($N$5=1,3<=$N$11),INDEX(IPC!$J$5:$J$16,MOD(J31,12)+1)&" de "&INT((J31)/12),"") | C31: =IF(AND(AND($N$5=1,3<=$N$11),$N$10=1),INDEX(IPC!$J$5:$J$16,MOD(L31,12)+1)&" de "&INT((L31)/12),"") | D31: =IF(AND(AND($N$5=1,3<=$N$11),$N$10=1),INDEX(IPC!$J$5:$J$16,MOD(K31,12)+1)&" de "&INT((K31)/12),"") | E31: =IF(NOT(AND($N$5=1,3<=$N$11)),"",IF($N$10=1,IF(AND($N$14=1,K31<=$N$12),INDEX(IPC!$D$5:$D$173,(K31)-IPC!$J$2+1)/INDEX(IPC!$D$5:$D$173,(L31)-IPC!$J$2+1)-1,""),IF(ISNUMBER(F31),F31/100,""))) | G31: =IF(AND(AND($N$5=1,3<=$N$11),ISNUMBER(G30),ISNUMBER(E31)),G30*(1+E31),"") | H31: =IF(NOT(AND($N$5=1,3<=$N$11)),"",IF(ISNUMBER(G31),"Aplicado",IF(ISNUMBER(G30),IF($N$10=1,"Falta el IPC de "&INDEX(IPC!$J$5:$J$16,MOD($N$12+1,12)+1)&" de "&INT(($N$12+1)/12),"Cargá el % de este ajuste en la columna F"),""))) | J31: =IF($N$5=1,$N$7+3*$N$8,"") | K31: =IF($N$5=1,J31-1-$N$9,"") | L31: =IF($N$5=1,K31-$N$8,"")
A32: =IF(AND($N$5=1,4<=$N$11),"4° ajuste","") | B32: =IF(AND($N$5=1,4<=$N$11),INDEX(IPC!$J$5:$J$16,MOD(J32,12)+1)&" de "&INT((J32)/12),"") | C32: =IF(AND(AND($N$5=1,4<=$N$11),$N$10=1),INDEX(IPC!$J$5:$J$16,MOD(L32,12)+1)&" de "&INT((L32)/12),"") | D32: =IF(AND(AND($N$5=1,4<=$N$11),$N$10=1),INDEX(IPC!$J$5:$J$16,MOD(K32,12)+1)&" de "&INT((K32)/12),"") | E32: =IF(NOT(AND($N$5=1,4<=$N$11)),"",IF($N$10=1,IF(AND($N$14=1,K32<=$N$12),INDEX(IPC!$D$5:$D$173,(K32)-IPC!$J$2+1)/INDEX(IPC!$D$5:$D$173,(L32)-IPC!$J$2+1)-1,""),IF(ISNUMBER(F32),F32/100,""))) | G32: =IF(AND(AND($N$5=1,4<=$N$11),ISNUMBER(G31),ISNUMBER(E32)),G31*(1+E32),"") | H32: =IF(NOT(AND($N$5=1,4<=$N$11)),"",IF(ISNUMBER(G32),"Aplicado",IF(ISNUMBER(G31),IF($N$10=1,"Falta el IPC de "&INDEX(IPC!$J$5:$J$16,MOD($N$12+1,12)+1)&" de "&INT(($N$12+1)/12),"Cargá el % de este ajuste en la columna F"),""))) | J32: =IF($N$5=1,$N$7+4*$N$8,"") | K32: =IF($N$5=1,J32-1-$N$9,"") | L32: =IF($N$5=1,K32-$N$8,"")
A33: =IF(AND($N$5=1,5<=$N$11),"5° ajuste","") | B33: =IF(AND($N$5=1,5<=$N$11),INDEX(IPC!$J$5:$J$16,MOD(J33,12)+1)&" de "&INT((J33)/12),"") | C33: =IF(AND(AND($N$5=1,5<=$N$11),$N$10=1),INDEX(IPC!$J$5:$J$16,MOD(L33,12)+1)&" de "&INT((L33)/12),"") | D33: =IF(AND(AND($N$5=1,5<=$N$11),$N$10=1),INDEX(IPC!$J$5:$J$16,MOD(K33,12)+1)&" de "&INT((K33)/12),"") | E33: =IF(NOT(AND($N$5=1,5<=$N$11)),"",IF($N$10=1,IF(AND($N$14=1,K33<=$N$12),INDEX(IPC!$D$5:$D$173,(K33)-IPC!$J$2+1)/INDEX(IPC!$D$5:$D$173,(L33)-IPC!$J$2+1)-1,""),IF(ISNUMBER(F33),F33/100,""))) | G33: =IF(AND(AND($N$5=1,5<=$N$11),ISNUMBER(G32),ISNUMBER(E33)),G32*(1+E33),"") | H33: =IF(NOT(AND($N$5=1,5<=$N$11)),"",IF(ISNUMBER(G33),"Aplicado",IF(ISNUMBER(G32),IF($N$10=1,"Falta el IPC de "&INDEX(IPC!$J$5:$J$16,MOD($N$12+1,12)+1)&" de "&INT(($N$12+1)/12),"Cargá el % de este ajuste en la columna F"),""))) | J33: =IF($N$5=1,$N$7+5*$N$8,"") | K33: =IF($N$5=1,J33-1-$N$9,"") | L33: =IF($N$5=1,K33-$N$8,"")
A34: =IF(AND($N$5=1,6<=$N$11),"6° ajuste","") | B34: =IF(AND($N$5=1,6<=$N$11),INDEX(IPC!$J$5:$J$16,MOD(J34,12)+1)&" de "&INT((J34)/12),"") | C34: =IF(AND(AND($N$5=1,6<=$N$11),$N$10=1),INDEX(IPC!$J$5:$J$16,MOD(L34,12)+1)&" de "&INT((L34)/12),"") | D34: =IF(AND(AND($N$5=1,6<=$N$11),$N$10=1),INDEX(IPC!$J$5:$J$16,MOD(K34,12)+1)&" de "&INT((K34)/12),"") | E34: =IF(NOT(AND($N$5=1,6<=$N$11)),"",IF($N$10=1,IF(AND($N$14=1,K34<=$N$12),INDEX(IPC!$D$5:$D$173,(K34)-IPC!$J$2+1)/INDEX(IPC!$D$5:$D$173,(L34)-IPC!$J$2+1)-1,""),IF(ISNUMBER(F34),F34/100,""))) | G34: =IF(AND(AND($N$5=1,6<=$N$11),ISNUMBER(G33),ISNUMBER(E34)),G33*(1+E34),"") | H34: =IF(NOT(AND($N$5=1,6<=$N$11)),"",IF(ISNUMBER(G34),"Aplicado",IF(ISNUMBER(G33),IF($N$10=1,"Falta el IPC de "&INDEX(IPC!$J$5:$J$16,MOD($N$12+1,12)+1)&" de "&INT(($N$12+1)/12),"Cargá el % de este ajuste en la columna F"),""))) | J34: =IF($N$5=1,$N$7+6*$N$8,"") | K34: =IF($N$5=1,J34-1-$N$9,"") | L34: =IF($N$5=1,K34-$N$8,"")
A35: =IF(AND($N$5=1,7<=$N$11),"7° ajuste","") | B35: =IF(AND($N$5=1,7<=$N$11),INDEX(IPC!$J$5:$J$16,MOD(J35,12)+1)&" de "&INT((J35)/12),"") | C35: =IF(AND(AND($N$5=1,7<=$N$11),$N$10=1),INDEX(IPC!$J$5:$J$16,MOD(L35,12)+1)&" de "&INT((L35)/12),"") | D35: =IF(AND(AND($N$5=1,7<=$N$11),$N$10=1),INDEX(IPC!$J$5:$J$16,MOD(K35,12)+1)&" de "&INT((K35)/12),"") | E35: =IF(NOT(AND($N$5=1,7<=$N$11)),"",IF($N$10=1,IF(AND($N$14=1,K35<=$N$12),INDEX(IPC!$D$5:$D$173,(K35)-IPC!$J$2+1)/INDEX(IPC!$D$5:$D$173,(L35)-IPC!$J$2+1)-1,""),IF(ISNUMBER(F35),F35/100,""))) | G35: =IF(AND(AND($N$5=1,7<=$N$11),ISNUMBER(G34),ISNUMBER(E35)),G34*(1+E35),"") | H35: =IF(NOT(AND($N$5=1,7<=$N$11)),"",IF(ISNUMBER(G35),"Aplicado",IF(ISNUMBER(G34),IF($N$10=1,"Falta el IPC de "&INDEX(IPC!$J$5:$J$16,MOD($N$12+1,12)+1)&" de "&INT(($N$12+1)/12),"Cargá el % de este ajuste en la columna F"),""))) | J35: =IF($N$5=1,$N$7+7*$N$8,"") | K35: =IF($N$5=1,J35-1-$N$9,"") | L35: =IF($N$5=1,K35-$N$8,"")
A36: =IF(AND($N$5=1,8<=$N$11),"8° ajuste","") | B36: =IF(AND($N$5=1,8<=$N$11),INDEX(IPC!$J$5:$J$16,MOD(J36,12)+1)&" de "&INT((J36)/12),"") | C36: =IF(AND(AND($N$5=1,8<=$N$11),$N$10=1),INDEX(IPC!$J$5:$J$16,MOD(L36,12)+1)&" de "&INT((L36)/12),"") | D36: =IF(AND(AND($N$5=1,8<=$N$11),$N$10=1),INDEX(IPC!$J$5:$J$16,MOD(K36,12)+1)&" de "&INT((K36)/12),"") | E36: =IF(NOT(AND($N$5=1,8<=$N$11)),"",IF($N$10=1,IF(AND($N$14=1,K36<=$N$12),INDEX(IPC!$D$5:$D$173,(K36)-IPC!$J$2+1)/INDEX(IPC!$D$5:$D$173,(L36)-IPC!$J$2+1)-1,""),IF(ISNUMBER(F36),F36/100,""))) | G36: =IF(AND(AND($N$5=1,8<=$N$11),ISNUMBER(G35),ISNUMBER(E36)),G35*(1+E36),"") | H36: =IF(NOT(AND($N$5=1,8<=$N$11)),"",IF(ISNUMBER(G36),"Aplicado",IF(ISNUMBER(G35),IF($N$10=1,"Falta el IPC de "&INDEX(IPC!$J$5:$J$16,MOD($N$12+1,12)+1)&" de "&INT(($N$12+1)/12),"Cargá el % de este ajuste en la columna F"),""))) | J36: =IF($N$5=1,$N$7+8*$N$8,"") | K36: =IF($N$5=1,J36-1-$N$9,"") | L36: =IF($N$5=1,K36-$N$8,"")
A37: =IF(AND($N$5=1,9<=$N$11),"9° ajuste","") | B37: =IF(AND($N$5=1,9<=$N$11),INDEX(IPC!$J$5:$J$16,MOD(J37,12)+1)&" de "&INT((J37)/12),"") | C37: =IF(AND(AND($N$5=1,9<=$N$11),$N$10=1),INDEX(IPC!$J$5:$J$16,MOD(L37,12)+1)&" de "&INT((L37)/12),"") | D37: =IF(AND(AND($N$5=1,9<=$N$11),$N$10=1),INDEX(IPC!$J$5:$J$16,MOD(K37,12)+1)&" de "&INT((K37)/12),"") | E37: =IF(NOT(AND($N$5=1,9<=$N$11)),"",IF($N$10=1,IF(AND($N$14=1,K37<=$N$12),INDEX(IPC!$D$5:$D$173,(K37)-IPC!$J$2+1)/INDEX(IPC!$D$5:$D$173,(L37)-IPC!$J$2+1)-1,""),IF(ISNUMBER(F37),F37/100,""))) | G37: =IF(AND(AND($N$5=1,9<=$N$11),ISNUMBER(G36),ISNUMBER(E37)),G36*(1+E37),"") | H37: =IF(NOT(AND($N$5=1,9<=$N$11)),"",IF(ISNUMBER(G37),"Aplicado",IF(ISNUMBER(G36),IF($N$10=1,"Falta el IPC de "&INDEX(IPC!$J$5:$J$16,MOD($N$12+1,12)+1)&" de "&INT(($N$12+1)/12),"Cargá el % de este ajuste en la columna F"),""))) | J37: =IF($N$5=1,$N$7+9*$N$8,"") | K37: =IF($N$5=1,J37-1-$N$9,"") | L37: =IF($N$5=1,K37-$N$8,"")
A38: =IF(AND($N$5=1,10<=$N$11),"10° ajuste","") | B38: =IF(AND($N$5=1,10<=$N$11),INDEX(IPC!$J$5:$J$16,MOD(J38,12)+1)&" de "&INT((J38)/12),"") | C38: =IF(AND(AND($N$5=1,10<=$N$11),$N$10=1),INDEX(IPC!$J$5:$J$16,MOD(L38,12)+1)&" de "&INT((L38)/12),"") | D38: =IF(AND(AND($N$5=1,10<=$N$11),$N$10=1),INDEX(IPC!$J$5:$J$16,MOD(K38,12)+1)&" de "&INT((K38)/12),"") | E38: =IF(NOT(AND($N$5=1,10<=$N$11)),"",IF($N$10=1,IF(AND($N$14=1,K38<=$N$12),INDEX(IPC!$D$5:$D$173,(K38)-IPC!$J$2+1)/INDEX(IPC!$D$5:$D$173,(L38)-IPC!$J$2+1)-1,""),IF(ISNUMBER(F38),F38/100,""))) | G38: =IF(AND(AND($N$5=1,10<=$N$11),ISNUMBER(G37),ISNUMBER(E38)),G37*(1+E38),"") | H38: =IF(NOT(AND($N$5=1,10<=$N$11)),"",IF(ISNUMBER(G38),"Aplicado",IF(ISNUMBER(G37),IF($N$10=1,"Falta el IPC de "&INDEX(IPC!$J$5:$J$16,MOD($N$12+1,12)+1)&" de "&INT(($N$12+1)/12),"Cargá el % de este ajuste en la columna F"),""))) | J38: =IF($N$5=1,$N$7+10*$N$8,"") | K38: =IF($N$5=1,J38-1-$N$9,"") | L38: =IF($N$5=1,K38-$N$8,"")
A39: =IF(AND($N$5=1,11<=$N$11),"11° ajuste","") | B39: =IF(AND($N$5=1,11<=$N$11),INDEX(IPC!$J$5:$J$16,MOD(J39,12)+1)&" de "&INT((J39)/12),"") | C39: =IF(AND(AND($N$5=1,11<=$N$11),$N$10=1),INDEX(IPC!$J$5:$J$16,MOD(L39,12)+1)&" de "&INT((L39)/12),"") | D39: =IF(AND(AND($N$5=1,11<=$N$11),$N$10=1),INDEX(IPC!$J$5:$J$16,MOD(K39,12)+1)&" de "&INT((K39)/12),"") | E39: =IF(NOT(AND($N$5=1,11<=$N$11)),"",IF($N$10=1,IF(AND($N$14=1,K39<=$N$12),INDEX(IPC!$D$5:$D$173,(K39)-IPC!$J$2+1)/INDEX(IPC!$D$5:$D$173,(L39)-IPC!$J$2+1)-1,""),IF(ISNUMBER(F39),F39/100,""))) | G39: =IF(AND(AND($N$5=1,11<=$N$11),ISNUMBER(G38),ISNUMBER(E39)),G38*(1+E39),"") | H39: =IF(NOT(AND($N$5=1,11<=$N$11)),"",IF(ISNUMBER(G39),"Aplicado",IF(ISNUMBER(G38),IF($N$10=1,"Falta el IPC de "&INDEX(IPC!$J$5:$J$16,MOD($N$12+1,12)+1)&" de "&INT(($N$12+1)/12),"Cargá el % de este ajuste en la columna F"),""))) | J39: =IF($N$5=1,$N$7+11*$N$8,"") | K39: =IF($N$5=1,J39-1-$N$9,"") | L39: =IF($N$5=1,K39-$N$8,"")
A40: =IF(AND($N$5=1,12<=$N$11),"12° ajuste","") | B40: =IF(AND($N$5=1,12<=$N$11),INDEX(IPC!$J$5:$J$16,MOD(J40,12)+1)&" de "&INT((J40)/12),"") | C40: =IF(AND(AND($N$5=1,12<=$N$11),$N$10=1),INDEX(IPC!$J$5:$J$16,MOD(L40,12)+1)&" de "&INT((L40)/12),"") | D40: =IF(AND(AND($N$5=1,12<=$N$11),$N$10=1),INDEX(IPC!$J$5:$J$16,MOD(K40,12)+1)&" de "&INT((K40)/12),"") | E40: =IF(NOT(AND($N$5=1,12<=$N$11)),"",IF($N$10=1,IF(AND($N$14=1,K40<=$N$12),INDEX(IPC!$D$5:$D$173,(K40)-IPC!$J$2+1)/INDEX(IPC!$D$5:$D$173,(L40)-IPC!$J$2+1)-1,""),IF(ISNUMBER(F40),F40/100,""))) | G40: =IF(AND(AND($N$5=1,12<=$N$11),ISNUMBER(G39),ISNUMBER(E40)),G39*(1+E40),"") | H40: =IF(NOT(AND($N$5=1,12<=$N$11)),"",IF(ISNUMBER(G40),"Aplicado",IF(ISNUMBER(G39),IF($N$10=1,"Falta el IPC de "&INDEX(IPC!$J$5:$J$16,MOD($N$12+1,12)+1)&" de "&INT(($N$12+1)/12),"Cargá el % de este ajuste en la columna F"),""))) | J40: =IF($N$5=1,$N$7+12*$N$8,"") | K40: =IF($N$5=1,J40-1-$N$9,"") | L40: =IF($N$5=1,K40-$N$8,"")
A41: =IF(AND($N$5=1,13<=$N$11),"13° ajuste","") | B41: =IF(AND($N$5=1,13<=$N$11),INDEX(IPC!$J$5:$J$16,MOD(J41,12)+1)&" de "&INT((J41)/12),"") | C41: =IF(AND(AND($N$5=1,13<=$N$11),$N$10=1),INDEX(IPC!$J$5:$J$16,MOD(L41,12)+1)&" de "&INT((L41)/12),"") | D41: =IF(AND(AND($N$5=1,13<=$N$11),$N$10=1),INDEX(IPC!$J$5:$J$16,MOD(K41,12)+1)&" de "&INT((K41)/12),"") | E41: =IF(NOT(AND($N$5=1,13<=$N$11)),"",IF($N$10=1,IF(AND($N$14=1,K41<=$N$12),INDEX(IPC!$D$5:$D$173,(K41)-IPC!$J$2+1)/INDEX(IPC!$D$5:$D$173,(L41)-IPC!$J$2+1)-1,""),IF(ISNUMBER(F41),F41/100,""))) | G41: =IF(AND(AND($N$5=1,13<=$N$11),ISNUMBER(G40),ISNUMBER(E41)),G40*(1+E41),"") | H41: =IF(NOT(AND($N$5=1,13<=$N$11)),"",IF(ISNUMBER(G41),"Aplicado",IF(ISNUMBER(G40),IF($N$10=1,"Falta el IPC de "&INDEX(IPC!$J$5:$J$16,MOD($N$12+1,12)+1)&" de "&INT(($N$12+1)/12),"Cargá el % de este ajuste en la columna F"),""))) | J41: =IF($N$5=1,$N$7+13*$N$8,"") | K41: =IF($N$5=1,J41-1-$N$9,"") | L41: =IF($N$5=1,K41-$N$8,"")
A42: =IF(AND($N$5=1,14<=$N$11),"14° ajuste","") | B42: =IF(AND($N$5=1,14<=$N$11),INDEX(IPC!$J$5:$J$16,MOD(J42,12)+1)&" de "&INT((J42)/12),"") | C42: =IF(AND(AND($N$5=1,14<=$N$11),$N$10=1),INDEX(IPC!$J$5:$J$16,MOD(L42,12)+1)&" de "&INT((L42)/12),"") | D42: =IF(AND(AND($N$5=1,14<=$N$11),$N$10=1),INDEX(IPC!$J$5:$J$16,MOD(K42,12)+1)&" de "&INT((K42)/12),"") | E42: =IF(NOT(AND($N$5=1,14<=$N$11)),"",IF($N$10=1,IF(AND($N$14=1,K42<=$N$12),INDEX(IPC!$D$5:$D$173,(K42)-IPC!$J$2+1)/INDEX(IPC!$D$5:$D$173,(L42)-IPC!$J$2+1)-1,""),IF(ISNUMBER(F42),F42/100,""))) | G42: =IF(AND(AND($N$5=1,14<=$N$11),ISNUMBER(G41),ISNUMBER(E42)),G41*(1+E42),"") | H42: =IF(NOT(AND($N$5=1,14<=$N$11)),"",IF(ISNUMBER(G42),"Aplicado",IF(ISNUMBER(G41),IF($N$10=1,"Falta el IPC de "&INDEX(IPC!$J$5:$J$16,MOD($N$12+1,12)+1)&" de "&INT(($N$12+1)/12),"Cargá el % de este ajuste en la columna F"),""))) | J42: =IF($N$5=1,$N$7+14*$N$8,"") | K42: =IF($N$5=1,J42-1-$N$9,"") | L42: =IF($N$5=1,K42-$N$8,"")
A43: =IF(AND($N$5=1,15<=$N$11),"15° ajuste","") | B43: =IF(AND($N$5=1,15<=$N$11),INDEX(IPC!$J$5:$J$16,MOD(J43,12)+1)&" de "&INT((J43)/12),"") | C43: =IF(AND(AND($N$5=1,15<=$N$11),$N$10=1),INDEX(IPC!$J$5:$J$16,MOD(L43,12)+1)&" de "&INT((L43)/12),"") | D43: =IF(AND(AND($N$5=1,15<=$N$11),$N$10=1),INDEX(IPC!$J$5:$J$16,MOD(K43,12)+1)&" de "&INT((K43)/12),"") | E43: =IF(NOT(AND($N$5=1,15<=$N$11)),"",IF($N$10=1,IF(AND($N$14=1,K43<=$N$12),INDEX(IPC!$D$5:$D$173,(K43)-IPC!$J$2+1)/INDEX(IPC!$D$5:$D$173,(L43)-IPC!$J$2+1)-1,""),IF(ISNUMBER(F43),F43/100,""))) | G43: =IF(AND(AND($N$5=1,15<=$N$11),ISNUMBER(G42),ISNUMBER(E43)),G42*(1+E43),"") | H43: =IF(NOT(AND($N$5=1,15<=$N$11)),"",IF(ISNUMBER(G43),"Aplicado",IF(ISNUMBER(G42),IF($N$10=1,"Falta el IPC de "&INDEX(IPC!$J$5:$J$16,MOD($N$12+1,12)+1)&" de "&INT(($N$12+1)/12),"Cargá el % de este ajuste en la columna F"),""))) | J43: =IF($N$5=1,$N$7+15*$N$8,"") | K43: =IF($N$5=1,J43-1-$N$9,"") | L43: =IF($N$5=1,K43-$N$8,"")
A44: =IF(AND($N$5=1,16<=$N$11),"16° ajuste","") | B44: =IF(AND($N$5=1,16<=$N$11),INDEX(IPC!$J$5:$J$16,MOD(J44,12)+1)&" de "&INT((J44)/12),"") | C44: =IF(AND(AND($N$5=1,16<=$N$11),$N$10=1),INDEX(IPC!$J$5:$J$16,MOD(L44,12)+1)&" de "&INT((L44)/12),"") | D44: =IF(AND(AND($N$5=1,16<=$N$11),$N$10=1),INDEX(IPC!$J$5:$J$16,MOD(K44,12)+1)&" de "&INT((K44)/12),"") | E44: =IF(NOT(AND($N$5=1,16<=$N$11)),"",IF($N$10=1,IF(AND($N$14=1,K44<=$N$12),INDEX(IPC!$D$5:$D$173,(K44)-IPC!$J$2+1)/INDEX(IPC!$D$5:$D$173,(L44)-IPC!$J$2+1)-1,""),IF(ISNUMBER(F44),F44/100,""))) | G44: =IF(AND(AND($N$5=1,16<=$N$11),ISNUMBER(G43),ISNUMBER(E44)),G43*(1+E44),"") | H44: =IF(NOT(AND($N$5=1,16<=$N$11)),"",IF(ISNUMBER(G44),"Aplicado",IF(ISNUMBER(G43),IF($N$10=1,"Falta el IPC de "&INDEX(IPC!$J$5:$J$16,MOD($N$12+1,12)+1)&" de "&INT(($N$12+1)/12),"Cargá el % de este ajuste en la columna F"),""))) | J44: =IF($N$5=1,$N$7+16*$N$8,"") | K44: =IF($N$5=1,J44-1-$N$9,"") | L44: =IF($N$5=1,K44-$N$8,"")
A45: =IF(AND($N$5=1,17<=$N$11),"17° ajuste","") | B45: =IF(AND($N$5=1,17<=$N$11),INDEX(IPC!$J$5:$J$16,MOD(J45,12)+1)&" de "&INT((J45)/12),"") | C45: =IF(AND(AND($N$5=1,17<=$N$11),$N$10=1),INDEX(IPC!$J$5:$J$16,MOD(L45,12)+1)&" de "&INT((L45)/12),"") | D45: =IF(AND(AND($N$5=1,17<=$N$11),$N$10=1),INDEX(IPC!$J$5:$J$16,MOD(K45,12)+1)&" de "&INT((K45)/12),"") | E45: =IF(NOT(AND($N$5=1,17<=$N$11)),"",IF($N$10=1,IF(AND($N$14=1,K45<=$N$12),INDEX(IPC!$D$5:$D$173,(K45)-IPC!$J$2+1)/INDEX(IPC!$D$5:$D$173,(L45)-IPC!$J$2+1)-1,""),IF(ISNUMBER(F45),F45/100,""))) | G45: =IF(AND(AND($N$5=1,17<=$N$11),ISNUMBER(G44),ISNUMBER(E45)),G44*(1+E45),"") | H45: =IF(NOT(AND($N$5=1,17<=$N$11)),"",IF(ISNUMBER(G45),"Aplicado",IF(ISNUMBER(G44),IF($N$10=1,"Falta el IPC de "&INDEX(IPC!$J$5:$J$16,MOD($N$12+1,12)+1)&" de "&INT(($N$12+1)/12),"Cargá el % de este ajuste en la columna F"),""))) | J45: =IF($N$5=1,$N$7+17*$N$8,"") | K45: =IF($N$5=1,J45-1-$N$9,"") | L45: =IF($N$5=1,K45-$N$8,"")
A46: =IF(AND($N$5=1,18<=$N$11),"18° ajuste","") | B46: =IF(AND($N$5=1,18<=$N$11),INDEX(IPC!$J$5:$J$16,MOD(J46,12)+1)&" de "&INT((J46)/12),"") | C46: =IF(AND(AND($N$5=1,18<=$N$11),$N$10=1),INDEX(IPC!$J$5:$J$16,MOD(L46,12)+1)&" de "&INT((L46)/12),"") | D46: =IF(AND(AND($N$5=1,18<=$N$11),$N$10=1),INDEX(IPC!$J$5:$J$16,MOD(K46,12)+1)&" de "&INT((K46)/12),"") | E46: =IF(NOT(AND($N$5=1,18<=$N$11)),"",IF($N$10=1,IF(AND($N$14=1,K46<=$N$12),INDEX(IPC!$D$5:$D$173,(K46)-IPC!$J$2+1)/INDEX(IPC!$D$5:$D$173,(L46)-IPC!$J$2+1)-1,""),IF(ISNUMBER(F46),F46/100,""))) | G46: =IF(AND(AND($N$5=1,18<=$N$11),ISNUMBER(G45),ISNUMBER(E46)),G45*(1+E46),"") | H46: =IF(NOT(AND($N$5=1,18<=$N$11)),"",IF(ISNUMBER(G46),"Aplicado",IF(ISNUMBER(G45),IF($N$10=1,"Falta el IPC de "&INDEX(IPC!$J$5:$J$16,MOD($N$12+1,12)+1)&" de "&INT(($N$12+1)/12),"Cargá el % de este ajuste en la columna F"),""))) | J46: =IF($N$5=1,$N$7+18*$N$8,"") | K46: =IF($N$5=1,J46-1-$N$9,"") | L46: =IF($N$5=1,K46-$N$8,"")
A47: =IF(AND($N$5=1,19<=$N$11),"19° ajuste","") | B47: =IF(AND($N$5=1,19<=$N$11),INDEX(IPC!$J$5:$J$16,MOD(J47,12)+1)&" de "&INT((J47)/12),"") | C47: =IF(AND(AND($N$5=1,19<=$N$11),$N$10=1),INDEX(IPC!$J$5:$J$16,MOD(L47,12)+1)&" de "&INT((L47)/12),"") | D47: =IF(AND(AND($N$5=1,19<=$N$11),$N$10=1),INDEX(IPC!$J$5:$J$16,MOD(K47,12)+1)&" de "&INT((K47)/12),"") | E47: =IF(NOT(AND($N$5=1,19<=$N$11)),"",IF($N$10=1,IF(AND($N$14=1,K47<=$N$12),INDEX(IPC!$D$5:$D$173,(K47)-IPC!$J$2+1)/INDEX(IPC!$D$5:$D$173,(L47)-IPC!$J$2+1)-1,""),IF(ISNUMBER(F47),F47/100,""))) | G47: =IF(AND(AND($N$5=1,19<=$N$11),ISNUMBER(G46),ISNUMBER(E47)),G46*(1+E47),"") | H47: =IF(NOT(AND($N$5=1,19<=$N$11)),"",IF(ISNUMBER(G47),"Aplicado",IF(ISNUMBER(G46),IF($N$10=1,"Falta el IPC de "&INDEX(IPC!$J$5:$J$16,MOD($N$12+1,12)+1)&" de "&INT(($N$12+1)/12),"Cargá el % de este ajuste en la columna F"),""))) | J47: =IF($N$5=1,$N$7+19*$N$8,"") | K47: =IF($N$5=1,J47-1-$N$9,"") | L47: =IF($N$5=1,K47-$N$8,"")
A48: =IF(AND($N$5=1,20<=$N$11),"20° ajuste","") | B48: =IF(AND($N$5=1,20<=$N$11),INDEX(IPC!$J$5:$J$16,MOD(J48,12)+1)&" de "&INT((J48)/12),"") | C48: =IF(AND(AND($N$5=1,20<=$N$11),$N$10=1),INDEX(IPC!$J$5:$J$16,MOD(L48,12)+1)&" de "&INT((L48)/12),"") | D48: =IF(AND(AND($N$5=1,20<=$N$11),$N$10=1),INDEX(IPC!$J$5:$J$16,MOD(K48,12)+1)&" de "&INT((K48)/12),"") | E48: =IF(NOT(AND($N$5=1,20<=$N$11)),"",IF($N$10=1,IF(AND($N$14=1,K48<=$N$12),INDEX(IPC!$D$5:$D$173,(K48)-IPC!$J$2+1)/INDEX(IPC!$D$5:$D$173,(L48)-IPC!$J$2+1)-1,""),IF(ISNUMBER(F48),F48/100,""))) | G48: =IF(AND(AND($N$5=1,20<=$N$11),ISNUMBER(G47),ISNUMBER(E48)),G47*(1+E48),"") | H48: =IF(NOT(AND($N$5=1,20<=$N$11)),"",IF(ISNUMBER(G48),"Aplicado",IF(ISNUMBER(G47),IF($N$10=1,"Falta el IPC de "&INDEX(IPC!$J$5:$J$16,MOD($N$12+1,12)+1)&" de "&INT(($N$12+1)/12),"Cargá el % de este ajuste en la columna F"),""))) | J48: =IF($N$5=1,$N$7+20*$N$8,"") | K48: =IF($N$5=1,J48-1-$N$9,"") | L48: =IF($N$5=1,K48-$N$8,"")
A49: =IF(AND($N$5=1,21<=$N$11),"21° ajuste","") | B49: =IF(AND($N$5=1,21<=$N$11),INDEX(IPC!$J$5:$J$16,MOD(J49,12)+1)&" de "&INT((J49)/12),"") | C49: =IF(AND(AND($N$5=1,21<=$N$11),$N$10=1),INDEX(IPC!$J$5:$J$16,MOD(L49,12)+1)&" de "&INT((L49)/12),"") | D49: =IF(AND(AND($N$5=1,21<=$N$11),$N$10=1),INDEX(IPC!$J$5:$J$16,MOD(K49,12)+1)&" de "&INT((K49)/12),"") | E49: =IF(NOT(AND($N$5=1,21<=$N$11)),"",IF($N$10=1,IF(AND($N$14=1,K49<=$N$12),INDEX(IPC!$D$5:$D$173,(K49)-IPC!$J$2+1)/INDEX(IPC!$D$5:$D$173,(L49)-IPC!$J$2+1)-1,""),IF(ISNUMBER(F49),F49/100,""))) | G49: =IF(AND(AND($N$5=1,21<=$N$11),ISNUMBER(G48),ISNUMBER(E49)),G48*(1+E49),"") | H49: =IF(NOT(AND($N$5=1,21<=$N$11)),"",IF(ISNUMBER(G49),"Aplicado",IF(ISNUMBER(G48),IF($N$10=1,"Falta el IPC de "&INDEX(IPC!$J$5:$J$16,MOD($N$12+1,12)+1)&" de "&INT(($N$12+1)/12),"Cargá el % de este ajuste en la columna F"),""))) | J49: =IF($N$5=1,$N$7+21*$N$8,"") | K49: =IF($N$5=1,J49-1-$N$9,"") | L49: =IF($N$5=1,K49-$N$8,"")
A50: =IF(AND($N$5=1,22<=$N$11),"22° ajuste","") | B50: =IF(AND($N$5=1,22<=$N$11),INDEX(IPC!$J$5:$J$16,MOD(J50,12)+1)&" de "&INT((J50)/12),"") | C50: =IF(AND(AND($N$5=1,22<=$N$11),$N$10=1),INDEX(IPC!$J$5:$J$16,MOD(L50,12)+1)&" de "&INT((L50)/12),"") | D50: =IF(AND(AND($N$5=1,22<=$N$11),$N$10=1),INDEX(IPC!$J$5:$J$16,MOD(K50,12)+1)&" de "&INT((K50)/12),"") | E50: =IF(NOT(AND($N$5=1,22<=$N$11)),"",IF($N$10=1,IF(AND($N$14=1,K50<=$N$12),INDEX(IPC!$D$5:$D$173,(K50)-IPC!$J$2+1)/INDEX(IPC!$D$5:$D$173,(L50)-IPC!$J$2+1)-1,""),IF(ISNUMBER(F50),F50/100,""))) | G50: =IF(AND(AND($N$5=1,22<=$N$11),ISNUMBER(G49),ISNUMBER(E50)),G49*(1+E50),"") | H50: =IF(NOT(AND($N$5=1,22<=$N$11)),"",IF(ISNUMBER(G50),"Aplicado",IF(ISNUMBER(G49),IF($N$10=1,"Falta el IPC de "&INDEX(IPC!$J$5:$J$16,MOD($N$12+1,12)+1)&" de "&INT(($N$12+1)/12),"Cargá el % de este ajuste en la columna F"),""))) | J50: =IF($N$5=1,$N$7+22*$N$8,"") | K50: =IF($N$5=1,J50-1-$N$9,"") | L50: =IF($N$5=1,K50-$N$8,"")
A51: =IF(AND($N$5=1,23<=$N$11),"23° ajuste","") | B51: =IF(AND($N$5=1,23<=$N$11),INDEX(IPC!$J$5:$J$16,MOD(J51,12)+1)&" de "&INT((J51)/12),"") | C51: =IF(AND(AND($N$5=1,23<=$N$11),$N$10=1),INDEX(IPC!$J$5:$J$16,MOD(L51,12)+1)&" de "&INT((L51)/12),"") | D51: =IF(AND(AND($N$5=1,23<=$N$11),$N$10=1),INDEX(IPC!$J$5:$J$16,MOD(K51,12)+1)&" de "&INT((K51)/12),"") | E51: =IF(NOT(AND($N$5=1,23<=$N$11)),"",IF($N$10=1,IF(AND($N$14=1,K51<=$N$12),INDEX(IPC!$D$5:$D$173,(K51)-IPC!$J$2+1)/INDEX(IPC!$D$5:$D$173,(L51)-IPC!$J$2+1)-1,""),IF(ISNUMBER(F51),F51/100,""))) | G51: =IF(AND(AND($N$5=1,23<=$N$11),ISNUMBER(G50),ISNUMBER(E51)),G50*(1+E51),"") | H51: =IF(NOT(AND($N$5=1,23<=$N$11)),"",IF(ISNUMBER(G51),"Aplicado",IF(ISNUMBER(G50),IF($N$10=1,"Falta el IPC de "&INDEX(IPC!$J$5:$J$16,MOD($N$12+1,12)+1)&" de "&INT(($N$12+1)/12),"Cargá el % de este ajuste en la columna F"),""))) | J51: =IF($N$5=1,$N$7+23*$N$8,"") | K51: =IF($N$5=1,J51-1-$N$9,"") | L51: =IF($N$5=1,K51-$N$8,"")
A52: =IF(AND($N$5=1,24<=$N$11),"24° ajuste","") | B52: =IF(AND($N$5=1,24<=$N$11),INDEX(IPC!$J$5:$J$16,MOD(J52,12)+1)&" de "&INT((J52)/12),"") | C52: =IF(AND(AND($N$5=1,24<=$N$11),$N$10=1),INDEX(IPC!$J$5:$J$16,MOD(L52,12)+1)&" de "&INT((L52)/12),"") | D52: =IF(AND(AND($N$5=1,24<=$N$11),$N$10=1),INDEX(IPC!$J$5:$J$16,MOD(K52,12)+1)&" de "&INT((K52)/12),"") | E52: =IF(NOT(AND($N$5=1,24<=$N$11)),"",IF($N$10=1,IF(AND($N$14=1,K52<=$N$12),INDEX(IPC!$D$5:$D$173,(K52)-IPC!$J$2+1)/INDEX(IPC!$D$5:$D$173,(L52)-IPC!$J$2+1)-1,""),IF(ISNUMBER(F52),F52/100,""))) | G52: =IF(AND(AND($N$5=1,24<=$N$11),ISNUMBER(G51),ISNUMBER(E52)),G51*(1+E52),"") | H52: =IF(NOT(AND($N$5=1,24<=$N$11)),"",IF(ISNUMBER(G52),"Aplicado",IF(ISNUMBER(G51),IF($N$10=1,"Falta el IPC de "&INDEX(IPC!$J$5:$J$16,MOD($N$12+1,12)+1)&" de "&INT(($N$12+1)/12),"Cargá el % de este ajuste en la columna F"),""))) | J52: =IF($N$5=1,$N$7+24*$N$8,"") | K52: =IF($N$5=1,J52-1-$N$9,"") | L52: =IF($N$5=1,K52-$N$8,"")
A53: =IF(AND($N$5=1,25<=$N$11),"25° ajuste","") | B53: =IF(AND($N$5=1,25<=$N$11),INDEX(IPC!$J$5:$J$16,MOD(J53,12)+1)&" de "&INT((J53)/12),"") | C53: =IF(AND(AND($N$5=1,25<=$N$11),$N$10=1),INDEX(IPC!$J$5:$J$16,MOD(L53,12)+1)&" de "&INT((L53)/12),"") | D53: =IF(AND(AND($N$5=1,25<=$N$11),$N$10=1),INDEX(IPC!$J$5:$J$16,MOD(K53,12)+1)&" de "&INT((K53)/12),"") | E53: =IF(NOT(AND($N$5=1,25<=$N$11)),"",IF($N$10=1,IF(AND($N$14=1,K53<=$N$12),INDEX(IPC!$D$5:$D$173,(K53)-IPC!$J$2+1)/INDEX(IPC!$D$5:$D$173,(L53)-IPC!$J$2+1)-1,""),IF(ISNUMBER(F53),F53/100,""))) | G53: =IF(AND(AND($N$5=1,25<=$N$11),ISNUMBER(G52),ISNUMBER(E53)),G52*(1+E53),"") | H53: =IF(NOT(AND($N$5=1,25<=$N$11)),"",IF(ISNUMBER(G53),"Aplicado",IF(ISNUMBER(G52),IF($N$10=1,"Falta el IPC de "&INDEX(IPC!$J$5:$J$16,MOD($N$12+1,12)+1)&" de "&INT(($N$12+1)/12),"Cargá el % de este ajuste en la columna F"),""))) | J53: =IF($N$5=1,$N$7+25*$N$8,"") | K53: =IF($N$5=1,J53-1-$N$9,"") | L53: =IF($N$5=1,K53-$N$8,"")
A54: =IF(AND($N$5=1,26<=$N$11),"26° ajuste","") | B54: =IF(AND($N$5=1,26<=$N$11),INDEX(IPC!$J$5:$J$16,MOD(J54,12)+1)&" de "&INT((J54)/12),"") | C54: =IF(AND(AND($N$5=1,26<=$N$11),$N$10=1),INDEX(IPC!$J$5:$J$16,MOD(L54,12)+1)&" de "&INT((L54)/12),"") | D54: =IF(AND(AND($N$5=1,26<=$N$11),$N$10=1),INDEX(IPC!$J$5:$J$16,MOD(K54,12)+1)&" de "&INT((K54)/12),"") | E54: =IF(NOT(AND($N$5=1,26<=$N$11)),"",IF($N$10=1,IF(AND($N$14=1,K54<=$N$12),INDEX(IPC!$D$5:$D$173,(K54)-IPC!$J$2+1)/INDEX(IPC!$D$5:$D$173,(L54)-IPC!$J$2+1)-1,""),IF(ISNUMBER(F54),F54/100,""))) | G54: =IF(AND(AND($N$5=1,26<=$N$11),ISNUMBER(G53),ISNUMBER(E54)),G53*(1+E54),"") | H54: =IF(NOT(AND($N$5=1,26<=$N$11)),"",IF(ISNUMBER(G54),"Aplicado",IF(ISNUMBER(G53),IF($N$10=1,"Falta el IPC de "&INDEX(IPC!$J$5:$J$16,MOD($N$12+1,12)+1)&" de "&INT(($N$12+1)/12),"Cargá el % de este ajuste en la columna F"),""))) | J54: =IF($N$5=1,$N$7+26*$N$8,"") | K54: =IF($N$5=1,J54-1-$N$9,"") | L54: =IF($N$5=1,K54-$N$8,"")
A55: =IF(AND($N$5=1,27<=$N$11),"27° ajuste","") | B55: =IF(AND($N$5=1,27<=$N$11),INDEX(IPC!$J$5:$J$16,MOD(J55,12)+1)&" de "&INT((J55)/12),"") | C55: =IF(AND(AND($N$5=1,27<=$N$11),$N$10=1),INDEX(IPC!$J$5:$J$16,MOD(L55,12)+1)&" de "&INT((L55)/12),"") | D55: =IF(AND(AND($N$5=1,27<=$N$11),$N$10=1),INDEX(IPC!$J$5:$J$16,MOD(K55,12)+1)&" de "&INT((K55)/12),"") | E55: =IF(NOT(AND($N$5=1,27<=$N$11)),"",IF($N$10=1,IF(AND($N$14=1,K55<=$N$12),INDEX(IPC!$D$5:$D$173,(K55)-IPC!$J$2+1)/INDEX(IPC!$D$5:$D$173,(L55)-IPC!$J$2+1)-1,""),IF(ISNUMBER(F55),F55/100,""))) | G55: =IF(AND(AND($N$5=1,27<=$N$11),ISNUMBER(G54),ISNUMBER(E55)),G54*(1+E55),"") | H55: =IF(NOT(AND($N$5=1,27<=$N$11)),"",IF(ISNUMBER(G55),"Aplicado",IF(ISNUMBER(G54),IF($N$10=1,"Falta el IPC de "&INDEX(IPC!$J$5:$J$16,MOD($N$12+1,12)+1)&" de "&INT(($N$12+1)/12),"Cargá el % de este ajuste en la columna F"),""))) | J55: =IF($N$5=1,$N$7+27*$N$8,"") | K55: =IF($N$5=1,J55-1-$N$9,"") | L55: =IF($N$5=1,K55-$N$8,"")
A56: =IF(AND($N$5=1,28<=$N$11),"28° ajuste","") | B56: =IF(AND($N$5=1,28<=$N$11),INDEX(IPC!$J$5:$J$16,MOD(J56,12)+1)&" de "&INT((J56)/12),"") | C56: =IF(AND(AND($N$5=1,28<=$N$11),$N$10=1),INDEX(IPC!$J$5:$J$16,MOD(L56,12)+1)&" de "&INT((L56)/12),"") | D56: =IF(AND(AND($N$5=1,28<=$N$11),$N$10=1),INDEX(IPC!$J$5:$J$16,MOD(K56,12)+1)&" de "&INT((K56)/12),"") | E56: =IF(NOT(AND($N$5=1,28<=$N$11)),"",IF($N$10=1,IF(AND($N$14=1,K56<=$N$12),INDEX(IPC!$D$5:$D$173,(K56)-IPC!$J$2+1)/INDEX(IPC!$D$5:$D$173,(L56)-IPC!$J$2+1)-1,""),IF(ISNUMBER(F56),F56/100,""))) | G56: =IF(AND(AND($N$5=1,28<=$N$11),ISNUMBER(G55),ISNUMBER(E56)),G55*(1+E56),"") | H56: =IF(NOT(AND($N$5=1,28<=$N$11)),"",IF(ISNUMBER(G56),"Aplicado",IF(ISNUMBER(G55),IF($N$10=1,"Falta el IPC de "&INDEX(IPC!$J$5:$J$16,MOD($N$12+1,12)+1)&" de "&INT(($N$12+1)/12),"Cargá el % de este ajuste en la columna F"),""))) | J56: =IF($N$5=1,$N$7+28*$N$8,"") | K56: =IF($N$5=1,J56-1-$N$9,"") | L56: =IF($N$5=1,K56-$N$8,"")
A57: =IF(AND($N$5=1,29<=$N$11),"29° ajuste","") | B57: =IF(AND($N$5=1,29<=$N$11),INDEX(IPC!$J$5:$J$16,MOD(J57,12)+1)&" de "&INT((J57)/12),"") | C57: =IF(AND(AND($N$5=1,29<=$N$11),$N$10=1),INDEX(IPC!$J$5:$J$16,MOD(L57,12)+1)&" de "&INT((L57)/12),"") | D57: =IF(AND(AND($N$5=1,29<=$N$11),$N$10=1),INDEX(IPC!$J$5:$J$16,MOD(K57,12)+1)&" de "&INT((K57)/12),"") | E57: =IF(NOT(AND($N$5=1,29<=$N$11)),"",IF($N$10=1,IF(AND($N$14=1,K57<=$N$12),INDEX(IPC!$D$5:$D$173,(K57)-IPC!$J$2+1)/INDEX(IPC!$D$5:$D$173,(L57)-IPC!$J$2+1)-1,""),IF(ISNUMBER(F57),F57/100,""))) | G57: =IF(AND(AND($N$5=1,29<=$N$11),ISNUMBER(G56),ISNUMBER(E57)),G56*(1+E57),"") | H57: =IF(NOT(AND($N$5=1,29<=$N$11)),"",IF(ISNUMBER(G57),"Aplicado",IF(ISNUMBER(G56),IF($N$10=1,"Falta el IPC de "&INDEX(IPC!$J$5:$J$16,MOD($N$12+1,12)+1)&" de "&INT(($N$12+1)/12),"Cargá el % de este ajuste en la columna F"),""))) | J57: =IF($N$5=1,$N$7+29*$N$8,"") | K57: =IF($N$5=1,J57-1-$N$9,"") | L57: =IF($N$5=1,K57-$N$8,"")
A58: =IF(AND($N$5=1,30<=$N$11),"30° ajuste","") | B58: =IF(AND($N$5=1,30<=$N$11),INDEX(IPC!$J$5:$J$16,MOD(J58,12)+1)&" de "&INT((J58)/12),"") | C58: =IF(AND(AND($N$5=1,30<=$N$11),$N$10=1),INDEX(IPC!$J$5:$J$16,MOD(L58,12)+1)&" de "&INT((L58)/12),"") | D58: =IF(AND(AND($N$5=1,30<=$N$11),$N$10=1),INDEX(IPC!$J$5:$J$16,MOD(K58,12)+1)&" de "&INT((K58)/12),"") | E58: =IF(NOT(AND($N$5=1,30<=$N$11)),"",IF($N$10=1,IF(AND($N$14=1,K58<=$N$12),INDEX(IPC!$D$5:$D$173,(K58)-IPC!$J$2+1)/INDEX(IPC!$D$5:$D$173,(L58)-IPC!$J$2+1)-1,""),IF(ISNUMBER(F58),F58/100,""))) | G58: =IF(AND(AND($N$5=1,30<=$N$11),ISNUMBER(G57),ISNUMBER(E58)),G57*(1+E58),"") | H58: =IF(NOT(AND($N$5=1,30<=$N$11)),"",IF(ISNUMBER(G58),"Aplicado",IF(ISNUMBER(G57),IF($N$10=1,"Falta el IPC de "&INDEX(IPC!$J$5:$J$16,MOD($N$12+1,12)+1)&" de "&INT(($N$12+1)/12),"Cargá el % de este ajuste en la columna F"),""))) | J58: =IF($N$5=1,$N$7+30*$N$8,"") | K58: =IF($N$5=1,J58-1-$N$9,"") | L58: =IF($N$5=1,K58-$N$8,"")
A59: =IF(AND($N$5=1,31<=$N$11),"31° ajuste","") | B59: =IF(AND($N$5=1,31<=$N$11),INDEX(IPC!$J$5:$J$16,MOD(J59,12)+1)&" de "&INT((J59)/12),"") | C59: =IF(AND(AND($N$5=1,31<=$N$11),$N$10=1),INDEX(IPC!$J$5:$J$16,MOD(L59,12)+1)&" de "&INT((L59)/12),"") | D59: =IF(AND(AND($N$5=1,31<=$N$11),$N$10=1),INDEX(IPC!$J$5:$J$16,MOD(K59,12)+1)&" de "&INT((K59)/12),"") | E59: =IF(NOT(AND($N$5=1,31<=$N$11)),"",IF($N$10=1,IF(AND($N$14=1,K59<=$N$12),INDEX(IPC!$D$5:$D$173,(K59)-IPC!$J$2+1)/INDEX(IPC!$D$5:$D$173,(L59)-IPC!$J$2+1)-1,""),IF(ISNUMBER(F59),F59/100,""))) | G59: =IF(AND(AND($N$5=1,31<=$N$11),ISNUMBER(G58),ISNUMBER(E59)),G58*(1+E59),"") | H59: =IF(NOT(AND($N$5=1,31<=$N$11)),"",IF(ISNUMBER(G59),"Aplicado",IF(ISNUMBER(G58),IF($N$10=1,"Falta el IPC de "&INDEX(IPC!$J$5:$J$16,MOD($N$12+1,12)+1)&" de "&INT(($N$12+1)/12),"Cargá el % de este ajuste en la columna F"),""))) | J59: =IF($N$5=1,$N$7+31*$N$8,"") | K59: =IF($N$5=1,J59-1-$N$9,"") | L59: =IF($N$5=1,K59-$N$8,"")
A60: =IF(AND($N$5=1,32<=$N$11),"32° ajuste","") | B60: =IF(AND($N$5=1,32<=$N$11),INDEX(IPC!$J$5:$J$16,MOD(J60,12)+1)&" de "&INT((J60)/12),"") | C60: =IF(AND(AND($N$5=1,32<=$N$11),$N$10=1),INDEX(IPC!$J$5:$J$16,MOD(L60,12)+1)&" de "&INT((L60)/12),"") | D60: =IF(AND(AND($N$5=1,32<=$N$11),$N$10=1),INDEX(IPC!$J$5:$J$16,MOD(K60,12)+1)&" de "&INT((K60)/12),"") | E60: =IF(NOT(AND($N$5=1,32<=$N$11)),"",IF($N$10=1,IF(AND($N$14=1,K60<=$N$12),INDEX(IPC!$D$5:$D$173,(K60)-IPC!$J$2+1)/INDEX(IPC!$D$5:$D$173,(L60)-IPC!$J$2+1)-1,""),IF(ISNUMBER(F60),F60/100,""))) | G60: =IF(AND(AND($N$5=1,32<=$N$11),ISNUMBER(G59),ISNUMBER(E60)),G59*(1+E60),"") | H60: =IF(NOT(AND($N$5=1,32<=$N$11)),"",IF(ISNUMBER(G60),"Aplicado",IF(ISNUMBER(G59),IF($N$10=1,"Falta el IPC de "&INDEX(IPC!$J$5:$J$16,MOD($N$12+1,12)+1)&" de "&INT(($N$12+1)/12),"Cargá el % de este ajuste en la columna F"),""))) | J60: =IF($N$5=1,$N$7+32*$N$8,"") | K60: =IF($N$5=1,J60-1-$N$9,"") | L60: =IF($N$5=1,K60-$N$8,"")
A61: =IF(AND($N$5=1,33<=$N$11),"33° ajuste","") | B61: =IF(AND($N$5=1,33<=$N$11),INDEX(IPC!$J$5:$J$16,MOD(J61,12)+1)&" de "&INT((J61)/12),"") | C61: =IF(AND(AND($N$5=1,33<=$N$11),$N$10=1),INDEX(IPC!$J$5:$J$16,MOD(L61,12)+1)&" de "&INT((L61)/12),"") | D61: =IF(AND(AND($N$5=1,33<=$N$11),$N$10=1),INDEX(IPC!$J$5:$J$16,MOD(K61,12)+1)&" de "&INT((K61)/12),"") | E61: =IF(NOT(AND($N$5=1,33<=$N$11)),"",IF($N$10=1,IF(AND($N$14=1,K61<=$N$12),INDEX(IPC!$D$5:$D$173,(K61)-IPC!$J$2+1)/INDEX(IPC!$D$5:$D$173,(L61)-IPC!$J$2+1)-1,""),IF(ISNUMBER(F61),F61/100,""))) | G61: =IF(AND(AND($N$5=1,33<=$N$11),ISNUMBER(G60),ISNUMBER(E61)),G60*(1+E61),"") | H61: =IF(NOT(AND($N$5=1,33<=$N$11)),"",IF(ISNUMBER(G61),"Aplicado",IF(ISNUMBER(G60),IF($N$10=1,"Falta el IPC de "&INDEX(IPC!$J$5:$J$16,MOD($N$12+1,12)+1)&" de "&INT(($N$12+1)/12),"Cargá el % de este ajuste en la columna F"),""))) | J61: =IF($N$5=1,$N$7+33*$N$8,"") | K61: =IF($N$5=1,J61-1-$N$9,"") | L61: =IF($N$5=1,K61-$N$8,"")
A62: =IF(AND($N$5=1,34<=$N$11),"34° ajuste","") | B62: =IF(AND($N$5=1,34<=$N$11),INDEX(IPC!$J$5:$J$16,MOD(J62,12)+1)&" de "&INT((J62)/12),"") | C62: =IF(AND(AND($N$5=1,34<=$N$11),$N$10=1),INDEX(IPC!$J$5:$J$16,MOD(L62,12)+1)&" de "&INT((L62)/12),"") | D62: =IF(AND(AND($N$5=1,34<=$N$11),$N$10=1),INDEX(IPC!$J$5:$J$16,MOD(K62,12)+1)&" de "&INT((K62)/12),"") | E62: =IF(NOT(AND($N$5=1,34<=$N$11)),"",IF($N$10=1,IF(AND($N$14=1,K62<=$N$12),INDEX(IPC!$D$5:$D$173,(K62)-IPC!$J$2+1)/INDEX(IPC!$D$5:$D$173,(L62)-IPC!$J$2+1)-1,""),IF(ISNUMBER(F62),F62/100,""))) | G62: =IF(AND(AND($N$5=1,34<=$N$11),ISNUMBER(G61),ISNUMBER(E62)),G61*(1+E62),"") | H62: =IF(NOT(AND($N$5=1,34<=$N$11)),"",IF(ISNUMBER(G62),"Aplicado",IF(ISNUMBER(G61),IF($N$10=1,"Falta el IPC de "&INDEX(IPC!$J$5:$J$16,MOD($N$12+1,12)+1)&" de "&INT(($N$12+1)/12),"Cargá el % de este ajuste en la columna F"),""))) | J62: =IF($N$5=1,$N$7+34*$N$8,"") | K62: =IF($N$5=1,J62-1-$N$9,"") | L62: =IF($N$5=1,K62-$N$8,"")
A63: =IF(AND($N$5=1,35<=$N$11),"35° ajuste","") | B63: =IF(AND($N$5=1,35<=$N$11),INDEX(IPC!$J$5:$J$16,MOD(J63,12)+1)&" de "&INT((J63)/12),"") | C63: =IF(AND(AND($N$5=1,35<=$N$11),$N$10=1),INDEX(IPC!$J$5:$J$16,MOD(L63,12)+1)&" de "&INT((L63)/12),"") | D63: =IF(AND(AND($N$5=1,35<=$N$11),$N$10=1),INDEX(IPC!$J$5:$J$16,MOD(K63,12)+1)&" de "&INT((K63)/12),"") | E63: =IF(NOT(AND($N$5=1,35<=$N$11)),"",IF($N$10=1,IF(AND($N$14=1,K63<=$N$12),INDEX(IPC!$D$5:$D$173,(K63)-IPC!$J$2+1)/INDEX(IPC!$D$5:$D$173,(L63)-IPC!$J$2+1)-1,""),IF(ISNUMBER(F63),F63/100,""))) | G63: =IF(AND(AND($N$5=1,35<=$N$11),ISNUMBER(G62),ISNUMBER(E63)),G62*(1+E63),"") | H63: =IF(NOT(AND($N$5=1,35<=$N$11)),"",IF(ISNUMBER(G63),"Aplicado",IF(ISNUMBER(G62),IF($N$10=1,"Falta el IPC de "&INDEX(IPC!$J$5:$J$16,MOD($N$12+1,12)+1)&" de "&INT(($N$12+1)/12),"Cargá el % de este ajuste en la columna F"),""))) | J63: =IF($N$5=1,$N$7+35*$N$8,"") | K63: =IF($N$5=1,J63-1-$N$9,"") | L63: =IF($N$5=1,K63-$N$8,"")
A64: =IF(AND($N$5=1,36<=$N$11),"36° ajuste","") | B64: =IF(AND($N$5=1,36<=$N$11),INDEX(IPC!$J$5:$J$16,MOD(J64,12)+1)&" de "&INT((J64)/12),"") | C64: =IF(AND(AND($N$5=1,36<=$N$11),$N$10=1),INDEX(IPC!$J$5:$J$16,MOD(L64,12)+1)&" de "&INT((L64)/12),"") | D64: =IF(AND(AND($N$5=1,36<=$N$11),$N$10=1),INDEX(IPC!$J$5:$J$16,MOD(K64,12)+1)&" de "&INT((K64)/12),"") | E64: =IF(NOT(AND($N$5=1,36<=$N$11)),"",IF($N$10=1,IF(AND($N$14=1,K64<=$N$12),INDEX(IPC!$D$5:$D$173,(K64)-IPC!$J$2+1)/INDEX(IPC!$D$5:$D$173,(L64)-IPC!$J$2+1)-1,""),IF(ISNUMBER(F64),F64/100,""))) | G64: =IF(AND(AND($N$5=1,36<=$N$11),ISNUMBER(G63),ISNUMBER(E64)),G63*(1+E64),"") | H64: =IF(NOT(AND($N$5=1,36<=$N$11)),"",IF(ISNUMBER(G64),"Aplicado",IF(ISNUMBER(G63),IF($N$10=1,"Falta el IPC de "&INDEX(IPC!$J$5:$J$16,MOD($N$12+1,12)+1)&" de "&INT(($N$12+1)/12),"Cargá el % de este ajuste en la columna F"),""))) | J64: =IF($N$5=1,$N$7+36*$N$8,"") | K64: =IF($N$5=1,J64-1-$N$9,"") | L64: =IF($N$5=1,K64-$N$8,"")
A65: =IF(AND($N$5=1,37<=$N$11),"37° ajuste","") | B65: =IF(AND($N$5=1,37<=$N$11),INDEX(IPC!$J$5:$J$16,MOD(J65,12)+1)&" de "&INT((J65)/12),"") | C65: =IF(AND(AND($N$5=1,37<=$N$11),$N$10=1),INDEX(IPC!$J$5:$J$16,MOD(L65,12)+1)&" de "&INT((L65)/12),"") | D65: =IF(AND(AND($N$5=1,37<=$N$11),$N$10=1),INDEX(IPC!$J$5:$J$16,MOD(K65,12)+1)&" de "&INT((K65)/12),"") | E65: =IF(NOT(AND($N$5=1,37<=$N$11)),"",IF($N$10=1,IF(AND($N$14=1,K65<=$N$12),INDEX(IPC!$D$5:$D$173,(K65)-IPC!$J$2+1)/INDEX(IPC!$D$5:$D$173,(L65)-IPC!$J$2+1)-1,""),IF(ISNUMBER(F65),F65/100,""))) | G65: =IF(AND(AND($N$5=1,37<=$N$11),ISNUMBER(G64),ISNUMBER(E65)),G64*(1+E65),"") | H65: =IF(NOT(AND($N$5=1,37<=$N$11)),"",IF(ISNUMBER(G65),"Aplicado",IF(ISNUMBER(G64),IF($N$10=1,"Falta el IPC de "&INDEX(IPC!$J$5:$J$16,MOD($N$12+1,12)+1)&" de "&INT(($N$12+1)/12),"Cargá el % de este ajuste en la columna F"),""))) | J65: =IF($N$5=1,$N$7+37*$N$8,"") | K65: =IF($N$5=1,J65-1-$N$9,"") | L65: =IF($N$5=1,K65-$N$8,"")
A66: =IF(AND($N$5=1,38<=$N$11),"38° ajuste","") | B66: =IF(AND($N$5=1,38<=$N$11),INDEX(IPC!$J$5:$J$16,MOD(J66,12)+1)&" de "&INT((J66)/12),"") | C66: =IF(AND(AND($N$5=1,38<=$N$11),$N$10=1),INDEX(IPC!$J$5:$J$16,MOD(L66,12)+1)&" de "&INT((L66)/12),"") | D66: =IF(AND(AND($N$5=1,38<=$N$11),$N$10=1),INDEX(IPC!$J$5:$J$16,MOD(K66,12)+1)&" de "&INT((K66)/12),"") | E66: =IF(NOT(AND($N$5=1,38<=$N$11)),"",IF($N$10=1,IF(AND($N$14=1,K66<=$N$12),INDEX(IPC!$D$5:$D$173,(K66)-IPC!$J$2+1)/INDEX(IPC!$D$5:$D$173,(L66)-IPC!$J$2+1)-1,""),IF(ISNUMBER(F66),F66/100,""))) | G66: =IF(AND(AND($N$5=1,38<=$N$11),ISNUMBER(G65),ISNUMBER(E66)),G65*(1+E66),"") | H66: =IF(NOT(AND($N$5=1,38<=$N$11)),"",IF(ISNUMBER(G66),"Aplicado",IF(ISNUMBER(G65),IF($N$10=1,"Falta el IPC de "&INDEX(IPC!$J$5:$J$16,MOD($N$12+1,12)+1)&" de "&INT(($N$12+1)/12),"Cargá el % de este ajuste en la columna F"),""))) | J66: =IF($N$5=1,$N$7+38*$N$8,"") | K66: =IF($N$5=1,J66-1-$N$9,"") | L66: =IF($N$5=1,K66-$N$8,"")
A67: =IF(AND($N$5=1,39<=$N$11),"39° ajuste","") | B67: =IF(AND($N$5=1,39<=$N$11),INDEX(IPC!$J$5:$J$16,MOD(J67,12)+1)&" de "&INT((J67)/12),"") | C67: =IF(AND(AND($N$5=1,39<=$N$11),$N$10=1),INDEX(IPC!$J$5:$J$16,MOD(L67,12)+1)&" de "&INT((L67)/12),"") | D67: =IF(AND(AND($N$5=1,39<=$N$11),$N$10=1),INDEX(IPC!$J$5:$J$16,MOD(K67,12)+1)&" de "&INT((K67)/12),"") | E67: =IF(NOT(AND($N$5=1,39<=$N$11)),"",IF($N$10=1,IF(AND($N$14=1,K67<=$N$12),INDEX(IPC!$D$5:$D$173,(K67)-IPC!$J$2+1)/INDEX(IPC!$D$5:$D$173,(L67)-IPC!$J$2+1)-1,""),IF(ISNUMBER(F67),F67/100,""))) | G67: =IF(AND(AND($N$5=1,39<=$N$11),ISNUMBER(G66),ISNUMBER(E67)),G66*(1+E67),"") | H67: =IF(NOT(AND($N$5=1,39<=$N$11)),"",IF(ISNUMBER(G67),"Aplicado",IF(ISNUMBER(G66),IF($N$10=1,"Falta el IPC de "&INDEX(IPC!$J$5:$J$16,MOD($N$12+1,12)+1)&" de "&INT(($N$12+1)/12),"Cargá el % de este ajuste en la columna F"),""))) | J67: =IF($N$5=1,$N$7+39*$N$8,"") | K67: =IF($N$5=1,J67-1-$N$9,"") | L67: =IF($N$5=1,K67-$N$8,"")
A68: =IF(AND($N$5=1,40<=$N$11),"40° ajuste","") | B68: =IF(AND($N$5=1,40<=$N$11),INDEX(IPC!$J$5:$J$16,MOD(J68,12)+1)&" de "&INT((J68)/12),"") | C68: =IF(AND(AND($N$5=1,40<=$N$11),$N$10=1),INDEX(IPC!$J$5:$J$16,MOD(L68,12)+1)&" de "&INT((L68)/12),"") | D68: =IF(AND(AND($N$5=1,40<=$N$11),$N$10=1),INDEX(IPC!$J$5:$J$16,MOD(K68,12)+1)&" de "&INT((K68)/12),"") | E68: =IF(NOT(AND($N$5=1,40<=$N$11)),"",IF($N$10=1,IF(AND($N$14=1,K68<=$N$12),INDEX(IPC!$D$5:$D$173,(K68)-IPC!$J$2+1)/INDEX(IPC!$D$5:$D$173,(L68)-IPC!$J$2+1)-1,""),IF(ISNUMBER(F68),F68/100,""))) | G68: =IF(AND(AND($N$5=1,40<=$N$11),ISNUMBER(G67),ISNUMBER(E68)),G67*(1+E68),"") | H68: =IF(NOT(AND($N$5=1,40<=$N$11)),"",IF(ISNUMBER(G68),"Aplicado",IF(ISNUMBER(G67),IF($N$10=1,"Falta el IPC de "&INDEX(IPC!$J$5:$J$16,MOD($N$12+1,12)+1)&" de "&INT(($N$12+1)/12),"Cargá el % de este ajuste en la columna F"),""))) | J68: =IF($N$5=1,$N$7+40*$N$8,"") | K68: =IF($N$5=1,J68-1-$N$9,"") | L68: =IF($N$5=1,K68-$N$8,"")
A69: =IF(AND($N$5=1,41<=$N$11),"41° ajuste","") | B69: =IF(AND($N$5=1,41<=$N$11),INDEX(IPC!$J$5:$J$16,MOD(J69,12)+1)&" de "&INT((J69)/12),"") | C69: =IF(AND(AND($N$5=1,41<=$N$11),$N$10=1),INDEX(IPC!$J$5:$J$16,MOD(L69,12)+1)&" de "&INT((L69)/12),"") | D69: =IF(AND(AND($N$5=1,41<=$N$11),$N$10=1),INDEX(IPC!$J$5:$J$16,MOD(K69,12)+1)&" de "&INT((K69)/12),"") | E69: =IF(NOT(AND($N$5=1,41<=$N$11)),"",IF($N$10=1,IF(AND($N$14=1,K69<=$N$12),INDEX(IPC!$D$5:$D$173,(K69)-IPC!$J$2+1)/INDEX(IPC!$D$5:$D$173,(L69)-IPC!$J$2+1)-1,""),IF(ISNUMBER(F69),F69/100,""))) | G69: =IF(AND(AND($N$5=1,41<=$N$11),ISNUMBER(G68),ISNUMBER(E69)),G68*(1+E69),"") | H69: =IF(NOT(AND($N$5=1,41<=$N$11)),"",IF(ISNUMBER(G69),"Aplicado",IF(ISNUMBER(G68),IF($N$10=1,"Falta el IPC de "&INDEX(IPC!$J$5:$J$16,MOD($N$12+1,12)+1)&" de "&INT(($N$12+1)/12),"Cargá el % de este ajuste en la columna F"),""))) | J69: =IF($N$5=1,$N$7+41*$N$8,"") | K69: =IF($N$5=1,J69-1-$N$9,"") | L69: =IF($N$5=1,K69-$N$8,"")
A70: =IF(AND($N$5=1,42<=$N$11),"42° ajuste","") | B70: =IF(AND($N$5=1,42<=$N$11),INDEX(IPC!$J$5:$J$16,MOD(J70,12)+1)&" de "&INT((J70)/12),"") | C70: =IF(AND(AND($N$5=1,42<=$N$11),$N$10=1),INDEX(IPC!$J$5:$J$16,MOD(L70,12)+1)&" de "&INT((L70)/12),"") | D70: =IF(AND(AND($N$5=1,42<=$N$11),$N$10=1),INDEX(IPC!$J$5:$J$16,MOD(K70,12)+1)&" de "&INT((K70)/12),"") | E70: =IF(NOT(AND($N$5=1,42<=$N$11)),"",IF($N$10=1,IF(AND($N$14=1,K70<=$N$12),INDEX(IPC!$D$5:$D$173,(K70)-IPC!$J$2+1)/INDEX(IPC!$D$5:$D$173,(L70)-IPC!$J$2+1)-1,""),IF(ISNUMBER(F70),F70/100,""))) | G70: =IF(AND(AND($N$5=1,42<=$N$11),ISNUMBER(G69),ISNUMBER(E70)),G69*(1+E70),"") | H70: =IF(NOT(AND($N$5=1,42<=$N$11)),"",IF(ISNUMBER(G70),"Aplicado",IF(ISNUMBER(G69),IF($N$10=1,"Falta el IPC de "&INDEX(IPC!$J$5:$J$16,MOD($N$12+1,12)+1)&" de "&INT(($N$12+1)/12),"Cargá el % de este ajuste en la columna F"),""))) | J70: =IF($N$5=1,$N$7+42*$N$8,"") | K70: =IF($N$5=1,J70-1-$N$9,"") | L70: =IF($N$5=1,K70-$N$8,"")
A71: =IF(AND($N$5=1,43<=$N$11),"43° ajuste","") | B71: =IF(AND($N$5=1,43<=$N$11),INDEX(IPC!$J$5:$J$16,MOD(J71,12)+1)&" de "&INT((J71)/12),"") | C71: =IF(AND(AND($N$5=1,43<=$N$11),$N$10=1),INDEX(IPC!$J$5:$J$16,MOD(L71,12)+1)&" de "&INT((L71)/12),"") | D71: =IF(AND(AND($N$5=1,43<=$N$11),$N$10=1),INDEX(IPC!$J$5:$J$16,MOD(K71,12)+1)&" de "&INT((K71)/12),"") | E71: =IF(NOT(AND($N$5=1,43<=$N$11)),"",IF($N$10=1,IF(AND($N$14=1,K71<=$N$12),INDEX(IPC!$D$5:$D$173,(K71)-IPC!$J$2+1)/INDEX(IPC!$D$5:$D$173,(L71)-IPC!$J$2+1)-1,""),IF(ISNUMBER(F71),F71/100,""))) | G71: =IF(AND(AND($N$5=1,43<=$N$11),ISNUMBER(G70),ISNUMBER(E71)),G70*(1+E71),"") | H71: =IF(NOT(AND($N$5=1,43<=$N$11)),"",IF(ISNUMBER(G71),"Aplicado",IF(ISNUMBER(G70),IF($N$10=1,"Falta el IPC de "&INDEX(IPC!$J$5:$J$16,MOD($N$12+1,12)+1)&" de "&INT(($N$12+1)/12),"Cargá el % de este ajuste en la columna F"),""))) | J71: =IF($N$5=1,$N$7+43*$N$8,"") | K71: =IF($N$5=1,J71-1-$N$9,"") | L71: =IF($N$5=1,K71-$N$8,"")
A72: =IF(AND($N$5=1,44<=$N$11),"44° ajuste","") | B72: =IF(AND($N$5=1,44<=$N$11),INDEX(IPC!$J$5:$J$16,MOD(J72,12)+1)&" de "&INT((J72)/12),"") | C72: =IF(AND(AND($N$5=1,44<=$N$11),$N$10=1),INDEX(IPC!$J$5:$J$16,MOD(L72,12)+1)&" de "&INT((L72)/12),"") | D72: =IF(AND(AND($N$5=1,44<=$N$11),$N$10=1),INDEX(IPC!$J$5:$J$16,MOD(K72,12)+1)&" de "&INT((K72)/12),"") | E72: =IF(NOT(AND($N$5=1,44<=$N$11)),"",IF($N$10=1,IF(AND($N$14=1,K72<=$N$12),INDEX(IPC!$D$5:$D$173,(K72)-IPC!$J$2+1)/INDEX(IPC!$D$5:$D$173,(L72)-IPC!$J$2+1)-1,""),IF(ISNUMBER(F72),F72/100,""))) | G72: =IF(AND(AND($N$5=1,44<=$N$11),ISNUMBER(G71),ISNUMBER(E72)),G71*(1+E72),"") | H72: =IF(NOT(AND($N$5=1,44<=$N$11)),"",IF(ISNUMBER(G72),"Aplicado",IF(ISNUMBER(G71),IF($N$10=1,"Falta el IPC de "&INDEX(IPC!$J$5:$J$16,MOD($N$12+1,12)+1)&" de "&INT(($N$12+1)/12),"Cargá el % de este ajuste en la columna F"),""))) | J72: =IF($N$5=1,$N$7+44*$N$8,"") | K72: =IF($N$5=1,J72-1-$N$9,"") | L72: =IF($N$5=1,K72-$N$8,"")
A73: =IF(AND($N$5=1,45<=$N$11),"45° ajuste","") | B73: =IF(AND($N$5=1,45<=$N$11),INDEX(IPC!$J$5:$J$16,MOD(J73,12)+1)&" de "&INT((J73)/12),"") | C73: =IF(AND(AND($N$5=1,45<=$N$11),$N$10=1),INDEX(IPC!$J$5:$J$16,MOD(L73,12)+1)&" de "&INT((L73)/12),"") | D73: =IF(AND(AND($N$5=1,45<=$N$11),$N$10=1),INDEX(IPC!$J$5:$J$16,MOD(K73,12)+1)&" de "&INT((K73)/12),"") | E73: =IF(NOT(AND($N$5=1,45<=$N$11)),"",IF($N$10=1,IF(AND($N$14=1,K73<=$N$12),INDEX(IPC!$D$5:$D$173,(K73)-IPC!$J$2+1)/INDEX(IPC!$D$5:$D$173,(L73)-IPC!$J$2+1)-1,""),IF(ISNUMBER(F73),F73/100,""))) | G73: =IF(AND(AND($N$5=1,45<=$N$11),ISNUMBER(G72),ISNUMBER(E73)),G72*(1+E73),"") | H73: =IF(NOT(AND($N$5=1,45<=$N$11)),"",IF(ISNUMBER(G73),"Aplicado",IF(ISNUMBER(G72),IF($N$10=1,"Falta el IPC de "&INDEX(IPC!$J$5:$J$16,MOD($N$12+1,12)+1)&" de "&INT(($N$12+1)/12),"Cargá el % de este ajuste en la columna F"),""))) | J73: =IF($N$5=1,$N$7+45*$N$8,"") | K73: =IF($N$5=1,J73-1-$N$9,"") | L73: =IF($N$5=1,K73-$N$8,"")
A74: =IF(AND($N$5=1,46<=$N$11),"46° ajuste","") | B74: =IF(AND($N$5=1,46<=$N$11),INDEX(IPC!$J$5:$J$16,MOD(J74,12)+1)&" de "&INT((J74)/12),"") | C74: =IF(AND(AND($N$5=1,46<=$N$11),$N$10=1),INDEX(IPC!$J$5:$J$16,MOD(L74,12)+1)&" de "&INT((L74)/12),"") | D74: =IF(AND(AND($N$5=1,46<=$N$11),$N$10=1),INDEX(IPC!$J$5:$J$16,MOD(K74,12)+1)&" de "&INT((K74)/12),"") | E74: =IF(NOT(AND($N$5=1,46<=$N$11)),"",IF($N$10=1,IF(AND($N$14=1,K74<=$N$12),INDEX(IPC!$D$5:$D$173,(K74)-IPC!$J$2+1)/INDEX(IPC!$D$5:$D$173,(L74)-IPC!$J$2+1)-1,""),IF(ISNUMBER(F74),F74/100,""))) | G74: =IF(AND(AND($N$5=1,46<=$N$11),ISNUMBER(G73),ISNUMBER(E74)),G73*(1+E74),"") | H74: =IF(NOT(AND($N$5=1,46<=$N$11)),"",IF(ISNUMBER(G74),"Aplicado",IF(ISNUMBER(G73),IF($N$10=1,"Falta el IPC de "&INDEX(IPC!$J$5:$J$16,MOD($N$12+1,12)+1)&" de "&INT(($N$12+1)/12),"Cargá el % de este ajuste en la columna F"),""))) | J74: =IF($N$5=1,$N$7+46*$N$8,"") | K74: =IF($N$5=1,J74-1-$N$9,"") | L74: =IF($N$5=1,K74-$N$8,"")
A75: =IF(AND($N$5=1,47<=$N$11),"47° ajuste","") | B75: =IF(AND($N$5=1,47<=$N$11),INDEX(IPC!$J$5:$J$16,MOD(J75,12)+1)&" de "&INT((J75)/12),"") | C75: =IF(AND(AND($N$5=1,47<=$N$11),$N$10=1),INDEX(IPC!$J$5:$J$16,MOD(L75,12)+1)&" de "&INT((L75)/12),"") | D75: =IF(AND(AND($N$5=1,47<=$N$11),$N$10=1),INDEX(IPC!$J$5:$J$16,MOD(K75,12)+1)&" de "&INT((K75)/12),"") | E75: =IF(NOT(AND($N$5=1,47<=$N$11)),"",IF($N$10=1,IF(AND($N$14=1,K75<=$N$12),INDEX(IPC!$D$5:$D$173,(K75)-IPC!$J$2+1)/INDEX(IPC!$D$5:$D$173,(L75)-IPC!$J$2+1)-1,""),IF(ISNUMBER(F75),F75/100,""))) | G75: =IF(AND(AND($N$5=1,47<=$N$11),ISNUMBER(G74),ISNUMBER(E75)),G74*(1+E75),"") | H75: =IF(NOT(AND($N$5=1,47<=$N$11)),"",IF(ISNUMBER(G75),"Aplicado",IF(ISNUMBER(G74),IF($N$10=1,"Falta el IPC de "&INDEX(IPC!$J$5:$J$16,MOD($N$12+1,12)+1)&" de "&INT(($N$12+1)/12),"Cargá el % de este ajuste en la columna F"),""))) | J75: =IF($N$5=1,$N$7+47*$N$8,"") | K75: =IF($N$5=1,J75-1-$N$9,"") | L75: =IF($N$5=1,K75-$N$8,"")
A76: =IF(AND($N$5=1,48<=$N$11),"48° ajuste","") | B76: =IF(AND($N$5=1,48<=$N$11),INDEX(IPC!$J$5:$J$16,MOD(J76,12)+1)&" de "&INT((J76)/12),"") | C76: =IF(AND(AND($N$5=1,48<=$N$11),$N$10=1),INDEX(IPC!$J$5:$J$16,MOD(L76,12)+1)&" de "&INT((L76)/12),"") | D76: =IF(AND(AND($N$5=1,48<=$N$11),$N$10=1),INDEX(IPC!$J$5:$J$16,MOD(K76,12)+1)&" de "&INT((K76)/12),"") | E76: =IF(NOT(AND($N$5=1,48<=$N$11)),"",IF($N$10=1,IF(AND($N$14=1,K76<=$N$12),INDEX(IPC!$D$5:$D$173,(K76)-IPC!$J$2+1)/INDEX(IPC!$D$5:$D$173,(L76)-IPC!$J$2+1)-1,""),IF(ISNUMBER(F76),F76/100,""))) | G76: =IF(AND(AND($N$5=1,48<=$N$11),ISNUMBER(G75),ISNUMBER(E76)),G75*(1+E76),"") | H76: =IF(NOT(AND($N$5=1,48<=$N$11)),"",IF(ISNUMBER(G76),"Aplicado",IF(ISNUMBER(G75),IF($N$10=1,"Falta el IPC de "&INDEX(IPC!$J$5:$J$16,MOD($N$12+1,12)+1)&" de "&INT(($N$12+1)/12),"Cargá el % de este ajuste en la columna F"),""))) | J76: =IF($N$5=1,$N$7+48*$N$8,"") | K76: =IF($N$5=1,J76-1-$N$9,"") | L76: =IF($N$5=1,K76-$N$8,"")
A77: =IF(AND($N$5=1,49<=$N$11),"49° ajuste","") | B77: =IF(AND($N$5=1,49<=$N$11),INDEX(IPC!$J$5:$J$16,MOD(J77,12)+1)&" de "&INT((J77)/12),"") | C77: =IF(AND(AND($N$5=1,49<=$N$11),$N$10=1),INDEX(IPC!$J$5:$J$16,MOD(L77,12)+1)&" de "&INT((L77)/12),"") | D77: =IF(AND(AND($N$5=1,49<=$N$11),$N$10=1),INDEX(IPC!$J$5:$J$16,MOD(K77,12)+1)&" de "&INT((K77)/12),"") | E77: =IF(NOT(AND($N$5=1,49<=$N$11)),"",IF($N$10=1,IF(AND($N$14=1,K77<=$N$12),INDEX(IPC!$D$5:$D$173,(K77)-IPC!$J$2+1)/INDEX(IPC!$D$5:$D$173,(L77)-IPC!$J$2+1)-1,""),IF(ISNUMBER(F77),F77/100,""))) | G77: =IF(AND(AND($N$5=1,49<=$N$11),ISNUMBER(G76),ISNUMBER(E77)),G76*(1+E77),"") | H77: =IF(NOT(AND($N$5=1,49<=$N$11)),"",IF(ISNUMBER(G77),"Aplicado",IF(ISNUMBER(G76),IF($N$10=1,"Falta el IPC de "&INDEX(IPC!$J$5:$J$16,MOD($N$12+1,12)+1)&" de "&INT(($N$12+1)/12),"Cargá el % de este ajuste en la columna F"),""))) | J77: =IF($N$5=1,$N$7+49*$N$8,"") | K77: =IF($N$5=1,J77-1-$N$9,"") | L77: =IF($N$5=1,K77-$N$8,"")
A78: =IF(AND($N$5=1,50<=$N$11),"50° ajuste","") | B78: =IF(AND($N$5=1,50<=$N$11),INDEX(IPC!$J$5:$J$16,MOD(J78,12)+1)&" de "&INT((J78)/12),"") | C78: =IF(AND(AND($N$5=1,50<=$N$11),$N$10=1),INDEX(IPC!$J$5:$J$16,MOD(L78,12)+1)&" de "&INT((L78)/12),"") | D78: =IF(AND(AND($N$5=1,50<=$N$11),$N$10=1),INDEX(IPC!$J$5:$J$16,MOD(K78,12)+1)&" de "&INT((K78)/12),"") | E78: =IF(NOT(AND($N$5=1,50<=$N$11)),"",IF($N$10=1,IF(AND($N$14=1,K78<=$N$12),INDEX(IPC!$D$5:$D$173,(K78)-IPC!$J$2+1)/INDEX(IPC!$D$5:$D$173,(L78)-IPC!$J$2+1)-1,""),IF(ISNUMBER(F78),F78/100,""))) | G78: =IF(AND(AND($N$5=1,50<=$N$11),ISNUMBER(G77),ISNUMBER(E78)),G77*(1+E78),"") | H78: =IF(NOT(AND($N$5=1,50<=$N$11)),"",IF(ISNUMBER(G78),"Aplicado",IF(ISNUMBER(G77),IF($N$10=1,"Falta el IPC de "&INDEX(IPC!$J$5:$J$16,MOD($N$12+1,12)+1)&" de "&INT(($N$12+1)/12),"Cargá el % de este ajuste en la columna F"),""))) | J78: =IF($N$5=1,$N$7+50*$N$8,"") | K78: =IF($N$5=1,J78-1-$N$9,"") | L78: =IF($N$5=1,K78-$N$8,"")
A79: =IF(AND($N$5=1,51<=$N$11),"51° ajuste","") | B79: =IF(AND($N$5=1,51<=$N$11),INDEX(IPC!$J$5:$J$16,MOD(J79,12)+1)&" de "&INT((J79)/12),"") | C79: =IF(AND(AND($N$5=1,51<=$N$11),$N$10=1),INDEX(IPC!$J$5:$J$16,MOD(L79,12)+1)&" de "&INT((L79)/12),"") | D79: =IF(AND(AND($N$5=1,51<=$N$11),$N$10=1),INDEX(IPC!$J$5:$J$16,MOD(K79,12)+1)&" de "&INT((K79)/12),"") | E79: =IF(NOT(AND($N$5=1,51<=$N$11)),"",IF($N$10=1,IF(AND($N$14=1,K79<=$N$12),INDEX(IPC!$D$5:$D$173,(K79)-IPC!$J$2+1)/INDEX(IPC!$D$5:$D$173,(L79)-IPC!$J$2+1)-1,""),IF(ISNUMBER(F79),F79/100,""))) | G79: =IF(AND(AND($N$5=1,51<=$N$11),ISNUMBER(G78),ISNUMBER(E79)),G78*(1+E79),"") | H79: =IF(NOT(AND($N$5=1,51<=$N$11)),"",IF(ISNUMBER(G79),"Aplicado",IF(ISNUMBER(G78),IF($N$10=1,"Falta el IPC de "&INDEX(IPC!$J$5:$J$16,MOD($N$12+1,12)+1)&" de "&INT(($N$12+1)/12),"Cargá el % de este ajuste en la columna F"),""))) | J79: =IF($N$5=1,$N$7+51*$N$8,"") | K79: =IF($N$5=1,J79-1-$N$9,"") | L79: =IF($N$5=1,K79-$N$8,"")
A80: =IF(AND($N$5=1,52<=$N$11),"52° ajuste","") | B80: =IF(AND($N$5=1,52<=$N$11),INDEX(IPC!$J$5:$J$16,MOD(J80,12)+1)&" de "&INT((J80)/12),"") | C80: =IF(AND(AND($N$5=1,52<=$N$11),$N$10=1),INDEX(IPC!$J$5:$J$16,MOD(L80,12)+1)&" de "&INT((L80)/12),"") | D80: =IF(AND(AND($N$5=1,52<=$N$11),$N$10=1),INDEX(IPC!$J$5:$J$16,MOD(K80,12)+1)&" de "&INT((K80)/12),"") | E80: =IF(NOT(AND($N$5=1,52<=$N$11)),"",IF($N$10=1,IF(AND($N$14=1,K80<=$N$12),INDEX(IPC!$D$5:$D$173,(K80)-IPC!$J$2+1)/INDEX(IPC!$D$5:$D$173,(L80)-IPC!$J$2+1)-1,""),IF(ISNUMBER(F80),F80/100,""))) | G80: =IF(AND(AND($N$5=1,52<=$N$11),ISNUMBER(G79),ISNUMBER(E80)),G79*(1+E80),"") | H80: =IF(NOT(AND($N$5=1,52<=$N$11)),"",IF(ISNUMBER(G80),"Aplicado",IF(ISNUMBER(G79),IF($N$10=1,"Falta el IPC de "&INDEX(IPC!$J$5:$J$16,MOD($N$12+1,12)+1)&" de "&INT(($N$12+1)/12),"Cargá el % de este ajuste en la columna F"),""))) | J80: =IF($N$5=1,$N$7+52*$N$8,"") | K80: =IF($N$5=1,J80-1-$N$9,"") | L80: =IF($N$5=1,K80-$N$8,"")
A81: =IF(AND($N$5=1,53<=$N$11),"53° ajuste","") | B81: =IF(AND($N$5=1,53<=$N$11),INDEX(IPC!$J$5:$J$16,MOD(J81,12)+1)&" de "&INT((J81)/12),"") | C81: =IF(AND(AND($N$5=1,53<=$N$11),$N$10=1),INDEX(IPC!$J$5:$J$16,MOD(L81,12)+1)&" de "&INT((L81)/12),"") | D81: =IF(AND(AND($N$5=1,53<=$N$11),$N$10=1),INDEX(IPC!$J$5:$J$16,MOD(K81,12)+1)&" de "&INT((K81)/12),"") | E81: =IF(NOT(AND($N$5=1,53<=$N$11)),"",IF($N$10=1,IF(AND($N$14=1,K81<=$N$12),INDEX(IPC!$D$5:$D$173,(K81)-IPC!$J$2+1)/INDEX(IPC!$D$5:$D$173,(L81)-IPC!$J$2+1)-1,""),IF(ISNUMBER(F81),F81/100,""))) | G81: =IF(AND(AND($N$5=1,53<=$N$11),ISNUMBER(G80),ISNUMBER(E81)),G80*(1+E81),"") | H81: =IF(NOT(AND($N$5=1,53<=$N$11)),"",IF(ISNUMBER(G81),"Aplicado",IF(ISNUMBER(G80),IF($N$10=1,"Falta el IPC de "&INDEX(IPC!$J$5:$J$16,MOD($N$12+1,12)+1)&" de "&INT(($N$12+1)/12),"Cargá el % de este ajuste en la columna F"),""))) | J81: =IF($N$5=1,$N$7+53*$N$8,"") | K81: =IF($N$5=1,J81-1-$N$9,"") | L81: =IF($N$5=1,K81-$N$8,"")
A82: =IF(AND($N$5=1,54<=$N$11),"54° ajuste","") | B82: =IF(AND($N$5=1,54<=$N$11),INDEX(IPC!$J$5:$J$16,MOD(J82,12)+1)&" de "&INT((J82)/12),"") | C82: =IF(AND(AND($N$5=1,54<=$N$11),$N$10=1),INDEX(IPC!$J$5:$J$16,MOD(L82,12)+1)&" de "&INT((L82)/12),"") | D82: =IF(AND(AND($N$5=1,54<=$N$11),$N$10=1),INDEX(IPC!$J$5:$J$16,MOD(K82,12)+1)&" de "&INT((K82)/12),"") | E82: =IF(NOT(AND($N$5=1,54<=$N$11)),"",IF($N$10=1,IF(AND($N$14=1,K82<=$N$12),INDEX(IPC!$D$5:$D$173,(K82)-IPC!$J$2+1)/INDEX(IPC!$D$5:$D$173,(L82)-IPC!$J$2+1)-1,""),IF(ISNUMBER(F82),F82/100,""))) | G82: =IF(AND(AND($N$5=1,54<=$N$11),ISNUMBER(G81),ISNUMBER(E82)),G81*(1+E82),"") | H82: =IF(NOT(AND($N$5=1,54<=$N$11)),"",IF(ISNUMBER(G82),"Aplicado",IF(ISNUMBER(G81),IF($N$10=1,"Falta el IPC de "&INDEX(IPC!$J$5:$J$16,MOD($N$12+1,12)+1)&" de "&INT(($N$12+1)/12),"Cargá el % de este ajuste en la columna F"),""))) | J82: =IF($N$5=1,$N$7+54*$N$8,"") | K82: =IF($N$5=1,J82-1-$N$9,"") | L82: =IF($N$5=1,K82-$N$8,"")
A83: =IF(AND($N$5=1,55<=$N$11),"55° ajuste","") | B83: =IF(AND($N$5=1,55<=$N$11),INDEX(IPC!$J$5:$J$16,MOD(J83,12)+1)&" de "&INT((J83)/12),"") | C83: =IF(AND(AND($N$5=1,55<=$N$11),$N$10=1),INDEX(IPC!$J$5:$J$16,MOD(L83,12)+1)&" de "&INT((L83)/12),"") | D83: =IF(AND(AND($N$5=1,55<=$N$11),$N$10=1),INDEX(IPC!$J$5:$J$16,MOD(K83,12)+1)&" de "&INT((K83)/12),"") | E83: =IF(NOT(AND($N$5=1,55<=$N$11)),"",IF($N$10=1,IF(AND($N$14=1,K83<=$N$12),INDEX(IPC!$D$5:$D$173,(K83)-IPC!$J$2+1)/INDEX(IPC!$D$5:$D$173,(L83)-IPC!$J$2+1)-1,""),IF(ISNUMBER(F83),F83/100,""))) | G83: =IF(AND(AND($N$5=1,55<=$N$11),ISNUMBER(G82),ISNUMBER(E83)),G82*(1+E83),"") | H83: =IF(NOT(AND($N$5=1,55<=$N$11)),"",IF(ISNUMBER(G83),"Aplicado",IF(ISNUMBER(G82),IF($N$10=1,"Falta el IPC de "&INDEX(IPC!$J$5:$J$16,MOD($N$12+1,12)+1)&" de "&INT(($N$12+1)/12),"Cargá el % de este ajuste en la columna F"),""))) | J83: =IF($N$5=1,$N$7+55*$N$8,"") | K83: =IF($N$5=1,J83-1-$N$9,"") | L83: =IF($N$5=1,K83-$N$8,"")
A84: =IF(AND($N$5=1,56<=$N$11),"56° ajuste","") | B84: =IF(AND($N$5=1,56<=$N$11),INDEX(IPC!$J$5:$J$16,MOD(J84,12)+1)&" de "&INT((J84)/12),"") | C84: =IF(AND(AND($N$5=1,56<=$N$11),$N$10=1),INDEX(IPC!$J$5:$J$16,MOD(L84,12)+1)&" de "&INT((L84)/12),"") | D84: =IF(AND(AND($N$5=1,56<=$N$11),$N$10=1),INDEX(IPC!$J$5:$J$16,MOD(K84,12)+1)&" de "&INT((K84)/12),"") | E84: =IF(NOT(AND($N$5=1,56<=$N$11)),"",IF($N$10=1,IF(AND($N$14=1,K84<=$N$12),INDEX(IPC!$D$5:$D$173,(K84)-IPC!$J$2+1)/INDEX(IPC!$D$5:$D$173,(L84)-IPC!$J$2+1)-1,""),IF(ISNUMBER(F84),F84/100,""))) | G84: =IF(AND(AND($N$5=1,56<=$N$11),ISNUMBER(G83),ISNUMBER(E84)),G83*(1+E84),"") | H84: =IF(NOT(AND($N$5=1,56<=$N$11)),"",IF(ISNUMBER(G84),"Aplicado",IF(ISNUMBER(G83),IF($N$10=1,"Falta el IPC de "&INDEX(IPC!$J$5:$J$16,MOD($N$12+1,12)+1)&" de "&INT(($N$12+1)/12),"Cargá el % de este ajuste en la columna F"),""))) | J84: =IF($N$5=1,$N$7+56*$N$8,"") | K84: =IF($N$5=1,J84-1-$N$9,"") | L84: =IF($N$5=1,K84-$N$8,"")
A85: =IF(AND($N$5=1,57<=$N$11),"57° ajuste","") | B85: =IF(AND($N$5=1,57<=$N$11),INDEX(IPC!$J$5:$J$16,MOD(J85,12)+1)&" de "&INT((J85)/12),"") | C85: =IF(AND(AND($N$5=1,57<=$N$11),$N$10=1),INDEX(IPC!$J$5:$J$16,MOD(L85,12)+1)&" de "&INT((L85)/12),"") | D85: =IF(AND(AND($N$5=1,57<=$N$11),$N$10=1),INDEX(IPC!$J$5:$J$16,MOD(K85,12)+1)&" de "&INT((K85)/12),"") | E85: =IF(NOT(AND($N$5=1,57<=$N$11)),"",IF($N$10=1,IF(AND($N$14=1,K85<=$N$12),INDEX(IPC!$D$5:$D$173,(K85)-IPC!$J$2+1)/INDEX(IPC!$D$5:$D$173,(L85)-IPC!$J$2+1)-1,""),IF(ISNUMBER(F85),F85/100,""))) | G85: =IF(AND(AND($N$5=1,57<=$N$11),ISNUMBER(G84),ISNUMBER(E85)),G84*(1+E85),"") | H85: =IF(NOT(AND($N$5=1,57<=$N$11)),"",IF(ISNUMBER(G85),"Aplicado",IF(ISNUMBER(G84),IF($N$10=1,"Falta el IPC de "&INDEX(IPC!$J$5:$J$16,MOD($N$12+1,12)+1)&" de "&INT(($N$12+1)/12),"Cargá el % de este ajuste en la columna F"),""))) | J85: =IF($N$5=1,$N$7+57*$N$8,"") | K85: =IF($N$5=1,J85-1-$N$9,"") | L85: =IF($N$5=1,K85-$N$8,"")
A86: =IF(AND($N$5=1,58<=$N$11),"58° ajuste","") | B86: =IF(AND($N$5=1,58<=$N$11),INDEX(IPC!$J$5:$J$16,MOD(J86,12)+1)&" de "&INT((J86)/12),"") | C86: =IF(AND(AND($N$5=1,58<=$N$11),$N$10=1),INDEX(IPC!$J$5:$J$16,MOD(L86,12)+1)&" de "&INT((L86)/12),"") | D86: =IF(AND(AND($N$5=1,58<=$N$11),$N$10=1),INDEX(IPC!$J$5:$J$16,MOD(K86,12)+1)&" de "&INT((K86)/12),"") | E86: =IF(NOT(AND($N$5=1,58<=$N$11)),"",IF($N$10=1,IF(AND($N$14=1,K86<=$N$12),INDEX(IPC!$D$5:$D$173,(K86)-IPC!$J$2+1)/INDEX(IPC!$D$5:$D$173,(L86)-IPC!$J$2+1)-1,""),IF(ISNUMBER(F86),F86/100,""))) | G86: =IF(AND(AND($N$5=1,58<=$N$11),ISNUMBER(G85),ISNUMBER(E86)),G85*(1+E86),"") | H86: =IF(NOT(AND($N$5=1,58<=$N$11)),"",IF(ISNUMBER(G86),"Aplicado",IF(ISNUMBER(G85),IF($N$10=1,"Falta el IPC de "&INDEX(IPC!$J$5:$J$16,MOD($N$12+1,12)+1)&" de "&INT(($N$12+1)/12),"Cargá el % de este ajuste en la columna F"),""))) | J86: =IF($N$5=1,$N$7+58*$N$8,"") | K86: =IF($N$5=1,J86-1-$N$9,"") | L86: =IF($N$5=1,K86-$N$8,"")
A87: =IF(AND($N$5=1,59<=$N$11),"59° ajuste","") | B87: =IF(AND($N$5=1,59<=$N$11),INDEX(IPC!$J$5:$J$16,MOD(J87,12)+1)&" de "&INT((J87)/12),"") | C87: =IF(AND(AND($N$5=1,59<=$N$11),$N$10=1),INDEX(IPC!$J$5:$J$16,MOD(L87,12)+1)&" de "&INT((L87)/12),"") | D87: =IF(AND(AND($N$5=1,59<=$N$11),$N$10=1),INDEX(IPC!$J$5:$J$16,MOD(K87,12)+1)&" de "&INT((K87)/12),"") | E87: =IF(NOT(AND($N$5=1,59<=$N$11)),"",IF($N$10=1,IF(AND($N$14=1,K87<=$N$12),INDEX(IPC!$D$5:$D$173,(K87)-IPC!$J$2+1)/INDEX(IPC!$D$5:$D$173,(L87)-IPC!$J$2+1)-1,""),IF(ISNUMBER(F87),F87/100,""))) | G87: =IF(AND(AND($N$5=1,59<=$N$11),ISNUMBER(G86),ISNUMBER(E87)),G86*(1+E87),"") | H87: =IF(NOT(AND($N$5=1,59<=$N$11)),"",IF(ISNUMBER(G87),"Aplicado",IF(ISNUMBER(G86),IF($N$10=1,"Falta el IPC de "&INDEX(IPC!$J$5:$J$16,MOD($N$12+1,12)+1)&" de "&INT(($N$12+1)/12),"Cargá el % de este ajuste en la columna F"),""))) | J87: =IF($N$5=1,$N$7+59*$N$8,"") | K87: =IF($N$5=1,J87-1-$N$9,"") | L87: =IF($N$5=1,K87-$N$8,"")
A88: =IF(AND($N$5=1,60<=$N$11),"60° ajuste","") | B88: =IF(AND($N$5=1,60<=$N$11),INDEX(IPC!$J$5:$J$16,MOD(J88,12)+1)&" de "&INT((J88)/12),"") | C88: =IF(AND(AND($N$5=1,60<=$N$11),$N$10=1),INDEX(IPC!$J$5:$J$16,MOD(L88,12)+1)&" de "&INT((L88)/12),"") | D88: =IF(AND(AND($N$5=1,60<=$N$11),$N$10=1),INDEX(IPC!$J$5:$J$16,MOD(K88,12)+1)&" de "&INT((K88)/12),"") | E88: =IF(NOT(AND($N$5=1,60<=$N$11)),"",IF($N$10=1,IF(AND($N$14=1,K88<=$N$12),INDEX(IPC!$D$5:$D$173,(K88)-IPC!$J$2+1)/INDEX(IPC!$D$5:$D$173,(L88)-IPC!$J$2+1)-1,""),IF(ISNUMBER(F88),F88/100,""))) | G88: =IF(AND(AND($N$5=1,60<=$N$11),ISNUMBER(G87),ISNUMBER(E88)),G87*(1+E88),"") | H88: =IF(NOT(AND($N$5=1,60<=$N$11)),"",IF(ISNUMBER(G88),"Aplicado",IF(ISNUMBER(G87),IF($N$10=1,"Falta el IPC de "&INDEX(IPC!$J$5:$J$16,MOD($N$12+1,12)+1)&" de "&INT(($N$12+1)/12),"Cargá el % de este ajuste en la columna F"),""))) | J88: =IF($N$5=1,$N$7+60*$N$8,"") | K88: =IF($N$5=1,J88-1-$N$9,"") | L88: =IF($N$5=1,K88-$N$8,"")
A90: Cada ajuste multiplica el alquiler vigente por la variación del índice del período: IPC del último mes ÷ IPC del mes anterior al primero. Los porcentajes se componen, no se suman. La letra de tu contrato manda: si dice otra cosa, ajustá el índice o la convención de arriba.

Sheet Contrato 2
A1: Contrato 2
A2: Completá las celdas amarillas con los datos del contrato. Las verdes se calculan solas.
A4: DATOS DEL CONTRATO
A5: Propiedad (dirección) | N5: =IF(AND(N6>0,ISNUMBER(B9),ISNUMBER(B11),B11>0,ISNUMBER(B13),B13>=1,ISNUMBER(B10),B10>=1),1,0)
A6: Inquilino/a | N6: =IFERROR(MATCH(B8,IPC!$J$5:$J$16,0),0)
A7: Tu nombre (para el recibo y el aviso) | N7: =IF(N5=1,B9*12+N6-1,0)
A8: Mes de inicio del contrato | C8: El primer mes en que se cobró el valor inicial. | N8: =IF(N5=1,INT(B13),1)
A9: Año de inicio | N9: =IF(B14="Los últimos publicados",1,0)
A10: Duración (meses) | B10: 24 | N10: =IF(B12="Otro índice (cargo el %)",0,1)
A11: Alquiler inicial (el del primer mes) | N11: =IF(N5=1,MIN(INT((B10-1)/N8),60),0)
A12: Índice de ajuste | B12: IPC (INDEC) | C12: Si tu contrato ajusta por ICL, Casa Propia u otro índice, elegí «Otro» y cargá el % de cada ajuste en el cronograma (columna F). | N12: =IPC!$J$3
A13: Se ajusta cada (meses) | B13: 3 | C13: Trimestral = 3, cuatrimestral = 4, semestral = 6, anual = 12. | N13: =IPC!$J$2
A14: Meses del IPC que toma | B14: Los completos antes del ajuste | C14: «Completos»: un ajuste de julio usa el IPC de abril a junio (como la calculadora de calcular.ar). «Últimos publicados»: usa el de marzo a mayo, porque el de junio sale a mitad de julio. Fijate qué dice tu contrato. | N14: =IF(N5=0,0,IF(N10=0,1,IF(AND(N7-1-N9>=N13,N7-1-N9<=N12),1,0)))
N15: =COUNT(G29:G88)
A16: CÓMO VIENE EL CONTRATO | N16: =IF(N5=1,INDEX(G28:G88,N15+1),"")
A17: Alquiler que se cobra hoy | B17: =N16 | N17: =N15+1
A18: Rige desde | B18: =IF(N5=1,INDEX(B28:B88,N15+1),"") | N18: =IF(AND(N5=1,N17<=N11),1,0)
A19: Ajustes aplicados | B19: =IF(N5=1,N15,"") | N19: =N7+N17*N8-1-N9
A20: Aumento desde el inicio | B20: =IF(N5=1,N16/B11-1,"") | N20: =N19-N12
A21: Próximo ajuste | B21: =IF(N18=1,INDEX(B28:B88,N17+1),IF(N5=1,"No quedan ajustes antes de que termine","")) | N21: =INDEX(IPC!$D$5:$D$173,(N12)-IPC!$J$2+1)/INDEX(IPC!$D$5:$D$173,(N12-1)-IPC!$J$2+1)-1
A22: Próximo alquiler estimado | B22: =N22 | N22: =IF(AND(N18=1,N10=1,N14=1,N20>0,N20<=12),N16*INDEX(IPC!$D$5:$D$173,(N12)-IPC!$J$2+1)*(1+N21)^N20/INDEX(IPC!$D$5:$D$173,(N19-N8)-IPC!$J$2+1),"")
A23: Último mes del contrato | B23: =IF(N5=1,INDEX(IPC!$J$5:$J$16,MOD(N7+B10-1,12)+1)&" de "&INT((N7+B10-1)/12),"") | N23: =IF(ISNUMBER(N22),ROUND(N22,0),"")
A24: Qué hacer ahora | B24: =IF(N5=0,"Completá las celdas amarillas de arriba y acá aparece el cronograma de aumentos.",IF(N14=0,"Todavía no está publicado el IPC de "&INDEX(IPC!$J$5:$J$16,MOD(N7-1-N9,12)+1)&" de "&INT((N7-1-N9)/12)&", que es la base de este contrato. Mientras tanto se cobra el valor inicial.",IF(N18=0,"No quedan ajustes: el contrato termina en "&INDEX(IPC!$J$5:$J$16,MOD(N7+B10-1,12)+1)&" de "&INT((N7+B10-1)/12)&".",IF(N10=1,"El próximo ajuste rige desde "&B21&". Se calcula cuando el INDEC publique el IPC de "&INDEX(IPC!$J$5:$J$16,MOD(N19,12)+1)&" de "&INT((N19)/12)&" (sale entre el 10 y el 15 del mes siguiente)"&IF(ISNUMBER(N22),". Si la inflación siguiera como el último mes, el alquiler quedaría en unos $ "&N24&".","."),"El próximo ajuste rige desde "&B21&": cuando lo tengas, cargá el % del índice pactado en la columna F del cronograma.")))) | N24: =IF(ISNUMBER(N23),IF(N23>=1000000000,INT(N23/1000000000)&"."&RIGHT("00"&INT(MOD(N23,1000000000)/1000000),3)&"."&RIGHT("00"&INT(MOD(N23,1000000)/1000),3)&"."&RIGHT("00"&INT(MOD(N23,1000)/1),3),IF(N23>=1000000,INT(N23/1000000)&"."&RIGHT("00"&INT(MOD(N23,1000000)/1000),3)&"."&RIGHT("00"&INT(MOD(N23,1000)/1),3),IF(N23>=1000,INT(N23/1000)&"."&RIGHT("00"&INT(MOD(N23,1000)/1),3),""&N23))),"")
A26: CRONOGRAMA DE AJUSTES
A27: Ajuste | B27: Rige desde | C27: Mes del IPC base | D27: Mes del IPC final | E27: Variación | F27: % a mano (otro índice) | G27: Alquiler | H27: Estado
A28: =IF($N$5=1,"Valor inicial","") | B28: =IF($N$5=1,INDEX(IPC!$J$5:$J$16,MOD(J28,12)+1)&" de "&INT((J28)/12),"") | G28: =IF($N$5=1,B11,"") | H28: =IF($N$5=1,"Valor inicial del contrato","") | J28: =IF($N$5=1,$N$7+0*$N$8,"") | K28: =IF($N$5=1,J28-1-$N$9,"") | L28: =IF($N$5=1,K28-$N$8,"")
A29: =IF(AND($N$5=1,1<=$N$11),"1° ajuste","") | B29: =IF(AND($N$5=1,1<=$N$11),INDEX(IPC!$J$5:$J$16,MOD(J29,12)+1)&" de "&INT((J29)/12),"") | C29: =IF(AND(AND($N$5=1,1<=$N$11),$N$10=1),INDEX(IPC!$J$5:$J$16,MOD(L29,12)+1)&" de "&INT((L29)/12),"") | D29: =IF(AND(AND($N$5=1,1<=$N$11),$N$10=1),INDEX(IPC!$J$5:$J$16,MOD(K29,12)+1)&" de "&INT((K29)/12),"") | E29: =IF(NOT(AND($N$5=1,1<=$N$11)),"",IF($N$10=1,IF(AND($N$14=1,K29<=$N$12),INDEX(IPC!$D$5:$D$173,(K29)-IPC!$J$2+1)/INDEX(IPC!$D$5:$D$173,(L29)-IPC!$J$2+1)-1,""),IF(ISNUMBER(F29),F29/100,""))) | G29: =IF(AND(AND($N$5=1,1<=$N$11),ISNUMBER(G28),ISNUMBER(E29)),G28*(1+E29),"") | H29: =IF(NOT(AND($N$5=1,1<=$N$11)),"",IF(ISNUMBER(G29),"Aplicado",IF(ISNUMBER(G28),IF($N$10=1,"Falta el IPC de "&INDEX(IPC!$J$5:$J$16,MOD($N$12+1,12)+1)&" de "&INT(($N$12+1)/12),"Cargá el % de este ajuste en la columna F"),""))) | J29: =IF($N$5=1,$N$7+1*$N$8,"") | K29: =IF($N$5=1,J29-1-$N$9,"") | L29: =IF($N$5=1,K29-$N$8,"")
A30: =IF(AND($N$5=1,2<=$N$11),"2° ajuste","") | B30: =IF(AND($N$5=1,2<=$N$11),INDEX(IPC!$J$5:$J$16,MOD(J30,12)+1)&" de "&INT((J30)/12),"") | C30: =IF(AND(AND($N$5=1,2<=$N$11),$N$10=1),INDEX(IPC!$J$5:$J$16,MOD(L30,12)+1)&" de "&INT((L30)/12),"") | D30: =IF(AND(AND($N$5=1,2<=$N$11),$N$10=1),INDEX(IPC!$J$5:$J$16,MOD(K30,12)+1)&" de "&INT((K30)/12),"") | E30: =IF(NOT(AND($N$5=1,2<=$N$11)),"",IF($N$10=1,IF(AND($N$14=1,K30<=$N$12),INDEX(IPC!$D$5:$D$173,(K30)-IPC!$J$2+1)/INDEX(IPC!$D$5:$D$173,(L30)-IPC!$J$2+1)-1,""),IF(ISNUMBER(F30),F30/100,""))) | G30: =IF(AND(AND($N$5=1,2<=$N$11),ISNUMBER(G29),ISNUMBER(E30)),G29*(1+E30),"") | H30: =IF(NOT(AND($N$5=1,2<=$N$11)),"",IF(ISNUMBER(G30),"Aplicado",IF(ISNUMBER(G29),IF($N$10=1,"Falta el IPC de "&INDEX(IPC!$J$5:$J$16,MOD($N$12+1,12)+1)&" de "&INT(($N$12+1)/12),"Cargá el % de este ajuste en la columna F"),""))) | J30: =IF($N$5=1,$N$7+2*$N$8,"") | K30: =IF($N$5=1,J30-1-$N$9,"") | L30: =IF($N$5=1,K30-$N$8,"")
A31: =IF(AND($N$5=1,3<=$N$11),"3° ajuste","") | B31: =IF(AND($N$5=1,3<=$N$11),INDEX(IPC!$J$5:$J$16,MOD(J31,12)+1)&" de "&INT((J31)/12),"") | C31: =IF(AND(AND($N$5=1,3<=$N$11),$N$10=1),INDEX(IPC!$J$5:$J$16,MOD(L31,12)+1)&" de "&INT((L31)/12),"") | D31: =IF(AND(AND($N$5=1,3<=$N$11),$N$10=1),INDEX(IPC!$J$5:$J$16,MOD(K31,12)+1)&" de "&INT((K31)/12),"") | E31: =IF(NOT(AND($N$5=1,3<=$N$11)),"",IF($N$10=1,IF(AND($N$14=1,K31<=$N$12),INDEX(IPC!$D$5:$D$173,(K31)-IPC!$J$2+1)/INDEX(IPC!$D$5:$D$173,(L31)-IPC!$J$2+1)-1,""),IF(ISNUMBER(F31),F31/100,""))) | G31: =IF(AND(AND($N$5=1,3<=$N$11),ISNUMBER(G30),ISNUMBER(E31)),G30*(1+E31),"") | H31: =IF(NOT(AND($N$5=1,3<=$N$11)),"",IF(ISNUMBER(G31),"Aplicado",IF(ISNUMBER(G30),IF($N$10=1,"Falta el IPC de "&INDEX(IPC!$J$5:$J$16,MOD($N$12+1,12)+1)&" de "&INT(($N$12+1)/12),"Cargá el % de este ajuste en la columna F"),""))) | J31: =IF($N$5=1,$N$7+3*$N$8,"") | K31: =IF($N$5=1,J31-1-$N$9,"") | L31: =IF($N$5=1,K31-$N$8,"")
A32: =IF(AND($N$5=1,4<=$N$11),"4° ajuste","") | B32: =IF(AND($N$5=1,4<=$N$11),INDEX(IPC!$J$5:$J$16,MOD(J32,12)+1)&" de "&INT((J32)/12),"") | C32: =IF(AND(AND($N$5=1,4<=$N$11),$N$10=1),INDEX(IPC!$J$5:$J$16,MOD(L32,12)+1)&" de "&INT((L32)/12),"") | D32: =IF(AND(AND($N$5=1,4<=$N$11),$N$10=1),INDEX(IPC!$J$5:$J$16,MOD(K32,12)+1)&" de "&INT((K32)/12),"") | E32: =IF(NOT(AND($N$5=1,4<=$N$11)),"",IF($N$10=1,IF(AND($N$14=1,K32<=$N$12),INDEX(IPC!$D$5:$D$173,(K32)-IPC!$J$2+1)/INDEX(IPC!$D$5:$D$173,(L32)-IPC!$J$2+1)-1,""),IF(ISNUMBER(F32),F32/100,""))) | G32: =IF(AND(AND($N$5=1,4<=$N$11),ISNUMBER(G31),ISNUMBER(E32)),G31*(1+E32),"") | H32: =IF(NOT(AND($N$5=1,4<=$N$11)),"",IF(ISNUMBER(G32),"Aplicado",IF(ISNUMBER(G31),IF($N$10=1,"Falta el IPC de "&INDEX(IPC!$J$5:$J$16,MOD($N$12+1,12)+1)&" de "&INT(($N$12+1)/12),"Cargá el % de este ajuste en la columna F"),""))) | J32: =IF($N$5=1,$N$7+4*$N$8,"") | K32: =IF($N$5=1,J32-1-$N$9,"") | L32: =IF($N$5=1,K32-$N$8,"")
A33: =IF(AND($N$5=1,5<=$N$11),"5° ajuste","") | B33: =IF(AND($N$5=1,5<=$N$11),INDEX(IPC!$J$5:$J$16,MOD(J33,12)+1)&" de "&INT((J33)/12),"") | C33: =IF(AND(AND($N$5=1,5<=$N$11),$N$10=1),INDEX(IPC!$J$5:$J$16,MOD(L33,12)+1)&" de "&INT((L33)/12),"") | D33: =IF(AND(AND($N$5=1,5<=$N$11),$N$10=1),INDEX(IPC!$J$5:$J$16,MOD(K33,12)+1)&" de "&INT((K33)/12),"") | E33: =IF(NOT(AND($N$5=1,5<=$N$11)),"",IF($N$10=1,IF(AND($N$14=1,K33<=$N$12),INDEX(IPC!$D$5:$D$173,(K33)-IPC!$J$2+1)/INDEX(IPC!$D$5:$D$173,(L33)-IPC!$J$2+1)-1,""),IF(ISNUMBER(F33),F33/100,""))) | G33: =IF(AND(AND($N$5=1,5<=$N$11),ISNUMBER(G32),ISNUMBER(E33)),G32*(1+E33),"") | H33: =IF(NOT(AND($N$5=1,5<=$N$11)),"",IF(ISNUMBER(G33),"Aplicado",IF(ISNUMBER(G32),IF($N$10=1,"Falta el IPC de "&INDEX(IPC!$J$5:$J$16,MOD($N$12+1,12)+1)&" de "&INT(($N$12+1)/12),"Cargá el % de este ajuste en la columna F"),""))) | J33: =IF($N$5=1,$N$7+5*$N$8,"") | K33: =IF($N$5=1,J33-1-$N$9,"") | L33: =IF($N$5=1,K33-$N$8,"")
A34: =IF(AND($N$5=1,6<=$N$11),"6° ajuste","") | B34: =IF(AND($N$5=1,6<=$N$11),INDEX(IPC!$J$5:$J$16,MOD(J34,12)+1)&" de "&INT((J34)/12),"") | C34: =IF(AND(AND($N$5=1,6<=$N$11),$N$10=1),INDEX(IPC!$J$5:$J$16,MOD(L34,12)+1)&" de "&INT((L34)/12),"") | D34: =IF(AND(AND($N$5=1,6<=$N$11),$N$10=1),INDEX(IPC!$J$5:$J$16,MOD(K34,12)+1)&" de "&INT((K34)/12),"") | E34: =IF(NOT(AND($N$5=1,6<=$N$11)),"",IF($N$10=1,IF(AND($N$14=1,K34<=$N$12),INDEX(IPC!$D$5:$D$173,(K34)-IPC!$J$2+1)/INDEX(IPC!$D$5:$D$173,(L34)-IPC!$J$2+1)-1,""),IF(ISNUMBER(F34),F34/100,""))) | G34: =IF(AND(AND($N$5=1,6<=$N$11),ISNUMBER(G33),ISNUMBER(E34)),G33*(1+E34),"") | H34: =IF(NOT(AND($N$5=1,6<=$N$11)),"",IF(ISNUMBER(G34),"Aplicado",IF(ISNUMBER(G33),IF($N$10=1,"Falta el IPC de "&INDEX(IPC!$J$5:$J$16,MOD($N$12+1,12)+1)&" de "&INT(($N$12+1)/12),"Cargá el % de este ajuste en la columna F"),""))) | J34: =IF($N$5=1,$N$7+6*$N$8,"") | K34: =IF($N$5=1,J34-1-$N$9,"") | L34: =IF($N$5=1,K34-$N$8,"")
A35: =IF(AND($N$5=1,7<=$N$11),"7° ajuste","") | B35: =IF(AND($N$5=1,7<=$N$11),INDEX(IPC!$J$5:$J$16,MOD(J35,12)+1)&" de "&INT((J35)/12),"") | C35: =IF(AND(AND($N$5=1,7<=$N$11),$N$10=1),INDEX(IPC!$J$5:$J$16,MOD(L35,12)+1)&" de "&INT((L35)/12),"") | D35: =IF(AND(AND($N$5=1,7<=$N$11),$N$10=1),INDEX(IPC!$J$5:$J$16,MOD(K35,12)+1)&" de "&INT((K35)/12),"") | E35: =IF(NOT(AND($N$5=1,7<=$N$11)),"",IF($N$10=1,IF(AND($N$14=1,K35<=$N$12),INDEX(IPC!$D$5:$D$173,(K35)-IPC!$J$2+1)/INDEX(IPC!$D$5:$D$173,(L35)-IPC!$J$2+1)-1,""),IF(ISNUMBER(F35),F35/100,""))) | G35: =IF(AND(AND($N$5=1,7<=$N$11),ISNUMBER(G34),ISNUMBER(E35)),G34*(1+E35),"") | H35: =IF(NOT(AND($N$5=1,7<=$N$11)),"",IF(ISNUMBER(G35),"Aplicado",IF(ISNUMBER(G34),IF($N$10=1,"Falta el IPC de "&INDEX(IPC!$J$5:$J$16,MOD($N$12+1,12)+1)&" de "&INT(($N$12+1)/12),"Cargá el % de este ajuste en la columna F"),""))) | J35: =IF($N$5=1,$N$7+7*$N$8,"") | K35: =IF($N$5=1,J35-1-$N$9,"") | L35: =IF($N$5=1,K35-$N$8,"")
A36: =IF(AND($N$5=1,8<=$N$11),"8° ajuste","") | B36: =IF(AND($N$5=1,8<=$N$11),INDEX(IPC!$J$5:$J$16,MOD(J36,12)+1)&" de "&INT((J36)/12),"") | C36: =IF(AND(AND($N$5=1,8<=$N$11),$N$10=1),INDEX(IPC!$J$5:$J$16,MOD(L36,12)+1)&" de "&INT((L36)/12),"") | D36: =IF(AND(AND($N$5=1,8<=$N$11),$N$10=1),INDEX(IPC!$J$5:$J$16,MOD(K36,12)+1)&" de "&INT((K36)/12),"") | E36: =IF(NOT(AND($N$5=1,8<=$N$11)),"",IF($N$10=1,IF(AND($N$14=1,K36<=$N$12),INDEX(IPC!$D$5:$D$173,(K36)-IPC!$J$2+1)/INDEX(IPC!$D$5:$D$173,(L36)-IPC!$J$2+1)-1,""),IF(ISNUMBER(F36),F36/100,""))) | G36: =IF(AND(AND($N$5=1,8<=$N$11),ISNUMBER(G35),ISNUMBER(E36)),G35*(1+E36),"") | H36: =IF(NOT(AND($N$5=1,8<=$N$11)),"",IF(ISNUMBER(G36),"Aplicado",IF(ISNUMBER(G35),IF($N$10=1,"Falta el IPC de "&INDEX(IPC!$J$5:$J$16,MOD($N$12+1,12)+1)&" de "&INT(($N$12+1)/12),"Cargá el % de este ajuste en la columna F"),""))) | J36: =IF($N$5=1,$N$7+8*$N$8,"") | K36: =IF($N$5=1,J36-1-$N$9,"") | L36: =IF($N$5=1,K36-$N$8,"")
A37: =IF(AND($N$5=1,9<=$N$11),"9° ajuste","") | B37: =IF(AND($N$5=1,9<=$N$11),INDEX(IPC!$J$5:$J$16,MOD(J37,12)+1)&" de "&INT((J37)/12),"") | C37: =IF(AND(AND($N$5=1,9<=$N$11),$N$10=1),INDEX(IPC!$J$5:$J$16,MOD(L37,12)+1)&" de "&INT((L37)/12),"") | D37: =IF(AND(AND($N$5=1,9<=$N$11),$N$10=1),INDEX(IPC!$J$5:$J$16,MOD(K37,12)+1)&" de "&INT((K37)/12),"") | E37: =IF(NOT(AND($N$5=1,9<=$N$11)),"",IF($N$10=1,IF(AND($N$14=1,K37<=$N$12),INDEX(IPC!$D$5:$D$173,(K37)-IPC!$J$2+1)/INDEX(IPC!$D$5:$D$173,(L37)-IPC!$J$2+1)-1,""),IF(ISNUMBER(F37),F37/100,""))) | G37: =IF(AND(AND($N$5=1,9<=$N$11),ISNUMBER(G36),ISNUMBER(E37)),G36*(1+E37),"") | H37: =IF(NOT(AND($N$5=1,9<=$N$11)),"",IF(ISNUMBER(G37),"Aplicado",IF(ISNUMBER(G36),IF($N$10=1,"Falta el IPC de "&INDEX(IPC!$J$5:$J$16,MOD($N$12+1,12)+1)&" de "&INT(($N$12+1)/12),"Cargá el % de este ajuste en la columna F"),""))) | J37: =IF($N$5=1,$N$7+9*$N$8,"") | K37: =IF($N$5=1,J37-1-$N$9,"") | L37: =IF($N$5=1,K37-$N$8,"")
A38: =IF(AND($N$5=1,10<=$N$11),"10° ajuste","") | B38: =IF(AND($N$5=1,10<=$N$11),INDEX(IPC!$J$5:$J$16,MOD(J38,12)+1)&" de "&INT((J38)/12),"") | C38: =IF(AND(AND($N$5=1,10<=$N$11),$N$10=1),INDEX(IPC!$J$5:$J$16,MOD(L38,12)+1)&" de "&INT((L38)/12),"") | D38: =IF(AND(AND($N$5=1,10<=$N$11),$N$10=1),INDEX(IPC!$J$5:$J$16,MOD(K38,12)+1)&" de "&INT((K38)/12),"") | E38: =IF(NOT(AND($N$5=1,10<=$N$11)),"",IF($N$10=1,IF(AND($N$14=1,K38<=$N$12),INDEX(IPC!$D$5:$D$173,(K38)-IPC!$J$2+1)/INDEX(IPC!$D$5:$D$173,(L38)-IPC!$J$2+1)-1,""),IF(ISNUMBER(F38),F38/100,""))) | G38: =IF(AND(AND($N$5=1,10<=$N$11),ISNUMBER(G37),ISNUMBER(E38)),G37*(1+E38),"") | H38: =IF(NOT(AND($N$5=1,10<=$N$11)),"",IF(ISNUMBER(G38),"Aplicado",IF(ISNUMBER(G37),IF($N$10=1,"Falta el IPC de "&INDEX(IPC!$J$5:$J$16,MOD($N$12+1,12)+1)&" de "&INT(($N$12+1)/12),"Cargá el % de este ajuste en la columna F"),""))) | J38: =IF($N$5=1,$N$7+10*$N$8,"") | K38: =IF($N$5=1,J38-1-$N$9,"") | L38: =IF($N$5=1,K38-$N$8,"")
A39: =IF(AND($N$5=1,11<=$N$11),"11° ajuste","") | B39: =IF(AND($N$5=1,11<=$N$11),INDEX(IPC!$J$5:$J$16,MOD(J39,12)+1)&" de "&INT((J39)/12),"") | C39: =IF(AND(AND($N$5=1,11<=$N$11),$N$10=1),INDEX(IPC!$J$5:$J$16,MOD(L39,12)+1)&" de "&INT((L39)/12),"") | D39: =IF(AND(AND($N$5=1,11<=$N$11),$N$10=1),INDEX(IPC!$J$5:$J$16,MOD(K39,12)+1)&" de "&INT((K39)/12),"") | E39: =IF(NOT(AND($N$5=1,11<=$N$11)),"",IF($N$10=1,IF(AND($N$14=1,K39<=$N$12),INDEX(IPC!$D$5:$D$173,(K39)-IPC!$J$2+1)/INDEX(IPC!$D$5:$D$173,(L39)-IPC!$J$2+1)-1,""),IF(ISNUMBER(F39),F39/100,""))) | G39: =IF(AND(AND($N$5=1,11<=$N$11),ISNUMBER(G38),ISNUMBER(E39)),G38*(1+E39),"") | H39: =IF(NOT(AND($N$5=1,11<=$N$11)),"",IF(ISNUMBER(G39),"Aplicado",IF(ISNUMBER(G38),IF($N$10=1,"Falta el IPC de "&INDEX(IPC!$J$5:$J$16,MOD($N$12+1,12)+1)&" de "&INT(($N$12+1)/12),"Cargá el % de este ajuste en la columna F"),""))) | J39: =IF($N$5=1,$N$7+11*$N$8,"") | K39: =IF($N$5=1,J39-1-$N$9,"") | L39: =IF($N$5=1,K39-$N$8,"")
A40: =IF(AND($N$5=1,12<=$N$11),"12° ajuste","") | B40: =IF(AND($N$5=1,12<=$N$11),INDEX(IPC!$J$5:$J$16,MOD(J40,12)+1)&" de "&INT((J40)/12),"") | C40: =IF(AND(AND($N$5=1,12<=$N$11),$N$10=1),INDEX(IPC!$J$5:$J$16,MOD(L40,12)+1)&" de "&INT((L40)/12),"") | D40: =IF(AND(AND($N$5=1,12<=$N$11),$N$10=1),INDEX(IPC!$J$5:$J$16,MOD(K40,12)+1)&" de "&INT((K40)/12),"") | E40: =IF(NOT(AND($N$5=1,12<=$N$11)),"",IF($N$10=1,IF(AND($N$14=1,K40<=$N$12),INDEX(IPC!$D$5:$D$173,(K40)-IPC!$J$2+1)/INDEX(IPC!$D$5:$D$173,(L40)-IPC!$J$2+1)-1,""),IF(ISNUMBER(F40),F40/100,""))) | G40: =IF(AND(AND($N$5=1,12<=$N$11),ISNUMBER(G39),ISNUMBER(E40)),G39*(1+E40),"") | H40: =IF(NOT(AND($N$5=1,12<=$N$11)),"",IF(ISNUMBER(G40),"Aplicado",IF(ISNUMBER(G39),IF($N$10=1,"Falta el IPC de "&INDEX(IPC!$J$5:$J$16,MOD($N$12+1,12)+1)&" de "&INT(($N$12+1)/12),"Cargá el % de este ajuste en la columna F"),""))) | J40: =IF($N$5=1,$N$7+12*$N$8,"") | K40: =IF($N$5=1,J40-1-$N$9,"") | L40: =IF($N$5=1,K40-$N$8,"")
A41: =IF(AND($N$5=1,13<=$N$11),"13° ajuste","") | B41: =IF(AND($N$5=1,13<=$N$11),INDEX(IPC!$J$5:$J$16,MOD(J41,12)+1)&" de "&INT((J41)/12),"") | C41: =IF(AND(AND($N$5=1,13<=$N$11),$N$10=1),INDEX(IPC!$J$5:$J$16,MOD(L41,12)+1)&" de "&INT((L41)/12),"") | D41: =IF(AND(AND($N$5=1,13<=$N$11),$N$10=1),INDEX(IPC!$J$5:$J$16,MOD(K41,12)+1)&" de "&INT((K41)/12),"") | E41: =IF(NOT(AND($N$5=1,13<=$N$11)),"",IF($N$10=1,IF(AND($N$14=1,K41<=$N$12),INDEX(IPC!$D$5:$D$173,(K41)-IPC!$J$2+1)/INDEX(IPC!$D$5:$D$173,(L41)-IPC!$J$2+1)-1,""),IF(ISNUMBER(F41),F41/100,""))) | G41: =IF(AND(AND($N$5=1,13<=$N$11),ISNUMBER(G40),ISNUMBER(E41)),G40*(1+E41),"") | H41: =IF(NOT(AND($N$5=1,13<=$N$11)),"",IF(ISNUMBER(G41),"Aplicado",IF(ISNUMBER(G40),IF($N$10=1,"Falta el IPC de "&INDEX(IPC!$J$5:$J$16,MOD($N$12+1,12)+1)&" de "&INT(($N$12+1)/12),"Cargá el % de este ajuste en la columna F"),""))) | J41: =IF($N$5=1,$N$7+13*$N$8,"") | K41: =IF($N$5=1,J41-1-$N$9,"") | L41: =IF($N$5=1,K41-$N$8,"")
A42: =IF(AND($N$5=1,14<=$N$11),"14° ajuste","") | B42: =IF(AND($N$5=1,14<=$N$11),INDEX(IPC!$J$5:$J$16,MOD(J42,12)+1)&" de "&INT((J42)/12),"") | C42: =IF(AND(AND($N$5=1,14<=$N$11),$N$10=1),INDEX(IPC!$J$5:$J$16,MOD(L42,12)+1)&" de "&INT((L42)/12),"") | D42: =IF(AND(AND($N$5=1,14<=$N$11),$N$10=1),INDEX(IPC!$J$5:$J$16,MOD(K42,12)+1)&" de "&INT((K42)/12),"") | E42: =IF(NOT(AND($N$5=1,14<=$N$11)),"",IF($N$10=1,IF(AND($N$14=1,K42<=$N$12),INDEX(IPC!$D$5:$D$173,(K42)-IPC!$J$2+1)/INDEX(IPC!$D$5:$D$173,(L42)-IPC!$J$2+1)-1,""),IF(ISNUMBER(F42),F42/100,""))) | G42: =IF(AND(AND($N$5=1,14<=$N$11),ISNUMBER(G41),ISNUMBER(E42)),G41*(1+E42),"") | H42: =IF(NOT(AND($N$5=1,14<=$N$11)),"",IF(ISNUMBER(G42),"Aplicado",IF(ISNUMBER(G41),IF($N$10=1,"Falta el IPC de "&INDEX(IPC!$J$5:$J$16,MOD($N$12+1,12)+1)&" de "&INT(($N$12+1)/12),"Cargá el % de este ajuste en la columna F"),""))) | J42: =IF($N$5=1,$N$7+14*$N$8,"") | K42: =IF($N$5=1,J42-1-$N$9,"") | L42: =IF($N$5=1,K42-$N$8,"")
A43: =IF(AND($N$5=1,15<=$N$11),"15° ajuste","") | B43: =IF(AND($N$5=1,15<=$N$11),INDEX(IPC!$J$5:$J$16,MOD(J43,12)+1)&" de "&INT((J43)/12),"") | C43: =IF(AND(AND($N$5=1,15<=$N$11),$N$10=1),INDEX(IPC!$J$5:$J$16,MOD(L43,12)+1)&" de "&INT((L43)/12),"") | D43: =IF(AND(AND($N$5=1,15<=$N$11),$N$10=1),INDEX(IPC!$J$5:$J$16,MOD(K43,12)+1)&" de "&INT((K43)/12),"") | E43: =IF(NOT(AND($N$5=1,15<=$N$11)),"",IF($N$10=1,IF(AND($N$14=1,K43<=$N$12),INDEX(IPC!$D$5:$D$173,(K43)-IPC!$J$2+1)/INDEX(IPC!$D$5:$D$173,(L43)-IPC!$J$2+1)-1,""),IF(ISNUMBER(F43),F43/100,""))) | G43: =IF(AND(AND($N$5=1,15<=$N$11),ISNUMBER(G42),ISNUMBER(E43)),G42*(1+E43),"") | H43: =IF(NOT(AND($N$5=1,15<=$N$11)),"",IF(ISNUMBER(G43),"Aplicado",IF(ISNUMBER(G42),IF($N$10=1,"Falta el IPC de "&INDEX(IPC!$J$5:$J$16,MOD($N$12+1,12)+1)&" de "&INT(($N$12+1)/12),"Cargá el % de este ajuste en la columna F"),""))) | J43: =IF($N$5=1,$N$7+15*$N$8,"") | K43: =IF($N$5=1,J43-1-$N$9,"") | L43: =IF($N$5=1,K43-$N$8,"")
A44: =IF(AND($N$5=1,16<=$N$11),"16° ajuste","") | B44: =IF(AND($N$5=1,16<=$N$11),INDEX(IPC!$J$5:$J$16,MOD(J44,12)+1)&" de "&INT((J44)/12),"") | C44: =IF(AND(AND($N$5=1,16<=$N$11),$N$10=1),INDEX(IPC!$J$5:$J$16,MOD(L44,12)+1)&" de "&INT((L44)/12),"") | D44: =IF(AND(AND($N$5=1,16<=$N$11),$N$10=1),INDEX(IPC!$J$5:$J$16,MOD(K44,12)+1)&" de "&INT((K44)/12),"") | E44: =IF(NOT(AND($N$5=1,16<=$N$11)),"",IF($N$10=1,IF(AND($N$14=1,K44<=$N$12),INDEX(IPC!$D$5:$D$173,(K44)-IPC!$J$2+1)/INDEX(IPC!$D$5:$D$173,(L44)-IPC!$J$2+1)-1,""),IF(ISNUMBER(F44),F44/100,""))) | G44: =IF(AND(AND($N$5=1,16<=$N$11),ISNUMBER(G43),ISNUMBER(E44)),G43*(1+E44),"") | H44: =IF(NOT(AND($N$5=1,16<=$N$11)),"",IF(ISNUMBER(G44),"Aplicado",IF(ISNUMBER(G43),IF($N$10=1,"Falta el IPC de "&INDEX(IPC!$J$5:$J$16,MOD($N$12+1,12)+1)&" de "&INT(($N$12+1)/12),"Cargá el % de este ajuste en la columna F"),""))) | J44: =IF($N$5=1,$N$7+16*$N$8,"") | K44: =IF($N$5=1,J44-1-$N$9,"") | L44: =IF($N$5=1,K44-$N$8,"")
A45: =IF(AND($N$5=1,17<=$N$11),"17° ajuste","") | B45: =IF(AND($N$5=1,17<=$N$11),INDEX(IPC!$J$5:$J$16,MOD(J45,12)+1)&" de "&INT((J45)/12),"") | C45: =IF(AND(AND($N$5=1,17<=$N$11),$N$10=1),INDEX(IPC!$J$5:$J$16,MOD(L45,12)+1)&" de "&INT((L45)/12),"") | D45: =IF(AND(AND($N$5=1,17<=$N$11),$N$10=1),INDEX(IPC!$J$5:$J$16,MOD(K45,12)+1)&" de "&INT((K45)/12),"") | E45: =IF(NOT(AND($N$5=1,17<=$N$11)),"",IF($N$10=1,IF(AND($N$14=1,K45<=$N$12),INDEX(IPC!$D$5:$D$173,(K45)-IPC!$J$2+1)/INDEX(IPC!$D$5:$D$173,(L45)-IPC!$J$2+1)-1,""),IF(ISNUMBER(F45),F45/100,""))) | G45: =IF(AND(AND($N$5=1,17<=$N$11),ISNUMBER(G44),ISNUMBER(E45)),G44*(1+E45),"") | H45: =IF(NOT(AND($N$5=1,17<=$N$11)),"",IF(ISNUMBER(G45),"Aplicado",IF(ISNUMBER(G44),IF($N$10=1,"Falta el IPC de "&INDEX(IPC!$J$5:$J$16,MOD($N$12+1,12)+1)&" de "&INT(($N$12+1)/12),"Cargá el % de este ajuste en la columna F"),""))) | J45: =IF($N$5=1,$N$7+17*$N$8,"") | K45: =IF($N$5=1,J45-1-$N$9,"") | L45: =IF($N$5=1,K45-$N$8,"")
A46: =IF(AND($N$5=1,18<=$N$11),"18° ajuste","") | B46: =IF(AND($N$5=1,18<=$N$11),INDEX(IPC!$J$5:$J$16,MOD(J46,12)+1)&" de "&INT((J46)/12),"") | C46: =IF(AND(AND($N$5=1,18<=$N$11),$N$10=1),INDEX(IPC!$J$5:$J$16,MOD(L46,12)+1)&" de "&INT((L46)/12),"") | D46: =IF(AND(AND($N$5=1,18<=$N$11),$N$10=1),INDEX(IPC!$J$5:$J$16,MOD(K46,12)+1)&" de "&INT((K46)/12),"") | E46: =IF(NOT(AND($N$5=1,18<=$N$11)),"",IF($N$10=1,IF(AND($N$14=1,K46<=$N$12),INDEX(IPC!$D$5:$D$173,(K46)-IPC!$J$2+1)/INDEX(IPC!$D$5:$D$173,(L46)-IPC!$J$2+1)-1,""),IF(ISNUMBER(F46),F46/100,""))) | G46: =IF(AND(AND($N$5=1,18<=$N$11),ISNUMBER(G45),ISNUMBER(E46)),G45*(1+E46),"") | H46: =IF(NOT(AND($N$5=1,18<=$N$11)),"",IF(ISNUMBER(G46),"Aplicado",IF(ISNUMBER(G45),IF($N$10=1,"Falta el IPC de "&INDEX(IPC!$J$5:$J$16,MOD($N$12+1,12)+1)&" de "&INT(($N$12+1)/12),"Cargá el % de este ajuste en la columna F"),""))) | J46: =IF($N$5=1,$N$7+18*$N$8,"") | K46: =IF($N$5=1,J46-1-$N$9,"") | L46: =IF($N$5=1,K46-$N$8,"")
A47: =IF(AND($N$5=1,19<=$N$11),"19° ajuste","") | B47: =IF(AND($N$5=1,19<=$N$11),INDEX(IPC!$J$5:$J$16,MOD(J47,12)+1)&" de "&INT((J47)/12),"") | C47: =IF(AND(AND($N$5=1,19<=$N$11),$N$10=1),INDEX(IPC!$J$5:$J$16,MOD(L47,12)+1)&" de "&INT((L47)/12),"") | D47: =IF(AND(AND($N$5=1,19<=$N$11),$N$10=1),INDEX(IPC!$J$5:$J$16,MOD(K47,12)+1)&" de "&INT((K47)/12),"") | E47: =IF(NOT(AND($N$5=1,19<=$N$11)),"",IF($N$10=1,IF(AND($N$14=1,K47<=$N$12),INDEX(IPC!$D$5:$D$173,(K47)-IPC!$J$2+1)/INDEX(IPC!$D$5:$D$173,(L47)-IPC!$J$2+1)-1,""),IF(ISNUMBER(F47),F47/100,""))) | G47: =IF(AND(AND($N$5=1,19<=$N$11),ISNUMBER(G46),ISNUMBER(E47)),G46*(1+E47),"") | H47: =IF(NOT(AND($N$5=1,19<=$N$11)),"",IF(ISNUMBER(G47),"Aplicado",IF(ISNUMBER(G46),IF($N$10=1,"Falta el IPC de "&INDEX(IPC!$J$5:$J$16,MOD($N$12+1,12)+1)&" de "&INT(($N$12+1)/12),"Cargá el % de este ajuste en la columna F"),""))) | J47: =IF($N$5=1,$N$7+19*$N$8,"") | K47: =IF($N$5=1,J47-1-$N$9,"") | L47: =IF($N$5=1,K47-$N$8,"")
A48: =IF(AND($N$5=1,20<=$N$11),"20° ajuste","") | B48: =IF(AND($N$5=1,20<=$N$11),INDEX(IPC!$J$5:$J$16,MOD(J48,12)+1)&" de "&INT((J48)/12),"") | C48: =IF(AND(AND($N$5=1,20<=$N$11),$N$10=1),INDEX(IPC!$J$5:$J$16,MOD(L48,12)+1)&" de "&INT((L48)/12),"") | D48: =IF(AND(AND($N$5=1,20<=$N$11),$N$10=1),INDEX(IPC!$J$5:$J$16,MOD(K48,12)+1)&" de "&INT((K48)/12),"") | E48: =IF(NOT(AND($N$5=1,20<=$N$11)),"",IF($N$10=1,IF(AND($N$14=1,K48<=$N$12),INDEX(IPC!$D$5:$D$173,(K48)-IPC!$J$2+1)/INDEX(IPC!$D$5:$D$173,(L48)-IPC!$J$2+1)-1,""),IF(ISNUMBER(F48),F48/100,""))) | G48: =IF(AND(AND($N$5=1,20<=$N$11),ISNUMBER(G47),ISNUMBER(E48)),G47*(1+E48),"") | H48: =IF(NOT(AND($N$5=1,20<=$N$11)),"",IF(ISNUMBER(G48),"Aplicado",IF(ISNUMBER(G47),IF($N$10=1,"Falta el IPC de "&INDEX(IPC!$J$5:$J$16,MOD($N$12+1,12)+1)&" de "&INT(($N$12+1)/12),"Cargá el % de este ajuste en la columna F"),""))) | J48: =IF($N$5=1,$N$7+20*$N$8,"") | K48: =IF($N$5=1,J48-1-$N$9,"") | L48: =IF($N$5=1,K48-$N$8,"")
A49: =IF(AND($N$5=1,21<=$N$11),"21° ajuste","") | B49: =IF(AND($N$5=1,21<=$N$11),INDEX(IPC!$J$5:$J$16,MOD(J49,12)+1)&" de "&INT((J49)/12),"") | C49: =IF(AND(AND($N$5=1,21<=$N$11),$N$10=1),INDEX(IPC!$J$5:$J$16,MOD(L49,12)+1)&" de "&INT((L49)/12),"") | D49: =IF(AND(AND($N$5=1,21<=$N$11),$N$10=1),INDEX(IPC!$J$5:$J$16,MOD(K49,12)+1)&" de "&INT((K49)/12),"") | E49: =IF(NOT(AND($N$5=1,21<=$N$11)),"",IF($N$10=1,IF(AND($N$14=1,K49<=$N$12),INDEX(IPC!$D$5:$D$173,(K49)-IPC!$J$2+1)/INDEX(IPC!$D$5:$D$173,(L49)-IPC!$J$2+1)-1,""),IF(ISNUMBER(F49),F49/100,""))) | G49: =IF(AND(AND($N$5=1,21<=$N$11),ISNUMBER(G48),ISNUMBER(E49)),G48*(1+E49),"") | H49: =IF(NOT(AND($N$5=1,21<=$N$11)),"",IF(ISNUMBER(G49),"Aplicado",IF(ISNUMBER(G48),IF($N$10=1,"Falta el IPC de "&INDEX(IPC!$J$5:$J$16,MOD($N$12+1,12)+1)&" de "&INT(($N$12+1)/12),"Cargá el % de este ajuste en la columna F"),""))) | J49: =IF($N$5=1,$N$7+21*$N$8,"") | K49: =IF($N$5=1,J49-1-$N$9,"") | L49: =IF($N$5=1,K49-$N$8,"")
A50: =IF(AND($N$5=1,22<=$N$11),"22° ajuste","") | B50: =IF(AND($N$5=1,22<=$N$11),INDEX(IPC!$J$5:$J$16,MOD(J50,12)+1)&" de "&INT((J50)/12),"") | C50: =IF(AND(AND($N$5=1,22<=$N$11),$N$10=1),INDEX(IPC!$J$5:$J$16,MOD(L50,12)+1)&" de "&INT((L50)/12),"") | D50: =IF(AND(AND($N$5=1,22<=$N$11),$N$10=1),INDEX(IPC!$J$5:$J$16,MOD(K50,12)+1)&" de "&INT((K50)/12),"") | E50: =IF(NOT(AND($N$5=1,22<=$N$11)),"",IF($N$10=1,IF(AND($N$14=1,K50<=$N$12),INDEX(IPC!$D$5:$D$173,(K50)-IPC!$J$2+1)/INDEX(IPC!$D$5:$D$173,(L50)-IPC!$J$2+1)-1,""),IF(ISNUMBER(F50),F50/100,""))) | G50: =IF(AND(AND($N$5=1,22<=$N$11),ISNUMBER(G49),ISNUMBER(E50)),G49*(1+E50),"") | H50: =IF(NOT(AND($N$5=1,22<=$N$11)),"",IF(ISNUMBER(G50),"Aplicado",IF(ISNUMBER(G49),IF($N$10=1,"Falta el IPC de "&INDEX(IPC!$J$5:$J$16,MOD($N$12+1,12)+1)&" de "&INT(($N$12+1)/12),"Cargá el % de este ajuste en la columna F"),""))) | J50: =IF($N$5=1,$N$7+22*$N$8,"") | K50: =IF($N$5=1,J50-1-$N$9,"") | L50: =IF($N$5=1,K50-$N$8,"")
A51: =IF(AND($N$5=1,23<=$N$11),"23° ajuste","") | B51: =IF(AND($N$5=1,23<=$N$11),INDEX(IPC!$J$5:$J$16,MOD(J51,12)+1)&" de "&INT((J51)/12),"") | C51: =IF(AND(AND($N$5=1,23<=$N$11),$N$10=1),INDEX(IPC!$J$5:$J$16,MOD(L51,12)+1)&" de "&INT((L51)/12),"") | D51: =IF(AND(AND($N$5=1,23<=$N$11),$N$10=1),INDEX(IPC!$J$5:$J$16,MOD(K51,12)+1)&" de "&INT((K51)/12),"") | E51: =IF(NOT(AND($N$5=1,23<=$N$11)),"",IF($N$10=1,IF(AND($N$14=1,K51<=$N$12),INDEX(IPC!$D$5:$D$173,(K51)-IPC!$J$2+1)/INDEX(IPC!$D$5:$D$173,(L51)-IPC!$J$2+1)-1,""),IF(ISNUMBER(F51),F51/100,""))) | G51: =IF(AND(AND($N$5=1,23<=$N$11),ISNUMBER(G50),ISNUMBER(E51)),G50*(1+E51),"") | H51: =IF(NOT(AND($N$5=1,23<=$N$11)),"",IF(ISNUMBER(G51),"Aplicado",IF(ISNUMBER(G50),IF($N$10=1,"Falta el IPC de "&INDEX(IPC!$J$5:$J$16,MOD($N$12+1,12)+1)&" de "&INT(($N$12+1)/12),"Cargá el % de este ajuste en la columna F"),""))) | J51: =IF($N$5=1,$N$7+23*$N$8,"") | K51: =IF($N$5=1,J51-1-$N$9,"") | L51: =IF($N$5=1,K51-$N$8,"")
A52: =IF(AND($N$5=1,24<=$N$11),"24° ajuste","") | B52: =IF(AND($N$5=1,24<=$N$11),INDEX(IPC!$J$5:$J$16,MOD(J52,12)+1)&" de "&INT((J52)/12),"") | C52: =IF(AND(AND($N$5=1,24<=$N$11),$N$10=1),INDEX(IPC!$J$5:$J$16,MOD(L52,12)+1)&" de "&INT((L52)/12),"") | D52: =IF(AND(AND($N$5=1,24<=$N$11),$N$10=1),INDEX(IPC!$J$5:$J$16,MOD(K52,12)+1)&" de "&INT((K52)/12),"") | E52: =IF(NOT(AND($N$5=1,24<=$N$11)),"",IF($N$10=1,IF(AND($N$14=1,K52<=$N$12),INDEX(IPC!$D$5:$D$173,(K52)-IPC!$J$2+1)/INDEX(IPC!$D$5:$D$173,(L52)-IPC!$J$2+1)-1,""),IF(ISNUMBER(F52),F52/100,""))) | G52: =IF(AND(AND($N$5=1,24<=$N$11),ISNUMBER(G51),ISNUMBER(E52)),G51*(1+E52),"") | H52: =IF(NOT(AND($N$5=1,24<=$N$11)),"",IF(ISNUMBER(G52),"Aplicado",IF(ISNUMBER(G51),IF($N$10=1,"Falta el IPC de "&INDEX(IPC!$J$5:$J$16,MOD($N$12+1,12)+1)&" de "&INT(($N$12+1)/12),"Cargá el % de este ajuste en la columna F"),""))) | J52: =IF($N$5=1,$N$7+24*$N$8,"") | K52: =IF($N$5=1,J52-1-$N$9,"") | L52: =IF($N$5=1,K52-$N$8,"")
A53: =IF(AND($N$5=1,25<=$N$11),"25° ajuste","") | B53: =IF(AND($N$5=1,25<=$N$11),INDEX(IPC!$J$5:$J$16,MOD(J53,12)+1)&" de "&INT((J53)/12),"") | C53: =IF(AND(AND($N$5=1,25<=$N$11),$N$10=1),INDEX(IPC!$J$5:$J$16,MOD(L53,12)+1)&" de "&INT((L53)/12),"") | D53: =IF(AND(AND($N$5=1,25<=$N$11),$N$10=1),INDEX(IPC!$J$5:$J$16,MOD(K53,12)+1)&" de "&INT((K53)/12),"") | E53: =IF(NOT(AND($N$5=1,25<=$N$11)),"",IF($N$10=1,IF(AND($N$14=1,K53<=$N$12),INDEX(IPC!$D$5:$D$173,(K53)-IPC!$J$2+1)/INDEX(IPC!$D$5:$D$173,(L53)-IPC!$J$2+1)-1,""),IF(ISNUMBER(F53),F53/100,""))) | G53: =IF(AND(AND($N$5=1,25<=$N$11),ISNUMBER(G52),ISNUMBER(E53)),G52*(1+E53),"") | H53: =IF(NOT(AND($N$5=1,25<=$N$11)),"",IF(ISNUMBER(G53),"Aplicado",IF(ISNUMBER(G52),IF($N$10=1,"Falta el IPC de "&INDEX(IPC!$J$5:$J$16,MOD($N$12+1,12)+1)&" de "&INT(($N$12+1)/12),"Cargá el % de este ajuste en la columna F"),""))) | J53: =IF($N$5=1,$N$7+25*$N$8,"") | K53: =IF($N$5=1,J53-1-$N$9,"") | L53: =IF($N$5=1,K53-$N$8,"")
A54: =IF(AND($N$5=1,26<=$N$11),"26° ajuste","") | B54: =IF(AND($N$5=1,26<=$N$11),INDEX(IPC!$J$5:$J$16,MOD(J54,12)+1)&" de "&INT((J54)/12),"") | C54: =IF(AND(AND($N$5=1,26<=$N$11),$N$10=1),INDEX(IPC!$J$5:$J$16,MOD(L54,12)+1)&" de "&INT((L54)/12),"") | D54: =IF(AND(AND($N$5=1,26<=$N$11),$N$10=1),INDEX(IPC!$J$5:$J$16,MOD(K54,12)+1)&" de "&INT((K54)/12),"") | E54: =IF(NOT(AND($N$5=1,26<=$N$11)),"",IF($N$10=1,IF(AND($N$14=1,K54<=$N$12),INDEX(IPC!$D$5:$D$173,(K54)-IPC!$J$2+1)/INDEX(IPC!$D$5:$D$173,(L54)-IPC!$J$2+1)-1,""),IF(ISNUMBER(F54),F54/100,""))) | G54: =IF(AND(AND($N$5=1,26<=$N$11),ISNUMBER(G53),ISNUMBER(E54)),G53*(1+E54),"") | H54: =IF(NOT(AND($N$5=1,26<=$N$11)),"",IF(ISNUMBER(G54),"Aplicado",IF(ISNUMBER(G53),IF($N$10=1,"Falta el IPC de "&INDEX(IPC!$J$5:$J$16,MOD($N$12+1,12)+1)&" de "&INT(($N$12+1)/12),"Cargá el % de este ajuste en la columna F"),""))) | J54: =IF($N$5=1,$N$7+26*$N$8,"") | K54: =IF($N$5=1,J54-1-$N$9,"") | L54: =IF($N$5=1,K54-$N$8,"")
A55: =IF(AND($N$5=1,27<=$N$11),"27° ajuste","") | B55: =IF(AND($N$5=1,27<=$N$11),INDEX(IPC!$J$5:$J$16,MOD(J55,12)+1)&" de "&INT((J55)/12),"") | C55: =IF(AND(AND($N$5=1,27<=$N$11),$N$10=1),INDEX(IPC!$J$5:$J$16,MOD(L55,12)+1)&" de "&INT((L55)/12),"") | D55: =IF(AND(AND($N$5=1,27<=$N$11),$N$10=1),INDEX(IPC!$J$5:$J$16,MOD(K55,12)+1)&" de "&INT((K55)/12),"") | E55: =IF(NOT(AND($N$5=1,27<=$N$11)),"",IF($N$10=1,IF(AND($N$14=1,K55<=$N$12),INDEX(IPC!$D$5:$D$173,(K55)-IPC!$J$2+1)/INDEX(IPC!$D$5:$D$173,(L55)-IPC!$J$2+1)-1,""),IF(ISNUMBER(F55),F55/100,""))) | G55: =IF(AND(AND($N$5=1,27<=$N$11),ISNUMBER(G54),ISNUMBER(E55)),G54*(1+E55),"") | H55: =IF(NOT(AND($N$5=1,27<=$N$11)),"",IF(ISNUMBER(G55),"Aplicado",IF(ISNUMBER(G54),IF($N$10=1,"Falta el IPC de "&INDEX(IPC!$J$5:$J$16,MOD($N$12+1,12)+1)&" de "&INT(($N$12+1)/12),"Cargá el % de este ajuste en la columna F"),""))) | J55: =IF($N$5=1,$N$7+27*$N$8,"") | K55: =IF($N$5=1,J55-1-$N$9,"") | L55: =IF($N$5=1,K55-$N$8,"")
A56: =IF(AND($N$5=1,28<=$N$11),"28° ajuste","") | B56: =IF(AND($N$5=1,28<=$N$11),INDEX(IPC!$J$5:$J$16,MOD(J56,12)+1)&" de "&INT((J56)/12),"") | C56: =IF(AND(AND($N$5=1,28<=$N$11),$N$10=1),INDEX(IPC!$J$5:$J$16,MOD(L56,12)+1)&" de "&INT((L56)/12),"") | D56: =IF(AND(AND($N$5=1,28<=$N$11),$N$10=1),INDEX(IPC!$J$5:$J$16,MOD(K56,12)+1)&" de "&INT((K56)/12),"") | E56: =IF(NOT(AND($N$5=1,28<=$N$11)),"",IF($N$10=1,IF(AND($N$14=1,K56<=$N$12),INDEX(IPC!$D$5:$D$173,(K56)-IPC!$J$2+1)/INDEX(IPC!$D$5:$D$173,(L56)-IPC!$J$2+1)-1,""),IF(ISNUMBER(F56),F56/100,""))) | G56: =IF(AND(AND($N$5=1,28<=$N$11),ISNUMBER(G55),ISNUMBER(E56)),G55*(1+E56),"") | H56: =IF(NOT(AND($N$5=1,28<=$N$11)),"",IF(ISNUMBER(G56),"Aplicado",IF(ISNUMBER(G55),IF($N$10=1,"Falta el IPC de "&INDEX(IPC!$J$5:$J$16,MOD($N$12+1,12)+1)&" de "&INT(($N$12+1)/12),"Cargá el % de este ajuste en la columna F"),""))) | J56: =IF($N$5=1,$N$7+28*$N$8,"") | K56: =IF($N$5=1,J56-1-$N$9,"") | L56: =IF($N$5=1,K56-$N$8,"")
A57: =IF(AND($N$5=1,29<=$N$11),"29° ajuste","") | B57: =IF(AND($N$5=1,29<=$N$11),INDEX(IPC!$J$5:$J$16,MOD(J57,12)+1)&" de "&INT((J57)/12),"") | C57: =IF(AND(AND($N$5=1,29<=$N$11),$N$10=1),INDEX(IPC!$J$5:$J$16,MOD(L57,12)+1)&" de "&INT((L57)/12),"") | D57: =IF(AND(AND($N$5=1,29<=$N$11),$N$10=1),INDEX(IPC!$J$5:$J$16,MOD(K57,12)+1)&" de "&INT((K57)/12),"") | E57: =IF(NOT(AND($N$5=1,29<=$N$11)),"",IF($N$10=1,IF(AND($N$14=1,K57<=$N$12),INDEX(IPC!$D$5:$D$173,(K57)-IPC!$J$2+1)/INDEX(IPC!$D$5:$D$173,(L57)-IPC!$J$2+1)-1,""),IF(ISNUMBER(F57),F57/100,""))) | G57: =IF(AND(AND($N$5=1,29<=$N$11),ISNUMBER(G56),ISNUMBER(E57)),G56*(1+E57),"") | H57: =IF(NOT(AND($N$5=1,29<=$N$11)),"",IF(ISNUMBER(G57),"Aplicado",IF(ISNUMBER(G56),IF($N$10=1,"Falta el IPC de "&INDEX(IPC!$J$5:$J$16,MOD($N$12+1,12)+1)&" de "&INT(($N$12+1)/12),"Cargá el % de este ajuste en la columna F"),""))) | J57: =IF($N$5=1,$N$7+29*$N$8,"") | K57: =IF($N$5=1,J57-1-$N$9,"") | L57: =IF($N$5=1,K57-$N$8,"")
A58: =IF(AND($N$5=1,30<=$N$11),"30° ajuste","") | B58: =IF(AND($N$5=1,30<=$N$11),INDEX(IPC!$J$5:$J$16,MOD(J58,12)+1)&" de "&INT((J58)/12),"") | C58: =IF(AND(AND($N$5=1,30<=$N$11),$N$10=1),INDEX(IPC!$J$5:$J$16,MOD(L58,12)+1)&" de "&INT((L58)/12),"") | D58: =IF(AND(AND($N$5=1,30<=$N$11),$N$10=1),INDEX(IPC!$J$5:$J$16,MOD(K58,12)+1)&" de "&INT((K58)/12),"") | E58: =IF(NOT(AND($N$5=1,30<=$N$11)),"",IF($N$10=1,IF(AND($N$14=1,K58<=$N$12),INDEX(IPC!$D$5:$D$173,(K58)-IPC!$J$2+1)/INDEX(IPC!$D$5:$D$173,(L58)-IPC!$J$2+1)-1,""),IF(ISNUMBER(F58),F58/100,""))) | G58: =IF(AND(AND($N$5=1,30<=$N$11),ISNUMBER(G57),ISNUMBER(E58)),G57*(1+E58),"") | H58: =IF(NOT(AND($N$5=1,30<=$N$11)),"",IF(ISNUMBER(G58),"Aplicado",IF(ISNUMBER(G57),IF($N$10=1,"Falta el IPC de "&INDEX(IPC!$J$5:$J$16,MOD($N$12+1,12)+1)&" de "&INT(($N$12+1)/12),"Cargá el % de este ajuste en la columna F"),""))) | J58: =IF($N$5=1,$N$7+30*$N$8,"") | K58: =IF($N$5=1,J58-1-$N$9,"") | L58: =IF($N$5=1,K58-$N$8,"")
A59: =IF(AND($N$5=1,31<=$N$11),"31° ajuste","") | B59: =IF(AND($N$5=1,31<=$N$11),INDEX(IPC!$J$5:$J$16,MOD(J59,12)+1)&" de "&INT((J59)/12),"") | C59: =IF(AND(AND($N$5=1,31<=$N$11),$N$10=1),INDEX(IPC!$J$5:$J$16,MOD(L59,12)+1)&" de "&INT((L59)/12),"") | D59: =IF(AND(AND($N$5=1,31<=$N$11),$N$10=1),INDEX(IPC!$J$5:$J$16,MOD(K59,12)+1)&" de "&INT((K59)/12),"") | E59: =IF(NOT(AND($N$5=1,31<=$N$11)),"",IF($N$10=1,IF(AND($N$14=1,K59<=$N$12),INDEX(IPC!$D$5:$D$173,(K59)-IPC!$J$2+1)/INDEX(IPC!$D$5:$D$173,(L59)-IPC!$J$2+1)-1,""),IF(ISNUMBER(F59),F59/100,""))) | G59: =IF(AND(AND($N$5=1,31<=$N$11),ISNUMBER(G58),ISNUMBER(E59)),G58*(1+E59),"") | H59: =IF(NOT(AND($N$5=1,31<=$N$11)),"",IF(ISNUMBER(G59),"Aplicado",IF(ISNUMBER(G58),IF($N$10=1,"Falta el IPC de "&INDEX(IPC!$J$5:$J$16,MOD($N$12+1,12)+1)&" de "&INT(($N$12+1)/12),"Cargá el % de este ajuste en la columna F"),""))) | J59: =IF($N$5=1,$N$7+31*$N$8,"") | K59: =IF($N$5=1,J59-1-$N$9,"") | L59: =IF($N$5=1,K59-$N$8,"")
A60: =IF(AND($N$5=1,32<=$N$11),"32° ajuste","") | B60: =IF(AND($N$5=1,32<=$N$11),INDEX(IPC!$J$5:$J$16,MOD(J60,12)+1)&" de "&INT((J60)/12),"") | C60: =IF(AND(AND($N$5=1,32<=$N$11),$N$10=1),INDEX(IPC!$J$5:$J$16,MOD(L60,12)+1)&" de "&INT((L60)/12),"") | D60: =IF(AND(AND($N$5=1,32<=$N$11),$N$10=1),INDEX(IPC!$J$5:$J$16,MOD(K60,12)+1)&" de "&INT((K60)/12),"") | E60: =IF(NOT(AND($N$5=1,32<=$N$11)),"",IF($N$10=1,IF(AND($N$14=1,K60<=$N$12),INDEX(IPC!$D$5:$D$173,(K60)-IPC!$J$2+1)/INDEX(IPC!$D$5:$D$173,(L60)-IPC!$J$2+1)-1,""),IF(ISNUMBER(F60),F60/100,""))) | G60: =IF(AND(AND($N$5=1,32<=$N$11),ISNUMBER(G59),ISNUMBER(E60)),G59*(1+E60),"") | H60: =IF(NOT(AND($N$5=1,32<=$N$11)),"",IF(ISNUMBER(G60),"Aplicado",IF(ISNUMBER(G59),IF($N$10=1,"Falta el IPC de "&INDEX(IPC!$J$5:$J$16,MOD($N$12+1,12)+1)&" de "&INT(($N$12+1)/12),"Cargá el % de este ajuste en la columna F"),""))) | J60: =IF($N$5=1,$N$7+32*$N$8,"") | K60: =IF($N$5=1,J60-1-$N$9,"") | L60: =IF($N$5=1,K60-$N$8,"")
A61: =IF(AND($N$5=1,33<=$N$11),"33° ajuste","") | B61: =IF(AND($N$5=1,33<=$N$11),INDEX(IPC!$J$5:$J$16,MOD(J61,12)+1)&" de "&INT((J61)/12),"") | C61: =IF(AND(AND($N$5=1,33<=$N$11),$N$10=1),INDEX(IPC!$J$5:$J$16,MOD(L61,12)+1)&" de "&INT((L61)/12),"") | D61: =IF(AND(AND($N$5=1,33<=$N$11),$N$10=1),INDEX(IPC!$J$5:$J$16,MOD(K61,12)+1)&" de "&INT((K61)/12),"") | E61: =IF(NOT(AND($N$5=1,33<=$N$11)),"",IF($N$10=1,IF(AND($N$14=1,K61<=$N$12),INDEX(IPC!$D$5:$D$173,(K61)-IPC!$J$2+1)/INDEX(IPC!$D$5:$D$173,(L61)-IPC!$J$2+1)-1,""),IF(ISNUMBER(F61),F61/100,""))) | G61: =IF(AND(AND($N$5=1,33<=$N$11),ISNUMBER(G60),ISNUMBER(E61)),G60*(1+E61),"") | H61: =IF(NOT(AND($N$5=1,33<=$N$11)),"",IF(ISNUMBER(G61),"Aplicado",IF(ISNUMBER(G60),IF($N$10=1,"Falta el IPC de "&INDEX(IPC!$J$5:$J$16,MOD($N$12+1,12)+1)&" de "&INT(($N$12+1)/12),"Cargá el % de este ajuste en la columna F"),""))) | J61: =IF($N$5=1,$N$7+33*$N$8,"") | K61: =IF($N$5=1,J61-1-$N$9,"") | L61: =IF($N$5=1,K61-$N$8,"")
A62: =IF(AND($N$5=1,34<=$N$11),"34° ajuste","") | B62: =IF(AND($N$5=1,34<=$N$11),INDEX(IPC!$J$5:$J$16,MOD(J62,12)+1)&" de "&INT((J62)/12),"") | C62: =IF(AND(AND($N$5=1,34<=$N$11),$N$10=1),INDEX(IPC!$J$5:$J$16,MOD(L62,12)+1)&" de "&INT((L62)/12),"") | D62: =IF(AND(AND($N$5=1,34<=$N$11),$N$10=1),INDEX(IPC!$J$5:$J$16,MOD(K62,12)+1)&" de "&INT((K62)/12),"") | E62: =IF(NOT(AND($N$5=1,34<=$N$11)),"",IF($N$10=1,IF(AND($N$14=1,K62<=$N$12),INDEX(IPC!$D$5:$D$173,(K62)-IPC!$J$2+1)/INDEX(IPC!$D$5:$D$173,(L62)-IPC!$J$2+1)-1,""),IF(ISNUMBER(F62),F62/100,""))) | G62: =IF(AND(AND($N$5=1,34<=$N$11),ISNUMBER(G61),ISNUMBER(E62)),G61*(1+E62),"") | H62: =IF(NOT(AND($N$5=1,34<=$N$11)),"",IF(ISNUMBER(G62),"Aplicado",IF(ISNUMBER(G61),IF($N$10=1,"Falta el IPC de "&INDEX(IPC!$J$5:$J$16,MOD($N$12+1,12)+1)&" de "&INT(($N$12+1)/12),"Cargá el % de este ajuste en la columna F"),""))) | J62: =IF($N$5=1,$N$7+34*$N$8,"") | K62: =IF($N$5=1,J62-1-$N$9,"") | L62: =IF($N$5=1,K62-$N$8,"")
A63: =IF(AND($N$5=1,35<=$N$11),"35° ajuste","") | B63: =IF(AND($N$5=1,35<=$N$11),INDEX(IPC!$J$5:$J$16,MOD(J63,12)+1)&" de "&INT((J63)/12),"") | C63: =IF(AND(AND($N$5=1,35<=$N$11),$N$10=1),INDEX(IPC!$J$5:$J$16,MOD(L63,12)+1)&" de "&INT((L63)/12),"") | D63: =IF(AND(AND($N$5=1,35<=$N$11),$N$10=1),INDEX(IPC!$J$5:$J$16,MOD(K63,12)+1)&" de "&INT((K63)/12),"") | E63: =IF(NOT(AND($N$5=1,35<=$N$11)),"",IF($N$10=1,IF(AND($N$14=1,K63<=$N$12),INDEX(IPC!$D$5:$D$173,(K63)-IPC!$J$2+1)/INDEX(IPC!$D$5:$D$173,(L63)-IPC!$J$2+1)-1,""),IF(ISNUMBER(F63),F63/100,""))) | G63: =IF(AND(AND($N$5=1,35<=$N$11),ISNUMBER(G62),ISNUMBER(E63)),G62*(1+E63),"") | H63: =IF(NOT(AND($N$5=1,35<=$N$11)),"",IF(ISNUMBER(G63),"Aplicado",IF(ISNUMBER(G62),IF($N$10=1,"Falta el IPC de "&INDEX(IPC!$J$5:$J$16,MOD($N$12+1,12)+1)&" de "&INT(($N$12+1)/12),"Cargá el % de este ajuste en la columna F"),""))) | J63: =IF($N$5=1,$N$7+35*$N$8,"") | K63: =IF($N$5=1,J63-1-$N$9,"") | L63: =IF($N$5=1,K63-$N$8,"")
A64: =IF(AND($N$5=1,36<=$N$11),"36° ajuste","") | B64: =IF(AND($N$5=1,36<=$N$11),INDEX(IPC!$J$5:$J$16,MOD(J64,12)+1)&" de "&INT((J64)/12),"") | C64: =IF(AND(AND($N$5=1,36<=$N$11),$N$10=1),INDEX(IPC!$J$5:$J$16,MOD(L64,12)+1)&" de "&INT((L64)/12),"") | D64: =IF(AND(AND($N$5=1,36<=$N$11),$N$10=1),INDEX(IPC!$J$5:$J$16,MOD(K64,12)+1)&" de "&INT((K64)/12),"") | E64: =IF(NOT(AND($N$5=1,36<=$N$11)),"",IF($N$10=1,IF(AND($N$14=1,K64<=$N$12),INDEX(IPC!$D$5:$D$173,(K64)-IPC!$J$2+1)/INDEX(IPC!$D$5:$D$173,(L64)-IPC!$J$2+1)-1,""),IF(ISNUMBER(F64),F64/100,""))) | G64: =IF(AND(AND($N$5=1,36<=$N$11),ISNUMBER(G63),ISNUMBER(E64)),G63*(1+E64),"") | H64: =IF(NOT(AND($N$5=1,36<=$N$11)),"",IF(ISNUMBER(G64),"Aplicado",IF(ISNUMBER(G63),IF($N$10=1,"Falta el IPC de "&INDEX(IPC!$J$5:$J$16,MOD($N$12+1,12)+1)&" de "&INT(($N$12+1)/12),"Cargá el % de este ajuste en la columna F"),""))) | J64: =IF($N$5=1,$N$7+36*$N$8,"") | K64: =IF($N$5=1,J64-1-$N$9,"") | L64: =IF($N$5=1,K64-$N$8,"")
A65: =IF(AND($N$5=1,37<=$N$11),"37° ajuste","") | B65: =IF(AND($N$5=1,37<=$N$11),INDEX(IPC!$J$5:$J$16,MOD(J65,12)+1)&" de "&INT((J65)/12),"") | C65: =IF(AND(AND($N$5=1,37<=$N$11),$N$10=1),INDEX(IPC!$J$5:$J$16,MOD(L65,12)+1)&" de "&INT((L65)/12),"") | D65: =IF(AND(AND($N$5=1,37<=$N$11),$N$10=1),INDEX(IPC!$J$5:$J$16,MOD(K65,12)+1)&" de "&INT((K65)/12),"") | E65: =IF(NOT(AND($N$5=1,37<=$N$11)),"",IF($N$10=1,IF(AND($N$14=1,K65<=$N$12),INDEX(IPC!$D$5:$D$173,(K65)-IPC!$J$2+1)/INDEX(IPC!$D$5:$D$173,(L65)-IPC!$J$2+1)-1,""),IF(ISNUMBER(F65),F65/100,""))) | G65: =IF(AND(AND($N$5=1,37<=$N$11),ISNUMBER(G64),ISNUMBER(E65)),G64*(1+E65),"") | H65: =IF(NOT(AND($N$5=1,37<=$N$11)),"",IF(ISNUMBER(G65),"Aplicado",IF(ISNUMBER(G64),IF($N$10=1,"Falta el IPC de "&INDEX(IPC!$J$5:$J$16,MOD($N$12+1,12)+1)&" de "&INT(($N$12+1)/12),"Cargá el % de este ajuste en la columna F"),""))) | J65: =IF($N$5=1,$N$7+37*$N$8,"") | K65: =IF($N$5=1,J65-1-$N$9,"") | L65: =IF($N$5=1,K65-$N$8,"")
A66: =IF(AND($N$5=1,38<=$N$11),"38° ajuste","") | B66: =IF(AND($N$5=1,38<=$N$11),INDEX(IPC!$J$5:$J$16,MOD(J66,12)+1)&" de "&INT((J66)/12),"") | C66: =IF(AND(AND($N$5=1,38<=$N$11),$N$10=1),INDEX(IPC!$J$5:$J$16,MOD(L66,12)+1)&" de "&INT((L66)/12),"") | D66: =IF(AND(AND($N$5=1,38<=$N$11),$N$10=1),INDEX(IPC!$J$5:$J$16,MOD(K66,12)+1)&" de "&INT((K66)/12),"") | E66: =IF(NOT(AND($N$5=1,38<=$N$11)),"",IF($N$10=1,IF(AND($N$14=1,K66<=$N$12),INDEX(IPC!$D$5:$D$173,(K66)-IPC!$J$2+1)/INDEX(IPC!$D$5:$D$173,(L66)-IPC!$J$2+1)-1,""),IF(ISNUMBER(F66),F66/100,""))) | G66: =IF(AND(AND($N$5=1,38<=$N$11),ISNUMBER(G65),ISNUMBER(E66)),G65*(1+E66),"") | H66: =IF(NOT(AND($N$5=1,38<=$N$11)),"",IF(ISNUMBER(G66),"Aplicado",IF(ISNUMBER(G65),IF($N$10=1,"Falta el IPC de "&INDEX(IPC!$J$5:$J$16,MOD($N$12+1,12)+1)&" de "&INT(($N$12+1)/12),"Cargá el % de este ajuste en la columna F"),""))) | J66: =IF($N$5=1,$N$7+38*$N$8,"") | K66: =IF($N$5=1,J66-1-$N$9,"") | L66: =IF($N$5=1,K66-$N$8,"")
A67: =IF(AND($N$5=1,39<=$N$11),"39° ajuste","") | B67: =IF(AND($N$5=1,39<=$N$11),INDEX(IPC!$J$5:$J$16,MOD(J67,12)+1)&" de "&INT((J67)/12),"") | C67: =IF(AND(AND($N$5=1,39<=$N$11),$N$10=1),INDEX(IPC!$J$5:$J$16,MOD(L67,12)+1)&" de "&INT((L67)/12),"") | D67: =IF(AND(AND($N$5=1,39<=$N$11),$N$10=1),INDEX(IPC!$J$5:$J$16,MOD(K67,12)+1)&" de "&INT((K67)/12),"") | E67: =IF(NOT(AND($N$5=1,39<=$N$11)),"",IF($N$10=1,IF(AND($N$14=1,K67<=$N$12),INDEX(IPC!$D$5:$D$173,(K67)-IPC!$J$2+1)/INDEX(IPC!$D$5:$D$173,(L67)-IPC!$J$2+1)-1,""),IF(ISNUMBER(F67),F67/100,""))) | G67: =IF(AND(AND($N$5=1,39<=$N$11),ISNUMBER(G66),ISNUMBER(E67)),G66*(1+E67),"") | H67: =IF(NOT(AND($N$5=1,39<=$N$11)),"",IF(ISNUMBER(G67),"Aplicado",IF(ISNUMBER(G66),IF($N$10=1,"Falta el IPC de "&INDEX(IPC!$J$5:$J$16,MOD($N$12+1,12)+1)&" de "&INT(($N$12+1)/12),"Cargá el % de este ajuste en la columna F"),""))) | J67: =IF($N$5=1,$N$7+39*$N$8,"") | K67: =IF($N$5=1,J67-1-$N$9,"") | L67: =IF($N$5=1,K67-$N$8,"")
A68: =IF(AND($N$5=1,40<=$N$11),"40° ajuste","") | B68: =IF(AND($N$5=1,40<=$N$11),INDEX(IPC!$J$5:$J$16,MOD(J68,12)+1)&" de "&INT((J68)/12),"") | C68: =IF(AND(AND($N$5=1,40<=$N$11),$N$10=1),INDEX(IPC!$J$5:$J$16,MOD(L68,12)+1)&" de "&INT((L68)/12),"") | D68: =IF(AND(AND($N$5=1,40<=$N$11),$N$10=1),INDEX(IPC!$J$5:$J$16,MOD(K68,12)+1)&" de "&INT((K68)/12),"") | E68: =IF(NOT(AND($N$5=1,40<=$N$11)),"",IF($N$10=1,IF(AND($N$14=1,K68<=$N$12),INDEX(IPC!$D$5:$D$173,(K68)-IPC!$J$2+1)/INDEX(IPC!$D$5:$D$173,(L68)-IPC!$J$2+1)-1,""),IF(ISNUMBER(F68),F68/100,""))) | G68: =IF(AND(AND($N$5=1,40<=$N$11),ISNUMBER(G67),ISNUMBER(E68)),G67*(1+E68),"") | H68: =IF(NOT(AND($N$5=1,40<=$N$11)),"",IF(ISNUMBER(G68),"Aplicado",IF(ISNUMBER(G67),IF($N$10=1,"Falta el IPC de "&INDEX(IPC!$J$5:$J$16,MOD($N$12+1,12)+1)&" de "&INT(($N$12+1)/12),"Cargá el % de este ajuste en la columna F"),""))) | J68: =IF($N$5=1,$N$7+40*$N$8,"") | K68: =IF($N$5=1,J68-1-$N$9,"") | L68: =IF($N$5=1,K68-$N$8,"")
A69: =IF(AND($N$5=1,41<=$N$11),"41° ajuste","") | B69: =IF(AND($N$5=1,41<=$N$11),INDEX(IPC!$J$5:$J$16,MOD(J69,12)+1)&" de "&INT((J69)/12),"") | C69: =IF(AND(AND($N$5=1,41<=$N$11),$N$10=1),INDEX(IPC!$J$5:$J$16,MOD(L69,12)+1)&" de "&INT((L69)/12),"") | D69: =IF(AND(AND($N$5=1,41<=$N$11),$N$10=1),INDEX(IPC!$J$5:$J$16,MOD(K69,12)+1)&" de "&INT((K69)/12),"") | E69: =IF(NOT(AND($N$5=1,41<=$N$11)),"",IF($N$10=1,IF(AND($N$14=1,K69<=$N$12),INDEX(IPC!$D$5:$D$173,(K69)-IPC!$J$2+1)/INDEX(IPC!$D$5:$D$173,(L69)-IPC!$J$2+1)-1,""),IF(ISNUMBER(F69),F69/100,""))) | G69: =IF(AND(AND($N$5=1,41<=$N$11),ISNUMBER(G68),ISNUMBER(E69)),G68*(1+E69),"") | H69: =IF(NOT(AND($N$5=1,41<=$N$11)),"",IF(ISNUMBER(G69),"Aplicado",IF(ISNUMBER(G68),IF($N$10=1,"Falta el IPC de "&INDEX(IPC!$J$5:$J$16,MOD($N$12+1,12)+1)&" de "&INT(($N$12+1)/12),"Cargá el % de este ajuste en la columna F"),""))) | J69: =IF($N$5=1,$N$7+41*$N$8,"") | K69: =IF($N$5=1,J69-1-$N$9,"") | L69: =IF($N$5=1,K69-$N$8,"")
A70: =IF(AND($N$5=1,42<=$N$11),"42° ajuste","") | B70: =IF(AND($N$5=1,42<=$N$11),INDEX(IPC!$J$5:$J$16,MOD(J70,12)+1)&" de "&INT((J70)/12),"") | C70: =IF(AND(AND($N$5=1,42<=$N$11),$N$10=1),INDEX(IPC!$J$5:$J$16,MOD(L70,12)+1)&" de "&INT((L70)/12),"") | D70: =IF(AND(AND($N$5=1,42<=$N$11),$N$10=1),INDEX(IPC!$J$5:$J$16,MOD(K70,12)+1)&" de "&INT((K70)/12),"") | E70: =IF(NOT(AND($N$5=1,42<=$N$11)),"",IF($N$10=1,IF(AND($N$14=1,K70<=$N$12),INDEX(IPC!$D$5:$D$173,(K70)-IPC!$J$2+1)/INDEX(IPC!$D$5:$D$173,(L70)-IPC!$J$2+1)-1,""),IF(ISNUMBER(F70),F70/100,""))) | G70: =IF(AND(AND($N$5=1,42<=$N$11),ISNUMBER(G69),ISNUMBER(E70)),G69*(1+E70),"") | H70: =IF(NOT(AND($N$5=1,42<=$N$11)),"",IF(ISNUMBER(G70),"Aplicado",IF(ISNUMBER(G69),IF($N$10=1,"Falta el IPC de "&INDEX(IPC!$J$5:$J$16,MOD($N$12+1,12)+1)&" de "&INT(($N$12+1)/12),"Cargá el % de este ajuste en la columna F"),""))) | J70: =IF($N$5=1,$N$7+42*$N$8,"") | K70: =IF($N$5=1,J70-1-$N$9,"") | L70: =IF($N$5=1,K70-$N$8,"")
A71: =IF(AND($N$5=1,43<=$N$11),"43° ajuste","") | B71: =IF(AND($N$5=1,43<=$N$11),INDEX(IPC!$J$5:$J$16,MOD(J71,12)+1)&" de "&INT((J71)/12),"") | C71: =IF(AND(AND($N$5=1,43<=$N$11),$N$10=1),INDEX(IPC!$J$5:$J$16,MOD(L71,12)+1)&" de "&INT((L71)/12),"") | D71: =IF(AND(AND($N$5=1,43<=$N$11),$N$10=1),INDEX(IPC!$J$5:$J$16,MOD(K71,12)+1)&" de "&INT((K71)/12),"") | E71: =IF(NOT(AND($N$5=1,43<=$N$11)),"",IF($N$10=1,IF(AND($N$14=1,K71<=$N$12),INDEX(IPC!$D$5:$D$173,(K71)-IPC!$J$2+1)/INDEX(IPC!$D$5:$D$173,(L71)-IPC!$J$2+1)-1,""),IF(ISNUMBER(F71),F71/100,""))) | G71: =IF(AND(AND($N$5=1,43<=$N$11),ISNUMBER(G70),ISNUMBER(E71)),G70*(1+E71),"") | H71: =IF(NOT(AND($N$5=1,43<=$N$11)),"",IF(ISNUMBER(G71),"Aplicado",IF(ISNUMBER(G70),IF($N$10=1,"Falta el IPC de "&INDEX(IPC!$J$5:$J$16,MOD($N$12+1,12)+1)&" de "&INT(($N$12+1)/12),"Cargá el % de este ajuste en la columna F"),""))) | J71: =IF($N$5=1,$N$7+43*$N$8,"") | K71: =IF($N$5=1,J71-1-$N$9,"") | L71: =IF($N$5=1,K71-$N$8,"")
A72: =IF(AND($N$5=1,44<=$N$11),"44° ajuste","") | B72: =IF(AND($N$5=1,44<=$N$11),INDEX(IPC!$J$5:$J$16,MOD(J72,12)+1)&" de "&INT((J72)/12),"") | C72: =IF(AND(AND($N$5=1,44<=$N$11),$N$10=1),INDEX(IPC!$J$5:$J$16,MOD(L72,12)+1)&" de "&INT((L72)/12),"") | D72: =IF(AND(AND($N$5=1,44<=$N$11),$N$10=1),INDEX(IPC!$J$5:$J$16,MOD(K72,12)+1)&" de "&INT((K72)/12),"") | E72: =IF(NOT(AND($N$5=1,44<=$N$11)),"",IF($N$10=1,IF(AND($N$14=1,K72<=$N$12),INDEX(IPC!$D$5:$D$173,(K72)-IPC!$J$2+1)/INDEX(IPC!$D$5:$D$173,(L72)-IPC!$J$2+1)-1,""),IF(ISNUMBER(F72),F72/100,""))) | G72: =IF(AND(AND($N$5=1,44<=$N$11),ISNUMBER(G71),ISNUMBER(E72)),G71*(1+E72),"") | H72: =IF(NOT(AND($N$5=1,44<=$N$11)),"",IF(ISNUMBER(G72),"Aplicado",IF(ISNUMBER(G71),IF($N$10=1,"Falta el IPC de "&INDEX(IPC!$J$5:$J$16,MOD($N$12+1,12)+1)&" de "&INT(($N$12+1)/12),"Cargá el % de este ajuste en la columna F"),""))) | J72: =IF($N$5=1,$N$7+44*$N$8,"") | K72: =IF($N$5=1,J72-1-$N$9,"") | L72: =IF($N$5=1,K72-$N$8,"")
A73: =IF(AND($N$5=1,45<=$N$11),"45° ajuste","") | B73: =IF(AND($N$5=1,45<=$N$11),INDEX(IPC!$J$5:$J$16,MOD(J73,12)+1)&" de "&INT((J73)/12),"") | C73: =IF(AND(AND($N$5=1,45<=$N$11),$N$10=1),INDEX(IPC!$J$5:$J$16,MOD(L73,12)+1)&" de "&INT((L73)/12),"") | D73: =IF(AND(AND($N$5=1,45<=$N$11),$N$10=1),INDEX(IPC!$J$5:$J$16,MOD(K73,12)+1)&" de "&INT((K73)/12),"") | E73: =IF(NOT(AND($N$5=1,45<=$N$11)),"",IF($N$10=1,IF(AND($N$14=1,K73<=$N$12),INDEX(IPC!$D$5:$D$173,(K73)-IPC!$J$2+1)/INDEX(IPC!$D$5:$D$173,(L73)-IPC!$J$2+1)-1,""),IF(ISNUMBER(F73),F73/100,""))) | G73: =IF(AND(AND($N$5=1,45<=$N$11),ISNUMBER(G72),ISNUMBER(E73)),G72*(1+E73),"") | H73: =IF(NOT(AND($N$5=1,45<=$N$11)),"",IF(ISNUMBER(G73),"Aplicado",IF(ISNUMBER(G72),IF($N$10=1,"Falta el IPC de "&INDEX(IPC!$J$5:$J$16,MOD($N$12+1,12)+1)&" de "&INT(($N$12+1)/12),"Cargá el % de este ajuste en la columna F"),""))) | J73: =IF($N$5=1,$N$7+45*$N$8,"") | K73: =IF($N$5=1,J73-1-$N$9,"") | L73: =IF($N$5=1,K73-$N$8,"")
A74: =IF(AND($N$5=1,46<=$N$11),"46° ajuste","") | B74: =IF(AND($N$5=1,46<=$N$11),INDEX(IPC!$J$5:$J$16,MOD(J74,12)+1)&" de "&INT((J74)/12),"") | C74: =IF(AND(AND($N$5=1,46<=$N$11),$N$10=1),INDEX(IPC!$J$5:$J$16,MOD(L74,12)+1)&" de "&INT((L74)/12),"") | D74: =IF(AND(AND($N$5=1,46<=$N$11),$N$10=1),INDEX(IPC!$J$5:$J$16,MOD(K74,12)+1)&" de "&INT((K74)/12),"") | E74: =IF(NOT(AND($N$5=1,46<=$N$11)),"",IF($N$10=1,IF(AND($N$14=1,K74<=$N$12),INDEX(IPC!$D$5:$D$173,(K74)-IPC!$J$2+1)/INDEX(IPC!$D$5:$D$173,(L74)-IPC!$J$2+1)-1,""),IF(ISNUMBER(F74),F74/100,""))) | G74: =IF(AND(AND($N$5=1,46<=$N$11),ISNUMBER(G73),ISNUMBER(E74)),G73*(1+E74),"") | H74: =IF(NOT(AND($N$5=1,46<=$N$11)),"",IF(ISNUMBER(G74),"Aplicado",IF(ISNUMBER(G73),IF($N$10=1,"Falta el IPC de "&INDEX(IPC!$J$5:$J$16,MOD($N$12+1,12)+1)&" de "&INT(($N$12+1)/12),"Cargá el % de este ajuste en la columna F"),""))) | J74: =IF($N$5=1,$N$7+46*$N$8,"") | K74: =IF($N$5=1,J74-1-$N$9,"") | L74: =IF($N$5=1,K74-$N$8,"")
A75: =IF(AND($N$5=1,47<=$N$11),"47° ajuste","") | B75: =IF(AND($N$5=1,47<=$N$11),INDEX(IPC!$J$5:$J$16,MOD(J75,12)+1)&" de "&INT((J75)/12),"") | C75: =IF(AND(AND($N$5=1,47<=$N$11),$N$10=1),INDEX(IPC!$J$5:$J$16,MOD(L75,12)+1)&" de "&INT((L75)/12),"") | D75: =IF(AND(AND($N$5=1,47<=$N$11),$N$10=1),INDEX(IPC!$J$5:$J$16,MOD(K75,12)+1)&" de "&INT((K75)/12),"") | E75: =IF(NOT(AND($N$5=1,47<=$N$11)),"",IF($N$10=1,IF(AND($N$14=1,K75<=$N$12),INDEX(IPC!$D$5:$D$173,(K75)-IPC!$J$2+1)/INDEX(IPC!$D$5:$D$173,(L75)-IPC!$J$2+1)-1,""),IF(ISNUMBER(F75),F75/100,""))) | G75: =IF(AND(AND($N$5=1,47<=$N$11),ISNUMBER(G74),ISNUMBER(E75)),G74*(1+E75),"") | H75: =IF(NOT(AND($N$5=1,47<=$N$11)),"",IF(ISNUMBER(G75),"Aplicado",IF(ISNUMBER(G74),IF($N$10=1,"Falta el IPC de "&INDEX(IPC!$J$5:$J$16,MOD($N$12+1,12)+1)&" de "&INT(($N$12+1)/12),"Cargá el % de este ajuste en la columna F"),""))) | J75: =IF($N$5=1,$N$7+47*$N$8,"") | K75: =IF($N$5=1,J75-1-$N$9,"") | L75: =IF($N$5=1,K75-$N$8,"")
A76: =IF(AND($N$5=1,48<=$N$11),"48° ajuste","") | B76: =IF(AND($N$5=1,48<=$N$11),INDEX(IPC!$J$5:$J$16,MOD(J76,12)+1)&" de "&INT((J76)/12),"") | C76: =IF(AND(AND($N$5=1,48<=$N$11),$N$10=1),INDEX(IPC!$J$5:$J$16,MOD(L76,12)+1)&" de "&INT((L76)/12),"") | D76: =IF(AND(AND($N$5=1,48<=$N$11),$N$10=1),INDEX(IPC!$J$5:$J$16,MOD(K76,12)+1)&" de "&INT((K76)/12),"") | E76: =IF(NOT(AND($N$5=1,48<=$N$11)),"",IF($N$10=1,IF(AND($N$14=1,K76<=$N$12),INDEX(IPC!$D$5:$D$173,(K76)-IPC!$J$2+1)/INDEX(IPC!$D$5:$D$173,(L76)-IPC!$J$2+1)-1,""),IF(ISNUMBER(F76),F76/100,""))) | G76: =IF(AND(AND($N$5=1,48<=$N$11),ISNUMBER(G75),ISNUMBER(E76)),G75*(1+E76),"") | H76: =IF(NOT(AND($N$5=1,48<=$N$11)),"",IF(ISNUMBER(G76),"Aplicado",IF(ISNUMBER(G75),IF($N$10=1,"Falta el IPC de "&INDEX(IPC!$J$5:$J$16,MOD($N$12+1,12)+1)&" de "&INT(($N$12+1)/12),"Cargá el % de este ajuste en la columna F"),""))) | J76: =IF($N$5=1,$N$7+48*$N$8,"") | K76: =IF($N$5=1,J76-1-$N$9,"") | L76: =IF($N$5=1,K76-$N$8,"")
A77: =IF(AND($N$5=1,49<=$N$11),"49° ajuste","") | B77: =IF(AND($N$5=1,49<=$N$11),INDEX(IPC!$J$5:$J$16,MOD(J77,12)+1)&" de "&INT((J77)/12),"") | C77: =IF(AND(AND($N$5=1,49<=$N$11),$N$10=1),INDEX(IPC!$J$5:$J$16,MOD(L77,12)+1)&" de "&INT((L77)/12),"") | D77: =IF(AND(AND($N$5=1,49<=$N$11),$N$10=1),INDEX(IPC!$J$5:$J$16,MOD(K77,12)+1)&" de "&INT((K77)/12),"") | E77: =IF(NOT(AND($N$5=1,49<=$N$11)),"",IF($N$10=1,IF(AND($N$14=1,K77<=$N$12),INDEX(IPC!$D$5:$D$173,(K77)-IPC!$J$2+1)/INDEX(IPC!$D$5:$D$173,(L77)-IPC!$J$2+1)-1,""),IF(ISNUMBER(F77),F77/100,""))) | G77: =IF(AND(AND($N$5=1,49<=$N$11),ISNUMBER(G76),ISNUMBER(E77)),G76*(1+E77),"") | H77: =IF(NOT(AND($N$5=1,49<=$N$11)),"",IF(ISNUMBER(G77),"Aplicado",IF(ISNUMBER(G76),IF($N$10=1,"Falta el IPC de "&INDEX(IPC!$J$5:$J$16,MOD($N$12+1,12)+1)&" de "&INT(($N$12+1)/12),"Cargá el % de este ajuste en la columna F"),""))) | J77: =IF($N$5=1,$N$7+49*$N$8,"") | K77: =IF($N$5=1,J77-1-$N$9,"") | L77: =IF($N$5=1,K77-$N$8,"")
A78: =IF(AND($N$5=1,50<=$N$11),"50° ajuste","") | B78: =IF(AND($N$5=1,50<=$N$11),INDEX(IPC!$J$5:$J$16,MOD(J78,12)+1)&" de "&INT((J78)/12),"") | C78: =IF(AND(AND($N$5=1,50<=$N$11),$N$10=1),INDEX(IPC!$J$5:$J$16,MOD(L78,12)+1)&" de "&INT((L78)/12),"") | D78: =IF(AND(AND($N$5=1,50<=$N$11),$N$10=1),INDEX(IPC!$J$5:$J$16,MOD(K78,12)+1)&" de "&INT((K78)/12),"") | E78: =IF(NOT(AND($N$5=1,50<=$N$11)),"",IF($N$10=1,IF(AND($N$14=1,K78<=$N$12),INDEX(IPC!$D$5:$D$173,(K78)-IPC!$J$2+1)/INDEX(IPC!$D$5:$D$173,(L78)-IPC!$J$2+1)-1,""),IF(ISNUMBER(F78),F78/100,""))) | G78: =IF(AND(AND($N$5=1,50<=$N$11),ISNUMBER(G77),ISNUMBER(E78)),G77*(1+E78),"") | H78: =IF(NOT(AND($N$5=1,50<=$N$11)),"",IF(ISNUMBER(G78),"Aplicado",IF(ISNUMBER(G77),IF($N$10=1,"Falta el IPC de "&INDEX(IPC!$J$5:$J$16,MOD($N$12+1,12)+1)&" de "&INT(($N$12+1)/12),"Cargá el % de este ajuste en la columna F"),""))) | J78: =IF($N$5=1,$N$7+50*$N$8,"") | K78: =IF($N$5=1,J78-1-$N$9,"") | L78: =IF($N$5=1,K78-$N$8,"")
A79: =IF(AND($N$5=1,51<=$N$11),"51° ajuste","") | B79: =IF(AND($N$5=1,51<=$N$11),INDEX(IPC!$J$5:$J$16,MOD(J79,12)+1)&" de "&INT((J79)/12),"") | C79: =IF(AND(AND($N$5=1,51<=$N$11),$N$10=1),INDEX(IPC!$J$5:$J$16,MOD(L79,12)+1)&" de "&INT((L79)/12),"") | D79: =IF(AND(AND($N$5=1,51<=$N$11),$N$10=1),INDEX(IPC!$J$5:$J$16,MOD(K79,12)+1)&" de "&INT((K79)/12),"") | E79: =IF(NOT(AND($N$5=1,51<=$N$11)),"",IF($N$10=1,IF(AND($N$14=1,K79<=$N$12),INDEX(IPC!$D$5:$D$173,(K79)-IPC!$J$2+1)/INDEX(IPC!$D$5:$D$173,(L79)-IPC!$J$2+1)-1,""),IF(ISNUMBER(F79),F79/100,""))) | G79: =IF(AND(AND($N$5=1,51<=$N$11),ISNUMBER(G78),ISNUMBER(E79)),G78*(1+E79),"") | H79: =IF(NOT(AND($N$5=1,51<=$N$11)),"",IF(ISNUMBER(G79),"Aplicado",IF(ISNUMBER(G78),IF($N$10=1,"Falta el IPC de "&INDEX(IPC!$J$5:$J$16,MOD($N$12+1,12)+1)&" de "&INT(($N$12+1)/12),"Cargá el % de este ajuste en la columna F"),""))) | J79: =IF($N$5=1,$N$7+51*$N$8,"") | K79: =IF($N$5=1,J79-1-$N$9,"") | L79: =IF($N$5=1,K79-$N$8,"")
A80: =IF(AND($N$5=1,52<=$N$11),"52° ajuste","") | B80: =IF(AND($N$5=1,52<=$N$11),INDEX(IPC!$J$5:$J$16,MOD(J80,12)+1)&" de "&INT((J80)/12),"") | C80: =IF(AND(AND($N$5=1,52<=$N$11),$N$10=1),INDEX(IPC!$J$5:$J$16,MOD(L80,12)+1)&" de "&INT((L80)/12),"") | D80: =IF(AND(AND($N$5=1,52<=$N$11),$N$10=1),INDEX(IPC!$J$5:$J$16,MOD(K80,12)+1)&" de "&INT((K80)/12),"") | E80: =IF(NOT(AND($N$5=1,52<=$N$11)),"",IF($N$10=1,IF(AND($N$14=1,K80<=$N$12),INDEX(IPC!$D$5:$D$173,(K80)-IPC!$J$2+1)/INDEX(IPC!$D$5:$D$173,(L80)-IPC!$J$2+1)-1,""),IF(ISNUMBER(F80),F80/100,""))) | G80: =IF(AND(AND($N$5=1,52<=$N$11),ISNUMBER(G79),ISNUMBER(E80)),G79*(1+E80),"") | H80: =IF(NOT(AND($N$5=1,52<=$N$11)),"",IF(ISNUMBER(G80),"Aplicado",IF(ISNUMBER(G79),IF($N$10=1,"Falta el IPC de "&INDEX(IPC!$J$5:$J$16,MOD($N$12+1,12)+1)&" de "&INT(($N$12+1)/12),"Cargá el % de este ajuste en la columna F"),""))) | J80: =IF($N$5=1,$N$7+52*$N$8,"") | K80: =IF($N$5=1,J80-1-$N$9,"") | L80: =IF($N$5=1,K80-$N$8,"")
A81: =IF(AND($N$5=1,53<=$N$11),"53° ajuste","") | B81: =IF(AND($N$5=1,53<=$N$11),INDEX(IPC!$J$5:$J$16,MOD(J81,12)+1)&" de "&INT((J81)/12),"") | C81: =IF(AND(AND($N$5=1,53<=$N$11),$N$10=1),INDEX(IPC!$J$5:$J$16,MOD(L81,12)+1)&" de "&INT((L81)/12),"") | D81: =IF(AND(AND($N$5=1,53<=$N$11),$N$10=1),INDEX(IPC!$J$5:$J$16,MOD(K81,12)+1)&" de "&INT((K81)/12),"") | E81: =IF(NOT(AND($N$5=1,53<=$N$11)),"",IF($N$10=1,IF(AND($N$14=1,K81<=$N$12),INDEX(IPC!$D$5:$D$173,(K81)-IPC!$J$2+1)/INDEX(IPC!$D$5:$D$173,(L81)-IPC!$J$2+1)-1,""),IF(ISNUMBER(F81),F81/100,""))) | G81: =IF(AND(AND($N$5=1,53<=$N$11),ISNUMBER(G80),ISNUMBER(E81)),G80*(1+E81),"") | H81: =IF(NOT(AND($N$5=1,53<=$N$11)),"",IF(ISNUMBER(G81),"Aplicado",IF(ISNUMBER(G80),IF($N$10=1,"Falta el IPC de "&INDEX(IPC!$J$5:$J$16,MOD($N$12+1,12)+1)&" de "&INT(($N$12+1)/12),"Cargá el % de este ajuste en la columna F"),""))) | J81: =IF($N$5=1,$N$7+53*$N$8,"") | K81: =IF($N$5=1,J81-1-$N$9,"") | L81: =IF($N$5=1,K81-$N$8,"")
A82: =IF(AND($N$5=1,54<=$N$11),"54° ajuste","") | B82: =IF(AND($N$5=1,54<=$N$11),INDEX(IPC!$J$5:$J$16,MOD(J82,12)+1)&" de "&INT((J82)/12),"") | C82: =IF(AND(AND($N$5=1,54<=$N$11),$N$10=1),INDEX(IPC!$J$5:$J$16,MOD(L82,12)+1)&" de "&INT((L82)/12),"") | D82: =IF(AND(AND($N$5=1,54<=$N$11),$N$10=1),INDEX(IPC!$J$5:$J$16,MOD(K82,12)+1)&" de "&INT((K82)/12),"") | E82: =IF(NOT(AND($N$5=1,54<=$N$11)),"",IF($N$10=1,IF(AND($N$14=1,K82<=$N$12),INDEX(IPC!$D$5:$D$173,(K82)-IPC!$J$2+1)/INDEX(IPC!$D$5:$D$173,(L82)-IPC!$J$2+1)-1,""),IF(ISNUMBER(F82),F82/100,""))) | G82: =IF(AND(AND($N$5=1,54<=$N$11),ISNUMBER(G81),ISNUMBER(E82)),G81*(1+E82),"") | H82: =IF(NOT(AND($N$5=1,54<=$N$11)),"",IF(ISNUMBER(G82),"Aplicado",IF(ISNUMBER(G81),IF($N$10=1,"Falta el IPC de "&INDEX(IPC!$J$5:$J$16,MOD($N$12+1,12)+1)&" de "&INT(($N$12+1)/12),"Cargá el % de este ajuste en la columna F"),""))) | J82: =IF($N$5=1,$N$7+54*$N$8,"") | K82: =IF($N$5=1,J82-1-$N$9,"") | L82: =IF($N$5=1,K82-$N$8,"")
A83: =IF(AND($N$5=1,55<=$N$11),"55° ajuste","") | B83: =IF(AND($N$5=1,55<=$N$11),INDEX(IPC!$J$5:$J$16,MOD(J83,12)+1)&" de "&INT((J83)/12),"") | C83: =IF(AND(AND($N$5=1,55<=$N$11),$N$10=1),INDEX(IPC!$J$5:$J$16,MOD(L83,12)+1)&" de "&INT((L83)/12),"") | D83: =IF(AND(AND($N$5=1,55<=$N$11),$N$10=1),INDEX(IPC!$J$5:$J$16,MOD(K83,12)+1)&" de "&INT((K83)/12),"") | E83: =IF(NOT(AND($N$5=1,55<=$N$11)),"",IF($N$10=1,IF(AND($N$14=1,K83<=$N$12),INDEX(IPC!$D$5:$D$173,(K83)-IPC!$J$2+1)/INDEX(IPC!$D$5:$D$173,(L83)-IPC!$J$2+1)-1,""),IF(ISNUMBER(F83),F83/100,""))) | G83: =IF(AND(AND($N$5=1,55<=$N$11),ISNUMBER(G82),ISNUMBER(E83)),G82*(1+E83),"") | H83: =IF(NOT(AND($N$5=1,55<=$N$11)),"",IF(ISNUMBER(G83),"Aplicado",IF(ISNUMBER(G82),IF($N$10=1,"Falta el IPC de "&INDEX(IPC!$J$5:$J$16,MOD($N$12+1,12)+1)&" de "&INT(($N$12+1)/12),"Cargá el % de este ajuste en la columna F"),""))) | J83: =IF($N$5=1,$N$7+55*$N$8,"") | K83: =IF($N$5=1,J83-1-$N$9,"") | L83: =IF($N$5=1,K83-$N$8,"")
A84: =IF(AND($N$5=1,56<=$N$11),"56° ajuste","") | B84: =IF(AND($N$5=1,56<=$N$11),INDEX(IPC!$J$5:$J$16,MOD(J84,12)+1)&" de "&INT((J84)/12),"") | C84: =IF(AND(AND($N$5=1,56<=$N$11),$N$10=1),INDEX(IPC!$J$5:$J$16,MOD(L84,12)+1)&" de "&INT((L84)/12),"") | D84: =IF(AND(AND($N$5=1,56<=$N$11),$N$10=1),INDEX(IPC!$J$5:$J$16,MOD(K84,12)+1)&" de "&INT((K84)/12),"") | E84: =IF(NOT(AND($N$5=1,56<=$N$11)),"",IF($N$10=1,IF(AND($N$14=1,K84<=$N$12),INDEX(IPC!$D$5:$D$173,(K84)-IPC!$J$2+1)/INDEX(IPC!$D$5:$D$173,(L84)-IPC!$J$2+1)-1,""),IF(ISNUMBER(F84),F84/100,""))) | G84: =IF(AND(AND($N$5=1,56<=$N$11),ISNUMBER(G83),ISNUMBER(E84)),G83*(1+E84),"") | H84: =IF(NOT(AND($N$5=1,56<=$N$11)),"",IF(ISNUMBER(G84),"Aplicado",IF(ISNUMBER(G83),IF($N$10=1,"Falta el IPC de "&INDEX(IPC!$J$5:$J$16,MOD($N$12+1,12)+1)&" de "&INT(($N$12+1)/12),"Cargá el % de este ajuste en la columna F"),""))) | J84: =IF($N$5=1,$N$7+56*$N$8,"") | K84: =IF($N$5=1,J84-1-$N$9,"") | L84: =IF($N$5=1,K84-$N$8,"")
A85: =IF(AND($N$5=1,57<=$N$11),"57° ajuste","") | B85: =IF(AND($N$5=1,57<=$N$11),INDEX(IPC!$J$5:$J$16,MOD(J85,12)+1)&" de "&INT((J85)/12),"") | C85: =IF(AND(AND($N$5=1,57<=$N$11),$N$10=1),INDEX(IPC!$J$5:$J$16,MOD(L85,12)+1)&" de "&INT((L85)/12),"") | D85: =IF(AND(AND($N$5=1,57<=$N$11),$N$10=1),INDEX(IPC!$J$5:$J$16,MOD(K85,12)+1)&" de "&INT((K85)/12),"") | E85: =IF(NOT(AND($N$5=1,57<=$N$11)),"",IF($N$10=1,IF(AND($N$14=1,K85<=$N$12),INDEX(IPC!$D$5:$D$173,(K85)-IPC!$J$2+1)/INDEX(IPC!$D$5:$D$173,(L85)-IPC!$J$2+1)-1,""),IF(ISNUMBER(F85),F85/100,""))) | G85: =IF(AND(AND($N$5=1,57<=$N$11),ISNUMBER(G84),ISNUMBER(E85)),G84*(1+E85),"") | H85: =IF(NOT(AND($N$5=1,57<=$N$11)),"",IF(ISNUMBER(G85),"Aplicado",IF(ISNUMBER(G84),IF($N$10=1,"Falta el IPC de "&INDEX(IPC!$J$5:$J$16,MOD($N$12+1,12)+1)&" de "&INT(($N$12+1)/12),"Cargá el % de este ajuste en la columna F"),""))) | J85: =IF($N$5=1,$N$7+57*$N$8,"") | K85: =IF($N$5=1,J85-1-$N$9,"") | L85: =IF($N$5=1,K85-$N$8,"")
A86: =IF(AND($N$5=1,58<=$N$11),"58° ajuste","") | B86: =IF(AND($N$5=1,58<=$N$11),INDEX(IPC!$J$5:$J$16,MOD(J86,12)+1)&" de "&INT((J86)/12),"") | C86: =IF(AND(AND($N$5=1,58<=$N$11),$N$10=1),INDEX(IPC!$J$5:$J$16,MOD(L86,12)+1)&" de "&INT((L86)/12),"") | D86: =IF(AND(AND($N$5=1,58<=$N$11),$N$10=1),INDEX(IPC!$J$5:$J$16,MOD(K86,12)+1)&" de "&INT((K86)/12),"") | E86: =IF(NOT(AND($N$5=1,58<=$N$11)),"",IF($N$10=1,IF(AND($N$14=1,K86<=$N$12),INDEX(IPC!$D$5:$D$173,(K86)-IPC!$J$2+1)/INDEX(IPC!$D$5:$D$173,(L86)-IPC!$J$2+1)-1,""),IF(ISNUMBER(F86),F86/100,""))) | G86: =IF(AND(AND($N$5=1,58<=$N$11),ISNUMBER(G85),ISNUMBER(E86)),G85*(1+E86),"") | H86: =IF(NOT(AND($N$5=1,58<=$N$11)),"",IF(ISNUMBER(G86),"Aplicado",IF(ISNUMBER(G85),IF($N$10=1,"Falta el IPC de "&INDEX(IPC!$J$5:$J$16,MOD($N$12+1,12)+1)&" de "&INT(($N$12+1)/12),"Cargá el % de este ajuste en la columna F"),""))) | J86: =IF($N$5=1,$N$7+58*$N$8,"") | K86: =IF($N$5=1,J86-1-$N$9,"") | L86: =IF($N$5=1,K86-$N$8,"")
A87: =IF(AND($N$5=1,59<=$N$11),"59° ajuste","") | B87: =IF(AND($N$5=1,59<=$N$11),INDEX(IPC!$J$5:$J$16,MOD(J87,12)+1)&" de "&INT((J87)/12),"") | C87: =IF(AND(AND($N$5=1,59<=$N$11),$N$10=1),INDEX(IPC!$J$5:$J$16,MOD(L87,12)+1)&" de "&INT((L87)/12),"") | D87: =IF(AND(AND($N$5=1,59<=$N$11),$N$10=1),INDEX(IPC!$J$5:$J$16,MOD(K87,12)+1)&" de "&INT((K87)/12),"") | E87: =IF(NOT(AND($N$5=1,59<=$N$11)),"",IF($N$10=1,IF(AND($N$14=1,K87<=$N$12),INDEX(IPC!$D$5:$D$173,(K87)-IPC!$J$2+1)/INDEX(IPC!$D$5:$D$173,(L87)-IPC!$J$2+1)-1,""),IF(ISNUMBER(F87),F87/100,""))) | G87: =IF(AND(AND($N$5=1,59<=$N$11),ISNUMBER(G86),ISNUMBER(E87)),G86*(1+E87),"") | H87: =IF(NOT(AND($N$5=1,59<=$N$11)),"",IF(ISNUMBER(G87),"Aplicado",IF(ISNUMBER(G86),IF($N$10=1,"Falta el IPC de "&INDEX(IPC!$J$5:$J$16,MOD($N$12+1,12)+1)&" de "&INT(($N$12+1)/12),"Cargá el % de este ajuste en la columna F"),""))) | J87: =IF($N$5=1,$N$7+59*$N$8,"") | K87: =IF($N$5=1,J87-1-$N$9,"") | L87: =IF($N$5=1,K87-$N$8,"")
A88: =IF(AND($N$5=1,60<=$N$11),"60° ajuste","") | B88: =IF(AND($N$5=1,60<=$N$11),INDEX(IPC!$J$5:$J$16,MOD(J88,12)+1)&" de "&INT((J88)/12),"") | C88: =IF(AND(AND($N$5=1,60<=$N$11),$N$10=1),INDEX(IPC!$J$5:$J$16,MOD(L88,12)+1)&" de "&INT((L88)/12),"") | D88: =IF(AND(AND($N$5=1,60<=$N$11),$N$10=1),INDEX(IPC!$J$5:$J$16,MOD(K88,12)+1)&" de "&INT((K88)/12),"") | E88: =IF(NOT(AND($N$5=1,60<=$N$11)),"",IF($N$10=1,IF(AND($N$14=1,K88<=$N$12),INDEX(IPC!$D$5:$D$173,(K88)-IPC!$J$2+1)/INDEX(IPC!$D$5:$D$173,(L88)-IPC!$J$2+1)-1,""),IF(ISNUMBER(F88),F88/100,""))) | G88: =IF(AND(AND($N$5=1,60<=$N$11),ISNUMBER(G87),ISNUMBER(E88)),G87*(1+E88),"") | H88: =IF(NOT(AND($N$5=1,60<=$N$11)),"",IF(ISNUMBER(G88),"Aplicado",IF(ISNUMBER(G87),IF($N$10=1,"Falta el IPC de "&INDEX(IPC!$J$5:$J$16,MOD($N$12+1,12)+1)&" de "&INT(($N$12+1)/12),"Cargá el % de este ajuste en la columna F"),""))) | J88: =IF($N$5=1,$N$7+60*$N$8,"") | K88: =IF($N$5=1,J88-1-$N$9,"") | L88: =IF($N$5=1,K88-$N$8,"")
A90: Cada ajuste multiplica el alquiler vigente por la variación del índice del período: IPC del último mes ÷ IPC del mes anterior al primero. Los porcentajes se componen, no se suman. La letra de tu contrato manda: si dice otra cosa, ajustá el índice o la convención de arriba.

Sheet Contrato 3
A1: Contrato 3
A2: Completá las celdas amarillas con los datos del contrato. Las verdes se calculan solas.
A4: DATOS DEL CONTRATO
A5: Propiedad (dirección) | N5: =IF(AND(N6>0,ISNUMBER(B9),ISNUMBER(B11),B11>0,ISNUMBER(B13),B13>=1,ISNUMBER(B10),B10>=1),1,0)
A6: Inquilino/a | N6: =IFERROR(MATCH(B8,IPC!$J$5:$J$16,0),0)
A7: Tu nombre (para el recibo y el aviso) | N7: =IF(N5=1,B9*12+N6-1,0)
A8: Mes de inicio del contrato | C8: El primer mes en que se cobró el valor inicial. | N8: =IF(N5=1,INT(B13),1)
A9: Año de inicio | N9: =IF(B14="Los últimos publicados",1,0)
A10: Duración (meses) | B10: 24 | N10: =IF(B12="Otro índice (cargo el %)",0,1)
A11: Alquiler inicial (el del primer mes) | N11: =IF(N5=1,MIN(INT((B10-1)/N8),60),0)
A12: Índice de ajuste | B12: IPC (INDEC) | C12: Si tu contrato ajusta por ICL, Casa Propia u otro índice, elegí «Otro» y cargá el % de cada ajuste en el cronograma (columna F). | N12: =IPC!$J$3
A13: Se ajusta cada (meses) | B13: 3 | C13: Trimestral = 3, cuatrimestral = 4, semestral = 6, anual = 12. | N13: =IPC!$J$2
A14: Meses del IPC que toma | B14: Los completos antes del ajuste | C14: «Completos»: un ajuste de julio usa el IPC de abril a junio (como la calculadora de calcular.ar). «Últimos publicados»: usa el de marzo a mayo, porque el de junio sale a mitad de julio. Fijate qué dice tu contrato. | N14: =IF(N5=0,0,IF(N10=0,1,IF(AND(N7-1-N9>=N13,N7-1-N9<=N12),1,0)))
N15: =COUNT(G29:G88)
A16: CÓMO VIENE EL CONTRATO | N16: =IF(N5=1,INDEX(G28:G88,N15+1),"")
A17: Alquiler que se cobra hoy | B17: =N16 | N17: =N15+1
A18: Rige desde | B18: =IF(N5=1,INDEX(B28:B88,N15+1),"") | N18: =IF(AND(N5=1,N17<=N11),1,0)
A19: Ajustes aplicados | B19: =IF(N5=1,N15,"") | N19: =N7+N17*N8-1-N9
A20: Aumento desde el inicio | B20: =IF(N5=1,N16/B11-1,"") | N20: =N19-N12
A21: Próximo ajuste | B21: =IF(N18=1,INDEX(B28:B88,N17+1),IF(N5=1,"No quedan ajustes antes de que termine","")) | N21: =INDEX(IPC!$D$5:$D$173,(N12)-IPC!$J$2+1)/INDEX(IPC!$D$5:$D$173,(N12-1)-IPC!$J$2+1)-1
A22: Próximo alquiler estimado | B22: =N22 | N22: =IF(AND(N18=1,N10=1,N14=1,N20>0,N20<=12),N16*INDEX(IPC!$D$5:$D$173,(N12)-IPC!$J$2+1)*(1+N21)^N20/INDEX(IPC!$D$5:$D$173,(N19-N8)-IPC!$J$2+1),"")
A23: Último mes del contrato | B23: =IF(N5=1,INDEX(IPC!$J$5:$J$16,MOD(N7+B10-1,12)+1)&" de "&INT((N7+B10-1)/12),"") | N23: =IF(ISNUMBER(N22),ROUND(N22,0),"")
A24: Qué hacer ahora | B24: =IF(N5=0,"Completá las celdas amarillas de arriba y acá aparece el cronograma de aumentos.",IF(N14=0,"Todavía no está publicado el IPC de "&INDEX(IPC!$J$5:$J$16,MOD(N7-1-N9,12)+1)&" de "&INT((N7-1-N9)/12)&", que es la base de este contrato. Mientras tanto se cobra el valor inicial.",IF(N18=0,"No quedan ajustes: el contrato termina en "&INDEX(IPC!$J$5:$J$16,MOD(N7+B10-1,12)+1)&" de "&INT((N7+B10-1)/12)&".",IF(N10=1,"El próximo ajuste rige desde "&B21&". Se calcula cuando el INDEC publique el IPC de "&INDEX(IPC!$J$5:$J$16,MOD(N19,12)+1)&" de "&INT((N19)/12)&" (sale entre el 10 y el 15 del mes siguiente)"&IF(ISNUMBER(N22),". Si la inflación siguiera como el último mes, el alquiler quedaría en unos $ "&N24&".","."),"El próximo ajuste rige desde "&B21&": cuando lo tengas, cargá el % del índice pactado en la columna F del cronograma.")))) | N24: =IF(ISNUMBER(N23),IF(N23>=1000000000,INT(N23/1000000000)&"."&RIGHT("00"&INT(MOD(N23,1000000000)/1000000),3)&"."&RIGHT("00"&INT(MOD(N23,1000000)/1000),3)&"."&RIGHT("00"&INT(MOD(N23,1000)/1),3),IF(N23>=1000000,INT(N23/1000000)&"."&RIGHT("00"&INT(MOD(N23,1000000)/1000),3)&"."&RIGHT("00"&INT(MOD(N23,1000)/1),3),IF(N23>=1000,INT(N23/1000)&"."&RIGHT("00"&INT(MOD(N23,1000)/1),3),""&N23))),"")
A26: CRONOGRAMA DE AJUSTES
A27: Ajuste | B27: Rige desde | C27: Mes del IPC base | D27: Mes del IPC final | E27: Variación | F27: % a mano (otro índice) | G27: Alquiler | H27: Estado
A28: =IF($N$5=1,"Valor inicial","") | B28: =IF($N$5=1,INDEX(IPC!$J$5:$J$16,MOD(J28,12)+1)&" de "&INT((J28)/12),"") | G28: =IF($N$5=1,B11,"") | H28: =IF($N$5=1,"Valor inicial del contrato","") | J28: =IF($N$5=1,$N$7+0*$N$8,"") | K28: =IF($N$5=1,J28-1-$N$9,"") | L28: =IF($N$5=1,K28-$N$8,"")
A29: =IF(AND($N$5=1,1<=$N$11),"1° ajuste","") | B29: =IF(AND($N$5=1,1<=$N$11),INDEX(IPC!$J$5:$J$16,MOD(J29,12)+1)&" de "&INT((J29)/12),"") | C29: =IF(AND(AND($N$5=1,1<=$N$11),$N$10=1),INDEX(IPC!$J$5:$J$16,MOD(L29,12)+1)&" de "&INT((L29)/12),"") | D29: =IF(AND(AND($N$5=1,1<=$N$11),$N$10=1),INDEX(IPC!$J$5:$J$16,MOD(K29,12)+1)&" de "&INT((K29)/12),"") | E29: =IF(NOT(AND($N$5=1,1<=$N$11)),"",IF($N$10=1,IF(AND($N$14=1,K29<=$N$12),INDEX(IPC!$D$5:$D$173,(K29)-IPC!$J$2+1)/INDEX(IPC!$D$5:$D$173,(L29)-IPC!$J$2+1)-1,""),IF(ISNUMBER(F29),F29/100,""))) | G29: =IF(AND(AND($N$5=1,1<=$N$11),ISNUMBER(G28),ISNUMBER(E29)),G28*(1+E29),"") | H29: =IF(NOT(AND($N$5=1,1<=$N$11)),"",IF(ISNUMBER(G29),"Aplicado",IF(ISNUMBER(G28),IF($N$10=1,"Falta el IPC de "&INDEX(IPC!$J$5:$J$16,MOD($N$12+1,12)+1)&" de "&INT(($N$12+1)/12),"Cargá el % de este ajuste en la columna F"),""))) | J29: =IF($N$5=1,$N$7+1*$N$8,"") | K29: =IF($N$5=1,J29-1-$N$9,"") | L29: =IF($N$5=1,K29-$N$8,"")
A30: =IF(AND($N$5=1,2<=$N$11),"2° ajuste","") | B30: =IF(AND($N$5=1,2<=$N$11),INDEX(IPC!$J$5:$J$16,MOD(J30,12)+1)&" de "&INT((J30)/12),"") | C30: =IF(AND(AND($N$5=1,2<=$N$11),$N$10=1),INDEX(IPC!$J$5:$J$16,MOD(L30,12)+1)&" de "&INT((L30)/12),"") | D30: =IF(AND(AND($N$5=1,2<=$N$11),$N$10=1),INDEX(IPC!$J$5:$J$16,MOD(K30,12)+1)&" de "&INT((K30)/12),"") | E30: =IF(NOT(AND($N$5=1,2<=$N$11)),"",IF($N$10=1,IF(AND($N$14=1,K30<=$N$12),INDEX(IPC!$D$5:$D$173,(K30)-IPC!$J$2+1)/INDEX(IPC!$D$5:$D$173,(L30)-IPC!$J$2+1)-1,""),IF(ISNUMBER(F30),F30/100,""))) | G30: =IF(AND(AND($N$5=1,2<=$N$11),ISNUMBER(G29),ISNUMBER(E30)),G29*(1+E30),"") | H30: =IF(NOT(AND($N$5=1,2<=$N$11)),"",IF(ISNUMBER(G30),"Aplicado",IF(ISNUMBER(G29),IF($N$10=1,"Falta el IPC de "&INDEX(IPC!$J$5:$J$16,MOD($N$12+1,12)+1)&" de "&INT(($N$12+1)/12),"Cargá el % de este ajuste en la columna F"),""))) | J30: =IF($N$5=1,$N$7+2*$N$8,"") | K30: =IF($N$5=1,J30-1-$N$9,"") | L30: =IF($N$5=1,K30-$N$8,"")
A31: =IF(AND($N$5=1,3<=$N$11),"3° ajuste","") | B31: =IF(AND($N$5=1,3<=$N$11),INDEX(IPC!$J$5:$J$16,MOD(J31,12)+1)&" de "&INT((J31)/12),"") | C31: =IF(AND(AND($N$5=1,3<=$N$11),$N$10=1),INDEX(IPC!$J$5:$J$16,MOD(L31,12)+1)&" de "&INT((L31)/12),"") | D31: =IF(AND(AND($N$5=1,3<=$N$11),$N$10=1),INDEX(IPC!$J$5:$J$16,MOD(K31,12)+1)&" de "&INT((K31)/12),"") | E31: =IF(NOT(AND($N$5=1,3<=$N$11)),"",IF($N$10=1,IF(AND($N$14=1,K31<=$N$12),INDEX(IPC!$D$5:$D$173,(K31)-IPC!$J$2+1)/INDEX(IPC!$D$5:$D$173,(L31)-IPC!$J$2+1)-1,""),IF(ISNUMBER(F31),F31/100,""))) | G31: =IF(AND(AND($N$5=1,3<=$N$11),ISNUMBER(G30),ISNUMBER(E31)),G30*(1+E31),"") | H31: =IF(NOT(AND($N$5=1,3<=$N$11)),"",IF(ISNUMBER(G31),"Aplicado",IF(ISNUMBER(G30),IF($N$10=1,"Falta el IPC de "&INDEX(IPC!$J$5:$J$16,MOD($N$12+1,12)+1)&" de "&INT(($N$12+1)/12),"Cargá el % de este ajuste en la columna F"),""))) | J31: =IF($N$5=1,$N$7+3*$N$8,"") | K31: =IF($N$5=1,J31-1-$N$9,"") | L31: =IF($N$5=1,K31-$N$8,"")
A32: =IF(AND($N$5=1,4<=$N$11),"4° ajuste","") | B32: =IF(AND($N$5=1,4<=$N$11),INDEX(IPC!$J$5:$J$16,MOD(J32,12)+1)&" de "&INT((J32)/12),"") | C32: =IF(AND(AND($N$5=1,4<=$N$11),$N$10=1),INDEX(IPC!$J$5:$J$16,MOD(L32,12)+1)&" de "&INT((L32)/12),"") | D32: =IF(AND(AND($N$5=1,4<=$N$11),$N$10=1),INDEX(IPC!$J$5:$J$16,MOD(K32,12)+1)&" de "&INT((K32)/12),"") | E32: =IF(NOT(AND($N$5=1,4<=$N$11)),"",IF($N$10=1,IF(AND($N$14=1,K32<=$N$12),INDEX(IPC!$D$5:$D$173,(K32)-IPC!$J$2+1)/INDEX(IPC!$D$5:$D$173,(L32)-IPC!$J$2+1)-1,""),IF(ISNUMBER(F32),F32/100,""))) | G32: =IF(AND(AND($N$5=1,4<=$N$11),ISNUMBER(G31),ISNUMBER(E32)),G31*(1+E32),"") | H32: =IF(NOT(AND($N$5=1,4<=$N$11)),"",IF(ISNUMBER(G32),"Aplicado",IF(ISNUMBER(G31),IF($N$10=1,"Falta el IPC de "&INDEX(IPC!$J$5:$J$16,MOD($N$12+1,12)+1)&" de "&INT(($N$12+1)/12),"Cargá el % de este ajuste en la columna F"),""))) | J32: =IF($N$5=1,$N$7+4*$N$8,"") | K32: =IF($N$5=1,J32-1-$N$9,"") | L32: =IF($N$5=1,K32-$N$8,"")
A33: =IF(AND($N$5=1,5<=$N$11),"5° ajuste","") | B33: =IF(AND($N$5=1,5<=$N$11),INDEX(IPC!$J$5:$J$16,MOD(J33,12)+1)&" de "&INT((J33)/12),"") | C33: =IF(AND(AND($N$5=1,5<=$N$11),$N$10=1),INDEX(IPC!$J$5:$J$16,MOD(L33,12)+1)&" de "&INT((L33)/12),"") | D33: =IF(AND(AND($N$5=1,5<=$N$11),$N$10=1),INDEX(IPC!$J$5:$J$16,MOD(K33,12)+1)&" de "&INT((K33)/12),"") | E33: =IF(NOT(AND($N$5=1,5<=$N$11)),"",IF($N$10=1,IF(AND($N$14=1,K33<=$N$12),INDEX(IPC!$D$5:$D$173,(K33)-IPC!$J$2+1)/INDEX(IPC!$D$5:$D$173,(L33)-IPC!$J$2+1)-1,""),IF(ISNUMBER(F33),F33/100,""))) | G33: =IF(AND(AND($N$5=1,5<=$N$11),ISNUMBER(G32),ISNUMBER(E33)),G32*(1+E33),"") | H33: =IF(NOT(AND($N$5=1,5<=$N$11)),"",IF(ISNUMBER(G33),"Aplicado",IF(ISNUMBER(G32),IF($N$10=1,"Falta el IPC de "&INDEX(IPC!$J$5:$J$16,MOD($N$12+1,12)+1)&" de "&INT(($N$12+1)/12),"Cargá el % de este ajuste en la columna F"),""))) | J33: =IF($N$5=1,$N$7+5*$N$8,"") | K33: =IF($N$5=1,J33-1-$N$9,"") | L33: =IF($N$5=1,K33-$N$8,"")
A34: =IF(AND($N$5=1,6<=$N$11),"6° ajuste","") | B34: =IF(AND($N$5=1,6<=$N$11),INDEX(IPC!$J$5:$J$16,MOD(J34,12)+1)&" de "&INT((J34)/12),"") | C34: =IF(AND(AND($N$5=1,6<=$N$11),$N$10=1),INDEX(IPC!$J$5:$J$16,MOD(L34,12)+1)&" de "&INT((L34)/12),"") | D34: =IF(AND(AND($N$5=1,6<=$N$11),$N$10=1),INDEX(IPC!$J$5:$J$16,MOD(K34,12)+1)&" de "&INT((K34)/12),"") | E34: =IF(NOT(AND($N$5=1,6<=$N$11)),"",IF($N$10=1,IF(AND($N$14=1,K34<=$N$12),INDEX(IPC!$D$5:$D$173,(K34)-IPC!$J$2+1)/INDEX(IPC!$D$5:$D$173,(L34)-IPC!$J$2+1)-1,""),IF(ISNUMBER(F34),F34/100,""))) | G34: =IF(AND(AND($N$5=1,6<=$N$11),ISNUMBER(G33),ISNUMBER(E34)),G33*(1+E34),"") | H34: =IF(NOT(AND($N$5=1,6<=$N$11)),"",IF(ISNUMBER(G34),"Aplicado",IF(ISNUMBER(G33),IF($N$10=1,"Falta el IPC de "&INDEX(IPC!$J$5:$J$16,MOD($N$12+1,12)+1)&" de "&INT(($N$12+1)/12),"Cargá el % de este ajuste en la columna F"),""))) | J34: =IF($N$5=1,$N$7+6*$N$8,"") | K34: =IF($N$5=1,J34-1-$N$9,"") | L34: =IF($N$5=1,K34-$N$8,"")
A35: =IF(AND($N$5=1,7<=$N$11),"7° ajuste","") | B35: =IF(AND($N$5=1,7<=$N$11),INDEX(IPC!$J$5:$J$16,MOD(J35,12)+1)&" de "&INT((J35)/12),"") | C35: =IF(AND(AND($N$5=1,7<=$N$11),$N$10=1),INDEX(IPC!$J$5:$J$16,MOD(L35,12)+1)&" de "&INT((L35)/12),"") | D35: =IF(AND(AND($N$5=1,7<=$N$11),$N$10=1),INDEX(IPC!$J$5:$J$16,MOD(K35,12)+1)&" de "&INT((K35)/12),"") | E35: =IF(NOT(AND($N$5=1,7<=$N$11)),"",IF($N$10=1,IF(AND($N$14=1,K35<=$N$12),INDEX(IPC!$D$5:$D$173,(K35)-IPC!$J$2+1)/INDEX(IPC!$D$5:$D$173,(L35)-IPC!$J$2+1)-1,""),IF(ISNUMBER(F35),F35/100,""))) | G35: =IF(AND(AND($N$5=1,7<=$N$11),ISNUMBER(G34),ISNUMBER(E35)),G34*(1+E35),"") | H35: =IF(NOT(AND($N$5=1,7<=$N$11)),"",IF(ISNUMBER(G35),"Aplicado",IF(ISNUMBER(G34),IF($N$10=1,"Falta el IPC de "&INDEX(IPC!$J$5:$J$16,MOD($N$12+1,12)+1)&" de "&INT(($N$12+1)/12),"Cargá el % de este ajuste en la columna F"),""))) | J35: =IF($N$5=1,$N$7+7*$N$8,"") | K35: =IF($N$5=1,J35-1-$N$9,"") | L35: =IF($N$5=1,K35-$N$8,"")
A36: =IF(AND($N$5=1,8<=$N$11),"8° ajuste","") | B36: =IF(AND($N$5=1,8<=$N$11),INDEX(IPC!$J$5:$J$16,MOD(J36,12)+1)&" de "&INT((J36)/12),"") | C36: =IF(AND(AND($N$5=1,8<=$N$11),$N$10=1),INDEX(IPC!$J$5:$J$16,MOD(L36,12)+1)&" de "&INT((L36)/12),"") | D36: =IF(AND(AND($N$5=1,8<=$N$11),$N$10=1),INDEX(IPC!$J$5:$J$16,MOD(K36,12)+1)&" de "&INT((K36)/12),"") | E36: =IF(NOT(AND($N$5=1,8<=$N$11)),"",IF($N$10=1,IF(AND($N$14=1,K36<=$N$12),INDEX(IPC!$D$5:$D$173,(K36)-IPC!$J$2+1)/INDEX(IPC!$D$5:$D$173,(L36)-IPC!$J$2+1)-1,""),IF(ISNUMBER(F36),F36/100,""))) | G36: =IF(AND(AND($N$5=1,8<=$N$11),ISNUMBER(G35),ISNUMBER(E36)),G35*(1+E36),"") | H36: =IF(NOT(AND($N$5=1,8<=$N$11)),"",IF(ISNUMBER(G36),"Aplicado",IF(ISNUMBER(G35),IF($N$10=1,"Falta el IPC de "&INDEX(IPC!$J$5:$J$16,MOD($N$12+1,12)+1)&" de "&INT(($N$12+1)/12),"Cargá el % de este ajuste en la columna F"),""))) | J36: =IF($N$5=1,$N$7+8*$N$8,"") | K36: =IF($N$5=1,J36-1-$N$9,"") | L36: =IF($N$5=1,K36-$N$8,"")
A37: =IF(AND($N$5=1,9<=$N$11),"9° ajuste","") | B37: =IF(AND($N$5=1,9<=$N$11),INDEX(IPC!$J$5:$J$16,MOD(J37,12)+1)&" de "&INT((J37)/12),"") | C37: =IF(AND(AND($N$5=1,9<=$N$11),$N$10=1),INDEX(IPC!$J$5:$J$16,MOD(L37,12)+1)&" de "&INT((L37)/12),"") | D37: =IF(AND(AND($N$5=1,9<=$N$11),$N$10=1),INDEX(IPC!$J$5:$J$16,MOD(K37,12)+1)&" de "&INT((K37)/12),"") | E37: =IF(NOT(AND($N$5=1,9<=$N$11)),"",IF($N$10=1,IF(AND($N$14=1,K37<=$N$12),INDEX(IPC!$D$5:$D$173,(K37)-IPC!$J$2+1)/INDEX(IPC!$D$5:$D$173,(L37)-IPC!$J$2+1)-1,""),IF(ISNUMBER(F37),F37/100,""))) | G37: =IF(AND(AND($N$5=1,9<=$N$11),ISNUMBER(G36),ISNUMBER(E37)),G36*(1+E37),"") | H37: =IF(NOT(AND($N$5=1,9<=$N$11)),"",IF(ISNUMBER(G37),"Aplicado",IF(ISNUMBER(G36),IF($N$10=1,"Falta el IPC de "&INDEX(IPC!$J$5:$J$16,MOD($N$12+1,12)+1)&" de "&INT(($N$12+1)/12),"Cargá el % de este ajuste en la columna F"),""))) | J37: =IF($N$5=1,$N$7+9*$N$8,"") | K37: =IF($N$5=1,J37-1-$N$9,"") | L37: =IF($N$5=1,K37-$N$8,"")
A38: =IF(AND($N$5=1,10<=$N$11),"10° ajuste","") | B38: =IF(AND($N$5=1,10<=$N$11),INDEX(IPC!$J$5:$J$16,MOD(J38,12)+1)&" de "&INT((J38)/12),"") | C38: =IF(AND(AND($N$5=1,10<=$N$11),$N$10=1),INDEX(IPC!$J$5:$J$16,MOD(L38,12)+1)&" de "&INT((L38)/12),"") | D38: =IF(AND(AND($N$5=1,10<=$N$11),$N$10=1),INDEX(IPC!$J$5:$J$16,MOD(K38,12)+1)&" de "&INT((K38)/12),"") | E38: =IF(NOT(AND($N$5=1,10<=$N$11)),"",IF($N$10=1,IF(AND($N$14=1,K38<=$N$12),INDEX(IPC!$D$5:$D$173,(K38)-IPC!$J$2+1)/INDEX(IPC!$D$5:$D$173,(L38)-IPC!$J$2+1)-1,""),IF(ISNUMBER(F38),F38/100,""))) | G38: =IF(AND(AND($N$5=1,10<=$N$11),ISNUMBER(G37),ISNUMBER(E38)),G37*(1+E38),"") | H38: =IF(NOT(AND($N$5=1,10<=$N$11)),"",IF(ISNUMBER(G38),"Aplicado",IF(ISNUMBER(G37),IF($N$10=1,"Falta el IPC de "&INDEX(IPC!$J$5:$J$16,MOD($N$12+1,12)+1)&" de "&INT(($N$12+1)/12),"Cargá el % de este ajuste en la columna F"),""))) | J38: =IF($N$5=1,$N$7+10*$N$8,"") | K38: =IF($N$5=1,J38-1-$N$9,"") | L38: =IF($N$5=1,K38-$N$8,"")
A39: =IF(AND($N$5=1,11<=$N$11),"11° ajuste","") | B39: =IF(AND($N$5=1,11<=$N$11),INDEX(IPC!$J$5:$J$16,MOD(J39,12)+1)&" de "&INT((J39)/12),"") | C39: =IF(AND(AND($N$5=1,11<=$N$11),$N$10=1),INDEX(IPC!$J$5:$J$16,MOD(L39,12)+1)&" de "&INT((L39)/12),"") | D39: =IF(AND(AND($N$5=1,11<=$N$11),$N$10=1),INDEX(IPC!$J$5:$J$16,MOD(K39,12)+1)&" de "&INT((K39)/12),"") | E39: =IF(NOT(AND($N$5=1,11<=$N$11)),"",IF($N$10=1,IF(AND($N$14=1,K39<=$N$12),INDEX(IPC!$D$5:$D$173,(K39)-IPC!$J$2+1)/INDEX(IPC!$D$5:$D$173,(L39)-IPC!$J$2+1)-1,""),IF(ISNUMBER(F39),F39/100,""))) | G39: =IF(AND(AND($N$5=1,11<=$N$11),ISNUMBER(G38),ISNUMBER(E39)),G38*(1+E39),"") | H39: =IF(NOT(AND($N$5=1,11<=$N$11)),"",IF(ISNUMBER(G39),"Aplicado",IF(ISNUMBER(G38),IF($N$10=1,"Falta el IPC de "&INDEX(IPC!$J$5:$J$16,MOD($N$12+1,12)+1)&" de "&INT(($N$12+1)/12),"Cargá el % de este ajuste en la columna F"),""))) | J39: =IF($N$5=1,$N$7+11*$N$8,"") | K39: =IF($N$5=1,J39-1-$N$9,"") | L39: =IF($N$5=1,K39-$N$8,"")
A40: =IF(AND($N$5=1,12<=$N$11),"12° ajuste","") | B40: =IF(AND($N$5=1,12<=$N$11),INDEX(IPC!$J$5:$J$16,MOD(J40,12)+1)&" de "&INT((J40)/12),"") | C40: =IF(AND(AND($N$5=1,12<=$N$11),$N$10=1),INDEX(IPC!$J$5:$J$16,MOD(L40,12)+1)&" de "&INT((L40)/12),"") | D40: =IF(AND(AND($N$5=1,12<=$N$11),$N$10=1),INDEX(IPC!$J$5:$J$16,MOD(K40,12)+1)&" de "&INT((K40)/12),"") | E40: =IF(NOT(AND($N$5=1,12<=$N$11)),"",IF($N$10=1,IF(AND($N$14=1,K40<=$N$12),INDEX(IPC!$D$5:$D$173,(K40)-IPC!$J$2+1)/INDEX(IPC!$D$5:$D$173,(L40)-IPC!$J$2+1)-1,""),IF(ISNUMBER(F40),F40/100,""))) | G40: =IF(AND(AND($N$5=1,12<=$N$11),ISNUMBER(G39),ISNUMBER(E40)),G39*(1+E40),"") | H40: =IF(NOT(AND($N$5=1,12<=$N$11)),"",IF(ISNUMBER(G40),"Aplicado",IF(ISNUMBER(G39),IF($N$10=1,"Falta el IPC de "&INDEX(IPC!$J$5:$J$16,MOD($N$12+1,12)+1)&" de "&INT(($N$12+1)/12),"Cargá el % de este ajuste en la columna F"),""))) | J40: =IF($N$5=1,$N$7+12*$N$8,"") | K40: =IF($N$5=1,J40-1-$N$9,"") | L40: =IF($N$5=1,K40-$N$8,"")
A41: =IF(AND($N$5=1,13<=$N$11),"13° ajuste","") | B41: =IF(AND($N$5=1,13<=$N$11),INDEX(IPC!$J$5:$J$16,MOD(J41,12)+1)&" de "&INT((J41)/12),"") | C41: =IF(AND(AND($N$5=1,13<=$N$11),$N$10=1),INDEX(IPC!$J$5:$J$16,MOD(L41,12)+1)&" de "&INT((L41)/12),"") | D41: =IF(AND(AND($N$5=1,13<=$N$11),$N$10=1),INDEX(IPC!$J$5:$J$16,MOD(K41,12)+1)&" de "&INT((K41)/12),"") | E41: =IF(NOT(AND($N$5=1,13<=$N$11)),"",IF($N$10=1,IF(AND($N$14=1,K41<=$N$12),INDEX(IPC!$D$5:$D$173,(K41)-IPC!$J$2+1)/INDEX(IPC!$D$5:$D$173,(L41)-IPC!$J$2+1)-1,""),IF(ISNUMBER(F41),F41/100,""))) | G41: =IF(AND(AND($N$5=1,13<=$N$11),ISNUMBER(G40),ISNUMBER(E41)),G40*(1+E41),"") | H41: =IF(NOT(AND($N$5=1,13<=$N$11)),"",IF(ISNUMBER(G41),"Aplicado",IF(ISNUMBER(G40),IF($N$10=1,"Falta el IPC de "&INDEX(IPC!$J$5:$J$16,MOD($N$12+1,12)+1)&" de "&INT(($N$12+1)/12),"Cargá el % de este ajuste en la columna F"),""))) | J41: =IF($N$5=1,$N$7+13*$N$8,"") | K41: =IF($N$5=1,J41-1-$N$9,"") | L41: =IF($N$5=1,K41-$N$8,"")
A42: =IF(AND($N$5=1,14<=$N$11),"14° ajuste","") | B42: =IF(AND($N$5=1,14<=$N$11),INDEX(IPC!$J$5:$J$16,MOD(J42,12)+1)&" de "&INT((J42)/12),"") | C42: =IF(AND(AND($N$5=1,14<=$N$11),$N$10=1),INDEX(IPC!$J$5:$J$16,MOD(L42,12)+1)&" de "&INT((L42)/12),"") | D42: =IF(AND(AND($N$5=1,14<=$N$11),$N$10=1),INDEX(IPC!$J$5:$J$16,MOD(K42,12)+1)&" de "&INT((K42)/12),"") | E42: =IF(NOT(AND($N$5=1,14<=$N$11)),"",IF($N$10=1,IF(AND($N$14=1,K42<=$N$12),INDEX(IPC!$D$5:$D$173,(K42)-IPC!$J$2+1)/INDEX(IPC!$D$5:$D$173,(L42)-IPC!$J$2+1)-1,""),IF(ISNUMBER(F42),F42/100,""))) | G42: =IF(AND(AND($N$5=1,14<=$N$11),ISNUMBER(G41),ISNUMBER(E42)),G41*(1+E42),"") | H42: =IF(NOT(AND($N$5=1,14<=$N$11)),"",IF(ISNUMBER(G42),"Aplicado",IF(ISNUMBER(G41),IF($N$10=1,"Falta el IPC de "&INDEX(IPC!$J$5:$J$16,MOD($N$12+1,12)+1)&" de "&INT(($N$12+1)/12),"Cargá el % de este ajuste en la columna F"),""))) | J42: =IF($N$5=1,$N$7+14*$N$8,"") | K42: =IF($N$5=1,J42-1-$N$9,"") | L42: =IF($N$5=1,K42-$N$8,"")
A43: =IF(AND($N$5=1,15<=$N$11),"15° ajuste","") | B43: =IF(AND($N$5=1,15<=$N$11),INDEX(IPC!$J$5:$J$16,MOD(J43,12)+1)&" de "&INT((J43)/12),"") | C43: =IF(AND(AND($N$5=1,15<=$N$11),$N$10=1),INDEX(IPC!$J$5:$J$16,MOD(L43,12)+1)&" de "&INT((L43)/12),"") | D43: =IF(AND(AND($N$5=1,15<=$N$11),$N$10=1),INDEX(IPC!$J$5:$J$16,MOD(K43,12)+1)&" de "&INT((K43)/12),"") | E43: =IF(NOT(AND($N$5=1,15<=$N$11)),"",IF($N$10=1,IF(AND($N$14=1,K43<=$N$12),INDEX(IPC!$D$5:$D$173,(K43)-IPC!$J$2+1)/INDEX(IPC!$D$5:$D$173,(L43)-IPC!$J$2+1)-1,""),IF(ISNUMBER(F43),F43/100,""))) | G43: =IF(AND(AND($N$5=1,15<=$N$11),ISNUMBER(G42),ISNUMBER(E43)),G42*(1+E43),"") | H43: =IF(NOT(AND($N$5=1,15<=$N$11)),"",IF(ISNUMBER(G43),"Aplicado",IF(ISNUMBER(G42),IF($N$10=1,"Falta el IPC de "&INDEX(IPC!$J$5:$J$16,MOD($N$12+1,12)+1)&" de "&INT(($N$12+1)/12),"Cargá el % de este ajuste en la columna F"),""))) | J43: =IF($N$5=1,$N$7+15*$N$8,"") | K43: =IF($N$5=1,J43-1-$N$9,"") | L43: =IF($N$5=1,K43-$N$8,"")
A44: =IF(AND($N$5=1,16<=$N$11),"16° ajuste","") | B44: =IF(AND($N$5=1,16<=$N$11),INDEX(IPC!$J$5:$J$16,MOD(J44,12)+1)&" de "&INT((J44)/12),"") | C44: =IF(AND(AND($N$5=1,16<=$N$11),$N$10=1),INDEX(IPC!$J$5:$J$16,MOD(L44,12)+1)&" de "&INT((L44)/12),"") | D44: =IF(AND(AND($N$5=1,16<=$N$11),$N$10=1),INDEX(IPC!$J$5:$J$16,MOD(K44,12)+1)&" de "&INT((K44)/12),"") | E44: =IF(NOT(AND($N$5=1,16<=$N$11)),"",IF($N$10=1,IF(AND($N$14=1,K44<=$N$12),INDEX(IPC!$D$5:$D$173,(K44)-IPC!$J$2+1)/INDEX(IPC!$D$5:$D$173,(L44)-IPC!$J$2+1)-1,""),IF(ISNUMBER(F44),F44/100,""))) | G44: =IF(AND(AND($N$5=1,16<=$N$11),ISNUMBER(G43),ISNUMBER(E44)),G43*(1+E44),"") | H44: =IF(NOT(AND($N$5=1,16<=$N$11)),"",IF(ISNUMBER(G44),"Aplicado",IF(ISNUMBER(G43),IF($N$10=1,"Falta el IPC de "&INDEX(IPC!$J$5:$J$16,MOD($N$12+1,12)+1)&" de "&INT(($N$12+1)/12),"Cargá el % de este ajuste en la columna F"),""))) | J44: =IF($N$5=1,$N$7+16*$N$8,"") | K44: =IF($N$5=1,J44-1-$N$9,"") | L44: =IF($N$5=1,K44-$N$8,"")
A45: =IF(AND($N$5=1,17<=$N$11),"17° ajuste","") | B45: =IF(AND($N$5=1,17<=$N$11),INDEX(IPC!$J$5:$J$16,MOD(J45,12)+1)&" de "&INT((J45)/12),"") | C45: =IF(AND(AND($N$5=1,17<=$N$11),$N$10=1),INDEX(IPC!$J$5:$J$16,MOD(L45,12)+1)&" de "&INT((L45)/12),"") | D45: =IF(AND(AND($N$5=1,17<=$N$11),$N$10=1),INDEX(IPC!$J$5:$J$16,MOD(K45,12)+1)&" de "&INT((K45)/12),"") | E45: =IF(NOT(AND($N$5=1,17<=$N$11)),"",IF($N$10=1,IF(AND($N$14=1,K45<=$N$12),INDEX(IPC!$D$5:$D$173,(K45)-IPC!$J$2+1)/INDEX(IPC!$D$5:$D$173,(L45)-IPC!$J$2+1)-1,""),IF(ISNUMBER(F45),F45/100,""))) | G45: =IF(AND(AND($N$5=1,17<=$N$11),ISNUMBER(G44),ISNUMBER(E45)),G44*(1+E45),"") | H45: =IF(NOT(AND($N$5=1,17<=$N$11)),"",IF(ISNUMBER(G45),"Aplicado",IF(ISNUMBER(G44),IF($N$10=1,"Falta el IPC de "&INDEX(IPC!$J$5:$J$16,MOD($N$12+1,12)+1)&" de "&INT(($N$12+1)/12),"Cargá el % de este ajuste en la columna F"),""))) | J45: =IF($N$5=1,$N$7+17*$N$8,"") | K45: =IF($N$5=1,J45-1-$N$9,"") | L45: =IF($N$5=1,K45-$N$8,"")
A46: =IF(AND($N$5=1,18<=$N$11),"18° ajuste","") | B46: =IF(AND($N$5=1,18<=$N$11),INDEX(IPC!$J$5:$J$16,MOD(J46,12)+1)&" de "&INT((J46)/12),"") | C46: =IF(AND(AND($N$5=1,18<=$N$11),$N$10=1),INDEX(IPC!$J$5:$J$16,MOD(L46,12)+1)&" de "&INT((L46)/12),"") | D46: =IF(AND(AND($N$5=1,18<=$N$11),$N$10=1),INDEX(IPC!$J$5:$J$16,MOD(K46,12)+1)&" de "&INT((K46)/12),"") | E46: =IF(NOT(AND($N$5=1,18<=$N$11)),"",IF($N$10=1,IF(AND($N$14=1,K46<=$N$12),INDEX(IPC!$D$5:$D$173,(K46)-IPC!$J$2+1)/INDEX(IPC!$D$5:$D$173,(L46)-IPC!$J$2+1)-1,""),IF(ISNUMBER(F46),F46/100,""))) | G46: =IF(AND(AND($N$5=1,18<=$N$11),ISNUMBER(G45),ISNUMBER(E46)),G45*(1+E46),"") | H46: =IF(NOT(AND($N$5=1,18<=$N$11)),"",IF(ISNUMBER(G46),"Aplicado",IF(ISNUMBER(G45),IF($N$10=1,"Falta el IPC de "&INDEX(IPC!$J$5:$J$16,MOD($N$12+1,12)+1)&" de "&INT(($N$12+1)/12),"Cargá el % de este ajuste en la columna F"),""))) | J46: =IF($N$5=1,$N$7+18*$N$8,"") | K46: =IF($N$5=1,J46-1-$N$9,"") | L46: =IF($N$5=1,K46-$N$8,"")
A47: =IF(AND($N$5=1,19<=$N$11),"19° ajuste","") | B47: =IF(AND($N$5=1,19<=$N$11),INDEX(IPC!$J$5:$J$16,MOD(J47,12)+1)&" de "&INT((J47)/12),"") | C47: =IF(AND(AND($N$5=1,19<=$N$11),$N$10=1),INDEX(IPC!$J$5:$J$16,MOD(L47,12)+1)&" de "&INT((L47)/12),"") | D47: =IF(AND(AND($N$5=1,19<=$N$11),$N$10=1),INDEX(IPC!$J$5:$J$16,MOD(K47,12)+1)&" de "&INT((K47)/12),"") | E47: =IF(NOT(AND($N$5=1,19<=$N$11)),"",IF($N$10=1,IF(AND($N$14=1,K47<=$N$12),INDEX(IPC!$D$5:$D$173,(K47)-IPC!$J$2+1)/INDEX(IPC!$D$5:$D$173,(L47)-IPC!$J$2+1)-1,""),IF(ISNUMBER(F47),F47/100,""))) | G47: =IF(AND(AND($N$5=1,19<=$N$11),ISNUMBER(G46),ISNUMBER(E47)),G46*(1+E47),"") | H47: =IF(NOT(AND($N$5=1,19<=$N$11)),"",IF(ISNUMBER(G47),"Aplicado",IF(ISNUMBER(G46),IF($N$10=1,"Falta el IPC de "&INDEX(IPC!$J$5:$J$16,MOD($N$12+1,12)+1)&" de "&INT(($N$12+1)/12),"Cargá el % de este ajuste en la columna F"),""))) | J47: =IF($N$5=1,$N$7+19*$N$8,"") | K47: =IF($N$5=1,J47-1-$N$9,"") | L47: =IF($N$5=1,K47-$N$8,"")
A48: =IF(AND($N$5=1,20<=$N$11),"20° ajuste","") | B48: =IF(AND($N$5=1,20<=$N$11),INDEX(IPC!$J$5:$J$16,MOD(J48,12)+1)&" de "&INT((J48)/12),"") | C48: =IF(AND(AND($N$5=1,20<=$N$11),$N$10=1),INDEX(IPC!$J$5:$J$16,MOD(L48,12)+1)&" de "&INT((L48)/12),"") | D48: =IF(AND(AND($N$5=1,20<=$N$11),$N$10=1),INDEX(IPC!$J$5:$J$16,MOD(K48,12)+1)&" de "&INT((K48)/12),"") | E48: =IF(NOT(AND($N$5=1,20<=$N$11)),"",IF($N$10=1,IF(AND($N$14=1,K48<=$N$12),INDEX(IPC!$D$5:$D$173,(K48)-IPC!$J$2+1)/INDEX(IPC!$D$5:$D$173,(L48)-IPC!$J$2+1)-1,""),IF(ISNUMBER(F48),F48/100,""))) | G48: =IF(AND(AND($N$5=1,20<=$N$11),ISNUMBER(G47),ISNUMBER(E48)),G47*(1+E48),"") | H48: =IF(NOT(AND($N$5=1,20<=$N$11)),"",IF(ISNUMBER(G48),"Aplicado",IF(ISNUMBER(G47),IF($N$10=1,"Falta el IPC de "&INDEX(IPC!$J$5:$J$16,MOD($N$12+1,12)+1)&" de "&INT(($N$12+1)/12),"Cargá el % de este ajuste en la columna F"),""))) | J48: =IF($N$5=1,$N$7+20*$N$8,"") | K48: =IF($N$5=1,J48-1-$N$9,"") | L48: =IF($N$5=1,K48-$N$8,"")
A49: =IF(AND($N$5=1,21<=$N$11),"21° ajuste","") | B49: =IF(AND($N$5=1,21<=$N$11),INDEX(IPC!$J$5:$J$16,MOD(J49,12)+1)&" de "&INT((J49)/12),"") | C49: =IF(AND(AND($N$5=1,21<=$N$11),$N$10=1),INDEX(IPC!$J$5:$J$16,MOD(L49,12)+1)&" de "&INT((L49)/12),"") | D49: =IF(AND(AND($N$5=1,21<=$N$11),$N$10=1),INDEX(IPC!$J$5:$J$16,MOD(K49,12)+1)&" de "&INT((K49)/12),"") | E49: =IF(NOT(AND($N$5=1,21<=$N$11)),"",IF($N$10=1,IF(AND($N$14=1,K49<=$N$12),INDEX(IPC!$D$5:$D$173,(K49)-IPC!$J$2+1)/INDEX(IPC!$D$5:$D$173,(L49)-IPC!$J$2+1)-1,""),IF(ISNUMBER(F49),F49/100,""))) | G49: =IF(AND(AND($N$5=1,21<=$N$11),ISNUMBER(G48),ISNUMBER(E49)),G48*(1+E49),"") | H49: =IF(NOT(AND($N$5=1,21<=$N$11)),"",IF(ISNUMBER(G49),"Aplicado",IF(ISNUMBER(G48),IF($N$10=1,"Falta el IPC de "&INDEX(IPC!$J$5:$J$16,MOD($N$12+1,12)+1)&" de "&INT(($N$12+1)/12),"Cargá el % de este ajuste en la columna F"),""))) | J49: =IF($N$5=1,$N$7+21*$N$8,"") | K49: =IF($N$5=1,J49-1-$N$9,"") | L49: =IF($N$5=1,K49-$N$8,"")
A50: =IF(AND($N$5=1,22<=$N$11),"22° ajuste","") | B50: =IF(AND($N$5=1,22<=$N$11),INDEX(IPC!$J$5:$J$16,MOD(J50,12)+1)&" de "&INT((J50)/12),"") | C50: =IF(AND(AND($N$5=1,22<=$N$11),$N$10=1),INDEX(IPC!$J$5:$J$16,MOD(L50,12)+1)&" de "&INT((L50)/12),"") | D50: =IF(AND(AND($N$5=1,22<=$N$11),$N$10=1),INDEX(IPC!$J$5:$J$16,MOD(K50,12)+1)&" de "&INT((K50)/12),"") | E50: =IF(NOT(AND($N$5=1,22<=$N$11)),"",IF($N$10=1,IF(AND($N$14=1,K50<=$N$12),INDEX(IPC!$D$5:$D$173,(K50)-IPC!$J$2+1)/INDEX(IPC!$D$5:$D$173,(L50)-IPC!$J$2+1)-1,""),IF(ISNUMBER(F50),F50/100,""))) | G50: =IF(AND(AND($N$5=1,22<=$N$11),ISNUMBER(G49),ISNUMBER(E50)),G49*(1+E50),"") | H50: =IF(NOT(AND($N$5=1,22<=$N$11)),"",IF(ISNUMBER(G50),"Aplicado",IF(ISNUMBER(G49),IF($N$10=1,"Falta el IPC de "&INDEX(IPC!$J$5:$J$16,MOD($N$12+1,12)+1)&" de "&INT(($N$12+1)/12),"Cargá el % de este ajuste en la columna F"),""))) | J50: =IF($N$5=1,$N$7+22*$N$8,"") | K50: =IF($N$5=1,J50-1-$N$9,"") | L50: =IF($N$5=1,K50-$N$8,"")
A51: =IF(AND($N$5=1,23<=$N$11),"23° ajuste","") | B51: =IF(AND($N$5=1,23<=$N$11),INDEX(IPC!$J$5:$J$16,MOD(J51,12)+1)&" de "&INT((J51)/12),"") | C51: =IF(AND(AND($N$5=1,23<=$N$11),$N$10=1),INDEX(IPC!$J$5:$J$16,MOD(L51,12)+1)&" de "&INT((L51)/12),"") | D51: =IF(AND(AND($N$5=1,23<=$N$11),$N$10=1),INDEX(IPC!$J$5:$J$16,MOD(K51,12)+1)&" de "&INT((K51)/12),"") | E51: =IF(NOT(AND($N$5=1,23<=$N$11)),"",IF($N$10=1,IF(AND($N$14=1,K51<=$N$12),INDEX(IPC!$D$5:$D$173,(K51)-IPC!$J$2+1)/INDEX(IPC!$D$5:$D$173,(L51)-IPC!$J$2+1)-1,""),IF(ISNUMBER(F51),F51/100,""))) | G51: =IF(AND(AND($N$5=1,23<=$N$11),ISNUMBER(G50),ISNUMBER(E51)),G50*(1+E51),"") | H51: =IF(NOT(AND($N$5=1,23<=$N$11)),"",IF(ISNUMBER(G51),"Aplicado",IF(ISNUMBER(G50),IF($N$10=1,"Falta el IPC de "&INDEX(IPC!$J$5:$J$16,MOD($N$12+1,12)+1)&" de "&INT(($N$12+1)/12),"Cargá el % de este ajuste en la columna F"),""))) | J51: =IF($N$5=1,$N$7+23*$N$8,"") | K51: =IF($N$5=1,J51-1-$N$9,"") | L51: =IF($N$5=1,K51-$N$8,"")
A52: =IF(AND($N$5=1,24<=$N$11),"24° ajuste","") | B52: =IF(AND($N$5=1,24<=$N$11),INDEX(IPC!$J$5:$J$16,MOD(J52,12)+1)&" de "&INT((J52)/12),"") | C52: =IF(AND(AND($N$5=1,24<=$N$11),$N$10=1),INDEX(IPC!$J$5:$J$16,MOD(L52,12)+1)&" de "&INT((L52)/12),"") | D52: =IF(AND(AND($N$5=1,24<=$N$11),$N$10=1),INDEX(IPC!$J$5:$J$16,MOD(K52,12)+1)&" de "&INT((K52)/12),"") | E52: =IF(NOT(AND($N$5=1,24<=$N$11)),"",IF($N$10=1,IF(AND($N$14=1,K52<=$N$12),INDEX(IPC!$D$5:$D$173,(K52)-IPC!$J$2+1)/INDEX(IPC!$D$5:$D$173,(L52)-IPC!$J$2+1)-1,""),IF(ISNUMBER(F52),F52/100,""))) | G52: =IF(AND(AND($N$5=1,24<=$N$11),ISNUMBER(G51),ISNUMBER(E52)),G51*(1+E52),"") | H52: =IF(NOT(AND($N$5=1,24<=$N$11)),"",IF(ISNUMBER(G52),"Aplicado",IF(ISNUMBER(G51),IF($N$10=1,"Falta el IPC de "&INDEX(IPC!$J$5:$J$16,MOD($N$12+1,12)+1)&" de "&INT(($N$12+1)/12),"Cargá el % de este ajuste en la columna F"),""))) | J52: =IF($N$5=1,$N$7+24*$N$8,"") | K52: =IF($N$5=1,J52-1-$N$9,"") | L52: =IF($N$5=1,K52-$N$8,"")
A53: =IF(AND($N$5=1,25<=$N$11),"25° ajuste","") | B53: =IF(AND($N$5=1,25<=$N$11),INDEX(IPC!$J$5:$J$16,MOD(J53,12)+1)&" de "&INT((J53)/12),"") | C53: =IF(AND(AND($N$5=1,25<=$N$11),$N$10=1),INDEX(IPC!$J$5:$J$16,MOD(L53,12)+1)&" de "&INT((L53)/12),"") | D53: =IF(AND(AND($N$5=1,25<=$N$11),$N$10=1),INDEX(IPC!$J$5:$J$16,MOD(K53,12)+1)&" de "&INT((K53)/12),"") | E53: =IF(NOT(AND($N$5=1,25<=$N$11)),"",IF($N$10=1,IF(AND($N$14=1,K53<=$N$12),INDEX(IPC!$D$5:$D$173,(K53)-IPC!$J$2+1)/INDEX(IPC!$D$5:$D$173,(L53)-IPC!$J$2+1)-1,""),IF(ISNUMBER(F53),F53/100,""))) | G53: =IF(AND(AND($N$5=1,25<=$N$11),ISNUMBER(G52),ISNUMBER(E53)),G52*(1+E53),"") | H53: =IF(NOT(AND($N$5=1,25<=$N$11)),"",IF(ISNUMBER(G53),"Aplicado",IF(ISNUMBER(G52),IF($N$10=1,"Falta el IPC de "&INDEX(IPC!$J$5:$J$16,MOD($N$12+1,12)+1)&" de "&INT(($N$12+1)/12),"Cargá el % de este ajuste en la columna F"),""))) | J53: =IF($N$5=1,$N$7+25*$N$8,"") | K53: =IF($N$5=1,J53-1-$N$9,"") | L53: =IF($N$5=1,K53-$N$8,"")
A54: =IF(AND($N$5=1,26<=$N$11),"26° ajuste","") | B54: =IF(AND($N$5=1,26<=$N$11),INDEX(IPC!$J$5:$J$16,MOD(J54,12)+1)&" de "&INT((J54)/12),"") | C54: =IF(AND(AND($N$5=1,26<=$N$11),$N$10=1),INDEX(IPC!$J$5:$J$16,MOD(L54,12)+1)&" de "&INT((L54)/12),"") | D54: =IF(AND(AND($N$5=1,26<=$N$11),$N$10=1),INDEX(IPC!$J$5:$J$16,MOD(K54,12)+1)&" de "&INT((K54)/12),"") | E54: =IF(NOT(AND($N$5=1,26<=$N$11)),"",IF($N$10=1,IF(AND($N$14=1,K54<=$N$12),INDEX(IPC!$D$5:$D$173,(K54)-IPC!$J$2+1)/INDEX(IPC!$D$5:$D$173,(L54)-IPC!$J$2+1)-1,""),IF(ISNUMBER(F54),F54/100,""))) | G54: =IF(AND(AND($N$5=1,26<=$N$11),ISNUMBER(G53),ISNUMBER(E54)),G53*(1+E54),"") | H54: =IF(NOT(AND($N$5=1,26<=$N$11)),"",IF(ISNUMBER(G54),"Aplicado",IF(ISNUMBER(G53),IF($N$10=1,"Falta el IPC de "&INDEX(IPC!$J$5:$J$16,MOD($N$12+1,12)+1)&" de "&INT(($N$12+1)/12),"Cargá el % de este ajuste en la columna F"),""))) | J54: =IF($N$5=1,$N$7+26*$N$8,"") | K54: =IF($N$5=1,J54-1-$N$9,"") | L54: =IF($N$5=1,K54-$N$8,"")
A55: =IF(AND($N$5=1,27<=$N$11),"27° ajuste","") | B55: =IF(AND($N$5=1,27<=$N$11),INDEX(IPC!$J$5:$J$16,MOD(J55,12)+1)&" de "&INT((J55)/12),"") | C55: =IF(AND(AND($N$5=1,27<=$N$11),$N$10=1),INDEX(IPC!$J$5:$J$16,MOD(L55,12)+1)&" de "&INT((L55)/12),"") | D55: =IF(AND(AND($N$5=1,27<=$N$11),$N$10=1),INDEX(IPC!$J$5:$J$16,MOD(K55,12)+1)&" de "&INT((K55)/12),"") | E55: =IF(NOT(AND($N$5=1,27<=$N$11)),"",IF($N$10=1,IF(AND($N$14=1,K55<=$N$12),INDEX(IPC!$D$5:$D$173,(K55)-IPC!$J$2+1)/INDEX(IPC!$D$5:$D$173,(L55)-IPC!$J$2+1)-1,""),IF(ISNUMBER(F55),F55/100,""))) | G55: =IF(AND(AND($N$5=1,27<=$N$11),ISNUMBER(G54),ISNUMBER(E55)),G54*(1+E55),"") | H55: =IF(NOT(AND($N$5=1,27<=$N$11)),"",IF(ISNUMBER(G55),"Aplicado",IF(ISNUMBER(G54),IF($N$10=1,"Falta el IPC de "&INDEX(IPC!$J$5:$J$16,MOD($N$12+1,12)+1)&" de "&INT(($N$12+1)/12),"Cargá el % de este ajuste en la columna F"),""))) | J55: =IF($N$5=1,$N$7+27*$N$8,"") | K55: =IF($N$5=1,J55-1-$N$9,"") | L55: =IF($N$5=1,K55-$N$8,"")
A56: =IF(AND($N$5=1,28<=$N$11),"28° ajuste","") | B56: =IF(AND($N$5=1,28<=$N$11),INDEX(IPC!$J$5:$J$16,MOD(J56,12)+1)&" de "&INT((J56)/12),"") | C56: =IF(AND(AND($N$5=1,28<=$N$11),$N$10=1),INDEX(IPC!$J$5:$J$16,MOD(L56,12)+1)&" de "&INT((L56)/12),"") | D56: =IF(AND(AND($N$5=1,28<=$N$11),$N$10=1),INDEX(IPC!$J$5:$J$16,MOD(K56,12)+1)&" de "&INT((K56)/12),"") | E56: =IF(NOT(AND($N$5=1,28<=$N$11)),"",IF($N$10=1,IF(AND($N$14=1,K56<=$N$12),INDEX(IPC!$D$5:$D$173,(K56)-IPC!$J$2+1)/INDEX(IPC!$D$5:$D$173,(L56)-IPC!$J$2+1)-1,""),IF(ISNUMBER(F56),F56/100,""))) | G56: =IF(AND(AND($N$5=1,28<=$N$11),ISNUMBER(G55),ISNUMBER(E56)),G55*(1+E56),"") | H56: =IF(NOT(AND($N$5=1,28<=$N$11)),"",IF(ISNUMBER(G56),"Aplicado",IF(ISNUMBER(G55),IF($N$10=1,"Falta el IPC de "&INDEX(IPC!$J$5:$J$16,MOD($N$12+1,12)+1)&" de "&INT(($N$12+1)/12),"Cargá el % de este ajuste en la columna F"),""))) | J56: =IF($N$5=1,$N$7+28*$N$8,"") | K56: =IF($N$5=1,J56-1-$N$9,"") | L56: =IF($N$5=1,K56-$N$8,"")
A57: =IF(AND($N$5=1,29<=$N$11),"29° ajuste","") | B57: =IF(AND($N$5=1,29<=$N$11),INDEX(IPC!$J$5:$J$16,MOD(J57,12)+1)&" de "&INT((J57)/12),"") | C57: =IF(AND(AND($N$5=1,29<=$N$11),$N$10=1),INDEX(IPC!$J$5:$J$16,MOD(L57,12)+1)&" de "&INT((L57)/12),"") | D57: =IF(AND(AND($N$5=1,29<=$N$11),$N$10=1),INDEX(IPC!$J$5:$J$16,MOD(K57,12)+1)&" de "&INT((K57)/12),"") | E57: =IF(NOT(AND($N$5=1,29<=$N$11)),"",IF($N$10=1,IF(AND($N$14=1,K57<=$N$12),INDEX(IPC!$D$5:$D$173,(K57)-IPC!$J$2+1)/INDEX(IPC!$D$5:$D$173,(L57)-IPC!$J$2+1)-1,""),IF(ISNUMBER(F57),F57/100,""))) | G57: =IF(AND(AND($N$5=1,29<=$N$11),ISNUMBER(G56),ISNUMBER(E57)),G56*(1+E57),"") | H57: =IF(NOT(AND($N$5=1,29<=$N$11)),"",IF(ISNUMBER(G57),"Aplicado",IF(ISNUMBER(G56),IF($N$10=1,"Falta el IPC de "&INDEX(IPC!$J$5:$J$16,MOD($N$12+1,12)+1)&" de "&INT(($N$12+1)/12),"Cargá el % de este ajuste en la columna F"),""))) | J57: =IF($N$5=1,$N$7+29*$N$8,"") | K57: =IF($N$5=1,J57-1-$N$9,"") | L57: =IF($N$5=1,K57-$N$8,"")
A58: =IF(AND($N$5=1,30<=$N$11),"30° ajuste","") | B58: =IF(AND($N$5=1,30<=$N$11),INDEX(IPC!$J$5:$J$16,MOD(J58,12)+1)&" de "&INT((J58)/12),"") | C58: =IF(AND(AND($N$5=1,30<=$N$11),$N$10=1),INDEX(IPC!$J$5:$J$16,MOD(L58,12)+1)&" de "&INT((L58)/12),"") | D58: =IF(AND(AND($N$5=1,30<=$N$11),$N$10=1),INDEX(IPC!$J$5:$J$16,MOD(K58,12)+1)&" de "&INT((K58)/12),"") | E58: =IF(NOT(AND($N$5=1,30<=$N$11)),"",IF($N$10=1,IF(AND($N$14=1,K58<=$N$12),INDEX(IPC!$D$5:$D$173,(K58)-IPC!$J$2+1)/INDEX(IPC!$D$5:$D$173,(L58)-IPC!$J$2+1)-1,""),IF(ISNUMBER(F58),F58/100,""))) | G58: =IF(AND(AND($N$5=1,30<=$N$11),ISNUMBER(G57),ISNUMBER(E58)),G57*(1+E58),"") | H58: =IF(NOT(AND($N$5=1,30<=$N$11)),"",IF(ISNUMBER(G58),"Aplicado",IF(ISNUMBER(G57),IF($N$10=1,"Falta el IPC de "&INDEX(IPC!$J$5:$J$16,MOD($N$12+1,12)+1)&" de "&INT(($N$12+1)/12),"Cargá el % de este ajuste en la columna F"),""))) | J58: =IF($N$5=1,$N$7+30*$N$8,"") | K58: =IF($N$5=1,J58-1-$N$9,"") | L58: =IF($N$5=1,K58-$N$8,"")
A59: =IF(AND($N$5=1,31<=$N$11),"31° ajuste","") | B59: =IF(AND($N$5=1,31<=$N$11),INDEX(IPC!$J$5:$J$16,MOD(J59,12)+1)&" de "&INT((J59)/12),"") | C59: =IF(AND(AND($N$5=1,31<=$N$11),$N$10=1),INDEX(IPC!$J$5:$J$16,MOD(L59,12)+1)&" de "&INT((L59)/12),"") | D59: =IF(AND(AND($N$5=1,31<=$N$11),$N$10=1),INDEX(IPC!$J$5:$J$16,MOD(K59,12)+1)&" de "&INT((K59)/12),"") | E59: =IF(NOT(AND($N$5=1,31<=$N$11)),"",IF($N$10=1,IF(AND($N$14=1,K59<=$N$12),INDEX(IPC!$D$5:$D$173,(K59)-IPC!$J$2+1)/INDEX(IPC!$D$5:$D$173,(L59)-IPC!$J$2+1)-1,""),IF(ISNUMBER(F59),F59/100,""))) | G59: =IF(AND(AND($N$5=1,31<=$N$11),ISNUMBER(G58),ISNUMBER(E59)),G58*(1+E59),"") | H59: =IF(NOT(AND($N$5=1,31<=$N$11)),"",IF(ISNUMBER(G59),"Aplicado",IF(ISNUMBER(G58),IF($N$10=1,"Falta el IPC de "&INDEX(IPC!$J$5:$J$16,MOD($N$12+1,12)+1)&" de "&INT(($N$12+1)/12),"Cargá el % de este ajuste en la columna F"),""))) | J59: =IF($N$5=1,$N$7+31*$N$8,"") | K59: =IF($N$5=1,J59-1-$N$9,"") | L59: =IF($N$5=1,K59-$N$8,"")
A60: =IF(AND($N$5=1,32<=$N$11),"32° ajuste","") | B60: =IF(AND($N$5=1,32<=$N$11),INDEX(IPC!$J$5:$J$16,MOD(J60,12)+1)&" de "&INT((J60)/12),"") | C60: =IF(AND(AND($N$5=1,32<=$N$11),$N$10=1),INDEX(IPC!$J$5:$J$16,MOD(L60,12)+1)&" de "&INT((L60)/12),"") | D60: =IF(AND(AND($N$5=1,32<=$N$11),$N$10=1),INDEX(IPC!$J$5:$J$16,MOD(K60,12)+1)&" de "&INT((K60)/12),"") | E60: =IF(NOT(AND($N$5=1,32<=$N$11)),"",IF($N$10=1,IF(AND($N$14=1,K60<=$N$12),INDEX(IPC!$D$5:$D$173,(K60)-IPC!$J$2+1)/INDEX(IPC!$D$5:$D$173,(L60)-IPC!$J$2+1)-1,""),IF(ISNUMBER(F60),F60/100,""))) | G60: =IF(AND(AND($N$5=1,32<=$N$11),ISNUMBER(G59),ISNUMBER(E60)),G59*(1+E60),"") | H60: =IF(NOT(AND($N$5=1,32<=$N$11)),"",IF(ISNUMBER(G60),"Aplicado",IF(ISNUMBER(G59),IF($N$10=1,"Falta el IPC de "&INDEX(IPC!$J$5:$J$16,MOD($N$12+1,12)+1)&" de "&INT(($N$12+1)/12),"Cargá el % de este ajuste en la columna F"),""))) | J60: =IF($N$5=1,$N$7+32*$N$8,"") | K60: =IF($N$5=1,J60-1-$N$9,"") | L60: =IF($N$5=1,K60-$N$8,"")
A61: =IF(AND($N$5=1,33<=$N$11),"33° ajuste","") | B61: =IF(AND($N$5=1,33<=$N$11),INDEX(IPC!$J$5:$J$16,MOD(J61,12)+1)&" de "&INT((J61)/12),"") | C61: =IF(AND(AND($N$5=1,33<=$N$11),$N$10=1),INDEX(IPC!$J$5:$J$16,MOD(L61,12)+1)&" de "&INT((L61)/12),"") | D61: =IF(AND(AND($N$5=1,33<=$N$11),$N$10=1),INDEX(IPC!$J$5:$J$16,MOD(K61,12)+1)&" de "&INT((K61)/12),"") | E61: =IF(NOT(AND($N$5=1,33<=$N$11)),"",IF($N$10=1,IF(AND($N$14=1,K61<=$N$12),INDEX(IPC!$D$5:$D$173,(K61)-IPC!$J$2+1)/INDEX(IPC!$D$5:$D$173,(L61)-IPC!$J$2+1)-1,""),IF(ISNUMBER(F61),F61/100,""))) | G61: =IF(AND(AND($N$5=1,33<=$N$11),ISNUMBER(G60),ISNUMBER(E61)),G60*(1+E61),"") | H61: =IF(NOT(AND($N$5=1,33<=$N$11)),"",IF(ISNUMBER(G61),"Aplicado",IF(ISNUMBER(G60),IF($N$10=1,"Falta el IPC de "&INDEX(IPC!$J$5:$J$16,MOD($N$12+1,12)+1)&" de "&INT(($N$12+1)/12),"Cargá el % de este ajuste en la columna F"),""))) | J61: =IF($N$5=1,$N$7+33*$N$8,"") | K61: =IF($N$5=1,J61-1-$N$9,"") | L61: =IF($N$5=1,K61-$N$8,"")
A62: =IF(AND($N$5=1,34<=$N$11),"34° ajuste","") | B62: =IF(AND($N$5=1,34<=$N$11),INDEX(IPC!$J$5:$J$16,MOD(J62,12)+1)&" de "&INT((J62)/12),"") | C62: =IF(AND(AND($N$5=1,34<=$N$11),$N$10=1),INDEX(IPC!$J$5:$J$16,MOD(L62,12)+1)&" de "&INT((L62)/12),"") | D62: =IF(AND(AND($N$5=1,34<=$N$11),$N$10=1),INDEX(IPC!$J$5:$J$16,MOD(K62,12)+1)&" de "&INT((K62)/12),"") | E62: =IF(NOT(AND($N$5=1,34<=$N$11)),"",IF($N$10=1,IF(AND($N$14=1,K62<=$N$12),INDEX(IPC!$D$5:$D$173,(K62)-IPC!$J$2+1)/INDEX(IPC!$D$5:$D$173,(L62)-IPC!$J$2+1)-1,""),IF(ISNUMBER(F62),F62/100,""))) | G62: =IF(AND(AND($N$5=1,34<=$N$11),ISNUMBER(G61),ISNUMBER(E62)),G61*(1+E62),"") | H62: =IF(NOT(AND($N$5=1,34<=$N$11)),"",IF(ISNUMBER(G62),"Aplicado",IF(ISNUMBER(G61),IF($N$10=1,"Falta el IPC de "&INDEX(IPC!$J$5:$J$16,MOD($N$12+1,12)+1)&" de "&INT(($N$12+1)/12),"Cargá el % de este ajuste en la columna F"),""))) | J62: =IF($N$5=1,$N$7+34*$N$8,"") | K62: =IF($N$5=1,J62-1-$N$9,"") | L62: =IF($N$5=1,K62-$N$8,"")
A63: =IF(AND($N$5=1,35<=$N$11),"35° ajuste","") | B63: =IF(AND($N$5=1,35<=$N$11),INDEX(IPC!$J$5:$J$16,MOD(J63,12)+1)&" de "&INT((J63)/12),"") | C63: =IF(AND(AND($N$5=1,35<=$N$11),$N$10=1),INDEX(IPC!$J$5:$J$16,MOD(L63,12)+1)&" de "&INT((L63)/12),"") | D63: =IF(AND(AND($N$5=1,35<=$N$11),$N$10=1),INDEX(IPC!$J$5:$J$16,MOD(K63,12)+1)&" de "&INT((K63)/12),"") | E63: =IF(NOT(AND($N$5=1,35<=$N$11)),"",IF($N$10=1,IF(AND($N$14=1,K63<=$N$12),INDEX(IPC!$D$5:$D$173,(K63)-IPC!$J$2+1)/INDEX(IPC!$D$5:$D$173,(L63)-IPC!$J$2+1)-1,""),IF(ISNUMBER(F63),F63/100,""))) | G63: =IF(AND(AND($N$5=1,35<=$N$11),ISNUMBER(G62),ISNUMBER(E63)),G62*(1+E63),"") | H63: =IF(NOT(AND($N$5=1,35<=$N$11)),"",IF(ISNUMBER(G63),"Aplicado",IF(ISNUMBER(G62),IF($N$10=1,"Falta el IPC de "&INDEX(IPC!$J$5:$J$16,MOD($N$12+1,12)+1)&" de "&INT(($N$12+1)/12),"Cargá el % de este ajuste en la columna F"),""))) | J63: =IF($N$5=1,$N$7+35*$N$8,"") | K63: =IF($N$5=1,J63-1-$N$9,"") | L63: =IF($N$5=1,K63-$N$8,"")
A64: =IF(AND($N$5=1,36<=$N$11),"36° ajuste","") | B64: =IF(AND($N$5=1,36<=$N$11),INDEX(IPC!$J$5:$J$16,MOD(J64,12)+1)&" de "&INT((J64)/12),"") | C64: =IF(AND(AND($N$5=1,36<=$N$11),$N$10=1),INDEX(IPC!$J$5:$J$16,MOD(L64,12)+1)&" de "&INT((L64)/12),"") | D64: =IF(AND(AND($N$5=1,36<=$N$11),$N$10=1),INDEX(IPC!$J$5:$J$16,MOD(K64,12)+1)&" de "&INT((K64)/12),"") | E64: =IF(NOT(AND($N$5=1,36<=$N$11)),"",IF($N$10=1,IF(AND($N$14=1,K64<=$N$12),INDEX(IPC!$D$5:$D$173,(K64)-IPC!$J$2+1)/INDEX(IPC!$D$5:$D$173,(L64)-IPC!$J$2+1)-1,""),IF(ISNUMBER(F64),F64/100,""))) | G64: =IF(AND(AND($N$5=1,36<=$N$11),ISNUMBER(G63),ISNUMBER(E64)),G63*(1+E64),"") | H64: =IF(NOT(AND($N$5=1,36<=$N$11)),"",IF(ISNUMBER(G64),"Aplicado",IF(ISNUMBER(G63),IF($N$10=1,"Falta el IPC de "&INDEX(IPC!$J$5:$J$16,MOD($N$12+1,12)+1)&" de "&INT(($N$12+1)/12),"Cargá el % de este ajuste en la columna F"),""))) | J64: =IF($N$5=1,$N$7+36*$N$8,"") | K64: =IF($N$5=1,J64-1-$N$9,"") | L64: =IF($N$5=1,K64-$N$8,"")
A65: =IF(AND($N$5=1,37<=$N$11),"37° ajuste","") | B65: =IF(AND($N$5=1,37<=$N$11),INDEX(IPC!$J$5:$J$16,MOD(J65,12)+1)&" de "&INT((J65)/12),"") | C65: =IF(AND(AND($N$5=1,37<=$N$11),$N$10=1),INDEX(IPC!$J$5:$J$16,MOD(L65,12)+1)&" de "&INT((L65)/12),"") | D65: =IF(AND(AND($N$5=1,37<=$N$11),$N$10=1),INDEX(IPC!$J$5:$J$16,MOD(K65,12)+1)&" de "&INT((K65)/12),"") | E65: =IF(NOT(AND($N$5=1,37<=$N$11)),"",IF($N$10=1,IF(AND($N$14=1,K65<=$N$12),INDEX(IPC!$D$5:$D$173,(K65)-IPC!$J$2+1)/INDEX(IPC!$D$5:$D$173,(L65)-IPC!$J$2+1)-1,""),IF(ISNUMBER(F65),F65/100,""))) | G65: =IF(AND(AND($N$5=1,37<=$N$11),ISNUMBER(G64),ISNUMBER(E65)),G64*(1+E65),"") | H65: =IF(NOT(AND($N$5=1,37<=$N$11)),"",IF(ISNUMBER(G65),"Aplicado",IF(ISNUMBER(G64),IF($N$10=1,"Falta el IPC de "&INDEX(IPC!$J$5:$J$16,MOD($N$12+1,12)+1)&" de "&INT(($N$12+1)/12),"Cargá el % de este ajuste en la columna F"),""))) | J65: =IF($N$5=1,$N$7+37*$N$8,"") | K65: =IF($N$5=1,J65-1-$N$9,"") | L65: =IF($N$5=1,K65-$N$8,"")
A66: =IF(AND($N$5=1,38<=$N$11),"38° ajuste","") | B66: =IF(AND($N$5=1,38<=$N$11),INDEX(IPC!$J$5:$J$16,MOD(J66,12)+1)&" de "&INT((J66)/12),"") | C66: =IF(AND(AND($N$5=1,38<=$N$11),$N$10=1),INDEX(IPC!$J$5:$J$16,MOD(L66,12)+1)&" de "&INT((L66)/12),"") | D66: =IF(AND(AND($N$5=1,38<=$N$11),$N$10=1),INDEX(IPC!$J$5:$J$16,MOD(K66,12)+1)&" de "&INT((K66)/12),"") | E66: =IF(NOT(AND($N$5=1,38<=$N$11)),"",IF($N$10=1,IF(AND($N$14=1,K66<=$N$12),INDEX(IPC!$D$5:$D$173,(K66)-IPC!$J$2+1)/INDEX(IPC!$D$5:$D$173,(L66)-IPC!$J$2+1)-1,""),IF(ISNUMBER(F66),F66/100,""))) | G66: =IF(AND(AND($N$5=1,38<=$N$11),ISNUMBER(G65),ISNUMBER(E66)),G65*(1+E66),"") | H66: =IF(NOT(AND($N$5=1,38<=$N$11)),"",IF(ISNUMBER(G66),"Aplicado",IF(ISNUMBER(G65),IF($N$10=1,"Falta el IPC de "&INDEX(IPC!$J$5:$J$16,MOD($N$12+1,12)+1)&" de "&INT(($N$12+1)/12),"Cargá el % de este ajuste en la columna F"),""))) | J66: =IF($N$5=1,$N$7+38*$N$8,"") | K66: =IF($N$5=1,J66-1-$N$9,"") | L66: =IF($N$5=1,K66-$N$8,"")
A67: =IF(AND($N$5=1,39<=$N$11),"39° ajuste","") | B67: =IF(AND($N$5=1,39<=$N$11),INDEX(IPC!$J$5:$J$16,MOD(J67,12)+1)&" de "&INT((J67)/12),"") | C67: =IF(AND(AND($N$5=1,39<=$N$11),$N$10=1),INDEX(IPC!$J$5:$J$16,MOD(L67,12)+1)&" de "&INT((L67)/12),"") | D67: =IF(AND(AND($N$5=1,39<=$N$11),$N$10=1),INDEX(IPC!$J$5:$J$16,MOD(K67,12)+1)&" de "&INT((K67)/12),"") | E67: =IF(NOT(AND($N$5=1,39<=$N$11)),"",IF($N$10=1,IF(AND($N$14=1,K67<=$N$12),INDEX(IPC!$D$5:$D$173,(K67)-IPC!$J$2+1)/INDEX(IPC!$D$5:$D$173,(L67)-IPC!$J$2+1)-1,""),IF(ISNUMBER(F67),F67/100,""))) | G67: =IF(AND(AND($N$5=1,39<=$N$11),ISNUMBER(G66),ISNUMBER(E67)),G66*(1+E67),"") | H67: =IF(NOT(AND($N$5=1,39<=$N$11)),"",IF(ISNUMBER(G67),"Aplicado",IF(ISNUMBER(G66),IF($N$10=1,"Falta el IPC de "&INDEX(IPC!$J$5:$J$16,MOD($N$12+1,12)+1)&" de "&INT(($N$12+1)/12),"Cargá el % de este ajuste en la columna F"),""))) | J67: =IF($N$5=1,$N$7+39*$N$8,"") | K67: =IF($N$5=1,J67-1-$N$9,"") | L67: =IF($N$5=1,K67-$N$8,"")
A68: =IF(AND($N$5=1,40<=$N$11),"40° ajuste","") | B68: =IF(AND($N$5=1,40<=$N$11),INDEX(IPC!$J$5:$J$16,MOD(J68,12)+1)&" de "&INT((J68)/12),"") | C68: =IF(AND(AND($N$5=1,40<=$N$11),$N$10=1),INDEX(IPC!$J$5:$J$16,MOD(L68,12)+1)&" de "&INT((L68)/12),"") | D68: =IF(AND(AND($N$5=1,40<=$N$11),$N$10=1),INDEX(IPC!$J$5:$J$16,MOD(K68,12)+1)&" de "&INT((K68)/12),"") | E68: =IF(NOT(AND($N$5=1,40<=$N$11)),"",IF($N$10=1,IF(AND($N$14=1,K68<=$N$12),INDEX(IPC!$D$5:$D$173,(K68)-IPC!$J$2+1)/INDEX(IPC!$D$5:$D$173,(L68)-IPC!$J$2+1)-1,""),IF(ISNUMBER(F68),F68/100,""))) | G68: =IF(AND(AND($N$5=1,40<=$N$11),ISNUMBER(G67),ISNUMBER(E68)),G67*(1+E68),"") | H68: =IF(NOT(AND($N$5=1,40<=$N$11)),"",IF(ISNUMBER(G68),"Aplicado",IF(ISNUMBER(G67),IF($N$10=1,"Falta el IPC de "&INDEX(IPC!$J$5:$J$16,MOD($N$12+1,12)+1)&" de "&INT(($N$12+1)/12),"Cargá el % de este ajuste en la columna F"),""))) | J68: =IF($N$5=1,$N$7+40*$N$8,"") | K68: =IF($N$5=1,J68-1-$N$9,"") | L68: =IF($N$5=1,K68-$N$8,"")
A69: =IF(AND($N$5=1,41<=$N$11),"41° ajuste","") | B69: =IF(AND($N$5=1,41<=$N$11),INDEX(IPC!$J$5:$J$16,MOD(J69,12)+1)&" de "&INT((J69)/12),"") | C69: =IF(AND(AND($N$5=1,41<=$N$11),$N$10=1),INDEX(IPC!$J$5:$J$16,MOD(L69,12)+1)&" de "&INT((L69)/12),"") | D69: =IF(AND(AND($N$5=1,41<=$N$11),$N$10=1),INDEX(IPC!$J$5:$J$16,MOD(K69,12)+1)&" de "&INT((K69)/12),"") | E69: =IF(NOT(AND($N$5=1,41<=$N$11)),"",IF($N$10=1,IF(AND($N$14=1,K69<=$N$12),INDEX(IPC!$D$5:$D$173,(K69)-IPC!$J$2+1)/INDEX(IPC!$D$5:$D$173,(L69)-IPC!$J$2+1)-1,""),IF(ISNUMBER(F69),F69/100,""))) | G69: =IF(AND(AND($N$5=1,41<=$N$11),ISNUMBER(G68),ISNUMBER(E69)),G68*(1+E69),"") | H69: =IF(NOT(AND($N$5=1,41<=$N$11)),"",IF(ISNUMBER(G69),"Aplicado",IF(ISNUMBER(G68),IF($N$10=1,"Falta el IPC de "&INDEX(IPC!$J$5:$J$16,MOD($N$12+1,12)+1)&" de "&INT(($N$12+1)/12),"Cargá el % de este ajuste en la columna F"),""))) | J69: =IF($N$5=1,$N$7+41*$N$8,"") | K69: =IF($N$5=1,J69-1-$N$9,"") | L69: =IF($N$5=1,K69-$N$8,"")
A70: =IF(AND($N$5=1,42<=$N$11),"42° ajuste","") | B70: =IF(AND($N$5=1,42<=$N$11),INDEX(IPC!$J$5:$J$16,MOD(J70,12)+1)&" de "&INT((J70)/12),"") | C70: =IF(AND(AND($N$5=1,42<=$N$11),$N$10=1),INDEX(IPC!$J$5:$J$16,MOD(L70,12)+1)&" de "&INT((L70)/12),"") | D70: =IF(AND(AND($N$5=1,42<=$N$11),$N$10=1),INDEX(IPC!$J$5:$J$16,MOD(K70,12)+1)&" de "&INT((K70)/12),"") | E70: =IF(NOT(AND($N$5=1,42<=$N$11)),"",IF($N$10=1,IF(AND($N$14=1,K70<=$N$12),INDEX(IPC!$D$5:$D$173,(K70)-IPC!$J$2+1)/INDEX(IPC!$D$5:$D$173,(L70)-IPC!$J$2+1)-1,""),IF(ISNUMBER(F70),F70/100,""))) | G70: =IF(AND(AND($N$5=1,42<=$N$11),ISNUMBER(G69),ISNUMBER(E70)),G69*(1+E70),"") | H70: =IF(NOT(AND($N$5=1,42<=$N$11)),"",IF(ISNUMBER(G70),"Aplicado",IF(ISNUMBER(G69),IF($N$10=1,"Falta el IPC de "&INDEX(IPC!$J$5:$J$16,MOD($N$12+1,12)+1)&" de "&INT(($N$12+1)/12),"Cargá el % de este ajuste en la columna F"),""))) | J70: =IF($N$5=1,$N$7+42*$N$8,"") | K70: =IF($N$5=1,J70-1-$N$9,"") | L70: =IF($N$5=1,K70-$N$8,"")
A71: =IF(AND($N$5=1,43<=$N$11),"43° ajuste","") | B71: =IF(AND($N$5=1,43<=$N$11),INDEX(IPC!$J$5:$J$16,MOD(J71,12)+1)&" de "&INT((J71)/12),"") | C71: =IF(AND(AND($N$5=1,43<=$N$11),$N$10=1),INDEX(IPC!$J$5:$J$16,MOD(L71,12)+1)&" de "&INT((L71)/12),"") | D71: =IF(AND(AND($N$5=1,43<=$N$11),$N$10=1),INDEX(IPC!$J$5:$J$16,MOD(K71,12)+1)&" de "&INT((K71)/12),"") | E71: =IF(NOT(AND($N$5=1,43<=$N$11)),"",IF($N$10=1,IF(AND($N$14=1,K71<=$N$12),INDEX(IPC!$D$5:$D$173,(K71)-IPC!$J$2+1)/INDEX(IPC!$D$5:$D$173,(L71)-IPC!$J$2+1)-1,""),IF(ISNUMBER(F71),F71/100,""))) | G71: =IF(AND(AND($N$5=1,43<=$N$11),ISNUMBER(G70),ISNUMBER(E71)),G70*(1+E71),"") | H71: =IF(NOT(AND($N$5=1,43<=$N$11)),"",IF(ISNUMBER(G71),"Aplicado",IF(ISNUMBER(G70),IF($N$10=1,"Falta el IPC de "&INDEX(IPC!$J$5:$J$16,MOD($N$12+1,12)+1)&" de "&INT(($N$12+1)/12),"Cargá el % de este ajuste en la columna F"),""))) | J71: =IF($N$5=1,$N$7+43*$N$8,"") | K71: =IF($N$5=1,J71-1-$N$9,"") | L71: =IF($N$5=1,K71-$N$8,"")
A72: =IF(AND($N$5=1,44<=$N$11),"44° ajuste","") | B72: =IF(AND($N$5=1,44<=$N$11),INDEX(IPC!$J$5:$J$16,MOD(J72,12)+1)&" de "&INT((J72)/12),"") | C72: =IF(AND(AND($N$5=1,44<=$N$11),$N$10=1),INDEX(IPC!$J$5:$J$16,MOD(L72,12)+1)&" de "&INT((L72)/12),"") | D72: =IF(AND(AND($N$5=1,44<=$N$11),$N$10=1),INDEX(IPC!$J$5:$J$16,MOD(K72,12)+1)&" de "&INT((K72)/12),"") | E72: =IF(NOT(AND($N$5=1,44<=$N$11)),"",IF($N$10=1,IF(AND($N$14=1,K72<=$N$12),INDEX(IPC!$D$5:$D$173,(K72)-IPC!$J$2+1)/INDEX(IPC!$D$5:$D$173,(L72)-IPC!$J$2+1)-1,""),IF(ISNUMBER(F72),F72/100,""))) | G72: =IF(AND(AND($N$5=1,44<=$N$11),ISNUMBER(G71),ISNUMBER(E72)),G71*(1+E72),"") | H72: =IF(NOT(AND($N$5=1,44<=$N$11)),"",IF(ISNUMBER(G72),"Aplicado",IF(ISNUMBER(G71),IF($N$10=1,"Falta el IPC de "&INDEX(IPC!$J$5:$J$16,MOD($N$12+1,12)+1)&" de "&INT(($N$12+1)/12),"Cargá el % de este ajuste en la columna F"),""))) | J72: =IF($N$5=1,$N$7+44*$N$8,"") | K72: =IF($N$5=1,J72-1-$N$9,"") | L72: =IF($N$5=1,K72-$N$8,"")
A73: =IF(AND($N$5=1,45<=$N$11),"45° ajuste","") | B73: =IF(AND($N$5=1,45<=$N$11),INDEX(IPC!$J$5:$J$16,MOD(J73,12)+1)&" de "&INT((J73)/12),"") | C73: =IF(AND(AND($N$5=1,45<=$N$11),$N$10=1),INDEX(IPC!$J$5:$J$16,MOD(L73,12)+1)&" de "&INT((L73)/12),"") | D73: =IF(AND(AND($N$5=1,45<=$N$11),$N$10=1),INDEX(IPC!$J$5:$J$16,MOD(K73,12)+1)&" de "&INT((K73)/12),"") | E73: =IF(NOT(AND($N$5=1,45<=$N$11)),"",IF($N$10=1,IF(AND($N$14=1,K73<=$N$12),INDEX(IPC!$D$5:$D$173,(K73)-IPC!$J$2+1)/INDEX(IPC!$D$5:$D$173,(L73)-IPC!$J$2+1)-1,""),IF(ISNUMBER(F73),F73/100,""))) | G73: =IF(AND(AND($N$5=1,45<=$N$11),ISNUMBER(G72),ISNUMBER(E73)),G72*(1+E73),"") | H73: =IF(NOT(AND($N$5=1,45<=$N$11)),"",IF(ISNUMBER(G73),"Aplicado",IF(ISNUMBER(G72),IF($N$10=1,"Falta el IPC de "&INDEX(IPC!$J$5:$J$16,MOD($N$12+1,12)+1)&" de "&INT(($N$12+1)/12),"Cargá el % de este ajuste en la columna F"),""))) | J73: =IF($N$5=1,$N$7+45*$N$8,"") | K73: =IF($N$5=1,J73-1-$N$9,"") | L73: =IF($N$5=1,K73-$N$8,"")
A74: =IF(AND($N$5=1,46<=$N$11),"46° ajuste","") | B74: =IF(AND($N$5=1,46<=$N$11),INDEX(IPC!$J$5:$J$16,MOD(J74,12)+1)&" de "&INT((J74)/12),"") | C74: =IF(AND(AND($N$5=1,46<=$N$11),$N$10=1),INDEX(IPC!$J$5:$J$16,MOD(L74,12)+1)&" de "&INT((L74)/12),"") | D74: =IF(AND(AND($N$5=1,46<=$N$11),$N$10=1),INDEX(IPC!$J$5:$J$16,MOD(K74,12)+1)&" de "&INT((K74)/12),"") | E74: =IF(NOT(AND($N$5=1,46<=$N$11)),"",IF($N$10=1,IF(AND($N$14=1,K74<=$N$12),INDEX(IPC!$D$5:$D$173,(K74)-IPC!$J$2+1)/INDEX(IPC!$D$5:$D$173,(L74)-IPC!$J$2+1)-1,""),IF(ISNUMBER(F74),F74/100,""))) | G74: =IF(AND(AND($N$5=1,46<=$N$11),ISNUMBER(G73),ISNUMBER(E74)),G73*(1+E74),"") | H74: =IF(NOT(AND($N$5=1,46<=$N$11)),"",IF(ISNUMBER(G74),"Aplicado",IF(ISNUMBER(G73),IF($N$10=1,"Falta el IPC de "&INDEX(IPC!$J$5:$J$16,MOD($N$12+1,12)+1)&" de "&INT(($N$12+1)/12),"Cargá el % de este ajuste en la columna F"),""))) | J74: =IF($N$5=1,$N$7+46*$N$8,"") | K74: =IF($N$5=1,J74-1-$N$9,"") | L74: =IF($N$5=1,K74-$N$8,"")
A75: =IF(AND($N$5=1,47<=$N$11),"47° ajuste","") | B75: =IF(AND($N$5=1,47<=$N$11),INDEX(IPC!$J$5:$J$16,MOD(J75,12)+1)&" de "&INT((J75)/12),"") | C75: =IF(AND(AND($N$5=1,47<=$N$11),$N$10=1),INDEX(IPC!$J$5:$J$16,MOD(L75,12)+1)&" de "&INT((L75)/12),"") | D75: =IF(AND(AND($N$5=1,47<=$N$11),$N$10=1),INDEX(IPC!$J$5:$J$16,MOD(K75,12)+1)&" de "&INT((K75)/12),"") | E75: =IF(NOT(AND($N$5=1,47<=$N$11)),"",IF($N$10=1,IF(AND($N$14=1,K75<=$N$12),INDEX(IPC!$D$5:$D$173,(K75)-IPC!$J$2+1)/INDEX(IPC!$D$5:$D$173,(L75)-IPC!$J$2+1)-1,""),IF(ISNUMBER(F75),F75/100,""))) | G75: =IF(AND(AND($N$5=1,47<=$N$11),ISNUMBER(G74),ISNUMBER(E75)),G74*(1+E75),"") | H75: =IF(NOT(AND($N$5=1,47<=$N$11)),"",IF(ISNUMBER(G75),"Aplicado",IF(ISNUMBER(G74),IF($N$10=1,"Falta el IPC de "&INDEX(IPC!$J$5:$J$16,MOD($N$12+1,12)+1)&" de "&INT(($N$12+1)/12),"Cargá el % de este ajuste en la columna F"),""))) | J75: =IF($N$5=1,$N$7+47*$N$8,"") | K75: =IF($N$5=1,J75-1-$N$9,"") | L75: =IF($N$5=1,K75-$N$8,"")
A76: =IF(AND($N$5=1,48<=$N$11),"48° ajuste","") | B76: =IF(AND($N$5=1,48<=$N$11),INDEX(IPC!$J$5:$J$16,MOD(J76,12)+1)&" de "&INT((J76)/12),"") | C76: =IF(AND(AND($N$5=1,48<=$N$11),$N$10=1),INDEX(IPC!$J$5:$J$16,MOD(L76,12)+1)&" de "&INT((L76)/12),"") | D76: =IF(AND(AND($N$5=1,48<=$N$11),$N$10=1),INDEX(IPC!$J$5:$J$16,MOD(K76,12)+1)&" de "&INT((K76)/12),"") | E76: =IF(NOT(AND($N$5=1,48<=$N$11)),"",IF($N$10=1,IF(AND($N$14=1,K76<=$N$12),INDEX(IPC!$D$5:$D$173,(K76)-IPC!$J$2+1)/INDEX(IPC!$D$5:$D$173,(L76)-IPC!$J$2+1)-1,""),IF(ISNUMBER(F76),F76/100,""))) | G76: =IF(AND(AND($N$5=1,48<=$N$11),ISNUMBER(G75),ISNUMBER(E76)),G75*(1+E76),"") | H76: =IF(NOT(AND($N$5=1,48<=$N$11)),"",IF(ISNUMBER(G76),"Aplicado",IF(ISNUMBER(G75),IF($N$10=1,"Falta el IPC de "&INDEX(IPC!$J$5:$J$16,MOD($N$12+1,12)+1)&" de "&INT(($N$12+1)/12),"Cargá el % de este ajuste en la columna F"),""))) | J76: =IF($N$5=1,$N$7+48*$N$8,"") | K76: =IF($N$5=1,J76-1-$N$9,"") | L76: =IF($N$5=1,K76-$N$8,"")
A77: =IF(AND($N$5=1,49<=$N$11),"49° ajuste","") | B77: =IF(AND($N$5=1,49<=$N$11),INDEX(IPC!$J$5:$J$16,MOD(J77,12)+1)&" de "&INT((J77)/12),"") | C77: =IF(AND(AND($N$5=1,49<=$N$11),$N$10=1),INDEX(IPC!$J$5:$J$16,MOD(L77,12)+1)&" de "&INT((L77)/12),"") | D77: =IF(AND(AND($N$5=1,49<=$N$11),$N$10=1),INDEX(IPC!$J$5:$J$16,MOD(K77,12)+1)&" de "&INT((K77)/12),"") | E77: =IF(NOT(AND($N$5=1,49<=$N$11)),"",IF($N$10=1,IF(AND($N$14=1,K77<=$N$12),INDEX(IPC!$D$5:$D$173,(K77)-IPC!$J$2+1)/INDEX(IPC!$D$5:$D$173,(L77)-IPC!$J$2+1)-1,""),IF(ISNUMBER(F77),F77/100,""))) | G77: =IF(AND(AND($N$5=1,49<=$N$11),ISNUMBER(G76),ISNUMBER(E77)),G76*(1+E77),"") | H77: =IF(NOT(AND($N$5=1,49<=$N$11)),"",IF(ISNUMBER(G77),"Aplicado",IF(ISNUMBER(G76),IF($N$10=1,"Falta el IPC de "&INDEX(IPC!$J$5:$J$16,MOD($N$12+1,12)+1)&" de "&INT(($N$12+1)/12),"Cargá el % de este ajuste en la columna F"),""))) | J77: =IF($N$5=1,$N$7+49*$N$8,"") | K77: =IF($N$5=1,J77-1-$N$9,"") | L77: =IF($N$5=1,K77-$N$8,"")
A78: =IF(AND($N$5=1,50<=$N$11),"50° ajuste","") | B78: =IF(AND($N$5=1,50<=$N$11),INDEX(IPC!$J$5:$J$16,MOD(J78,12)+1)&" de "&INT((J78)/12),"") | C78: =IF(AND(AND($N$5=1,50<=$N$11),$N$10=1),INDEX(IPC!$J$5:$J$16,MOD(L78,12)+1)&" de "&INT((L78)/12),"") | D78: =IF(AND(AND($N$5=1,50<=$N$11),$N$10=1),INDEX(IPC!$J$5:$J$16,MOD(K78,12)+1)&" de "&INT((K78)/12),"") | E78: =IF(NOT(AND($N$5=1,50<=$N$11)),"",IF($N$10=1,IF(AND($N$14=1,K78<=$N$12),INDEX(IPC!$D$5:$D$173,(K78)-IPC!$J$2+1)/INDEX(IPC!$D$5:$D$173,(L78)-IPC!$J$2+1)-1,""),IF(ISNUMBER(F78),F78/100,""))) | G78: =IF(AND(AND($N$5=1,50<=$N$11),ISNUMBER(G77),ISNUMBER(E78)),G77*(1+E78),"") | H78: =IF(NOT(AND($N$5=1,50<=$N$11)),"",IF(ISNUMBER(G78),"Aplicado",IF(ISNUMBER(G77),IF($N$10=1,"Falta el IPC de "&INDEX(IPC!$J$5:$J$16,MOD($N$12+1,12)+1)&" de "&INT(($N$12+1)/12),"Cargá el % de este ajuste en la columna F"),""))) | J78: =IF($N$5=1,$N$7+50*$N$8,"") | K78: =IF($N$5=1,J78-1-$N$9,"") | L78: =IF($N$5=1,K78-$N$8,"")
A79: =IF(AND($N$5=1,51<=$N$11),"51° ajuste","") | B79: =IF(AND($N$5=1,51<=$N$11),INDEX(IPC!$J$5:$J$16,MOD(J79,12)+1)&" de "&INT((J79)/12),"") | C79: =IF(AND(AND($N$5=1,51<=$N$11),$N$10=1),INDEX(IPC!$J$5:$J$16,MOD(L79,12)+1)&" de "&INT((L79)/12),"") | D79: =IF(AND(AND($N$5=1,51<=$N$11),$N$10=1),INDEX(IPC!$J$5:$J$16,MOD(K79,12)+1)&" de "&INT((K79)/12),"") | E79: =IF(NOT(AND($N$5=1,51<=$N$11)),"",IF($N$10=1,IF(AND($N$14=1,K79<=$N$12),INDEX(IPC!$D$5:$D$173,(K79)-IPC!$J$2+1)/INDEX(IPC!$D$5:$D$173,(L79)-IPC!$J$2+1)-1,""),IF(ISNUMBER(F79),F79/100,""))) | G79: =IF(AND(AND($N$5=1,51<=$N$11),ISNUMBER(G78),ISNUMBER(E79)),G78*(1+E79),"") | H79: =IF(NOT(AND($N$5=1,51<=$N$11)),"",IF(ISNUMBER(G79),"Aplicado",IF(ISNUMBER(G78),IF($N$10=1,"Falta el IPC de "&INDEX(IPC!$J$5:$J$16,MOD($N$12+1,12)+1)&" de "&INT(($N$12+1)/12),"Cargá el % de este ajuste en la columna F"),""))) | J79: =IF($N$5=1,$N$7+51*$N$8,"") | K79: =IF($N$5=1,J79-1-$N$9,"") | L79: =IF($N$5=1,K79-$N$8,"")
A80: =IF(AND($N$5=1,52<=$N$11),"52° ajuste","") | B80: =IF(AND($N$5=1,52<=$N$11),INDEX(IPC!$J$5:$J$16,MOD(J80,12)+1)&" de "&INT((J80)/12),"") | C80: =IF(AND(AND($N$5=1,52<=$N$11),$N$10=1),INDEX(IPC!$J$5:$J$16,MOD(L80,12)+1)&" de "&INT((L80)/12),"") | D80: =IF(AND(AND($N$5=1,52<=$N$11),$N$10=1),INDEX(IPC!$J$5:$J$16,MOD(K80,12)+1)&" de "&INT((K80)/12),"") | E80: =IF(NOT(AND($N$5=1,52<=$N$11)),"",IF($N$10=1,IF(AND($N$14=1,K80<=$N$12),INDEX(IPC!$D$5:$D$173,(K80)-IPC!$J$2+1)/INDEX(IPC!$D$5:$D$173,(L80)-IPC!$J$2+1)-1,""),IF(ISNUMBER(F80),F80/100,""))) | G80: =IF(AND(AND($N$5=1,52<=$N$11),ISNUMBER(G79),ISNUMBER(E80)),G79*(1+E80),"") | H80: =IF(NOT(AND($N$5=1,52<=$N$11)),"",IF(ISNUMBER(G80),"Aplicado",IF(ISNUMBER(G79),IF($N$10=1,"Falta el IPC de "&INDEX(IPC!$J$5:$J$16,MOD($N$12+1,12)+1)&" de "&INT(($N$12+1)/12),"Cargá el % de este ajuste en la columna F"),""))) | J80: =IF($N$5=1,$N$7+52*$N$8,"") | K80: =IF($N$5=1,J80-1-$N$9,"") | L80: =IF($N$5=1,K80-$N$8,"")
A81: =IF(AND($N$5=1,53<=$N$11),"53° ajuste","") | B81: =IF(AND($N$5=1,53<=$N$11),INDEX(IPC!$J$5:$J$16,MOD(J81,12)+1)&" de "&INT((J81)/12),"") | C81: =IF(AND(AND($N$5=1,53<=$N$11),$N$10=1),INDEX(IPC!$J$5:$J$16,MOD(L81,12)+1)&" de "&INT((L81)/12),"") | D81: =IF(AND(AND($N$5=1,53<=$N$11),$N$10=1),INDEX(IPC!$J$5:$J$16,MOD(K81,12)+1)&" de "&INT((K81)/12),"") | E81: =IF(NOT(AND($N$5=1,53<=$N$11)),"",IF($N$10=1,IF(AND($N$14=1,K81<=$N$12),INDEX(IPC!$D$5:$D$173,(K81)-IPC!$J$2+1)/INDEX(IPC!$D$5:$D$173,(L81)-IPC!$J$2+1)-1,""),IF(ISNUMBER(F81),F81/100,""))) | G81: =IF(AND(AND($N$5=1,53<=$N$11),ISNUMBER(G80),ISNUMBER(E81)),G80*(1+E81),"") | H81: =IF(NOT(AND($N$5=1,53<=$N$11)),"",IF(ISNUMBER(G81),"Aplicado",IF(ISNUMBER(G80),IF($N$10=1,"Falta el IPC de "&INDEX(IPC!$J$5:$J$16,MOD($N$12+1,12)+1)&" de "&INT(($N$12+1)/12),"Cargá el % de este ajuste en la columna F"),""))) | J81: =IF($N$5=1,$N$7+53*$N$8,"") | K81: =IF($N$5=1,J81-1-$N$9,"") | L81: =IF($N$5=1,K81-$N$8,"")
A82: =IF(AND($N$5=1,54<=$N$11),"54° ajuste","") | B82: =IF(AND($N$5=1,54<=$N$11),INDEX(IPC!$J$5:$J$16,MOD(J82,12)+1)&" de "&INT((J82)/12),"") | C82: =IF(AND(AND($N$5=1,54<=$N$11),$N$10=1),INDEX(IPC!$J$5:$J$16,MOD(L82,12)+1)&" de "&INT((L82)/12),"") | D82: =IF(AND(AND($N$5=1,54<=$N$11),$N$10=1),INDEX(IPC!$J$5:$J$16,MOD(K82,12)+1)&" de "&INT((K82)/12),"") | E82: =IF(NOT(AND($N$5=1,54<=$N$11)),"",IF($N$10=1,IF(AND($N$14=1,K82<=$N$12),INDEX(IPC!$D$5:$D$173,(K82)-IPC!$J$2+1)/INDEX(IPC!$D$5:$D$173,(L82)-IPC!$J$2+1)-1,""),IF(ISNUMBER(F82),F82/100,""))) | G82: =IF(AND(AND($N$5=1,54<=$N$11),ISNUMBER(G81),ISNUMBER(E82)),G81*(1+E82),"") | H82: =IF(NOT(AND($N$5=1,54<=$N$11)),"",IF(ISNUMBER(G82),"Aplicado",IF(ISNUMBER(G81),IF($N$10=1,"Falta el IPC de "&INDEX(IPC!$J$5:$J$16,MOD($N$12+1,12)+1)&" de "&INT(($N$12+1)/12),"Cargá el % de este ajuste en la columna F"),""))) | J82: =IF($N$5=1,$N$7+54*$N$8,"") | K82: =IF($N$5=1,J82-1-$N$9,"") | L82: =IF($N$5=1,K82-$N$8,"")
A83: =IF(AND($N$5=1,55<=$N$11),"55° ajuste","") | B83: =IF(AND($N$5=1,55<=$N$11),INDEX(IPC!$J$5:$J$16,MOD(J83,12)+1)&" de "&INT((J83)/12),"") | C83: =IF(AND(AND($N$5=1,55<=$N$11),$N$10=1),INDEX(IPC!$J$5:$J$16,MOD(L83,12)+1)&" de "&INT((L83)/12),"") | D83: =IF(AND(AND($N$5=1,55<=$N$11),$N$10=1),INDEX(IPC!$J$5:$J$16,MOD(K83,12)+1)&" de "&INT((K83)/12),"") | E83: =IF(NOT(AND($N$5=1,55<=$N$11)),"",IF($N$10=1,IF(AND($N$14=1,K83<=$N$12),INDEX(IPC!$D$5:$D$173,(K83)-IPC!$J$2+1)/INDEX(IPC!$D$5:$D$173,(L83)-IPC!$J$2+1)-1,""),IF(ISNUMBER(F83),F83/100,""))) | G83: =IF(AND(AND($N$5=1,55<=$N$11),ISNUMBER(G82),ISNUMBER(E83)),G82*(1+E83),"") | H83: =IF(NOT(AND($N$5=1,55<=$N$11)),"",IF(ISNUMBER(G83),"Aplicado",IF(ISNUMBER(G82),IF($N$10=1,"Falta el IPC de "&INDEX(IPC!$J$5:$J$16,MOD($N$12+1,12)+1)&" de "&INT(($N$12+1)/12),"Cargá el % de este ajuste en la columna F"),""))) | J83: =IF($N$5=1,$N$7+55*$N$8,"") | K83: =IF($N$5=1,J83-1-$N$9,"") | L83: =IF($N$5=1,K83-$N$8,"")
A84: =IF(AND($N$5=1,56<=$N$11),"56° ajuste","") | B84: =IF(AND($N$5=1,56<=$N$11),INDEX(IPC!$J$5:$J$16,MOD(J84,12)+1)&" de "&INT((J84)/12),"") | C84: =IF(AND(AND($N$5=1,56<=$N$11),$N$10=1),INDEX(IPC!$J$5:$J$16,MOD(L84,12)+1)&" de "&INT((L84)/12),"") | D84: =IF(AND(AND($N$5=1,56<=$N$11),$N$10=1),INDEX(IPC!$J$5:$J$16,MOD(K84,12)+1)&" de "&INT((K84)/12),"") | E84: =IF(NOT(AND($N$5=1,56<=$N$11)),"",IF($N$10=1,IF(AND($N$14=1,K84<=$N$12),INDEX(IPC!$D$5:$D$173,(K84)-IPC!$J$2+1)/INDEX(IPC!$D$5:$D$173,(L84)-IPC!$J$2+1)-1,""),IF(ISNUMBER(F84),F84/100,""))) | G84: =IF(AND(AND($N$5=1,56<=$N$11),ISNUMBER(G83),ISNUMBER(E84)),G83*(1+E84),"") | H84: =IF(NOT(AND($N$5=1,56<=$N$11)),"",IF(ISNUMBER(G84),"Aplicado",IF(ISNUMBER(G83),IF($N$10=1,"Falta el IPC de "&INDEX(IPC!$J$5:$J$16,MOD($N$12+1,12)+1)&" de "&INT(($N$12+1)/12),"Cargá el % de este ajuste en la columna F"),""))) | J84: =IF($N$5=1,$N$7+56*$N$8,"") | K84: =IF($N$5=1,J84-1-$N$9,"") | L84: =IF($N$5=1,K84-$N$8,"")
A85: =IF(AND($N$5=1,57<=$N$11),"57° ajuste","") | B85: =IF(AND($N$5=1,57<=$N$11),INDEX(IPC!$J$5:$J$16,MOD(J85,12)+1)&" de "&INT((J85)/12),"") | C85: =IF(AND(AND($N$5=1,57<=$N$11),$N$10=1),INDEX(IPC!$J$5:$J$16,MOD(L85,12)+1)&" de "&INT((L85)/12),"") | D85: =IF(AND(AND($N$5=1,57<=$N$11),$N$10=1),INDEX(IPC!$J$5:$J$16,MOD(K85,12)+1)&" de "&INT((K85)/12),"") | E85: =IF(NOT(AND($N$5=1,57<=$N$11)),"",IF($N$10=1,IF(AND($N$14=1,K85<=$N$12),INDEX(IPC!$D$5:$D$173,(K85)-IPC!$J$2+1)/INDEX(IPC!$D$5:$D$173,(L85)-IPC!$J$2+1)-1,""),IF(ISNUMBER(F85),F85/100,""))) | G85: =IF(AND(AND($N$5=1,57<=$N$11),ISNUMBER(G84),ISNUMBER(E85)),G84*(1+E85),"") | H85: =IF(NOT(AND($N$5=1,57<=$N$11)),"",IF(ISNUMBER(G85),"Aplicado",IF(ISNUMBER(G84),IF($N$10=1,"Falta el IPC de "&INDEX(IPC!$J$5:$J$16,MOD($N$12+1,12)+1)&" de "&INT(($N$12+1)/12),"Cargá el % de este ajuste en la columna F"),""))) | J85: =IF($N$5=1,$N$7+57*$N$8,"") | K85: =IF($N$5=1,J85-1-$N$9,"") | L85: =IF($N$5=1,K85-$N$8,"")
A86: =IF(AND($N$5=1,58<=$N$11),"58° ajuste","") | B86: =IF(AND($N$5=1,58<=$N$11),INDEX(IPC!$J$5:$J$16,MOD(J86,12)+1)&" de "&INT((J86)/12),"") | C86: =IF(AND(AND($N$5=1,58<=$N$11),$N$10=1),INDEX(IPC!$J$5:$J$16,MOD(L86,12)+1)&" de "&INT((L86)/12),"") | D86: =IF(AND(AND($N$5=1,58<=$N$11),$N$10=1),INDEX(IPC!$J$5:$J$16,MOD(K86,12)+1)&" de "&INT((K86)/12),"") | E86: =IF(NOT(AND($N$5=1,58<=$N$11)),"",IF($N$10=1,IF(AND($N$14=1,K86<=$N$12),INDEX(IPC!$D$5:$D$173,(K86)-IPC!$J$2+1)/INDEX(IPC!$D$5:$D$173,(L86)-IPC!$J$2+1)-1,""),IF(ISNUMBER(F86),F86/100,""))) | G86: =IF(AND(AND($N$5=1,58<=$N$11),ISNUMBER(G85),ISNUMBER(E86)),G85*(1+E86),"") | H86: =IF(NOT(AND($N$5=1,58<=$N$11)),"",IF(ISNUMBER(G86),"Aplicado",IF(ISNUMBER(G85),IF($N$10=1,"Falta el IPC de "&INDEX(IPC!$J$5:$J$16,MOD($N$12+1,12)+1)&" de "&INT(($N$12+1)/12),"Cargá el % de este ajuste en la columna F"),""))) | J86: =IF($N$5=1,$N$7+58*$N$8,"") | K86: =IF($N$5=1,J86-1-$N$9,"") | L86: =IF($N$5=1,K86-$N$8,"")
A87: =IF(AND($N$5=1,59<=$N$11),"59° ajuste","") | B87: =IF(AND($N$5=1,59<=$N$11),INDEX(IPC!$J$5:$J$16,MOD(J87,12)+1)&" de "&INT((J87)/12),"") | C87: =IF(AND(AND($N$5=1,59<=$N$11),$N$10=1),INDEX(IPC!$J$5:$J$16,MOD(L87,12)+1)&" de "&INT((L87)/12),"") | D87: =IF(AND(AND($N$5=1,59<=$N$11),$N$10=1),INDEX(IPC!$J$5:$J$16,MOD(K87,12)+1)&" de "&INT((K87)/12),"") | E87: =IF(NOT(AND($N$5=1,59<=$N$11)),"",IF($N$10=1,IF(AND($N$14=1,K87<=$N$12),INDEX(IPC!$D$5:$D$173,(K87)-IPC!$J$2+1)/INDEX(IPC!$D$5:$D$173,(L87)-IPC!$J$2+1)-1,""),IF(ISNUMBER(F87),F87/100,""))) | G87: =IF(AND(AND($N$5=1,59<=$N$11),ISNUMBER(G86),ISNUMBER(E87)),G86*(1+E87),"") | H87: =IF(NOT(AND($N$5=1,59<=$N$11)),"",IF(ISNUMBER(G87),"Aplicado",IF(ISNUMBER(G86),IF($N$10=1,"Falta el IPC de "&INDEX(IPC!$J$5:$J$16,MOD($N$12+1,12)+1)&" de "&INT(($N$12+1)/12),"Cargá el % de este ajuste en la columna F"),""))) | J87: =IF($N$5=1,$N$7+59*$N$8,"") | K87: =IF($N$5=1,J87-1-$N$9,"") | L87: =IF($N$5=1,K87-$N$8,"")
A88: =IF(AND($N$5=1,60<=$N$11),"60° ajuste","") | B88: =IF(AND($N$5=1,60<=$N$11),INDEX(IPC!$J$5:$J$16,MOD(J88,12)+1)&" de "&INT((J88)/12),"") | C88: =IF(AND(AND($N$5=1,60<=$N$11),$N$10=1),INDEX(IPC!$J$5:$J$16,MOD(L88,12)+1)&" de "&INT((L88)/12),"") | D88: =IF(AND(AND($N$5=1,60<=$N$11),$N$10=1),INDEX(IPC!$J$5:$J$16,MOD(K88,12)+1)&" de "&INT((K88)/12),"") | E88: =IF(NOT(AND($N$5=1,60<=$N$11)),"",IF($N$10=1,IF(AND($N$14=1,K88<=$N$12),INDEX(IPC!$D$5:$D$173,(K88)-IPC!$J$2+1)/INDEX(IPC!$D$5:$D$173,(L88)-IPC!$J$2+1)-1,""),IF(ISNUMBER(F88),F88/100,""))) | G88: =IF(AND(AND($N$5=1,60<=$N$11),ISNUMBER(G87),ISNUMBER(E88)),G87*(1+E88),"") | H88: =IF(NOT(AND($N$5=1,60<=$N$11)),"",IF(ISNUMBER(G88),"Aplicado",IF(ISNUMBER(G87),IF($N$10=1,"Falta el IPC de "&INDEX(IPC!$J$5:$J$16,MOD($N$12+1,12)+1)&" de "&INT(($N$12+1)/12),"Cargá el % de este ajuste en la columna F"),""))) | J88: =IF($N$5=1,$N$7+60*$N$8,"") | K88: =IF($N$5=1,J88-1-$N$9,"") | L88: =IF($N$5=1,K88-$N$8,"")
A90: Cada ajuste multiplica el alquiler vigente por la variación del índice del período: IPC del último mes ÷ IPC del mes anterior al primero. Los porcentajes se componen, no se suman. La letra de tu contrato manda: si dice otra cosa, ajustá el índice o la convención de arriba.

Sheet Contrato 4
A1: Contrato 4
A2: Completá las celdas amarillas con los datos del contrato. Las verdes se calculan solas.
A4: DATOS DEL CONTRATO
A5: Propiedad (dirección) | N5: =IF(AND(N6>0,ISNUMBER(B9),ISNUMBER(B11),B11>0,ISNUMBER(B13),B13>=1,ISNUMBER(B10),B10>=1),1,0)
A6: Inquilino/a | N6: =IFERROR(MATCH(B8,IPC!$J$5:$J$16,0),0)
A7: Tu nombre (para el recibo y el aviso) | N7: =IF(N5=1,B9*12+N6-1,0)
A8: Mes de inicio del contrato | C8: El primer mes en que se cobró el valor inicial. | N8: =IF(N5=1,INT(B13),1)
A9: Año de inicio | N9: =IF(B14="Los últimos publicados",1,0)
A10: Duración (meses) | B10: 24 | N10: =IF(B12="Otro índice (cargo el %)",0,1)
A11: Alquiler inicial (el del primer mes) | N11: =IF(N5=1,MIN(INT((B10-1)/N8),60),0)
A12: Índice de ajuste | B12: IPC (INDEC) | C12: Si tu contrato ajusta por ICL, Casa Propia u otro índice, elegí «Otro» y cargá el % de cada ajuste en el cronograma (columna F). | N12: =IPC!$J$3
A13: Se ajusta cada (meses) | B13: 3 | C13: Trimestral = 3, cuatrimestral = 4, semestral = 6, anual = 12. | N13: =IPC!$J$2
A14: Meses del IPC que toma | B14: Los completos antes del ajuste | C14: «Completos»: un ajuste de julio usa el IPC de abril a junio (como la calculadora de calcular.ar). «Últimos publicados»: usa el de marzo a mayo, porque el de junio sale a mitad de julio. Fijate qué dice tu contrato. | N14: =IF(N5=0,0,IF(N10=0,1,IF(AND(N7-1-N9>=N13,N7-1-N9<=N12),1,0)))
N15: =COUNT(G29:G88)
A16: CÓMO VIENE EL CONTRATO | N16: =IF(N5=1,INDEX(G28:G88,N15+1),"")
A17: Alquiler que se cobra hoy | B17: =N16 | N17: =N15+1
A18: Rige desde | B18: =IF(N5=1,INDEX(B28:B88,N15+1),"") | N18: =IF(AND(N5=1,N17<=N11),1,0)
A19: Ajustes aplicados | B19: =IF(N5=1,N15,"") | N19: =N7+N17*N8-1-N9
A20: Aumento desde el inicio | B20: =IF(N5=1,N16/B11-1,"") | N20: =N19-N12
A21: Próximo ajuste | B21: =IF(N18=1,INDEX(B28:B88,N17+1),IF(N5=1,"No quedan ajustes antes de que termine","")) | N21: =INDEX(IPC!$D$5:$D$173,(N12)-IPC!$J$2+1)/INDEX(IPC!$D$5:$D$173,(N12-1)-IPC!$J$2+1)-1
A22: Próximo alquiler estimado | B22: =N22 | N22: =IF(AND(N18=1,N10=1,N14=1,N20>0,N20<=12),N16*INDEX(IPC!$D$5:$D$173,(N12)-IPC!$J$2+1)*(1+N21)^N20/INDEX(IPC!$D$5:$D$173,(N19-N8)-IPC!$J$2+1),"")
A23: Último mes del contrato | B23: =IF(N5=1,INDEX(IPC!$J$5:$J$16,MOD(N7+B10-1,12)+1)&" de "&INT((N7+B10-1)/12),"") | N23: =IF(ISNUMBER(N22),ROUND(N22,0),"")
A24: Qué hacer ahora | B24: =IF(N5=0,"Completá las celdas amarillas de arriba y acá aparece el cronograma de aumentos.",IF(N14=0,"Todavía no está publicado el IPC de "&INDEX(IPC!$J$5:$J$16,MOD(N7-1-N9,12)+1)&" de "&INT((N7-1-N9)/12)&", que es la base de este contrato. Mientras tanto se cobra el valor inicial.",IF(N18=0,"No quedan ajustes: el contrato termina en "&INDEX(IPC!$J$5:$J$16,MOD(N7+B10-1,12)+1)&" de "&INT((N7+B10-1)/12)&".",IF(N10=1,"El próximo ajuste rige desde "&B21&". Se calcula cuando el INDEC publique el IPC de "&INDEX(IPC!$J$5:$J$16,MOD(N19,12)+1)&" de "&INT((N19)/12)&" (sale entre el 10 y el 15 del mes siguiente)"&IF(ISNUMBER(N22),". Si la inflación siguiera como el último mes, el alquiler quedaría en unos $ "&N24&".","."),"El próximo ajuste rige desde "&B21&": cuando lo tengas, cargá el % del índice pactado en la columna F del cronograma.")))) | N24: =IF(ISNUMBER(N23),IF(N23>=1000000000,INT(N23/1000000000)&"."&RIGHT("00"&INT(MOD(N23,1000000000)/1000000),3)&"."&RIGHT("00"&INT(MOD(N23,1000000)/1000),3)&"."&RIGHT("00"&INT(MOD(N23,1000)/1),3),IF(N23>=1000000,INT(N23/1000000)&"."&RIGHT("00"&INT(MOD(N23,1000000)/1000),3)&"."&RIGHT("00"&INT(MOD(N23,1000)/1),3),IF(N23>=1000,INT(N23/1000)&"."&RIGHT("00"&INT(MOD(N23,1000)/1),3),""&N23))),"")
A26: CRONOGRAMA DE AJUSTES
A27: Ajuste | B27: Rige desde | C27: Mes del IPC base | D27: Mes del IPC final | E27: Variación | F27: % a mano (otro índice) | G27: Alquiler | H27: Estado
A28: =IF($N$5=1,"Valor inicial","") | B28: =IF($N$5=1,INDEX(IPC!$J$5:$J$16,MOD(J28,12)+1)&" de "&INT((J28)/12),"") | G28: =IF($N$5=1,B11,"") | H28: =IF($N$5=1,"Valor inicial del contrato","") | J28: =IF($N$5=1,$N$7+0*$N$8,"") | K28: =IF($N$5=1,J28-1-$N$9,"") | L28: =IF($N$5=1,K28-$N$8,"")
A29: =IF(AND($N$5=1,1<=$N$11),"1° ajuste","") | B29: =IF(AND($N$5=1,1<=$N$11),INDEX(IPC!$J$5:$J$16,MOD(J29,12)+1)&" de "&INT((J29)/12),"") | C29: =IF(AND(AND($N$5=1,1<=$N$11),$N$10=1),INDEX(IPC!$J$5:$J$16,MOD(L29,12)+1)&" de "&INT((L29)/12),"") | D29: =IF(AND(AND($N$5=1,1<=$N$11),$N$10=1),INDEX(IPC!$J$5:$J$16,MOD(K29,12)+1)&" de "&INT((K29)/12),"") | E29: =IF(NOT(AND($N$5=1,1<=$N$11)),"",IF($N$10=1,IF(AND($N$14=1,K29<=$N$12),INDEX(IPC!$D$5:$D$173,(K29)-IPC!$J$2+1)/INDEX(IPC!$D$5:$D$173,(L29)-IPC!$J$2+1)-1,""),IF(ISNUMBER(F29),F29/100,""))) | G29: =IF(AND(AND($N$5=1,1<=$N$11),ISNUMBER(G28),ISNUMBER(E29)),G28*(1+E29),"") | H29: =IF(NOT(AND($N$5=1,1<=$N$11)),"",IF(ISNUMBER(G29),"Aplicado",IF(ISNUMBER(G28),IF($N$10=1,"Falta el IPC de "&INDEX(IPC!$J$5:$J$16,MOD($N$12+1,12)+1)&" de "&INT(($N$12+1)/12),"Cargá el % de este ajuste en la columna F"),""))) | J29: =IF($N$5=1,$N$7+1*$N$8,"") | K29: =IF($N$5=1,J29-1-$N$9,"") | L29: =IF($N$5=1,K29-$N$8,"")
A30: =IF(AND($N$5=1,2<=$N$11),"2° ajuste","") | B30: =IF(AND($N$5=1,2<=$N$11),INDEX(IPC!$J$5:$J$16,MOD(J30,12)+1)&" de "&INT((J30)/12),"") | C30: =IF(AND(AND($N$5=1,2<=$N$11),$N$10=1),INDEX(IPC!$J$5:$J$16,MOD(L30,12)+1)&" de "&INT((L30)/12),"") | D30: =IF(AND(AND($N$5=1,2<=$N$11),$N$10=1),INDEX(IPC!$J$5:$J$16,MOD(K30,12)+1)&" de "&INT((K30)/12),"") | E30: =IF(NOT(AND($N$5=1,2<=$N$11)),"",IF($N$10=1,IF(AND($N$14=1,K30<=$N$12),INDEX(IPC!$D$5:$D$173,(K30)-IPC!$J$2+1)/INDEX(IPC!$D$5:$D$173,(L30)-IPC!$J$2+1)-1,""),IF(ISNUMBER(F30),F30/100,""))) | G30: =IF(AND(AND($N$5=1,2<=$N$11),ISNUMBER(G29),ISNUMBER(E30)),G29*(1+E30),"") | H30: =IF(NOT(AND($N$5=1,2<=$N$11)),"",IF(ISNUMBER(G30),"Aplicado",IF(ISNUMBER(G29),IF($N$10=1,"Falta el IPC de "&INDEX(IPC!$J$5:$J$16,MOD($N$12+1,12)+1)&" de "&INT(($N$12+1)/12),"Cargá el % de este ajuste en la columna F"),""))) | J30: =IF($N$5=1,$N$7+2*$N$8,"") | K30: =IF($N$5=1,J30-1-$N$9,"") | L30: =IF($N$5=1,K30-$N$8,"")
A31: =IF(AND($N$5=1,3<=$N$11),"3° ajuste","") | B31: =IF(AND($N$5=1,3<=$N$11),INDEX(IPC!$J$5:$J$16,MOD(J31,12)+1)&" de "&INT((J31)/12),"") | C31: =IF(AND(AND($N$5=1,3<=$N$11),$N$10=1),INDEX(IPC!$J$5:$J$16,MOD(L31,12)+1)&" de "&INT((L31)/12),"") | D31: =IF(AND(AND($N$5=1,3<=$N$11),$N$10=1),INDEX(IPC!$J$5:$J$16,MOD(K31,12)+1)&" de "&INT((K31)/12),"") | E31: =IF(NOT(AND($N$5=1,3<=$N$11)),"",IF($N$10=1,IF(AND($N$14=1,K31<=$N$12),INDEX(IPC!$D$5:$D$173,(K31)-IPC!$J$2+1)/INDEX(IPC!$D$5:$D$173,(L31)-IPC!$J$2+1)-1,""),IF(ISNUMBER(F31),F31/100,""))) | G31: =IF(AND(AND($N$5=1,3<=$N$11),ISNUMBER(G30),ISNUMBER(E31)),G30*(1+E31),"") | H31: =IF(NOT(AND($N$5=1,3<=$N$11)),"",IF(ISNUMBER(G31),"Aplicado",IF(ISNUMBER(G30),IF($N$10=1,"Falta el IPC de "&INDEX(IPC!$J$5:$J$16,MOD($N$12+1,12)+1)&" de "&INT(($N$12+1)/12),"Cargá el % de este ajuste en la columna F"),""))) | J31: =IF($N$5=1,$N$7+3*$N$8,"") | K31: =IF($N$5=1,J31-1-$N$9,"") | L31: =IF($N$5=1,K31-$N$8,"")
