Workbook

Sheet Instrucciones
A1: Planilla de salario y prestaciones República Dominicana 2026
A3: 1 | B3: Las celdas amarillas son para tus datos. Las verdes se calculan solas, con las fórmulas de la ley. A la derecha de cada hoja está el paso a paso de la cuenta.
A4: 2 | B4: «Salario neto»: pones tu salario bruto y te dice los descuentos de la TSS (SFS y AFP), el ISR que te retienen y tu salario neto.
A5: 3 | B5: «Regalía pascual»: calcula tu regalía pascual del año, completa o proporcional, con el tope legal.
A6: 4 | B6: «Prestaciones laborales»: pones tus fechas, tu salario promedio y cómo terminó el contrato, y te dice el preaviso, la cesantía, las vacaciones y la regalía.
A7: 5 | B7: «Tablas oficiales» tiene cada valor oficial que usan las fórmulas, con el enlace a su fuente y la fecha en que lo verificamos. Los valores son los vigentes al 22/10/2026.
A8: 6 | B8: Cuando cambia un valor oficial, actualizamos la planilla y el mismo enlace de descarga te baja la versión nueva.
A10: Da los mismos números que las calculadoras gratuitas de calcularya.com. Antes de publicar cada versión, una verificación automática recalcula este archivo y lo compara con ellas.
A11: Es una referencia de cálculo con sus fuentes, no asesoría legal. Tu contrato o tu empresa pueden darte más que el mínimo de ley.
A12: Las fechas van como dd/mm/aaaa. Si tu Excel está en inglés y las lee al revés, escríbelas como aaaa-mm-dd.

Sheet Salario neto
A1: Salario neto: SFS, AFP e ISR
E3: Paso a paso
A4: TUS DATOS | E4: Seguro Familiar de Salud (SFS) | F4: =ROUND(MIN(B5,'Tablas oficiales'!$C$4)*'Tablas oficiales'!$C$5/100,2)
A5: Salario bruto mensual | B5: 60000 | C5: Lo que dice tu contrato antes de los descuentos. | E5: Pensión (AFP) | F5: =ROUND(MIN(B5,'Tablas oficiales'!$C$6)*'Tablas oficiales'!$C$7/100,2)
E6: Salario sujeto a ISR | F6: =ROUND(B5-F4-F5,2)
A7: TU SALARIO NETO | E7: Base del año (por 12) | F7: =F6*12
A8: Salario bruto | B8: =B5 | E8: ISR del mes (impuesto anual entre 12) | F8: =ROUND(IF(F7<=0,0,INDEX('Tablas oficiales'!$E$10:$E$13,IFERROR(MATCH(F7,'Tablas oficiales'!$B$10:$B$13,1),1))+(F7-INDEX('Tablas oficiales'!$B$10:$B$13,IFERROR(MATCH(F7,'Tablas oficiales'!$B$10:$B$13,1),1)))*INDEX('Tablas oficiales'!$D$10:$D$13,IFERROR(MATCH(F7,'Tablas oficiales'!$B$10:$B$13,1),1))/100)/12,2)
A9: Seguro Familiar de Salud (SFS) | B9: =F4 | E9: Total de descuentos | F9: =ROUND(F4+F5+F8,2)
A10: Pensión (AFP) | B10: =F5
A11: Salario sujeto a ISR | B11: =F6
A12: ISR | B12: =F8
A13: Total de descuentos | B13: =F9
A14: Salario neto | B14: =ROUND(B5-F9,2)
A16: El SFS y la AFP se descuentan hasta sus topes. El ISR es la doceava parte del impuesto del año, como la tabla de retención de la DGII.

Sheet Regalía pascual
A1: Regalía pascual (salario de Navidad) | Z1: Empresa grande
Z2: Empresa mediana
E3: Paso a paso | Z3: Empresa pequeña
A4: TUS DATOS | E4: Año: desde | F4: =IF(AND(ISNUMBER(B6),B6>DATE(YEAR(B9),1,1)),B6,DATE(YEAR(B9),1,1)) | Z4: Microempresa
A5: Salario mensual | B5: 40000 | C5: Tu salario ordinario, sin horas extra ni bonificación. | E5: Año: hasta | F5: =IF(AND(ISNUMBER(B7),B7<DATE(YEAR(B9),12,31)),B7,DATE(YEAR(B9),12,31))
A6: Fecha en que empezaste, si fue este año (opcional) | C6: Déjala vacía si trabajas en la empresa desde antes del 1 de enero. | E6: Año: meses completos | F6: =MIN(12,IF(EDATE(F4,((YEAR((F5+1))-YEAR(F4))*12+MONTH((F5+1))-MONTH(F4)))>(F5+1),((YEAR((F5+1))-YEAR(F4))*12+MONTH((F5+1))-MONTH(F4))-1,((YEAR((F5+1))-YEAR(F4))*12+MONTH((F5+1))-MONTH(F4))))
A7: Último día de trabajo, si ya saliste este año (opcional) | C7: Déjala vacía si sigues trabajando. | E7: Año: meses trabajados | F7: =IF(F5<F4,0,MIN(12,F6+((F5+1)-EDATE(F4,F6))/30))
A8: Tamaño de la empresa | B8: Empresa grande | E8: Salario ganado en el año | F8: =ROUND(B5*F7,2)
A9: Fecha de hoy | B9: =TODAY() | C9: Se llena sola. Define el año de la regalía. | E9: Doceava parte | F9: =ROUND(F8/12,2)
E10: Tope (5 salarios mínimos) | F10: =ROUND(INDEX('Tablas oficiales'!$C$15:$C$18,MATCH(B8,'Tablas oficiales'!$B$15:$B$18,0))*'Tablas oficiales'!$C$19,2)
A11: TU REGALÍA
A12: =IF(AND(ISNUMBER(B6),ISNUMBER(B7),B7<B6),"El último día tiene que ser posterior a la fecha en que empezaste.","")
A13: Meses que cuentan | B13: =ROUND(F7,2)
A14: Salario ganado en el año | B14: =F8
A15: Regalía según tu salario | B15: =F9
A16: Tope legal | B16: =F10
A17: Regalía pascual | B17: =MIN(F9,F10)
A19: Se paga a más tardar el 20 de diciembre y no paga ISR. Para el tope se usa el salario mínimo del tamaño de tu empresa: el Código de Trabajo no aclara cuál se toma.

Sheet Prestaciones laborales
A1: Prestaciones laborales: preaviso, cesantía, vacaciones y regalía | Z1: Empresa grande
Z2: Empresa mediana
E3: Paso a paso | Z3: Empresa pequeña
A4: TUS DATOS | E4: Antigüedad: años completos | F4: =IF(EDATE(B5,12*(YEAR(B6)-YEAR(B5)))>B6,(YEAR(B6)-YEAR(B5))-1,(YEAR(B6)-YEAR(B5))) | Z4: Microempresa
A5: Fecha en que empezaste a trabajar | B5: 44635 | E5: Antigüedad: último aniversario | F5: =EDATE(B5,12*F4)
A6: Último día de trabajo | B6: 46317 | E6: Antigüedad: meses | F6: =MIN(12,IF(EDATE(F5,((YEAR(B6)-YEAR(F5))*12+MONTH(B6)-MONTH(F5)))>B6,((YEAR(B6)-YEAR(F5))*12+MONTH(B6)-MONTH(F5))-1,((YEAR(B6)-YEAR(F5))*12+MONTH(B6)-MONTH(F5))))
A7: Salario promedio mensual del último año | B7: 40000 | C7: Lo ganado en los últimos 12 meses (sin horas extra ni regalía) dividido entre los meses trabajados. | E7: Antigüedad: días | F7: =B6-EDATE(F5,F6)
A8: Cómo terminó el contrato | B8: Me desahuciaron (despido sin alegar causa) | E8: Salario diario (entre 23.83) | F8: =ROUND(B7/'Tablas oficiales'!$C$20,2)
A9: Te dieron el preaviso a tiempo | B9: No | C9: Solo cuenta en el desahucio. Si te avisaron con los días de ley, el preaviso no se paga.
A10: Días de vacaciones de años anteriores que no tomaste | B10: 0 | E10: Preaviso y cesantía
A11: Tamaño de la empresa | B11: Empresa grande | E11: Días de preaviso | F11: =IF(AND(OR(B8="Me desahuciaron (despido sin alegar causa)",B8="Despido injustificado o dimisión justificada"),OR(B8="Despido injustificado o dimisión justificada",AND(B8="Me desahuciaron (despido sin alegar causa)",B9="No"))),IF(F4>=1,'Tablas oficiales'!$C$23,IF(F6<3,0,IF(OR(F6<6,AND(F6=6,F7=0)),'Tablas oficiales'!$C$21,'Tablas oficiales'!$C$22))),0)
E12: Días de cesantía | F12: =IF(OR(B8="Me desahuciaron (despido sin alegar causa)",B8="Despido injustificado o dimisión justificada"),IF(F4=0,IF(OR(F6<3),0,IF(OR(F6<6,AND(F6=6,F7=0)),'Tablas oficiales'!$C$24,'Tablas oficiales'!$C$25)),F4*IF(F4>=5,'Tablas oficiales'!$C$27,'Tablas oficiales'!$C$26)+IF(OR(F6<3,AND(F6=3,F7=0)),0,IF(OR(F6<6,AND(F6=6,F7=0)),'Tablas oficiales'!$C$24,'Tablas oficiales'!$C$25))),0)
A13: TUS PRESTACIONES
A14: =IF(B6<B5,"El último día tiene que ser posterior a la fecha en que empezaste.","") | E14: Vacaciones y regalía
A15: Antigüedad | B15: =F4&" años, "&F6&" meses y "&F7&" días" | E15: Meses que pasaron del último aniversario | F15: =IF(F7>0,F6,F6-1)
A16: Salario diario | B16: =F8 | E16: Días de vacaciones | F16: =IF(F15<5,0,CHOOSE(MIN(F15,11)-4,'Tablas oficiales'!$C$28,'Tablas oficiales'!$C$29,'Tablas oficiales'!$C$30,'Tablas oficiales'!$C$31,'Tablas oficiales'!$C$32,'Tablas oficiales'!$C$33,'Tablas oficiales'!$C$34))+B10
A17: Días de preaviso | B17: =F11 | E17: Regalía: desde | F17: =IF(AND(ISNUMBER(B5),B5>DATE(YEAR(B6),1,1)),B5,DATE(YEAR(B6),1,1))
A18: Preaviso | B18: =F23 | E18: Regalía: hasta | F18: =IF(AND(ISNUMBER(B6),B6<DATE(YEAR(B6),12,31)),B6,DATE(YEAR(B6),12,31))
A19: Días de cesantía | B19: =F12 | E19: Regalía: meses completos | F19: =MIN(12,IF(EDATE(F17,((YEAR((F18+1))-YEAR(F17))*12+MONTH((F18+1))-MONTH(F17)))>(F18+1),((YEAR((F18+1))-YEAR(F17))*12+MONTH((F18+1))-MONTH(F17))-1,((YEAR((F18+1))-YEAR(F17))*12+MONTH((F18+1))-MONTH(F17))))
A20: Auxilio de cesantía | B20: =F24 | E20: Regalía: meses trabajados | F20: =IF(F18<F17,0,MIN(12,F19+((F18+1)-EDATE(F17,F19))/30))
A21: Días de vacaciones | B21: =F16 | E21: Tope de la regalía | F21: =ROUND(INDEX('Tablas oficiales'!$C$15:$C$18,MATCH(B11,'Tablas oficiales'!$B$15:$B$18,0))*'Tablas oficiales'!$C$19,2)
A22: Vacaciones | B22: =F25 | E22: Regalía proporcional | F22: =MIN(ROUND(B7*F20/12,2),F21)
A23: Regalía pascual proporcional | B23: =F22 | E23: Preaviso | F23: =ROUND(F8*F11,2)
A24: Total | B24: =ROUND(F23+F24+F25+F22,2) | E24: Cesantía | F24: =ROUND(F8*F12,2)
E25: Vacaciones | F25: =ROUND(F8*F16,2)
A26: Al renunciar no cobras preaviso ni cesantía. Preaviso y cesantía no pagan ISR, y el empleador tiene 10 días para pagarlos (art. 86). Los años anteriores al 29 de mayo de 1992 se pagan con otra escala.

Sheet Tablas oficiales
A1: Tablas oficiales de República Dominicana
A2: Son los valores que usan las fórmulas de esta planilla, vigentes al 22/10/2026. Cada uno trae el enlace a la norma o al organismo que lo publica y la fecha en que lo verificamos.
A3: Dato | B3: Detalle | C3: Valor | D3: Unidad | E3: Vigente desde | F3: Fuente oficial | G3: Verificado el
A4: Tope de cotización del Seguro Familiar de Salud (10 salarios mínimos nacionales) | C4: 232230 | D4: DOP | E4: 1/2/2026 | F4: https://tss.gob.do/preguntas-frecuentes/ | G4: 7/10/2026
A5: Seguro Familiar de Salud a cargo del trabajador | C5: 3.04 | D5: % | E5: 1/2/2026 | F5: https://tss.gob.do/preguntas-frecuentes/ | G5: 7/10/2026
A6: Tope de cotización del seguro de pensiones (20 salarios mínimos nacionales) | C6: 464460 | D6: DOP | E6: 1/2/2026 | F6: https://tss.gob.do/preguntas-frecuentes/ | G6: 7/10/2026
A7: Seguro de pensiones (AFP) a cargo del trabajador | C7: 2.87 | D7: % | E7: 1/2/2026 | F7: https://tss.gob.do/preguntas-frecuentes/ | G7: 7/10/2026
A8: Escala anual del impuesto sobre la renta de las personas físicas | D8: DOP | E8: 1/1/2026 | F8: https://dgii.gov.do/cicloContribuyente/obligacionesTributarias/principalesImpuestos/Paginas/impuestoSobreRenta.aspx | G8: 7/10/2026
B9: Desde | C9: Hasta | D9: Tasa % | E9: Cuota fija
B10: 0 | C10: 416220 | D10: 0 | E10: 0
B11: 416220.01 | C11: 624329 | D11: 15 | E11: 0
B12: 624329.01 | C12: 867123 | D12: 20 | E12: 31216
B13: 867123.01 | C13: 1e+15 | D13: 25 | E13: 79776
A15: Salario mínimo mensual del sector privado no sectorizado, por tamaño de empresa | B15: Empresa grande | C15: 29988 | D15: DOP | E15: 1/2/2026 | F15: https://mt.gob.do/ministerio-de-trabajo-llama-a-empresarios-a-cumplir-con-el-pago-del-aumento-del-8-del-salario-minimo/ | G15: 7/10/2026
A16: Salario mínimo mensual del sector privado no sectorizado, por tamaño de empresa | B16: Empresa mediana | C16: 27489.6 | D16: DOP | E16: 1/2/2026 | F16: https://mt.gob.do/ministerio-de-trabajo-llama-a-empresarios-a-cumplir-con-el-pago-del-aumento-del-8-del-salario-minimo/ | G16: 7/10/2026
A17: Salario mínimo mensual del sector privado no sectorizado, por tamaño de empresa | B17: Empresa pequeña | C17: 18421.2 | D17: DOP | E17: 1/2/2026 | F17: https://mt.gob.do/ministerio-de-trabajo-llama-a-empresarios-a-cumplir-con-el-pago-del-aumento-del-8-del-salario-minimo/ | G17: 7/10/2026
A18: Salario mínimo mensual del sector privado no sectorizado, por tamaño de empresa | B18: Microempresa | C18: 16993.2 | D18: DOP | E18: 1/2/2026 | F18: https://mt.gob.do/ministerio-de-trabajo-llama-a-empresarios-a-cumplir-con-el-pago-del-aumento-del-8-del-salario-minimo/ | G18: 7/10/2026
A19: Tope del salario de Navidad en salarios mínimos | C19: 5 | E19: 29/5/1992 | F19: https://transparencia.mt.gob.do/images/docs/publicaciones/codigo-de-trabajo.pdf | G19: 7/10/2026
A20: Divisor para pasar el salario mensual a diario | C20: 23.83 | D20: veces | E20: 30/12/1999 | F20: https://transparencia.mt.gob.do/images/docs/publicaciones/codigo-de-trabajo.pdf | G20: 7/10/2026
A21: Días de preaviso según la antigüedad | B21: De 3 a 6 meses | C21: 7 | D21: días | E21: 29/5/1992 | F21: https://transparencia.mt.gob.do/images/docs/publicaciones/codigo-de-trabajo.pdf | G21: 7/10/2026
A22: Días de preaviso según la antigüedad | B22: Más de 6 meses y hasta 1 año | C22: 14 | D22: días | E22: 29/5/1992 | F22: https://transparencia.mt.gob.do/images/docs/publicaciones/codigo-de-trabajo.pdf | G22: 7/10/2026
A23: Días de preaviso según la antigüedad | B23: Más de 1 año | C23: 28 | D23: días | E23: 29/5/1992 | F23: https://transparencia.mt.gob.do/images/docs/publicaciones/codigo-de-trabajo.pdf | G23: 7/10/2026
A24: Días de auxilio de cesantía según la antigüedad | B24: De 3 a 6 meses | C24: 6 | D24: días | E24: 29/5/1992 | F24: https://transparencia.mt.gob.do/images/docs/publicaciones/codigo-de-trabajo.pdf | G24: 7/10/2026
A25: Días de auxilio de cesantía según la antigüedad | B25: De 6 meses a 1 año | C25: 13 | D25: días | E25: 29/5/1992 | F25: https://transparencia.mt.gob.do/images/docs/publicaciones/codigo-de-trabajo.pdf | G25: 7/10/2026
A26: Días de auxilio de cesantía según la antigüedad | B26: De 1 a 5 años, por año | C26: 21 | D26: días | E26: 29/5/1992 | F26: https://transparencia.mt.gob.do/images/docs/publicaciones/codigo-de-trabajo.pdf | G26: 7/10/2026
A27: Días de auxilio de cesantía según la antigüedad | B27: 5 años o más, por año | C27: 23 | D27: días | E27: 29/5/1992 | F27: https://transparencia.mt.gob.do/images/docs/publicaciones/codigo-de-trabajo.pdf | G27: 7/10/2026
A28: Días de vacaciones proporcionales por meses trabajados | B28: 5 | C28: 6 | D28: días | E28: 29/5/1992 | F28: https://transparencia.mt.gob.do/images/docs/publicaciones/codigo-de-trabajo.pdf | G28: 7/10/2026
A29: Días de vacaciones proporcionales por meses trabajados | B29: 6 | C29: 7 | D29: días | E29: 29/5/1992 | F29: https://transparencia.mt.gob.do/images/docs/publicaciones/codigo-de-trabajo.pdf | G29: 7/10/2026
A30: Días de vacaciones proporcionales por meses trabajados | B30: 7 | C30: 8 | D30: días | E30: 29/5/1992 | F30: https://transparencia.mt.gob.do/images/docs/publicaciones/codigo-de-trabajo.pdf | G30: 7/10/2026
A31: Días de vacaciones proporcionales por meses trabajados | B31: 8 | C31: 9 | D31: días | E31: 29/5/1992 | F31: https://transparencia.mt.gob.do/images/docs/publicaciones/codigo-de-trabajo.pdf | G31: 7/10/2026
A32: Días de vacaciones proporcionales por meses trabajados | B32: 9 | C32: 10 | D32: días | E32: 29/5/1992 | F32: https://transparencia.mt.gob.do/images/docs/publicaciones/codigo-de-trabajo.pdf | G32: 7/10/2026
... A34: Días de vacaciones proporcionales por meses trabajados | B34: 11 | C34: 12 | D34: días | E34: 29/5/1992 | F34: https://transparencia.mt.gob.do/images/docs/publicaciones/codigo-de-trabajo.pdf | G34: 7/10/2026
