Workbook

Sheet Instrucciones
A1: Planilla de salario y prestaciones Honduras 2026
A3: 1 | B3: Las celdas amarillas son para sus datos. Las verdes se calculan solas, con las fórmulas de la ley. A la derecha de cada hoja está el paso a paso de la cuenta.
A4: 2 | B4: «ISR de su salario»: pone su salario mensual y le dice el ISR del año, la retención de cada mes y su tasa efectiva.
A5: 3 | B5: «Décimo cuarto mes»: calcula el décimo cuarto mes de junio, completo o proporcional si dejó de trabajar.
A6: 4 | B6: «Prestaciones laborales»: pone sus fechas, su salario promedio y cómo terminó el trabajo, y le dice el preaviso y el auxilio de cesantía.
A7: 5 | B7: «Tablas oficiales» tiene cada valor oficial que usan las fórmulas, con el enlace a su fuente y la fecha en que lo verificamos. Los valores son los vigentes al 14/10/2026.
A8: 6 | B8: Cuando cambia un valor oficial, actualizamos la planilla y el mismo enlace de descarga le baja la versión nueva.
A10: Da los mismos números que las calculadoras gratuitas de calcularya.com. Antes de publicar cada versión, una verificación automática recalcula este archivo y lo compara con ellas.
A11: Es una referencia de cálculo con sus fuentes, no asesoría legal. Su contrato o su empresa pueden darle más que el mínimo de ley.
A12: Las fechas van como dd/mm/aaaa. Si su Excel está en inglés y las lee al revés, escríbalas como aaaa-mm-dd.

Sheet ISR de su salario
A1: Impuesto sobre la renta del salario
E3: Paso a paso
A4: SUS DATOS | E4: Renta bruta del año | F4: =ROUND(B5*12+IF(ISNUMBER(B6),B6,0),2)
A5: Salario mensual | B5: 30000 | E5: Deducción por gastos médicos | F5: =MIN(F4,'Tablas oficiales'!$C$11)
A6: Otros ingresos del año que pagan ISR (opcional) | C6: Comisiones, bonos u otros pagos gravados que no estén en el salario mensual. | E6: Renta gravable | F6: =ROUND(F4-F5,2)
E7: Impuesto del tramo 1 | F7: =MAX(0,MIN(F6,'Tablas oficiales'!$C$6)-0)*'Tablas oficiales'!$D$6/100
A8: SU ISR | E8: Impuesto del tramo 2 | F8: =MAX(0,MIN(F6,'Tablas oficiales'!$C$7)-'Tablas oficiales'!$C$6)*'Tablas oficiales'!$D$7/100
A9: Renta bruta del año | B9: =F4 | E9: Impuesto del tramo 3 | F9: =MAX(0,MIN(F6,'Tablas oficiales'!$C$8)-'Tablas oficiales'!$C$7)*'Tablas oficiales'!$D$8/100
A10: Deducción por gastos médicos | B10: =F5 | E10: Impuesto del tramo 4 | F10: =MAX(0,MIN(F6,'Tablas oficiales'!$C$9)-'Tablas oficiales'!$C$8)*'Tablas oficiales'!$D$9/100
A11: Renta gravable | B11: =F6 | E11: ISR del año | F11: =ROUND(SUM(F7,F8,F9,F10),2)
A12: Tasa del último tramo | B12: =IF((IF(F6>0,1,0)+COUNTIF('Tablas oficiales'!$C$6:$C$9,"<"&F6))=0,0,INDEX('Tablas oficiales'!$D$6:$D$9,(IF(F6>0,1,0)+COUNTIF('Tablas oficiales'!$C$6:$C$9,"<"&F6))))
A13: ISR del año | B13: =F11
A14: Retención de cada mes | B14: =ROUND(F11/12,2)
A15: Tasa efectiva | B15: =IF(F4>0,ROUND(F11/F4*100,2),0)
A17: Se calcula con 12 salarios y la deducción por gastos médicos que el SAR resta en su tabla del año.

Sheet Décimo cuarto mes
A1: Décimo cuarto mes
E3: Paso a paso
A4: SUS DATOS | E4: Cierre del período | F4: =IF(B7="La parte que le toca porque dejó de trabajar",B8,DATE(IF(MONTH(B9)<=6,YEAR(B9),YEAR(B9)+1),6,30))
A5: Salario ordinario mensual promedio | B5: 15000 | C5: El promedio de lo que ganó cada mes desde el 1 de julio (o desde que entró), sin horas extra. | E5: Días del período | F5: =MIN(365,F4-MAX(B6,DATE(IF(MONTH(F4)>=7,YEAR(F4),YEAR(F4)-1),7,1))+1)
A6: Fecha en que empezó a trabajar | B6: 45323
A7: Qué quiere calcular | B7: El décimo cuarto mes que se paga en junio
A8: Último día de trabajo (opcional) | C8: Solo si dejó de trabajar.
A9: Fecha de hoy | B9: =TODAY() | C9: Se llena sola. Sirve para saber qué período se paga.
A11: SU DÉCIMO CUARTO
A12: =IF(AND(B7="La parte que le toca porque dejó de trabajar",NOT(ISNUMBER(B8))),"Indique su último día de trabajo.",IF(B6>F4,"La fecha de ingreso no puede ser posterior al cierre del período.",""))
A13: Días que cuentan | B13: =F5
A14: Décimo cuarto mes | B14: =ROUND(B5*'Tablas oficiales'!$C$12/100*F5/365,2)
A16: Es un salario por año, del 1 de julio al 30 de junio, y se paga en junio. Si renuncia o lo despiden, le pagan la parte proporcional.

Sheet Prestaciones laborales
A1: Preaviso y auxilio de cesantía
E3: Paso a paso
A4: SUS DATOS | E4: Tiempo trabajado: años completos | F4: =IF(EDATE(B6,12*(YEAR((B7+1))-YEAR(B6)))>(B7+1),(YEAR((B7+1))-YEAR(B6))-1,(YEAR((B7+1))-YEAR(B6)))
A5: Salario promedio mensual de los últimos seis meses | B5: 15000 | C5: Todo lo que ganó: salario, horas extra y comisiones. | E5: Tiempo trabajado: último aniversario | F5: =EDATE(B6,12*F4)
A6: Fecha de ingreso | B6: 44256 | E6: Tiempo trabajado: meses | F6: =MIN(12,IF(EDATE(F5,((YEAR((B7+1))-YEAR(F5))*12+MONTH((B7+1))-MONTH(F5)))>(B7+1),((YEAR((B7+1))-YEAR(F5))*12+MONTH((B7+1))-MONTH(F5))-1,((YEAR((B7+1))-YEAR(F5))*12+MONTH((B7+1))-MONTH(F5))))
A7: Último día de trabajo | B7: 46309 | E7: Tiempo trabajado: días | F7: =(B7+1)-EDATE(F5,F6)
A8: Cómo terminó el trabajo | B8: Me despidieron sin causa justificada | E8: Meses trabajados | F8: =F4*12+F6
A9: El patrono le dio el preaviso por escrito y lo trabajó | B9: No | E9: Salario diario (entre 30) | F9: =B5/30
A10: La empresa tiene 10 empleados o menos | B10: No
E11: Preaviso
A12: SUS PRESTACIONES | E12: Días de preaviso | F12: =IF(AND(B8="Me despidieron sin causa justificada",B9="No"),IF(F8<3,'Tablas oficiales'!$C$13,IF(OR(F8<6,AND(F8=6,F7=0)),'Tablas oficiales'!$C$14,IF(OR(F8<12,AND(F8=12,F7=0)),'Tablas oficiales'!$C$15,IF(OR(F8<24,AND(F8=24,F7=0)),'Tablas oficiales'!$C$16,'Tablas oficiales'!$C$17)))),0)
A13: =IF(B7<B6,"La fecha de salida tiene que ser igual o posterior a la de ingreso.","")
A14: Tiempo trabajado | B14: =F4&" años, "&F6&" meses y "&F7&" días" | E14: Auxilio de cesantía
A15: Salario diario | B15: =ROUND(F9,2) | E15: Tope en meses de salario | F15: =IF(B10="Sí",'Tablas oficiales'!$C$21,'Tablas oficiales'!$C$20)
A16: Días de preaviso | B16: =F12 | E16: Meses de salario de cesantía | F16: =IF(F8<3,0,IF(F4=0,IF(OR(F8<6,AND(F8=6,F7=0)),'Tablas oficiales'!$C$18,'Tablas oficiales'!$C$19)/30,MIN(F4+(F6*30+F7)/360,F15)))
A17: Preaviso | B17: =F18 | E17: Auxilio de cesantía | F17: =IF(B8="Me despidieron sin causa justificada",ROUND(B5*F16,2),IF(OR(B10="Sí",F4<'Tablas oficiales'!$C$22),0,ROUND(B5*F16*'Tablas oficiales'!$C$23/100,2)))
A18: Meses de salario de cesantía | B18: =IF(F17>0,F16,"") | E18: Preaviso | F18: =ROUND(F9*F12,2)
A19: Auxilio de cesantía | B19: =F17
A20: Total | B20: =ROUND(F18+F17,2)
A22: Si renuncia, el preaviso lo da usted y no se le paga. Al renunciar, la cesantía solo corresponde con 15 años o más (el 35 %) y nunca en una microempresa. Aparte le corresponden las vacaciones y los décimos proporcionales.

Sheet Tablas oficiales
A1: Tablas oficiales de Honduras
A2: Son los valores que usan las fórmulas de esta planilla, vigentes al 14/10/2026. Cada uno trae el enlace a la norma o al organismo que lo publica y la fecha en que lo verificamos.
A3: Dato | B3: Detalle | C3: Valor | D3: Unidad | E3: Vigente desde | F3: Fuente oficial | G3: Verificado el
A4: Tabla progresiva del ISR para personas naturales 2026 (renta neta gravable anual) | D4: HNL | E4: 1/1/2026 | F4: https://www.sar.gob.hn/2026/01/actualizacion-de-la-tabla-progresiva-2026/ | G4: 7/10/2026
B5: Desde | C5: Hasta | D5: Tasa % | E5: Cuota fija
B6: 0.01 | C6: 228324.32 | D6: 0 | E6: 0
B7: 228324.33 | C7: 348154.1 | D7: 15 | E7: 0
B8: 348154.11 | C8: 809660.75 | D8: 20 | E8: 0
B9: 809660.76 | C9: 1e+15 | D9: 25 | E9: 0
A11: Deducción anual por gastos médicos sin comprobantes | C11: 40000 | D11: HNL | E11: 1/1/2026 | F11: https://www.sar.gob.hn/2026/01/actualizacion-de-la-tabla-progresiva-2026/ | G11: 7/10/2026
A12: Décimo cuarto mes por año completo trabajado al 30 de junio | C12: 100 | D12: % | E12: 1/1/2026 | F12: https://www.trabajo.gob.hn/wp-content/uploads/2022/09/Codigo-del-Trabajo-y-sus-Reformas.pdf | G12: 7/10/2026
A13: Días de salario del preaviso según el tiempo trabajado | B13: Menos de 3 meses | C13: 1 | D13: días | E13: 1/1/2026 | F13: https://www.trabajo.gob.hn/wp-content/uploads/2022/09/Codigo-del-Trabajo-y-sus-Reformas.pdf | G13: 7/10/2026
A14: Días de salario del preaviso según el tiempo trabajado | B14: De 3 a 6 meses | C14: 7 | D14: días | E14: 1/1/2026 | F14: https://www.trabajo.gob.hn/wp-content/uploads/2022/09/Codigo-del-Trabajo-y-sus-Reformas.pdf | G14: 7/10/2026
A15: Días de salario del preaviso según el tiempo trabajado | B15: De 6 meses a 1 año | C15: 14 | D15: días | E15: 1/1/2026 | F15: https://www.trabajo.gob.hn/wp-content/uploads/2022/09/Codigo-del-Trabajo-y-sus-Reformas.pdf | G15: 7/10/2026
A16: Días de salario del preaviso según el tiempo trabajado | B16: De 1 a 2 años | C16: 30 | D16: días | E16: 1/1/2026 | F16: https://www.trabajo.gob.hn/wp-content/uploads/2022/09/Codigo-del-Trabajo-y-sus-Reformas.pdf | G16: 7/10/2026
A17: Días de salario del preaviso según el tiempo trabajado | B17: Más de 2 años | C17: 60 | D17: días | E17: 1/1/2026 | F17: https://www.trabajo.gob.hn/wp-content/uploads/2022/09/Codigo-del-Trabajo-y-sus-Reformas.pdf | G17: 7/10/2026
A18: Días de auxilio de cesantía con menos de un año trabajado | B18: 3-a-6-meses | C18: 10 | D18: días | E18: 1/1/2026 | F18: https://www.trabajo.gob.hn/wp-content/uploads/2022/09/Codigo-del-Trabajo-y-sus-Reformas.pdf | G18: 7/10/2026
A19: Días de auxilio de cesantía con menos de un año trabajado | B19: 6-a-12-meses | C19: 20 | D19: días | E19: 1/1/2026 | F19: https://www.trabajo.gob.hn/wp-content/uploads/2022/09/Codigo-del-Trabajo-y-sus-Reformas.pdf | G19: 7/10/2026
A20: Tope del auxilio de cesantía en meses de salario | B20: Empresa de más de 10 empleados | C20: 25 | D20: meses | E20: 1/1/2026 | F20: https://www.trabajo.gob.hn/wp-content/uploads/2016/07/Gaceta-31753-Decreto-No.-150-2008.pdf | G20: 7/10/2026
A21: Tope del auxilio de cesantía en meses de salario | B21: Microempresa (hasta 10 empleados) | C21: 15 | D21: meses | E21: 1/1/2026 | F21: https://www.trabajo.gob.hn/wp-content/uploads/2016/07/Gaceta-31753-Decreto-No.-150-2008.pdf | G21: 7/10/2026
A22: Años de trabajo continuo para cobrar cesantía al renunciar | C22: 15 | D22: años | E22: 1/1/2026 | F22: https://www.trabajo.gob.hn/wp-content/uploads/2016/07/Gaceta-31753-Decreto-No.-150-2008.pdf | G22: 7/10/2026
A23: Parte de la cesantía que cobra quien renuncia con 15 años o más | C23: 35 | D23: % | E23: 1/1/2026 | F23: https://www.trabajo.gob.hn/wp-content/uploads/2016/07/Gaceta-31753-Decreto-No.-150-2008.pdf | G23: 7/10/2026
