Workbook

Sheet Instrucciones
A1: Planilla de salario y liquidación Paraguay 2026
A3: 1 | B3: Las celdas amarillas son para tus datos. Las verdes se calculan solas, con las fórmulas de la ley. A la derecha de cada hoja está el paso a paso de la cuenta.
A4: 2 | B4: «Salario neto»: ponés tu salario bruto y te dice el aporte al IPS, tu salario neto y lo que le cuesta al empleador.
A5: 3 | B5: «Aguinaldo»: calcula tu aguinaldo con la doceava parte de lo que cobraste en el año.
A6: 4 | B6: «Liquidación»: ponés tus fechas, tu salario promedio y cómo terminó el trabajo, y te dice el preaviso, la indemnización, las vacaciones y el aguinaldo.
A7: 5 | B7: «Tablas oficiales» tiene cada valor oficial que usan las fórmulas, con el enlace a su fuente y la fecha en que lo verificamos. Los valores son los vigentes al 13/10/2026.
A8: 6 | B8: Cuando cambia un valor oficial, actualizamos la planilla y el mismo enlace de descarga te baja la versión nueva.
A10: Da los mismos números que las calculadoras gratuitas de calcularya.com. Antes de publicar cada versión, una verificación automática recalcula este archivo y lo compara con ellas.
A11: Es una referencia de cálculo con sus fuentes, no asesoramiento legal. Tu contrato o tu empresa pueden darte más que el mínimo de ley.
A12: Las fechas van como dd/mm/aaaa. Si tu Excel está en inglés y las lee al revés, escribilas como aaaa-mm-dd.

Sheet Salario neto
A1: Salario neto y aporte al IPS
E3: Paso a paso
A4: TUS DATOS | E4: Aporte al IPS | F4: =ROUND(B5*'Tablas oficiales'!$C$4/100,0)
A5: Salario bruto del mes | B5: 3500000 | C5: El salario más horas extra o comisiones del mes. El aguinaldo no va. | E5: Aporte del empleador al IPS | F5: =ROUND(B5*'Tablas oficiales'!$C$5/100,0)
A7: TU SALARIO
A8: Salario bruto | B8: =B5
A9: Aporte al IPS | B9: =F4
A10: Salario neto | B10: =ROUND(B5-F4,0)
A11: Aporte del empleador al IPS | B11: =F5
A12: Costo total para el empleador | B12: =ROUND(B5+F5,0)
A13: =IF(AND(B5>0,B5<'Tablas oficiales'!$C$6),"Tu salario está debajo del mínimo legal. Con jornada completa, el IPS toma como base el salario mínimo.","")
A15: No incluye el IRP: se liquida una vez al año, en la declaración de marzo, y solo si tus ingresos del año pasan el monto no alcanzado.

Sheet Aguinaldo
A1: Aguinaldo
E3: Paso a paso
A4: TUS DATOS | E4: Total cobrado en el año | F4: =ROUND(B5*B6+B7,0)
A5: Salario mensual | B5: 3500000 | C5: Si tu salario cambió durante el año, poné el promedio.
A6: Meses trabajados en el año | B6: 12 | C6: Hasta 12. Se aceptan fracciones: medio mes es 0,5.
A7: Horas extra, comisiones y otros cobros del año | B7: 0 | C7: Todo lo que cobraste aparte del salario desde enero. Si no tuviste, dejá 0.
A9: TU AGUINALDO
A10: Total cobrado en el año | B10: =F4
A11: Aguinaldo | B11: =ROUND(F4/12,0)
A13: Se paga antes del 31 de diciembre, o al terminar la relación laboral si eso pasa antes. No paga aporte al IPS y no se puede embargar.

Sheet Liquidación
A1: Liquidación: preaviso, indemnización, vacaciones y aguinaldo
E3: Paso a paso
A4: TUS DATOS
A5: Salario mensual promedio de los últimos 6 meses | B5: 3500000 | C5: Sumá todo lo que cobraste en esos meses y dividilo por 6. | E5: Antigüedad
A6: Fecha de ingreso | B6: 44287 | E6: Meses de servicio cumplidos | F6: =IF(EDATE(B6,((YEAR((B7+1))-YEAR(B6))*12+MONTH((B7+1))-MONTH(B6)))>(B7+1),((YEAR((B7+1))-YEAR(B6))*12+MONTH((B7+1))-MONTH(B6))-1,((YEAR((B7+1))-YEAR(B6))*12+MONTH((B7+1))-MONTH(B6)))
A7: Último día de trabajo | B7: 46308 | E7: Años cumplidos | F7: =INT(F6/12)
A8: Se dio el preaviso y se trabajó | B8: No | C8: Si te despidieron sin avisarte con anticipación, dejalo en No. Si renunciaste sin avisar, también. | E8: Meses sueltos | F8: =MOD(F6,12)
A9: Cómo termina el trabajo | B9: Me despidieron sin causa | E9: Días sueltos | F9: =(B7+1)-EDATE(B6,F6)
A10: Total cobrado este año desde enero (opcional) | C10: Salario, horas extra y comisiones. Si lo dejás vacío, se estima con tu salario promedio. | E10: Salario diario | F10: =B5/'Tablas oficiales'!$C$7
A11: Días de vacaciones ya ganadas que no tomaste | B11: 0 | E11: Días de preaviso | F11: =IF(OR(F7>10,AND(F7=10,OR(F8>0,F9>0))),'Tablas oficiales'!$C$11,IF(OR(F7>5,AND(F7=5,OR(F8>0,F9>0))),'Tablas oficiales'!$C$10,IF(OR(F7>1,AND(F7=1,OR(F8>0,F9>0))),'Tablas oficiales'!$C$9,'Tablas oficiales'!$C$8)))
A12: Pasaron más de 6 meses desde que ganaste esas vacaciones | B12: No | C12: Si te despiden después de ese plazo, se pagan el doble. | E12: Años indemnizables (más de seis meses suman uno) | F12: =IF((B7+1)>EDATE(B6,F7*12+6),F7+1,F7)
E13: Indemnización por despido sin causa | F13: =ROUND(F10*'Tablas oficiales'!$C$12*F12,0)
A14: TU LIQUIDACIÓN
A15: =IF(B7<B6,"El último día de trabajo tiene que ser posterior a la fecha de ingreso.","") | E15: Liquidación
A16: Antigüedad | B16: =F7&" años, "&F8&" meses y "&F9&" días" | E16: Preaviso | F16: =IF(AND(B9="Me despidieron sin causa",B8="No"),ROUND(F10*F11,0),0)
A17: Preaviso | B17: =F16 | E17: Descuento por no dar preaviso | F17: =IF(AND(B9="Renuncié",B8="No"),ROUND(F10*F11/2,0),0)
A18: Indemnización | B18: =F18 | E18: Indemnización | F18: =IF(B9="Me despidieron sin causa",F13,0)
A19: Vacaciones ya ganadas | B19: =F19 | E19: Vacaciones causadas | F19: =ROUND(F10*B11*IF(AND(NOT(B9="Renuncié"),B12="Sí"),2,1),0)
A20: Días de vacaciones proporcionales | B20: =F20 | E20: Días de vacaciones proporcionales | F20: =IF(B9="Me despidieron sin causa",IF((F7+1)>10,'Tablas oficiales'!$C$15,IF((F7+1)>5,'Tablas oficiales'!$C$14,'Tablas oficiales'!$C$13))*((B7+1)-EDATE(B6,F7*12))/(EDATE(B6,(F7+1)*12)-EDATE(B6,F7*12)),0)
A21: Vacaciones proporcionales | B21: =F21 | E21: Vacaciones proporcionales | F21: =ROUND(F10*F20,0)
A22: Aguinaldo proporcional | B22: =F23 | E22: Cobrado en el año | F22: =IF(ISNUMBER(B10),B10,B5*(B7-MAX(DATE(YEAR(B7),1,1),B6)+1)/'Tablas oficiales'!$C$7)
A23: Descuento por no dar preaviso | B23: =IF(F17=0,0,-F17) | E23: Aguinaldo proporcional | F23: =ROUND(F22/12,0)
A24: Total | B24: =ROUND(F16+F18+F19+F21+F23-F17,0) | E24: Preaviso no trabajado | F24: =IF(B8="Sí",0,ROUND(F10*F11,0))
A26: Son montos brutos. Con causa justificada no hay indemnización ni preaviso. Con diez años o más tenés estabilidad, y en algunos casos la indemnización es el doble.
A28: SOLO LA INDEMNIZACIÓN POR DESPIDO SIN CAUSA
A29: Años que se indemnizan | B29: =F12
A30: Indemnización | B30: =F13
A31: Días de preaviso | B31: =F11
A32: Preaviso | B32: =F24
A33: Indemnización más preaviso | B33: =ROUND(F13+F24,0)
A34: Indemnización doble (con diez años o más) | B34: =IF(F7>=10,ROUND(F13*2,0),"")

Sheet Tablas oficiales
A1: Tablas oficiales de Paraguay
A2: Son los valores que usan las fórmulas de esta planilla, vigentes al 13/10/2026. Cada uno trae el enlace a la norma o al organismo que lo publica y la fecha en que lo verificamos.
A3: Dato | B3: Detalle | C3: Valor | D3: Unidad | E3: Vigente desde | F3: Fuente oficial | G3: Verificado el
A4: Aporte del trabajador al IPS | C4: 9 | D4: % | E4: 1/7/2026 | F4: https://portal.ips.gov.py/sistemas/ipsportal/contenido.php?c=372 | G4: 7/10/2026
A5: Aporte del empleador al IPS | C5: 16.5 | D5: % | E5: 1/7/2026 | F5: https://portal.ips.gov.py/sistemas/ipsportal/contenido.php?c=372 | G5: 7/10/2026
A6: Salario mínimo legal mensual (actividades diversas no especificadas) | C6: 3044000 | D6: PYG | E6: 1/7/2026 | F6: https://www.mtess.gov.py/wp-content/uploads/2026/07/Resolucion-MTESS-N%C2%B0-670-REGLAMENTACION-SALARIO-2026.pdf | G6: 7/10/2026
A7: Días del mes para el salario diario del mensualero | C7: 30 | D7: días | E7: 1/7/2026 | F7: https://www.mtess.gov.py/wp-content/uploads/2026/07/Resolucion-MTESS-N%C2%B0-670-REGLAMENTACION-SALARIO-2026.pdf | G7: 7/10/2026
A8: Días de preaviso por antigüedad | B8: Hasta 1 año | C8: 30 | D8: días | E8: 1/1/2025 | F8: https://www.bacn.gov.py/leyes-paraguayas/2608/ley-n-213-establece-el-codigo-del-trabajo | G8: 7/10/2026
A9: Días de preaviso por antigüedad | B9: Más de 1 y hasta 5 años | C9: 45 | D9: días | E9: 1/1/2025 | F9: https://www.bacn.gov.py/leyes-paraguayas/2608/ley-n-213-establece-el-codigo-del-trabajo | G9: 7/10/2026
A10: Días de preaviso por antigüedad | B10: Más de 5 y hasta 10 años | C10: 60 | D10: días | E10: 1/1/2025 | F10: https://www.bacn.gov.py/leyes-paraguayas/2608/ley-n-213-establece-el-codigo-del-trabajo | G10: 7/10/2026
A11: Días de preaviso por antigüedad | B11: Más de 10 años | C11: 90 | D11: días | E11: 1/1/2025 | F11: https://www.bacn.gov.py/leyes-paraguayas/2608/ley-n-213-establece-el-codigo-del-trabajo | G11: 7/10/2026
A12: Salarios diarios de indemnización por año de servicio | C12: 15 | D12: días | E12: 1/1/2025 | F12: https://www.dnit.gov.py/web/portal-institucional/w/m-ley-n-496-94 | G12: 7/10/2026
A13: Días de vacaciones por antigüedad | B13: Hasta 5 años | C13: 12 | D13: días | E13: 1/1/2025 | F13: https://www.dnit.gov.py/web/portal-institucional/w/m-ley-n-496-94 | G13: 7/10/2026
A14: Días de vacaciones por antigüedad | B14: Más de 5 y hasta 10 años | C14: 18 | D14: días | E14: 1/1/2025 | F14: https://www.dnit.gov.py/web/portal-institucional/w/m-ley-n-496-94 | G14: 7/10/2026
A15: Días de vacaciones por antigüedad | B15: Más de 10 años | C15: 30 | D15: días | E15: 1/1/2025 | F15: https://www.dnit.gov.py/web/portal-institucional/w/m-ley-n-496-94 | G15: 7/10/2026
